Workbook
Name Saldovortrag_LW: 'Dashboard'!$C$14
Name Saldovortrag_EUR: 'Dashboard'!$E$14
Name Budget_Kurs: 'I. Budget'!$H$4
Name Eigenmittel_LW: 'I. Budget'!$E$7
Name Eigenmittel_EUR: 'I. Budget'!$I$7
Name Drittmittel_LW: 'I. Budget'!$E$10
Name Drittmittel_EUR: 'I. Budget'!$I$10
Name KMW_Mittel_LW: 'I. Budget'!$E$13
Name KMW_Mittel_EUR: 'I. Budget'!$I$13
Name Gesamtprojektmittel_LW: 'I. Budget'!$E$15
Name Gesamtprojektmittel_EUR: 'I. Budget'!$I$15
Name Kosten_Bauausgaben_LW: 'I. Budget'!$O$4
Name Kosten_Bauausgaben_EUR: 'I. Budget'!$P$4
Name Kosten_Investitionen_LW: 'I. Budget'!$O$5
Name Kosten_Investitionen_EUR: 'I. Budget'!$P$5
Name Kosten_Personalkosten_LW: 'I. Budget'!$O$6
Name Kosten_Personalkosten_EUR: 'I. Budget'!$P$6
Name Kosten_Projektaktivitaeten_LW: 'I. Budget'!$O$7
Name Kosten_Projektaktivitaeten_EUR: 'I. Budget'!$P$7
Name Kosten_Projektverwaltung_LW: 'I. Budget'!$O$8
Name Kosten_Projektverwaltung_EUR: 'I. Budget'!$P$8
Name Kosten_Evaluierung_LW: 'I. Budget'!$O$9
Name Kosten_Evaluierung_EUR: 'I. Budget'!$P$9
Name Kosten_Audit_LW: 'I. Budget'!$O$10
Name Kosten_Audit_EUR: 'I. Budget'!$P$10
Name Kosten_Reserve_LW: 'I. Budget'!$O$11
Name Kosten_Reserve_EUR: 'I. Budget'!$P$11
Name Gesamtausgaben_LW: 'I. Budget'!$O$12
Name Gesamtausgaben_EUR: 'I. Budget'!$P$12
Name Budget_ID_Liste: OFFSET('I. Budget'!$S$1, 0, 0, COUNTA('I. Budget'!S:S), 1)
Name Geber_Liste: OFFSET('I. Budget'!$K$19,0,0,MAX(1,COUNTA('I. Budget'!$K$19:$K$19)),1)
Name Reserve_Freigabe: 'I. Budget'!$K$5
Name FB_Kurs_1: 'III. Finanzberichte'!$C$8
Name FB_SaldoLC_1: 'III. Finanzberichte'!$C$144
Name FB_SaldoEUR_1: 'III. Finanzberichte'!$D$144
Name FB_Kurs_2: 'III. Finanzberichte'!$J$8
Name FB_SaldoLC_2: 'III. Finanzberichte'!$J$144
Name FB_SaldoEUR_2: 'III. Finanzberichte'!$K$144
Name FB_Kurs_3: 'III. Finanzberichte'!$Q$8
Name FB_SaldoLC_3: 'III. Finanzberichte'!$Q$144
Name FB_SaldoEUR_3: 'III. Finanzberichte'!$R$144
Name FB_Kurs_4: 'III. Finanzberichte'!$X$8
Name FB_SaldoLC_4: 'III. Finanzberichte'!$X$144
Name FB_SaldoEUR_4: 'III. Finanzberichte'!$Y$144
Name FB_Kurs_5: 'III. Finanzberichte'!$AE$8
Name FB_SaldoLC_5: 'III. Finanzberichte'!$AE$144
Name FB_SaldoEUR_5: 'III. Finanzberichte'!$AF$144
Name FB_Kurs_6: 'III. Finanzberichte'!$AL$8
Name FB_SaldoLC_6: 'III. Finanzberichte'!$AL$144
Name FB_SaldoEUR_6: 'III. Finanzberichte'!$AM$144
Name FB_Kurs_7: 'III. Finanzberichte'!$AS$8
Name FB_SaldoLC_7: 'III. Finanzberichte'!$AS$144
Name FB_SaldoEUR_7: 'III. Finanzberichte'!$AT$144
Name FB_Kurs_8: 'III. Finanzberichte'!$AZ$8
Name FB_SaldoLC_8: 'III. Finanzberichte'!$AZ$144
Name FB_SaldoEUR_8: 'III. Finanzberichte'!$BA$144
Name FB_Kurs_9: 'III. Finanzberichte'!$BG$8
Name FB_SaldoLC_9: 'III. Finanzberichte'!$BG$144
Name FB_SaldoEUR_9: 'III. Finanzberichte'!$BH$144
Name FB_Kurs_10: 'III. Finanzberichte'!$BN$8

Sheet Dashboard
AA1: AED
B2: DASHBOARD (v1.0) | AA2: AFN
AA3: ALL
B4: Statische Projektinformationen | AA4: AMD
B5: Projektnummer | D5: Vorprojekt vorhanden | E5: Ja | AA5: AOA
B6: Projekttitel | AA6: ARS
B7: Projekttraeger | D7: Berichtswaehrung | AA7: AUD
B8: Projektstart | D8: Projektende | AA8: AWG
B9: Projektlaufzeit (geplant) | C9: ==IF(AND(ISNUMBER($C$8),ISNUMBER($E$8)),TEXT(DAY($C$8),"00")&"."&TEXT(MONTH($C$8),"00")&"."&TEXT(YEAR($C$8),"0000")&" - "&TEXT(DAY($E$8),"00")&"."&TEXT(MONTH($E$8),"00")&"."&TEXT(YEAR($E$8),"0000"),"") | D9: In Monate | E9: ==IF(AND(ISNUMBER($C$8),ISNUMBER($E$8)),DATEDIF($C$8,$E$8+1,"M"),"") | AA9: AZN
B10: Vorprojektnummer | D10: VP-Berichtswaehrung | AA10: BAM
B11: Vorprojektende | D11: Wechselkurs | AA11: BBD
B12: Saldo (LW) | D12: Saldo (EUR) | E12: ==IFERROR(ROUND($C$12/$E$11,2),0) | AA12: BDT
B13: Folgeprojektstart | D13: Wechselkurs | AA13: BHD
B14: Saldovortrag (LW) | D14: Saldovortrag (EUR) | E14: ==IFERROR(ROUND($C$14/$E$13,2),0) | AA14: BIF
AA15: BMD
B16: Folgende Dokumente liegen vor: | D16: Nein | E16: Vorprojektsaldo (Nachweis) | AA16: BND
D17: Nein | E17: Vertrag | AA17: BOB
D18: Nein | E18: Budget | AA18: BRL
D19: Nein | E19: Bankbelege | AA19: BSD
D20: Nein | E20: Finanzbericht(e) | AA20: BTN
D21: Nein | E21: Einzelbelege und Beleglisten | AA21: BWP
D22: Nein | E22: Narrativer Bericht | AA22: BYN
AA23: BZD
AA24: CAD
AA25: CDF
AA26: CHF
AA27: CLP
AA28: CNY
AA29: COP
AA30: CRC
AA31: CUP
AA32: CVE
AA33: CZK
AA34: DJF
... AA155: ZWG

Sheet I. Budget
S1: {=IFERROR(_xlfn._xlws.FILTER(TblBudgetAusgaben[ID],TblBudgetAusgaben[ID]<>""),"")} -> 0
B2: I. KERNDATEN BUDGET | K2: Reserve Freigabe
K3: ==$P$11
B4: 1. GEPLANTE EINNAHMEN / FINANZIERUNG | G4: € Budget-Kurs: | H4: ==IFERROR($E$15/$I$15,0) | K4: Reserve freigeben: | O4: ==SUMIFS(TblBudgetAusgaben[Betrag (LC)],TblBudgetAusgaben[Kostenkategorie],"Bauausgaben") | P4: ==SUMIFS(TblBudgetAusgaben[Betrag (EUR)],TblBudgetAusgaben[Kostenkategorie],"Bauausgaben")
B5: Finanzierungsquelle | E5: Betrag (LC) | F5: Jahr 1 | G5: Jahr 2 | H5: Jahr 3 | I5: Betrag (EUR) | K5: Nein | O5: ==SUMIFS(TblBudgetAusgaben[Betrag (LC)],TblBudgetAusgaben[Kostenkategorie],"Investitionen") | P5: ==SUMIFS(TblBudgetAusgaben[Betrag (EUR)],TblBudgetAusgaben[Kostenkategorie],"Investitionen")
B6: 1.1 Eigenmittel | K6: ==IF($K$5="Ja","FREIGEGEBEN","NICHT FREIGEGEBEN") | O6: ==SUMIFS(TblBudgetAusgaben[Betrag (LC)],TblBudgetAusgaben[Kostenkategorie],"Personalkosten") | P6: ==SUMIFS(TblBudgetAusgaben[Betrag (EUR)],TblBudgetAusgaben[Kostenkategorie],"Personalkosten")
B7: Eigenmittel | E7: 120000 | F7: 50000 | G7: 30000 | H7: 40000 | I7: 60000 | O7: ==SUMIFS(TblBudgetAusgaben[Betrag (LC)],TblBudgetAusgaben[Kostenkategorie],"Projektaktivitaeten") | P7: ==SUMIFS(TblBudgetAusgaben[Betrag (EUR)],TblBudgetAusgaben[Kostenkategorie],"Projektaktivitaeten")
K8: Begruendung | O8: ==SUMIFS(TblBudgetAusgaben[Betrag (LC)],TblBudgetAusgaben[Kostenkategorie],"Projektverwaltung") | P8: ==SUMIFS(TblBudgetAusgaben[Betrag (EUR)],TblBudgetAusgaben[Kostenkategorie],"Projektverwaltung")
B9: 1.2 Drittmittel | O9: ==SUMIFS(TblBudgetAusgaben[Betrag (LC)],TblBudgetAusgaben[Kostenkategorie],"Evaluierung") | P9: ==SUMIFS(TblBudgetAusgaben[Betrag (EUR)],TblBudgetAusgaben[Kostenkategorie],"Evaluierung")
B10: Drittmittel (Summe): | D10: Aufstellung je Geber → Tabelle rechts | E10: ==SUM(TblDrittmittel[Betrag (LC)]) | F10: 3000 | G10: 2000 | H10: 1000 | I10: ==SUM(TblDrittmittel[Betrag (EUR)]) | O10: ==SUMIFS(TblBudgetAusgaben[Betrag (LC)],TblBudgetAusgaben[Kostenkategorie],"Audit") | P10: ==SUMIFS(TblBudgetAusgaben[Betrag (EUR)],TblBudgetAusgaben[Kostenkategorie],"Audit")
O11: ==SUMIFS(TblBudgetAusgaben[Betrag (LC)],TblBudgetAusgaben[Kostenkategorie],"Reserve") | P11: ==SUMIFS(TblBudgetAusgaben[Betrag (EUR)],TblBudgetAusgaben[Kostenkategorie],"Reserve")
B12: 1.3 KMW-Mittel | O12: ==SUBTOTAL(109,TblBudgetAusgaben[Betrag (LC)]) | P12: ==SUBTOTAL(109,TblBudgetAusgaben[Betrag (EUR)])
B13: KMW-Mittel | E13: 140700 | F13: 80350 | G13: 56900 | H13: 3450 | I13: 70350
B15: GESAMTPROJEKTMITTEL | E15: ==E7+E10+E13 | F15: ==F7+F10+F13 | G15: ==G7+G10+G13 | H15: ==H7+H10+H13 | I15: ==I7+I10+I13
B17: 2. GEPLANTE AUSGABEN | K17: Drittmittel – Aufstellung je Geber
B18: Kostenkategorie | C18: ID | D18: Kostenposition | E18: Betrag (LC) | F18: Jahr 1 | G18: Jahr 2 | H18: Jahr 3 | I18: Betrag (EUR) | K18: Name des Gebers | L18: Betrag (LC) | M18: Betrag (EUR)
B19: Bauausgaben | C19: 1.1 | D19: Test 1 | E19: 3000 | F19: 1500 | G19: 1000 | H19: 500 | I19: 1500 | K19: Sonstige | L19: 6000 | M19: 3000
B20: Bauausgaben | C20: 1.2 | D20: Test 2 | E20: 3000 | F20: 1500 | G20: 1000 | H20: 500 | I20: 1500
B21: Bauausgaben | C21: 1.3 | D21: Test 3 | E21: 3000 | F21: 1500 | G21: 1000 | H21: 500 | I21: 1500
B22: Bauausgaben | C22: 1.4 | D22: Test 4 | E22: 3000 | F22: 1500 | G22: 1000 | H22: 500 | I22: 1500
B23: Bauausgaben | C23: 1.5 | D23: Test 5 | E23: 3000 | F23: 1500 | G23: 1000 | H23: 500 | I23: 1500
B24: Bauausgaben | C24: 1.6 | D24: Test 6 | E24: 3000 | F24: 1500 | G24: 1000 | H24: 500 | I24: 1500
B25: Bauausgaben | C25: 1.7 | D25: Test 7 | E25: 3000 | F25: 1500 | G25: 1000 | H25: 500 | I25: 1500
B26: Bauausgaben | C26: 1.8 | D26: Test 8 | E26: 3000 | F26: 1500 | G26: 1000 | H26: 500 | I26: 1500
B27: Bauausgaben | C27: 1.9 | D27: Test 9 | E27: 3000 | F27: 1500 | G27: 1000 | H27: 500 | I27: 1500
B28: Bauausgaben | C28: 1.10 | D28: Test 10 | E28: 3000 | F28: 1500 | G28: 1000 | H28: 500 | I28: 1500
B29: Bauausgaben | C29: 1.11 | D29: Test 11 | E29: 3000 | F29: 1500 | G29: 1000 | H29: 500 | I29: 1500
B30: Bauausgaben | C30: 1.12 | D30: Test 12 | E30: 3000 | F30: 1500 | G30: 1000 | H30: 500 | I30: 1500
B31: Bauausgaben | C31: 1.13 | D31: Test 13 | E31: 3000 | F31: 1500 | G31: 1000 | H31: 500 | I31: 1500
... B58: Investitionen | C58: 2.20 | D58: Test 20 | E58: 3000 | F58: 1500 | G58: 1000 | H58: 500 | I58: 1500
B59: Personalkosten | C59: 3.1 | D59: Personalkosten | E59: 0 | I59: 0
B60: Personalkosten | C60: 3.2 | D60: Personalkosten | E60: 0 | I60: 0
B61: Personalkosten | C61: 3.3 | D61: Personalkosten | E61: 0 | I61: 0
B62: Personalkosten | C62: 3.4 | D62: Personalkosten | E62: 0 | I62: 0
B63: Personalkosten | C63: 3.5 | D63: Personalkosten | E63: 0 | I63: 0
B64: Personalkosten | C64: 3.6 | D64: Personalkosten | E64: 0 | I64: 0
B65: Personalkosten | C65: 3.7 | D65: Personalkosten | E65: 0 | I65: 0
B66: Personalkosten | C66: 3.8 | D66: Personalkosten | E66: 0 | I66: 0
B67: Personalkosten | C67: 3.9 | D67: Personalkosten | E67: 0 | I67: 0
B68: Personalkosten | C68: 3.10 | D68: Personalkosten | E68: 0 | I68: 0
B69: Personalkosten | C69: 3.11 | D69: Personalkosten | E69: 0 | I69: 0
B70: Personalkosten | C70: 3.12 | D70: Personalkosten | E70: 0 | I70: 0
... B88: Personalkosten | C88: 3.30 | D88: Personalkosten | E88: 0 | I88: 0
B89: Projektaktivitaeten | C89: 4.1 | D89: Test 1 | E89: 3000 | F89: 1500 | G89: 1000 | H89: 500 | I89: 1500
B90: Projektaktivitaeten | C90: 4.2 | D90: Test 2 | E90: 3000 | F90: 1500 | G90: 1000 | H90: 500 | I90: 1500
B91: Projektaktivitaeten | C91: 4.3 | D91: Test 3 | E91: 3000 | F91: 1500 | G91: 1000 | H91: 500 | I91: 1500
B92: Projektaktivitaeten | C92: 4.4 | D92: Test 4 | E92: 3000 | F92: 1500 | G92: 1000 | H92: 500 | I92: 1500
B93: Projektaktivitaeten | C93: 4.5 | D93: Test 5 | E93: 3000 | F93: 1500 | G93: 1000 | H93: 500 | I93: 1500
B94: Projektaktivitaeten | C94: 4.6 | D94: Test 6 | E94: 3000 | F94: 1500 | G94: 1000 | H94: 500 | I94: 1500
B95: Projektaktivitaeten | C95: 4.7 | D95: Test 7 | E95: 3000 | F95: 1500 | G95: 1000 | H95: 500 | I95: 1500
B96: Projektaktivitaeten | C96: 4.8 | D96: Test 8 | E96: 3000 | F96: 1500 | G96: 1000 | H96: 500 | I96: 1500
B97: Projektaktivitaeten | C97: 4.9 | D97: Test 9 | E97: 3000 | F97: 1500 | G97: 1000 | H97: 500 | I97: 1500
B98: Projektaktivitaeten | C98: 4.10 | D98: Test 10 | E98: 3000 | F98: 1500 | G98: 1000 | H98: 500 | I98: 1500
B99: Projektaktivitaeten | C99: 4.11 | D99: Test 11 | E99: 3000 | F99: 1500 | G99: 1000 | H99: 500 | I99: 1500
B100: Projektaktivitaeten | C100: 4.12 | D100: Test 12 | E100: 3000 | F100: 1500 | G100: 1000 | H100: 500 | I100: 1500
... B108: Projektaktivitaeten | C108: 4.20 | D108: Test 20 | E108: 3000 | F108: 1500 | G108: 1000 | H108: 500 | I108: 1500
B109: Projektaktivitaeten | C109: 4.21 | D109: Projektaktivitaeten | E109: 0 | I109: 0
B110: Projektaktivitaeten | C110: 4.22 | D110: Projektaktivitaeten | E110: 0 | I110: 0
B111: Projektaktivitaeten | C111: 4.23 | D111: Projektaktivitaeten | E111: 0 | I111: 0
B112: Projektaktivitaeten | C112: 4.24 | D112: Projektaktivitaeten | E112: 0 | I112: 0
B113: Projektaktivitaeten | C113: 4.25 | D113: Projektaktivitaeten | E113: 0 | I113: 0
B114: Projektaktivitaeten | C114: 4.26 | D114: Projektaktivitaeten | E114: 0 | I114: 0
B115: Projektaktivitaeten | C115: 4.27 | D115: Projektaktivitaeten | E115: 0 | I115: 0
B116: Projektaktivitaeten | C116: 4.28 | D116: Projektaktivitaeten | E116: 0 | I116: 0
B117: Projektaktivitaeten | C117: 4.29 | D117: Projektaktivitaeten | E117: 0 | I117: 0
B118: Projektaktivitaeten | C118: 4.30 | D118: Projektaktivitaeten | E118: 0 | I118: 0
B119: Projektverwaltung | C119: 5.1 | D119: Test 1 | E119: 3000 | F119: 1500 | G119: 1000 | H119: 500 | I119: 1500
B120: Projektverwaltung | C120: 5.2 | D120: Test 2 | E120: 3000 | F120: 1500 | G120: 1000 | H120: 500 | I120: 1500
B121: Projektverwaltung | C121: 5.3 | D121: Test 3 | E121: 3000 | F121: 1500 | G121: 1000 | H121: 500 | I121: 1500
B122: Projektverwaltung | C122: 5.4 | D122: Test 4 | E122: 3000 | F122: 1500 | G122: 1000 | H122: 500 | I122: 1500
B123: Projektverwaltung | C123: 5.5 | D123: Test 5 | E123: 3000 | F123: 1500 | G123: 1000 | H123: 500 | I123: 1500
B124: Projektverwaltung | C124: 5.6 | D124: Test 6 | E124: 3000 | F124: 1500 | G124: 1000 | H124: 500 | I124: 1500
B125: Projektverwaltung | C125: 5.7 | D125: Test 7 | E125: 3000 | F125: 1500 | G125: 1000 | H125: 500 | I125: 1500
B126: Projektverwaltung | C126: 5.8 | D126: Test 8 | E126: 3000 | F126: 1500 | G126: 1000 | H126: 500 | I126: 1500
B127: Projektverwaltung | C127: 5.9 | D127: Test 9 | E127: 3000 | F127: 1500 | G127: 1000 | H127: 500 | I127: 1500
B128: Projektverwaltung | C128: 5.10 | D128: Test 10 | E128: 3000 | F128: 1500 | G128: 1000 | H128: 500 | I128: 1500
B129: Projektverwaltung | C129: 5.11 | D129: Test 11 | E129: 3000 | F129: 1500 | G129: 1000 | H129: 500 | I129: 1500
B130: Projektverwaltung | C130: 5.12 | D130: Test 12 | E130: 3000 | F130: 1500 | G130: 1000 | H130: 500 | I130: 1500
... B141: Reserve | C141: 8. | D141: Contingency reserve - after authorisation only | E141: 12700 | F141: 6350 | G141: 4233.3333 | H141: 2116.6667 | I141: 6350
B142: Geplante Gesamtausgaben | E142: ==SUBTOTAL(109,TblBudgetAusgaben[Betrag (LC)]) | F142: ==SUBTOTAL(109,TblBudgetAusgaben[Jahr 1]) | G142: ==SUBTOTAL(109,TblBudgetAusgaben[Jahr 2]) | H142: ==SUBTOTAL(109,TblBudgetAusgaben[Jahr 3]) | I142: ==SUBTOTAL(109,TblBudgetAusgaben[Betrag (EUR)])
B144: Budgetpruefung
B145: Einnahmen = Ausgaben (LC) | E145: ==IF(ROUND($E$15-$O$12,2)=0,"OK","Abweichung")
B146: Einnahmen = Ausgaben (EUR) | E146: ==IF(ROUND($I$15-$P$12,2)=0,"OK","Abweichung")
B147: Gleicher Budget-Kurs | E147: ==IF(ROUND($H$4,4)=ROUND(IFERROR($O$12/$P$12,0),4),"OK","Abweichung")
B148: Einnahmen: Jahre = Gesamt (LC) | E148: ==IF(ROUND(($F$15+$G$15+$H$15)-$E$15,2)=0,"OK","Abweichung")
B149: Ausgaben: Jahre = Gesamt (LC) | E149: ==IF(ROUND(($F$142+$G$142+$H$142)-$O$12,2)=0,"OK","Abweichung")

Sheet II. KMW-Mittel
Z1: Periode 1
B2: II. KMW-MITTEL BEREITGESTELLT | Z2: Periode 2
Z3: Periode 3
B4: Periode | C4: Waehrung | D4: Betrag | E4: Datum | Z4: Periode 4
Z5: Periode 5
Z6: Periode 6
Z7: Periode 7
Z8: Periode 8
Z9: Periode 9
Z10: Periode 10
Z11: Periode 11
Z12: Periode 12
Z13: Periode 13
Z14: Periode 14
Z15: Periode 15
Z16: Periode 16
... Z22: Periode 22
B23: GESAMT | D23: ==SUBTOTAL(109,TblKMWMittel[Betrag]) | Z23: Periode 23
Z24: Periode 24
Z25: Periode 25
Z26: Periode 26
Z27: Periode 27
Z28: Periode 28
Z29: Periode 29
Z30: Periode 30
Z31: Periode 31
Z32: Periode 32
Z33: Periode 33
Z34: Periode 34
Z35: Periode 35
Z36: Periode 36

Sheet III. Finanzberichte
H3: ➤ | O3: ➤ | V3: ➤ | AC3: ➤ | AJ3: ➤ | AQ3: ➤ | AX3: ➤ | BE3: ➤ | BL3: ➤ | BS3: ➤ | BZ3: ➤ | CG3: ➤ | CN3: ➤ | CU3: ➤ | DB3: ➤ | DI3: ➤ | DP3: ➤
B4: Periode: | C4: Periode 1 | I4: Periode: | J4: Periode 2 | P4: Periode: | Q4: Periode 3 | W4: Periode: | X4: Periode 4 | AD4: Periode: | AE4: Periode 5 | AK4: Periode: | AL4: Periode 6 | AR4: Periode: | AS4: Periode 7 | AY4: Periode: | AZ4: Periode 8 | BF4: Periode: | BG4: Periode 9 | BM4: Periode: | BN4: Periode 10 | BT4: Periode: | BU4: Periode 11 | CA4: Periode: | CB4: Periode 12 | CH4: Periode: | CI4: Periode 13 | CO4: Periode: | CP4: Periode 14 | CV4: Periode: | CW4: Periode 15 | DC4: Periode: | DD4: Periode 16 | DJ4: Periode: | DK4: Periode 17 | DQ4: Periode: | DR4: Periode 18
B5: Von: | I5: Von: | P5: Von: | W5: Von: | AD5: Von: | AK5: Von: | AR5: Von: | AY5: Von: | BF5: Von: | BM5: Von: | BT5: Von: | CA5: Von: | CH5: Von: | CO5: Von: | CV5: Von: | DC5: Von: | DJ5: Von: | DQ5: Von:
B6: Bis: | I6: Bis: | P6: Bis: | W6: Bis: | AD6: Bis: | AK6: Bis: | AR6: Bis: | AY6: Bis: | BF6: Bis: | BM6: Bis: | BT6: Bis: | CA6: Bis: | CH6: Bis: | CO6: Bis: | CV6: Bis: | DC6: Bis: | DJ6: Bis: | DQ6: Bis:
B7: Zeitraum: | C7: ==IF(OR(C5="",C6=""),"",DATEDIF(C5,C6,"m")+1) -> 158 | I7: Zeitraum: | J7: ==IF(OR(J5="",J6=""),"",DATEDIF(J5,J6,"m")+1) -> 158 | P7: Zeitraum: | Q7: ==IF(OR(Q5="",Q6=""),"",DATEDIF(Q5,Q6,"m")+1) -> 158 | W7: Zeitraum: | X7: ==IF(OR(X5="",X6=""),"",DATEDIF(X5,X6,"m")+1) -> 158 | AD7: Zeitraum: | AE7: ==IF(OR(AE5="",AE6=""),"",DATEDIF(AE5,AE6,"m")+1) -> 158 | AK7: Zeitraum: | AL7: ==IF(OR(AL5="",AL6=""),"",DATEDIF(AL5,AL6,"m")+1) -> 158 | AR7: Zeitraum: | AS7: ==IF(OR(AS5="",AS6=""),"",DATEDIF(AS5,AS6,"m")+1) -> 158 | AY7: Zeitraum: | AZ7: ==IF(OR(AZ5="",AZ6=""),"",DATEDIF(AZ5,AZ6,"m")+1) -> 158 | BF7: Zeitraum: | BG7: ==IF(OR(BG5="",BG6=""),"",DATEDIF(BG5,BG6,"m")+1) -> 158 | BM7: Zeitraum: | BN7: ==IF(OR(BN5="",BN6=""),"",DATEDIF(BN5,BN6,"m")+1) -> 158 | BT7: Zeitraum: | BU7: ==IF(OR(BU5="",BU6=""),"",DATEDIF(BU5,BU6,"m")+1) -> 158 | CA7: Zeitraum: | CB7: ==IF(OR(CB5="",CB6=""),"",DATEDIF(CB5,CB6,"m")+1) -> 158 | CH7: Zeitraum: | CI7: ==IF(OR(CI5="",CI6=""),"",DATEDIF(CI5,CI6,"m")+1) -> 158 | CO7: Zeitraum: | CP7: ==IF(OR(CP5="",CP6=""),"",DATEDIF(CP5,CP6,"m")+1) -> 158 | CV7: Zeitraum: | CW7: ==IF(OR(CW5="",CW6=""),"",DATEDIF(CW5,CW6,"m")+1) -> 158 | DC7: Zeitraum: | DD7: ==IF(OR(DD5="",DD6=""),"",DATEDIF(DD5,DD6,"m")+1) -> 158 | DJ7: Zeitraum: | DK7: ==IF(OR(DK5="",DK6=""),"",DATEDIF(DK5,DK6,"m")+1) -> 158 | DQ7: Zeitraum: | DR7: ==IF(OR(DR5="",DR6=""),"",DATEDIF(DR5,DR6,"m")+1) -> 158
B8: Durchschnittskurs: | C8: ==ROUND(IFERROR(F161,0),6) -> 158 | I8: Durchschnittskurs: | J8: ==ROUND(IFERROR(M161,0),6) -> 158 | P8: Durchschnittskurs: | Q8: ==ROUND(IFERROR(T161,0),6) -> 158 | W8: Durchschnittskurs: | X8: ==ROUND(IFERROR(AA161,0),6) -> 158 | AD8: Durchschnittskurs: | AE8: ==ROUND(IFERROR(AH161,0),6) -> 158 | AK8: Durchschnittskurs: | AL8: ==ROUND(IFERROR(AO161,0),6) -> 158 | AR8: Durchschnittskurs: | AS8: ==ROUND(IFERROR(AV161,0),6) -> 158 | AY8: Durchschnittskurs: | AZ8: ==ROUND(IFERROR(BC161,0),6) -> 158 | BF8: Durchschnittskurs: | BG8: ==ROUND(IFERROR(BJ161,0),6) -> 158 | BM8: Durchschnittskurs: | BN8: ==ROUND(IFERROR(BQ161,0),6) -> 158 | BT8: Durchschnittskurs: | BU8: ==ROUND(IFERROR(BX161,0),6) -> 158 | CA8: Durchschnittskurs: | CB8: ==ROUND(IFERROR(CE161,0),6) -> 158 | CH8: Durchschnittskurs: | CI8: ==ROUND(IFERROR(CL161,0),6) -> 158 | CO8: Durchschnittskurs: | CP8: ==ROUND(IFERROR(CS161,0),6) -> 158 | CV8: Durchschnittskurs: | CW8: ==ROUND(IFERROR(CZ161,0),6) -> 158 | DC8: Durchschnittskurs: | DD8: ==ROUND(IFERROR(DG161,0),6) -> 158 | DJ8: Durchschnittskurs: | DK8: ==ROUND(IFERROR(DN161,0),6) -> 158 | DQ8: Durchschnittskurs: | DR8: ==ROUND(IFERROR(DU161,0),6) -> 158
B9: Einnahmen | I9: Einnahmen | P9: Einnahmen | W9: Einnahmen | AD9: Einnahmen | AK9: Einnahmen | AR9: Einnahmen | AY9: Einnahmen | BF9: Einnahmen | BM9: Einnahmen | BT9: Einnahmen | CA9: Einnahmen | CH9: Einnahmen | CO9: Einnahmen | CV9: Einnahmen | DC9: Einnahmen | DJ9: Einnahmen | DQ9: Einnahmen
B10: Typ / ID | C10: Einnahmen (LC) | D10: Einnahmen (EUR) | E10: Kum. Einnahmen (LC) | F10: Kum. Einnahmen (EUR) | I10: Typ / ID | J10: Einnahmen (LC) | K10: Einnahmen (EUR) | L10: Kum. Einnahmen (LC) | M10: Kum. Einnahmen (EUR) | P10: Typ / ID | Q10: Einnahmen (LC) | R10: Einnahmen (EUR) | S10: Kum. Einnahmen (LC) | T10: Kum. Einnahmen (EUR) | W10: Typ / ID | X10: Einnahmen (LC) | Y10: Einnahmen (EUR) | Z10: Kum. Einnahmen (LC) | AA10: Kum. Einnahmen (EUR) | AD10: Typ / ID | AE10: Einnahmen (LC) | AF10: Einnahmen (EUR) | AG10: Kum. Einnahmen (LC) | AH10: Kum. Einnahmen (EUR) | AK10: Typ / ID | AL10: Einnahmen (LC) | AM10: Einnahmen (EUR) | AN10: Kum. Einnahmen (LC) | AO10: Kum. Einnahmen (EUR) | AR10: Typ / ID | AS10: Einnahmen (LC) | AT10: Einnahmen (EUR) | AU10: Kum. Einnahmen (LC) | AV10: Kum. Einnahmen (EUR) | AY10: Typ / ID | AZ10: Einnahmen (LC) | BA10: Einnahmen (EUR) | BB10: Kum. Einnahmen (LC) | BC10: Kum. Einnahmen (EUR) | BF10: Typ / ID | BG10: Einnahmen (LC) | BH10: Einnahmen (EUR) | BI10: Kum. Einnahmen (LC) | BJ10: Kum. Einnahmen (EUR) | BM10: Typ / ID | BN10: Einnahmen (LC) | BO10: Einnahmen (EUR) | BP10: Kum. Einnahmen (LC) | BQ10: Kum. Einnahmen (EUR) | BT10: Typ / ID | BU10: Einnahmen (LC) | BV10: Einnahmen (EUR) | BW10: Kum. Einnahmen (LC) | BX10: Kum. Einnahmen (EUR) | CA10: Typ / ID | CB10: Einnahmen (LC) | CC10: Einnahmen (EUR) | CD10: Kum. Einnahmen (LC) | CE10: Kum. Einnahmen (EUR) | CH10: Typ / ID | CI10: Einnahmen (LC) | CJ10: Einnahmen (EUR) | CK10: Kum. Einnahmen (LC) | CL10: Kum. Einnahmen (EUR) | CO10: Typ / ID | CP10: Einnahmen (LC) | CQ10: Einnahmen (EUR) | CR10: Kum. Einnahmen (LC) | CS10: Kum. Einnahmen (EUR) | CV10: Typ / ID | CW10: Einnahmen (LC) | CX10: Einnahmen (EUR) | CY10: Kum. Einnahmen (LC) | CZ10: Kum. Einnahmen (EUR) | DC10: Typ / ID | DD10: Einnahmen (LC) | DE10: Einnahmen (EUR) | DF10: Kum. Einnahmen (LC) | DG10: Kum. Einnahmen (EUR) | DJ10: Typ / ID | DK10: Einnahmen (LC) | DL10: Einnahmen (EUR) | DM10: Kum. Einnahmen (LC) | DN10: Kum. Einnahmen (EUR) | DQ10: Typ / ID | DR10: Einnahmen (LC) | DS10: Einnahmen (EUR) | DT10: Kum. Einnahmen (LC) | DU10: Kum. Einnahmen (EUR)
B11: Vorprojektsaldo | C11: ==ROUND(IF(Saldovortrag_LW="",0,Saldovortrag_LW),2) | D11: ==ROUND(IF(Saldovortrag_EUR="",0,Saldovortrag_EUR),2) | E11: ==ROUND(IF(Saldovortrag_LW="",0,Saldovortrag_LW),2) | F11: ==ROUND(IF(Saldovortrag_EUR="",0,Saldovortrag_EUR),2) | I11: Vorperiodensaldo | J11: ==ROUND(FB_SaldoLC_1,2) | K11: ==ROUND(FB_SaldoEUR_1,2) | L11: ==ROUND(FB_SaldoLC_1,2) | M11: ==ROUND(FB_SaldoEUR_1,2) | P11: Vorperiodensaldo | Q11: ==ROUND(FB_SaldoLC_2,2) | R11: ==ROUND(FB_SaldoEUR_2,2) | S11: ==ROUND(FB_SaldoLC_2,2) | T11: ==ROUND(FB_SaldoEUR_2,2) | W11: Vorperiodensaldo | X11: ==ROUND(FB_SaldoLC_3,2) | Y11: ==ROUND(FB_SaldoEUR_3,2) | Z11: ==ROUND(FB_SaldoLC_3,2) | AA11: ==ROUND(FB_SaldoEUR_3,2) | AD11: Vorperiodensaldo | AE11: ==ROUND(FB_SaldoLC_4,2) | AF11: ==ROUND(FB_SaldoEUR_4,2) | AG11: ==ROUND(FB_SaldoLC_4,2) | AH11: ==ROUND(FB_SaldoEUR_4,2) | AK11: Vorperiodensaldo | AL11: ==ROUND(FB_SaldoLC_5,2) | AM11: ==ROUND(FB_SaldoEUR_5,2) | AN11: ==ROUND(FB_SaldoLC_5,2) | AO11: ==ROUND(FB_SaldoEUR_5,2) | AR11: Vorperiodensaldo | AS11: ==ROUND(FB_SaldoLC_6,2) | AT11: ==ROUND(FB_SaldoEUR_6,2) | AU11: ==ROUND(FB_SaldoLC_6,2) | AV11: ==ROUND(FB_SaldoEUR_6,2) | AY11: Vorperiodensaldo | AZ11: ==ROUND(FB_SaldoLC_7,2) | BA11: ==ROUND(FB_SaldoEUR_7,2) | BB11: ==ROUND(FB_SaldoLC_7,2) | BC11: ==ROUND(FB_SaldoEUR_7,2) | BF11: Vorperiodensaldo | BG11: ==ROUND(FB_SaldoLC_8,2) | BH11: ==ROUND(FB_SaldoEUR_8,2) | BI11: ==ROUND(FB_SaldoLC_8,2) | BJ11: ==ROUND(FB_SaldoEUR_8,2) | BM11: Vorperiodensaldo | BN11: ==ROUND(FB_SaldoLC_9,2) | BO11: ==ROUND(FB_SaldoEUR_9,2) | BP11: ==ROUND(FB_SaldoLC_9,2) | BQ11: ==ROUND(FB_SaldoEUR_9,2) | BT11: Vorperiodensaldo | BU11: ==ROUND(FB_SaldoLC_10,2) | BV11: ==ROUND(FB_SaldoEUR_10,2) | BW11: ==ROUND(FB_SaldoLC_10,2) | BX11: ==ROUND(FB_SaldoEUR_10,2) | CA11: Vorperiodensaldo | CB11: ==ROUND(FB_SaldoLC_11,2) | CC11: ==ROUND(FB_SaldoEUR_11,2) | CD11: ==ROUND(FB_SaldoLC_11,2) | CE11: ==ROUND(FB_SaldoEUR_11,2) | CH11: Vorperiodensaldo | CI11: ==ROUND(FB_SaldoLC_12,2) | CJ11: ==ROUND(FB_SaldoEUR_12,2) | CK11: ==ROUND(FB_SaldoLC_12,2) | CL11: ==ROUND(FB_SaldoEUR_12,2) | CO11: Vorperiodensaldo | CP11: ==ROUND(FB_SaldoLC_13,2) | CQ11: ==ROUND(FB_SaldoEUR_13,2) | CR11: ==ROUND(FB_SaldoLC_13,2) | CS11: ==ROUND(FB_SaldoEUR_13,2) | CV11: Vorperiodensaldo | CW11: ==ROUND(FB_SaldoLC_14,2) | CX11: ==ROUND(FB_SaldoEUR_14,2) | CY11: ==ROUND(FB_SaldoLC_14,2) | CZ11: ==ROUND(FB_SaldoEUR_14,2) | DC11: Vorperiodensaldo | DD11: ==ROUND(FB_SaldoLC_15,2) | DE11: ==ROUND(FB_SaldoEUR_15,2) | DF11: ==ROUND(FB_SaldoLC_15,2) | DG11: ==ROUND(FB_SaldoEUR_15,2) | DJ11: Vorperiodensaldo | DK11: ==ROUND(FB_SaldoLC_16,2) | DL11: ==ROUND(FB_SaldoEUR_16,2) | DM11: ==ROUND(FB_SaldoLC_16,2) | DN11: ==ROUND(FB_SaldoEUR_16,2) | DQ11: Vorperiodensaldo | DR11: ==ROUND(FB_SaldoLC_17,2) | DS11: ==ROUND(FB_SaldoEUR_17,2) | DT11: ==ROUND(FB_SaldoLC_17,2) | DU11: ==ROUND(FB_SaldoEUR_17,2)
B12: Eigenmittel | C12: ==ROUND(SUMIF($B$156:$B$160,"Eigenmittel",$D$156:$D$160)+SUMIF($B$165:$B$170,"Eigenmittel",$D$165:$D$170),2) | D12: ==ROUND(SUMIF($B$156:$B$160,"Eigenmittel",$E$156:$E$160)+SUMIF($B$165:$B$170,"Eigenmittel",$E$165:$E$170),2) | E12: ==ROUND(SUMIF($B$156:$B$160,"Eigenmittel",$D$156:$D$160)+SUMIF($B$165:$B$170,"Eigenmittel",$D$165:$D$170),2) | F12: ==ROUND(SUMIF($B$156:$B$160,"Eigenmittel",$E$156:$E$160)+SUMIF($B$165:$B$170,"Eigenmittel",$E$165:$E$170),2) | I12: Eigenmittel | J12: ==ROUND(SUMIF($I$156:$I$160,"Eigenmittel",$K$156:$K$160)+SUMIF($I$165:$I$170,"Eigenmittel",$K$165:$K$170),2) | K12: ==ROUND(SUMIF($I$156:$I$160,"Eigenmittel",$L$156:$L$160)+SUMIF($I$165:$I$170,"Eigenmittel",$L$165:$L$170),2) | L12: ==IFERROR(ROUND(E12 + J12, 2), J12) | M12: ==IFERROR(ROUND(F12 + K12, 2), K12) | P12: Eigenmittel | Q12: ==ROUND(SUMIF($P$156:$P$160,"Eigenmittel",$R$156:$R$160)+SUMIF($P$165:$P$170,"Eigenmittel",$R$165:$R$170),2) | R12: ==ROUND(SUMIF($P$156:$P$160,"Eigenmittel",$S$156:$S$160)+SUMIF($P$165:$P$170,"Eigenmittel",$S$165:$S$170),2) | S12: ==IFERROR(ROUND(L12 + Q12, 2), Q12) | T12: ==IFERROR(ROUND(M12 + R12, 2), R12) | W12: Eigenmittel | X12: ==ROUND(SUMIF($W$156:$W$160,"Eigenmittel",$Y$156:$Y$160)+SUMIF($W$165:$W$170,"Eigenmittel",$Y$165:$Y$170),2) | Y12: ==ROUND(SUMIF($W$156:$W$160,"Eigenmittel",$Z$156:$Z$160)+SUMIF($W$165:$W$170,"Eigenmittel",$Z$165:$Z$170),2) | Z12: ==IFERROR(ROUND(S12 + X12, 2), X12) | AA12: ==IFERROR(ROUND(T12 + Y12, 2), Y12) | AD12: Eigenmittel | AE12: ==ROUND(SUMIF($AD$156:$AD$160,"Eigenmittel",$AF$156:$AF$160)+SUMIF($AD$165:$AD$170,"Eigenmittel",$AF$165:$AF$170),2) | AF12: ==ROUND(SUMIF($AD$156:$AD$160,"Eigenmittel",$AG$156:$AG$160)+SUMIF($AD$165:$AD$170,"Eigenmittel",$AG$165:$AG$170),2) | AG12: ==IFERROR(ROUND(Z12 + AE12, 2), AE12) | AH12: ==IFERROR(ROUND(AA12 + AF12, 2), AF12) | AK12: Eigenmittel | AL12: ==ROUND(SUMIF($AK$156:$AK$160,"Eigenmittel",$AM$156:$AM$160)+SUMIF($AK$165:$AK$170,"Eigenmittel",$AM$165:$AM$170),2) | AM12: ==ROUND(SUMIF($AK$156:$AK$160,"Eigenmittel",$AN$156:$AN$160)+SUMIF($AK$165:$AK$170,"Eigenmittel",$AN$165:$AN$170),2) | AN12: ==IFERROR(ROUND(AG12 + AL12, 2), AL12) | AO12: ==IFERROR(ROUND(AH12 + AM12, 2), AM12) | AR12: Eigenmittel | AS12: ==ROUND(SUMIF($AR$156:$AR$160,"Eigenmittel",$AT$156:$AT$160)+SUMIF($AR$165:$AR$170,"Eigenmittel",$AT$165:$AT$170),2) | AT12: ==ROUND(SUMIF($AR$156:$AR$160,"Eigenmittel",$AU$156:$AU$160)+SUMIF($AR$165:$AR$170,"Eigenmittel",$AU$165:$AU$170),2) | AU12: ==IFERROR(ROUND(AN12 + AS12, 2), AS12) | AV12: ==IFERROR(ROUND(AO12 + AT12, 2), AT12) | AY12: Eigenmittel | AZ12: ==ROUND(SUMIF($AY$156:$AY$160,"Eigenmittel",$BA$156:$BA$160)+SUMIF($AY$165:$AY$170,"Eigenmittel",$BA$165:$BA$170),2) | BA12: ==ROUND(SUMIF($AY$156:$AY$160,"Eigenmittel",$BB$156:$BB$160)+SUMIF($AY$165:$AY$170,"Eigenmittel",$BB$165:$BB$170),2) | BB12: ==IFERROR(ROUND(AU12 + AZ12, 2), AZ12) | BC12: ==IFERROR(ROUND(AV12 + BA12, 2), BA12) | BF12: Eigenmittel | BG12: ==ROUND(SUMIF($BF$156:$BF$160,"Eigenmittel",$BH$156:$BH$160)+SUMIF($BF$165:$BF$170,"Eigenmittel",$BH$165:$BH$170),2) | BH12: ==ROUND(SUMIF($BF$156:$BF$160,"Eigenmittel",$BI$156:$BI$160)+SUMIF($BF$165:$BF$170,"Eigenmittel",$BI$165:$BI$170),2) | BI12: ==IFERROR(ROUND(BB12 + BG12, 2), BG12) | BJ12: ==IFERROR(ROUND(BC12 + BH12, 2), BH12) | BM12: Eigenmittel | BN12: ==ROUND(SUMIF($BM$156:$BM$160,"Eigenmittel",$BO$156:$BO$160)+SUMIF($BM$165:$BM$170,"Eigenmittel",$BO$165:$BO$170),2) | BO12: ==ROUND(SUMIF($BM$156:$BM$160,"Eigenmittel",$BP$156:$BP$160)+SUMIF($BM$165:$BM$170,"Eigenmittel",$BP$165:$BP$170),2) | BP12: ==IFERROR(ROUND(BI12 + BN12, 2), BN12) | BQ12: ==IFERROR(ROUND(BJ12 + BO12, 2), BO12) | BT12: Eigenmittel | BU12: ==ROUND(SUMIF($BT$156:$BT$160,"Eigenmittel",$BV$156:$BV$160)+SUMIF($BT$165:$BT$170,"Eigenmittel",$BV$165:$BV$170),2) | BV12: ==ROUND(SUMIF($BT$156:$BT$160,"Eigenmittel",$BW$156:$BW$160)+SUMIF($BT$165:$BT$170,"Eigenmittel",$BW$165:$BW$170),2) | BW12: ==IFERROR(ROUND(BP12 + BU12, 2), BU12) | BX12: ==IFERROR(ROUND(BQ12 + BV12, 2), BV12) | CA12: Eigenmittel | CB12: ==ROUND(SUMIF($CA$156:$CA$160,"Eigenmittel",$CC$156:$CC$160)+SUMIF($CA$165:$CA$170,"Eigenmittel",$CC$165:$CC$170),2) | CC12: ==ROUND(SUMIF($CA$156:$CA$160,"Eigenmittel",$CD$156:$CD$160)+SUMIF($CA$165:$CA$170,"Eigenmittel",$CD$165:$CD$170),2) | CD12: ==IFERROR(ROUND(BW12 + CB12, 2), CB12) | CE12: ==IFERROR(ROUND(BX12 + CC12, 2), CC12) | CH12: Eigenmittel | CI12: ==ROUND(SUMIF($CH$156:$CH$160,"Eigenmittel",$CJ$156:$CJ$160)+SUMIF($CH$165:$CH$170,"Eigenmittel",$CJ$165:$CJ$170),2) | CJ12: ==ROUND(SUMIF($CH$156:$CH$160,"Eigenmittel",$CK$156:$CK$160)+SUMIF($CH$165:$CH$170,"Eigenmittel",$CK$165:$CK$170),2) | CK12: ==IFERROR(ROUND(CD12 + CI12, 2), CI12) | CL12: ==IFERROR(ROUND(CE12 + CJ12, 2), CJ12) | CO12: Eigenmittel | CP12: ==ROUND(SUMIF($CO$156:$CO$160,"Eigenmittel",$CQ$156:$CQ$160)+SUMIF($CO$165:$CO$170,"Eigenmittel",$CQ$165:$CQ$170),2) | CQ12: ==ROUND(SUMIF($CO$156:$CO$160,"Eigenmittel",$CR$156:$CR$160)+SUMIF($CO$165:$CO$170,"Eigenmittel",$CR$165:$CR$170),2) | CR12: ==IFERROR(ROUND(CK12 + CP12, 2), CP12) | CS12: ==IFERROR(ROUND(CL12 + CQ12, 2), CQ12) | CV12: Eigenmittel | CW12: ==ROUND(SUMIF($CV$156:$CV$160,"Eigenmittel",$CX$156:$CX$160)+SUMIF($CV$165:$CV$170,"Eigenmittel",$CX$165:$CX$170),2) | CX12: ==ROUND(SUMIF($CV$156:$CV$160,"Eigenmittel",$CY$156:$CY$160)+SUMIF($CV$165:$CV$170,"Eigenmittel",$CY$165:$CY$170),2) | CY12: ==IFERROR(ROUND(CR12 + CW12, 2), CW12) | CZ12: ==IFERROR(ROUND(CS12 + CX12, 2), CX12) | DC12: Eigenmittel | DD12: ==ROUND(SUMIF($DC$156:$DC$160,"Eigenmittel",$DE$156:$DE$160)+SUMIF($DC$165:$DC$170,"Eigenmittel",$DE$165:$DE$170),2) | DE12: ==ROUND(SUMIF($DC$156:$DC$160,"Eigenmittel",$DF$156:$DF$160)+SUMIF($DC$165:$DC$170,"Eigenmittel",$DF$165:$DF$170),2) | DF12: ==IFERROR(ROUND(CY12 + DD12, 2), DD12) | DG12: ==IFERROR(ROUND(CZ12 + DE12, 2), DE12) | DJ12: Eigenmittel | DK12: ==ROUND(SUMIF($DJ$156:$DJ$160,"Eigenmittel",$DL$156:$DL$160)+SUMIF($DJ$165:$DJ$170,"Eigenmittel",$DL$165:$DL$170),2) | DL12: ==ROUND(SUMIF($DJ$156:$DJ$160,"Eigenmittel",$DM$156:$DM$160)+SUMIF($DJ$165:$DJ$170,"Eigenmittel",$DM$165:$DM$170),2) | DM12: ==IFERROR(ROUND(DF12 + DK12, 2), DK12) | DN12: ==IFERROR(ROUND(DG12 + DL12, 2), DL12) | DQ12: Eigenmittel | DR12: ==ROUND(SUMIF($DQ$156:$DQ$160,"Eigenmittel",$DS$156:$DS$160)+SUMIF($DQ$165:$DQ$170,"Eigenmittel",$DS$165:$DS$170),2) | DS12: ==ROUND(SUMIF($DQ$156:$DQ$160,"Eigenmittel",$DT$156:$DT$160)+SUMIF($DQ$165:$DQ$170,"Eigenmittel",$DT$165:$DT$170),2) | DT12: ==IFERROR(ROUND(DM12 + DR12, 2), DR12) | DU12: ==IFERROR(ROUND(DN12 + DS12, 2), DS12)
B13: Drittmittel | C13: ==ROUND(SUMIF($B$156:$B$160,"Drittmittel",$D$156:$D$160)+SUMIF($B$165:$B$170,"Drittmittel",$D$165:$D$170),2) | D13: ==ROUND(SUMIF($B$156:$B$160,"Drittmittel",$E$156:$E$160)+SUMIF($B$165:$B$170,"Drittmittel",$E$165:$E$170),2) | E13: ==ROUND(SUMIF($B$156:$B$160,"Drittmittel",$D$156:$D$160)+SUMIF($B$165:$B$170,"Drittmittel",$D$165:$D$170),2) | F13: ==ROUND(SUMIF($B$156:$B$160,"Drittmittel",$E$156:$E$160)+SUMIF($B$165:$B$170,"Drittmittel",$E$165:$E$170),2) | I13: Drittmittel | J13: ==ROUND(SUMIF($I$156:$I$160,"Drittmittel",$K$156:$K$160)+SUMIF($I$165:$I$170,"Drittmittel",$K$165:$K$170),2) | K13: ==ROUND(SUMIF($I$156:$I$160,"Drittmittel",$L$156:$L$160)+SUMIF($I$165:$I$170,"Drittmittel",$L$165:$L$170),2) | L13: ==IFERROR(ROUND(E13 + J13, 2), J13) | M13: ==IFERROR(ROUND(F13 + K13, 2), K13) | P13: Drittmittel | Q13: ==ROUND(SUMIF($P$156:$P$160,"Drittmittel",$R$156:$R$160)+SUMIF($P$165:$P$170,"Drittmittel",$R$165:$R$170),2) | R13: ==ROUND(SUMIF($P$156:$P$160,"Drittmittel",$S$156:$S$160)+SUMIF($P$165:$P$170,"Drittmittel",$S$165:$S$170),2) | S13: ==IFERROR(ROUND(L13 + Q13, 2), Q13) | T13: ==IFERROR(ROUND(M13 + R13, 2), R13) | W13: Drittmittel | X13: ==ROUND(SUMIF($W$156:$W$160,"Drittmittel",$Y$156:$Y$160)+SUMIF($W$165:$W$170,"Drittmittel",$Y$165:$Y$170),2) | Y13: ==ROUND(SUMIF($W$156:$W$160,"Drittmittel",$Z$156:$Z$160)+SUMIF($W$165:$W$170,"Drittmittel",$Z$165:$Z$170),2) | Z13: ==IFERROR(ROUND(S13 + X13, 2), X13) | AA13: ==IFERROR(ROUND(T13 + Y13, 2), Y13) | AD13: Drittmittel | AE13: ==ROUND(SUMIF($AD$156:$AD$160,"Drittmittel",$AF$156:$AF$160)+SUMIF($AD$165:$AD$170,"Drittmittel",$AF$165:$AF$170),2) | AF13: ==ROUND(SUMIF($AD$156:$AD$160,"Drittmittel",$AG$156:$AG$160)+SUMIF($AD$165:$AD$170,"Drittmittel",$AG$165:$AG$170),2) | AG13: ==IFERROR(ROUND(Z13 + AE13, 2), AE13) | AH13: ==IFERROR(ROUND(AA13 + AF13, 2), AF13) | AK13: Drittmittel | AL13: ==ROUND(SUMIF($AK$156:$AK$160,"Drittmittel",$AM$156:$AM$160)+SUMIF($AK$165:$AK$170,"Drittmittel",$AM$165:$AM$170),2) | AM13: ==ROUND(SUMIF($AK$156:$AK$160,"Drittmittel",$AN$156:$AN$160)+SUMIF($AK$165:$AK$170,"Drittmittel",$AN$165:$AN$170),2) | AN13: ==IFERROR(ROUND(AG13 + AL13, 2), AL13) | AO13: ==IFERROR(ROUND(AH13 + AM13, 2), AM13) | AR13: Drittmittel | AS13: ==ROUND(SUMIF($AR$156:$AR$160,"Drittmittel",$AT$156:$AT$160)+SUMIF($AR$165:$AR$170,"Drittmittel",$AT$165:$AT$170),2) | AT13: ==ROUND(SUMIF($AR$156:$AR$160,"Drittmittel",$AU$156:$AU$160)+SUMIF($AR$165:$AR$170,"Drittmittel",$AU$165:$AU$170),2) | AU13: ==IFERROR(ROUND(AN13 + AS13, 2), AS13) | AV13: ==IFERROR(ROUND(AO13 + AT13, 2), AT13) | AY13: Drittmittel | AZ13: ==ROUND(SUMIF($AY$156:$AY$160,"Drittmittel",$BA$156:$BA$160)+SUMIF($AY$165:$AY$170,"Drittmittel",$BA$165:$BA$170),2) | BA13: ==ROUND(SUMIF($AY$156:$AY$160,"Drittmittel",$BB$156:$BB$160)+SUMIF($AY$165:$AY$170,"Drittmittel",$BB$165:$BB$170),2) | BB13: ==IFERROR(ROUND(AU13 + AZ13, 2), AZ13) | BC13: ==IFERROR(ROUND(AV13 + BA13, 2), BA13) | BF13: Drittmittel | BG13: ==ROUND(SUMIF($BF$156:$BF$160,"Drittmittel",$BH$156:$BH$160)+SUMIF($BF$165:$BF$170,"Drittmittel",$BH$165:$BH$170),2) | BH13: ==ROUND(SUMIF($BF$156:$BF$160,"Drittmittel",$BI$156:$BI$160)+SUMIF($BF$165:$BF$170,"Drittmittel",$BI$165:$BI$170),2) | BI13: ==IFERROR(ROUND(BB13 + BG13, 2), BG13) | BJ13: ==IFERROR(ROUND(BC13 + BH13, 2), BH13) | BM13: Drittmittel | BN13: ==ROUND(SUMIF($BM$156:$BM$160,"Drittmittel",$BO$156:$BO$160)+SUMIF($BM$165:$BM$170,"Drittmittel",$BO$165:$BO$170),2) | BO13: ==ROUND(SUMIF($BM$156:$BM$160,"Drittmittel",$BP$156:$BP$160)+SUMIF($BM$165:$BM$170,"Drittmittel",$BP$165:$BP$170),2) | BP13: ==IFERROR(ROUND(BI13 + BN13, 2), BN13) | BQ13: ==IFERROR(ROUND(BJ13 + BO13, 2), BO13) | BT13: Drittmittel | BU13: ==ROUND(SUMIF($BT$156:$BT$160,"Drittmittel",$BV$156:$BV$160)+SUMIF($BT$165:$BT$170,"Drittmittel",$BV$165:$BV$170),2) | BV13: ==ROUND(SUMIF($BT$156:$BT$160,"Drittmittel",$BW$156:$BW$160)+SUMIF($BT$165:$BT$170,"Drittmittel",$BW$165:$BW$170),2) | BW13: ==IFERROR(ROUND(BP13 + BU13, 2), BU13) | BX13: ==IFERROR(ROUND(BQ13 + BV13, 2), BV13) | CA13: Drittmittel | CB13: ==ROUND(SUMIF($CA$156:$CA$160,"Drittmittel",$CC$156:$CC$160)+SUMIF($CA$165:$CA$170,"Drittmittel",$CC$165:$CC$170),2) | CC13: ==ROUND(SUMIF($CA$156:$CA$160,"Drittmittel",$CD$156:$CD$160)+SUMIF($CA$165:$CA$170,"Drittmittel",$CD$165:$CD$170),2) | CD13: ==IFERROR(ROUND(BW13 + CB13, 2), CB13) | CE13: ==IFERROR(ROUND(BX13 + CC13, 2), CC13) | CH13: Drittmittel | CI13: ==ROUND(SUMIF($CH$156:$CH$160,"Drittmittel",$CJ$156:$CJ$160)+SUMIF($CH$165:$CH$170,"Drittmittel",$CJ$165:$CJ$170),2) | CJ13: ==ROUND(SUMIF($CH$156:$CH$160,"Drittmittel",$CK$156:$CK$160)+SUMIF($CH$165:$CH$170,"Drittmittel",$CK$165:$CK$170),2) | CK13: ==IFERROR(ROUND(CD13 + CI13, 2), CI13) | CL13: ==IFERROR(ROUND(CE13 + CJ13, 2), CJ13) | CO13: Drittmittel | CP13: ==ROUND(SUMIF($CO$156:$CO$160,"Drittmittel",$CQ$156:$CQ$160)+SUMIF($CO$165:$CO$170,"Drittmittel",$CQ$165:$CQ$170),2) | CQ13: ==ROUND(SUMIF($CO$156:$CO$160,"Drittmittel",$CR$156:$CR$160)+SUMIF($CO$165:$CO$170,"Drittmittel",$CR$165:$CR$170),2) | CR13: ==IFERROR(ROUND(CK13 + CP13, 2), CP13) | CS13: ==IFERROR(ROUND(CL13 + CQ13, 2), CQ13) | CV13: Drittmittel | CW13: ==ROUND(SUMIF($CV$156:$CV$160,"Drittmittel",$CX$156:$CX$160)+SUMIF($CV$165:$CV$170,"Drittmittel",$CX$165:$CX$170),2) | CX13: ==ROUND(SUMIF($CV$156:$CV$160,"Drittmittel",$CY$156:$CY$160)+SUMIF($CV$165:$CV$170,"Drittmittel",$CY$165:$CY$170),2) | CY13: ==IFERROR(ROUND(CR13 + CW13, 2), CW13) | CZ13: ==IFERROR(ROUND(CS13 + CX13, 2), CX13) | DC13: Drittmittel | DD13: ==ROUND(SUMIF($DC$156:$DC$160,"Drittmittel",$DE$156:$DE$160)+SUMIF($DC$165:$DC$170,"Drittmittel",$DE$165:$DE$170),2) | DE13: ==ROUND(SUMIF($DC$156:$DC$160,"Drittmittel",$DF$156:$DF$160)+SUMIF($DC$165:$DC$170,"Drittmittel",$DF$165:$DF$170),2) | DF13: ==IFERROR(ROUND(CY13 + DD13, 2), DD13) | DG13: ==IFERROR(ROUND(CZ13 + DE13, 2), DE13) | DJ13: Drittmittel | DK13: ==ROUND(SUMIF($DJ$156:$DJ$160,"Drittmittel",$DL$156:$DL$160)+SUMIF($DJ$165:$DJ$170,"Drittmittel",$DL$165:$DL$170),2) | DL13: ==ROUND(SUMIF($DJ$156:$DJ$160,"Drittmittel",$DM$156:$DM$160)+SUMIF($DJ$165:$DJ$170,"Drittmittel",$DM$165:$DM$170),2) | DM13: ==IFERROR(ROUND(DF13 + DK13, 2), DK13) | DN13: ==IFERROR(ROUND(DG13 + DL13, 2), DL13) | DQ13: Drittmittel | DR13: ==ROUND(SUMIF($DQ$156:$DQ$160,"Drittmittel",$DS$156:$DS$160)+SUMIF($DQ$165:$DQ$170,"Drittmittel",$DS$165:$DS$170),2) | DS13: ==ROUND(SUMIF($DQ$156:$DQ$160,"Drittmittel",$DT$156:$DT$160)+SUMIF($DQ$165:$DQ$170,"Drittmittel",$DT$165:$DT$170),2) | DT13: ==IFERROR(ROUND(DM13 + DR13, 2), DR13) | DU13: ==IFERROR(ROUND(DN13 + DS13, 2), DS13)
B14: KMW-Mittel | C14: ==ROUND(SUMIF($B$156:$B$160,"KMW-Mittel",$D$156:$D$160)+SUMIF($B$165:$B$170,"KMW-Mittel",$D$165:$D$170),2) | D14: ==ROUND(SUMIF($B$156:$B$160,"KMW-Mittel",$E$156:$E$160)+SUMIF($B$165:$B$170,"KMW-Mittel",$E$165:$E$170),2) | E14: ==ROUND(SUMIF($B$156:$B$160,"KMW-Mittel",$D$156:$D$160)+SUMIF($B$165:$B$170,"KMW-Mittel",$D$165:$D$170),2) | F14: ==ROUND(SUMIF($B$156:$B$160,"KMW-Mittel",$E$156:$E$160)+SUMIF($B$165:$B$170,"KMW-Mittel",$E$165:$E$170),2) | I14: KMW-Mittel | J14: ==ROUND(SUMIF($I$156:$I$160,"KMW-Mittel",$K$156:$K$160)+SUMIF($I$165:$I$170,"KMW-Mittel",$K$165:$K$170),2) | K14: ==ROUND(SUMIF($I$156:$I$160,"KMW-Mittel",$L$156:$L$160)+SUMIF($I$165:$I$170,"KMW-Mittel",$L$165:$L$170),2) | L14: ==IFERROR(ROUND(E14 + J14, 2), J14) | M14: ==IFERROR(ROUND(F14 + K14, 2), K14) | P14: KMW-Mittel | Q14: ==ROUND(SUMIF($P$156:$P$160,"KMW-Mittel",$R$156:$R$160)+SUMIF($P$165:$P$170,"KMW-Mittel",$R$165:$R$170),2) | R14: ==ROUND(SUMIF($P$156:$P$160,"KMW-Mittel",$S$156:$S$160)+SUMIF($P$165:$P$170,"KMW-Mittel",$S$165:$S$170),2) | S14: ==IFERROR(ROUND(L14 + Q14, 2), Q14) | T14: ==IFERROR(ROUND(M14 + R14, 2), R14) | W14: KMW-Mittel | X14: ==ROUND(SUMIF($W$156:$W$160,"KMW-Mittel",$Y$156:$Y$160)+SUMIF($W$165:$W$170,"KMW-Mittel",$Y$165:$Y$170),2) | Y14: ==ROUND(SUMIF($W$156:$W$160,"KMW-Mittel",$Z$156:$Z$160)+SUMIF($W$165:$W$170,"KMW-Mittel",$Z$165:$Z$170),2) | Z14: ==IFERROR(ROUND(S14 + X14, 2), X14) | AA14: ==IFERROR(ROUND(T14 + Y14, 2), Y14) | AD14: KMW-Mittel | AE14: ==ROUND(SUMIF($AD$156:$AD$160,"KMW-Mittel",$AF$156:$AF$160)+SUMIF($AD$165:$AD$170,"KMW-Mittel",$AF$165:$AF$170),2) | AF14: ==ROUND(SUMIF($AD$156:$AD$160,"KMW-Mittel",$AG$156:$AG$160)+SUMIF($AD$165:$AD$170,"KMW-Mittel",$AG$165:$AG$170),2) | AG14: ==IFERROR(ROUND(Z14 + AE14, 2), AE14) | AH14: ==IFERROR(ROUND(AA14 + AF14, 2), AF14) | AK14: KMW-Mittel | AL14: ==ROUND(SUMIF($AK$156:$AK$160,"KMW-Mittel",$AM$156:$AM$160)+SUMIF($AK$165:$AK$170,"KMW-Mittel",$AM$165:$AM$170),2) | AM14: ==ROUND(SUMIF($AK$156:$AK$160,"KMW-Mittel",$AN$156:$AN$160)+SUMIF($AK$165:$AK$170,"KMW-Mittel",$AN$165:$AN$170),2) | AN14: ==IFERROR(ROUND(AG14 + AL14, 2), AL14) | AO14: ==IFERROR(ROUND(AH14 + AM14, 2), AM14) | AR14: KMW-Mittel | AS14: ==ROUND(SUMIF($AR$156:$AR$160,"KMW-Mittel",$AT$156:$AT$160)+SUMIF($AR$165:$AR$170,"KMW-Mittel",$AT$165:$AT$170),2) | AT14: ==ROUND(SUMIF($AR$156:$AR$160,"KMW-Mittel",$AU$156:$AU$160)+SUMIF($AR$165:$AR$170,"KMW-Mittel",$AU$165:$AU$170),2) | AU14: ==IFERROR(ROUND(AN14 + AS14, 2), AS14) | AV14: ==IFERROR(ROUND(AO14 + AT14, 2), AT14) | AY14: KMW-Mittel | AZ14: ==ROUND(SUMIF($AY$156:$AY$160,"KMW-Mittel",$BA$156:$BA$160)+SUMIF($AY$165:$AY$170,"KMW-Mittel",$BA$165:$BA$170),2) | BA14: ==ROUND(SUMIF($AY$156:$AY$160,"KMW-Mittel",$BB$156:$BB$160)+SUMIF($AY$165:$AY$170,"KMW-Mittel",$BB$165:$BB$170),2) | BB14: ==IFERROR(ROUND(AU14 + AZ14, 2), AZ14) | BC14: ==IFERROR(ROUND(AV14 + BA14, 2), BA14) | BF14: KMW-Mittel | BG14: ==ROUND(SUMIF($BF$156:$BF$160,"KMW-Mittel",$BH$156:$BH$160)+SUMIF($BF$165:$BF$170,"KMW-Mittel",$BH$165:$BH$170),2) | BH14: ==ROUND(SUMIF($BF$156:$BF$160,"KMW-Mittel",$BI$156:$BI$160)+SUMIF($BF$165:$BF$170,"KMW-Mittel",$BI$165:$BI$170),2) | BI14: ==IFERROR(ROUND(BB14 + BG14, 2), BG14) | BJ14: ==IFERROR(ROUND(BC14 + BH14, 2), BH14) | BM14: KMW-Mittel | BN14: ==ROUND(SUMIF($BM$156:$BM$160,"KMW-Mittel",$BO$156:$BO$160)+SUMIF($BM$165:$BM$170,"KMW-Mittel",$BO$165:$BO$170),2) | BO14: ==ROUND(SUMIF($BM$156:$BM$160,"KMW-Mittel",$BP$156:$BP$160)+SUMIF($BM$165:$BM$170,"KMW-Mittel",$BP$165:$BP$170),2) | BP14: ==IFERROR(ROUND(BI14 + BN14, 2), BN14) | BQ14: ==IFERROR(ROUND(BJ14 + BO14, 2), BO14) | BT14: KMW-Mittel | BU14: ==ROUND(SUMIF($BT$156:$BT$160,"KMW-Mittel",$BV$156:$BV$160)+SUMIF($BT$165:$BT$170,"KMW-Mittel",$BV$165:$BV$170),2) | BV14: ==ROUND(SUMIF($BT$156:$BT$160,"KMW-Mittel",$BW$156:$BW$160)+SUMIF($BT$165:$BT$170,"KMW-Mittel",$BW$165:$BW$170),2) | BW14: ==IFERROR(ROUND(BP14 + BU14, 2), BU14) | BX14: ==IFERROR(ROUND(BQ14 + BV14, 2), BV14) | CA14: KMW-Mittel | CB14: ==ROUND(SUMIF($CA$156:$CA$160,"KMW-Mittel",$CC$156:$CC$160)+SUMIF($CA$165:$CA$170,"KMW-Mittel",$CC$165:$CC$170),2) | CC14: ==ROUND(SUMIF($CA$156:$CA$160,"KMW-Mittel",$CD$156:$CD$160)+SUMIF($CA$165:$CA$170,"KMW-Mittel",$CD$165:$CD$170),2) | CD14: ==IFERROR(ROUND(BW14 + CB14, 2), CB14) | CE14: ==IFERROR(ROUND(BX14 + CC14, 2), CC14) | CH14: KMW-Mittel | CI14: ==ROUND(SUMIF($CH$156:$CH$160,"KMW-Mittel",$CJ$156:$CJ$160)+SUMIF($CH$165:$CH$170,"KMW-Mittel",$CJ$165:$CJ$170),2) | CJ14: ==ROUND(SUMIF($CH$156:$CH$160,"KMW-Mittel",$CK$156:$CK$160)+SUMIF($CH$165:$CH$170,"KMW-Mittel",$CK$165:$CK$170),2) | CK14: ==IFERROR(ROUND(CD14 + CI14, 2), CI14) | CL14: ==IFERROR(ROUND(CE14 + CJ14, 2), CJ14) | CO14: KMW-Mittel | CP14: ==ROUND(SUMIF($CO$156:$CO$160,"KMW-Mittel",$CQ$156:$CQ$160)+SUMIF($CO$165:$CO$170,"KMW-Mittel",$CQ$165:$CQ$170),2) | CQ14: ==ROUND(SUMIF($CO$156:$CO$160,"KMW-Mittel",$CR$156:$CR$160)+SUMIF($CO$165:$CO$170,"KMW-Mittel",$CR$165:$CR$170),2) | CR14: ==IFERROR(ROUND(CK14 + CP14, 2), CP14) | CS14: ==IFERROR(ROUND(CL14 + CQ14, 2), CQ14) | CV14: KMW-Mittel | CW14: ==ROUND(SUMIF($CV$156:$CV$160,"KMW-Mittel",$CX$156:$CX$160)+SUMIF($CV$165:$CV$170,"KMW-Mittel",$CX$165:$CX$170),2) | CX14: ==ROUND(SUMIF($CV$156:$CV$160,"KMW-Mittel",$CY$156:$CY$160)+SUMIF($CV$165:$CV$170,"KMW-Mittel",$CY$165:$CY$170),2) | CY14: ==IFERROR(ROUND(CR14 + CW14, 2), CW14) | CZ14: ==IFERROR(ROUND(CS14 + CX14, 2), CX14) | DC14: KMW-Mittel | DD14: ==ROUND(SUMIF($DC$156:$DC$160,"KMW-Mittel",$DE$156:$DE$160)+SUMIF($DC$165:$DC$170,"KMW-Mittel",$DE$165:$DE$170),2) | DE14: ==ROUND(SUMIF($DC$156:$DC$160,"KMW-Mittel",$DF$156:$DF$160)+SUMIF($DC$165:$DC$170,"KMW-Mittel",$DF$165:$DF$170),2) | DF14: ==IFERROR(ROUND(CY14 + DD14, 2), DD14) | DG14: ==IFERROR(ROUND(CZ14 + DE14, 2), DE14) | DJ14: KMW-Mittel | DK14: ==ROUND(SUMIF($DJ$156:$DJ$160,"KMW-Mittel",$DL$156:$DL$160)+SUMIF($DJ$165:$DJ$170,"KMW-Mittel",$DL$165:$DL$170),2) | DL14: ==ROUND(SUMIF($DJ$156:$DJ$160,"KMW-Mittel",$DM$156:$DM$160)+SUMIF($DJ$165:$DJ$170,"KMW-Mittel",$DM$165:$DM$170),2) | DM14: ==IFERROR(ROUND(DF14 + DK14, 2), DK14) | DN14: ==IFERROR(ROUND(DG14 + DL14, 2), DL14) | DQ14: KMW-Mittel | DR14: ==ROUND(SUMIF($DQ$156:$DQ$160,"KMW-Mittel",$DS$156:$DS$160)+SUMIF($DQ$165:$DQ$170,"KMW-Mittel",$DS$165:$DS$170),2) | DS14: ==ROUND(SUMIF($DQ$156:$DQ$160,"KMW-Mittel",$DT$156:$DT$160)+SUMIF($DQ$165:$DQ$170,"KMW-Mittel",$DT$165:$DT$170),2) | DT14: ==IFERROR(ROUND(DM14 + DR14, 2), DR14) | DU14: ==IFERROR(ROUND(DN14 + DS14, 2), DS14)
B15: Zinsertraege | C15: ==ROUND(SUMIF($B$156:$B$160,"Zinsertraege",$D$156:$D$160)+SUMIF($B$165:$B$170,"Zinsertraege",$D$165:$D$170),2) | D15: ==ROUND(SUMIF($B$156:$B$160,"Zinsertraege",$E$156:$E$160)+SUMIF($B$165:$B$170,"Zinsertraege",$E$165:$E$170),2) | E15: ==ROUND(SUMIF($B$156:$B$160,"Zinsertraege",$D$156:$D$160)+SUMIF($B$165:$B$170,"Zinsertraege",$D$165:$D$170),2) | F15: ==ROUND(SUMIF($B$156:$B$160,"Zinsertraege",$E$156:$E$160)+SUMIF($B$165:$B$170,"Zinsertraege",$E$165:$E$170),2) | I15: Zinsertraege | J15: ==ROUND(SUMIF($I$156:$I$160,"Zinsertraege",$K$156:$K$160)+SUMIF($I$165:$I$170,"Zinsertraege",$K$165:$K$170),2) | K15: ==ROUND(SUMIF($I$156:$I$160,"Zinsertraege",$L$156:$L$160)+SUMIF($I$165:$I$170,"Zinsertraege",$L$165:$L$170),2) | L15: ==IFERROR(ROUND(E15 + J15, 2), J15) | M15: ==IFERROR(ROUND(F15 + K15, 2), K15) | P15: Zinsertraege | Q15: ==ROUND(SUMIF($P$156:$P$160,"Zinsertraege",$R$156:$R$160)+SUMIF($P$165:$P$170,"Zinsertraege",$R$165:$R$170),2) | R15: ==ROUND(SUMIF($P$156:$P$160,"Zinsertraege",$S$156:$S$160)+SUMIF($P$165:$P$170,"Zinsertraege",$S$165:$S$170),2) | S15: ==IFERROR(ROUND(L15 + Q15, 2), Q15) | T15: ==IFERROR(ROUND(M15 + R15, 2), R15) | W15: Zinsertraege | X15: ==ROUND(SUMIF($W$156:$W$160,"Zinsertraege",$Y$156:$Y$160)+SUMIF($W$165:$W$170,"Zinsertraege",$Y$165:$Y$170),2) | Y15: ==ROUND(SUMIF($W$156:$W$160,"Zinsertraege",$Z$156:$Z$160)+SUMIF($W$165:$W$170,"Zinsertraege",$Z$165:$Z$170),2) | Z15: ==IFERROR(ROUND(S15 + X15, 2), X15) | AA15: ==IFERROR(ROUND(T15 + Y15, 2), Y15) | AD15: Zinsertraege | AE15: ==ROUND(SUMIF($AD$156:$AD$160,"Zinsertraege",$AF$156:$AF$160)+SUMIF($AD$165:$AD$170,"Zinsertraege",$AF$165:$AF$170),2) | AF15: ==ROUND(SUMIF($AD$156:$AD$160,"Zinsertraege",$AG$156:$AG$160)+SUMIF($AD$165:$AD$170,"Zinsertraege",$AG$165:$AG$170),2) | AG15: ==IFERROR(ROUND(Z15 + AE15, 2), AE15) | AH15: ==IFERROR(ROUND(AA15 + AF15, 2), AF15) | AK15: Zinsertraege | AL15: ==ROUND(SUMIF($AK$156:$AK$160,"Zinsertraege",$AM$156:$AM$160)+SUMIF($AK$165:$AK$170,"Zinsertraege",$AM$165:$AM$170),2) | AM15: ==ROUND(SUMIF($AK$156:$AK$160,"Zinsertraege",$AN$156:$AN$160)+SUMIF($AK$165:$AK$170,"Zinsertraege",$AN$165:$AN$170),2) | AN15: ==IFERROR(ROUND(AG15 + AL15, 2), AL15) | AO15: ==IFERROR(ROUND(AH15 + AM15, 2), AM15) | AR15: Zinsertraege | AS15: ==ROUND(SUMIF($AR$156:$AR$160,"Zinsertraege",$AT$156:$AT$160)+SUMIF($AR$165:$AR$170,"Zinsertraege",$AT$165:$AT$170),2) | AT15: ==ROUND(SUMIF($AR$156:$AR$160,"Zinsertraege",$AU$156:$AU$160)+SUMIF($AR$165:$AR$170,"Zinsertraege",$AU$165:$AU$170),2) | AU15: ==IFERROR(ROUND(AN15 + AS15, 2), AS15) | AV15: ==IFERROR(ROUND(AO15 + AT15, 2), AT15) | AY15: Zinsertraege | AZ15: ==ROUND(SUMIF($AY$156:$AY$160,"Zinsertraege",$BA$156:$BA$160)+SUMIF($AY$165:$AY$170,"Zinsertraege",$BA$165:$BA$170),2) | BA15: ==ROUND(SUMIF($AY$156:$AY$160,"Zinsertraege",$BB$156:$BB$160)+SUMIF($AY$165:$AY$170,"Zinsertraege",$BB$165:$BB$170),2) | BB15: ==IFERROR(ROUND(AU15 + AZ15, 2), AZ15) | BC15: ==IFERROR(ROUND(AV15 + BA15, 2), BA15) | BF15: Zinsertraege | BG15: ==ROUND(SUMIF($BF$156:$BF$160,"Zinsertraege",$BH$156:$BH$160)+SUMIF($BF$165:$BF$170,"Zinsertraege",$BH$165:$BH$170),2) | BH15: ==ROUND(SUMIF($BF$156:$BF$160,"Zinsertraege",$BI$156:$BI$160)+SUMIF($BF$165:$BF$170,"Zinsertraege",$BI$165:$BI$170),2) | BI15: ==IFERROR(ROUND(BB15 + BG15, 2), BG15) | BJ15: ==IFERROR(ROUND(BC15 + BH15, 2), BH15) | BM15: Zinsertraege | BN15: ==ROUND(SUMIF($BM$156:$BM$160,"Zinsertraege",$BO$156:$BO$160)+SUMIF($BM$165:$BM$170,"Zinsertraege",$BO$165:$BO$170),2) | BO15: ==ROUND(SUMIF($BM$156:$BM$160,"Zinsertraege",$BP$156:$BP$160)+SUMIF($BM$165:$BM$170,"Zinsertraege",$BP$165:$BP$170),2) | BP15: ==IFERROR(ROUND(BI15 + BN15, 2), BN15) | BQ15: ==IFERROR(ROUND(BJ15 + BO15, 2), BO15) | BT15: Zinsertraege | BU15: ==ROUND(SUMIF($BT$156:$BT$160,"Zinsertraege",$BV$156:$BV$160)+SUMIF($BT$165:$BT$170,"Zinsertraege",$BV$165:$BV$170),2) | BV15: ==ROUND(SUMIF($BT$156:$BT$160,"Zinsertraege",$BW$156:$BW$160)+SUMIF($BT$165:$BT$170,"Zinsertraege",$BW$165:$BW$170),2) | BW15: ==IFERROR(ROUND(BP15 + BU15, 2), BU15) | BX15: ==IFERROR(ROUND(BQ15 + BV15, 2), BV15) | CA15: Zinsertraege | CB15: ==ROUND(SUMIF($CA$156:$CA$160,"Zinsertraege",$CC$156:$CC$160)+SUMIF($CA$165:$CA$170,"Zinsertraege",$CC$165:$CC$170),2) | CC15: ==ROUND(SUMIF($CA$156:$CA$160,"Zinsertraege",$CD$156:$CD$160)+SUMIF($CA$165:$CA$170,"Zinsertraege",$CD$165:$CD$170),2) | CD15: ==IFERROR(ROUND(BW15 + CB15, 2), CB15) | CE15: ==IFERROR(ROUND(BX15 + CC15, 2), CC15) | CH15: Zinsertraege | CI15: ==ROUND(SUMIF($CH$156:$CH$160,"Zinsertraege",$CJ$156:$CJ$160)+SUMIF($CH$165:$CH$170,"Zinsertraege",$CJ$165:$CJ$170),2) | CJ15: ==ROUND(SUMIF($CH$156:$CH$160,"Zinsertraege",$CK$156:$CK$160)+SUMIF($CH$165:$CH$170,"Zinsertraege",$CK$165:$CK$170),2) | CK15: ==IFERROR(ROUND(CD15 + CI15, 2), CI15) | CL15: ==IFERROR(ROUND(CE15 + CJ15, 2), CJ15) | CO15: Zinsertraege | CP15: ==ROUND(SUMIF($CO$156:$CO$160,"Zinsertraege",$CQ$156:$CQ$160)+SUMIF($CO$165:$CO$170,"Zinsertraege",$CQ$165:$CQ$170),2) | CQ15: ==ROUND(SUMIF($CO$156:$CO$160,"Zinsertraege",$CR$156:$CR$160)+SUMIF($CO$165:$CO$170,"Zinsertraege",$CR$165:$CR$170),2) | CR15: ==IFERROR(ROUND(CK15 + CP15, 2), CP15) | CS15: ==IFERROR(ROUND(CL15 + CQ15, 2), CQ15) | CV15: Zinsertraege | CW15: ==ROUND(SUMIF($CV$156:$CV$160,"Zinsertraege",$CX$156:$CX$160)+SUMIF($CV$165:$CV$170,"Zinsertraege",$CX$165:$CX$170),2) | CX15: ==ROUND(SUMIF($CV$156:$CV$160,"Zinsertraege",$CY$156:$CY$160)+SUMIF($CV$165:$CV$170,"Zinsertraege",$CY$165:$CY$170),2) | CY15: ==IFERROR(ROUND(CR15 + CW15, 2), CW15) | CZ15: ==IFERROR(ROUND(CS15 + CX15, 2), CX15) | DC15: Zinsertraege | DD15: ==ROUND(SUMIF($DC$156:$DC$160,"Zinsertraege",$DE$156:$DE$160)+SUMIF($DC$165:$DC$170,"Zinsertraege",$DE$165:$DE$170),2) | DE15: ==ROUND(SUMIF($DC$156:$DC$160,"Zinsertraege",$DF$156:$DF$160)+SUMIF($DC$165:$DC$170,"Zinsertraege",$DF$165:$DF$170),2) | DF15: ==IFERROR(ROUND(CY15 + DD15, 2), DD15) | DG15: ==IFERROR(ROUND(CZ15 + DE15, 2), DE15) | DJ15: Zinsertraege | DK15: ==ROUND(SUMIF($DJ$156:$DJ$160,"Zinsertraege",$DL$156:$DL$160)+SUMIF($DJ$165:$DJ$170,"Zinsertraege",$DL$165:$DL$170),2) | DL15: ==ROUND(SUMIF($DJ$156:$DJ$160,"Zinsertraege",$DM$156:$DM$160)+SUMIF($DJ$165:$DJ$170,"Zinsertraege",$DM$165:$DM$170),2) | DM15: ==IFERROR(ROUND(DF15 + DK15, 2), DK15) | DN15: ==IFERROR(ROUND(DG15 + DL15, 2), DL15) | DQ15: Zinsertraege | DR15: ==ROUND(SUMIF($DQ$156:$DQ$160,"Zinsertraege",$DS$156:$DS$160)+SUMIF($DQ$165:$DQ$170,"Zinsertraege",$DS$165:$DS$170),2) | DS15: ==ROUND(SUMIF($DQ$156:$DQ$160,"Zinsertraege",$DT$156:$DT$160)+SUMIF($DQ$165:$DQ$170,"Zinsertraege",$DT$165:$DT$170),2) | DT15: ==IFERROR(ROUND(DM15 + DR15, 2), DR15) | DU15: ==IFERROR(ROUND(DN15 + DS15, 2), DS15)
B16: Gesamteinnahmen | C16: ==ROUND(SUM(C11:C15),2) | D16: ==ROUND(SUM(D11:D15),2) | E16: ==ROUND(SUM(E11:E15),2) | F16: ==ROUND(SUM(F11:F15),2) | I16: Gesamteinnahmen | J16: ==ROUND(SUM(J11:J15),2) | K16: ==ROUND(SUM(K11:K15),2) | L16: ==ROUND(SUM(L11:L15),2) | M16: ==ROUND(SUM(M11:M15),2) | P16: Gesamteinnahmen | Q16: ==ROUND(SUM(Q11:Q15),2) | R16: ==ROUND(SUM(R11:R15),2) | S16: ==ROUND(SUM(S11:S15),2) | T16: ==ROUND(SUM(T11:T15),2) | W16: Gesamteinnahmen | X16: ==ROUND(SUM(X11:X15),2) | Y16: ==ROUND(SUM(Y11:Y15),2) | Z16: ==ROUND(SUM(Z11:Z15),2) | AA16: ==ROUND(SUM(AA11:AA15),2) | AD16: Gesamteinnahmen | AE16: ==ROUND(SUM(AE11:AE15),2) | AF16: ==ROUND(SUM(AF11:AF15),2) | AG16: ==ROUND(SUM(AG11:AG15),2) | AH16: ==ROUND(SUM(AH11:AH15),2) | AK16: Gesamteinnahmen | AL16: ==ROUND(SUM(AL11:AL15),2) | AM16: ==ROUND(SUM(AM11:AM15),2) | AN16: ==ROUND(SUM(AN11:AN15),2) | AO16: ==ROUND(SUM(AO11:AO15),2) | AR16: Gesamteinnahmen | AS16: ==ROUND(SUM(AS11:AS15),2) | AT16: ==ROUND(SUM(AT11:AT15),2) | AU16: ==ROUND(SUM(AU11:AU15),2) | AV16: ==ROUND(SUM(AV11:AV15),2) | AY16: Gesamteinnahmen | AZ16: ==ROUND(SUM(AZ11:AZ15),2) | BA16: ==ROUND(SUM(BA11:BA15),2) | BB16: ==ROUND(SUM(BB11:BB15),2) | BC16: ==ROUND(SUM(BC11:BC15),2) | BF16: Gesamteinnahmen | BG16: ==ROUND(SUM(BG11:BG15),2) | BH16: ==ROUND(SUM(BH11:BH15),2) | BI16: ==ROUND(SUM(BI11:BI15),2) | BJ16: ==ROUND(SUM(BJ11:BJ15),2) | BM16: Gesamteinnahmen | BN16: ==ROUND(SUM(BN11:BN15),2) | BO16: ==ROUND(SUM(BO11:BO15),2) | BP16: ==ROUND(SUM(BP11:BP15),2) | BQ16: ==ROUND(SUM(BQ11:BQ15),2) | BT16: Gesamteinnahmen | BU16: ==ROUND(SUM(BU11:BU15),2) | BV16: ==ROUND(SUM(BV11:BV15),2) | BW16: ==ROUND(SUM(BW11:BW15),2) | BX16: ==ROUND(SUM(BX11:BX15),2) | CA16: Gesamteinnahmen | CB16: ==ROUND(SUM(CB11:CB15),2) | CC16: ==ROUND(SUM(CC11:CC15),2) | CD16: ==ROUND(SUM(CD11:CD15),2) | CE16: ==ROUND(SUM(CE11:CE15),2) | CH16: Gesamteinnahmen | CI16: ==ROUND(SUM(CI11:CI15),2) | CJ16: ==ROUND(SUM(CJ11:CJ15),2) | CK16: ==ROUND(SUM(CK11:CK15),2) | CL16: ==ROUND(SUM(CL11:CL15),2) | CO16: Gesamteinnahmen | CP16: ==ROUND(SUM(CP11:CP15),2) | CQ16: ==ROUND(SUM(CQ11:CQ15),2) | CR16: ==ROUND(SUM(CR11:CR15),2) | CS16: ==ROUND(SUM(CS11:CS15),2) | CV16: Gesamteinnahmen | CW16: ==ROUND(SUM(CW11:CW15),2) | CX16: ==ROUND(SUM(CX11:CX15),2) | CY16: ==ROUND(SUM(CY11:CY15),2) | CZ16: ==ROUND(SUM(CZ11:CZ15),2) | DC16: Gesamteinnahmen | DD16: ==ROUND(SUM(DD11:DD15),2) | DE16: ==ROUND(SUM(DE11:DE15),2) | DF16: ==ROUND(SUM(DF11:DF15),2) | DG16: ==ROUND(SUM(DG11:DG15),2) | DJ16: Gesamteinnahmen | DK16: ==ROUND(SUM(DK11:DK15),2) | DL16: ==ROUND(SUM(DL11:DL15),2) | DM16: ==ROUND(SUM(DM11:DM15),2) | DN16: ==ROUND(SUM(DN11:DN15),2) | DQ16: Gesamteinnahmen | DR16: ==ROUND(SUM(DR11:DR15),2) | DS16: ==ROUND(SUM(DS11:DS15),2) | DT16: ==ROUND(SUM(DT11:DT15),2) | DU16: ==ROUND(SUM(DU11:DU15),2)
B17: Ausgaben | I17: Ausgaben | P17: Ausgaben | W17: Ausgaben | AD17: Ausgaben | AK17: Ausgaben | AR17: Ausgaben | AY17: Ausgaben | BF17: Ausgaben | BM17: Ausgaben | BT17: Ausgaben | CA17: Ausgaben | CH17: Ausgaben | CO17: Ausgaben | CV17: Ausgaben | DC17: Ausgaben | DJ17: Ausgaben | DQ17: Ausgaben
B18: ID | C18: Ausgaben (LC) | D18: Ausgaben (EUR) | E18: Kum. Ausgaben (LC) | F18: Kum. Ausgaben (EUR) | I18: ID | J18: Ausgaben (LC) | K18: Ausgaben (EUR) | L18: Kum. Ausgaben (LC) | M18: Kum. Ausgaben (EUR) | P18: ID | Q18: Ausgaben (LC) | R18: Ausgaben (EUR) | S18: Kum. Ausgaben (LC) | T18: Kum. Ausgaben (EUR) | W18: ID | X18: Ausgaben (LC) | Y18: Ausgaben (EUR) | Z18: Kum. Ausgaben (LC) | AA18: Kum. Ausgaben (EUR) | AD18: ID | AE18: Ausgaben (LC) | AF18: Ausgaben (EUR) | AG18: Kum. Ausgaben (LC) | AH18: Kum. Ausgaben (EUR) | AK18: ID | AL18: Ausgaben (LC) | AM18: Ausgaben (EUR) | AN18: Kum. Ausgaben (LC) | AO18: Kum. Ausgaben (EUR) | AR18: ID | AS18: Ausgaben (LC) | AT18: Ausgaben (EUR) | AU18: Kum. Ausgaben (LC) | AV18: Kum. Ausgaben (EUR) | AY18: ID | AZ18: Ausgaben (LC) | BA18: Ausgaben (EUR) | BB18: Kum. Ausgaben (LC) | BC18: Kum. Ausgaben (EUR) | BF18: ID | BG18: Ausgaben (LC) | BH18: Ausgaben (EUR) | BI18: Kum. Ausgaben (LC) | BJ18: Kum. Ausgaben (EUR) | BM18: ID | BN18: Ausgaben (LC) | BO18: Ausgaben (EUR) | BP18: Kum. Ausgaben (LC) | BQ18: Kum. Ausgaben (EUR) | BT18: ID | BU18: Ausgaben (LC) | BV18: Ausgaben (EUR) | BW18: Kum. Ausgaben (LC) | BX18: Kum. Ausgaben (EUR) | CA18: ID | CB18: Ausgaben (LC) | CC18: Ausgaben (EUR) | CD18: Kum. Ausgaben (LC) | CE18: Kum. Ausgaben (EUR) | CH18: ID | CI18: Ausgaben (LC) | CJ18: Ausgaben (EUR) | CK18: Kum. Ausgaben (LC) | CL18: Kum. Ausgaben (EUR) | CO18: ID | CP18: Ausgaben (LC) | CQ18: Ausgaben (EUR) | CR18: Kum. Ausgaben (LC) | CS18: Kum. Ausgaben (EUR) | CV18: ID | CW18: Ausgaben (LC) | CX18: Ausgaben (EUR) | CY18: Kum. Ausgaben (LC) | CZ18: Kum. Ausgaben (EUR) | DC18: ID | DD18: Ausgaben (LC) | DE18: Ausgaben (EUR) | DF18: Kum. Ausgaben (LC) | DG18: Kum. Ausgaben (EUR) | DJ18: ID | DK18: Ausgaben (LC) | DL18: Ausgaben (EUR) | DM18: Kum. Ausgaben (LC) | DN18: Kum. Ausgaben (EUR) | DQ18: ID | DR18: Ausgaben (LC) | DS18: Ausgaben (EUR) | DT18: Kum. Ausgaben (LC) | DU18: Kum. Ausgaben (EUR)
B19: 1.1 | D19: ==IFERROR(ROUND(C19/FB_Kurs_1,2),0) | E19: ==ROUND(C19,2) | F19: ==ROUND(D19,2) | I19: 1.1 | K19: ==IFERROR(ROUND(J19/FB_Kurs_2,2),0) | L19: ==ROUND(J19+E19,2) | M19: ==ROUND(K19+F19,2) | P19: 1.1 | R19: ==IFERROR(ROUND(Q19/FB_Kurs_3,2),0) | S19: ==ROUND(Q19+L19,2) | T19: ==ROUND(R19+M19,2) | W19: 1.1 | Y19: ==IFERROR(ROUND(X19/FB_Kurs_4,2),0) | Z19: ==ROUND(X19+S19,2) | AA19: ==ROUND(Y19+T19,2) | AD19: 1.1 | AF19: ==IFERROR(ROUND(AE19/FB_Kurs_5,2),0) | AG19: ==ROUND(AE19+Z19,2) | AH19: ==ROUND(AF19+AA19,2) | AK19: 1.1 | AM19: ==IFERROR(ROUND(AL19/FB_Kurs_6,2),0) | AN19: ==ROUND(AL19+AG19,2) | AO19: ==ROUND(AM19+AH19,2) | AR19: 1.1 | AT19: ==IFERROR(ROUND(AS19/FB_Kurs_7,2),0) | AU19: ==ROUND(AS19+AN19,2) | AV19: ==ROUND(AT19+AO19,2) | AY19: 1.1 | BA19: ==IFERROR(ROUND(AZ19/FB_Kurs_8,2),0) | BB19: ==ROUND(AZ19+AU19,2) | BC19: ==ROUND(BA19+AV19,2) | BF19: 1.1 | BH19: ==IFERROR(ROUND(BG19/FB_Kurs_9,2),0) | BI19: ==ROUND(BG19+BB19,2) | BJ19: ==ROUND(BH19+BC19,2) | BM19: 1.1 | BO19: ==IFERROR(ROUND(BN19/FB_Kurs_10,2),0) | BP19: ==ROUND(BN19+BI19,2) | BQ19: ==ROUND(BO19+BJ19,2) | BT19: 1.1 | BV19: ==IFERROR(ROUND(BU19/FB_Kurs_11,2),0) | BW19: ==ROUND(BU19+BP19,2) | BX19: ==ROUND(BV19+BQ19,2) | CA19: 1.1 | CC19: ==IFERROR(ROUND(CB19/FB_Kurs_12,2),0) | CD19: ==ROUND(CB19+BW19,2) | CE19: ==ROUND(CC19+BX19,2) | CH19: 1.1 | CJ19: ==IFERROR(ROUND(CI19/FB_Kurs_13,2),0) | CK19: ==ROUND(CI19+CD19,2) | CL19: ==ROUND(CJ19+CE19,2) | CO19: 1.1 | CQ19: ==IFERROR(ROUND(CP19/FB_Kurs_14,2),0) | CR19: ==ROUND(CP19+CK19,2) | CS19: ==ROUND(CQ19+CL19,2) | CV19: 1.1 | CX19: ==IFERROR(ROUND(CW19/FB_Kurs_15,2),0) | CY19: ==ROUND(CW19+CR19,2) | CZ19: ==ROUND(CX19+CS19,2) | DC19: 1.1 | DE19: ==IFERROR(ROUND(DD19/FB_Kurs_16,2),0) | DF19: ==ROUND(DD19+CY19,2) | DG19: ==ROUND(DE19+CZ19,2) | DJ19: 1.1 | DL19: ==IFERROR(ROUND(DK19/FB_Kurs_17,2),0) | DM19: ==ROUND(DK19+DF19,2) | DN19: ==ROUND(DL19+DG19,2) | DQ19: 1.1 | DS19: ==IFERROR(ROUND(DR19/FB_Kurs_18,2),0) | DT19: ==ROUND(DR19+DM19,2) | DU19: ==ROUND(DS19+DN19,2)
B20: 1.2 | D20: ==IFERROR(ROUND(C20/FB_Kurs_1,2),0) | E20: ==ROUND(C20,2) | F20: ==ROUND(D20,2) | I20: 1.2 | K20: ==IFERROR(ROUND(J20/FB_Kurs_2,2),0) | L20: ==ROUND(J20+E20,2) | M20: ==ROUND(K20+F20,2) | P20: 1.2 | R20: ==IFERROR(ROUND(Q20/FB_Kurs_3,2),0) | S20: ==ROUND(Q20+L20,2) | T20: ==ROUND(R20+M20,2) | W20: 1.2 | Y20: ==IFERROR(ROUND(X20/FB_Kurs_4,2),0) | Z20: ==ROUND(X20+S20,2) | AA20: ==ROUND(Y20+T20,2) | AD20: 1.2 | AF20: ==IFERROR(ROUND(AE20/FB_Kurs_5,2),0) | AG20: ==ROUND(AE20+Z20,2) | AH20: ==ROUND(AF20+AA20,2) | AK20: 1.2 | AM20: ==IFERROR(ROUND(AL20/FB_Kurs_6,2),0) | AN20: ==ROUND(AL20+AG20,2) | AO20: ==ROUND(AM20+AH20,2) | AR20: 1.2 | AT20: ==IFERROR(ROUND(AS20/FB_Kurs_7,2),0) | AU20: ==ROUND(AS20+AN20,2) | AV20: ==ROUND(AT20+AO20,2) | AY20: 1.2 | BA20: ==IFERROR(ROUND(AZ20/FB_Kurs_8,2),0) | BB20: ==ROUND(AZ20+AU20,2) | BC20: ==ROUND(BA20+AV20,2) | BF20: 1.2 | BH20: ==IFERROR(ROUND(BG20/FB_Kurs_9,2),0) | BI20: ==ROUND(BG20+BB20,2) | BJ20: ==ROUND(BH20+BC20,2) | BM20: 1.2 | BO20: ==IFERROR(ROUND(BN20/FB_Kurs_10,2),0) | BP20: ==ROUND(BN20+BI20,2) | BQ20: ==ROUND(BO20+BJ20,2) | BT20: 1.2 | BV20: ==IFERROR(ROUND(BU20/FB_Kurs_11,2),0) | BW20: ==ROUND(BU20+BP20,2) | BX20: ==ROUND(BV20+BQ20,2) | CA20: 1.2 | CC20: ==IFERROR(ROUND(CB20/FB_Kurs_12,2),0) | CD20: ==ROUND(CB20+BW20,2) | CE20: ==ROUND(CC20+BX20,2) | CH20: 1.2 | CJ20: ==IFERROR(ROUND(CI20/FB_Kurs_13,2),0) | CK20: ==ROUND(CI20+CD20,2) | CL20: ==ROUND(CJ20+CE20,2) | CO20: 1.2 | CQ20: ==IFERROR(ROUND(CP20/FB_Kurs_14,2),0) | CR20: ==ROUND(CP20+CK20,2) | CS20: ==ROUND(CQ20+CL20,2) | CV20: 1.2 | CX20: ==IFERROR(ROUND(CW20/FB_Kurs_15,2),0) | CY20: ==ROUND(CW20+CR20,2) | CZ20: ==ROUND(CX20+CS20,2) | DC20: 1.2 | DE20: ==IFERROR(ROUND(DD20/FB_Kurs_16,2),0) | DF20: ==ROUND(DD20+CY20,2) | DG20: ==ROUND(DE20+CZ20,2) | DJ20: 1.2 | DL20: ==IFERROR(ROUND(DK20/FB_Kurs_17,2),0) | DM20: ==ROUND(DK20+DF20,2) | DN20: ==ROUND(DL20+DG20,2) | DQ20: 1.2 | DS20: ==IFERROR(ROUND(DR20/FB_Kurs_18,2),0) | DT20: ==ROUND(DR20+DM20,2) | DU20: ==ROUND(DS20+DN20,2)
B21: 1.3 | D21: ==IFERROR(ROUND(C21/FB_Kurs_1,2),0) | E21: ==ROUND(C21,2) | F21: ==ROUND(D21,2) | I21: 1.3 | K21: ==IFERROR(ROUND(J21/FB_Kurs_2,2),0) | L21: ==ROUND(J21+E21,2) | M21: ==ROUND(K21+F21,2) | P21: 1.3 | R21: ==IFERROR(ROUND(Q21/FB_Kurs_3,2),0) | S21: ==ROUND(Q21+L21,2) | T21: ==ROUND(R21+M21,2) | W21: 1.3 | Y21: ==IFERROR(ROUND(X21/FB_Kurs_4,2),0) | Z21: ==ROUND(X21+S21,2) | AA21: ==ROUND(Y21+T21,2) | AD21: 1.3 | AF21: ==IFERROR(ROUND(AE21/FB_Kurs_5,2),0) | AG21: ==ROUND(AE21+Z21,2) | AH21: ==ROUND(AF21+AA21,2) | AK21: 1.3 | AM21: ==IFERROR(ROUND(AL21/FB_Kurs_6,2),0) | AN21: ==ROUND(AL21+AG21,2) | AO21: ==ROUND(AM21+AH21,2) | AR21: 1.3 | AT21: ==IFERROR(ROUND(AS21/FB_Kurs_7,2),0) | AU21: ==ROUND(AS21+AN21,2) | AV21: ==ROUND(AT21+AO21,2) | AY21: 1.3 | BA21: ==IFERROR(ROUND(AZ21/FB_Kurs_8,2),0) | BB21: ==ROUND(AZ21+AU21,2) | BC21: ==ROUND(BA21+AV21,2) | BF21: 1.3 | BH21: ==IFERROR(ROUND(BG21/FB_Kurs_9,2),0) | BI21: ==ROUND(BG21+BB21,2) | BJ21: ==ROUND(BH21+BC21,2) | BM21: 1.3 | BO21: ==IFERROR(ROUND(BN21/FB_Kurs_10,2),0) | BP21: ==ROUND(BN21+BI21,2) | BQ21: ==ROUND(BO21+BJ21,2) | BT21: 1.3 | BV21: ==IFERROR(ROUND(BU21/FB_Kurs_11,2),0) | BW21: ==ROUND(BU21+BP21,2) | BX21: ==ROUND(BV21+BQ21,2) | CA21: 1.3 | CC21: ==IFERROR(ROUND(CB21/FB_Kurs_12,2),0) | CD21: ==ROUND(CB21+BW21,2) | CE21: ==ROUND(CC21+BX21,2) | CH21: 1.3 | CJ21: ==IFERROR(ROUND(CI21/FB_Kurs_13,2),0) | CK21: ==ROUND(CI21+CD21,2) | CL21: ==ROUND(CJ21+CE21,2) | CO21: 1.3 | CQ21: ==IFERROR(ROUND(CP21/FB_Kurs_14,2),0) | CR21: ==ROUND(CP21+CK21,2) | CS21: ==ROUND(CQ21+CL21,2) | CV21: 1.3 | CX21: ==IFERROR(ROUND(CW21/FB_Kurs_15,2),0) | CY21: ==ROUND(CW21+CR21,2) | CZ21: ==ROUND(CX21+CS21,2) | DC21: 1.3 | DE21: ==IFERROR(ROUND(DD21/FB_Kurs_16,2),0) | DF21: ==ROUND(DD21+CY21,2) | DG21: ==ROUND(DE21+CZ21,2) | DJ21: 1.3 | DL21: ==IFERROR(ROUND(DK21/FB_Kurs_17,2),0) | DM21: ==ROUND(DK21+DF21,2) | DN21: ==ROUND(DL21+DG21,2) | DQ21: 1.3 | DS21: ==IFERROR(ROUND(DR21/FB_Kurs_18,2),0) | DT21: ==ROUND(DR21+DM21,2) | DU21: ==ROUND(DS21+DN21,2)
B22: 1.4 | D22: ==IFERROR(ROUND(C22/FB_Kurs_1,2),0) | E22: ==ROUND(C22,2) | F22: ==ROUND(D22,2) | I22: 1.4 | K22: ==IFERROR(ROUND(J22/FB_Kurs_2,2),0) | L22: ==ROUND(J22+E22,2) | M22: ==ROUND(K22+F22,2) | P22: 1.4 | R22: ==IFERROR(ROUND(Q22/FB_Kurs_3,2),0) | S22: ==ROUND(Q22+L22,2) | T22: ==ROUND(R22+M22,2) | W22: 1.4 | Y22: ==IFERROR(ROUND(X22/FB_Kurs_4,2),0) | Z22: ==ROUND(X22+S22,2) | AA22: ==ROUND(Y22+T22,2) | AD22: 1.4 | AF22: ==IFERROR(ROUND(AE22/FB_Kurs_5,2),0) | AG22: ==ROUND(AE22+Z22,2) | AH22: ==ROUND(AF22+AA22,2) | AK22: 1.4 | AM22: ==IFERROR(ROUND(AL22/FB_Kurs_6,2),0) | AN22: ==ROUND(AL22+AG22,2) | AO22: ==ROUND(AM22+AH22,2) | AR22: 1.4 | AT22: ==IFERROR(ROUND(AS22/FB_Kurs_7,2),0) | AU22: ==ROUND(AS22+AN22,2) | AV22: ==ROUND(AT22+AO22,2) | AY22: 1.4 | BA22: ==IFERROR(ROUND(AZ22/FB_Kurs_8,2),0) | BB22: ==ROUND(AZ22+AU22,2) | BC22: ==ROUND(BA22+AV22,2) | BF22: 1.4 | BH22: ==IFERROR(ROUND(BG22/FB_Kurs_9,2),0) | BI22: ==ROUND(BG22+BB22,2) | BJ22: ==ROUND(BH22+BC22,2) | BM22: 1.4 | BO22: ==IFERROR(ROUND(BN22/FB_Kurs_10,2),0) | BP22: ==ROUND(BN22+BI22,2) | BQ22: ==ROUND(BO22+BJ22,2) | BT22: 1.4 | BV22: ==IFERROR(ROUND(BU22/FB_Kurs_11,2),0) | BW22: ==ROUND(BU22+BP22,2) | BX22: ==ROUND(BV22+BQ22,2) | CA22: 1.4 | CC22: ==IFERROR(ROUND(CB22/FB_Kurs_12,2),0) | CD22: ==ROUND(CB22+BW22,2) | CE22: ==ROUND(CC22+BX22,2) | CH22: 1.4 | CJ22: ==IFERROR(ROUND(CI22/FB_Kurs_13,2),0) | CK22: ==ROUND(CI22+CD22,2) | CL22: ==ROUND(CJ22+CE22,2) | CO22: 1.4 | CQ22: ==IFERROR(ROUND(CP22/FB_Kurs_14,2),0) | CR22: ==ROUND(CP22+CK22,2) | CS22: ==ROUND(CQ22+CL22,2) | CV22: 1.4 | CX22: ==IFERROR(ROUND(CW22/FB_Kurs_15,2),0) | CY22: ==ROUND(CW22+CR22,2) | CZ22: ==ROUND(CX22+CS22,2) | DC22: 1.4 | DE22: ==IFERROR(ROUND(DD22/FB_Kurs_16,2),0) | DF22: ==ROUND(DD22+CY22,2) | DG22: ==ROUND(DE22+CZ22,2) | DJ22: 1.4 | DL22: ==IFERROR(ROUND(DK22/FB_Kurs_17,2),0) | DM22: ==ROUND(DK22+DF22,2) | DN22: ==ROUND(DL22+DG22,2) | DQ22: 1.4 | DS22: ==IFERROR(ROUND(DR22/FB_Kurs_18,2),0) | DT22: ==ROUND(DR22+DM22,2) | DU22: ==ROUND(DS22+DN22,2)
B23: 1.5 | D23: ==IFERROR(ROUND(C23/FB_Kurs_1,2),0) | E23: ==ROUND(C23,2) | F23: ==ROUND(D23,2) | I23: 1.5 | K23: ==IFERROR(ROUND(J23/FB_Kurs_2,2),0) | L23: ==ROUND(J23+E23,2) | M23: ==ROUND(K23+F23,2) | P23: 1.5 | R23: ==IFERROR(ROUND(Q23/FB_Kurs_3,2),0) | S23: ==ROUND(Q23+L23,2) | T23: ==ROUND(R23+M23,2) | W23: 1.5 | Y23: ==IFERROR(ROUND(X23/FB_Kurs_4,2),0) | Z23: ==ROUND(X23+S23,2) | AA23: ==ROUND(Y23+T23,2) | AD23: 1.5 | AF23: ==IFERROR(ROUND(AE23/FB_Kurs_5,2),0) | AG23: ==ROUND(AE23+Z23,2) | AH23: ==ROUND(AF23+AA23,2) | AK23: 1.5 | AM23: ==IFERROR(ROUND(AL23/FB_Kurs_6,2),0) | AN23: ==ROUND(AL23+AG23,2) | AO23: ==ROUND(AM23+AH23,2) | AR23: 1.5 | AT23: ==IFERROR(ROUND(AS23/FB_Kurs_7,2),0) | AU23: ==ROUND(AS23+AN23,2) | AV23: ==ROUND(AT23+AO23,2) | AY23: 1.5 | BA23: ==IFERROR(ROUND(AZ23/FB_Kurs_8,2),0) | BB23: ==ROUND(AZ23+AU23,2) | BC23: ==ROUND(BA23+AV23,2) | BF23: 1.5 | BH23: ==IFERROR(ROUND(BG23/FB_Kurs_9,2),0) | BI23: ==ROUND(BG23+BB23,2) | BJ23: ==ROUND(BH23+BC23,2) | BM23: 1.5 | BO23: ==IFERROR(ROUND(BN23/FB_Kurs_10,2),0) | BP23: ==ROUND(BN23+BI23,2) | BQ23: ==ROUND(BO23+BJ23,2) | BT23: 1.5 | BV23: ==IFERROR(ROUND(BU23/FB_Kurs_11,2),0) | BW23: ==ROUND(BU23+BP23,2) | BX23: ==ROUND(BV23+BQ23,2) | CA23: 1.5 | CC23: ==IFERROR(ROUND(CB23/FB_Kurs_12,2),0) | CD23: ==ROUND(CB23+BW23,2) | CE23: ==ROUND(CC23+BX23,2) | CH23: 1.5 | CJ23: ==IFERROR(ROUND(CI23/FB_Kurs_13,2),0) | CK23: ==ROUND(CI23+CD23,2) | CL23: ==ROUND(CJ23+CE23,2) | CO23: 1.5 | CQ23: ==IFERROR(ROUND(CP23/FB_Kurs_14,2),0) | CR23: ==ROUND(CP23+CK23,2) | CS23: ==ROUND(CQ23+CL23,2) | CV23: 1.5 | CX23: ==IFERROR(ROUND(CW23/FB_Kurs_15,2),0) | CY23: ==ROUND(CW23+CR23,2) | CZ23: ==ROUND(CX23+CS23,2) | DC23: 1.5 | DE23: ==IFERROR(ROUND(DD23/FB_Kurs_16,2),0) | DF23: ==ROUND(DD23+CY23,2) | DG23: ==ROUND(DE23+CZ23,2) | DJ23: 1.5 | DL23: ==IFERROR(ROUND(DK23/FB_Kurs_17,2),0) | DM23: ==ROUND(DK23+DF23,2) | DN23: ==ROUND(DL23+DG23,2) | DQ23: 1.5 | DS23: ==IFERROR(ROUND(DR23/FB_Kurs_18,2),0) | DT23: ==ROUND(DR23+DM23,2) | DU23: ==ROUND(DS23+DN23,2)
B24: 1.6 | D24: ==IFERROR(ROUND(C24/FB_Kurs_1,2),0) | E24: ==ROUND(C24,2) | F24: ==ROUND(D24,2) | I24: 1.6 | K24: ==IFERROR(ROUND(J24/FB_Kurs_2,2),0) | L24: ==ROUND(J24+E24,2) | M24: ==ROUND(K24+F24,2) | P24: 1.6 | R24: ==IFERROR(ROUND(Q24/FB_Kurs_3,2),0) | S24: ==ROUND(Q24+L24,2) | T24: ==ROUND(R24+M24,2) | W24: 1.6 | Y24: ==IFERROR(ROUND(X24/FB_Kurs_4,2),0) | Z24: ==ROUND(X24+S24,2) | AA24: ==ROUND(Y24+T24,2) | AD24: 1.6 | AF24: ==IFERROR(ROUND(AE24/FB_Kurs_5,2),0) | AG24: ==ROUND(AE24+Z24,2) | AH24: ==ROUND(AF24+AA24,2) | AK24: 1.6 | AM24: ==IFERROR(ROUND(AL24/FB_Kurs_6,2),0) | AN24: ==ROUND(AL24+AG24,2) | AO24: ==ROUND(AM24+AH24,2) | AR24: 1.6 | AT24: ==IFERROR(ROUND(AS24/FB_Kurs_7,2),0) | AU24: ==ROUND(AS24+AN24,2) | AV24: ==ROUND(AT24+AO24,2) | AY24: 1.6 | BA24: ==IFERROR(ROUND(AZ24/FB_Kurs_8,2),0) | BB24: ==ROUND(AZ24+AU24,2) | BC24: ==ROUND(BA24+AV24,2) | BF24: 1.6 | BH24: ==IFERROR(ROUND(BG24/FB_Kurs_9,2),0) | BI24: ==ROUND(BG24+BB24,2) | BJ24: ==ROUND(BH24+BC24,2) | BM24: 1.6 | BO24: ==IFERROR(ROUND(BN24/FB_Kurs_10,2),0) | BP24: ==ROUND(BN24+BI24,2) | BQ24: ==ROUND(BO24+BJ24,2) | BT24: 1.6 | BV24: ==IFERROR(ROUND(BU24/FB_Kurs_11,2),0) | BW24: ==ROUND(BU24+BP24,2) | BX24: ==ROUND(BV24+BQ24,2) | CA24: 1.6 | CC24: ==IFERROR(ROUND(CB24/FB_Kurs_12,2),0) | CD24: ==ROUND(CB24+BW24,2) | CE24: ==ROUND(CC24+BX24,2) | CH24: 1.6 | CJ24: ==IFERROR(ROUND(CI24/FB_Kurs_13,2),0) | CK24: ==ROUND(CI24+CD24,2) | CL24: ==ROUND(CJ24+CE24,2) | CO24: 1.6 | CQ24: ==IFERROR(ROUND(CP24/FB_Kurs_14,2),0) | CR24: ==ROUND(CP24+CK24,2) | CS24: ==ROUND(CQ24+CL24,2) | CV24: 1.6 | CX24: ==IFERROR(ROUND(CW24/FB_Kurs_15,2),0) | CY24: ==ROUND(CW24+CR24,2) | CZ24: ==ROUND(CX24+CS24,2) | DC24: 1.6 | DE24: ==IFERROR(ROUND(DD24/FB_Kurs_16,2),0) | DF24: ==ROUND(DD24+CY24,2) | DG24: ==ROUND(DE24+CZ24,2) | DJ24: 1.6 | DL24: ==IFERROR(ROUND(DK24/FB_Kurs_17,2),0) | DM24: ==ROUND(DK24+DF24,2) | DN24: ==ROUND(DL24+DG24,2) | DQ24: 1.6 | DS24: ==IFERROR(ROUND(DR24/FB_Kurs_18,2),0) | DT24: ==ROUND(DR24+DM24,2) | DU24: ==ROUND(DS24+DN24,2)
B25: 1.7 | D25: ==IFERROR(ROUND(C25/FB_Kurs_1,2),0) | E25: ==ROUND(C25,2) | F25: ==ROUND(D25,2) | I25: 1.7 | K25: ==IFERROR(ROUND(J25/FB_Kurs_2,2),0) | L25: ==ROUND(J25+E25,2) | M25: ==ROUND(K25+F25,2) | P25: 1.7 | R25: ==IFERROR(ROUND(Q25/FB_Kurs_3,2),0) | S25: ==ROUND(Q25+L25,2) | T25: ==ROUND(R25+M25,2) | W25: 1.7 | Y25: ==IFERROR(ROUND(X25/FB_Kurs_4,2),0) | Z25: ==ROUND(X25+S25,2) | AA25: ==ROUND(Y25+T25,2) | AD25: 1.7 | AF25: ==IFERROR(ROUND(AE25/FB_Kurs_5,2),0) | AG25: ==ROUND(AE25+Z25,2) | AH25: ==ROUND(AF25+AA25,2) | AK25: 1.7 | AM25: ==IFERROR(ROUND(AL25/FB_Kurs_6,2),0) | AN25: ==ROUND(AL25+AG25,2) | AO25: ==ROUND(AM25+AH25,2) | AR25: 1.7 | AT25: ==IFERROR(ROUND(AS25/FB_Kurs_7,2),0) | AU25: ==ROUND(AS25+AN25,2) | AV25: ==ROUND(AT25+AO25,2) | AY25: 1.7 | BA25: ==IFERROR(ROUND(AZ25/FB_Kurs_8,2),0) | BB25: ==ROUND(AZ25+AU25,2) | BC25: ==ROUND(BA25+AV25,2) | BF25: 1.7 | BH25: ==IFERROR(ROUND(BG25/FB_Kurs_9,2),0) | BI25: ==ROUND(BG25+BB25,2) | BJ25: ==ROUND(BH25+BC25,2) | BM25: 1.7 | BO25: ==IFERROR(ROUND(BN25/FB_Kurs_10,2),0) | BP25: ==ROUND(BN25+BI25,2) | BQ25: ==ROUND(BO25+BJ25,2) | BT25: 1.7 | BV25: ==IFERROR(ROUND(BU25/FB_Kurs_11,2),0) | BW25: ==ROUND(BU25+BP25,2) | BX25: ==ROUND(BV25+BQ25,2) | CA25: 1.7 | CC25: ==IFERROR(ROUND(CB25/FB_Kurs_12,2),0) | CD25: ==ROUND(CB25+BW25,2) | CE25: ==ROUND(CC25+BX25,2) | CH25: 1.7 | CJ25: ==IFERROR(ROUND(CI25/FB_Kurs_13,2),0) | CK25: ==ROUND(CI25+CD25,2) | CL25: ==ROUND(CJ25+CE25,2) | CO25: 1.7 | CQ25: ==IFERROR(ROUND(CP25/FB_Kurs_14,2),0) | CR25: ==ROUND(CP25+CK25,2) | CS25: ==ROUND(CQ25+CL25,2) | CV25: 1.7 | CX25: ==IFERROR(ROUND(CW25/FB_Kurs_15,2),0) | CY25: ==ROUND(CW25+CR25,2) | CZ25: ==ROUND(CX25+CS25,2) | DC25: 1.7 | DE25: ==IFERROR(ROUND(DD25/FB_Kurs_16,2),0) | DF25: ==ROUND(DD25+CY25,2) | DG25: ==ROUND(DE25+CZ25,2) | DJ25: 1.7 | DL25: ==IFERROR(ROUND(DK25/FB_Kurs_17,2),0) | DM25: ==ROUND(DK25+DF25,2) | DN25: ==ROUND(DL25+DG25,2) | DQ25: 1.7 | DS25: ==IFERROR(ROUND(DR25/FB_Kurs_18,2),0) | DT25: ==ROUND(DR25+DM25,2) | DU25: ==ROUND(DS25+DN25,2)
B26: 1.8 | D26: ==IFERROR(ROUND(C26/FB_Kurs_1,2),0) | E26: ==ROUND(C26,2) | F26: ==ROUND(D26,2) | I26: 1.8 | K26: ==IFERROR(ROUND(J26/FB_Kurs_2,2),0) | L26: ==ROUND(J26+E26,2) | M26: ==ROUND(K26+F26,2) | P26: 1.8 | R26: ==IFERROR(ROUND(Q26/FB_Kurs_3,2),0) | S26: ==ROUND(Q26+L26,2) | T26: ==ROUND(R26+M26,2) | W26: 1.8 | Y26: ==IFERROR(ROUND(X26/FB_Kurs_4,2),0) | Z26: ==ROUND(X26+S26,2) | AA26: ==ROUND(Y26+T26,2) | AD26: 1.8 | AF26: ==IFERROR(ROUND(AE26/FB_Kurs_5,2),0) | AG26: ==ROUND(AE26+Z26,2) | AH26: ==ROUND(AF26+AA26,2) | AK26: 1.8 | AM26: ==IFERROR(ROUND(AL26/FB_Kurs_6,2),0) | AN26: ==ROUND(AL26+AG26,2) | AO26: ==ROUND(AM26+AH26,2) | AR26: 1.8 | AT26: ==IFERROR(ROUND(AS26/FB_Kurs_7,2),0) | AU26: ==ROUND(AS26+AN26,2) | AV26: ==ROUND(AT26+AO26,2) | AY26: 1.8 | BA26: ==IFERROR(ROUND(AZ26/FB_Kurs_8,2),0) | BB26: ==ROUND(AZ26+AU26,2) | BC26: ==ROUND(BA26+AV26,2) | BF26: 1.8 | BH26: ==IFERROR(ROUND(BG26/FB_Kurs_9,2),0) | BI26: ==ROUND(BG26+BB26,2) | BJ26: ==ROUND(BH26+BC26,2) | BM26: 1.8 | BO26: ==IFERROR(ROUND(BN26/FB_Kurs_10,2),0) | BP26: ==ROUND(BN26+BI26,2) | BQ26: ==ROUND(BO26+BJ26,2) | BT26: 1.8 | BV26: ==IFERROR(ROUND(BU26/FB_Kurs_11,2),0) | BW26: ==ROUND(BU26+BP26,2) | BX26: ==ROUND(BV26+BQ26,2) | CA26: 1.8 | CC26: ==IFERROR(ROUND(CB26/FB_Kurs_12,2),0) | CD26: ==ROUND(CB26+BW26,2) | CE26: ==ROUND(CC26+BX26,2) | CH26: 1.8 | CJ26: ==IFERROR(ROUND(CI26/FB_Kurs_13,2),0) | CK26: ==ROUND(CI26+CD26,2) | CL26: ==ROUND(CJ26+CE26,2) | CO26: 1.8 | CQ26: ==IFERROR(ROUND(CP26/FB_Kurs_14,2),0) | CR26: ==ROUND(CP26+CK26,2) | CS26: ==ROUND(CQ26+CL26,2) | CV26: 1.8 | CX26: ==IFERROR(ROUND(CW26/FB_Kurs_15,2),0) | CY26: ==ROUND(CW26+CR26,2) | CZ26: ==ROUND(CX26+CS26,2) | DC26: 1.8 | DE26: ==IFERROR(ROUND(DD26/FB_Kurs_16,2),0) | DF26: ==ROUND(DD26+CY26,2) | DG26: ==ROUND(DE26+CZ26,2) | DJ26: 1.8 | DL26: ==IFERROR(ROUND(DK26/FB_Kurs_17,2),0) | DM26: ==ROUND(DK26+DF26,2) | DN26: ==ROUND(DL26+DG26,2) | DQ26: 1.8 | DS26: ==IFERROR(ROUND(DR26/FB_Kurs_18,2),0) | DT26: ==ROUND(DR26+DM26,2) | DU26: ==ROUND(DS26+DN26,2)
B27: 1.9 | D27: ==IFERROR(ROUND(C27/FB_Kurs_1,2),0) | E27: ==ROUND(C27,2) | F27: ==ROUND(D27,2) | I27: 1.9 | K27: ==IFERROR(ROUND(J27/FB_Kurs_2,2),0) | L27: ==ROUND(J27+E27,2) | M27: ==ROUND(K27+F27,2) | P27: 1.9 | R27: ==IFERROR(ROUND(Q27/FB_Kurs_3,2),0) | S27: ==ROUND(Q27+L27,2) | T27: ==ROUND(R27+M27,2) | W27: 1.9 | Y27: ==IFERROR(ROUND(X27/FB_Kurs_4,2),0) | Z27: ==ROUND(X27+S27,2) | AA27: ==ROUND(Y27+T27,2) | AD27: 1.9 | AF27: ==IFERROR(ROUND(AE27/FB_Kurs_5,2),0) | AG27: ==ROUND(AE27+Z27,2) | AH27: ==ROUND(AF27+AA27,2) | AK27: 1.9 | AM27: ==IFERROR(ROUND(AL27/FB_Kurs_6,2),0) | AN27: ==ROUND(AL27+AG27,2) | AO27: ==ROUND(AM27+AH27,2) | AR27: 1.9 | AT27: ==IFERROR(ROUND(AS27/FB_Kurs_7,2),0) | AU27: ==ROUND(AS27+AN27,2) | AV27: ==ROUND(AT27+AO27,2) | AY27: 1.9 | BA27: ==IFERROR(ROUND(AZ27/FB_Kurs_8,2),0) | BB27: ==ROUND(AZ27+AU27,2) | BC27: ==ROUND(BA27+AV27,2) | BF27: 1.9 | BH27: ==IFERROR(ROUND(BG27/FB_Kurs_9,2),0) | BI27: ==ROUND(BG27+BB27,2) | BJ27: ==ROUND(BH27+BC27,2) | BM27: 1.9 | BO27: ==IFERROR(ROUND(BN27/FB_Kurs_10,2),0) | BP27: ==ROUND(BN27+BI27,2) | BQ27: ==ROUND(BO27+BJ27,2) | BT27: 1.9 | BV27: ==IFERROR(ROUND(BU27/FB_Kurs_11,2),0) | BW27: ==ROUND(BU27+BP27,2) | BX27: ==ROUND(BV27+BQ27,2) | CA27: 1.9 | CC27: ==IFERROR(ROUND(CB27/FB_Kurs_12,2),0) | CD27: ==ROUND(CB27+BW27,2) | CE27: ==ROUND(CC27+BX27,2) | CH27: 1.9 | CJ27: ==IFERROR(ROUND(CI27/FB_Kurs_13,2),0) | CK27: ==ROUND(CI27+CD27,2) | CL27: ==ROUND(CJ27+CE27,2) | CO27: 1.9 | CQ27: ==IFERROR(ROUND(CP27/FB_Kurs_14,2),0) | CR27: ==ROUND(CP27+CK27,2) | CS27: ==ROUND(CQ27+CL27,2) | CV27: 1.9 | CX27: ==IFERROR(ROUND(CW27/FB_Kurs_15,2),0) | CY27: ==ROUND(CW27+CR27,2) | CZ27: ==ROUND(CX27+CS27,2) | DC27: 1.9 | DE27: ==IFERROR(ROUND(DD27/FB_Kurs_16,2),0) | DF27: ==ROUND(DD27+CY27,2) | DG27: ==ROUND(DE27+CZ27,2) | DJ27: 1.9 | DL27: ==IFERROR(ROUND(DK27/FB_Kurs_17,2),0) | DM27: ==ROUND(DK27+DF27,2) | DN27: ==ROUND(DL27+DG27,2) | DQ27: 1.9 | DS27: ==IFERROR(ROUND(DR27/FB_Kurs_18,2),0) | DT27: ==ROUND(DR27+DM27,2) | DU27: ==ROUND(DS27+DN27,2)
B28: 1.10 | D28: ==IFERROR(ROUND(C28/FB_Kurs_1,2),0) | E28: ==ROUND(C28,2) | F28: ==ROUND(D28,2) | I28: 1.10 | K28: ==IFERROR(ROUND(J28/FB_Kurs_2,2),0) | L28: ==ROUND(J28+E28,2) | M28: ==ROUND(K28+F28,2) | P28: 1.10 | R28: ==IFERROR(ROUND(Q28/FB_Kurs_3,2),0) | S28: ==ROUND(Q28+L28,2) | T28: ==ROUND(R28+M28,2) | W28: 1.10 | Y28: ==IFERROR(ROUND(X28/FB_Kurs_4,2),0) | Z28: ==ROUND(X28+S28,2) | AA28: ==ROUND(Y28+T28,2) | AD28: 1.10 | AF28: ==IFERROR(ROUND(AE28/FB_Kurs_5,2),0) | AG28: ==ROUND(AE28+Z28,2) | AH28: ==ROUND(AF28+AA28,2) | AK28: 1.10 | AM28: ==IFERROR(ROUND(AL28/FB_Kurs_6,2),0) | AN28: ==ROUND(AL28+AG28,2) | AO28: ==ROUND(AM28+AH28,2) | AR28: 1.10 | AT28: ==IFERROR(ROUND(AS28/FB_Kurs_7,2),0) | AU28: ==ROUND(AS28+AN28,2) | AV28: ==ROUND(AT28+AO28,2) | AY28: 1.10 | BA28: ==IFERROR(ROUND(AZ28/FB_Kurs_8,2),0) | BB28: ==ROUND(AZ28+AU28,2) | BC28: ==ROUND(BA28+AV28,2) | BF28: 1.10 | BH28: ==IFERROR(ROUND(BG28/FB_Kurs_9,2),0) | BI28: ==ROUND(BG28+BB28,2) | BJ28: ==ROUND(BH28+BC28,2) | BM28: 1.10 | BO28: ==IFERROR(ROUND(BN28/FB_Kurs_10,2),0) | BP28: ==ROUND(BN28+BI28,2) | BQ28: ==ROUND(BO28+BJ28,2) | BT28: 1.10 | BV28: ==IFERROR(ROUND(BU28/FB_Kurs_11,2),0) | BW28: ==ROUND(BU28+BP28,2) | BX28: ==ROUND(BV28+BQ28,2) | CA28: 1.10 | CC28: ==IFERROR(ROUND(CB28/FB_Kurs_12,2),0) | CD28: ==ROUND(CB28+BW28,2) | CE28: ==ROUND(CC28+BX28,2) | CH28: 1.10 | CJ28: ==IFERROR(ROUND(CI28/FB_Kurs_13,2),0) | CK28: ==ROUND(CI28+CD28,2) | CL28: ==ROUND(CJ28+CE28,2) | CO28: 1.10 | CQ28: ==IFERROR(ROUND(CP28/FB_Kurs_14,2),0) | CR28: ==ROUND(CP28+CK28,2) | CS28: ==ROUND(CQ28+CL28,2) | CV28: 1.10 | CX28: ==IFERROR(ROUND(CW28/FB_Kurs_15,2),0) | CY28: ==ROUND(CW28+CR28,2) | CZ28: ==ROUND(CX28+CS28,2) | DC28: 1.10 | DE28: ==IFERROR(ROUND(DD28/FB_Kurs_16,2),0) | DF28: ==ROUND(DD28+CY28,2) | DG28: ==ROUND(DE28+CZ28,2) | DJ28: 1.10 | DL28: ==IFERROR(ROUND(DK28/FB_Kurs_17,2),0) | DM28: ==ROUND(DK28+DF28,2) | DN28: ==ROUND(DL28+DG28,2) | DQ28: 1.10 | DS28: ==IFERROR(ROUND(DR28/FB_Kurs_18,2),0) | DT28: ==ROUND(DR28+DM28,2) | DU28: ==ROUND(DS28+DN28,2)
B29: 1.11 | D29: ==IFERROR(ROUND(C29/FB_Kurs_1,2),0) | E29: ==ROUND(C29,2) | F29: ==ROUND(D29,2) | I29: 1.11 | K29: ==IFERROR(ROUND(J29/FB_Kurs_2,2),0) | L29: ==ROUND(J29+E29,2) | M29: ==ROUND(K29+F29,2) | P29: 1.11 | R29: ==IFERROR(ROUND(Q29/FB_Kurs_3,2),0) | S29: ==ROUND(Q29+L29,2) | T29: ==ROUND(R29+M29,2) | W29: 1.11 | Y29: ==IFERROR(ROUND(X29/FB_Kurs_4,2),0) | Z29: ==ROUND(X29+S29,2) | AA29: ==ROUND(Y29+T29,2) | AD29: 1.11 | AF29: ==IFERROR(ROUND(AE29/FB_Kurs_5,2),0) | AG29: ==ROUND(AE29+Z29,2) | AH29: ==ROUND(AF29+AA29,2) | AK29: 1.11 | AM29: ==IFERROR(ROUND(AL29/FB_Kurs_6,2),0) | AN29: ==ROUND(AL29+AG29,2) | AO29: ==ROUND(AM29+AH29,2) | AR29: 1.11 | AT29: ==IFERROR(ROUND(AS29/FB_Kurs_7,2),0) | AU29: ==ROUND(AS29+AN29,2) | AV29: ==ROUND(AT29+AO29,2) | AY29: 1.11 | BA29: ==IFERROR(ROUND(AZ29/FB_Kurs_8,2),0) | BB29: ==ROUND(AZ29+AU29,2) | BC29: ==ROUND(BA29+AV29,2) | BF29: 1.11 | BH29: ==IFERROR(ROUND(BG29/FB_Kurs_9,2),0) | BI29: ==ROUND(BG29+BB29,2) | BJ29: ==ROUND(BH29+BC29,2) | BM29: 1.11 | BO29: ==IFERROR(ROUND(BN29/FB_Kurs_10,2),0) | BP29: ==ROUND(BN29+BI29,2) | BQ29: ==ROUND(BO29+BJ29,2) | BT29: 1.11 | BV29: ==IFERROR(ROUND(BU29/FB_Kurs_11,2),0) | BW29: ==ROUND(BU29+BP29,2) | BX29: ==ROUND(BV29+BQ29,2) | CA29: 1.11 | CC29: ==IFERROR(ROUND(CB29/FB_Kurs_12,2),0) | CD29: ==ROUND(CB29+BW29,2) | CE29: ==ROUND(CC29+BX29,2) | CH29: 1.11 | CJ29: ==IFERROR(ROUND(CI29/FB_Kurs_13,2),0) | CK29: ==ROUND(CI29+CD29,2) | CL29: ==ROUND(CJ29+CE29,2) | CO29: 1.11 | CQ29: ==IFERROR(ROUND(CP29/FB_Kurs_14,2),0) | CR29: ==ROUND(CP29+CK29,2) | CS29: ==ROUND(CQ29+CL29,2) | CV29: 1.11 | CX29: ==IFERROR(ROUND(CW29/FB_Kurs_15,2),0) | CY29: ==ROUND(CW29+CR29,2) | CZ29: ==ROUND(CX29+CS29,2) | DC29: 1.11 | DE29: ==IFERROR(ROUND(DD29/FB_Kurs_16,2),0) | DF29: ==ROUND(DD29+CY29,2) | DG29: ==ROUND(DE29+CZ29,2) | DJ29: 1.11 | DL29: ==IFERROR(ROUND(DK29/FB_Kurs_17,2),0) | DM29: ==ROUND(DK29+DF29,2) | DN29: ==ROUND(DL29+DG29,2) | DQ29: 1.11 | DS29: ==IFERROR(ROUND(DR29/FB_Kurs_18,2),0) | DT29: ==ROUND(DR29+DM29,2) | DU29: ==ROUND(DS29+DN29,2)
B30: 1.12 | D30: ==IFERROR(ROUND(C30/FB_Kurs_1,2),0) | E30: ==ROUND(C30,2) | F30: ==ROUND(D30,2) | I30: 1.12 | K30: ==IFERROR(ROUND(J30/FB_Kurs_2,2),0) | L30: ==ROUND(J30+E30,2) | M30: ==ROUND(K30+F30,2) | P30: 1.12 | R30: ==IFERROR(ROUND(Q30/FB_Kurs_3,2),0) | S30: ==ROUND(Q30+L30,2) | T30: ==ROUND(R30+M30,2) | W30: 1.12 | Y30: ==IFERROR(ROUND(X30/FB_Kurs_4,2),0) | Z30: ==ROUND(X30+S30,2) | AA30: ==ROUND(Y30+T30,2) | AD30: 1.12 | AF30: ==IFERROR(ROUND(AE30/FB_Kurs_5,2),0) | AG30: ==ROUND(AE30+Z30,2) | AH30: ==ROUND(AF30+AA30,2) | AK30: 1.12 | AM30: ==IFERROR(ROUND(AL30/FB_Kurs_6,2),0) | AN30: ==ROUND(AL30+AG30,2) | AO30: ==ROUND(AM30+AH30,2) | AR30: 1.12 | AT30: ==IFERROR(ROUND(AS30/FB_Kurs_7,2),0) | AU30: ==ROUND(AS30+AN30,2) | AV30: ==ROUND(AT30+AO30,2) | AY30: 1.12 | BA30: ==IFERROR(ROUND(AZ30/FB_Kurs_8,2),0) | BB30: ==ROUND(AZ30+AU30,2) | BC30: ==ROUND(BA30+AV30,2) | BF30: 1.12 | BH30: ==IFERROR(ROUND(BG30/FB_Kurs_9,2),0) | BI30: ==ROUND(BG30+BB30,2) | BJ30: ==ROUND(BH30+BC30,2) | BM30: 1.12 | BO30: ==IFERROR(ROUND(BN30/FB_Kurs_10,2),0) | BP30: ==ROUND(BN30+BI30,2) | BQ30: ==ROUND(BO30+BJ30,2) | BT30: 1.12 | BV30: ==IFERROR(ROUND(BU30/FB_Kurs_11,2),0) | BW30: ==ROUND(BU30+BP30,2) | BX30: ==ROUND(BV30+BQ30,2) | CA30: 1.12 | CC30: ==IFERROR(ROUND(CB30/FB_Kurs_12,2),0) | CD30: ==ROUND(CB30+BW30,2) | CE30: ==ROUND(CC30+BX30,2) | CH30: 1.12 | CJ30: ==IFERROR(ROUND(CI30/FB_Kurs_13,2),0) | CK30: ==ROUND(CI30+CD30,2) | CL30: ==ROUND(CJ30+CE30,2) | CO30: 1.12 | CQ30: ==IFERROR(ROUND(CP30/FB_Kurs_14,2),0) | CR30: ==ROUND(CP30+CK30,2) | CS30: ==ROUND(CQ30+CL30,2) | CV30: 1.12 | CX30: ==IFERROR(ROUND(CW30/FB_Kurs_15,2),0) | CY30: ==ROUND(CW30+CR30,2) | CZ30: ==ROUND(CX30+CS30,2) | DC30: 1.12 | DE30: ==IFERROR(ROUND(DD30/FB_Kurs_16,2),0) | DF30: ==ROUND(DD30+CY30,2) | DG30: ==ROUND(DE30+CZ30,2) | DJ30: 1.12 | DL30: ==IFERROR(ROUND(DK30/FB_Kurs_17,2),0) | DM30: ==ROUND(DK30+DF30,2) | DN30: ==ROUND(DL30+DG30,2) | DQ30: 1.12 | DS30: ==IFERROR(ROUND(DR30/FB_Kurs_18,2),0) | DT30: ==ROUND(DR30+DM30,2) | DU30: ==ROUND(DS30+DN30,2)
... B141: 8. | D141: ==IFERROR(ROUND(C141/FB_Kurs_1,2),0) | E141: ==ROUND(C141,2) | F141: ==ROUND(D141,2) | I141: 8. | K141: ==IFERROR(ROUND(J141/FB_Kurs_2,2),0) | L141: ==ROUND(J141+E141,2) | M141: ==ROUND(K141+F141,2) | P141: 8. | R141: ==IFERROR(ROUND(Q141/FB_Kurs_3,2),0) | S141: ==ROUND(Q141+L141,2) | T141: ==ROUND(R141+M141,2) | W141: 8. | Y141: ==IFERROR(ROUND(X141/FB_Kurs_4,2),0) | Z141: ==ROUND(X141+S141,2) | AA141: ==ROUND(Y141+T141,2) | AD141: 8. | AF141: ==IFERROR(ROUND(AE141/FB_Kurs_5,2),0) | AG141: ==ROUND(AE141+Z141,2) | AH141: ==ROUND(AF141+AA141,2) | AK141: 8. | AM141: ==IFERROR(ROUND(AL141/FB_Kurs_6,2),0) | AN141: ==ROUND(AL141+AG141,2) | AO141: ==ROUND(AM141+AH141,2) | AR141: 8. | AT141: ==IFERROR(ROUND(AS141/FB_Kurs_7,2),0) | AU141: ==ROUND(AS141+AN141,2) | AV141: ==ROUND(AT141+AO141,2) | AY141: 8. | BA141: ==IFERROR(ROUND(AZ141/FB_Kurs_8,2),0) | BB141: ==ROUND(AZ141+AU141,2) | BC141: ==ROUND(BA141+AV141,2) | BF141: 8. | BH141: ==IFERROR(ROUND(BG141/FB_Kurs_9,2),0) | BI141: ==ROUND(BG141+BB141,2) | BJ141: ==ROUND(BH141+BC141,2) | BM141: 8. | BO141: ==IFERROR(ROUND(BN141/FB_Kurs_10,2),0) | BP141: ==ROUND(BN141+BI141,2) | BQ141: ==ROUND(BO141+BJ141,2) | BT141: 8. | BV141: ==IFERROR(ROUND(BU141/FB_Kurs_11,2),0) | BW141: ==ROUND(BU141+BP141,2) | BX141: ==ROUND(BV141+BQ141,2) | CA141: 8. | CC141: ==IFERROR(ROUND(CB141/FB_Kurs_12,2),0) | CD141: ==ROUND(CB141+BW141,2) | CE141: ==ROUND(CC141+BX141,2) | CH141: 8. | CJ141: ==IFERROR(ROUND(CI141/FB_Kurs_13,2),0) | CK141: ==ROUND(CI141+CD141,2) | CL141: ==ROUND(CJ141+CE141,2) | CO141: 8. | CQ141: ==IFERROR(ROUND(CP141/FB_Kurs_14,2),0) | CR141: ==ROUND(CP141+CK141,2) | CS141: ==ROUND(CQ141+CL141,2) | CV141: 8. | CX141: ==IFERROR(ROUND(CW141/FB_Kurs_15,2),0) | CY141: ==ROUND(CW141+CR141,2) | CZ141: ==ROUND(CX141+CS141,2) | DC141: 8. | DE141: ==IFERROR(ROUND(DD141/FB_Kurs_16,2),0) | DF141: ==ROUND(DD141+CY141,2) | DG141: ==ROUND(DE141+CZ141,2) | DJ141: 8. | DL141: ==IFERROR(ROUND(DK141/FB_Kurs_17,2),0) | DM141: ==ROUND(DK141+DF141,2) | DN141: ==ROUND(DL141+DG141,2) | DQ141: 8. | DS141: ==IFERROR(ROUND(DR141/FB_Kurs_18,2),0) | DT141: ==ROUND(DR141+DM141,2) | DU141: ==ROUND(DS141+DN141,2)
B142: Gesamtausgaben | C142: ==ROUND(SUBTOTAL(109,$C$19:$C$141),2) | D142: ==ROUND(SUBTOTAL(109,$D$19:$D$141),2) | E142: ==ROUND(SUBTOTAL(109,$E$19:$E$141),2) | F142: ==ROUND(SUBTOTAL(109,$F$19:$F$141),2) | I142: Gesamtausgaben | J142: ==ROUND(SUBTOTAL(109,$J$19:$J$141),2) | K142: ==ROUND(SUBTOTAL(109,$K$19:$K$141),2) | L142: ==ROUND(SUBTOTAL(109,$L$19:$L$141),2) | M142: ==ROUND(SUBTOTAL(109,$M$19:$M$141),2) | P142: Gesamtausgaben | Q142: ==ROUND(SUBTOTAL(109,$Q$19:$Q$141),2) | R142: ==ROUND(SUBTOTAL(109,$R$19:$R$141),2) | S142: ==ROUND(SUBTOTAL(109,$S$19:$S$141),2) | T142: ==ROUND(SUBTOTAL(109,$T$19:$T$141),2) | W142: Gesamtausgaben | X142: ==ROUND(SUBTOTAL(109,$X$19:$X$141),2) | Y142: ==ROUND(SUBTOTAL(109,$Y$19:$Y$141),2) | Z142: ==ROUND(SUBTOTAL(109,$Z$19:$Z$141),2) | AA142: ==ROUND(SUBTOTAL(109,$AA$19:$AA$141),2) | AD142: Gesamtausgaben | AE142: ==ROUND(SUBTOTAL(109,$AE$19:$AE$141),2) | AF142: ==ROUND(SUBTOTAL(109,$AF$19:$AF$141),2) | AG142: ==ROUND(SUBTOTAL(109,$AG$19:$AG$141),2) | AH142: ==ROUND(SUBTOTAL(109,$AH$19:$AH$141),2) | AK142: Gesamtausgaben | AL142: ==ROUND(SUBTOTAL(109,$AL$19:$AL$141),2) | AM142: ==ROUND(SUBTOTAL(109,$AM$19:$AM$141),2) | AN142: ==ROUND(SUBTOTAL(109,$AN$19:$AN$141),2) | AO142: ==ROUND(SUBTOTAL(109,$AO$19:$AO$141),2) | AR142: Gesamtausgaben | AS142: ==ROUND(SUBTOTAL(109,$AS$19:$AS$141),2) | AT142: ==ROUND(SUBTOTAL(109,$AT$19:$AT$141),2) | AU142: ==ROUND(SUBTOTAL(109,$AU$19:$AU$141),2) | AV142: ==ROUND(SUBTOTAL(109,$AV$19:$AV$141),2) | AY142: Gesamtausgaben | AZ142: ==ROUND(SUBTOTAL(109,$AZ$19:$AZ$141),2) | BA142: ==ROUND(SUBTOTAL(109,$BA$19:$BA$141),2) | BB142: ==ROUND(SUBTOTAL(109,$BB$19:$BB$141),2) | BC142: ==ROUND(SUBTOTAL(109,$BC$19:$BC$141),2) | BF142: Gesamtausgaben | BG142: ==ROUND(SUBTOTAL(109,$BG$19:$BG$141),2) | BH142: ==ROUND(SUBTOTAL(109,$BH$19:$BH$141),2) | BI142: ==ROUND(SUBTOTAL(109,$BI$19:$BI$141),2) | BJ142: ==ROUND(SUBTOTAL(109,$BJ$19:$BJ$141),2) | BM142: Gesamtausgaben | BN142: ==ROUND(SUBTOTAL(109,$BN$19:$BN$141),2) | BO142: ==ROUND(SUBTOTAL(109,$BO$19:$BO$141),2) | BP142: ==ROUND(SUBTOTAL(109,$BP$19:$BP$141),2) | BQ142: ==ROUND(SUBTOTAL(109,$BQ$19:$BQ$141),2) | BT142: Gesamtausgaben | BU142: ==ROUND(SUBTOTAL(109,$BU$19:$BU$141),2) | BV142: ==ROUND(SUBTOTAL(109,$BV$19:$BV$141),2) | BW142: ==ROUND(SUBTOTAL(109,$BW$19:$BW$141),2) | BX142: ==ROUND(SUBTOTAL(109,$BX$19:$BX$141),2) | CA142: Gesamtausgaben | CB142: ==ROUND(SUBTOTAL(109,$CB$19:$CB$141),2) | CC142: ==ROUND(SUBTOTAL(109,$CC$19:$CC$141),2) | CD142: ==ROUND(SUBTOTAL(109,$CD$19:$CD$141),2) | CE142: ==ROUND(SUBTOTAL(109,$CE$19:$CE$141),2) | CH142: Gesamtausgaben | CI142: ==ROUND(SUBTOTAL(109,$CI$19:$CI$141),2) | CJ142: ==ROUND(SUBTOTAL(109,$CJ$19:$CJ$141),2) | CK142: ==ROUND(SUBTOTAL(109,$CK$19:$CK$141),2) | CL142: ==ROUND(SUBTOTAL(109,$CL$19:$CL$141),2) | CO142: Gesamtausgaben | CP142: ==ROUND(SUBTOTAL(109,$CP$19:$CP$141),2) | CQ142: ==ROUND(SUBTOTAL(109,$CQ$19:$CQ$141),2) | CR142: ==ROUND(SUBTOTAL(109,$CR$19:$CR$141),2) | CS142: ==ROUND(SUBTOTAL(109,$CS$19:$CS$141),2) | CV142: Gesamtausgaben | CW142: ==ROUND(SUBTOTAL(109,$CW$19:$CW$141),2) | CX142: ==ROUND(SUBTOTAL(109,$CX$19:$CX$141),2) | CY142: ==ROUND(SUBTOTAL(109,$CY$19:$CY$141),2) | CZ142: ==ROUND(SUBTOTAL(109,$CZ$19:$CZ$141),2) | DC142: Gesamtausgaben | DD142: ==ROUND(SUBTOTAL(109,$DD$19:$DD$141),2) | DE142: ==ROUND(SUBTOTAL(109,$DE$19:$DE$141),2) | DF142: ==ROUND(SUBTOTAL(109,$DF$19:$DF$141),2) | DG142: ==ROUND(SUBTOTAL(109,$DG$19:$DG$141),2) | DJ142: Gesamtausgaben | DK142: ==ROUND(SUBTOTAL(109,$DK$19:$DK$141),2) | DL142: ==ROUND(SUBTOTAL(109,$DL$19:$DL$141),2) | DM142: ==ROUND(SUBTOTAL(109,$DM$19:$DM$141),2) | DN142: ==ROUND(SUBTOTAL(109,$DN$19:$DN$141),2) | DQ142: Gesamtausgaben | DR142: ==ROUND(SUBTOTAL(109,$DR$19:$DR$141),2) | DS142: ==ROUND(SUBTOTAL(109,$DS$19:$DS$141),2) | DT142: ==ROUND(SUBTOTAL(109,$DT$19:$DT$141),2) | DU142: ==ROUND(SUBTOTAL(109,$DU$19:$DU$141),2)
B144: Saldo des Finanzberichts | C144: ==ROUND(IFERROR(C16-$C$142,""),2) | D144: ==ROUND(IFERROR(D16-$D$142,""),2) | E144: ==ROUND(IFERROR(E16-E142,""),2) | F144: ==ROUND(IFERROR(F16-F142,""),2) | I144: Saldo des Finanzberichts | J144: ==ROUND(IFERROR(J16-$J$142,""),2) | K144: ==ROUND(IFERROR(K16-$K$142,""),2) | L144: ==ROUND(IFERROR(L16-L142,""),2) | M144: ==ROUND(IFERROR(M16-M142,""),2) | P144: Saldo des Finanzberichts | Q144: ==ROUND(IFERROR(Q16-$Q$142,""),2) | R144: ==ROUND(IFERROR(R16-$R$142,""),2) | S144: ==ROUND(IFERROR(S16-S142,""),2) | T144: ==ROUND(IFERROR(T16-T142,""),2) | W144: Saldo des Finanzberichts | X144: ==ROUND(IFERROR(X16-$X$142,""),2) | Y144: ==ROUND(IFERROR(Y16-$Y$142,""),2) | Z144: ==ROUND(IFERROR(Z16-Z142,""),2) | AA144: ==ROUND(IFERROR(AA16-AA142,""),2) | AD144: Saldo des Finanzberichts | AE144: ==ROUND(IFERROR(AE16-$AE$142,""),2) | AF144: ==ROUND(IFERROR(AF16-$AF$142,""),2) | AG144: ==ROUND(IFERROR(AG16-AG142,""),2) | AH144: ==ROUND(IFERROR(AH16-AH142,""),2) | AK144: Saldo des Finanzberichts | AL144: ==ROUND(IFERROR(AL16-$AL$142,""),2) | AM144: ==ROUND(IFERROR(AM16-$AM$142,""),2) | AN144: ==ROUND(IFERROR(AN16-AN142,""),2) | AO144: ==ROUND(IFERROR(AO16-AO142,""),2) | AR144: Saldo des Finanzberichts | AS144: ==ROUND(IFERROR(AS16-$AS$142,""),2) | AT144: ==ROUND(IFERROR(AT16-$AT$142,""),2) | AU144: ==ROUND(IFERROR(AU16-AU142,""),2) | AV144: ==ROUND(IFERROR(AV16-AV142,""),2) | AY144: Saldo des Finanzberichts | AZ144: ==ROUND(IFERROR(AZ16-$AZ$142,""),2) | BA144: ==ROUND(IFERROR(BA16-$BA$142,""),2) | BB144: ==ROUND(IFERROR(BB16-BB142,""),2) | BC144: ==ROUND(IFERROR(BC16-BC142,""),2) | BF144: Saldo des Finanzberichts | BG144: ==ROUND(IFERROR(BG16-$BG$142,""),2) | BH144: ==ROUND(IFERROR(BH16-$BH$142,""),2) | BI144: ==ROUND(IFERROR(BI16-BI142,""),2) | BJ144: ==ROUND(IFERROR(BJ16-BJ142,""),2) | BM144: Saldo des Finanzberichts | BN144: ==ROUND(IFERROR(BN16-$BN$142,""),2) | BO144: ==ROUND(IFERROR(BO16-$BO$142,""),2) | BP144: ==ROUND(IFERROR(BP16-BP142,""),2) | BQ144: ==ROUND(IFERROR(BQ16-BQ142,""),2) | BT144: Saldo des Finanzberichts | BU144: ==ROUND(IFERROR(BU16-$BU$142,""),2) | BV144: ==ROUND(IFERROR(BV16-$BV$142,""),2) | BW144: ==ROUND(IFERROR(BW16-BW142,""),2) | BX144: ==ROUND(IFERROR(BX16-BX142,""),2) | CA144: Saldo des Finanzberichts | CB144: ==ROUND(IFERROR(CB16-$CB$142,""),2) | CC144: ==ROUND(IFERROR(CC16-$CC$142,""),2) | CD144: ==ROUND(IFERROR(CD16-CD142,""),2) | CE144: ==ROUND(IFERROR(CE16-CE142,""),2) | CH144: Saldo des Finanzberichts | CI144: ==ROUND(IFERROR(CI16-$CI$142,""),2) | CJ144: ==ROUND(IFERROR(CJ16-$CJ$142,""),2) | CK144: ==ROUND(IFERROR(CK16-CK142,""),2) | CL144: ==ROUND(IFERROR(CL16-CL142,""),2) | CO144: Saldo des Finanzberichts | CP144: ==ROUND(IFERROR(CP16-$CP$142,""),2) | CQ144: ==ROUND(IFERROR(CQ16-$CQ$142,""),2) | CR144: ==ROUND(IFERROR(CR16-CR142,""),2) | CS144: ==ROUND(IFERROR(CS16-CS142,""),2) | CV144: Saldo des Finanzberichts | CW144: ==ROUND(IFERROR(CW16-$CW$142,""),2) | CX144: ==ROUND(IFERROR(CX16-$CX$142,""),2) | CY144: ==ROUND(IFERROR(CY16-CY142,""),2) | CZ144: ==ROUND(IFERROR(CZ16-CZ142,""),2) | DC144: Saldo des Finanzberichts | DD144: ==ROUND(IFERROR(DD16-$DD$142,""),2) | DE144: ==ROUND(IFERROR(DE16-$DE$142,""),2) | DF144: ==ROUND(IFERROR(DF16-DF142,""),2) | DG144: ==ROUND(IFERROR(DG16-DG142,""),2) | DJ144: Saldo des Finanzberichts | DK144: ==ROUND(IFERROR(DK16-$DK$142,""),2) | DL144: ==ROUND(IFERROR(DL16-$DL$142,""),2) | DM144: ==ROUND(IFERROR(DM16-DM142,""),2) | DN144: ==ROUND(IFERROR(DN16-DN142,""),2) | DQ144: Saldo des Finanzberichts | DR144: ==ROUND(IFERROR(DR16-$DR$142,""),2) | DS144: ==ROUND(IFERROR(DS16-$DS$142,""),2) | DT144: ==ROUND(IFERROR(DT16-DT142,""),2) | DU144: ==ROUND(IFERROR(DU16-DU142,""),2)
B146: Aufschluesselung: | I146: Aufschluesselung: | P146: Aufschluesselung: | W146: Aufschluesselung: | AD146: Aufschluesselung: | AK146: Aufschluesselung: | AR146: Aufschluesselung: | AY146: Aufschluesselung: | BF146: Aufschluesselung: | BM146: Aufschluesselung: | BT146: Aufschluesselung: | CA146: Aufschluesselung: | CH146: Aufschluesselung: | CO146: Aufschluesselung: | CV146: Aufschluesselung: | DC146: Aufschluesselung: | DJ146: Aufschluesselung: | DQ146: Aufschluesselung:
B147: Bank | D147: ==IF(C147=0, 0, IF(ROUND(SUM(C148:C149), 2)=0, ROUND(D144 - 0, 2), ROUND(C147 / ROUND(SUM(C147:C149), 2) * D144, 2))) | I147: Bank | K147: ==IF(J147=0, 0, IF(ROUND(SUM(J148:J149), 2)=0, ROUND(K144 - 0, 2), ROUND(J147 / ROUND(SUM(J147:J149), 2) * K144, 2))) | P147: Bank | R147: ==IF(Q147=0, 0, IF(ROUND(SUM(Q148:Q149), 2)=0, ROUND(R144 - 0, 2), ROUND(Q147 / ROUND(SUM(Q147:Q149), 2) * R144, 2))) | W147: Bank | Y147: ==IF(X147=0, 0, IF(ROUND(SUM(X148:X149), 2)=0, ROUND(Y144 - 0, 2), ROUND(X147 / ROUND(SUM(X147:X149), 2) * Y144, 2))) | AD147: Bank | AF147: ==IF(AE147=0, 0, IF(ROUND(SUM(AE148:AE149), 2)=0, ROUND(AF144 - 0, 2), ROUND(AE147 / ROUND(SUM(AE147:AE149), 2) * AF144, 2))) | AK147: Bank | AM147: ==IF(AL147=0, 0, IF(ROUND(SUM(AL148:AL149), 2)=0, ROUND(AM144 - 0, 2), ROUND(AL147 / ROUND(SUM(AL147:AL149), 2) * AM144, 2))) | AR147: Bank | AT147: ==IF(AS147=0, 0, IF(ROUND(SUM(AS148:AS149), 2)=0, ROUND(AT144 - 0, 2), ROUND(AS147 / ROUND(SUM(AS147:AS149), 2) * AT144, 2))) | AY147: Bank | BA147: ==IF(AZ147=0, 0, IF(ROUND(SUM(AZ148:AZ149), 2)=0, ROUND(BA144 - 0, 2), ROUND(AZ147 / ROUND(SUM(AZ147:AZ149), 2) * BA144, 2))) | BF147: Bank | BH147: ==IF(BG147=0, 0, IF(ROUND(SUM(BG148:BG149), 2)=0, ROUND(BH144 - 0, 2), ROUND(BG147 / ROUND(SUM(BG147:BG149), 2) * BH144, 2))) | BM147: Bank | BO147: ==IF(BN147=0, 0, IF(ROUND(SUM(BN148:BN149), 2)=0, ROUND(BO144 - 0, 2), ROUND(BN147 / ROUND(SUM(BN147:BN149), 2) * BO144, 2))) | BT147: Bank | BV147: ==IF(BU147=0, 0, IF(ROUND(SUM(BU148:BU149), 2)=0, ROUND(BV144 - 0, 2), ROUND(BU147 / ROUND(SUM(BU147:BU149), 2) * BV144, 2))) | CA147: Bank | CC147: ==IF(CB147=0, 0, IF(ROUND(SUM(CB148:CB149), 2)=0, ROUND(CC144 - 0, 2), ROUND(CB147 / ROUND(SUM(CB147:CB149), 2) * CC144, 2))) | CH147: Bank | CJ147: ==IF(CI147=0, 0, IF(ROUND(SUM(CI148:CI149), 2)=0, ROUND(CJ144 - 0, 2), ROUND(CI147 / ROUND(SUM(CI147:CI149), 2) * CJ144, 2))) | CO147: Bank | CQ147: ==IF(CP147=0, 0, IF(ROUND(SUM(CP148:CP149), 2)=0, ROUND(CQ144 - 0, 2), ROUND(CP147 / ROUND(SUM(CP147:CP149), 2) * CQ144, 2))) | CV147: Bank | CX147: ==IF(CW147=0, 0, IF(ROUND(SUM(CW148:CW149), 2)=0, ROUND(CX144 - 0, 2), ROUND(CW147 / ROUND(SUM(CW147:CW149), 2) * CX144, 2))) | DC147: Bank | DE147: ==IF(DD147=0, 0, IF(ROUND(SUM(DD148:DD149), 2)=0, ROUND(DE144 - 0, 2), ROUND(DD147 / ROUND(SUM(DD147:DD149), 2) * DE144, 2))) | DJ147: Bank | DL147: ==IF(DK147=0, 0, IF(ROUND(SUM(DK148:DK149), 2)=0, ROUND(DL144 - 0, 2), ROUND(DK147 / ROUND(SUM(DK147:DK149), 2) * DL144, 2))) | DQ147: Bank | DS147: ==IF(DR147=0, 0, IF(ROUND(SUM(DR148:DR149), 2)=0, ROUND(DS144 - 0, 2), ROUND(DR147 / ROUND(SUM(DR147:DR149), 2) * DS144, 2)))
B148: Kasse | D148: ==IF(C148=0, 0, IF(ROUND(SUM(C149:C149), 2)=0, ROUND(D144 - SUM(D147:D147), 2), ROUND(C148 / ROUND(SUM(C147:C149), 2) * D144, 2))) | I148: Kasse | K148: ==IF(J148=0, 0, IF(ROUND(SUM(J149:J149), 2)=0, ROUND(K144 - SUM(K147:K147), 2), ROUND(J148 / ROUND(SUM(J147:J149), 2) * K144, 2))) | P148: Kasse | R148: ==IF(Q148=0, 0, IF(ROUND(SUM(Q149:Q149), 2)=0, ROUND(R144 - SUM(R147:R147), 2), ROUND(Q148 / ROUND(SUM(Q147:Q149), 2) * R144, 2))) | W148: Kasse | Y148: ==IF(X148=0, 0, IF(ROUND(SUM(X149:X149), 2)=0, ROUND(Y144 - SUM(Y147:Y147), 2), ROUND(X148 / ROUND(SUM(X147:X149), 2) * Y144, 2))) | AD148: Kasse | AF148: ==IF(AE148=0, 0, IF(ROUND(SUM(AE149:AE149), 2)=0, ROUND(AF144 - SUM(AF147:AF147), 2), ROUND(AE148 / ROUND(SUM(AE147:AE149), 2) * AF144, 2))) | AK148: Kasse | AM148: ==IF(AL148=0, 0, IF(ROUND(SUM(AL149:AL149), 2)=0, ROUND(AM144 - SUM(AM147:AM147), 2), ROUND(AL148 / ROUND(SUM(AL147:AL149), 2) * AM144, 2))) | AR148: Kasse | AT148: ==IF(AS148=0, 0, IF(ROUND(SUM(AS149:AS149), 2)=0, ROUND(AT144 - SUM(AT147:AT147), 2), ROUND(AS148 / ROUND(SUM(AS147:AS149), 2) * AT144, 2))) | AY148: Kasse | BA148: ==IF(AZ148=0, 0, IF(ROUND(SUM(AZ149:AZ149), 2)=0, ROUND(BA144 - SUM(BA147:BA147), 2), ROUND(AZ148 / ROUND(SUM(AZ147:AZ149), 2) * BA144, 2))) | BF148: Kasse | BH148: ==IF(BG148=0, 0, IF(ROUND(SUM(BG149:BG149), 2)=0, ROUND(BH144 - SUM(BH147:BH147), 2), ROUND(BG148 / ROUND(SUM(BG147:BG149), 2) * BH144, 2))) | BM148: Kasse | BO148: ==IF(BN148=0, 0, IF(ROUND(SUM(BN149:BN149), 2)=0, ROUND(BO144 - SUM(BO147:BO147), 2), ROUND(BN148 / ROUND(SUM(BN147:BN149), 2) * BO144, 2))) | BT148: Kasse | BV148: ==IF(BU148=0, 0, IF(ROUND(SUM(BU149:BU149), 2)=0, ROUND(BV144 - SUM(BV147:BV147), 2), ROUND(BU148 / ROUND(SUM(BU147:BU149), 2) * BV144, 2))) | CA148: Kasse | CC148: ==IF(CB148=0, 0, IF(ROUND(SUM(CB149:CB149), 2)=0, ROUND(CC144 - SUM(CC147:CC147), 2), ROUND(CB148 / ROUND(SUM(CB147:CB149), 2) * CC144, 2))) | CH148: Kasse | CJ148: ==IF(CI148=0, 0, IF(ROUND(SUM(CI149:CI149), 2)=0, ROUND(CJ144 - SUM(CJ147:CJ147), 2), ROUND(CI148 / ROUND(SUM(CI147:CI149), 2) * CJ144, 2))) | CO148: Kasse | CQ148: ==IF(CP148=0, 0, IF(ROUND(SUM(CP149:CP149), 2)=0, ROUND(CQ144 - SUM(CQ147:CQ147), 2), ROUND(CP148 / ROUND(SUM(CP147:CP149), 2) * CQ144, 2))) | CV148: Kasse | CX148: ==IF(CW148=0, 0, IF(ROUND(SUM(CW149:CW149), 2)=0, ROUND(CX144 - SUM(CX147:CX147), 2), ROUND(CW148 / ROUND(SUM(CW147:CW149), 2) * CX144, 2))) | DC148: Kasse | DE148: ==IF(DD148=0, 0, IF(ROUND(SUM(DD149:DD149), 2)=0, ROUND(DE144 - SUM(DE147:DE147), 2), ROUND(DD148 / ROUND(SUM(DD147:DD149), 2) * DE144, 2))) | DJ148: Kasse | DL148: ==IF(DK148=0, 0, IF(ROUND(SUM(DK149:DK149), 2)=0, ROUND(DL144 - SUM(DL147:DL147), 2), ROUND(DK148 / ROUND(SUM(DK147:DK149), 2) * DL144, 2))) | DQ148: Kasse | DS148: ==IF(DR148=0, 0, IF(ROUND(SUM(DR149:DR149), 2)=0, ROUND(DS144 - SUM(DS147:DS147), 2), ROUND(DR148 / ROUND(SUM(DR147:DR149), 2) * DS144, 2)))
B149: Sonstiges | D149: ==IF(C149=0, 0, ROUND(D144 - SUM(D147:D148), 2)) | I149: Sonstiges | K149: ==IF(J149=0, 0, ROUND(K144 - SUM(K147:K148), 2)) | P149: Sonstiges | R149: ==IF(Q149=0, 0, ROUND(R144 - SUM(R147:R148), 2)) | W149: Sonstiges | Y149: ==IF(X149=0, 0, ROUND(Y144 - SUM(Y147:Y148), 2)) | AD149: Sonstiges | AF149: ==IF(AE149=0, 0, ROUND(AF144 - SUM(AF147:AF148), 2)) | AK149: Sonstiges | AM149: ==IF(AL149=0, 0, ROUND(AM144 - SUM(AM147:AM148), 2)) | AR149: Sonstiges | AT149: ==IF(AS149=0, 0, ROUND(AT144 - SUM(AT147:AT148), 2)) | AY149: Sonstiges | BA149: ==IF(AZ149=0, 0, ROUND(BA144 - SUM(BA147:BA148), 2)) | BF149: Sonstiges | BH149: ==IF(BG149=0, 0, ROUND(BH144 - SUM(BH147:BH148), 2)) | BM149: Sonstiges | BO149: ==IF(BN149=0, 0, ROUND(BO144 - SUM(BO147:BO148), 2)) | BT149: Sonstiges | BV149: ==IF(BU149=0, 0, ROUND(BV144 - SUM(BV147:BV148), 2)) | CA149: Sonstiges | CC149: ==IF(CB149=0, 0, ROUND(CC144 - SUM(CC147:CC148), 2)) | CH149: Sonstiges | CJ149: ==IF(CI149=0, 0, ROUND(CJ144 - SUM(CJ147:CJ148), 2)) | CO149: Sonstiges | CQ149: ==IF(CP149=0, 0, ROUND(CQ144 - SUM(CQ147:CQ148), 2)) | CV149: Sonstiges | CX149: ==IF(CW149=0, 0, ROUND(CX144 - SUM(CX147:CX148), 2)) | DC149: Sonstiges | DE149: ==IF(DD149=0, 0, ROUND(DE144 - SUM(DE147:DE148), 2)) | DJ149: Sonstiges | DL149: ==IF(DK149=0, 0, ROUND(DL144 - SUM(DL147:DL148), 2)) | DQ149: Sonstiges | DS149: ==IF(DR149=0, 0, ROUND(DS144 - SUM(DS147:DS148), 2))
B151: Differenz (Pruefung): | C151: ==ROUND(IFERROR(C144-SUM(C147:C149),""),2) | D151: ==ROUND(IFERROR(D144-SUM(D147:D149),""),2) | I151: Differenz (Pruefung): | J151: ==ROUND(IFERROR(J144-SUM(J147:J149),""),2) | K151: ==ROUND(IFERROR(K144-SUM(K147:K149),""),2) | P151: Differenz (Pruefung): | Q151: ==ROUND(IFERROR(Q144-SUM(Q147:Q149),""),2) | R151: ==ROUND(IFERROR(R144-SUM(R147:R149),""),2) | W151: Differenz (Pruefung): | X151: ==ROUND(IFERROR(X144-SUM(X147:X149),""),2) | Y151: ==ROUND(IFERROR(Y144-SUM(Y147:Y149),""),2) | AD151: Differenz (Pruefung): | AE151: ==ROUND(IFERROR(AE144-SUM(AE147:AE149),""),2) | AF151: ==ROUND(IFERROR(AF144-SUM(AF147:AF149),""),2) | AK151: Differenz (Pruefung): | AL151: ==ROUND(IFERROR(AL144-SUM(AL147:AL149),""),2) | AM151: ==ROUND(IFERROR(AM144-SUM(AM147:AM149),""),2) | AR151: Differenz (Pruefung): | AS151: ==ROUND(IFERROR(AS144-SUM(AS147:AS149),""),2) | AT151: ==ROUND(IFERROR(AT144-SUM(AT147:AT149),""),2) | AY151: Differenz (Pruefung): | AZ151: ==ROUND(IFERROR(AZ144-SUM(AZ147:AZ149),""),2) | BA151: ==ROUND(IFERROR(BA144-SUM(BA147:BA149),""),2) | BF151: Differenz (Pruefung): | BG151: ==ROUND(IFERROR(BG144-SUM(BG147:BG149),""),2) | BH151: ==ROUND(IFERROR(BH144-SUM(BH147:BH149),""),2) | BM151: Differenz (Pruefung): | BN151: ==ROUND(IFERROR(BN144-SUM(BN147:BN149),""),2) | BO151: ==ROUND(IFERROR(BO144-SUM(BO147:BO149),""),2) | BT151: Differenz (Pruefung): | BU151: ==ROUND(IFERROR(BU144-SUM(BU147:BU149),""),2) | BV151: ==ROUND(IFERROR(BV144-SUM(BV147:BV149),""),2) | CA151: Differenz (Pruefung): | CB151: ==ROUND(IFERROR(CB144-SUM(CB147:CB149),""),2) | CC151: ==ROUND(IFERROR(CC144-SUM(CC147:CC149),""),2) | CH151: Differenz (Pruefung): | CI151: ==ROUND(IFERROR(CI144-SUM(CI147:CI149),""),2) | CJ151: ==ROUND(IFERROR(CJ144-SUM(CJ147:CJ149),""),2) | CO151: Differenz (Pruefung): | CP151: ==ROUND(IFERROR(CP144-SUM(CP147:CP149),""),2) | CQ151: ==ROUND(IFERROR(CQ144-SUM(CQ147:CQ149),""),2) | CV151: Differenz (Pruefung): | CW151: ==ROUND(IFERROR(CW144-SUM(CW147:CW149),""),2) | CX151: ==ROUND(IFERROR(CX144-SUM(CX147:CX149),""),2) | DC151: Differenz (Pruefung): | DD151: ==ROUND(IFERROR(DD144-SUM(DD147:DD149),""),2) | DE151: ==ROUND(IFERROR(DE144-SUM(DE147:DE149),""),2) | DJ151: Differenz (Pruefung): | DK151: ==ROUND(IFERROR(DK144-SUM(DK147:DK149),""),2) | DL151: ==ROUND(IFERROR(DL144-SUM(DL147:DL149),""),2) | DQ151: Differenz (Pruefung): | DR151: ==ROUND(IFERROR(DR144-SUM(DR147:DR149),""),2) | DS151: ==ROUND(IFERROR(DS144-SUM(DS147:DS149),""),2)
B154: Einnahmen (Explizite Kurseingabe) | I154: Einnahmen (Explizite Kurseingabe) | P154: Einnahmen (Explizite Kurseingabe) | W154: Einnahmen (Explizite Kurseingabe) | AD154: Einnahmen (Explizite Kurseingabe) | AK154: Einnahmen (Explizite Kurseingabe) | AR154: Einnahmen (Explizite Kurseingabe) | AY154: Einnahmen (Explizite Kurseingabe) | BF154: Einnahmen (Explizite Kurseingabe) | BM154: Einnahmen (Explizite Kurseingabe) | BT154: Einnahmen (Explizite Kurseingabe) | CA154: Einnahmen (Explizite Kurseingabe) | CH154: Einnahmen (Explizite Kurseingabe) | CO154: Einnahmen (Explizite Kurseingabe) | CV154: Einnahmen (Explizite Kurseingabe) | DC154: Einnahmen (Explizite Kurseingabe) | DJ154: Einnahmen (Explizite Kurseingabe) | DQ154: Einnahmen (Explizite Kurseingabe)
B155: Typ | C155: Geber | D155: Einnahmen (LC) | E155: Einnahmen (EUR) | F155: Kurs | I155: Typ | J155: Geber | K155: Einnahmen (LC) | L155: Einnahmen (EUR) | M155: Kurs | P155: Typ | Q155: Geber | R155: Einnahmen (LC) | S155: Einnahmen (EUR) | T155: Kurs | W155: Typ | X155: Geber | Y155: Einnahmen (LC) | Z155: Einnahmen (EUR) | AA155: Kurs | AD155: Typ | AE155: Geber | AF155: Einnahmen (LC) | AG155: Einnahmen (EUR) | AH155: Kurs | AK155: Typ | AL155: Geber | AM155: Einnahmen (LC) | AN155: Einnahmen (EUR) | AO155: Kurs | AR155: Typ | AS155: Geber | AT155: Einnahmen (LC) | AU155: Einnahmen (EUR) | AV155: Kurs | AY155: Typ | AZ155: Geber | BA155: Einnahmen (LC) | BB155: Einnahmen (EUR) | BC155: Kurs | BF155: Typ | BG155: Geber | BH155: Einnahmen (LC) | BI155: Einnahmen (EUR) | BJ155: Kurs | BM155: Typ | BN155: Geber | BO155: Einnahmen (LC) | BP155: Einnahmen (EUR) | BQ155: Kurs | BT155: Typ | BU155: Geber | BV155: Einnahmen (LC) | BW155: Einnahmen (EUR) | BX155: Kurs | CA155: Typ | CB155: Geber | CC155: Einnahmen (LC) | CD155: Einnahmen (EUR) | CE155: Kurs | CH155: Typ | CI155: Geber | CJ155: Einnahmen (LC) | CK155: Einnahmen (EUR) | CL155: Kurs | CO155: Typ | CP155: Geber | CQ155: Einnahmen (LC) | CR155: Einnahmen (EUR) | CS155: Kurs | CV155: Typ | CW155: Geber | CX155: Einnahmen (LC) | CY155: Einnahmen (EUR) | CZ155: Kurs | DC155: Typ | DD155: Geber | DE155: Einnahmen (LC) | DF155: Einnahmen (EUR) | DG155: Kurs | DJ155: Typ | DK155: Geber | DL155: Einnahmen (LC) | DM155: Einnahmen (EUR) | DN155: Kurs | DQ155: Typ | DR155: Geber | DS155: Einnahmen (LC) | DT155: Einnahmen (EUR) | DU155: Kurs
B156: Saldo des Vorprojekts | D156: ==ROUND(C11,2) | E156: ==ROUND(D11,2) | F156: ==ROUND(IFERROR(D156/E156,0),6) | I156: Saldo der Vorperiode | K156: ==ROUND(J11,2) | L156: ==ROUND(K11,2) | M156: ==ROUND(IFERROR(K156/L156,0),6) | P156: Saldo der Vorperiode | R156: ==ROUND(Q11,2) | S156: ==ROUND(R11,2) | T156: ==ROUND(IFERROR(R156/S156,0),6) | W156: Saldo der Vorperiode | Y156: ==ROUND(X11,2) | Z156: ==ROUND(Y11,2) | AA156: ==ROUND(IFERROR(Y156/Z156,0),6) | AD156: Saldo der Vorperiode | AF156: ==ROUND(AE11,2) | AG156: ==ROUND(AF11,2) | AH156: ==ROUND(IFERROR(AF156/AG156,0),6) | AK156: Saldo der Vorperiode | AM156: ==ROUND(AL11,2) | AN156: ==ROUND(AM11,2) | AO156: ==ROUND(IFERROR(AM156/AN156,0),6) | AR156: Saldo der Vorperiode | AT156: ==ROUND(AS11,2) | AU156: ==ROUND(AT11,2) | AV156: ==ROUND(IFERROR(AT156/AU156,0),6) | AY156: Saldo der Vorperiode | BA156: ==ROUND(AZ11,2) | BB156: ==ROUND(BA11,2) | BC156: ==ROUND(IFERROR(BA156/BB156,0),6) | BF156: Saldo der Vorperiode | BH156: ==ROUND(BG11,2) | BI156: ==ROUND(BH11,2) | BJ156: ==ROUND(IFERROR(BH156/BI156,0),6) | BM156: Saldo der Vorperiode | BO156: ==ROUND(BN11,2) | BP156: ==ROUND(BO11,2) | BQ156: ==ROUND(IFERROR(BO156/BP156,0),6) | BT156: Saldo der Vorperiode | BV156: ==ROUND(BU11,2) | BW156: ==ROUND(BV11,2) | BX156: ==ROUND(IFERROR(BV156/BW156,0),6) | CA156: Saldo der Vorperiode | CC156: ==ROUND(CB11,2) | CD156: ==ROUND(CC11,2) | CE156: ==ROUND(IFERROR(CC156/CD156,0),6) | CH156: Saldo der Vorperiode | CJ156: ==ROUND(CI11,2) | CK156: ==ROUND(CJ11,2) | CL156: ==ROUND(IFERROR(CJ156/CK156,0),6) | CO156: Saldo der Vorperiode | CQ156: ==ROUND(CP11,2) | CR156: ==ROUND(CQ11,2) | CS156: ==ROUND(IFERROR(CQ156/CR156,0),6) | CV156: Saldo der Vorperiode | CX156: ==ROUND(CW11,2) | CY156: ==ROUND(CX11,2) | CZ156: ==ROUND(IFERROR(CX156/CY156,0),6) | DC156: Saldo der Vorperiode | DE156: ==ROUND(DD11,2) | DF156: ==ROUND(DE11,2) | DG156: ==ROUND(IFERROR(DE156/DF156,0),6) | DJ156: Saldo der Vorperiode | DL156: ==ROUND(DK11,2) | DM156: ==ROUND(DL11,2) | DN156: ==ROUND(IFERROR(DL156/DM156,0),6) | DQ156: Saldo der Vorperiode | DS156: ==ROUND(DR11,2) | DT156: ==ROUND(DS11,2) | DU156: ==ROUND(IFERROR(DS156/DT156,0),6)
B157: KMW-Mittel | F157: ==ROUND(IFERROR(D157/E157,0),6) | I157: KMW-Mittel | M157: ==ROUND(IFERROR(K157/L157,0),6) | P157: KMW-Mittel | T157: ==ROUND(IFERROR(R157/S157,0),6) | W157: KMW-Mittel | AA157: ==ROUND(IFERROR(Y157/Z157,0),6) | AD157: KMW-Mittel | AH157: ==ROUND(IFERROR(AF157/AG157,0),6) | AK157: KMW-Mittel | AO157: ==ROUND(IFERROR(AM157/AN157,0),6) | AR157: KMW-Mittel | AV157: ==ROUND(IFERROR(AT157/AU157,0),6) | AY157: KMW-Mittel | BC157: ==ROUND(IFERROR(BA157/BB157,0),6) | BF157: KMW-Mittel | BJ157: ==ROUND(IFERROR(BH157/BI157,0),6) | BM157: KMW-Mittel | BQ157: ==ROUND(IFERROR(BO157/BP157,0),6) | BT157: KMW-Mittel | BX157: ==ROUND(IFERROR(BV157/BW157,0),6) | CA157: KMW-Mittel | CE157: ==ROUND(IFERROR(CC157/CD157,0),6) | CH157: KMW-Mittel | CL157: ==ROUND(IFERROR(CJ157/CK157,0),6) | CO157: KMW-Mittel | CS157: ==ROUND(IFERROR(CQ157/CR157,0),6) | CV157: KMW-Mittel | CZ157: ==ROUND(IFERROR(CX157/CY157,0),6) | DC157: KMW-Mittel | DG157: ==ROUND(IFERROR(DE157/DF157,0),6) | DJ157: KMW-Mittel | DN157: ==ROUND(IFERROR(DL157/DM157,0),6) | DQ157: KMW-Mittel | DU157: ==ROUND(IFERROR(DS157/DT157,0),6)
F158: ==ROUND(IFERROR(D158/E158,0),6) | M158: ==ROUND(IFERROR(K158/L158,0),6) | T158: ==ROUND(IFERROR(R158/S158,0),6) | AA158: ==ROUND(IFERROR(Y158/Z158,0),6) | AH158: ==ROUND(IFERROR(AF158/AG158,0),6) | AO158: ==ROUND(IFERROR(AM158/AN158,0),6) | AV158: ==ROUND(IFERROR(AT158/AU158,0),6) | BC158: ==ROUND(IFERROR(BA158/BB158,0),6) | BJ158: ==ROUND(IFERROR(BH158/BI158,0),6) | BQ158: ==ROUND(IFERROR(BO158/BP158,0),6) | BX158: ==ROUND(IFERROR(BV158/BW158,0),6) | CE158: ==ROUND(IFERROR(CC158/CD158,0),6) | CL158: ==ROUND(IFERROR(CJ158/CK158,0),6) | CS158: ==ROUND(IFERROR(CQ158/CR158,0),6) | CZ158: ==ROUND(IFERROR(CX158/CY158,0),6) | DG158: ==ROUND(IFERROR(DE158/DF158,0),6) | DN158: ==ROUND(IFERROR(DL158/DM158,0),6) | DU158: ==ROUND(IFERROR(DS158/DT158,0),6)
F159: ==ROUND(IFERROR(D159/E159,0),6) | M159: ==ROUND(IFERROR(K159/L159,0),6) | T159: ==ROUND(IFERROR(R159/S159,0),6) | AA159: ==ROUND(IFERROR(Y159/Z159,0),6) | AH159: ==ROUND(IFERROR(AF159/AG159,0),6) | AO159: ==ROUND(IFERROR(AM159/AN159,0),6) | AV159: ==ROUND(IFERROR(AT159/AU159,0),6) | BC159: ==ROUND(IFERROR(BA159/BB159,0),6) | BJ159: ==ROUND(IFERROR(BH159/BI159,0),6) | BQ159: ==ROUND(IFERROR(BO159/BP159,0),6) | BX159: ==ROUND(IFERROR(BV159/BW159,0),6) | CE159: ==ROUND(IFERROR(CC159/CD159,0),6) | CL159: ==ROUND(IFERROR(CJ159/CK159,0),6) | CS159: ==ROUND(IFERROR(CQ159/CR159,0),6) | CZ159: ==ROUND(IFERROR(CX159/CY159,0),6) | DG159: ==ROUND(IFERROR(DE159/DF159,0),6) | DN159: ==ROUND(IFERROR(DL159/DM159,0),6) | DU159: ==ROUND(IFERROR(DS159/DT159,0),6)
F160: ==ROUND(IFERROR(D160/E160,0),6) | M160: ==ROUND(IFERROR(K160/L160,0),6) | T160: ==ROUND(IFERROR(R160/S160,0),6) | AA160: ==ROUND(IFERROR(Y160/Z160,0),6) | AH160: ==ROUND(IFERROR(AF160/AG160,0),6) | AO160: ==ROUND(IFERROR(AM160/AN160,0),6) | AV160: ==ROUND(IFERROR(AT160/AU160,0),6) | BC160: ==ROUND(IFERROR(BA160/BB160,0),6) | BJ160: ==ROUND(IFERROR(BH160/BI160,0),6) | BQ160: ==ROUND(IFERROR(BO160/BP160,0),6) | BX160: ==ROUND(IFERROR(BV160/BW160,0),6) | CE160: ==ROUND(IFERROR(CC160/CD160,0),6) | CL160: ==ROUND(IFERROR(CJ160/CK160,0),6) | CS160: ==ROUND(IFERROR(CQ160/CR160,0),6) | CZ160: ==ROUND(IFERROR(CX160/CY160,0),6) | DG160: ==ROUND(IFERROR(DE160/DF160,0),6) | DN160: ==ROUND(IFERROR(DL160/DM160,0),6) | DU160: ==ROUND(IFERROR(DS160/DT160,0),6)
B161: Gesamteinnahmen in Periode | C161: Durchschnittskurs: | D161: ==ROUND(SUBTOTAL(109,$D$156:$D$160),2) | E161: ==ROUND(SUBTOTAL(109,$E$156:$E$160),2) | F161: ==ROUND(IFERROR(D161/E161,0),6) | I161: Gesamteinnahmen in Periode | J161: Durchschnittskurs: | K161: ==ROUND(SUBTOTAL(109,$K$156:$K$160),2) | L161: ==ROUND(SUBTOTAL(109,$L$156:$L$160),2) | M161: ==ROUND(IFERROR(K161/L161,0),6) | P161: Gesamteinnahmen in Periode | Q161: Durchschnittskurs: | R161: ==ROUND(SUBTOTAL(109,$R$156:$R$160),2) | S161: ==ROUND(SUBTOTAL(109,$S$156:$S$160),2) | T161: ==ROUND(IFERROR(R161/S161,0),6) | W161: Gesamteinnahmen in Periode | X161: Durchschnittskurs: | Y161: ==ROUND(SUBTOTAL(109,$Y$156:$Y$160),2) | Z161: ==ROUND(SUBTOTAL(109,$Z$156:$Z$160),2) | AA161: ==ROUND(IFERROR(Y161/Z161,0),6) | AD161: Gesamteinnahmen in Periode | AE161: Durchschnittskurs: | AF161: ==ROUND(SUBTOTAL(109,$AF$156:$AF$160),2) | AG161: ==ROUND(SUBTOTAL(109,$AG$156:$AG$160),2) | AH161: ==ROUND(IFERROR(AF161/AG161,0),6) | AK161: Gesamteinnahmen in Periode | AL161: Durchschnittskurs: | AM161: ==ROUND(SUBTOTAL(109,$AM$156:$AM$160),2) | AN161: ==ROUND(SUBTOTAL(109,$AN$156:$AN$160),2) | AO161: ==ROUND(IFERROR(AM161/AN161,0),6) | AR161: Gesamteinnahmen in Periode | AS161: Durchschnittskurs: | AT161: ==ROUND(SUBTOTAL(109,$AT$156:$AT$160),2) | AU161: ==ROUND(SUBTOTAL(109,$AU$156:$AU$160),2) | AV161: ==ROUND(IFERROR(AT161/AU161,0),6) | AY161: Gesamteinnahmen in Periode | AZ161: Durchschnittskurs: | BA161: ==ROUND(SUBTOTAL(109,$BA$156:$BA$160),2) | BB161: ==ROUND(SUBTOTAL(109,$BB$156:$BB$160),2) | BC161: ==ROUND(IFERROR(BA161/BB161,0),6) | BF161: Gesamteinnahmen in Periode | BG161: Durchschnittskurs: | BH161: ==ROUND(SUBTOTAL(109,$BH$156:$BH$160),2) | BI161: ==ROUND(SUBTOTAL(109,$BI$156:$BI$160),2) | BJ161: ==ROUND(IFERROR(BH161/BI161,0),6) | BM161: Gesamteinnahmen in Periode | BN161: Durchschnittskurs: | BO161: ==ROUND(SUBTOTAL(109,$BO$156:$BO$160),2) | BP161: ==ROUND(SUBTOTAL(109,$BP$156:$BP$160),2) | BQ161: ==ROUND(IFERROR(BO161/BP161,0),6) | BT161: Gesamteinnahmen in Periode | BU161: Durchschnittskurs: | BV161: ==ROUND(SUBTOTAL(109,$BV$156:$BV$160),2) | BW161: ==ROUND(SUBTOTAL(109,$BW$156:$BW$160),2) | BX161: ==ROUND(IFERROR(BV161/BW161,0),6) | CA161: Gesamteinnahmen in Periode | CB161: Durchschnittskurs: | CC161: ==ROUND(SUBTOTAL(109,$CC$156:$CC$160),2) | CD161: ==ROUND(SUBTOTAL(109,$CD$156:$CD$160),2) | CE161: ==ROUND(IFERROR(CC161/CD161,0),6) | CH161: Gesamteinnahmen in Periode | CI161: Durchschnittskurs: | CJ161: ==ROUND(SUBTOTAL(109,$CJ$156:$CJ$160),2) | CK161: ==ROUND(SUBTOTAL(109,$CK$156:$CK$160),2) | CL161: ==ROUND(IFERROR(CJ161/CK161,0),6) | CO161: Gesamteinnahmen in Periode | CP161: Durchschnittskurs: | CQ161: ==ROUND(SUBTOTAL(109,$CQ$156:$CQ$160),2) | CR161: ==ROUND(SUBTOTAL(109,$CR$156:$CR$160),2) | CS161: ==ROUND(IFERROR(CQ161/CR161,0),6) | CV161: Gesamteinnahmen in Periode | CW161: Durchschnittskurs: | CX161: ==ROUND(SUBTOTAL(109,$CX$156:$CX$160),2) | CY161: ==ROUND(SUBTOTAL(109,$CY$156:$CY$160),2) | CZ161: ==ROUND(IFERROR(CX161/CY161,0),6) | DC161: Gesamteinnahmen in Periode | DD161: Durchschnittskurs: | DE161: ==ROUND(SUBTOTAL(109,$DE$156:$DE$160),2) | DF161: ==ROUND(SUBTOTAL(109,$DF$156:$DF$160),2) | DG161: ==ROUND(IFERROR(DE161/DF161,0),6) | DJ161: Gesamteinnahmen in Periode | DK161: Durchschnittskurs: | DL161: ==ROUND(SUBTOTAL(109,$DL$156:$DL$160),2) | DM161: ==ROUND(SUBTOTAL(109,$DM$156:$DM$160),2) | DN161: ==ROUND(IFERROR(DL161/DM161,0),6) | DQ161: Gesamteinnahmen in Periode | DR161: Durchschnittskurs: | DS161: ==ROUND(SUBTOTAL(109,$DS$156:$DS$160),2) | DT161: ==ROUND(SUBTOTAL(109,$DT$156:$DT$160),2) | DU161: ==ROUND(IFERROR(DS161/DT161,0),6)
B163: Einnahmen (Durchschnittskurs) | I163: Einnahmen (Durchschnittskurs) | P163: Einnahmen (Durchschnittskurs) | W163: Einnahmen (Durchschnittskurs) | AD163: Einnahmen (Durchschnittskurs) | AK163: Einnahmen (Durchschnittskurs) | AR163: Einnahmen (Durchschnittskurs) | AY163: Einnahmen (Durchschnittskurs) | BF163: Einnahmen (Durchschnittskurs) | BM163: Einnahmen (Durchschnittskurs) | BT163: Einnahmen (Durchschnittskurs) | CA163: Einnahmen (Durchschnittskurs) | CH163: Einnahmen (Durchschnittskurs) | CO163: Einnahmen (Durchschnittskurs) | CV163: Einnahmen (Durchschnittskurs) | DC163: Einnahmen (Durchschnittskurs) | DJ163: Einnahmen (Durchschnittskurs) | DQ163: Einnahmen (Durchschnittskurs)
B164: Typ | C164: Geber | D164: Einnahmen (LC) | E164: Einnahmen (EUR) | F164: Kurs | I164: Typ | J164: Geber | K164: Einnahmen (LC) | L164: Einnahmen (EUR) | M164: Kurs | P164: Typ | Q164: Geber | R164: Einnahmen (LC) | S164: Einnahmen (EUR) | T164: Kurs | W164: Typ | X164: Geber | Y164: Einnahmen (LC) | Z164: Einnahmen (EUR) | AA164: Kurs | AD164: Typ | AE164: Geber | AF164: Einnahmen (LC) | AG164: Einnahmen (EUR) | AH164: Kurs | AK164: Typ | AL164: Geber | AM164: Einnahmen (LC) | AN164: Einnahmen (EUR) | AO164: Kurs | AR164: Typ | AS164: Geber | AT164: Einnahmen (LC) | AU164: Einnahmen (EUR) | AV164: Kurs | AY164: Typ | AZ164: Geber | BA164: Einnahmen (LC) | BB164: Einnahmen (EUR) | BC164: Kurs | BF164: Typ | BG164: Geber | BH164: Einnahmen (LC) | BI164: Einnahmen (EUR) | BJ164: Kurs | BM164: Typ | BN164: Geber | BO164: Einnahmen (LC) | BP164: Einnahmen (EUR) | BQ164: Kurs | BT164: Typ | BU164: Geber | BV164: Einnahmen (LC) | BW164: Einnahmen (EUR) | BX164: Kurs | CA164: Typ | CB164: Geber | CC164: Einnahmen (LC) | CD164: Einnahmen (EUR) | CE164: Kurs | CH164: Typ | CI164: Geber | CJ164: Einnahmen (LC) | CK164: Einnahmen (EUR) | CL164: Kurs | CO164: Typ | CP164: Geber | CQ164: Einnahmen (LC) | CR164: Einnahmen (EUR) | CS164: Kurs | CV164: Typ | CW164: Geber | CX164: Einnahmen (LC) | CY164: Einnahmen (EUR) | CZ164: Kurs | DC164: Typ | DD164: Geber | DE164: Einnahmen (LC) | DF164: Einnahmen (EUR) | DG164: Kurs | DJ164: Typ | DK164: Geber | DL164: Einnahmen (LC) | DM164: Einnahmen (EUR) | DN164: Kurs | DQ164: Typ | DR164: Geber | DS164: Einnahmen (LC) | DT164: Einnahmen (EUR) | DU164: Kurs
B165: Eigenmittel | E165: ==IFERROR(ROUND(D165/$C$8,2),0) | F165: ==ROUND(IFERROR(D165/E165,0),6) | I165: Eigenmittel | L165: ==IFERROR(ROUND(K165/$J$8,2),0) | M165: ==ROUND(IFERROR(K165/L165,0),6) | P165: Eigenmittel | S165: ==IFERROR(ROUND(R165/$Q$8,2),0) | T165: ==ROUND(IFERROR(R165/S165,0),6) | W165: Eigenmittel | Z165: ==IFERROR(ROUND(Y165/$X$8,2),0) | AA165: ==ROUND(IFERROR(Y165/Z165,0),6) | AD165: Eigenmittel | AG165: ==IFERROR(ROUND(AF165/$AE$8,2),0) | AH165: ==ROUND(IFERROR(AF165/AG165,0),6) | AK165: Eigenmittel | AN165: ==IFERROR(ROUND(AM165/$AL$8,2),0) | AO165: ==ROUND(IFERROR(AM165/AN165,0),6) | AR165: Eigenmittel | AU165: ==IFERROR(ROUND(AT165/$AS$8,2),0) | AV165: ==ROUND(IFERROR(AT165/AU165,0),6) | AY165: Eigenmittel | BB165: ==IFERROR(ROUND(BA165/$AZ$8,2),0) | BC165: ==ROUND(IFERROR(BA165/BB165,0),6) | BF165: Eigenmittel | BI165: ==IFERROR(ROUND(BH165/$BG$8,2),0) | BJ165: ==ROUND(IFERROR(BH165/BI165,0),6) | BM165: Eigenmittel | BP165: ==IFERROR(ROUND(BO165/$BN$8,2),0) | BQ165: ==ROUND(IFERROR(BO165/BP165,0),6) | BT165: Eigenmittel | BW165: ==IFERROR(ROUND(BV165/$BU$8,2),0) | BX165: ==ROUND(IFERROR(BV165/BW165,0),6) | CA165: Eigenmittel | CD165: ==IFERROR(ROUND(CC165/$CB$8,2),0) | CE165: ==ROUND(IFERROR(CC165/CD165,0),6) | CH165: Eigenmittel | CK165: ==IFERROR(ROUND(CJ165/$CI$8,2),0) | CL165: ==ROUND(IFERROR(CJ165/CK165,0),6) | CO165: Eigenmittel | CR165: ==IFERROR(ROUND(CQ165/$CP$8,2),0) | CS165: ==ROUND(IFERROR(CQ165/CR165,0),6) | CV165: Eigenmittel | CY165: ==IFERROR(ROUND(CX165/$CW$8,2),0) | CZ165: ==ROUND(IFERROR(CX165/CY165,0),6) | DC165: Eigenmittel | DF165: ==IFERROR(ROUND(DE165/$DD$8,2),0) | DG165: ==ROUND(IFERROR(DE165/DF165,0),6) | DJ165: Eigenmittel | DM165: ==IFERROR(ROUND(DL165/$DK$8,2),0) | DN165: ==ROUND(IFERROR(DL165/DM165,0),6) | DQ165: Eigenmittel | DT165: ==IFERROR(ROUND(DS165/$DR$8,2),0) | DU165: ==ROUND(IFERROR(DS165/DT165,0),6)
B166: Drittmittel | E166: ==IFERROR(ROUND(D166/$C$8,2),0) | F166: ==ROUND(IFERROR(D166/E166,0),6) | I166: Drittmittel | L166: ==IFERROR(ROUND(K166/$J$8,2),0) | M166: ==ROUND(IFERROR(K166/L166,0),6) | P166: Drittmittel | S166: ==IFERROR(ROUND(R166/$Q$8,2),0) | T166: ==ROUND(IFERROR(R166/S166,0),6) | W166: Drittmittel | Z166: ==IFERROR(ROUND(Y166/$X$8,2),0) | AA166: ==ROUND(IFERROR(Y166/Z166,0),6) | AD166: Drittmittel | AG166: ==IFERROR(ROUND(AF166/$AE$8,2),0) | AH166: ==ROUND(IFERROR(AF166/AG166,0),6) | AK166: Drittmittel | AN166: ==IFERROR(ROUND(AM166/$AL$8,2),0) | AO166: ==ROUND(IFERROR(AM166/AN166,0),6) | AR166: Drittmittel | AU166: ==IFERROR(ROUND(AT166/$AS$8,2),0) | AV166: ==ROUND(IFERROR(AT166/AU166,0),6) | AY166: Drittmittel | BB166: ==IFERROR(ROUND(BA166/$AZ$8,2),0) | BC166: ==ROUND(IFERROR(BA166/BB166,0),6) | BF166: Drittmittel | BI166: ==IFERROR(ROUND(BH166/$BG$8,2),0) | BJ166: ==ROUND(IFERROR(BH166/BI166,0),6) | BM166: Drittmittel | BP166: ==IFERROR(ROUND(BO166/$BN$8,2),0) | BQ166: ==ROUND(IFERROR(BO166/BP166,0),6) | BT166: Drittmittel | BW166: ==IFERROR(ROUND(BV166/$BU$8,2),0) | BX166: ==ROUND(IFERROR(BV166/BW166,0),6) | CA166: Drittmittel | CD166: ==IFERROR(ROUND(CC166/$CB$8,2),0) | CE166: ==ROUND(IFERROR(CC166/CD166,0),6) | CH166: Drittmittel | CK166: ==IFERROR(ROUND(CJ166/$CI$8,2),0) | CL166: ==ROUND(IFERROR(CJ166/CK166,0),6) | CO166: Drittmittel | CR166: ==IFERROR(ROUND(CQ166/$CP$8,2),0) | CS166: ==ROUND(IFERROR(CQ166/CR166,0),6) | CV166: Drittmittel | CY166: ==IFERROR(ROUND(CX166/$CW$8,2),0) | CZ166: ==ROUND(IFERROR(CX166/CY166,0),6) | DC166: Drittmittel | DF166: ==IFERROR(ROUND(DE166/$DD$8,2),0) | DG166: ==ROUND(IFERROR(DE166/DF166,0),6) | DJ166: Drittmittel | DM166: ==IFERROR(ROUND(DL166/$DK$8,2),0) | DN166: ==ROUND(IFERROR(DL166/DM166,0),6) | DQ166: Drittmittel | DT166: ==IFERROR(ROUND(DS166/$DR$8,2),0) | DU166: ==ROUND(IFERROR(DS166/DT166,0),6)
B167: Zinsertraege | E167: ==IFERROR(ROUND(D167/$C$8,2),0) | F167: ==ROUND(IFERROR(D167/E167,0),6) | I167: Zinsertraege | L167: ==IFERROR(ROUND(K167/$J$8,2),0) | M167: ==ROUND(IFERROR(K167/L167,0),6) | P167: Zinsertraege | S167: ==IFERROR(ROUND(R167/$Q$8,2),0) | T167: ==ROUND(IFERROR(R167/S167,0),6) | W167: Zinsertraege | Z167: ==IFERROR(ROUND(Y167/$X$8,2),0) | AA167: ==ROUND(IFERROR(Y167/Z167,0),6) | AD167: Zinsertraege | AG167: ==IFERROR(ROUND(AF167/$AE$8,2),0) | AH167: ==ROUND(IFERROR(AF167/AG167,0),6) | AK167: Zinsertraege | AN167: ==IFERROR(ROUND(AM167/$AL$8,2),0) | AO167: ==ROUND(IFERROR(AM167/AN167,0),6) | AR167: Zinsertraege | AU167: ==IFERROR(ROUND(AT167/$AS$8,2),0) | AV167: ==ROUND(IFERROR(AT167/AU167,0),6) | AY167: Zinsertraege | BB167: ==IFERROR(ROUND(BA167/$AZ$8,2),0) | BC167: ==ROUND(IFERROR(BA167/BB167,0),6) | BF167: Zinsertraege | BI167: ==IFERROR(ROUND(BH167/$BG$8,2),0) | BJ167: ==ROUND(IFERROR(BH167/BI167,0),6) | BM167: Zinsertraege | BP167: ==IFERROR(ROUND(BO167/$BN$8,2),0) | BQ167: ==ROUND(IFERROR(BO167/BP167,0),6) | BT167: Zinsertraege | BW167: ==IFERROR(ROUND(BV167/$BU$8,2),0) | BX167: ==ROUND(IFERROR(BV167/BW167,0),6) | CA167: Zinsertraege | CD167: ==IFERROR(ROUND(CC167/$CB$8,2),0) | CE167: ==ROUND(IFERROR(CC167/CD167,0),6) | CH167: Zinsertraege | CK167: ==IFERROR(ROUND(CJ167/$CI$8,2),0) | CL167: ==ROUND(IFERROR(CJ167/CK167,0),6) | CO167: Zinsertraege | CR167: ==IFERROR(ROUND(CQ167/$CP$8,2),0) | CS167: ==ROUND(IFERROR(CQ167/CR167,0),6) | CV167: Zinsertraege | CY167: ==IFERROR(ROUND(CX167/$CW$8,2),0) | CZ167: ==ROUND(IFERROR(CX167/CY167,0),6) | DC167: Zinsertraege | DF167: ==IFERROR(ROUND(DE167/$DD$8,2),0) | DG167: ==ROUND(IFERROR(DE167/DF167,0),6) | DJ167: Zinsertraege | DM167: ==IFERROR(ROUND(DL167/$DK$8,2),0) | DN167: ==ROUND(IFERROR(DL167/DM167,0),6) | DQ167: Zinsertraege | DT167: ==IFERROR(ROUND(DS167/$DR$8,2),0) | DU167: ==ROUND(IFERROR(DS167/DT167,0),6)
E168: ==IFERROR(ROUND(D168/$C$8,2),0) | F168: ==ROUND(IFERROR(D168/E168,0),6) | L168: ==IFERROR(ROUND(K168/$J$8,2),0) | M168: ==ROUND(IFERROR(K168/L168,0),6) | S168: ==IFERROR(ROUND(R168/$Q$8,2),0) | T168: ==ROUND(IFERROR(R168/S168,0),6) | Z168: ==IFERROR(ROUND(Y168/$X$8,2),0) | AA168: ==ROUND(IFERROR(Y168/Z168,0),6) | AG168: ==IFERROR(ROUND(AF168/$AE$8,2),0) | AH168: ==ROUND(IFERROR(AF168/AG168,0),6) | AN168: ==IFERROR(ROUND(AM168/$AL$8,2),0) | AO168: ==ROUND(IFERROR(AM168/AN168,0),6) | AU168: ==IFERROR(ROUND(AT168/$AS$8,2),0) | AV168: ==ROUND(IFERROR(AT168/AU168,0),6) | BB168: ==IFERROR(ROUND(BA168/$AZ$8,2),0) | BC168: ==ROUND(IFERROR(BA168/BB168,0),6) | BI168: ==IFERROR(ROUND(BH168/$BG$8,2),0) | BJ168: ==ROUND(IFERROR(BH168/BI168,0),6) | BP168: ==IFERROR(ROUND(BO168/$BN$8,2),0) | BQ168: ==ROUND(IFERROR(BO168/BP168,0),6) | BW168: ==IFERROR(ROUND(BV168/$BU$8,2),0) | BX168: ==ROUND(IFERROR(BV168/BW168,0),6) | CD168: ==IFERROR(ROUND(CC168/$CB$8,2),0) | CE168: ==ROUND(IFERROR(CC168/CD168,0),6) | CK168: ==IFERROR(ROUND(CJ168/$CI$8,2),0) | CL168: ==ROUND(IFERROR(CJ168/CK168,0),6) | CR168: ==IFERROR(ROUND(CQ168/$CP$8,2),0) | CS168: ==ROUND(IFERROR(CQ168/CR168,0),6) | CY168: ==IFERROR(ROUND(CX168/$CW$8,2),0) | CZ168: ==ROUND(IFERROR(CX168/CY168,0),6) | DF168: ==IFERROR(ROUND(DE168/$DD$8,2),0) | DG168: ==ROUND(IFERROR(DE168/DF168,0),6) | DM168: ==IFERROR(ROUND(DL168/$DK$8,2),0) | DN168: ==ROUND(IFERROR(DL168/DM168,0),6) | DT168: ==IFERROR(ROUND(DS168/$DR$8,2),0) | DU168: ==ROUND(IFERROR(DS168/DT168,0),6)
E169: ==IFERROR(ROUND(D169/$C$8,2),0) | F169: ==ROUND(IFERROR(D169/E169,0),6) | L169: ==IFERROR(ROUND(K169/$J$8,2),0) | M169: ==ROUND(IFERROR(K169/L169,0),6) | S169: ==IFERROR(ROUND(R169/$Q$8,2),0) | T169: ==ROUND(IFERROR(R169/S169,0),6) | Z169: ==IFERROR(ROUND(Y169/$X$8,2),0) | AA169: ==ROUND(IFERROR(Y169/Z169,0),6) | AG169: ==IFERROR(ROUND(AF169/$AE$8,2),0) | AH169: ==ROUND(IFERROR(AF169/AG169,0),6) | AN169: ==IFERROR(ROUND(AM169/$AL$8,2),0) | AO169: ==ROUND(IFERROR(AM169/AN169,0),6) | AU169: ==IFERROR(ROUND(AT169/$AS$8,2),0) | AV169: ==ROUND(IFERROR(AT169/AU169,0),6) | BB169: ==IFERROR(ROUND(BA169/$AZ$8,2),0) | BC169: ==ROUND(IFERROR(BA169/BB169,0),6) | BI169: ==IFERROR(ROUND(BH169/$BG$8,2),0) | BJ169: ==ROUND(IFERROR(BH169/BI169,0),6) | BP169: ==IFERROR(ROUND(BO169/$BN$8,2),0) | BQ169: ==ROUND(IFERROR(BO169/BP169,0),6) | BW169: ==IFERROR(ROUND(BV169/$BU$8,2),0) | BX169: ==ROUND(IFERROR(BV169/BW169,0),6) | CD169: ==IFERROR(ROUND(CC169/$CB$8,2),0) | CE169: ==ROUND(IFERROR(CC169/CD169,0),6) | CK169: ==IFERROR(ROUND(CJ169/$CI$8,2),0) | CL169: ==ROUND(IFERROR(CJ169/CK169,0),6) | CR169: ==IFERROR(ROUND(CQ169/$CP$8,2),0) | CS169: ==ROUND(IFERROR(CQ169/CR169,0),6) | CY169: ==IFERROR(ROUND(CX169/$CW$8,2),0) | CZ169: ==ROUND(IFERROR(CX169/CY169,0),6) | DF169: ==IFERROR(ROUND(DE169/$DD$8,2),0) | DG169: ==ROUND(IFERROR(DE169/DF169,0),6) | DM169: ==IFERROR(ROUND(DL169/$DK$8,2),0) | DN169: ==ROUND(IFERROR(DL169/DM169,0),6) | DT169: ==IFERROR(ROUND(DS169/$DR$8,2),0) | DU169: ==ROUND(IFERROR(DS169/DT169,0),6)
E170: ==IFERROR(ROUND(D170/$C$8,2),0) | F170: ==ROUND(IFERROR(D170/E170,0),6) | L170: ==IFERROR(ROUND(K170/$J$8,2),0) | M170: ==ROUND(IFERROR(K170/L170,0),6) | S170: ==IFERROR(ROUND(R170/$Q$8,2),0) | T170: ==ROUND(IFERROR(R170/S170,0),6) | Z170: ==IFERROR(ROUND(Y170/$X$8,2),0) | AA170: ==ROUND(IFERROR(Y170/Z170,0),6) | AG170: ==IFERROR(ROUND(AF170/$AE$8,2),0) | AH170: ==ROUND(IFERROR(AF170/AG170,0),6) | AN170: ==IFERROR(ROUND(AM170/$AL$8,2),0) | AO170: ==ROUND(IFERROR(AM170/AN170,0),6) | AU170: ==IFERROR(ROUND(AT170/$AS$8,2),0) | AV170: ==ROUND(IFERROR(AT170/AU170,0),6) | BB170: ==IFERROR(ROUND(BA170/$AZ$8,2),0) | BC170: ==ROUND(IFERROR(BA170/BB170,0),6) | BI170: ==IFERROR(ROUND(BH170/$BG$8,2),0) | BJ170: ==ROUND(IFERROR(BH170/BI170,0),6) | BP170: ==IFERROR(ROUND(BO170/$BN$8,2),0) | BQ170: ==ROUND(IFERROR(BO170/BP170,0),6) | BW170: ==IFERROR(ROUND(BV170/$BU$8,2),0) | BX170: ==ROUND(IFERROR(BV170/BW170,0),6) | CD170: ==IFERROR(ROUND(CC170/$CB$8,2),0) | CE170: ==ROUND(IFERROR(CC170/CD170,0),6) | CK170: ==IFERROR(ROUND(CJ170/$CI$8,2),0) | CL170: ==ROUND(IFERROR(CJ170/CK170,0),6) | CR170: ==IFERROR(ROUND(CQ170/$CP$8,2),0) | CS170: ==ROUND(IFERROR(CQ170/CR170,0),6) | CY170: ==IFERROR(ROUND(CX170/$CW$8,2),0) | CZ170: ==ROUND(IFERROR(CX170/CY170,0),6) | DF170: ==IFERROR(ROUND(DE170/$DD$8,2),0) | DG170: ==ROUND(IFERROR(DE170/DF170,0),6) | DM170: ==IFERROR(ROUND(DL170/$DK$8,2),0) | DN170: ==ROUND(IFERROR(DL170/DM170,0),6) | DT170: ==IFERROR(ROUND(DS170/$DR$8,2),0) | DU170: ==ROUND(IFERROR(DS170/DT170,0),6)
B171: Gesamt (Durchschnittskurs) | C171: Durchschnittskurs: | D171: ==ROUND(SUBTOTAL(109,$D$165:$D$170),2) | E171: ==ROUND(SUBTOTAL(109,$E$165:$E$170),2) | F171: ==ROUND(IFERROR(D171/E171,0),6) | I171: Gesamt (Durchschnittskurs) | J171: Durchschnittskurs: | K171: ==ROUND(SUBTOTAL(109,$K$165:$K$170),2) | L171: ==ROUND(SUBTOTAL(109,$L$165:$L$170),2) | M171: ==ROUND(IFERROR(K171/L171,0),6) | P171: Gesamt (Durchschnittskurs) | Q171: Durchschnittskurs: | R171: ==ROUND(SUBTOTAL(109,$R$165:$R$170),2) | S171: ==ROUND(SUBTOTAL(109,$S$165:$S$170),2) | T171: ==ROUND(IFERROR(R171/S171,0),6) | W171: Gesamt (Durchschnittskurs) | X171: Durchschnittskurs: | Y171: ==ROUND(SUBTOTAL(109,$Y$165:$Y$170),2) | Z171: ==ROUND(SUBTOTAL(109,$Z$165:$Z$170),2) | AA171: ==ROUND(IFERROR(Y171/Z171,0),6) | AD171: Gesamt (Durchschnittskurs) | AE171: Durchschnittskurs: | AF171: ==ROUND(SUBTOTAL(109,$AF$165:$AF$170),2) | AG171: ==ROUND(SUBTOTAL(109,$AG$165:$AG$170),2) | AH171: ==ROUND(IFERROR(AF171/AG171,0),6) | AK171: Gesamt (Durchschnittskurs) | AL171: Durchschnittskurs: | AM171: ==ROUND(SUBTOTAL(109,$AM$165:$AM$170),2) | AN171: ==ROUND(SUBTOTAL(109,$AN$165:$AN$170),2) | AO171: ==ROUND(IFERROR(AM171/AN171,0),6) | AR171: Gesamt (Durchschnittskurs) | AS171: Durchschnittskurs: | AT171: ==ROUND(SUBTOTAL(109,$AT$165:$AT$170),2) | AU171: ==ROUND(SUBTOTAL(109,$AU$165:$AU$170),2) | AV171: ==ROUND(IFERROR(AT171/AU171,0),6) | AY171: Gesamt (Durchschnittskurs) | AZ171: Durchschnittskurs: | BA171: ==ROUND(SUBTOTAL(109,$BA$165:$BA$170),2) | BB171: ==ROUND(SUBTOTAL(109,$BB$165:$BB$170),2) | BC171: ==ROUND(IFERROR(BA171/BB171,0),6) | BF171: Gesamt (Durchschnittskurs) | BG171: Durchschnittskurs: | BH171: ==ROUND(SUBTOTAL(109,$BH$165:$BH$170),2) | BI171: ==ROUND(SUBTOTAL(109,$BI$165:$BI$170),2) | BJ171: ==ROUND(IFERROR(BH171/BI171,0),6) | BM171: Gesamt (Durchschnittskurs) | BN171: Durchschnittskurs: | BO171: ==ROUND(SUBTOTAL(109,$BO$165:$BO$170),2) | BP171: ==ROUND(SUBTOTAL(109,$BP$165:$BP$170),2) | BQ171: ==ROUND(IFERROR(BO171/BP171,0),6) | BT171: Gesamt (Durchschnittskurs) | BU171: Durchschnittskurs: | BV171: ==ROUND(SUBTOTAL(109,$BV$165:$BV$170),2) | BW171: ==ROUND(SUBTOTAL(109,$BW$165:$BW$170),2) | BX171: ==ROUND(IFERROR(BV171/BW171,0),6) | CA171: Gesamt (Durchschnittskurs) | CB171: Durchschnittskurs: | CC171: ==ROUND(SUBTOTAL(109,$CC$165:$CC$170),2) | CD171: ==ROUND(SUBTOTAL(109,$CD$165:$CD$170),2) | CE171: ==ROUND(IFERROR(CC171/CD171,0),6) | CH171: Gesamt (Durchschnittskurs) | CI171: Durchschnittskurs: | CJ171: ==ROUND(SUBTOTAL(109,$CJ$165:$CJ$170),2) | CK171: ==ROUND(SUBTOTAL(109,$CK$165:$CK$170),2) | CL171: ==ROUND(IFERROR(CJ171/CK171,0),6) | CO171: Gesamt (Durchschnittskurs) | CP171: Durchschnittskurs: | CQ171: ==ROUND(SUBTOTAL(109,$CQ$165:$CQ$170),2) | CR171: ==ROUND(SUBTOTAL(109,$CR$165:$CR$170),2) | CS171: ==ROUND(IFERROR(CQ171/CR171,0),6) | CV171: Gesamt (Durchschnittskurs) | CW171: Durchschnittskurs: | CX171: ==ROUND(SUBTOTAL(109,$CX$165:$CX$170),2) | CY171: ==ROUND(SUBTOTAL(109,$CY$165:$CY$170),2) | CZ171: ==ROUND(IFERROR(CX171/CY171,0),6) | DC171: Gesamt (Durchschnittskurs) | DD171: Durchschnittskurs: | DE171: ==ROUND(SUBTOTAL(109,$DE$165:$DE$170),2) | DF171: ==ROUND(SUBTOTAL(109,$DF$165:$DF$170),2) | DG171: ==ROUND(IFERROR(DE171/DF171,0),6) | DJ171: Gesamt (Durchschnittskurs) | DK171: Durchschnittskurs: | DL171: ==ROUND(SUBTOTAL(109,$DL$165:$DL$170),2) | DM171: ==ROUND(SUBTOTAL(109,$DM$165:$DM$170),2) | DN171: ==ROUND(IFERROR(DL171/DM171,0),6) | DQ171: Gesamt (Durchschnittskurs) | DR171: Durchschnittskurs: | DS171: ==ROUND(SUBTOTAL(109,$DS$165:$DS$170),2) | DT171: ==ROUND(SUBTOTAL(109,$DT$165:$DT$170),2) | DU171: ==ROUND(IFERROR(DS171/DT171,0),6)

Sheet IV. MA
E3: ➤ | I3: ➤ | M3: ➤ | Q3: ➤ | U3: ➤ | Y3: ➤ | AC3: ➤ | AG3: ➤ | AK3: ➤ | AO3: ➤ | AS3: ➤ | AW3: ➤ | BA3: ➤ | BE3: ➤ | BI3: ➤ | BM3: ➤ | BQ3: ➤
B4: Periode: | C4: Periode 1 | F4: Periode: | G4: Periode 2 | J4: Periode: | K4: Periode 3 | N4: Periode: | O4: Periode 4 | R4: Periode: | S4: Periode 5 | V4: Periode: | W4: Periode 6 | Z4: Periode: | AA4: Periode 7 | AD4: Periode: | AE4: Periode 8 | AH4: Periode: | AI4: Periode 9 | AL4: Periode: | AM4: Periode 10 | AP4: Periode: | AQ4: Periode 11 | AT4: Periode: | AU4: Periode 12 | AX4: Periode: | AY4: Periode 13 | BB4: Periode: | BC4: Periode 14 | BF4: Periode: | BG4: Periode 15 | BJ4: Periode: | BK4: Periode 16 | BN4: Periode: | BO4: Periode 17 | BR4: Periode: | BS4: Periode 18
B5: Von: | F5: Von: | J5: Von: | N5: Von: | R5: Von: | V5: Von: | Z5: Von: | AD5: Von: | AH5: Von: | AL5: Von: | AP5: Von: | AT5: Von: | AX5: Von: | BB5: Von: | BF5: Von: | BJ5: Von: | BN5: Von: | BR5: Von:
B6: Bis: | F6: Bis: | J6: Bis: | N6: Bis: | R6: Bis: | V6: Bis: | Z6: Bis: | AD6: Bis: | AH6: Bis: | AL6: Bis: | AP6: Bis: | AT6: Bis: | AX6: Bis: | BB6: Bis: | BF6: Bis: | BJ6: Bis: | BN6: Bis: | BR6: Bis:
B7: Zeitraum: | C7: ==IF(OR(C5="",C6=""),"",DATEDIF(C5,C6,"m")+1) | F7: Zeitraum: | G7: ==IF(OR(G5="",G6=""),"",DATEDIF(G5,G6,"m")+1) | J7: Zeitraum: | K7: ==IF(OR(K5="",K6=""),"",DATEDIF(K5,K6,"m")+1) | N7: Zeitraum: | O7: ==IF(OR(O5="",O6=""),"",DATEDIF(O5,O6,"m")+1) | R7: Zeitraum: | S7: ==IF(OR(S5="",S6=""),"",DATEDIF(S5,S6,"m")+1) | V7: Zeitraum: | W7: ==IF(OR(W5="",W6=""),"",DATEDIF(W5,W6,"m")+1) | Z7: Zeitraum: | AA7: ==IF(OR(AA5="",AA6=""),"",DATEDIF(AA5,AA6,"m")+1) | AD7: Zeitraum: | AE7: ==IF(OR(AE5="",AE6=""),"",DATEDIF(AE5,AE6,"m")+1) | AH7: Zeitraum: | AI7: ==IF(OR(AI5="",AI6=""),"",DATEDIF(AI5,AI6,"m")+1) | AL7: Zeitraum: | AM7: ==IF(OR(AM5="",AM6=""),"",DATEDIF(AM5,AM6,"m")+1) | AP7: Zeitraum: | AQ7: ==IF(OR(AQ5="",AQ6=""),"",DATEDIF(AQ5,AQ6,"m")+1) | AT7: Zeitraum: | AU7: ==IF(OR(AU5="",AU6=""),"",DATEDIF(AU5,AU6,"m")+1) | AX7: Zeitraum: | AY7: ==IF(OR(AY5="",AY6=""),"",DATEDIF(AY5,AY6,"m")+1) | BB7: Zeitraum: | BC7: ==IF(OR(BC5="",BC6=""),"",DATEDIF(BC5,BC6,"m")+1) | BF7: Zeitraum: | BG7: ==IF(OR(BG5="",BG6=""),"",DATEDIF(BG5,BG6,"m")+1) | BJ7: Zeitraum: | BK7: ==IF(OR(BK5="",BK6=""),"",DATEDIF(BK5,BK6,"m")+1) | BN7: Zeitraum: | BO7: ==IF(OR(BO5="",BO6=""),"",DATEDIF(BO5,BO6,"m")+1) | BR7: Zeitraum: | BS7: ==IF(OR(BS5="",BS6=""),"",DATEDIF(BS5,BS6,"m")+1)
B8: OANDA-Kurs: | F8: OANDA-Kurs: | J8: OANDA-Kurs: | N8: OANDA-Kurs: | R8: OANDA-Kurs: | V8: OANDA-Kurs: | Z8: OANDA-Kurs: | AD8: OANDA-Kurs: | AH8: OANDA-Kurs: | AL8: OANDA-Kurs: | AP8: OANDA-Kurs: | AT8: OANDA-Kurs: | AX8: OANDA-Kurs: | BB8: OANDA-Kurs: | BF8: OANDA-Kurs: | BJ8: OANDA-Kurs: | BN8: OANDA-Kurs: | BR8: OANDA-Kurs:
B9: Kostenkategorie | C9: Angefordert (LC) | D9: Angefordert (EUR) | F9: Kostenkategorie | G9: Angefordert (LC) | H9: Angefordert (EUR) | J9: Kostenkategorie | K9: Angefordert (LC) | L9: Angefordert (EUR) | N9: Kostenkategorie | O9: Angefordert (LC) | P9: Angefordert (EUR) | R9: Kostenkategorie | S9: Angefordert (LC) | T9: Angefordert (EUR) | V9: Kostenkategorie | W9: Angefordert (LC) | X9: Angefordert (EUR) | Z9: Kostenkategorie | AA9: Angefordert (LC) | AB9: Angefordert (EUR) | AD9: Kostenkategorie | AE9: Angefordert (LC) | AF9: Angefordert (EUR) | AH9: Kostenkategorie | AI9: Angefordert (LC) | AJ9: Angefordert (EUR) | AL9: Kostenkategorie | AM9: Angefordert (LC) | AN9: Angefordert (EUR) | AP9: Kostenkategorie | AQ9: Angefordert (LC) | AR9: Angefordert (EUR) | AT9: Kostenkategorie | AU9: Angefordert (LC) | AV9: Angefordert (EUR) | AX9: Kostenkategorie | AY9: Angefordert (LC) | AZ9: Angefordert (EUR) | BB9: Kostenkategorie | BC9: Angefordert (LC) | BD9: Angefordert (EUR) | BF9: Kostenkategorie | BG9: Angefordert (LC) | BH9: Angefordert (EUR) | BJ9: Kostenkategorie | BK9: Angefordert (LC) | BL9: Angefordert (EUR) | BN9: Kostenkategorie | BO9: Angefordert (LC) | BP9: Angefordert (EUR) | BR9: Kostenkategorie | BS9: Angefordert (LC) | BT9: Angefordert (EUR)
B10: Bauausgaben | D10: ==IFERROR(ROUND(C10/MA_Kurs_1,2),0) | F10: Bauausgaben | H10: ==IFERROR(ROUND(G10/MA_Kurs_2,2),0) | J10: Bauausgaben | L10: ==IFERROR(ROUND(K10/MA_Kurs_3,2),0) | N10: Bauausgaben | P10: ==IFERROR(ROUND(O10/MA_Kurs_4,2),0) | R10: Bauausgaben | T10: ==IFERROR(ROUND(S10/MA_Kurs_5,2),0) | V10: Bauausgaben | X10: ==IFERROR(ROUND(W10/MA_Kurs_6,2),0) | Z10: Bauausgaben | AB10: ==IFERROR(ROUND(AA10/MA_Kurs_7,2),0) | AD10: Bauausgaben | AF10: ==IFERROR(ROUND(AE10/MA_Kurs_8,2),0) | AH10: Bauausgaben | AJ10: ==IFERROR(ROUND(AI10/MA_Kurs_9,2),0) | AL10: Bauausgaben | AN10: ==IFERROR(ROUND(AM10/MA_Kurs_10,2),0) | AP10: Bauausgaben | AR10: ==IFERROR(ROUND(AQ10/MA_Kurs_11,2),0) | AT10: Bauausgaben | AV10: ==IFERROR(ROUND(AU10/MA_Kurs_12,2),0) | AX10: Bauausgaben | AZ10: ==IFERROR(ROUND(AY10/MA_Kurs_13,2),0) | BB10: Bauausgaben | BD10: ==IFERROR(ROUND(BC10/MA_Kurs_14,2),0) | BF10: Bauausgaben | BH10: ==IFERROR(ROUND(BG10/MA_Kurs_15,2),0) | BJ10: Bauausgaben | BL10: ==IFERROR(ROUND(BK10/MA_Kurs_16,2),0) | BN10: Bauausgaben | BP10: ==IFERROR(ROUND(BO10/MA_Kurs_17,2),0) | BR10: Bauausgaben | BT10: ==IFERROR(ROUND(BS10/MA_Kurs_18,2),0)
B11: Investitionen | D11: ==IFERROR(ROUND(C11/MA_Kurs_1,2),0) | F11: Investitionen | H11: ==IFERROR(ROUND(G11/MA_Kurs_2,2),0) | J11: Investitionen | L11: ==IFERROR(ROUND(K11/MA_Kurs_3,2),0) | N11: Investitionen | P11: ==IFERROR(ROUND(O11/MA_Kurs_4,2),0) | R11: Investitionen | T11: ==IFERROR(ROUND(S11/MA_Kurs_5,2),0) | V11: Investitionen | X11: ==IFERROR(ROUND(W11/MA_Kurs_6,2),0) | Z11: Investitionen | AB11: ==IFERROR(ROUND(AA11/MA_Kurs_7,2),0) | AD11: Investitionen | AF11: ==IFERROR(ROUND(AE11/MA_Kurs_8,2),0) | AH11: Investitionen | AJ11: ==IFERROR(ROUND(AI11/MA_Kurs_9,2),0) | AL11: Investitionen | AN11: ==IFERROR(ROUND(AM11/MA_Kurs_10,2),0) | AP11: Investitionen | AR11: ==IFERROR(ROUND(AQ11/MA_Kurs_11,2),0) | AT11: Investitionen | AV11: ==IFERROR(ROUND(AU11/MA_Kurs_12,2),0) | AX11: Investitionen | AZ11: ==IFERROR(ROUND(AY11/MA_Kurs_13,2),0) | BB11: Investitionen | BD11: ==IFERROR(ROUND(BC11/MA_Kurs_14,2),0) | BF11: Investitionen | BH11: ==IFERROR(ROUND(BG11/MA_Kurs_15,2),0) | BJ11: Investitionen | BL11: ==IFERROR(ROUND(BK11/MA_Kurs_16,2),0) | BN11: Investitionen | BP11: ==IFERROR(ROUND(BO11/MA_Kurs_17,2),0) | BR11: Investitionen | BT11: ==IFERROR(ROUND(BS11/MA_Kurs_18,2),0)
B12: Personalkosten | D12: ==IFERROR(ROUND(C12/MA_Kurs_1,2),0) | F12: Personalkosten | H12: ==IFERROR(ROUND(G12/MA_Kurs_2,2),0) | J12: Personalkosten | L12: ==IFERROR(ROUND(K12/MA_Kurs_3,2),0) | N12: Personalkosten | P12: ==IFERROR(ROUND(O12/MA_Kurs_4,2),0) | R12: Personalkosten | T12: ==IFERROR(ROUND(S12/MA_Kurs_5,2),0) | V12: Personalkosten | X12: ==IFERROR(ROUND(W12/MA_Kurs_6,2),0) | Z12: Personalkosten | AB12: ==IFERROR(ROUND(AA12/MA_Kurs_7,2),0) | AD12: Personalkosten | AF12: ==IFERROR(ROUND(AE12/MA_Kurs_8,2),0) | AH12: Personalkosten | AJ12: ==IFERROR(ROUND(AI12/MA_Kurs_9,2),0) | AL12: Personalkosten | AN12: ==IFERROR(ROUND(AM12/MA_Kurs_10,2),0) | AP12: Personalkosten | AR12: ==IFERROR(ROUND(AQ12/MA_Kurs_11,2),0) | AT12: Personalkosten | AV12: ==IFERROR(ROUND(AU12/MA_Kurs_12,2),0) | AX12: Personalkosten | AZ12: ==IFERROR(ROUND(AY12/MA_Kurs_13,2),0) | BB12: Personalkosten | BD12: ==IFERROR(ROUND(BC12/MA_Kurs_14,2),0) | BF12: Personalkosten | BH12: ==IFERROR(ROUND(BG12/MA_Kurs_15,2),0) | BJ12: Personalkosten | BL12: ==IFERROR(ROUND(BK12/MA_Kurs_16,2),0) | BN12: Personalkosten | BP12: ==IFERROR(ROUND(BO12/MA_Kurs_17,2),0) | BR12: Personalkosten | BT12: ==IFERROR(ROUND(BS12/MA_Kurs_18,2),0)
B13: Projektaktivitaeten | D13: ==IFERROR(ROUND(C13/MA_Kurs_1,2),0) | F13: Projektaktivitaeten | H13: ==IFERROR(ROUND(G13/MA_Kurs_2,2),0) | J13: Projektaktivitaeten | L13: ==IFERROR(ROUND(K13/MA_Kurs_3,2),0) | N13: Projektaktivitaeten | P13: ==IFERROR(ROUND(O13/MA_Kurs_4,2),0) | R13: Projektaktivitaeten | T13: ==IFERROR(ROUND(S13/MA_Kurs_5,2),0) | V13: Projektaktivitaeten | X13: ==IFERROR(ROUND(W13/MA_Kurs_6,2),0) | Z13: Projektaktivitaeten | AB13: ==IFERROR(ROUND(AA13/MA_Kurs_7,2),0) | AD13: Projektaktivitaeten | AF13: ==IFERROR(ROUND(AE13/MA_Kurs_8,2),0) | AH13: Projektaktivitaeten | AJ13: ==IFERROR(ROUND(AI13/MA_Kurs_9,2),0) | AL13: Projektaktivitaeten | AN13: ==IFERROR(ROUND(AM13/MA_Kurs_10,2),0) | AP13: Projektaktivitaeten | AR13: ==IFERROR(ROUND(AQ13/MA_Kurs_11,2),0) | AT13: Projektaktivitaeten | AV13: ==IFERROR(ROUND(AU13/MA_Kurs_12,2),0) | AX13: Projektaktivitaeten | AZ13: ==IFERROR(ROUND(AY13/MA_Kurs_13,2),0) | BB13: Projektaktivitaeten | BD13: ==IFERROR(ROUND(BC13/MA_Kurs_14,2),0) | BF13: Projektaktivitaeten | BH13: ==IFERROR(ROUND(BG13/MA_Kurs_15,2),0) | BJ13: Projektaktivitaeten | BL13: ==IFERROR(ROUND(BK13/MA_Kurs_16,2),0) | BN13: Projektaktivitaeten | BP13: ==IFERROR(ROUND(BO13/MA_Kurs_17,2),0) | BR13: Projektaktivitaeten | BT13: ==IFERROR(ROUND(BS13/MA_Kurs_18,2),0)
B14: Projektverwaltung | D14: ==IFERROR(ROUND(C14/MA_Kurs_1,2),0) | F14: Projektverwaltung | H14: ==IFERROR(ROUND(G14/MA_Kurs_2,2),0) | J14: Projektverwaltung | L14: ==IFERROR(ROUND(K14/MA_Kurs_3,2),0) | N14: Projektverwaltung | P14: ==IFERROR(ROUND(O14/MA_Kurs_4,2),0) | R14: Projektverwaltung | T14: ==IFERROR(ROUND(S14/MA_Kurs_5,2),0) | V14: Projektverwaltung | X14: ==IFERROR(ROUND(W14/MA_Kurs_6,2),0) | Z14: Projektverwaltung | AB14: ==IFERROR(ROUND(AA14/MA_Kurs_7,2),0) | AD14: Projektverwaltung | AF14: ==IFERROR(ROUND(AE14/MA_Kurs_8,2),0) | AH14: Projektverwaltung | AJ14: ==IFERROR(ROUND(AI14/MA_Kurs_9,2),0) | AL14: Projektverwaltung | AN14: ==IFERROR(ROUND(AM14/MA_Kurs_10,2),0) | AP14: Projektverwaltung | AR14: ==IFERROR(ROUND(AQ14/MA_Kurs_11,2),0) | AT14: Projektverwaltung | AV14: ==IFERROR(ROUND(AU14/MA_Kurs_12,2),0) | AX14: Projektverwaltung | AZ14: ==IFERROR(ROUND(AY14/MA_Kurs_13,2),0) | BB14: Projektverwaltung | BD14: ==IFERROR(ROUND(BC14/MA_Kurs_14,2),0) | BF14: Projektverwaltung | BH14: ==IFERROR(ROUND(BG14/MA_Kurs_15,2),0) | BJ14: Projektverwaltung | BL14: ==IFERROR(ROUND(BK14/MA_Kurs_16,2),0) | BN14: Projektverwaltung | BP14: ==IFERROR(ROUND(BO14/MA_Kurs_17,2),0) | BR14: Projektverwaltung | BT14: ==IFERROR(ROUND(BS14/MA_Kurs_18,2),0)
B15: Evaluierung | D15: ==IFERROR(ROUND(C15/MA_Kurs_1,2),0) | F15: Evaluierung | H15: ==IFERROR(ROUND(G15/MA_Kurs_2,2),0) | J15: Evaluierung | L15: ==IFERROR(ROUND(K15/MA_Kurs_3,2),0) | N15: Evaluierung | P15: ==IFERROR(ROUND(O15/MA_Kurs_4,2),0) | R15: Evaluierung | T15: ==IFERROR(ROUND(S15/MA_Kurs_5,2),0) | V15: Evaluierung | X15: ==IFERROR(ROUND(W15/MA_Kurs_6,2),0) | Z15: Evaluierung | AB15: ==IFERROR(ROUND(AA15/MA_Kurs_7,2),0) | AD15: Evaluierung | AF15: ==IFERROR(ROUND(AE15/MA_Kurs_8,2),0) | AH15: Evaluierung | AJ15: ==IFERROR(ROUND(AI15/MA_Kurs_9,2),0) | AL15: Evaluierung | AN15: ==IFERROR(ROUND(AM15/MA_Kurs_10,2),0) | AP15: Evaluierung | AR15: ==IFERROR(ROUND(AQ15/MA_Kurs_11,2),0) | AT15: Evaluierung | AV15: ==IFERROR(ROUND(AU15/MA_Kurs_12,2),0) | AX15: Evaluierung | AZ15: ==IFERROR(ROUND(AY15/MA_Kurs_13,2),0) | BB15: Evaluierung | BD15: ==IFERROR(ROUND(BC15/MA_Kurs_14,2),0) | BF15: Evaluierung | BH15: ==IFERROR(ROUND(BG15/MA_Kurs_15,2),0) | BJ15: Evaluierung | BL15: ==IFERROR(ROUND(BK15/MA_Kurs_16,2),0) | BN15: Evaluierung | BP15: ==IFERROR(ROUND(BO15/MA_Kurs_17,2),0) | BR15: Evaluierung | BT15: ==IFERROR(ROUND(BS15/MA_Kurs_18,2),0)
B16: Audit | D16: ==IFERROR(ROUND(C16/MA_Kurs_1,2),0) | F16: Audit | H16: ==IFERROR(ROUND(G16/MA_Kurs_2,2),0) | J16: Audit | L16: ==IFERROR(ROUND(K16/MA_Kurs_3,2),0) | N16: Audit | P16: ==IFERROR(ROUND(O16/MA_Kurs_4,2),0) | R16: Audit | T16: ==IFERROR(ROUND(S16/MA_Kurs_5,2),0) | V16: Audit | X16: ==IFERROR(ROUND(W16/MA_Kurs_6,2),0) | Z16: Audit | AB16: ==IFERROR(ROUND(AA16/MA_Kurs_7,2),0) | AD16: Audit | AF16: ==IFERROR(ROUND(AE16/MA_Kurs_8,2),0) | AH16: Audit | AJ16: ==IFERROR(ROUND(AI16/MA_Kurs_9,2),0) | AL16: Audit | AN16: ==IFERROR(ROUND(AM16/MA_Kurs_10,2),0) | AP16: Audit | AR16: ==IFERROR(ROUND(AQ16/MA_Kurs_11,2),0) | AT16: Audit | AV16: ==IFERROR(ROUND(AU16/MA_Kurs_12,2),0) | AX16: Audit | AZ16: ==IFERROR(ROUND(AY16/MA_Kurs_13,2),0) | BB16: Audit | BD16: ==IFERROR(ROUND(BC16/MA_Kurs_14,2),0) | BF16: Audit | BH16: ==IFERROR(ROUND(BG16/MA_Kurs_15,2),0) | BJ16: Audit | BL16: ==IFERROR(ROUND(BK16/MA_Kurs_16,2),0) | BN16: Audit | BP16: ==IFERROR(ROUND(BO16/MA_Kurs_17,2),0) | BR16: Audit | BT16: ==IFERROR(ROUND(BS16/MA_Kurs_18,2),0)
B17: Reserve | D17: ==IFERROR(ROUND(C17/MA_Kurs_1,2),0) | F17: Reserve | H17: ==IFERROR(ROUND(G17/MA_Kurs_2,2),0) | J17: Reserve | L17: ==IFERROR(ROUND(K17/MA_Kurs_3,2),0) | N17: Reserve | P17: ==IFERROR(ROUND(O17/MA_Kurs_4,2),0) | R17: Reserve | T17: ==IFERROR(ROUND(S17/MA_Kurs_5,2),0) | V17: Reserve | X17: ==IFERROR(ROUND(W17/MA_Kurs_6,2),0) | Z17: Reserve | AB17: ==IFERROR(ROUND(AA17/MA_Kurs_7,2),0) | AD17: Reserve | AF17: ==IFERROR(ROUND(AE17/MA_Kurs_8,2),0) | AH17: Reserve | AJ17: ==IFERROR(ROUND(AI17/MA_Kurs_9,2),0) | AL17: Reserve | AN17: ==IFERROR(ROUND(AM17/MA_Kurs_10,2),0) | AP17: Reserve | AR17: ==IFERROR(ROUND(AQ17/MA_Kurs_11,2),0) | AT17: Reserve | AV17: ==IFERROR(ROUND(AU17/MA_Kurs_12,2),0) | AX17: Reserve | AZ17: ==IFERROR(ROUND(AY17/MA_Kurs_13,2),0) | BB17: Reserve | BD17: ==IFERROR(ROUND(BC17/MA_Kurs_14,2),0) | BF17: Reserve | BH17: ==IFERROR(ROUND(BG17/MA_Kurs_15,2),0) | BJ17: Reserve | BL17: ==IFERROR(ROUND(BK17/MA_Kurs_16,2),0) | BN17: Reserve | BP17: ==IFERROR(ROUND(BO17/MA_Kurs_17,2),0) | BR17: Reserve | BT17: ==IFERROR(ROUND(BS17/MA_Kurs_18,2),0)
B18: SUMME | C18: ==ROUND(SUBTOTAL(109,MA_1[Angefordert (LC)]),2) | D18: ==ROUND(SUBTOTAL(109,MA_1[Angefordert (EUR)]),2) | F18: SUMME | G18: ==ROUND(SUBTOTAL(109,MA_2[Angefordert (LC)]),2) | H18: ==ROUND(SUBTOTAL(109,MA_2[Angefordert (EUR)]),2) | J18: SUMME | K18: ==ROUND(SUBTOTAL(109,MA_3[Angefordert (LC)]),2) | L18: ==ROUND(SUBTOTAL(109,MA_3[Angefordert (EUR)]),2) | N18: SUMME | O18: ==ROUND(SUBTOTAL(109,MA_4[Angefordert (LC)]),2) | P18: ==ROUND(SUBTOTAL(109,MA_4[Angefordert (EUR)]),2) | R18: SUMME | S18: ==ROUND(SUBTOTAL(109,MA_5[Angefordert (LC)]),2) | T18: ==ROUND(SUBTOTAL(109,MA_5[Angefordert (EUR)]),2) | V18: SUMME | W18: ==ROUND(SUBTOTAL(109,MA_6[Angefordert (LC)]),2) | X18: ==ROUND(SUBTOTAL(109,MA_6[Angefordert (EUR)]),2) | Z18: SUMME | AA18: ==ROUND(SUBTOTAL(109,MA_7[Angefordert (LC)]),2) | AB18: ==ROUND(SUBTOTAL(109,MA_7[Angefordert (EUR)]),2) | AD18: SUMME | AE18: ==ROUND(SUBTOTAL(109,MA_8[Angefordert (LC)]),2) | AF18: ==ROUND(SUBTOTAL(109,MA_8[Angefordert (EUR)]),2) | AH18: SUMME | AI18: ==ROUND(SUBTOTAL(109,MA_9[Angefordert (LC)]),2) | AJ18: ==ROUND(SUBTOTAL(109,MA_9[Angefordert (EUR)]),2) | AL18: SUMME | AM18: ==ROUND(SUBTOTAL(109,MA_10[Angefordert (LC)]),2) | AN18: ==ROUND(SUBTOTAL(109,MA_10[Angefordert (EUR)]),2) | AP18: SUMME | AQ18: ==ROUND(SUBTOTAL(109,MA_11[Angefordert (LC)]),2) | AR18: ==ROUND(SUBTOTAL(109,MA_11[Angefordert (EUR)]),2) | AT18: SUMME | AU18: ==ROUND(SUBTOTAL(109,MA_12[Angefordert (LC)]),2) | AV18: ==ROUND(SUBTOTAL(109,MA_12[Angefordert (EUR)]),2) | AX18: SUMME | AY18: ==ROUND(SUBTOTAL(109,MA_13[Angefordert (LC)]),2) | AZ18: ==ROUND(SUBTOTAL(109,MA_13[Angefordert (EUR)]),2) | BB18: SUMME | BC18: ==ROUND(SUBTOTAL(109,MA_14[Angefordert (LC)]),2) | BD18: ==ROUND(SUBTOTAL(109,MA_14[Angefordert (EUR)]),2) | BF18: SUMME | BG18: ==ROUND(SUBTOTAL(109,MA_15[Angefordert (LC)]),2) | BH18: ==ROUND(SUBTOTAL(109,MA_15[Angefordert (EUR)]),2) | BJ18: SUMME | BK18: ==ROUND(SUBTOTAL(109,MA_16[Angefordert (LC)]),2) | BL18: ==ROUND(SUBTOTAL(109,MA_16[Angefordert (EUR)]),2) | BN18: SUMME | BO18: ==ROUND(SUBTOTAL(109,MA_17[Angefordert (LC)]),2) | BP18: ==ROUND(SUBTOTAL(109,MA_17[Angefordert (EUR)]),2) | BR18: SUMME | BS18: ==ROUND(SUBTOTAL(109,MA_18[Angefordert (LC)]),2) | BT18: ==ROUND(SUBTOTAL(109,MA_18[Angefordert (EUR)]),2)
B20: Gesamtbedarf an Mitteln: | C20: ==ROUND($C$18,2) | D20: ==ROUND($D$18,2) | F20: Gesamtbedarf an Mitteln: | G20: ==ROUND($G$18,2) | H20: ==ROUND($H$18,2) | J20: Gesamtbedarf an Mitteln: | K20: ==ROUND($K$18,2) | L20: ==ROUND($L$18,2) | N20: Gesamtbedarf an Mitteln: | O20: ==ROUND($O$18,2) | P20: ==ROUND($P$18,2) | R20: Gesamtbedarf an Mitteln: | S20: ==ROUND($S$18,2) | T20: ==ROUND($T$18,2) | V20: Gesamtbedarf an Mitteln: | W20: ==ROUND($W$18,2) | X20: ==ROUND($X$18,2) | Z20: Gesamtbedarf an Mitteln: | AA20: ==ROUND($AA$18,2) | AB20: ==ROUND($AB$18,2) | AD20: Gesamtbedarf an Mitteln: | AE20: ==ROUND($AE$18,2) | AF20: ==ROUND($AF$18,2) | AH20: Gesamtbedarf an Mitteln: | AI20: ==ROUND($AI$18,2) | AJ20: ==ROUND($AJ$18,2) | AL20: Gesamtbedarf an Mitteln: | AM20: ==ROUND($AM$18,2) | AN20: ==ROUND($AN$18,2) | AP20: Gesamtbedarf an Mitteln: | AQ20: ==ROUND($AQ$18,2) | AR20: ==ROUND($AR$18,2) | AT20: Gesamtbedarf an Mitteln: | AU20: ==ROUND($AU$18,2) | AV20: ==ROUND($AV$18,2) | AX20: Gesamtbedarf an Mitteln: | AY20: ==ROUND($AY$18,2) | AZ20: ==ROUND($AZ$18,2) | BB20: Gesamtbedarf an Mitteln: | BC20: ==ROUND($BC$18,2) | BD20: ==ROUND($BD$18,2) | BF20: Gesamtbedarf an Mitteln: | BG20: ==ROUND($BG$18,2) | BH20: ==ROUND($BH$18,2) | BJ20: Gesamtbedarf an Mitteln: | BK20: ==ROUND($BK$18,2) | BL20: ==ROUND($BL$18,2) | BN20: Gesamtbedarf an Mitteln: | BO20: ==ROUND($BO$18,2) | BP20: ==ROUND($BP$18,2) | BR20: Gesamtbedarf an Mitteln: | BS20: ==ROUND($BS$18,2) | BT20: ==ROUND($BT$18,2)
B21: abzueglich Eigenmittel: | D21: ==IFERROR(ROUND($C$21/$C$8,2),0) | F21: abzueglich Eigenmittel: | H21: ==IFERROR(ROUND($G$21/$G$8,2),0) | J21: abzueglich Eigenmittel: | L21: ==IFERROR(ROUND($K$21/$K$8,2),0) | N21: abzueglich Eigenmittel: | P21: ==IFERROR(ROUND($O$21/$O$8,2),0) | R21: abzueglich Eigenmittel: | T21: ==IFERROR(ROUND($S$21/$S$8,2),0) | V21: abzueglich Eigenmittel: | X21: ==IFERROR(ROUND($W$21/$W$8,2),0) | Z21: abzueglich Eigenmittel: | AB21: ==IFERROR(ROUND($AA$21/$AA$8,2),0) | AD21: abzueglich Eigenmittel: | AF21: ==IFERROR(ROUND($AE$21/$AE$8,2),0) | AH21: abzueglich Eigenmittel: | AJ21: ==IFERROR(ROUND($AI$21/$AI$8,2),0) | AL21: abzueglich Eigenmittel: | AN21: ==IFERROR(ROUND($AM$21/$AM$8,2),0) | AP21: abzueglich Eigenmittel: | AR21: ==IFERROR(ROUND($AQ$21/$AQ$8,2),0) | AT21: abzueglich Eigenmittel: | AV21: ==IFERROR(ROUND($AU$21/$AU$8,2),0) | AX21: abzueglich Eigenmittel: | AZ21: ==IFERROR(ROUND($AY$21/$AY$8,2),0) | BB21: abzueglich Eigenmittel: | BD21: ==IFERROR(ROUND($BC$21/$BC$8,2),0) | BF21: abzueglich Eigenmittel: | BH21: ==IFERROR(ROUND($BG$21/$BG$8,2),0) | BJ21: abzueglich Eigenmittel: | BL21: ==IFERROR(ROUND($BK$21/$BK$8,2),0) | BN21: abzueglich Eigenmittel: | BP21: ==IFERROR(ROUND($BO$21/$BO$8,2),0) | BR21: abzueglich Eigenmittel: | BT21: ==IFERROR(ROUND($BS$21/$BS$8,2),0)
B22: abzueglich Drittmittel: | D22: ==IFERROR(ROUND($C$22/$C$8,2),0) | F22: abzueglich Drittmittel: | H22: ==IFERROR(ROUND($G$22/$G$8,2),0) | J22: abzueglich Drittmittel: | L22: ==IFERROR(ROUND($K$22/$K$8,2),0) | N22: abzueglich Drittmittel: | P22: ==IFERROR(ROUND($O$22/$O$8,2),0) | R22: abzueglich Drittmittel: | T22: ==IFERROR(ROUND($S$22/$S$8,2),0) | V22: abzueglich Drittmittel: | X22: ==IFERROR(ROUND($W$22/$W$8,2),0) | Z22: abzueglich Drittmittel: | AB22: ==IFERROR(ROUND($AA$22/$AA$8,2),0) | AD22: abzueglich Drittmittel: | AF22: ==IFERROR(ROUND($AE$22/$AE$8,2),0) | AH22: abzueglich Drittmittel: | AJ22: ==IFERROR(ROUND($AI$22/$AI$8,2),0) | AL22: abzueglich Drittmittel: | AN22: ==IFERROR(ROUND($AM$22/$AM$8,2),0) | AP22: abzueglich Drittmittel: | AR22: ==IFERROR(ROUND($AQ$22/$AQ$8,2),0) | AT22: abzueglich Drittmittel: | AV22: ==IFERROR(ROUND($AU$22/$AU$8,2),0) | AX22: abzueglich Drittmittel: | AZ22: ==IFERROR(ROUND($AY$22/$AY$8,2),0) | BB22: abzueglich Drittmittel: | BD22: ==IFERROR(ROUND($BC$22/$BC$8,2),0) | BF22: abzueglich Drittmittel: | BH22: ==IFERROR(ROUND($BG$22/$BG$8,2),0) | BJ22: abzueglich Drittmittel: | BL22: ==IFERROR(ROUND($BK$22/$BK$8,2),0) | BN22: abzueglich Drittmittel: | BP22: ==IFERROR(ROUND($BO$22/$BO$8,2),0) | BR22: abzueglich Drittmittel: | BT22: ==IFERROR(ROUND($BS$22/$BS$8,2),0)
B23: abzueglich Saldo Vorprojekt: | C23: ==ROUND(IF(Saldovortrag_LW="",0,Saldovortrag_LW),2) | D23: ==IFERROR(ROUND($C$23/$C$8,2),0) | F23: abzueglich Saldo Vorperiode (FB): | G23: ==ROUND(IFERROR(FB_SaldoLC_1,0),2) | H23: ==IFERROR(ROUND($G$23/$G$8,2),0) | J23: abzueglich Saldo Vorperiode (FB): | K23: ==ROUND(IFERROR(FB_SaldoLC_2,0),2) | L23: ==IFERROR(ROUND($K$23/$K$8,2),0) | N23: abzueglich Saldo Vorperiode (FB): | O23: ==ROUND(IFERROR(FB_SaldoLC_3,0),2) | P23: ==IFERROR(ROUND($O$23/$O$8,2),0) | R23: abzueglich Saldo Vorperiode (FB): | S23: ==ROUND(IFERROR(FB_SaldoLC_4,0),2) | T23: ==IFERROR(ROUND($S$23/$S$8,2),0) | V23: abzueglich Saldo Vorperiode (FB): | W23: ==ROUND(IFERROR(FB_SaldoLC_5,0),2) | X23: ==IFERROR(ROUND($W$23/$W$8,2),0) | Z23: abzueglich Saldo Vorperiode (FB): | AA23: ==ROUND(IFERROR(FB_SaldoLC_6,0),2) | AB23: ==IFERROR(ROUND($AA$23/$AA$8,2),0) | AD23: abzueglich Saldo Vorperiode (FB): | AE23: ==ROUND(IFERROR(FB_SaldoLC_7,0),2) | AF23: ==IFERROR(ROUND($AE$23/$AE$8,2),0) | AH23: abzueglich Saldo Vorperiode (FB): | AI23: ==ROUND(IFERROR(FB_SaldoLC_8,0),2) | AJ23: ==IFERROR(ROUND($AI$23/$AI$8,2),0) | AL23: abzueglich Saldo Vorperiode (FB): | AM23: ==ROUND(IFERROR(FB_SaldoLC_9,0),2) | AN23: ==IFERROR(ROUND($AM$23/$AM$8,2),0) | AP23: abzueglich Saldo Vorperiode (FB): | AQ23: ==ROUND(IFERROR(FB_SaldoLC_10,0),2) | AR23: ==IFERROR(ROUND($AQ$23/$AQ$8,2),0) | AT23: abzueglich Saldo Vorperiode (FB): | AU23: ==ROUND(IFERROR(FB_SaldoLC_11,0),2) | AV23: ==IFERROR(ROUND($AU$23/$AU$8,2),0) | AX23: abzueglich Saldo Vorperiode (FB): | AY23: ==ROUND(IFERROR(FB_SaldoLC_12,0),2) | AZ23: ==IFERROR(ROUND($AY$23/$AY$8,2),0) | BB23: abzueglich Saldo Vorperiode (FB): | BC23: ==ROUND(IFERROR(FB_SaldoLC_13,0),2) | BD23: ==IFERROR(ROUND($BC$23/$BC$8,2),0) | BF23: abzueglich Saldo Vorperiode (FB): | BG23: ==ROUND(IFERROR(FB_SaldoLC_14,0),2) | BH23: ==IFERROR(ROUND($BG$23/$BG$8,2),0) | BJ23: abzueglich Saldo Vorperiode (FB): | BK23: ==ROUND(IFERROR(FB_SaldoLC_15,0),2) | BL23: ==IFERROR(ROUND($BK$23/$BK$8,2),0) | BN23: abzueglich Saldo Vorperiode (FB): | BO23: ==ROUND(IFERROR(FB_SaldoLC_16,0),2) | BP23: ==IFERROR(ROUND($BO$23/$BO$8,2),0) | BR23: abzueglich Saldo Vorperiode (FB): | BS23: ==ROUND(IFERROR(FB_SaldoLC_17,0),2) | BT23: ==IFERROR(ROUND($BS$23/$BS$8,2),0)
B25: KMW-Mittel Anforderung: | C25: ==IFERROR(ROUND($C$18-$C$21-$C$22-$C$23,2),0) | D25: ==IFERROR(ROUND($D$18-$D$21-$D$22-$D$23,2),0) | F25: KMW-Mittel Anforderung: | G25: ==IFERROR(ROUND($G$18-$G$21-$G$22-$G$23,2),0) | H25: ==IFERROR(ROUND($H$18-$H$21-$H$22-$H$23,2),0) | J25: KMW-Mittel Anforderung: | K25: ==IFERROR(ROUND($K$18-$K$21-$K$22-$K$23,2),0) | L25: ==IFERROR(ROUND($L$18-$L$21-$L$22-$L$23,2),0) | N25: KMW-Mittel Anforderung: | O25: ==IFERROR(ROUND($O$18-$O$21-$O$22-$O$23,2),0) | P25: ==IFERROR(ROUND($P$18-$P$21-$P$22-$P$23,2),0) | R25: KMW-Mittel Anforderung: | S25: ==IFERROR(ROUND($S$18-$S$21-$S$22-$S$23,2),0) | T25: ==IFERROR(ROUND($T$18-$T$21-$T$22-$T$23,2),0) | V25: KMW-Mittel Anforderung: | W25: ==IFERROR(ROUND($W$18-$W$21-$W$22-$W$23,2),0) | X25: ==IFERROR(ROUND($X$18-$X$21-$X$22-$X$23,2),0) | Z25: KMW-Mittel Anforderung: | AA25: ==IFERROR(ROUND($AA$18-$AA$21-$AA$22-$AA$23,2),0) | AB25: ==IFERROR(ROUND($AB$18-$AB$21-$AB$22-$AB$23,2),0) | AD25: KMW-Mittel Anforderung: | AE25: ==IFERROR(ROUND($AE$18-$AE$21-$AE$22-$AE$23,2),0) | AF25: ==IFERROR(ROUND($AF$18-$AF$21-$AF$22-$AF$23,2),0) | AH25: KMW-Mittel Anforderung: | AI25: ==IFERROR(ROUND($AI$18-$AI$21-$AI$22-$AI$23,2),0) | AJ25: ==IFERROR(ROUND($AJ$18-$AJ$21-$AJ$22-$AJ$23,2),0) | AL25: KMW-Mittel Anforderung: | AM25: ==IFERROR(ROUND($AM$18-$AM$21-$AM$22-$AM$23,2),0) | AN25: ==IFERROR(ROUND($AN$18-$AN$21-$AN$22-$AN$23,2),0) | AP25: KMW-Mittel Anforderung: | AQ25: ==IFERROR(ROUND($AQ$18-$AQ$21-$AQ$22-$AQ$23,2),0) | AR25: ==IFERROR(ROUND($AR$18-$AR$21-$AR$22-$AR$23,2),0) | AT25: KMW-Mittel Anforderung: | AU25: ==IFERROR(ROUND($AU$18-$AU$21-$AU$22-$AU$23,2),0) | AV25: ==IFERROR(ROUND($AV$18-$AV$21-$AV$22-$AV$23,2),0) | AX25: KMW-Mittel Anforderung: | AY25: ==IFERROR(ROUND($AY$18-$AY$21-$AY$22-$AY$23,2),0) | AZ25: ==IFERROR(ROUND($AZ$18-$AZ$21-$AZ$22-$AZ$23,2),0) | BB25: KMW-Mittel Anforderung: | BC25: ==IFERROR(ROUND($BC$18-$BC$21-$BC$22-$BC$23,2),0) | BD25: ==IFERROR(ROUND($BD$18-$BD$21-$BD$22-$BD$23,2),0) | BF25: KMW-Mittel Anforderung: | BG25: ==IFERROR(ROUND($BG$18-$BG$21-$BG$22-$BG$23,2),0) | BH25: ==IFERROR(ROUND($BH$18-$BH$21-$BH$22-$BH$23,2),0) | BJ25: KMW-Mittel Anforderung: | BK25: ==IFERROR(ROUND($BK$18-$BK$21-$BK$22-$BK$23,2),0) | BL25: ==IFERROR(ROUND($BL$18-$BL$21-$BL$22-$BL$23,2),0) | BN25: KMW-Mittel Anforderung: | BO25: ==IFERROR(ROUND($BO$18-$BO$21-$BO$22-$BO$23,2),0) | BP25: ==IFERROR(ROUND($BP$18-$BP$21-$BP$22-$BP$23,2),0) | BR25: KMW-Mittel Anforderung: | BS25: ==IFERROR(ROUND($BS$18-$BS$21-$BS$22-$BS$23,2),0) | BT25: ==IFERROR(ROUND($BT$18-$BT$21-$BT$22-$BT$23,2),0)
B27: Manueller Betrag (EUR): | F27: Manueller Betrag (EUR): | J27: Manueller Betrag (EUR): | N27: Manueller Betrag (EUR): | R27: Manueller Betrag (EUR): | V27: Manueller Betrag (EUR): | Z27: Manueller Betrag (EUR): | AD27: Manueller Betrag (EUR): | AH27: Manueller Betrag (EUR): | AL27: Manueller Betrag (EUR): | AP27: Manueller Betrag (EUR): | AT27: Manueller Betrag (EUR): | AX27: Manueller Betrag (EUR): | BB27: Manueller Betrag (EUR): | BF27: Manueller Betrag (EUR): | BJ27: Manueller Betrag (EUR): | BN27: Manueller Betrag (EUR): | BR27: Manueller Betrag (EUR):

Sheet V. AUSWERTUNG
B2: V. AUSWERTUNG
B3: Automatische Prüfung von Mittelanforderung und Finanzberichten
B5: MITTELANFORDERUNGSPRÜFUNG | L5: ==IF(E11=0,"Aktuelle Mittelanforderung (keine gewählt)","Aktuelle Mittelanforderung – Periode "&E10&" (#"&E11&")") | AD5: ==IFERROR(SUMPRODUCT('Daten'!$BA$1:$BA$18,('Daten'!$BB$1:$BB$18=E10)*('Daten'!$BD$1:$BD$18=E11)),0)
B6: Basis: ausgewählte Mittelanforderung (Folgeperiode des Finanzberichts) | L6: Periode: | M6: ==IFERROR(CHOOSE($AD$5,'IV. MA'!$C$4,'IV. MA'!$G$4,'IV. MA'!$K$4,'IV. MA'!$O$4,'IV. MA'!$S$4,'IV. MA'!$W$4,'IV. MA'!$AA$4,'IV. MA'!$AE$4,'IV. MA'!$AI$4,'IV. MA'!$AM$4,'IV. MA'!$AQ$4,'IV. MA'!$AU$4,'IV. MA'!$AY$4,'IV. MA'!$BC$4,'IV. MA'!$BG$4,'IV. MA'!$BK$4,'IV. MA'!$BO$4,'IV. MA'!$BS$4),"")
L7: Von: | M7: ==IFERROR(CHOOSE($AD$5,'IV. MA'!$C$5,'IV. MA'!$G$5,'IV. MA'!$K$5,'IV. MA'!$O$5,'IV. MA'!$S$5,'IV. MA'!$W$5,'IV. MA'!$AA$5,'IV. MA'!$AE$5,'IV. MA'!$AI$5,'IV. MA'!$AM$5,'IV. MA'!$AQ$5,'IV. MA'!$AU$5,'IV. MA'!$AY$5,'IV. MA'!$BC$5,'IV. MA'!$BG$5,'IV. MA'!$BK$5,'IV. MA'!$BO$5,'IV. MA'!$BS$5),"")
C8: Mittelanforderung auswählen | L8: Bis: | M8: ==IFERROR(CHOOSE($AD$5,'IV. MA'!$C$6,'IV. MA'!$G$6,'IV. MA'!$K$6,'IV. MA'!$O$6,'IV. MA'!$S$6,'IV. MA'!$W$6,'IV. MA'!$AA$6,'IV. MA'!$AE$6,'IV. MA'!$AI$6,'IV. MA'!$AM$6,'IV. MA'!$AQ$6,'IV. MA'!$AU$6,'IV. MA'!$AY$6,'IV. MA'!$BC$6,'IV. MA'!$BG$6,'IV. MA'!$BK$6,'IV. MA'!$BO$6,'IV. MA'!$BS$6),"")
C9: Auswahl: | E9: Neuste MA | L9: Zeitraum: | M9: ==IFERROR(CHOOSE($AD$5,'IV. MA'!$C$7,'IV. MA'!$G$7,'IV. MA'!$K$7,'IV. MA'!$O$7,'IV. MA'!$S$7,'IV. MA'!$W$7,'IV. MA'!$AA$7,'IV. MA'!$AE$7,'IV. MA'!$AI$7,'IV. MA'!$AM$7,'IV. MA'!$AQ$7,'IV. MA'!$AU$7,'IV. MA'!$AY$7,'IV. MA'!$BC$7,'IV. MA'!$BG$7,'IV. MA'!$BK$7,'IV. MA'!$BO$7,'IV. MA'!$BS$7),"")
C10: Geprüfte Periode | E10: ==E81+1 -> 0 | L10: OANDA-Kurs: | M10: ==IFERROR(CHOOSE($AD$5,'IV. MA'!$C$8,'IV. MA'!$G$8,'IV. MA'!$K$8,'IV. MA'!$O$8,'IV. MA'!$S$8,'IV. MA'!$W$8,'IV. MA'!$AA$8,'IV. MA'!$AE$8,'IV. MA'!$AI$8,'IV. MA'!$AM$8,'IV. MA'!$AQ$8,'IV. MA'!$AU$8,'IV. MA'!$AY$8,'IV. MA'!$BC$8,'IV. MA'!$BG$8,'IV. MA'!$BK$8,'IV. MA'!$BO$8,'IV. MA'!$BS$8),"")
C11: Ausgewählte Anforderung (#) | E11: ==IF(E9="Neuste MA",IFERROR(SUMPRODUCT(MAX(('Daten'!$BB$1:$BB$18=E10)*('Daten'!$BC$1:$BC$18=1)*'Daten'!$BD$1:$BD$18)),0),IFERROR(VALUE(MID(E9,FIND("(#",E9)+2,FIND(")",E9)-FIND("(#",E9)-2)),0))
C12: Einbezogene Anforderungen | L12: Kostenkategorie | M12: Angefordert (LC) | N12: Angefordert (EUR)
C13: ==IF(1<=E11,"Periode "&E10&" (#1)","") | E13: ==IF(1<=E11,IFERROR(SUMIFS('Daten'!$BF$1:$BF$18,'Daten'!$BB$1:$BB$18,E10,'Daten'!$BD$1:$BD$18,1),0),"") | G13: ==IF(1<=E11,IFERROR(SUMIFS('Daten'!$BG$1:$BG$18,'Daten'!$BB$1:$BB$18,E10,'Daten'!$BD$1:$BD$18,1),0),"") | L13: Bauausgaben | M13: ==IFERROR(CHOOSE($AD$5,'IV. MA'!$C$10,'IV. MA'!$G$10,'IV. MA'!$K$10,'IV. MA'!$O$10,'IV. MA'!$S$10,'IV. MA'!$W$10,'IV. MA'!$AA$10,'IV. MA'!$AE$10,'IV. MA'!$AI$10,'IV. MA'!$AM$10,'IV. MA'!$AQ$10,'IV. MA'!$AU$10,'IV. MA'!$AY$10,'IV. MA'!$BC$10,'IV. MA'!$BG$10,'IV. MA'!$BK$10,'IV. MA'!$BO$10,'IV. MA'!$BS$10),"") | N13: ==IFERROR(CHOOSE($AD$5,'IV. MA'!$D$10,'IV. MA'!$H$10,'IV. MA'!$L$10,'IV. MA'!$P$10,'IV. MA'!$T$10,'IV. MA'!$X$10,'IV. MA'!$AB$10,'IV. MA'!$AF$10,'IV. MA'!$AJ$10,'IV. MA'!$AN$10,'IV. MA'!$AR$10,'IV. MA'!$AV$10,'IV. MA'!$AZ$10,'IV. MA'!$BD$10,'IV. MA'!$BH$10,'IV. MA'!$BL$10,'IV. MA'!$BP$10,'IV. MA'!$BT$10),"")
C14: ==IF(2<=E11,"Periode "&E10&" (#2)","") | E14: ==IF(2<=E11,IFERROR(SUMIFS('Daten'!$BF$1:$BF$18,'Daten'!$BB$1:$BB$18,E10,'Daten'!$BD$1:$BD$18,2),0),"") | G14: ==IF(2<=E11,IFERROR(SUMIFS('Daten'!$BG$1:$BG$18,'Daten'!$BB$1:$BB$18,E10,'Daten'!$BD$1:$BD$18,2),0),"") | L14: Investitionen | M14: ==IFERROR(CHOOSE($AD$5,'IV. MA'!$C$11,'IV. MA'!$G$11,'IV. MA'!$K$11,'IV. MA'!$O$11,'IV. MA'!$S$11,'IV. MA'!$W$11,'IV. MA'!$AA$11,'IV. MA'!$AE$11,'IV. MA'!$AI$11,'IV. MA'!$AM$11,'IV. MA'!$AQ$11,'IV. MA'!$AU$11,'IV. MA'!$AY$11,'IV. MA'!$BC$11,'IV. MA'!$BG$11,'IV. MA'!$BK$11,'IV. MA'!$BO$11,'IV. MA'!$BS$11),"") | N14: ==IFERROR(CHOOSE($AD$5,'IV. MA'!$D$11,'IV. MA'!$H$11,'IV. MA'!$L$11,'IV. MA'!$P$11,'IV. MA'!$T$11,'IV. MA'!$X$11,'IV. MA'!$AB$11,'IV. MA'!$AF$11,'IV. MA'!$AJ$11,'IV. MA'!$AN$11,'IV. MA'!$AR$11,'IV. MA'!$AV$11,'IV. MA'!$AZ$11,'IV. MA'!$BD$11,'IV. MA'!$BH$11,'IV. MA'!$BL$11,'IV. MA'!$BP$11,'IV. MA'!$BT$11),"")
C15: ==IF(3<=E11,"Periode "&E10&" (#3)","") | E15: ==IF(3<=E11,IFERROR(SUMIFS('Daten'!$BF$1:$BF$18,'Daten'!$BB$1:$BB$18,E10,'Daten'!$BD$1:$BD$18,3),0),"") | G15: ==IF(3<=E11,IFERROR(SUMIFS('Daten'!$BG$1:$BG$18,'Daten'!$BB$1:$BB$18,E10,'Daten'!$BD$1:$BD$18,3),0),"") | L15: Personalkosten | M15: ==IFERROR(CHOOSE($AD$5,'IV. MA'!$C$12,'IV. MA'!$G$12,'IV. MA'!$K$12,'IV. MA'!$O$12,'IV. MA'!$S$12,'IV. MA'!$W$12,'IV. MA'!$AA$12,'IV. MA'!$AE$12,'IV. MA'!$AI$12,'IV. MA'!$AM$12,'IV. MA'!$AQ$12,'IV. MA'!$AU$12,'IV. MA'!$AY$12,'IV. MA'!$BC$12,'IV. MA'!$BG$12,'IV. MA'!$BK$12,'IV. MA'!$BO$12,'IV. MA'!$BS$12),"") | N15: ==IFERROR(CHOOSE($AD$5,'IV. MA'!$D$12,'IV. MA'!$H$12,'IV. MA'!$L$12,'IV. MA'!$P$12,'IV. MA'!$T$12,'IV. MA'!$X$12,'IV. MA'!$AB$12,'IV. MA'!$AF$12,'IV. MA'!$AJ$12,'IV. MA'!$AN$12,'IV. MA'!$AR$12,'IV. MA'!$AV$12,'IV. MA'!$AZ$12,'IV. MA'!$BD$12,'IV. MA'!$BH$12,'IV. MA'!$BL$12,'IV. MA'!$BP$12,'IV. MA'!$BT$12),"")
C16: ==IF(4<=E11,"Periode "&E10&" (#4)","") | E16: ==IF(4<=E11,IFERROR(SUMIFS('Daten'!$BF$1:$BF$18,'Daten'!$BB$1:$BB$18,E10,'Daten'!$BD$1:$BD$18,4),0),"") | G16: ==IF(4<=E11,IFERROR(SUMIFS('Daten'!$BG$1:$BG$18,'Daten'!$BB$1:$BB$18,E10,'Daten'!$BD$1:$BD$18,4),0),"") | L16: Projektaktivitaeten | M16: ==IFERROR(CHOOSE($AD$5,'IV. MA'!$C$13,'IV. MA'!$G$13,'IV. MA'!$K$13,'IV. MA'!$O$13,'IV. MA'!$S$13,'IV. MA'!$W$13,'IV. MA'!$AA$13,'IV. MA'!$AE$13,'IV. MA'!$AI$13,'IV. MA'!$AM$13,'IV. MA'!$AQ$13,'IV. MA'!$AU$13,'IV. MA'!$AY$13,'IV. MA'!$BC$13,'IV. MA'!$BG$13,'IV. MA'!$BK$13,'IV. MA'!$BO$13,'IV. MA'!$BS$13),"") | N16: ==IFERROR(CHOOSE($AD$5,'IV. MA'!$D$13,'IV. MA'!$H$13,'IV. MA'!$L$13,'IV. MA'!$P$13,'IV. MA'!$T$13,'IV. MA'!$X$13,'IV. MA'!$AB$13,'IV. MA'!$AF$13,'IV. MA'!$AJ$13,'IV. MA'!$AN$13,'IV. MA'!$AR$13,'IV. MA'!$AV$13,'IV. MA'!$AZ$13,'IV. MA'!$BD$13,'IV. MA'!$BH$13,'IV. MA'!$BL$13,'IV. MA'!$BP$13,'IV. MA'!$BT$13),"")
C17: ==IF(5<=E11,"Periode "&E10&" (#5)","") | E17: ==IF(5<=E11,IFERROR(SUMIFS('Daten'!$BF$1:$BF$18,'Daten'!$BB$1:$BB$18,E10,'Daten'!$BD$1:$BD$18,5),0),"") | G17: ==IF(5<=E11,IFERROR(SUMIFS('Daten'!$BG$1:$BG$18,'Daten'!$BB$1:$BB$18,E10,'Daten'!$BD$1:$BD$18,5),0),"") | L17: Projektverwaltung | M17: ==IFERROR(CHOOSE($AD$5,'IV. MA'!$C$14,'IV. MA'!$G$14,'IV. MA'!$K$14,'IV. MA'!$O$14,'IV. MA'!$S$14,'IV. MA'!$W$14,'IV. MA'!$AA$14,'IV. MA'!$AE$14,'IV. MA'!$AI$14,'IV. MA'!$AM$14,'IV. MA'!$AQ$14,'IV. MA'!$AU$14,'IV. MA'!$AY$14,'IV. MA'!$BC$14,'IV. MA'!$BG$14,'IV. MA'!$BK$14,'IV. MA'!$BO$14,'IV. MA'!$BS$14),"") | N17: ==IFERROR(CHOOSE($AD$5,'IV. MA'!$D$14,'IV. MA'!$H$14,'IV. MA'!$L$14,'IV. MA'!$P$14,'IV. MA'!$T$14,'IV. MA'!$X$14,'IV. MA'!$AB$14,'IV. MA'!$AF$14,'IV. MA'!$AJ$14,'IV. MA'!$AN$14,'IV. MA'!$AR$14,'IV. MA'!$AV$14,'IV. MA'!$AZ$14,'IV. MA'!$BD$14,'IV. MA'!$BH$14,'IV. MA'!$BL$14,'IV. MA'!$BP$14,'IV. MA'!$BT$14),"")
C18: ==IF(6<=E11,"Periode "&E10&" (#6)","") | E18: ==IF(6<=E11,IFERROR(SUMIFS('Daten'!$BF$1:$BF$18,'Daten'!$BB$1:$BB$18,E10,'Daten'!$BD$1:$BD$18,6),0),"") | G18: ==IF(6<=E11,IFERROR(SUMIFS('Daten'!$BG$1:$BG$18,'Daten'!$BB$1:$BB$18,E10,'Daten'!$BD$1:$BD$18,6),0),"") | L18: Evaluierung | M18: ==IFERROR(CHOOSE($AD$5,'IV. MA'!$C$15,'IV. MA'!$G$15,'IV. MA'!$K$15,'IV. MA'!$O$15,'IV. MA'!$S$15,'IV. MA'!$W$15,'IV. MA'!$AA$15,'IV. MA'!$AE$15,'IV. MA'!$AI$15,'IV. MA'!$AM$15,'IV. MA'!$AQ$15,'IV. MA'!$AU$15,'IV. MA'!$AY$15,'IV. MA'!$BC$15,'IV. MA'!$BG$15,'IV. MA'!$BK$15,'IV. MA'!$BO$15,'IV. MA'!$BS$15),"") | N18: ==IFERROR(CHOOSE($AD$5,'IV. MA'!$D$15,'IV. MA'!$H$15,'IV. MA'!$L$15,'IV. MA'!$P$15,'IV. MA'!$T$15,'IV. MA'!$X$15,'IV. MA'!$AB$15,'IV. MA'!$AF$15,'IV. MA'!$AJ$15,'IV. MA'!$AN$15,'IV. MA'!$AR$15,'IV. MA'!$AV$15,'IV. MA'!$AZ$15,'IV. MA'!$BD$15,'IV. MA'!$BH$15,'IV. MA'!$BL$15,'IV. MA'!$BP$15,'IV. MA'!$BT$15),"")
L19: Audit | M19: ==IFERROR(CHOOSE($AD$5,'IV. MA'!$C$16,'IV. MA'!$G$16,'IV. MA'!$K$16,'IV. MA'!$O$16,'IV. MA'!$S$16,'IV. MA'!$W$16,'IV. MA'!$AA$16,'IV. MA'!$AE$16,'IV. MA'!$AI$16,'IV. MA'!$AM$16,'IV. MA'!$AQ$16,'IV. MA'!$AU$16,'IV. MA'!$AY$16,'IV. MA'!$BC$16,'IV. MA'!$BG$16,'IV. MA'!$BK$16,'IV. MA'!$BO$16,'IV. MA'!$BS$16),"") | N19: ==IFERROR(CHOOSE($AD$5,'IV. MA'!$D$16,'IV. MA'!$H$16,'IV. MA'!$L$16,'IV. MA'!$P$16,'IV. MA'!$T$16,'IV. MA'!$X$16,'IV. MA'!$AB$16,'IV. MA'!$AF$16,'IV. MA'!$AJ$16,'IV. MA'!$AN$16,'IV. MA'!$AR$16,'IV. MA'!$AV$16,'IV. MA'!$AZ$16,'IV. MA'!$BD$16,'IV. MA'!$BH$16,'IV. MA'!$BL$16,'IV. MA'!$BP$16,'IV. MA'!$BT$16),"")
B20: KMW-Mittelprüfung (Mittelanforderung) | L20: Reserve | M20: ==IFERROR(CHOOSE($AD$5,'IV. MA'!$C$17,'IV. MA'!$G$17,'IV. MA'!$K$17,'IV. MA'!$O$17,'IV. MA'!$S$17,'IV. MA'!$W$17,'IV. MA'!$AA$17,'IV. MA'!$AE$17,'IV. MA'!$AI$17,'IV. MA'!$AM$17,'IV. MA'!$AQ$17,'IV. MA'!$AU$17,'IV. MA'!$AY$17,'IV. MA'!$BC$17,'IV. MA'!$BG$17,'IV. MA'!$BK$17,'IV. MA'!$BO$17,'IV. MA'!$BS$17),"") | N20: ==IFERROR(CHOOSE($AD$5,'IV. MA'!$D$17,'IV. MA'!$H$17,'IV. MA'!$L$17,'IV. MA'!$P$17,'IV. MA'!$T$17,'IV. MA'!$X$17,'IV. MA'!$AB$17,'IV. MA'!$AF$17,'IV. MA'!$AJ$17,'IV. MA'!$AN$17,'IV. MA'!$AR$17,'IV. MA'!$AV$17,'IV. MA'!$AZ$17,'IV. MA'!$BD$17,'IV. MA'!$BH$17,'IV. MA'!$BL$17,'IV. MA'!$BP$17,'IV. MA'!$BT$17),"")
L21: SUMME | M21: ==IFERROR(CHOOSE($AD$5,'IV. MA'!$C$18,'IV. MA'!$G$18,'IV. MA'!$K$18,'IV. MA'!$O$18,'IV. MA'!$S$18,'IV. MA'!$W$18,'IV. MA'!$AA$18,'IV. MA'!$AE$18,'IV. MA'!$AI$18,'IV. MA'!$AM$18,'IV. MA'!$AQ$18,'IV. MA'!$AU$18,'IV. MA'!$AY$18,'IV. MA'!$BC$18,'IV. MA'!$BG$18,'IV. MA'!$BK$18,'IV. MA'!$BO$18,'IV. MA'!$BS$18),"") | N21: ==IFERROR(CHOOSE($AD$5,'IV. MA'!$D$18,'IV. MA'!$H$18,'IV. MA'!$L$18,'IV. MA'!$P$18,'IV. MA'!$T$18,'IV. MA'!$X$18,'IV. MA'!$AB$18,'IV. MA'!$AF$18,'IV. MA'!$AJ$18,'IV. MA'!$AN$18,'IV. MA'!$AR$18,'IV. MA'!$AV$18,'IV. MA'!$AZ$18,'IV. MA'!$BD$18,'IV. MA'!$BH$18,'IV. MA'!$BL$18,'IV. MA'!$BP$18,'IV. MA'!$BT$18),"")
B22: Bewilligte KMW-Mittel | D22: ==IFERROR(ROUND(KMW_Mittel_EUR,2),0) | F22: Abzugsoptionen KMW-Mittel
B23: Davon Reserve | D23: ==IFERROR(ROUND(Kosten_Reserve_EUR,2),0) | F23: Abzug | G23: Saldovortrag | I23: ==IFERROR(ROUND(Saldovortrag_EUR,2),0) | L23: Gesamtbedarf an Mitteln: | M23: ==IFERROR(CHOOSE($AD$5,'IV. MA'!$C$20,'IV. MA'!$G$20,'IV. MA'!$K$20,'IV. MA'!$O$20,'IV. MA'!$S$20,'IV. MA'!$W$20,'IV. MA'!$AA$20,'IV. MA'!$AE$20,'IV. MA'!$AI$20,'IV. MA'!$AM$20,'IV. MA'!$AQ$20,'IV. MA'!$AU$20,'IV. MA'!$AY$20,'IV. MA'!$BC$20,'IV. MA'!$BG$20,'IV. MA'!$BK$20,'IV. MA'!$BO$20,'IV. MA'!$BS$20),"") | N23: ==IFERROR(CHOOSE($AD$5,'IV. MA'!$D$20,'IV. MA'!$H$20,'IV. MA'!$L$20,'IV. MA'!$P$20,'IV. MA'!$T$20,'IV. MA'!$X$20,'IV. MA'!$AB$20,'IV. MA'!$AF$20,'IV. MA'!$AJ$20,'IV. MA'!$AN$20,'IV. MA'!$AR$20,'IV. MA'!$AV$20,'IV. MA'!$AZ$20,'IV. MA'!$BD$20,'IV. MA'!$BH$20,'IV. MA'!$BL$20,'IV. MA'!$BP$20,'IV. MA'!$BT$20),"")
B24: ==IF(Reserve_Freigabe="Ja","Operatives Budget (Reserve freigegeben)","Operatives Budget (abzgl. Reserve)") | D24: ==IF(Reserve_Freigabe="Ja",ROUND($D$22,2),ROUND($D$22-$D$23,2)) | F24: Abzug | G24: Mehreinnahmen | I24: ==I87 -> 0 | L24: abzüglich Eigenmittel: | M24: ==IFERROR(CHOOSE($AD$5,'IV. MA'!$C$21,'IV. MA'!$G$21,'IV. MA'!$K$21,'IV. MA'!$O$21,'IV. MA'!$S$21,'IV. MA'!$W$21,'IV. MA'!$AA$21,'IV. MA'!$AE$21,'IV. MA'!$AI$21,'IV. MA'!$AM$21,'IV. MA'!$AQ$21,'IV. MA'!$AU$21,'IV. MA'!$AY$21,'IV. MA'!$BC$21,'IV. MA'!$BG$21,'IV. MA'!$BK$21,'IV. MA'!$BO$21,'IV. MA'!$BS$21),"") | N24: ==IFERROR(CHOOSE($AD$5,'IV. MA'!$D$21,'IV. MA'!$H$21,'IV. MA'!$L$21,'IV. MA'!$P$21,'IV. MA'!$T$21,'IV. MA'!$X$21,'IV. MA'!$AB$21,'IV. MA'!$AF$21,'IV. MA'!$AJ$21,'IV. MA'!$AN$21,'IV. MA'!$AR$21,'IV. MA'!$AV$21,'IV. MA'!$AZ$21,'IV. MA'!$BD$21,'IV. MA'!$BH$21,'IV. MA'!$BL$21,'IV. MA'!$BP$21,'IV. MA'!$BT$21),"")
B25: Bereitgestellte KMW-Mittel | D25: ==IFERROR(ROUND(SUBTOTAL(109,TblKMWMittel[Betrag]),2),0) | F25: Abzug | G25: Prognostizierte Mehreinnahmen | I25: ==ROUND(MAX(0,MAX(0,(SUM($G$96:$G$99)-$G$98)+SUMIFS('Daten'!$BH$1:$BH$18,'Daten'!$BB$1:$BB$18,E10,'Daten'!$BD$1:$BD$18,"<="&E11,'Daten'!$BD$1:$BD$18,">=1")-(SUM($H$96:$H$99)-$H$98))-I87),2) -> 0 | L25: abzüglich Drittmittel: | M25: ==IFERROR(CHOOSE($AD$5,'IV. MA'!$C$22,'IV. MA'!$G$22,'IV. MA'!$K$22,'IV. MA'!$O$22,'IV. MA'!$S$22,'IV. MA'!$W$22,'IV. MA'!$AA$22,'IV. MA'!$AE$22,'IV. MA'!$AI$22,'IV. MA'!$AM$22,'IV. MA'!$AQ$22,'IV. MA'!$AU$22,'IV. MA'!$AY$22,'IV. MA'!$BC$22,'IV. MA'!$BG$22,'IV. MA'!$BK$22,'IV. MA'!$BO$22,'IV. MA'!$BS$22),"") | N25: ==IFERROR(CHOOSE($AD$5,'IV. MA'!$D$22,'IV. MA'!$H$22,'IV. MA'!$L$22,'IV. MA'!$P$22,'IV. MA'!$T$22,'IV. MA'!$X$22,'IV. MA'!$AB$22,'IV. MA'!$AF$22,'IV. MA'!$AJ$22,'IV. MA'!$AN$22,'IV. MA'!$AR$22,'IV. MA'!$AV$22,'IV. MA'!$AZ$22,'IV. MA'!$BD$22,'IV. MA'!$BH$22,'IV. MA'!$BL$22,'IV. MA'!$BP$22,'IV. MA'!$BT$22),"")
B26: Verfügbare KMW-Mittel | D26: ==ROUND($D$24-$D$25,2) | G26: Abzugsoptionen KMW insgesamt | I26: ==ROUND(IF($F$23="Abzug",MAX(0,$I$23),0)+IF($F$24="Abzug",MAX(0,$I$24),0)+IF($F$25="Abzug",MAX(0,$I$25),0),2) | L26: ==IFERROR(CHOOSE($AD$5,'IV. MA'!$B$23,'IV. MA'!$F$23,'IV. MA'!$J$23,'IV. MA'!$N$23,'IV. MA'!$R$23,'IV. MA'!$V$23,'IV. MA'!$Z$23,'IV. MA'!$AD$23,'IV. MA'!$AH$23,'IV. MA'!$AL$23,'IV. MA'!$AP$23,'IV. MA'!$AT$23,'IV. MA'!$AX$23,'IV. MA'!$BB$23,'IV. MA'!$BF$23,'IV. MA'!$BJ$23,'IV. MA'!$BN$23,'IV. MA'!$BR$23),"") | M26: ==IFERROR(CHOOSE($AD$5,'IV. MA'!$C$23,'IV. MA'!$G$23,'IV. MA'!$K$23,'IV. MA'!$O$23,'IV. MA'!$S$23,'IV. MA'!$W$23,'IV. MA'!$AA$23,'IV. MA'!$AE$23,'IV. MA'!$AI$23,'IV. MA'!$AM$23,'IV. MA'!$AQ$23,'IV. MA'!$AU$23,'IV. MA'!$AY$23,'IV. MA'!$BC$23,'IV. MA'!$BG$23,'IV. MA'!$BK$23,'IV. MA'!$BO$23,'IV. MA'!$BS$23),"") | N26: ==IFERROR(CHOOSE($AD$5,'IV. MA'!$D$23,'IV. MA'!$H$23,'IV. MA'!$L$23,'IV. MA'!$P$23,'IV. MA'!$T$23,'IV. MA'!$X$23,'IV. MA'!$AB$23,'IV. MA'!$AF$23,'IV. MA'!$AJ$23,'IV. MA'!$AN$23,'IV. MA'!$AR$23,'IV. MA'!$AV$23,'IV. MA'!$AZ$23,'IV. MA'!$BD$23,'IV. MA'!$BH$23,'IV. MA'!$BL$23,'IV. MA'!$BP$23,'IV. MA'!$BT$23),"")
G27: Verfügbare KMW-Mittel (bereinigt) | I27: ==ROUND($D$26-$I$26,2)
L28: KMW-Mittel Anforderung: | M28: ==IFERROR(CHOOSE($AD$5,'IV. MA'!$C$25,'IV. MA'!$G$25,'IV. MA'!$K$25,'IV. MA'!$O$25,'IV. MA'!$S$25,'IV. MA'!$W$25,'IV. MA'!$AA$25,'IV. MA'!$AE$25,'IV. MA'!$AI$25,'IV. MA'!$AM$25,'IV. MA'!$AQ$25,'IV. MA'!$AU$25,'IV. MA'!$AY$25,'IV. MA'!$BC$25,'IV. MA'!$BG$25,'IV. MA'!$BK$25,'IV. MA'!$BO$25,'IV. MA'!$BS$25),"") | N28: ==IFERROR(CHOOSE($AD$5,'IV. MA'!$D$25,'IV. MA'!$H$25,'IV. MA'!$L$25,'IV. MA'!$P$25,'IV. MA'!$T$25,'IV. MA'!$X$25,'IV. MA'!$AB$25,'IV. MA'!$AF$25,'IV. MA'!$AJ$25,'IV. MA'!$AN$25,'IV. MA'!$AR$25,'IV. MA'!$AV$25,'IV. MA'!$AZ$25,'IV. MA'!$BD$25,'IV. MA'!$BH$25,'IV. MA'!$BL$25,'IV. MA'!$BP$25,'IV. MA'!$BT$25),"")
B29: Abzüglich aktuelle Anforderung | D29: ==IFERROR(ROUND(SUMIFS('Daten'!$BV$1:$BV$198,'Daten'!$BT$1:$BT$198,"KMW-Mittel",'Daten'!$BR$1:$BR$198,E10,'Daten'!$BS$1:$BS$198,E11),2),0) | F29: Abzüglich aktuelle Anforderung | I29: ==IFERROR(ROUND(SUMIFS('Daten'!$BV$1:$BV$198,'Daten'!$BT$1:$BT$198,"KMW-Mittel",'Daten'!$BR$1:$BR$198,E10,'Daten'!$BS$1:$BS$198,E11),2),0)
B30: Verbleibende KMW-Mittel | D30: ==ROUND($D$26-MAX(0,$D$29),2) | F30: Verbleibende KMW-Mittel (bereinigt) | I30: ==ROUND($I$27-MAX(0,$I$29),2)
B32: Abzüglich manueller Betrag | D32: ==IFERROR(CHOOSE(E10,MA_ManBetrag_1,MA_ManBetrag_2,MA_ManBetrag_3,MA_ManBetrag_4,MA_ManBetrag_5,MA_ManBetrag_6,MA_ManBetrag_7,MA_ManBetrag_8,MA_ManBetrag_9,MA_ManBetrag_10,MA_ManBetrag_11,MA_ManBetrag_12,MA_ManBetrag_13,MA_ManBetrag_14,MA_ManBetrag_15,MA_ManBetrag_16,MA_ManBetrag_17,MA_ManBetrag_18),0) | F32: Abzüglich manueller Betrag | I32: ==IFERROR(CHOOSE(E10,MA_ManBetrag_1,MA_ManBetrag_2,MA_ManBetrag_3,MA_ManBetrag_4,MA_ManBetrag_5,MA_ManBetrag_6,MA_ManBetrag_7,MA_ManBetrag_8,MA_ManBetrag_9,MA_ManBetrag_10,MA_ManBetrag_11,MA_ManBetrag_12,MA_ManBetrag_13,MA_ManBetrag_14,MA_ManBetrag_15,MA_ManBetrag_16,MA_ManBetrag_17,MA_ManBetrag_18),0)
B33: Verbleibende KMW-Mittel | D33: ==ROUND(MAX(0,$D$26-MAX(0,$D$32)),2) | F33: Verbleibende KMW-Mittel (bereinigt) | I33: ==ROUND(MAX(0,$I$27-MAX(0,$I$32)),2)
B36: Monatslimit-Prüfung
C38: Lokalwährung | D38: Monate (von 12) | E38: Euro
B39: Anforderungshöhe | C39: ==IFERROR(ROUND(SUMIFS('Daten'!$BF$1:$BF$18,'Daten'!$BB$1:$BB$18,E10,'Daten'!$BD$1:$BD$18,"<="&E11,'Daten'!$BD$1:$BD$18,">=1"),2),0) | E39: ==IFERROR(ROUND(SUMIFS('Daten'!$BG$1:$BG$18,'Daten'!$BB$1:$BB$18,E10,'Daten'!$BD$1:$BD$18,"<="&E11,'Daten'!$BD$1:$BD$18,">=1"),2),0)
B40: Jahresbudget Jahr 1 | C40: ==IFERROR(ROUND(SUBTOTAL(109,TblBudgetAusgaben[Jahr 1]),2),0) | D40: 8 | E40: ==IFERROR(ROUND($C$40/Budget_Kurs,2),0)
B41: Jahresbudget Jahr 2 | C41: ==IFERROR(ROUND(SUBTOTAL(109,TblBudgetAusgaben[Jahr 2]),2),0) | D41: 0 | E41: ==IFERROR(ROUND($C$41/Budget_Kurs,2),0)
B42: Jahresbudget Jahr 3 | C42: ==IFERROR(ROUND(SUBTOTAL(109,TblBudgetAusgaben[Jahr 3]),2),0) | D42: 0 | E42: ==IFERROR(ROUND($C$42/Budget_Kurs,2),0)
B43: Limit-Monate (Summe Anteile) | C43: ==$D$40+$D$41+$D$42
B44: Bezugszeitraum (Monate, aus MA) | C44: ==IFERROR(CHOOSE(IFERROR(SUMPRODUCT('Daten'!$BA$1:$BA$18,('Daten'!$BB$1:$BB$18=E10)*('Daten'!$BD$1:$BD$18=E11)),0),'IV. MA'!$C$7,'IV. MA'!$G$7,'IV. MA'!$K$7,'IV. MA'!$O$7,'IV. MA'!$S$7,'IV. MA'!$W$7,'IV. MA'!$AA$7,'IV. MA'!$AE$7,'IV. MA'!$AI$7,'IV. MA'!$AM$7,'IV. MA'!$AQ$7,'IV. MA'!$AU$7,'IV. MA'!$AY$7,'IV. MA'!$BC$7,'IV. MA'!$BG$7,'IV. MA'!$BK$7,'IV. MA'!$BO$7,'IV. MA'!$BS$7),0)
B45: Monatslimit (anteilig) | C45: ==IFERROR(ROUND($C$40*$D$40/12+$C$41*$D$41/12+$C$42*$D$42/12,2),0) | E45: ==IFERROR(ROUND($E$40*$D$40/12+$E$41*$D$41/12+$E$42*$D$42/12,2),0)
B46: Status | C46: ==IF($C$39<=$C$45,"OK","ÜBERSCHRITTEN") | E46: ==IF($E$39<=$E$45,"OK","ÜBERSCHRITTEN")
B47: Überschreitung | C47: ==ROUND(MAX(0,$C$39-$C$45),2) | E47: ==ROUND(MAX(0,$E$39-$E$45),2)
B48: Auslastung % | C48: ==IFERROR($C$39/$C$45,0) | E48: ==IFERROR($E$39/$E$45,0)
B50: Prognostizierte Finanzierungsanteile
B52: Kategorie | C52: Prognose (LC) | D52: Budget (LC) | E52: Differenz (LC) | F52: Abweichung (LC) | G52: Prognose (EUR) | H52: Budget (EUR) | I52: Differenz (EUR) | J52: Abweichung (EUR)
B53: Eigenmittel | C53: ==IFERROR(ROUND(SUMIFS('Daten'!$BU$1:$BU$198,'Daten'!$BT$1:$BT$198,"Eigenmittel",'Daten'!$BR$1:$BR$198,E10,'Daten'!$BS$1:$BS$198,"<="&E11,'Daten'!$BS$1:$BS$198,">=1"),2),0) | D53: ==IFERROR(ROUND(Eigenmittel_LW,2),0) | E53: ==ROUND(IFERROR($C$53-$D$53,0),2) | F53: ==ROUND(IFERROR(($C$53/$D$53)-1,0),4) | G53: ==IFERROR(ROUND(SUMIFS('Daten'!$BV$1:$BV$198,'Daten'!$BT$1:$BT$198,"Eigenmittel",'Daten'!$BR$1:$BR$198,E10,'Daten'!$BS$1:$BS$198,"<="&E11,'Daten'!$BS$1:$BS$198,">=1"),2),0) | H53: ==IFERROR(ROUND(Eigenmittel_EUR,2),0) | I53: ==ROUND(IFERROR($G$53-$H$53,0),2) | J53: ==ROUND(IFERROR(($G$53/$H$53)-1,0),4)
B54: Drittmittel | C54: ==IFERROR(ROUND(SUMIFS('Daten'!$BU$1:$BU$198,'Daten'!$BT$1:$BT$198,"Drittmittel",'Daten'!$BR$1:$BR$198,E10,'Daten'!$BS$1:$BS$198,"<="&E11,'Daten'!$BS$1:$BS$198,">=1"),2),0) | D54: ==IFERROR(ROUND(Drittmittel_LW,2),0) | E54: ==ROUND(IFERROR($C$54-$D$54,0),2) | F54: ==ROUND(IFERROR(($C$54/$D$54)-1,0),4) | G54: ==IFERROR(ROUND(SUMIFS('Daten'!$BV$1:$BV$198,'Daten'!$BT$1:$BT$198,"Drittmittel",'Daten'!$BR$1:$BR$198,E10,'Daten'!$BS$1:$BS$198,"<="&E11,'Daten'!$BS$1:$BS$198,">=1"),2),0) | H54: ==IFERROR(ROUND(Drittmittel_EUR,2),0) | I54: ==ROUND(IFERROR($G$54-$H$54,0),2) | J54: ==ROUND(IFERROR(($G$54/$H$54)-1,0),4)
B55: KMW-Mittel | C55: ==IFERROR(ROUND(SUMIFS('Daten'!$BU$1:$BU$198,'Daten'!$BT$1:$BT$198,"KMW-Mittel",'Daten'!$BR$1:$BR$198,E10,'Daten'!$BS$1:$BS$198,"<="&E11,'Daten'!$BS$1:$BS$198,">=1"),2),0) | D55: ==IFERROR(ROUND(KMW_Mittel_LW,2),0) | E55: ==ROUND(IFERROR($C$55-$D$55,0),2) | F55: ==ROUND(IFERROR(($C$55/$D$55)-1,0),4) | G55: ==IFERROR(ROUND(SUMIFS('Daten'!$BV$1:$BV$198,'Daten'!$BT$1:$BT$198,"KMW-Mittel",'Daten'!$BR$1:$BR$198,E10,'Daten'!$BS$1:$BS$198,"<="&E11,'Daten'!$BS$1:$BS$198,">=1"),2),0) | H55: ==IFERROR(ROUND(KMW_Mittel_EUR,2),0) | I55: ==ROUND(IFERROR($G$55-$H$55,0),2) | J55: ==ROUND(IFERROR(($G$55/$H$55)-1,0),4)
B56: Zinsertraege | C56: ==IFERROR(ROUND(SUMIFS('Daten'!$BU$1:$BU$198,'Daten'!$BT$1:$BT$198,"Zinsertraege",'Daten'!$BR$1:$BR$198,E10,'Daten'!$BS$1:$BS$198,"<="&E11,'Daten'!$BS$1:$BS$198,">=1"),2),0) | D56: ==IFERROR(ROUND(0,2),0) | E56: ==ROUND(IFERROR($C$56-$D$56,0),2) | F56: ==ROUND(IFERROR(($C$56/$D$56)-1,0),4) | G56: ==IFERROR(ROUND(SUMIFS('Daten'!$BV$1:$BV$198,'Daten'!$BT$1:$BT$198,"Zinsertraege",'Daten'!$BR$1:$BR$198,E10,'Daten'!$BS$1:$BS$198,"<="&E11,'Daten'!$BS$1:$BS$198,">=1"),2),0) | H56: ==IFERROR(ROUND(0,2),0) | I56: ==ROUND(IFERROR($G$56-$H$56,0),2) | J56: ==ROUND(IFERROR(($G$56/$H$56)-1,0),4)
B57: GESAMT | C57: ==ROUND(SUM($C$53:$C$56),2) | D57: ==ROUND(SUM($D$53:$D$56),2) | E57: ==ROUND(SUM($E$53:$E$56),2) | F57: ==ROUND(IFERROR(($C$57/$D$57)-1,0),4) | G57: ==ROUND(SUM($G$53:$G$56),2) | H57: ==ROUND(SUM($H$53:$H$56),2) | I57: ==ROUND(SUM($I$53:$I$56),2) | J57: ==ROUND(IFERROR(($G$57/$H$57)-1,0),4)
B59: Prognoseprüfung (Ausgaben)
B61: Kategorie | C61: Prognose (LC) | D61: Budget (LC) | E61: Differenz (LC) | F61: Abweichung (LC) | G61: Prognose (EUR) | H61: Budget (EUR) | I61: Differenz (EUR) | J61: Abweichung (EUR)
B62: Bauausgaben | C62: ==IFERROR(ROUND(SUMIFS('Daten'!$BU$1:$BU$198,'Daten'!$BT$1:$BT$198,"Bauausgaben",'Daten'!$BR$1:$BR$198,E10,'Daten'!$BS$1:$BS$198,"<="&E11,'Daten'!$BS$1:$BS$198,">=1"),2),0) | D62: ==IFERROR(ROUND(Kosten_Bauausgaben_LW,2),0) | E62: ==ROUND(IFERROR($C$62-$D$62,0),2) | F62: ==ROUND(IFERROR(($C$62/$D$62)-1,0),4) | G62: ==IFERROR(ROUND(SUMIFS('Daten'!$BV$1:$BV$198,'Daten'!$BT$1:$BT$198,"Bauausgaben",'Daten'!$BR$1:$BR$198,E10,'Daten'!$BS$1:$BS$198,"<="&E11,'Daten'!$BS$1:$BS$198,">=1"),2),0) | H62: ==IFERROR(ROUND(Kosten_Bauausgaben_EUR,2),0) | I62: ==ROUND(IFERROR($G$62-$H$62,0),2) | J62: ==ROUND(IFERROR(($G$62/$H$62)-1,0),4)
B63: Investitionen | C63: ==IFERROR(ROUND(SUMIFS('Daten'!$BU$1:$BU$198,'Daten'!$BT$1:$BT$198,"Investitionen",'Daten'!$BR$1:$BR$198,E10,'Daten'!$BS$1:$BS$198,"<="&E11,'Daten'!$BS$1:$BS$198,">=1"),2),0) | D63: ==IFERROR(ROUND(Kosten_Investitionen_LW,2),0) | E63: ==ROUND(IFERROR($C$63-$D$63,0),2) | F63: ==ROUND(IFERROR(($C$63/$D$63)-1,0),4) | G63: ==IFERROR(ROUND(SUMIFS('Daten'!$BV$1:$BV$198,'Daten'!$BT$1:$BT$198,"Investitionen",'Daten'!$BR$1:$BR$198,E10,'Daten'!$BS$1:$BS$198,"<="&E11,'Daten'!$BS$1:$BS$198,">=1"),2),0) | H63: ==IFERROR(ROUND(Kosten_Investitionen_EUR,2),0) | I63: ==ROUND(IFERROR($G$63-$H$63,0),2) | J63: ==ROUND(IFERROR(($G$63/$H$63)-1,0),4)
B64: Personalkosten | C64: ==IFERROR(ROUND(SUMIFS('Daten'!$BU$1:$BU$198,'Daten'!$BT$1:$BT$198,"Personalkosten",'Daten'!$BR$1:$BR$198,E10,'Daten'!$BS$1:$BS$198,"<="&E11,'Daten'!$BS$1:$BS$198,">=1"),2),0) | D64: ==IFERROR(ROUND(Kosten_Personalkosten_LW,2),0) | E64: ==ROUND(IFERROR($C$64-$D$64,0),2) | F64: ==ROUND(IFERROR(($C$64/$D$64)-1,0),4) | G64: ==IFERROR(ROUND(SUMIFS('Daten'!$BV$1:$BV$198,'Daten'!$BT$1:$BT$198,"Personalkosten",'Daten'!$BR$1:$BR$198,E10,'Daten'!$BS$1:$BS$198,"<="&E11,'Daten'!$BS$1:$BS$198,">=1"),2),0) | H64: ==IFERROR(ROUND(Kosten_Personalkosten_EUR,2),0) | I64: ==ROUND(IFERROR($G$64-$H$64,0),2) | J64: ==ROUND(IFERROR(($G$64/$H$64)-1,0),4)
B65: Projektaktivitaeten | C65: ==IFERROR(ROUND(SUMIFS('Daten'!$BU$1:$BU$198,'Daten'!$BT$1:$BT$198,"Projektaktivitaeten",'Daten'!$BR$1:$BR$198,E10,'Daten'!$BS$1:$BS$198,"<="&E11,'Daten'!$BS$1:$BS$198,">=1"),2),0) | D65: ==IFERROR(ROUND(Kosten_Projektaktivitaeten_LW,2),0) | E65: ==ROUND(IFERROR($C$65-$D$65,0),2) | F65: ==ROUND(IFERROR(($C$65/$D$65)-1,0),4) | G65: ==IFERROR(ROUND(SUMIFS('Daten'!$BV$1:$BV$198,'Daten'!$BT$1:$BT$198,"Projektaktivitaeten",'Daten'!$BR$1:$BR$198,E10,'Daten'!$BS$1:$BS$198,"<="&E11,'Daten'!$BS$1:$BS$198,">=1"),2),0) | H65: ==IFERROR(ROUND(Kosten_Projektaktivitaeten_EUR,2),0) | I65: ==ROUND(IFERROR($G$65-$H$65,0),2) | J65: ==ROUND(IFERROR(($G$65/$H$65)-1,0),4)
B66: Projektverwaltung | C66: ==IFERROR(ROUND(SUMIFS('Daten'!$BU$1:$BU$198,'Daten'!$BT$1:$BT$198,"Projektverwaltung",'Daten'!$BR$1:$BR$198,E10,'Daten'!$BS$1:$BS$198,"<="&E11,'Daten'!$BS$1:$BS$198,">=1"),2),0) | D66: ==IFERROR(ROUND(Kosten_Projektverwaltung_LW,2),0) | E66: ==ROUND(IFERROR($C$66-$D$66,0),2) | F66: ==ROUND(IFERROR(($C$66/$D$66)-1,0),4) | G66: ==IFERROR(ROUND(SUMIFS('Daten'!$BV$1:$BV$198,'Daten'!$BT$1:$BT$198,"Projektverwaltung",'Daten'!$BR$1:$BR$198,E10,'Daten'!$BS$1:$BS$198,"<="&E11,'Daten'!$BS$1:$BS$198,">=1"),2),0) | H66: ==IFERROR(ROUND(Kosten_Projektverwaltung_EUR,2),0) | I66: ==ROUND(IFERROR($G$66-$H$66,0),2) | J66: ==ROUND(IFERROR(($G$66/$H$66)-1,0),4)
B67: Evaluierung | C67: ==IFERROR(ROUND(SUMIFS('Daten'!$BU$1:$BU$198,'Daten'!$BT$1:$BT$198,"Evaluierung",'Daten'!$BR$1:$BR$198,E10,'Daten'!$BS$1:$BS$198,"<="&E11,'Daten'!$BS$1:$BS$198,">=1"),2),0) | D67: ==IFERROR(ROUND(Kosten_Evaluierung_LW,2),0) | E67: ==ROUND(IFERROR($C$67-$D$67,0),2) | F67: ==ROUND(IFERROR(($C$67/$D$67)-1,0),4) | G67: ==IFERROR(ROUND(SUMIFS('Daten'!$BV$1:$BV$198,'Daten'!$BT$1:$BT$198,"Evaluierung",'Daten'!$BR$1:$BR$198,E10,'Daten'!$BS$1:$BS$198,"<="&E11,'Daten'!$BS$1:$BS$198,">=1"),2),0) | H67: ==IFERROR(ROUND(Kosten_Evaluierung_EUR,2),0) | I67: ==ROUND(IFERROR($G$67-$H$67,0),2) | J67: ==ROUND(IFERROR(($G$67/$H$67)-1,0),4)
B68: Audit | C68: ==IFERROR(ROUND(SUMIFS('Daten'!$BU$1:$BU$198,'Daten'!$BT$1:$BT$198,"Audit",'Daten'!$BR$1:$BR$198,E10,'Daten'!$BS$1:$BS$198,"<="&E11,'Daten'!$BS$1:$BS$198,">=1"),2),0) | D68: ==IFERROR(ROUND(Kosten_Audit_LW,2),0) | E68: ==ROUND(IFERROR($C$68-$D$68,0),2) | F68: ==ROUND(IFERROR(($C$68/$D$68)-1,0),4) | G68: ==IFERROR(ROUND(SUMIFS('Daten'!$BV$1:$BV$198,'Daten'!$BT$1:$BT$198,"Audit",'Daten'!$BR$1:$BR$198,E10,'Daten'!$BS$1:$BS$198,"<="&E11,'Daten'!$BS$1:$BS$198,">=1"),2),0) | H68: ==IFERROR(ROUND(Kosten_Audit_EUR,2),0) | I68: ==ROUND(IFERROR($G$68-$H$68,0),2) | J68: ==ROUND(IFERROR(($G$68/$H$68)-1,0),4)
B69: Reserve | C69: ==IFERROR(ROUND(SUMIFS('Daten'!$BU$1:$BU$198,'Daten'!$BT$1:$BT$198,"Reserve",'Daten'!$BR$1:$BR$198,E10,'Daten'!$BS$1:$BS$198,"<="&E11,'Daten'!$BS$1:$BS$198,">=1"),2),0) | D69: ==IFERROR(ROUND(Kosten_Reserve_LW,2),0) | E69: ==ROUND(IFERROR($C$69-$D$69,0),2) | F69: ==ROUND(IFERROR(($C$69/$D$69)-1,0),4) | G69: ==IFERROR(ROUND(SUMIFS('Daten'!$BV$1:$BV$198,'Daten'!$BT$1:$BT$198,"Reserve",'Daten'!$BR$1:$BR$198,E10,'Daten'!$BS$1:$BS$198,"<="&E11,'Daten'!$BS$1:$BS$198,">=1"),2),0) | H69: ==IFERROR(ROUND(Kosten_Reserve_EUR,2),0) | I69: ==ROUND(IFERROR($G$69-$H$69,0),2) | J69: ==ROUND(IFERROR(($G$69/$H$69)-1,0),4)
B70: GESAMT | C70: ==ROUND(SUM($C$62:$C$69),2) | D70: ==ROUND(SUM($D$62:$D$69),2) | E70: ==ROUND(SUM($E$62:$E$69),2) | F70: ==ROUND(IFERROR(($C$70/$D$70)-1,0),4) | G70: ==ROUND(SUM($G$62:$G$69),2) | H70: ==ROUND(SUM($H$62:$H$69),2) | I70: ==ROUND(SUM($I$62:$I$69),2) | J70: ==ROUND(IFERROR(($G$70/$H$70)-1,0),4)
B76: FINANZBERICHTSPRÜFUNG | L76: ==IF(E81=0,"Aktueller Finanzbericht (keiner gewählt)","Aktueller Finanzbericht – Periode "&E81)
B77: Basis: ausgewählter Finanzbericht (kumulativ bis zur Periode) | L77: Periode: | M77: ==IFERROR(CHOOSE(E81,'III. Finanzberichte'!$C$4,'III. Finanzberichte'!$J$4,'III. Finanzberichte'!$Q$4,'III. Finanzberichte'!$X$4,'III. Finanzberichte'!$AE$4,'III. Finanzberichte'!$AL$4,'III. Finanzberichte'!$AS$4,'III. Finanzberichte'!$AZ$4,'III. Finanzberichte'!$BG$4,'III. Finanzberichte'!$BN$4,'III. Finanzberichte'!$BU$4,'III. Finanzberichte'!$CB$4,'III. Finanzberichte'!$CI$4,'III. Finanzberichte'!$CP$4,'III. Finanzberichte'!$CW$4,'III. Finanzberichte'!$DD$4,'III. Finanzberichte'!$DK$4,'III. Finanzberichte'!$DR$4),"")
L78: Von: | M78: ==IFERROR(CHOOSE(E81,'III. Finanzberichte'!$C$5,'III. Finanzberichte'!$J$5,'III. Finanzberichte'!$Q$5,'III. Finanzberichte'!$X$5,'III. Finanzberichte'!$AE$5,'III. Finanzberichte'!$AL$5,'III. Finanzberichte'!$AS$5,'III. Finanzberichte'!$AZ$5,'III. Finanzberichte'!$BG$5,'III. Finanzberichte'!$BN$5,'III. Finanzberichte'!$BU$5,'III. Finanzberichte'!$CB$5,'III. Finanzberichte'!$CI$5,'III. Finanzberichte'!$CP$5,'III. Finanzberichte'!$CW$5,'III. Finanzberichte'!$DD$5,'III. Finanzberichte'!$DK$5,'III. Finanzberichte'!$DR$5),"")
C79: Finanzbericht auswählen | L79: Bis: | M79: ==IFERROR(CHOOSE(E81,'III. Finanzberichte'!$C$6,'III. Finanzberichte'!$J$6,'III. Finanzberichte'!$Q$6,'III. Finanzberichte'!$X$6,'III. Finanzberichte'!$AE$6,'III. Finanzberichte'!$AL$6,'III. Finanzberichte'!$AS$6,'III. Finanzberichte'!$AZ$6,'III. Finanzberichte'!$BG$6,'III. Finanzberichte'!$BN$6,'III. Finanzberichte'!$BU$6,'III. Finanzberichte'!$CB$6,'III. Finanzberichte'!$CI$6,'III. Finanzberichte'!$CP$6,'III. Finanzberichte'!$CW$6,'III. Finanzberichte'!$DD$6,'III. Finanzberichte'!$DK$6,'III. Finanzberichte'!$DR$6),"")
C80: Auswahl: | E80: Neuester FB | L80: Zeitraum: | M80: ==IFERROR(CHOOSE(E81,'III. Finanzberichte'!$C$7,'III. Finanzberichte'!$J$7,'III. Finanzberichte'!$Q$7,'III. Finanzberichte'!$X$7,'III. Finanzberichte'!$AE$7,'III. Finanzberichte'!$AL$7,'III. Finanzberichte'!$AS$7,'III. Finanzberichte'!$AZ$7,'III. Finanzberichte'!$BG$7,'III. Finanzberichte'!$BN$7,'III. Finanzberichte'!$BU$7,'III. Finanzberichte'!$CB$7,'III. Finanzberichte'!$CI$7,'III. Finanzberichte'!$CP$7,'III. Finanzberichte'!$CW$7,'III. Finanzberichte'!$DD$7,'III. Finanzberichte'!$DK$7,'III. Finanzberichte'!$DR$7),"")
C81: Geprüfte Periode | E81: ==IF(E80="Neuester FB",IFERROR(SUMPRODUCT(MAX(('Daten'!$BK$1:$BK$18=1)*'Daten'!$BJ$1:$BJ$18)),0),IF(LEFT(E80,8)="Periode ",IFERROR(VALUE(TRIM(MID(E80,9,5))),0),0)) | L81: Durchschnittskurs: | M81: ==IFERROR(CHOOSE(E81,'III. Finanzberichte'!$C$8,'III. Finanzberichte'!$J$8,'III. Finanzberichte'!$Q$8,'III. Finanzberichte'!$X$8,'III. Finanzberichte'!$AE$8,'III. Finanzberichte'!$AL$8,'III. Finanzberichte'!$AS$8,'III. Finanzberichte'!$AZ$8,'III. Finanzberichte'!$BG$8,'III. Finanzberichte'!$BN$8,'III. Finanzberichte'!$BU$8,'III. Finanzberichte'!$CB$8,'III. Finanzberichte'!$CI$8,'III. Finanzberichte'!$CP$8,'III. Finanzberichte'!$CW$8,'III. Finanzberichte'!$DD$8,'III. Finanzberichte'!$DK$8,'III. Finanzberichte'!$DR$8),"")
B83: KMW-Mittelprüfung | L83: Einnahmen
L84: Typ / ID | M84: Einnahmen (LC) | N84: Einnahmen (EUR) | O84: Kum. Einnahmen (LC) | P84: Kum. Einnahmen (EUR)
B85: Bewilligte KMW-Mittel | D85: ==IFERROR(ROUND(KMW_Mittel_EUR,2),0) | F85: Abzugsoptionen KMW-Mittel | L85: ==IFERROR(CHOOSE(E81,'III. Finanzberichte'!$B$11,'III. Finanzberichte'!$I$11,'III. Finanzberichte'!$P$11,'III. Finanzberichte'!$W$11,'III. Finanzberichte'!$AD$11,'III. Finanzberichte'!$AK$11,'III. Finanzberichte'!$AR$11,'III. Finanzberichte'!$AY$11,'III. Finanzberichte'!$BF$11,'III. Finanzberichte'!$BM$11,'III. Finanzberichte'!$BT$11,'III. Finanzberichte'!$CA$11,'III. Finanzberichte'!$CH$11,'III. Finanzberichte'!$CO$11,'III. Finanzberichte'!$CV$11,'III. Finanzberichte'!$DC$11,'III. Finanzberichte'!$DJ$11,'III. Finanzberichte'!$DQ$11),"") | M85: ==IFERROR(CHOOSE(E81,'III. Finanzberichte'!$C$11,'III. Finanzberichte'!$J$11,'III. Finanzberichte'!$Q$11,'III. Finanzberichte'!$X$11,'III. Finanzberichte'!$AE$11,'III. Finanzberichte'!$AL$11,'III. Finanzberichte'!$AS$11,'III. Finanzberichte'!$AZ$11,'III. Finanzberichte'!$BG$11,'III. Finanzberichte'!$BN$11,'III. Finanzberichte'!$BU$11,'III. Finanzberichte'!$CB$11,'III. Finanzberichte'!$CI$11,'III. Finanzberichte'!$CP$11,'III. Finanzberichte'!$CW$11,'III. Finanzberichte'!$DD$11,'III. Finanzberichte'!$DK$11,'III. Finanzberichte'!$DR$11),"") | N85: ==IFERROR(CHOOSE(E81,'III. Finanzberichte'!$D$11,'III. Finanzberichte'!$K$11,'III. Finanzberichte'!$R$11,'III. Finanzberichte'!$Y$11,'III. Finanzberichte'!$AF$11,'III. Finanzberichte'!$AM$11,'III. Finanzberichte'!$AT$11,'III. Finanzberichte'!$BA$11,'III. Finanzberichte'!$BH$11,'III. Finanzberichte'!$BO$11,'III. Finanzberichte'!$BV$11,'III. Finanzberichte'!$CC$11,'III. Finanzberichte'!$CJ$11,'III. Finanzberichte'!$CQ$11,'III. Finanzberichte'!$CX$11,'III. Finanzberichte'!$DE$11,'III. Finanzberichte'!$DL$11,'III. Finanzberichte'!$DS$11),"") | O85: ==IFERROR(CHOOSE(E81,'III. Finanzberichte'!$E$11,'III. Finanzberichte'!$L$11,'III. Finanzberichte'!$S$11,'III. Finanzberichte'!$Z$11,'III. Finanzberichte'!$AG$11,'III. Finanzberichte'!$AN$11,'III. Finanzberichte'!$AU$11,'III. Finanzberichte'!$BB$11,'III. Finanzberichte'!$BI$11,'III. Finanzberichte'!$BP$11,'III. Finanzberichte'!$BW$11,'III. Finanzberichte'!$CD$11,'III. Finanzberichte'!$CK$11,'III. Finanzberichte'!$CR$11,'III. Finanzberichte'!$CY$11,'III. Finanzberichte'!$DF$11,'III. Finanzberichte'!$DM$11,'III. Finanzberichte'!$DT$11),"") | P85: ==IFERROR(CHOOSE(E81,'III. Finanzberichte'!$F$11,'III. Finanzberichte'!$M$11,'III. Finanzberichte'!$T$11,'III. Finanzberichte'!$AA$11,'III. Finanzberichte'!$AH$11,'III. Finanzberichte'!$AO$11,'III. Finanzberichte'!$AV$11,'III. Finanzberichte'!$BC$11,'III. Finanzberichte'!$BJ$11,'III. Finanzberichte'!$BQ$11,'III. Finanzberichte'!$BX$11,'III. Finanzberichte'!$CE$11,'III. Finanzberichte'!$CL$11,'III. Finanzberichte'!$CS$11,'III. Finanzberichte'!$CZ$11,'III. Finanzberichte'!$DG$11,'III. Finanzberichte'!$DN$11,'III. Finanzberichte'!$DU$11),"")
B86: Davon Reserve | D86: ==IFERROR(ROUND(Kosten_Reserve_EUR,2),0) | F86: Abzug | G86: Saldovortrag | I86: ==IFERROR(ROUND(Saldovortrag_EUR,2),0) | L86: Eigenmittel | M86: ==IFERROR(CHOOSE(E81,'III. Finanzberichte'!$C$12,'III. Finanzberichte'!$J$12,'III. Finanzberichte'!$Q$12,'III. Finanzberichte'!$X$12,'III. Finanzberichte'!$AE$12,'III. Finanzberichte'!$AL$12,'III. Finanzberichte'!$AS$12,'III. Finanzberichte'!$AZ$12,'III. Finanzberichte'!$BG$12,'III. Finanzberichte'!$BN$12,'III. Finanzberichte'!$BU$12,'III. Finanzberichte'!$CB$12,'III. Finanzberichte'!$CI$12,'III. Finanzberichte'!$CP$12,'III. Finanzberichte'!$CW$12,'III. Finanzberichte'!$DD$12,'III. Finanzberichte'!$DK$12,'III. Finanzberichte'!$DR$12),"") | N86: ==IFERROR(CHOOSE(E81,'III. Finanzberichte'!$D$12,'III. Finanzberichte'!$K$12,'III. Finanzberichte'!$R$12,'III. Finanzberichte'!$Y$12,'III. Finanzberichte'!$AF$12,'III. Finanzberichte'!$AM$12,'III. Finanzberichte'!$AT$12,'III. Finanzberichte'!$BA$12,'III. Finanzberichte'!$BH$12,'III. Finanzberichte'!$BO$12,'III. Finanzberichte'!$BV$12,'III. Finanzberichte'!$CC$12,'III. Finanzberichte'!$CJ$12,'III. Finanzberichte'!$CQ$12,'III. Finanzberichte'!$CX$12,'III. Finanzberichte'!$DE$12,'III. Finanzberichte'!$DL$12,'III. Finanzberichte'!$DS$12),"") | O86: ==IFERROR(CHOOSE(E81,'III. Finanzberichte'!$E$12,'III. Finanzberichte'!$L$12,'III. Finanzberichte'!$S$12,'III. Finanzberichte'!$Z$12,'III. Finanzberichte'!$AG$12,'III. Finanzberichte'!$AN$12,'III. Finanzberichte'!$AU$12,'III. Finanzberichte'!$BB$12,'III. Finanzberichte'!$BI$12,'III. Finanzberichte'!$BP$12,'III. Finanzberichte'!$BW$12,'III. Finanzberichte'!$CD$12,'III. Finanzberichte'!$CK$12,'III. Finanzberichte'!$CR$12,'III. Finanzberichte'!$CY$12,'III. Finanzberichte'!$DF$12,'III. Finanzberichte'!$DM$12,'III. Finanzberichte'!$DT$12),"") | P86: ==IFERROR(CHOOSE(E81,'III. Finanzberichte'!$F$12,'III. Finanzberichte'!$M$12,'III. Finanzberichte'!$T$12,'III. Finanzberichte'!$AA$12,'III. Finanzberichte'!$AH$12,'III. Finanzberichte'!$AO$12,'III. Finanzberichte'!$AV$12,'III. Finanzberichte'!$BC$12,'III. Finanzberichte'!$BJ$12,'III. Finanzberichte'!$BQ$12,'III. Finanzberichte'!$BX$12,'III. Finanzberichte'!$CE$12,'III. Finanzberichte'!$CL$12,'III. Finanzberichte'!$CS$12,'III. Finanzberichte'!$CZ$12,'III. Finanzberichte'!$DG$12,'III. Finanzberichte'!$DN$12,'III. Finanzberichte'!$DU$12),"")
B87: ==IF(Reserve_Freigabe="Ja","Operatives Budget (Reserve freigegeben)","Operatives Budget (abzgl. Reserve)") | D87: ==IF(Reserve_Freigabe="Ja",ROUND($D$85,2),ROUND($D$85-$D$86,2)) | F87: Abzug | G87: Mehreinnahmen | I87: ==IFERROR(ROUND(MAX(0,(SUM($G$96:$G$99)-$G$98)-(SUM($H$96:$H$99)-$H$98)),2),0) -> 0 | L87: Drittmittel | M87: ==IFERROR(CHOOSE(E81,'III. Finanzberichte'!$C$13,'III. Finanzberichte'!$J$13,'III. Finanzberichte'!$Q$13,'III. Finanzberichte'!$X$13,'III. Finanzberichte'!$AE$13,'III. Finanzberichte'!$AL$13,'III. Finanzberichte'!$AS$13,'III. Finanzberichte'!$AZ$13,'III. Finanzberichte'!$BG$13,'III. Finanzberichte'!$BN$13,'III. Finanzberichte'!$BU$13,'III. Finanzberichte'!$CB$13,'III. Finanzberichte'!$CI$13,'III. Finanzberichte'!$CP$13,'III. Finanzberichte'!$CW$13,'III. Finanzberichte'!$DD$13,'III. Finanzberichte'!$DK$13,'III. Finanzberichte'!$DR$13),"") | N87: ==IFERROR(CHOOSE(E81,'III. Finanzberichte'!$D$13,'III. Finanzberichte'!$K$13,'III. Finanzberichte'!$R$13,'III. Finanzberichte'!$Y$13,'III. Finanzberichte'!$AF$13,'III. Finanzberichte'!$AM$13,'III. Finanzberichte'!$AT$13,'III. Finanzberichte'!$BA$13,'III. Finanzberichte'!$BH$13,'III. Finanzberichte'!$BO$13,'III. Finanzberichte'!$BV$13,'III. Finanzberichte'!$CC$13,'III. Finanzberichte'!$CJ$13,'III. Finanzberichte'!$CQ$13,'III. Finanzberichte'!$CX$13,'III. Finanzberichte'!$DE$13,'III. Finanzberichte'!$DL$13,'III. Finanzberichte'!$DS$13),"") | O87: ==IFERROR(CHOOSE(E81,'III. Finanzberichte'!$E$13,'III. Finanzberichte'!$L$13,'III. Finanzberichte'!$S$13,'III. Finanzberichte'!$Z$13,'III. Finanzberichte'!$AG$13,'III. Finanzberichte'!$AN$13,'III. Finanzberichte'!$AU$13,'III. Finanzberichte'!$BB$13,'III. Finanzberichte'!$BI$13,'III. Finanzberichte'!$BP$13,'III. Finanzberichte'!$BW$13,'III. Finanzberichte'!$CD$13,'III. Finanzberichte'!$CK$13,'III. Finanzberichte'!$CR$13,'III. Finanzberichte'!$CY$13,'III. Finanzberichte'!$DF$13,'III. Finanzberichte'!$DM$13,'III. Finanzberichte'!$DT$13),"") | P87: ==IFERROR(CHOOSE(E81,'III. Finanzberichte'!$F$13,'III. Finanzberichte'!$M$13,'III. Finanzberichte'!$T$13,'III. Finanzberichte'!$AA$13,'III. Finanzberichte'!$AH$13,'III. Finanzberichte'!$AO$13,'III. Finanzberichte'!$AV$13,'III. Finanzberichte'!$BC$13,'III. Finanzberichte'!$BJ$13,'III. Finanzberichte'!$BQ$13,'III. Finanzberichte'!$BX$13,'III. Finanzberichte'!$CE$13,'III. Finanzberichte'!$CL$13,'III. Finanzberichte'!$CS$13,'III. Finanzberichte'!$CZ$13,'III. Finanzberichte'!$DG$13,'III. Finanzberichte'!$DN$13,'III. Finanzberichte'!$DU$13),"")
B88: Bereitgestellte KMW-Mittel | D88: ==IFERROR(ROUND(SUBTOTAL(109,TblKMWMittel[Betrag]),2),0) | G88: Abzugsoptionen KMW insgesamt | I88: ==ROUND(IF($F$86="Abzug",MAX(0,$I$86),0)+IF($F$87="Abzug",MAX(0,$I$87),0),2) | L88: KMW-Mittel | M88: ==IFERROR(CHOOSE(E81,'III. Finanzberichte'!$C$14,'III. Finanzberichte'!$J$14,'III. Finanzberichte'!$Q$14,'III. Finanzberichte'!$X$14,'III. Finanzberichte'!$AE$14,'III. Finanzberichte'!$AL$14,'III. Finanzberichte'!$AS$14,'III. Finanzberichte'!$AZ$14,'III. Finanzberichte'!$BG$14,'III. Finanzberichte'!$BN$14,'III. Finanzberichte'!$BU$14,'III. Finanzberichte'!$CB$14,'III. Finanzberichte'!$CI$14,'III. Finanzberichte'!$CP$14,'III. Finanzberichte'!$CW$14,'III. Finanzberichte'!$DD$14,'III. Finanzberichte'!$DK$14,'III. Finanzberichte'!$DR$14),"") | N88: ==IFERROR(CHOOSE(E81,'III. Finanzberichte'!$D$14,'III. Finanzberichte'!$K$14,'III. Finanzberichte'!$R$14,'III. Finanzberichte'!$Y$14,'III. Finanzberichte'!$AF$14,'III. Finanzberichte'!$AM$14,'III. Finanzberichte'!$AT$14,'III. Finanzberichte'!$BA$14,'III. Finanzberichte'!$BH$14,'III. Finanzberichte'!$BO$14,'III. Finanzberichte'!$BV$14,'III. Finanzberichte'!$CC$14,'III. Finanzberichte'!$CJ$14,'III. Finanzberichte'!$CQ$14,'III. Finanzberichte'!$CX$14,'III. Finanzberichte'!$DE$14,'III. Finanzberichte'!$DL$14,'III. Finanzberichte'!$DS$14),"") | O88: ==IFERROR(CHOOSE(E81,'III. Finanzberichte'!$E$14,'III. Finanzberichte'!$L$14,'III. Finanzberichte'!$S$14,'III. Finanzberichte'!$Z$14,'III. Finanzberichte'!$AG$14,'III. Finanzberichte'!$AN$14,'III. Finanzberichte'!$AU$14,'III. Finanzberichte'!$BB$14,'III. Finanzberichte'!$BI$14,'III. Finanzberichte'!$BP$14,'III. Finanzberichte'!$BW$14,'III. Finanzberichte'!$CD$14,'III. Finanzberichte'!$CK$14,'III. Finanzberichte'!$CR$14,'III. Finanzberichte'!$CY$14,'III. Finanzberichte'!$DF$14,'III. Finanzberichte'!$DM$14,'III. Finanzberichte'!$DT$14),"") | P88: ==IFERROR(CHOOSE(E81,'III. Finanzberichte'!$F$14,'III. Finanzberichte'!$M$14,'III. Finanzberichte'!$T$14,'III. Finanzberichte'!$AA$14,'III. Finanzberichte'!$AH$14,'III. Finanzberichte'!$AO$14,'III. Finanzberichte'!$AV$14,'III. Finanzberichte'!$BC$14,'III. Finanzberichte'!$BJ$14,'III. Finanzberichte'!$BQ$14,'III. Finanzberichte'!$BX$14,'III. Finanzberichte'!$CE$14,'III. Finanzberichte'!$CL$14,'III. Finanzberichte'!$CS$14,'III. Finanzberichte'!$CZ$14,'III. Finanzberichte'!$DG$14,'III. Finanzberichte'!$DN$14,'III. Finanzberichte'!$DU$14),"")
B89: Verfügbare KMW-Mittel | D89: ==ROUND($D$87-$D$88,2) | G89: Verfügbare KMW-Mittel (bereinigt) | I89: ==ROUND($D$89-$I$88,2) | L89: Zinsertraege | M89: ==IFERROR(CHOOSE(E81,'III. Finanzberichte'!$C$15,'III. Finanzberichte'!$J$15,'III. Finanzberichte'!$Q$15,'III. Finanzberichte'!$X$15,'III. Finanzberichte'!$AE$15,'III. Finanzberichte'!$AL$15,'III. Finanzberichte'!$AS$15,'III. Finanzberichte'!$AZ$15,'III. Finanzberichte'!$BG$15,'III. Finanzberichte'!$BN$15,'III. Finanzberichte'!$BU$15,'III. Finanzberichte'!$CB$15,'III. Finanzberichte'!$CI$15,'III. Finanzberichte'!$CP$15,'III. Finanzberichte'!$CW$15,'III. Finanzberichte'!$DD$15,'III. Finanzberichte'!$DK$15,'III. Finanzberichte'!$DR$15),"") | N89: ==IFERROR(CHOOSE(E81,'III. Finanzberichte'!$D$15,'III. Finanzberichte'!$K$15,'III. Finanzberichte'!$R$15,'III. Finanzberichte'!$Y$15,'III. Finanzberichte'!$AF$15,'III. Finanzberichte'!$AM$15,'III. Finanzberichte'!$AT$15,'III. Finanzberichte'!$BA$15,'III. Finanzberichte'!$BH$15,'III. Finanzberichte'!$BO$15,'III. Finanzberichte'!$BV$15,'III. Finanzberichte'!$CC$15,'III. Finanzberichte'!$CJ$15,'III. Finanzberichte'!$CQ$15,'III. Finanzberichte'!$CX$15,'III. Finanzberichte'!$DE$15,'III. Finanzberichte'!$DL$15,'III. Finanzberichte'!$DS$15),"") | O89: ==IFERROR(CHOOSE(E81,'III. Finanzberichte'!$E$15,'III. Finanzberichte'!$L$15,'III. Finanzberichte'!$S$15,'III. Finanzberichte'!$Z$15,'III. Finanzberichte'!$AG$15,'III. Finanzberichte'!$AN$15,'III. Finanzberichte'!$AU$15,'III. Finanzberichte'!$BB$15,'III. Finanzberichte'!$BI$15,'III. Finanzberichte'!$BP$15,'III. Finanzberichte'!$BW$15,'III. Finanzberichte'!$CD$15,'III. Finanzberichte'!$CK$15,'III. Finanzberichte'!$CR$15,'III. Finanzberichte'!$CY$15,'III. Finanzberichte'!$DF$15,'III. Finanzberichte'!$DM$15,'III. Finanzberichte'!$DT$15),"") | P89: ==IFERROR(CHOOSE(E81,'III. Finanzberichte'!$F$15,'III. Finanzberichte'!$M$15,'III. Finanzberichte'!$T$15,'III. Finanzberichte'!$AA$15,'III. Finanzberichte'!$AH$15,'III. Finanzberichte'!$AO$15,'III. Finanzberichte'!$AV$15,'III. Finanzberichte'!$BC$15,'III. Finanzberichte'!$BJ$15,'III. Finanzberichte'!$BQ$15,'III. Finanzberichte'!$BX$15,'III. Finanzberichte'!$CE$15,'III. Finanzberichte'!$CL$15,'III. Finanzberichte'!$CS$15,'III. Finanzberichte'!$CZ$15,'III. Finanzberichte'!$DG$15,'III. Finanzberichte'!$DN$15,'III. Finanzberichte'!$DU$15),"")
L90: Gesamteinnahmen | M90: ==IFERROR(CHOOSE(E81,'III. Finanzberichte'!$C$16,'III. Finanzberichte'!$J$16,'III. Finanzberichte'!$Q$16,'III. Finanzberichte'!$X$16,'III. Finanzberichte'!$AE$16,'III. Finanzberichte'!$AL$16,'III. Finanzberichte'!$AS$16,'III. Finanzberichte'!$AZ$16,'III. Finanzberichte'!$BG$16,'III. Finanzberichte'!$BN$16,'III. Finanzberichte'!$BU$16,'III. Finanzberichte'!$CB$16,'III. Finanzberichte'!$CI$16,'III. Finanzberichte'!$CP$16,'III. Finanzberichte'!$CW$16,'III. Finanzberichte'!$DD$16,'III. Finanzberichte'!$DK$16,'III. Finanzberichte'!$DR$16),"") | N90: ==IFERROR(CHOOSE(E81,'III. Finanzberichte'!$D$16,'III. Finanzberichte'!$K$16,'III. Finanzberichte'!$R$16,'III. Finanzberichte'!$Y$16,'III. Finanzberichte'!$AF$16,'III. Finanzberichte'!$AM$16,'III. Finanzberichte'!$AT$16,'III. Finanzberichte'!$BA$16,'III. Finanzberichte'!$BH$16,'III. Finanzberichte'!$BO$16,'III. Finanzberichte'!$BV$16,'III. Finanzberichte'!$CC$16,'III. Finanzberichte'!$CJ$16,'III. Finanzberichte'!$CQ$16,'III. Finanzberichte'!$CX$16,'III. Finanzberichte'!$DE$16,'III. Finanzberichte'!$DL$16,'III. Finanzberichte'!$DS$16),"") | O90: ==IFERROR(CHOOSE(E81,'III. Finanzberichte'!$E$16,'III. Finanzberichte'!$L$16,'III. Finanzberichte'!$S$16,'III. Finanzberichte'!$Z$16,'III. Finanzberichte'!$AG$16,'III. Finanzberichte'!$AN$16,'III. Finanzberichte'!$AU$16,'III. Finanzberichte'!$BB$16,'III. Finanzberichte'!$BI$16,'III. Finanzberichte'!$BP$16,'III. Finanzberichte'!$BW$16,'III. Finanzberichte'!$CD$16,'III. Finanzberichte'!$CK$16,'III. Finanzberichte'!$CR$16,'III. Finanzberichte'!$CY$16,'III. Finanzberichte'!$DF$16,'III. Finanzberichte'!$DM$16,'III. Finanzberichte'!$DT$16),"") | P90: ==IFERROR(CHOOSE(E81,'III. Finanzberichte'!$F$16,'III. Finanzberichte'!$M$16,'III. Finanzberichte'!$T$16,'III. Finanzberichte'!$AA$16,'III. Finanzberichte'!$AH$16,'III. Finanzberichte'!$AO$16,'III. Finanzberichte'!$AV$16,'III. Finanzberichte'!$BC$16,'III. Finanzberichte'!$BJ$16,'III. Finanzberichte'!$BQ$16,'III. Finanzberichte'!$BX$16,'III. Finanzberichte'!$CE$16,'III. Finanzberichte'!$CL$16,'III. Finanzberichte'!$CS$16,'III. Finanzberichte'!$CZ$16,'III. Finanzberichte'!$DG$16,'III. Finanzberichte'!$DN$16,'III. Finanzberichte'!$DU$16),"")
L91: Ausgaben
L92: ID | M92: Ausgaben (LC) | N92: Ausgaben (EUR) | O92: Kum. Ausgaben (LC) | P92: Kum. Ausgaben (EUR)
