Workbook
Name Saldovortrag_LW: Dashboard!$C$14
Name Saldovortrag_EUR: Dashboard!$E$14
Name Budget_Kurs: 'I. Budget'!$H$4
Name Eigenmittel_LW: 'I. Budget'!$E$7
Name Eigenmittel_EUR: 'I. Budget'!$I$7
Name Drittmittel_LW: 'I. Budget'!$E$10
Name Drittmittel_EUR: 'I. Budget'!$I$10
Name KMW_Mittel_LW: 'I. Budget'!$E$13
Name KMW_Mittel_EUR: 'I. Budget'!$I$13
Name Gesamtprojektmittel_LW: 'I. Budget'!$E$15
Name Gesamtprojektmittel_EUR: 'I. Budget'!$I$15
Name Kosten_Bauausgaben_LW: 'I. Budget'!$O$4
Name Kosten_Bauausgaben_EUR: 'I. Budget'!$P$4
Name Kosten_Investitionen_LW: 'I. Budget'!$O$5
Name Kosten_Investitionen_EUR: 'I. Budget'!$P$5
Name Kosten_Personalkosten_LW: 'I. Budget'!$O$6
Name Kosten_Personalkosten_EUR: 'I. Budget'!$P$6
Name Kosten_Projektaktivitaeten_LW: 'I. Budget'!$O$7
Name Kosten_Projektaktivitaeten_EUR: 'I. Budget'!$P$7
Name Kosten_Projektverwaltung_LW: 'I. Budget'!$O$8
Name Kosten_Projektverwaltung_EUR: 'I. Budget'!$P$8
Name Kosten_Evaluierung_LW: 'I. Budget'!$O$9
Name Kosten_Evaluierung_EUR: 'I. Budget'!$P$9
Name Kosten_Audit_LW: 'I. Budget'!$O$10
Name Kosten_Audit_EUR: 'I. Budget'!$P$10
Name Kosten_Reserve_LW: 'I. Budget'!$O$11
Name Kosten_Reserve_EUR: 'I. Budget'!$P$11
Name Gesamtausgaben_LW: 'I. Budget'!$O$12
Name Gesamtausgaben_EUR: 'I. Budget'!$P$12
Name Budget_ID_Liste: OFFSET('I. Budget'!$S$1,0,0,COUNTA('I. Budget'!S:S),1)
Name Geber_Liste: OFFSET('I. Budget'!$K$19,0,0,MAX(1,COUNTA('I. Budget'!$K$19:$K$19)),1)
Name Reserve_Freigabe: 'I. Budget'!$K$5
Name FB_Kurs_1: 'III. Finanzberichte'!$C$8
Name FB_SaldoLC_1: 'III. Finanzberichte'!$C$104
Name FB_SaldoEUR_1: 'III. Finanzberichte'!$D$104
Name FB_Kurs_2: 'III. Finanzberichte'!$J$8
Name FB_SaldoLC_2: 'III. Finanzberichte'!$J$104
Name FB_SaldoEUR_2: 'III. Finanzberichte'!$K$104
Name FB_Kurs_3: 'III. Finanzberichte'!$Q$8
Name FB_SaldoLC_3: 'III. Finanzberichte'!$Q$104
Name FB_SaldoEUR_3: 'III. Finanzberichte'!$R$104
Name FB_Kurs_4: 'III. Finanzberichte'!$X$8
Name FB_SaldoLC_4: 'III. Finanzberichte'!$X$104
Name FB_SaldoEUR_4: 'III. Finanzberichte'!$Y$104
Name FB_Kurs_5: 'III. Finanzberichte'!$AE$8
Name FB_SaldoLC_5: 'III. Finanzberichte'!$AE$104
Name FB_SaldoEUR_5: 'III. Finanzberichte'!$AF$104
Name FB_Kurs_6: 'III. Finanzberichte'!$AL$8
Name FB_SaldoLC_6: 'III. Finanzberichte'!$AL$104
Name FB_SaldoEUR_6: 'III. Finanzberichte'!$AM$104
Name FB_Kurs_7: 'III. Finanzberichte'!$AS$8
Name FB_SaldoLC_7: 'III. Finanzberichte'!$AS$104
Name FB_SaldoEUR_7: 'III. Finanzberichte'!$AT$104
Name FB_Kurs_8: 'III. Finanzberichte'!$AZ$8
Name FB_SaldoLC_8: 'III. Finanzberichte'!$AZ$104
Name FB_SaldoEUR_8: 'III. Finanzberichte'!$BA$104
Name FB_Kurs_9: 'III. Finanzberichte'!$BG$8
Name FB_SaldoLC_9: 'III. Finanzberichte'!$BG$104
Name FB_SaldoEUR_9: 'III. Finanzberichte'!$BH$104
Name FB_Kurs_10: 'III. Finanzberichte'!$BN$8

Sheet Dashboard
AA1: AED
B2: DASHBOARD (v1.0) | AA2: AFN
AA3: ALL
B4: Statische Projektinformationen | AA4: AMD
B5: Projektnummer | D5: Vorprojekt vorhanden | E5: Ja | AA5: AOA
B6: Projekttitel | AA6: ARS
B7: Projekttraeger | D7: Berichtswaehrung | AA7: AUD
B8: Projektstart | D8: Projektende | AA8: AWG
B9: Projektlaufzeit (geplant) | C9: =IF(AND(ISNUMBER($C$8),ISNUMBER($E$8)),TEXT(DAY($C$8),"00")&"."&TEXT(MONTH($C$8),"00")&"."&TEXT(YEAR($C$8),"0000")&" - "&TEXT(DAY($E$8),"00")&"."&TEXT(MONTH($E$8),"00")&"."&TEXT(YEAR($E$8),"0000"),"") | D9: In Monate | E9: =IF(AND(ISNUMBER($C$8),ISNUMBER($E$8)),DATEDIF($C$8,$E$8+1,"M"),"") | AA9: AZN
B10: Vorprojektnummer | D10: VP-Berichtswaehrung | AA10: BAM
B11: Vorprojektende | D11: Wechselkurs | AA11: BBD
B12: Saldo (LW) | D12: Saldo (EUR) | E12: =IFERROR(ROUND($C$12/$E$11,2),0) -> 0 | AA12: BDT
B13: Folgeprojektstart | D13: Wechselkurs | AA13: BHD
B14: Saldovortrag (LW) | D14: Saldovortrag (EUR) | E14: =IFERROR(ROUND($C$14/$E$13,2),0) -> 0 | AA14: BIF
AA15: BMD
B16: Folgende Dokumente liegen vor: | D16: Nein | E16: Vorprojektsaldo (Nachweis) | AA16: BND
D17: Nein | E17: Vertrag | AA17: BOB
D18: Nein | E18: Budget | AA18: BRL
D19: Nein | E19: Bankbelege | AA19: BSD
D20: Nein | E20: Finanzbericht(e) | AA20: BTN
D21: Nein | E21: Einzelbelege und Beleglisten | AA21: BWP
D22: Nein | E22: Narrativer Bericht | AA22: BYN
AA23: BZD
AA24: CAD
AA25: CDF
AA26: CHF
AA27: CLP
AA28: CNY
AA29: COP
AA30: CRC
AA31: CUP
AA32: CVE
AA33: CZK
AA34: DJF
... AA155: ZWG

Sheet I. Budget
S1: {=IFERROR(_xlfn._xlws.FILTER(TblBudgetAusgaben[ID],TblBudgetAusgaben[ID]<>""),"")} -> 0
B2: I. KERNDATEN BUDGET | K2: Reserve Freigabe
K3: =$P$11 -> 39500
B4: 1. GEPLANTE EINNAHMEN / FINANZIERUNG | G4: € Budget-Kurs: | H4: =IFERROR($E$15/$I$15,0) -> 2 | K4: Reserve freigeben: | O4: =SUMIFS(TblBudgetAusgaben[Betrag (LC)],TblBudgetAusgaben[Kostenkategorie],"Bauausgaben") -> 390000 | P4: =SUMIFS(TblBudgetAusgaben[Betrag (EUR)],TblBudgetAusgaben[Kostenkategorie],"Bauausgaben") -> 195000
B5: Finanzierungsquelle | E5: Betrag (LC) | F5: Jahr 1 | G5: Jahr 2 | H5: Jahr 3 | I5: Betrag (EUR) | K5: Nein | O5: =SUMIFS(TblBudgetAusgaben[Betrag (LC)],TblBudgetAusgaben[Kostenkategorie],"Investitionen") -> 390000 | P5: =SUMIFS(TblBudgetAusgaben[Betrag (EUR)],TblBudgetAusgaben[Kostenkategorie],"Investitionen") -> 195000
B6: 1.1 Eigenmittel | K6: =IF($K$5="Ja","FREIGEGEBEN","NICHT FREIGEGEBEN") -> NICHT FREIGEGEBEN | O6: =SUMIFS(TblBudgetAusgaben[Betrag (LC)],TblBudgetAusgaben[Kostenkategorie],"Personalkosten") -> 0 | P6: =SUMIFS(TblBudgetAusgaben[Betrag (EUR)],TblBudgetAusgaben[Kostenkategorie],"Personalkosten") -> 0
B7: Eigenmittel | E7: 40000 | F7: 40000 | I7: 20000 | O7: =SUMIFS(TblBudgetAusgaben[Betrag (LC)],TblBudgetAusgaben[Kostenkategorie],"Projektaktivitaeten") -> 390000 | P7: =SUMIFS(TblBudgetAusgaben[Betrag (EUR)],TblBudgetAusgaben[Kostenkategorie],"Projektaktivitaeten") -> 195000
K8: Begruendung | O8: =SUMIFS(TblBudgetAusgaben[Betrag (LC)],TblBudgetAusgaben[Kostenkategorie],"Projektverwaltung") -> 390000 | P8: =SUMIFS(TblBudgetAusgaben[Betrag (EUR)],TblBudgetAusgaben[Kostenkategorie],"Projektverwaltung") -> 195000
B9: 1.2 Drittmittel | O9: =SUMIFS(TblBudgetAusgaben[Betrag (LC)],TblBudgetAusgaben[Kostenkategorie],"Evaluierung") -> 10000 | P9: =SUMIFS(TblBudgetAusgaben[Betrag (EUR)],TblBudgetAusgaben[Kostenkategorie],"Evaluierung") -> 5000
B10: Drittmittel (Summe): | D10: Aufstellung je Geber → Tabelle rechts | E10: =SUM(TblDrittmittel[Betrag (LC)]) -> 30000 | F10: 30000 | I10: =SUM(TblDrittmittel[Betrag (EUR)]) -> 15000 | O10: =SUMIFS(TblBudgetAusgaben[Betrag (LC)],TblBudgetAusgaben[Kostenkategorie],"Audit") -> 10000 | P10: =SUMIFS(TblBudgetAusgaben[Betrag (EUR)],TblBudgetAusgaben[Kostenkategorie],"Audit") -> 5000
O11: =SUMIFS(TblBudgetAusgaben[Betrag (LC)],TblBudgetAusgaben[Kostenkategorie],"Reserve") -> 79000 | P11: =SUMIFS(TblBudgetAusgaben[Betrag (EUR)],TblBudgetAusgaben[Kostenkategorie],"Reserve") -> 39500
B12: 1.3 KMW-Mittel | O12: =SUBTOTAL(109,TblBudgetAusgaben[Betrag (LC)]) -> 1659000 | P12: =SUBTOTAL(109,TblBudgetAusgaben[Betrag (EUR)]) -> 829500
B13: KMW-Mittel | E13: 1589000 | F13: 1589000 | G13: 0 | H13: 0 | I13: 794500
B15: GESAMTPROJEKTMITTEL | E15: =E7+E10+E13 -> 1659000 | F15: =F7+F10+F13 -> 1659000 | G15: =G7+G10+G13 -> 0 | H15: =H7+H10+H13 -> 0 | I15: =I7+I10+I13 -> 829500
B17: 2. GEPLANTE AUSGABEN | K17: Drittmittel – Aufstellung je Geber
B18: Kostenkategorie | C18: ID | D18: Kostenposition | E18: Betrag (LC) | F18: Jahr 1 | G18: Jahr 2 | H18: Jahr 3 | I18: Betrag (EUR) | K18: Name des Gebers | L18: Betrag (LC) | M18: Betrag (EUR)
B19: Bauausgaben | C19: 1.1 | D19: Hallo1 | E19: 10000 | F19: 10000 | I19: 5000 | K19: Sonstige | L19: 30000 | M19: 15000
B20: Bauausgaben | C20: 1.2 | D20: Hallo2 | E20: 11000 | F20: 11000 | I20: 5500
B21: Bauausgaben | C21: 1.3 | D21: Hallo3 | E21: 12000 | F21: 12000 | I21: 6000
B22: Bauausgaben | C22: 1.4 | D22: Hallo4 | E22: 13000 | F22: 13000 | I22: 6500
B23: Bauausgaben | C23: 1.5 | D23: Hallo5 | E23: 14000 | F23: 14000 | I23: 7000
B24: Bauausgaben | C24: 1.6 | D24: Hallo6 | E24: 15000 | F24: 15000 | I24: 7500
B25: Bauausgaben | C25: 1.7 | D25: Hallo7 | E25: 16000 | F25: 16000 | I25: 8000
B26: Bauausgaben | C26: 1.8 | D26: Hallo8 | E26: 17000 | F26: 17000 | I26: 8500
B27: Bauausgaben | C27: 1.9 | D27: Hallo9 | E27: 18000 | F27: 18000 | I27: 9000
B28: Bauausgaben | C28: 1.10 | D28: Hallo10 | E28: 19000 | F28: 19000 | I28: 9500
B29: Bauausgaben | C29: 1.11 | D29: Hallo11 | E29: 20000 | F29: 20000 | I29: 10000
B30: Bauausgaben | C30: 1.12 | D30: Hallo12 | E30: 21000 | F30: 21000 | I30: 10500
B31: Bauausgaben | C31: 1.13 | D31: Hallo13 | E31: 22000 | F31: 22000 | I31: 11000
... B100: Audit | C100: 7. | D100: Audit | E100: 10000 | F100: 10000 | I100: 5000
B101: Reserve | C101: 8. | D101: Reserve - nur nach Genehmigung | E101: 79000 | F101: 79000 | G101: 0 | H101: 0 | I101: 39500
B102: Geplante Gesamtausgaben | E102: =SUBTOTAL(109,TblBudgetAusgaben[Betrag (LC)]) -> 1659000 | F102: =SUBTOTAL(109,TblBudgetAusgaben[Jahr 1]) -> 1659000 | G102: =SUBTOTAL(109,TblBudgetAusgaben[Jahr 2]) -> 0 | H102: =SUBTOTAL(109,TblBudgetAusgaben[Jahr 3]) -> 0 | I102: =SUBTOTAL(109,TblBudgetAusgaben[Betrag (EUR)]) -> 829500
B104: Budgetpruefung
B105: Einnahmen = Ausgaben (LC) | E105: =IF(ROUND($E$15-$O$12,2)=0,"OK","Abweichung") -> OK
B106: Einnahmen = Ausgaben (EUR) | E106: =IF(ROUND($I$15-$P$12,2)=0,"OK","Abweichung") -> OK
B107: Gleicher Budget-Kurs | E107: =IF(ROUND($H$4,4)=ROUND(IFERROR($O$12/$P$12,0),4),"OK","Abweichung") -> OK
B108: Einnahmen: Jahre = Gesamt (LC) | E108: =IF(ROUND(($F$15+$G$15+$H$15)-$E$15,2)=0,"OK","Abweichung") -> OK
B109: Ausgaben: Jahre = Gesamt (LC) | E109: =IF(ROUND(($F$102+$G$102+$H$102)-$O$12,2)=0,"OK","Abweichung") -> OK

Sheet II. KMW-Mittel
Z1: Periode 1
B2: II. KMW-MITTEL BEREITGESTELLT | Z2: Periode 2
Z3: Periode 3
B4: Periode | C4: Waehrung | D4: Betrag | E4: Datum | Z4: Periode 4
Z5: Periode 5
Z6: Periode 6
Z7: Periode 7
Z8: Periode 8
Z9: Periode 9
Z10: Periode 10
Z11: Periode 11
Z12: Periode 12
Z13: Periode 13
Z14: Periode 14
Z15: Periode 15
Z16: Periode 16
... Z22: Periode 22
B23: GESAMT | D23: =SUBTOTAL(109,TblKMWMittel[Betrag]) -> 0 | Z23: Periode 23
Z24: Periode 24
Z25: Periode 25
Z26: Periode 26
Z27: Periode 27
Z28: Periode 28
Z29: Periode 29
Z30: Periode 30
Z31: Periode 31
Z32: Periode 32
Z33: Periode 33
Z34: Periode 34
Z35: Periode 35
Z36: Periode 36

Sheet III. Finanzberichte
H3: ➤ | O3: ➤ | V3: ➤ | AC3: ➤ | AJ3: ➤ | AQ3: ➤ | AX3: ➤ | BE3: ➤ | BL3: ➤ | BS3: ➤ | BZ3: ➤ | CG3: ➤ | CN3: ➤ | CU3: ➤ | DB3: ➤ | DI3: ➤ | DP3: ➤
B4: Periode: | C4: Periode 1 | I4: Periode: | J4: Periode 2 | P4: Periode: | Q4: Periode 3 | W4: Periode: | X4: Periode 4 | AD4: Periode: | AE4: Periode 5 | AK4: Periode: | AL4: Periode 6 | AR4: Periode: | AS4: Periode 7 | AY4: Periode: | AZ4: Periode 8 | BF4: Periode: | BG4: Periode 9 | BM4: Periode: | BN4: Periode 10 | BT4: Periode: | BU4: Periode 11 | CA4: Periode: | CB4: Periode 12 | CH4: Periode: | CI4: Periode 13 | CO4: Periode: | CP4: Periode 14 | CV4: Periode: | CW4: Periode 15 | DC4: Periode: | DD4: Periode 16 | DJ4: Periode: | DK4: Periode 17 | DQ4: Periode: | DR4: Periode 18
B5: Von: | I5: Von: | P5: Von: | W5: Von: | AD5: Von: | AK5: Von: | AR5: Von: | AY5: Von: | BF5: Von: | BM5: Von: | BT5: Von: | CA5: Von: | CH5: Von: | CO5: Von: | CV5: Von: | DC5: Von: | DJ5: Von: | DQ5: Von:
B6: Bis: | I6: Bis: | P6: Bis: | W6: Bis: | AD6: Bis: | AK6: Bis: | AR6: Bis: | AY6: Bis: | BF6: Bis: | BM6: Bis: | BT6: Bis: | CA6: Bis: | CH6: Bis: | CO6: Bis: | CV6: Bis: | DC6: Bis: | DJ6: Bis: | DQ6: Bis:
B7: Zeitraum: | C7: =IF(OR(C5="",C6=""),"",DATEDIF(C5,C6,"m")+1) -> 158 | I7: Zeitraum: | J7: =IF(OR(J5="",J6=""),"",DATEDIF(J5,J6,"m")+1) -> 158 | P7: Zeitraum: | Q7: =IF(OR(Q5="",Q6=""),"",DATEDIF(Q5,Q6,"m")+1) -> 158 | W7: Zeitraum: | X7: =IF(OR(X5="",X6=""),"",DATEDIF(X5,X6,"m")+1) -> 158 | AD7: Zeitraum: | AE7: =IF(OR(AE5="",AE6=""),"",DATEDIF(AE5,AE6,"m")+1) -> 158 | AK7: Zeitraum: | AL7: =IF(OR(AL5="",AL6=""),"",DATEDIF(AL5,AL6,"m")+1) -> 158 | AR7: Zeitraum: | AS7: =IF(OR(AS5="",AS6=""),"",DATEDIF(AS5,AS6,"m")+1) -> 158 | AY7: Zeitraum: | AZ7: =IF(OR(AZ5="",AZ6=""),"",DATEDIF(AZ5,AZ6,"m")+1) -> 158 | BF7: Zeitraum: | BG7: =IF(OR(BG5="",BG6=""),"",DATEDIF(BG5,BG6,"m")+1) -> 158 | BM7: Zeitraum: | BN7: =IF(OR(BN5="",BN6=""),"",DATEDIF(BN5,BN6,"m")+1) -> 158 | BT7: Zeitraum: | BU7: =IF(OR(BU5="",BU6=""),"",DATEDIF(BU5,BU6,"m")+1) -> 158 | CA7: Zeitraum: | CB7: =IF(OR(CB5="",CB6=""),"",DATEDIF(CB5,CB6,"m")+1) -> 158 | CH7: Zeitraum: | CI7: =IF(OR(CI5="",CI6=""),"",DATEDIF(CI5,CI6,"m")+1) -> 158 | CO7: Zeitraum: | CP7: =IF(OR(CP5="",CP6=""),"",DATEDIF(CP5,CP6,"m")+1) -> 158 | CV7: Zeitraum: | CW7: =IF(OR(CW5="",CW6=""),"",DATEDIF(CW5,CW6,"m")+1) -> 158 | DC7: Zeitraum: | DD7: =IF(OR(DD5="",DD6=""),"",DATEDIF(DD5,DD6,"m")+1) -> 158 | DJ7: Zeitraum: | DK7: =IF(OR(DK5="",DK6=""),"",DATEDIF(DK5,DK6,"m")+1) -> 158 | DQ7: Zeitraum: | DR7: =IF(OR(DR5="",DR6=""),"",DATEDIF(DR5,DR6,"m")+1) -> 158
B8: Durchschnittskurs: | C8: =ROUND(IFERROR(F121,0),6) -> 0 | I8: Durchschnittskurs: | J8: =ROUND(IFERROR(M121,0),6) -> 0 | P8: Durchschnittskurs: | Q8: =ROUND(IFERROR(T121,0),6) -> 0 | W8: Durchschnittskurs: | X8: =ROUND(IFERROR(AA121,0),6) -> 0 | AD8: Durchschnittskurs: | AE8: =ROUND(IFERROR(AH121,0),6) -> 0 | AK8: Durchschnittskurs: | AL8: =ROUND(IFERROR(AO121,0),6) -> 0 | AR8: Durchschnittskurs: | AS8: =ROUND(IFERROR(AV121,0),6) -> 0 | AY8: Durchschnittskurs: | AZ8: =ROUND(IFERROR(BC121,0),6) -> 0 | BF8: Durchschnittskurs: | BG8: =ROUND(IFERROR(BJ121,0),6) -> 0 | BM8: Durchschnittskurs: | BN8: =ROUND(IFERROR(BQ121,0),6) -> 0 | BT8: Durchschnittskurs: | BU8: =ROUND(IFERROR(BX121,0),6) -> 0 | CA8: Durchschnittskurs: | CB8: =ROUND(IFERROR(CE121,0),6) -> 0 | CH8: Durchschnittskurs: | CI8: =ROUND(IFERROR(CL121,0),6) -> 0 | CO8: Durchschnittskurs: | CP8: =ROUND(IFERROR(CS121,0),6) -> 0 | CV8: Durchschnittskurs: | CW8: =ROUND(IFERROR(CZ121,0),6) -> 0 | DC8: Durchschnittskurs: | DD8: =ROUND(IFERROR(DG121,0),6) -> 0 | DJ8: Durchschnittskurs: | DK8: =ROUND(IFERROR(DN121,0),6) -> 0 | DQ8: Durchschnittskurs: | DR8: =ROUND(IFERROR(DU121,0),6) -> 0
B9: Einnahmen | I9: Einnahmen | P9: Einnahmen | W9: Einnahmen | AD9: Einnahmen | AK9: Einnahmen | AR9: Einnahmen | AY9: Einnahmen | BF9: Einnahmen | BM9: Einnahmen | BT9: Einnahmen | CA9: Einnahmen | CH9: Einnahmen | CO9: Einnahmen | CV9: Einnahmen | DC9: Einnahmen | DJ9: Einnahmen | DQ9: Einnahmen
B10: Typ / ID | C10: Einnahmen (LC) | D10: Einnahmen (EUR) | E10: Kum. Einnahmen (LC) | F10: Kum. Einnahmen (EUR) | I10: Typ / ID | J10: Einnahmen (LC) | K10: Einnahmen (EUR) | L10: Kum. Einnahmen (LC) | M10: Kum. Einnahmen (EUR) | P10: Typ / ID | Q10: Einnahmen (LC) | R10: Einnahmen (EUR) | S10: Kum. Einnahmen (LC) | T10: Kum. Einnahmen (EUR) | W10: Typ / ID | X10: Einnahmen (LC) | Y10: Einnahmen (EUR) | Z10: Kum. Einnahmen (LC) | AA10: Kum. Einnahmen (EUR) | AD10: Typ / ID | AE10: Einnahmen (LC) | AF10: Einnahmen (EUR) | AG10: Kum. Einnahmen (LC) | AH10: Kum. Einnahmen (EUR) | AK10: Typ / ID | AL10: Einnahmen (LC) | AM10: Einnahmen (EUR) | AN10: Kum. Einnahmen (LC) | AO10: Kum. Einnahmen (EUR) | AR10: Typ / ID | AS10: Einnahmen (LC) | AT10: Einnahmen (EUR) | AU10: Kum. Einnahmen (LC) | AV10: Kum. Einnahmen (EUR) | AY10: Typ / ID | AZ10: Einnahmen (LC) | BA10: Einnahmen (EUR) | BB10: Kum. Einnahmen (LC) | BC10: Kum. Einnahmen (EUR) | BF10: Typ / ID | BG10: Einnahmen (LC) | BH10: Einnahmen (EUR) | BI10: Kum. Einnahmen (LC) | BJ10: Kum. Einnahmen (EUR) | BM10: Typ / ID | BN10: Einnahmen (LC) | BO10: Einnahmen (EUR) | BP10: Kum. Einnahmen (LC) | BQ10: Kum. Einnahmen (EUR) | BT10: Typ / ID | BU10: Einnahmen (LC) | BV10: Einnahmen (EUR) | BW10: Kum. Einnahmen (LC) | BX10: Kum. Einnahmen (EUR) | CA10: Typ / ID | CB10: Einnahmen (LC) | CC10: Einnahmen (EUR) | CD10: Kum. Einnahmen (LC) | CE10: Kum. Einnahmen (EUR) | CH10: Typ / ID | CI10: Einnahmen (LC) | CJ10: Einnahmen (EUR) | CK10: Kum. Einnahmen (LC) | CL10: Kum. Einnahmen (EUR) | CO10: Typ / ID | CP10: Einnahmen (LC) | CQ10: Einnahmen (EUR) | CR10: Kum. Einnahmen (LC) | CS10: Kum. Einnahmen (EUR) | CV10: Typ / ID | CW10: Einnahmen (LC) | CX10: Einnahmen (EUR) | CY10: Kum. Einnahmen (LC) | CZ10: Kum. Einnahmen (EUR) | DC10: Typ / ID | DD10: Einnahmen (LC) | DE10: Einnahmen (EUR) | DF10: Kum. Einnahmen (LC) | DG10: Kum. Einnahmen (EUR) | DJ10: Typ / ID | DK10: Einnahmen (LC) | DL10: Einnahmen (EUR) | DM10: Kum. Einnahmen (LC) | DN10: Kum. Einnahmen (EUR) | DQ10: Typ / ID | DR10: Einnahmen (LC) | DS10: Einnahmen (EUR) | DT10: Kum. Einnahmen (LC) | DU10: Kum. Einnahmen (EUR)
B11: Vorprojektsaldo | C11: =ROUND(IF(Saldovortrag_LW="",0,Saldovortrag_LW),2) -> 0 | D11: =ROUND(IF(Saldovortrag_EUR="",0,Saldovortrag_EUR),2) -> 0 | E11: =ROUND(IF(Saldovortrag_LW="",0,Saldovortrag_LW),2) -> 0 | F11: =ROUND(IF(Saldovortrag_EUR="",0,Saldovortrag_EUR),2) -> 0 | I11: Vorperiodensaldo | J11: =ROUND(FB_SaldoLC_1,2) -> 0 | K11: =ROUND(FB_SaldoEUR_1,2) -> 0 | L11: =ROUND(FB_SaldoLC_1,2) -> 0 | M11: =ROUND(FB_SaldoEUR_1,2) -> 0 | P11: Vorperiodensaldo | Q11: =ROUND(FB_SaldoLC_2,2) -> 0 | R11: =ROUND(FB_SaldoEUR_2,2) -> 0 | S11: =ROUND(FB_SaldoLC_2,2) -> 0 | T11: =ROUND(FB_SaldoEUR_2,2) -> 0 | W11: Vorperiodensaldo | X11: =ROUND(FB_SaldoLC_3,2) -> 0 | Y11: =ROUND(FB_SaldoEUR_3,2) -> 0 | Z11: =ROUND(FB_SaldoLC_3,2) -> 0 | AA11: =ROUND(FB_SaldoEUR_3,2) -> 0 | AD11: Vorperiodensaldo | AE11: =ROUND(FB_SaldoLC_4,2) -> 0 | AF11: =ROUND(FB_SaldoEUR_4,2) -> 0 | AG11: =ROUND(FB_SaldoLC_4,2) -> 0 | AH11: =ROUND(FB_SaldoEUR_4,2) -> 0 | AK11: Vorperiodensaldo | AL11: =ROUND(FB_SaldoLC_5,2) -> 0 | AM11: =ROUND(FB_SaldoEUR_5,2) -> 0 | AN11: =ROUND(FB_SaldoLC_5,2) -> 0 | AO11: =ROUND(FB_SaldoEUR_5,2) -> 0 | AR11: Vorperiodensaldo | AS11: =ROUND(FB_SaldoLC_6,2) -> 0 | AT11: =ROUND(FB_SaldoEUR_6,2) -> 0 | AU11: =ROUND(FB_SaldoLC_6,2) -> 0 | AV11: =ROUND(FB_SaldoEUR_6,2) -> 0 | AY11: Vorperiodensaldo | AZ11: =ROUND(FB_SaldoLC_7,2) -> 0 | BA11: =ROUND(FB_SaldoEUR_7,2) -> 0 | BB11: =ROUND(FB_SaldoLC_7,2) -> 0 | BC11: =ROUND(FB_SaldoEUR_7,2) -> 0 | BF11: Vorperiodensaldo | BG11: =ROUND(FB_SaldoLC_8,2) -> 0 | BH11: =ROUND(FB_SaldoEUR_8,2) -> 0 | BI11: =ROUND(FB_SaldoLC_8,2) -> 0 | BJ11: =ROUND(FB_SaldoEUR_8,2) -> 0 | BM11: Vorperiodensaldo | BN11: =ROUND(FB_SaldoLC_9,2) -> 0 | BO11: =ROUND(FB_SaldoEUR_9,2) -> 0 | BP11: =ROUND(FB_SaldoLC_9,2) -> 0 | BQ11: =ROUND(FB_SaldoEUR_9,2) -> 0 | BT11: Vorperiodensaldo | BU11: =ROUND(FB_SaldoLC_10,2) -> 0 | BV11: =ROUND(FB_SaldoEUR_10,2) -> 0 | BW11: =ROUND(FB_SaldoLC_10,2) -> 0 | BX11: =ROUND(FB_SaldoEUR_10,2) -> 0 | CA11: Vorperiodensaldo | CB11: =ROUND(FB_SaldoLC_11,2) -> 0 | CC11: =ROUND(FB_SaldoEUR_11,2) -> 0 | CD11: =ROUND(FB_SaldoLC_11,2) -> 0 | CE11: =ROUND(FB_SaldoEUR_11,2) -> 0 | CH11: Vorperiodensaldo | CI11: =ROUND(FB_SaldoLC_12,2) -> 0 | CJ11: =ROUND(FB_SaldoEUR_12,2) -> 0 | CK11: =ROUND(FB_SaldoLC_12,2) -> 0 | CL11: =ROUND(FB_SaldoEUR_12,2) -> 0 | CO11: Vorperiodensaldo | CP11: =ROUND(FB_SaldoLC_13,2) -> 0 | CQ11: =ROUND(FB_SaldoEUR_13,2) -> 0 | CR11: =ROUND(FB_SaldoLC_13,2) -> 0 | CS11: =ROUND(FB_SaldoEUR_13,2) -> 0 | CV11: Vorperiodensaldo | CW11: =ROUND(FB_SaldoLC_14,2) -> 0 | CX11: =ROUND(FB_SaldoEUR_14,2) -> 0 | CY11: =ROUND(FB_SaldoLC_14,2) -> 0 | CZ11: =ROUND(FB_SaldoEUR_14,2) -> 0 | DC11: Vorperiodensaldo | DD11: =ROUND(FB_SaldoLC_15,2) -> 0 | DE11: =ROUND(FB_SaldoEUR_15,2) -> 0 | DF11: =ROUND(FB_SaldoLC_15,2) -> 0 | DG11: =ROUND(FB_SaldoEUR_15,2) -> 0 | DJ11: Vorperiodensaldo | DK11: =ROUND(FB_SaldoLC_16,2) -> 0 | DL11: =ROUND(FB_SaldoEUR_16,2) -> 0 | DM11: =ROUND(FB_SaldoLC_16,2) -> 0 | DN11: =ROUND(FB_SaldoEUR_16,2) -> 0 | DQ11: Vorperiodensaldo | DR11: =ROUND(FB_SaldoLC_17,2) -> 0 | DS11: =ROUND(FB_SaldoEUR_17,2) -> 0 | DT11: =ROUND(FB_SaldoLC_17,2) -> 0 | DU11: =ROUND(FB_SaldoEUR_17,2) -> 0
B12: Eigenmittel | C12: =ROUND(SUMIF($B$116:$B$120,"Eigenmittel",$D$116:$D$120)+SUMIF($B$125:$B$130,"Eigenmittel",$D$125:$D$130),2) -> 0 | D12: =ROUND(SUMIF($B$116:$B$120,"Eigenmittel",$E$116:$E$120)+SUMIF($B$125:$B$130,"Eigenmittel",$E$125:$E$130),2) -> 0 | E12: =ROUND(SUMIF($B$116:$B$120,"Eigenmittel",$D$116:$D$120)+SUMIF($B$125:$B$130,"Eigenmittel",$D$125:$D$130),2) -> 0 | F12: =ROUND(SUMIF($B$116:$B$120,"Eigenmittel",$E$116:$E$120)+SUMIF($B$125:$B$130,"Eigenmittel",$E$125:$E$130),2) -> 0 | I12: Eigenmittel | J12: =ROUND(SUMIF($I$116:$I$120,"Eigenmittel",$K$116:$K$120)+SUMIF($I$125:$I$130,"Eigenmittel",$K$125:$K$130),2) -> 0 | K12: =ROUND(SUMIF($I$116:$I$120,"Eigenmittel",$L$116:$L$120)+SUMIF($I$125:$I$130,"Eigenmittel",$L$125:$L$130),2) -> 0 | L12: =IFERROR(ROUND(E12 + J12, 2), J12) -> 0 | M12: =IFERROR(ROUND(F12 + K12, 2), K12) -> 0 | P12: Eigenmittel | Q12: =ROUND(SUMIF($P$116:$P$120,"Eigenmittel",$R$116:$R$120)+SUMIF($P$125:$P$130,"Eigenmittel",$R$125:$R$130),2) -> 0 | R12: =ROUND(SUMIF($P$116:$P$120,"Eigenmittel",$S$116:$S$120)+SUMIF($P$125:$P$130,"Eigenmittel",$S$125:$S$130),2) -> 0 | S12: =IFERROR(ROUND(L12 + Q12, 2), Q12) -> 0 | T12: =IFERROR(ROUND(M12 + R12, 2), R12) -> 0 | W12: Eigenmittel | X12: =ROUND(SUMIF($W$116:$W$120,"Eigenmittel",$Y$116:$Y$120)+SUMIF($W$125:$W$130,"Eigenmittel",$Y$125:$Y$130),2) -> 0 | Y12: =ROUND(SUMIF($W$116:$W$120,"Eigenmittel",$Z$116:$Z$120)+SUMIF($W$125:$W$130,"Eigenmittel",$Z$125:$Z$130),2) -> 0 | Z12: =IFERROR(ROUND(S12 + X12, 2), X12) -> 0 | AA12: =IFERROR(ROUND(T12 + Y12, 2), Y12) -> 0 | AD12: Eigenmittel | AE12: =ROUND(SUMIF($AD$116:$AD$120,"Eigenmittel",$AF$116:$AF$120)+SUMIF($AD$125:$AD$130,"Eigenmittel",$AF$125:$AF$130),2) -> 0 | AF12: =ROUND(SUMIF($AD$116:$AD$120,"Eigenmittel",$AG$116:$AG$120)+SUMIF($AD$125:$AD$130,"Eigenmittel",$AG$125:$AG$130),2) -> 0 | AG12: =IFERROR(ROUND(Z12 + AE12, 2), AE12) -> 0 | AH12: =IFERROR(ROUND(AA12 + AF12, 2), AF12) -> 0 | AK12: Eigenmittel | AL12: =ROUND(SUMIF($AK$116:$AK$120,"Eigenmittel",$AM$116:$AM$120)+SUMIF($AK$125:$AK$130,"Eigenmittel",$AM$125:$AM$130),2) -> 0 | AM12: =ROUND(SUMIF($AK$116:$AK$120,"Eigenmittel",$AN$116:$AN$120)+SUMIF($AK$125:$AK$130,"Eigenmittel",$AN$125:$AN$130),2) -> 0 | AN12: =IFERROR(ROUND(AG12 + AL12, 2), AL12) -> 0 | AO12: =IFERROR(ROUND(AH12 + AM12, 2), AM12) -> 0 | AR12: Eigenmittel | AS12: =ROUND(SUMIF($AR$116:$AR$120,"Eigenmittel",$AT$116:$AT$120)+SUMIF($AR$125:$AR$130,"Eigenmittel",$AT$125:$AT$130),2) -> 0 | AT12: =ROUND(SUMIF($AR$116:$AR$120,"Eigenmittel",$AU$116:$AU$120)+SUMIF($AR$125:$AR$130,"Eigenmittel",$AU$125:$AU$130),2) -> 0 | AU12: =IFERROR(ROUND(AN12 + AS12, 2), AS12) -> 0 | AV12: =IFERROR(ROUND(AO12 + AT12, 2), AT12) -> 0 | AY12: Eigenmittel | AZ12: =ROUND(SUMIF($AY$116:$AY$120,"Eigenmittel",$BA$116:$BA$120)+SUMIF($AY$125:$AY$130,"Eigenmittel",$BA$125:$BA$130),2) -> 0 | BA12: =ROUND(SUMIF($AY$116:$AY$120,"Eigenmittel",$BB$116:$BB$120)+SUMIF($AY$125:$AY$130,"Eigenmittel",$BB$125:$BB$130),2) -> 0 | BB12: =IFERROR(ROUND(AU12 + AZ12, 2), AZ12) -> 0 | BC12: =IFERROR(ROUND(AV12 + BA12, 2), BA12) -> 0 | BF12: Eigenmittel | BG12: =ROUND(SUMIF($BF$116:$BF$120,"Eigenmittel",$BH$116:$BH$120)+SUMIF($BF$125:$BF$130,"Eigenmittel",$BH$125:$BH$130),2) -> 0 | BH12: =ROUND(SUMIF($BF$116:$BF$120,"Eigenmittel",$BI$116:$BI$120)+SUMIF($BF$125:$BF$130,"Eigenmittel",$BI$125:$BI$130),2) -> 0 | BI12: =IFERROR(ROUND(BB12 + BG12, 2), BG12) -> 0 | BJ12: =IFERROR(ROUND(BC12 + BH12, 2), BH12) -> 0 | BM12: Eigenmittel | BN12: =ROUND(SUMIF($BM$116:$BM$120,"Eigenmittel",$BO$116:$BO$120)+SUMIF($BM$125:$BM$130,"Eigenmittel",$BO$125:$BO$130),2) -> 0 | BO12: =ROUND(SUMIF($BM$116:$BM$120,"Eigenmittel",$BP$116:$BP$120)+SUMIF($BM$125:$BM$130,"Eigenmittel",$BP$125:$BP$130),2) -> 0 | BP12: =IFERROR(ROUND(BI12 + BN12, 2), BN12) -> 0 | BQ12: =IFERROR(ROUND(BJ12 + BO12, 2), BO12) -> 0 | BT12: Eigenmittel | BU12: =ROUND(SUMIF($BT$116:$BT$120,"Eigenmittel",$BV$116:$BV$120)+SUMIF($BT$125:$BT$130,"Eigenmittel",$BV$125:$BV$130),2) -> 0 | BV12: =ROUND(SUMIF($BT$116:$BT$120,"Eigenmittel",$BW$116:$BW$120)+SUMIF($BT$125:$BT$130,"Eigenmittel",$BW$125:$BW$130),2) -> 0 | BW12: =IFERROR(ROUND(BP12 + BU12, 2), BU12) -> 0 | BX12: =IFERROR(ROUND(BQ12 + BV12, 2), BV12) -> 0 | CA12: Eigenmittel | CB12: =ROUND(SUMIF($CA$116:$CA$120,"Eigenmittel",$CC$116:$CC$120)+SUMIF($CA$125:$CA$130,"Eigenmittel",$CC$125:$CC$130),2) -> 0 | CC12: =ROUND(SUMIF($CA$116:$CA$120,"Eigenmittel",$CD$116:$CD$120)+SUMIF($CA$125:$CA$130,"Eigenmittel",$CD$125:$CD$130),2) -> 0 | CD12: =IFERROR(ROUND(BW12 + CB12, 2), CB12) -> 0 | CE12: =IFERROR(ROUND(BX12 + CC12, 2), CC12) -> 0 | CH12: Eigenmittel | CI12: =ROUND(SUMIF($CH$116:$CH$120,"Eigenmittel",$CJ$116:$CJ$120)+SUMIF($CH$125:$CH$130,"Eigenmittel",$CJ$125:$CJ$130),2) -> 0 | CJ12: =ROUND(SUMIF($CH$116:$CH$120,"Eigenmittel",$CK$116:$CK$120)+SUMIF($CH$125:$CH$130,"Eigenmittel",$CK$125:$CK$130),2) -> 0 | CK12: =IFERROR(ROUND(CD12 + CI12, 2), CI12) -> 0 | CL12: =IFERROR(ROUND(CE12 + CJ12, 2), CJ12) -> 0 | CO12: Eigenmittel | CP12: =ROUND(SUMIF($CO$116:$CO$120,"Eigenmittel",$CQ$116:$CQ$120)+SUMIF($CO$125:$CO$130,"Eigenmittel",$CQ$125:$CQ$130),2) -> 0 | CQ12: =ROUND(SUMIF($CO$116:$CO$120,"Eigenmittel",$CR$116:$CR$120)+SUMIF($CO$125:$CO$130,"Eigenmittel",$CR$125:$CR$130),2) -> 0 | CR12: =IFERROR(ROUND(CK12 + CP12, 2), CP12) -> 0 | CS12: =IFERROR(ROUND(CL12 + CQ12, 2), CQ12) -> 0 | CV12: Eigenmittel | CW12: =ROUND(SUMIF($CV$116:$CV$120,"Eigenmittel",$CX$116:$CX$120)+SUMIF($CV$125:$CV$130,"Eigenmittel",$CX$125:$CX$130),2) -> 0 | CX12: =ROUND(SUMIF($CV$116:$CV$120,"Eigenmittel",$CY$116:$CY$120)+SUMIF($CV$125:$CV$130,"Eigenmittel",$CY$125:$CY$130),2) -> 0 | CY12: =IFERROR(ROUND(CR12 + CW12, 2), CW12) -> 0 | CZ12: =IFERROR(ROUND(CS12 + CX12, 2), CX12) -> 0 | DC12: Eigenmittel | DD12: =ROUND(SUMIF($DC$116:$DC$120,"Eigenmittel",$DE$116:$DE$120)+SUMIF($DC$125:$DC$130,"Eigenmittel",$DE$125:$DE$130),2) -> 0 | DE12: =ROUND(SUMIF($DC$116:$DC$120,"Eigenmittel",$DF$116:$DF$120)+SUMIF($DC$125:$DC$130,"Eigenmittel",$DF$125:$DF$130),2) -> 0 | DF12: =IFERROR(ROUND(CY12 + DD12, 2), DD12) -> 0 | DG12: =IFERROR(ROUND(CZ12 + DE12, 2), DE12) -> 0 | DJ12: Eigenmittel | DK12: =ROUND(SUMIF($DJ$116:$DJ$120,"Eigenmittel",$DL$116:$DL$120)+SUMIF($DJ$125:$DJ$130,"Eigenmittel",$DL$125:$DL$130),2) -> 0 | DL12: =ROUND(SUMIF($DJ$116:$DJ$120,"Eigenmittel",$DM$116:$DM$120)+SUMIF($DJ$125:$DJ$130,"Eigenmittel",$DM$125:$DM$130),2) -> 0 | DM12: =IFERROR(ROUND(DF12 + DK12, 2), DK12) -> 0 | DN12: =IFERROR(ROUND(DG12 + DL12, 2), DL12) -> 0 | DQ12: Eigenmittel | DR12: =ROUND(SUMIF($DQ$116:$DQ$120,"Eigenmittel",$DS$116:$DS$120)+SUMIF($DQ$125:$DQ$130,"Eigenmittel",$DS$125:$DS$130),2) -> 0 | DS12: =ROUND(SUMIF($DQ$116:$DQ$120,"Eigenmittel",$DT$116:$DT$120)+SUMIF($DQ$125:$DQ$130,"Eigenmittel",$DT$125:$DT$130),2) -> 0 | DT12: =IFERROR(ROUND(DM12 + DR12, 2), DR12) -> 0 | DU12: =IFERROR(ROUND(DN12 + DS12, 2), DS12) -> 0
B13: Drittmittel | C13: =ROUND(SUMIF($B$116:$B$120,"Drittmittel",$D$116:$D$120)+SUMIF($B$125:$B$130,"Drittmittel",$D$125:$D$130),2) -> 0 | D13: =ROUND(SUMIF($B$116:$B$120,"Drittmittel",$E$116:$E$120)+SUMIF($B$125:$B$130,"Drittmittel",$E$125:$E$130),2) -> 0 | E13: =ROUND(SUMIF($B$116:$B$120,"Drittmittel",$D$116:$D$120)+SUMIF($B$125:$B$130,"Drittmittel",$D$125:$D$130),2) -> 0 | F13: =ROUND(SUMIF($B$116:$B$120,"Drittmittel",$E$116:$E$120)+SUMIF($B$125:$B$130,"Drittmittel",$E$125:$E$130),2) -> 0 | I13: Drittmittel | J13: =ROUND(SUMIF($I$116:$I$120,"Drittmittel",$K$116:$K$120)+SUMIF($I$125:$I$130,"Drittmittel",$K$125:$K$130),2) -> 0 | K13: =ROUND(SUMIF($I$116:$I$120,"Drittmittel",$L$116:$L$120)+SUMIF($I$125:$I$130,"Drittmittel",$L$125:$L$130),2) -> 0 | L13: =IFERROR(ROUND(E13 + J13, 2), J13) -> 0 | M13: =IFERROR(ROUND(F13 + K13, 2), K13) -> 0 | P13: Drittmittel | Q13: =ROUND(SUMIF($P$116:$P$120,"Drittmittel",$R$116:$R$120)+SUMIF($P$125:$P$130,"Drittmittel",$R$125:$R$130),2) -> 0 | R13: =ROUND(SUMIF($P$116:$P$120,"Drittmittel",$S$116:$S$120)+SUMIF($P$125:$P$130,"Drittmittel",$S$125:$S$130),2) -> 0 | S13: =IFERROR(ROUND(L13 + Q13, 2), Q13) -> 0 | T13: =IFERROR(ROUND(M13 + R13, 2), R13) -> 0 | W13: Drittmittel | X13: =ROUND(SUMIF($W$116:$W$120,"Drittmittel",$Y$116:$Y$120)+SUMIF($W$125:$W$130,"Drittmittel",$Y$125:$Y$130),2) -> 0 | Y13: =ROUND(SUMIF($W$116:$W$120,"Drittmittel",$Z$116:$Z$120)+SUMIF($W$125:$W$130,"Drittmittel",$Z$125:$Z$130),2) -> 0 | Z13: =IFERROR(ROUND(S13 + X13, 2), X13) -> 0 | AA13: =IFERROR(ROUND(T13 + Y13, 2), Y13) -> 0 | AD13: Drittmittel | AE13: =ROUND(SUMIF($AD$116:$AD$120,"Drittmittel",$AF$116:$AF$120)+SUMIF($AD$125:$AD$130,"Drittmittel",$AF$125:$AF$130),2) -> 0 | AF13: =ROUND(SUMIF($AD$116:$AD$120,"Drittmittel",$AG$116:$AG$120)+SUMIF($AD$125:$AD$130,"Drittmittel",$AG$125:$AG$130),2) -> 0 | AG13: =IFERROR(ROUND(Z13 + AE13, 2), AE13) -> 0 | AH13: =IFERROR(ROUND(AA13 + AF13, 2), AF13) -> 0 | AK13: Drittmittel | AL13: =ROUND(SUMIF($AK$116:$AK$120,"Drittmittel",$AM$116:$AM$120)+SUMIF($AK$125:$AK$130,"Drittmittel",$AM$125:$AM$130),2) -> 0 | AM13: =ROUND(SUMIF($AK$116:$AK$120,"Drittmittel",$AN$116:$AN$120)+SUMIF($AK$125:$AK$130,"Drittmittel",$AN$125:$AN$130),2) -> 0 | AN13: =IFERROR(ROUND(AG13 + AL13, 2), AL13) -> 0 | AO13: =IFERROR(ROUND(AH13 + AM13, 2), AM13) -> 0 | AR13: Drittmittel | AS13: =ROUND(SUMIF($AR$116:$AR$120,"Drittmittel",$AT$116:$AT$120)+SUMIF($AR$125:$AR$130,"Drittmittel",$AT$125:$AT$130),2) -> 0 | AT13: =ROUND(SUMIF($AR$116:$AR$120,"Drittmittel",$AU$116:$AU$120)+SUMIF($AR$125:$AR$130,"Drittmittel",$AU$125:$AU$130),2) -> 0 | AU13: =IFERROR(ROUND(AN13 + AS13, 2), AS13) -> 0 | AV13: =IFERROR(ROUND(AO13 + AT13, 2), AT13) -> 0 | AY13: Drittmittel | AZ13: =ROUND(SUMIF($AY$116:$AY$120,"Drittmittel",$BA$116:$BA$120)+SUMIF($AY$125:$AY$130,"Drittmittel",$BA$125:$BA$130),2) -> 0 | BA13: =ROUND(SUMIF($AY$116:$AY$120,"Drittmittel",$BB$116:$BB$120)+SUMIF($AY$125:$AY$130,"Drittmittel",$BB$125:$BB$130),2) -> 0 | BB13: =IFERROR(ROUND(AU13 + AZ13, 2), AZ13) -> 0 | BC13: =IFERROR(ROUND(AV13 + BA13, 2), BA13) -> 0 | BF13: Drittmittel | BG13: =ROUND(SUMIF($BF$116:$BF$120,"Drittmittel",$BH$116:$BH$120)+SUMIF($BF$125:$BF$130,"Drittmittel",$BH$125:$BH$130),2) -> 0 | BH13: =ROUND(SUMIF($BF$116:$BF$120,"Drittmittel",$BI$116:$BI$120)+SUMIF($BF$125:$BF$130,"Drittmittel",$BI$125:$BI$130),2) -> 0 | BI13: =IFERROR(ROUND(BB13 + BG13, 2), BG13) -> 0 | BJ13: =IFERROR(ROUND(BC13 + BH13, 2), BH13) -> 0 | BM13: Drittmittel | BN13: =ROUND(SUMIF($BM$116:$BM$120,"Drittmittel",$BO$116:$BO$120)+SUMIF($BM$125:$BM$130,"Drittmittel",$BO$125:$BO$130),2) -> 0 | BO13: =ROUND(SUMIF($BM$116:$BM$120,"Drittmittel",$BP$116:$BP$120)+SUMIF($BM$125:$BM$130,"Drittmittel",$BP$125:$BP$130),2) -> 0 | BP13: =IFERROR(ROUND(BI13 + BN13, 2), BN13) -> 0 | BQ13: =IFERROR(ROUND(BJ13 + BO13, 2), BO13) -> 0 | BT13: Drittmittel | BU13: =ROUND(SUMIF($BT$116:$BT$120,"Drittmittel",$BV$116:$BV$120)+SUMIF($BT$125:$BT$130,"Drittmittel",$BV$125:$BV$130),2) -> 0 | BV13: =ROUND(SUMIF($BT$116:$BT$120,"Drittmittel",$BW$116:$BW$120)+SUMIF($BT$125:$BT$130,"Drittmittel",$BW$125:$BW$130),2) -> 0 | BW13: =IFERROR(ROUND(BP13 + BU13, 2), BU13) -> 0 | BX13: =IFERROR(ROUND(BQ13 + BV13, 2), BV13) -> 0 | CA13: Drittmittel | CB13: =ROUND(SUMIF($CA$116:$CA$120,"Drittmittel",$CC$116:$CC$120)+SUMIF($CA$125:$CA$130,"Drittmittel",$CC$125:$CC$130),2) -> 0 | CC13: =ROUND(SUMIF($CA$116:$CA$120,"Drittmittel",$CD$116:$CD$120)+SUMIF($CA$125:$CA$130,"Drittmittel",$CD$125:$CD$130),2) -> 0 | CD13: =IFERROR(ROUND(BW13 + CB13, 2), CB13) -> 0 | CE13: =IFERROR(ROUND(BX13 + CC13, 2), CC13) -> 0 | CH13: Drittmittel | CI13: =ROUND(SUMIF($CH$116:$CH$120,"Drittmittel",$CJ$116:$CJ$120)+SUMIF($CH$125:$CH$130,"Drittmittel",$CJ$125:$CJ$130),2) -> 0 | CJ13: =ROUND(SUMIF($CH$116:$CH$120,"Drittmittel",$CK$116:$CK$120)+SUMIF($CH$125:$CH$130,"Drittmittel",$CK$125:$CK$130),2) -> 0 | CK13: =IFERROR(ROUND(CD13 + CI13, 2), CI13) -> 0 | CL13: =IFERROR(ROUND(CE13 + CJ13, 2), CJ13) -> 0 | CO13: Drittmittel | CP13: =ROUND(SUMIF($CO$116:$CO$120,"Drittmittel",$CQ$116:$CQ$120)+SUMIF($CO$125:$CO$130,"Drittmittel",$CQ$125:$CQ$130),2) -> 0 | CQ13: =ROUND(SUMIF($CO$116:$CO$120,"Drittmittel",$CR$116:$CR$120)+SUMIF($CO$125:$CO$130,"Drittmittel",$CR$125:$CR$130),2) -> 0 | CR13: =IFERROR(ROUND(CK13 + CP13, 2), CP13) -> 0 | CS13: =IFERROR(ROUND(CL13 + CQ13, 2), CQ13) -> 0 | CV13: Drittmittel | CW13: =ROUND(SUMIF($CV$116:$CV$120,"Drittmittel",$CX$116:$CX$120)+SUMIF($CV$125:$CV$130,"Drittmittel",$CX$125:$CX$130),2) -> 0 | CX13: =ROUND(SUMIF($CV$116:$CV$120,"Drittmittel",$CY$116:$CY$120)+SUMIF($CV$125:$CV$130,"Drittmittel",$CY$125:$CY$130),2) -> 0 | CY13: =IFERROR(ROUND(CR13 + CW13, 2), CW13) -> 0 | CZ13: =IFERROR(ROUND(CS13 + CX13, 2), CX13) -> 0 | DC13: Drittmittel | DD13: =ROUND(SUMIF($DC$116:$DC$120,"Drittmittel",$DE$116:$DE$120)+SUMIF($DC$125:$DC$130,"Drittmittel",$DE$125:$DE$130),2) -> 0 | DE13: =ROUND(SUMIF($DC$116:$DC$120,"Drittmittel",$DF$116:$DF$120)+SUMIF($DC$125:$DC$130,"Drittmittel",$DF$125:$DF$130),2) -> 0 | DF13: =IFERROR(ROUND(CY13 + DD13, 2), DD13) -> 0 | DG13: =IFERROR(ROUND(CZ13 + DE13, 2), DE13) -> 0 | DJ13: Drittmittel | DK13: =ROUND(SUMIF($DJ$116:$DJ$120,"Drittmittel",$DL$116:$DL$120)+SUMIF($DJ$125:$DJ$130,"Drittmittel",$DL$125:$DL$130),2) -> 0 | DL13: =ROUND(SUMIF($DJ$116:$DJ$120,"Drittmittel",$DM$116:$DM$120)+SUMIF($DJ$125:$DJ$130,"Drittmittel",$DM$125:$DM$130),2) -> 0 | DM13: =IFERROR(ROUND(DF13 + DK13, 2), DK13) -> 0 | DN13: =IFERROR(ROUND(DG13 + DL13, 2), DL13) -> 0 | DQ13: Drittmittel | DR13: =ROUND(SUMIF($DQ$116:$DQ$120,"Drittmittel",$DS$116:$DS$120)+SUMIF($DQ$125:$DQ$130,"Drittmittel",$DS$125:$DS$130),2) -> 0 | DS13: =ROUND(SUMIF($DQ$116:$DQ$120,"Drittmittel",$DT$116:$DT$120)+SUMIF($DQ$125:$DQ$130,"Drittmittel",$DT$125:$DT$130),2) -> 0 | DT13: =IFERROR(ROUND(DM13 + DR13, 2), DR13) -> 0 | DU13: =IFERROR(ROUND(DN13 + DS13, 2), DS13) -> 0
B14: KMW-Mittel | C14: =ROUND(SUMIF($B$116:$B$120,"KMW-Mittel",$D$116:$D$120)+SUMIF($B$125:$B$130,"KMW-Mittel",$D$125:$D$130),2) -> 0 | D14: =ROUND(SUMIF($B$116:$B$120,"KMW-Mittel",$E$116:$E$120)+SUMIF($B$125:$B$130,"KMW-Mittel",$E$125:$E$130),2) -> 0 | E14: =ROUND(SUMIF($B$116:$B$120,"KMW-Mittel",$D$116:$D$120)+SUMIF($B$125:$B$130,"KMW-Mittel",$D$125:$D$130),2) -> 0 | F14: =ROUND(SUMIF($B$116:$B$120,"KMW-Mittel",$E$116:$E$120)+SUMIF($B$125:$B$130,"KMW-Mittel",$E$125:$E$130),2) -> 0 | I14: KMW-Mittel | J14: =ROUND(SUMIF($I$116:$I$120,"KMW-Mittel",$K$116:$K$120)+SUMIF($I$125:$I$130,"KMW-Mittel",$K$125:$K$130),2) -> 0 | K14: =ROUND(SUMIF($I$116:$I$120,"KMW-Mittel",$L$116:$L$120)+SUMIF($I$125:$I$130,"KMW-Mittel",$L$125:$L$130),2) -> 0 | L14: =IFERROR(ROUND(E14 + J14, 2), J14) -> 0 | M14: =IFERROR(ROUND(F14 + K14, 2), K14) -> 0 | P14: KMW-Mittel | Q14: =ROUND(SUMIF($P$116:$P$120,"KMW-Mittel",$R$116:$R$120)+SUMIF($P$125:$P$130,"KMW-Mittel",$R$125:$R$130),2) -> 0 | R14: =ROUND(SUMIF($P$116:$P$120,"KMW-Mittel",$S$116:$S$120)+SUMIF($P$125:$P$130,"KMW-Mittel",$S$125:$S$130),2) -> 0 | S14: =IFERROR(ROUND(L14 + Q14, 2), Q14) -> 0 | T14: =IFERROR(ROUND(M14 + R14, 2), R14) -> 0 | W14: KMW-Mittel | X14: =ROUND(SUMIF($W$116:$W$120,"KMW-Mittel",$Y$116:$Y$120)+SUMIF($W$125:$W$130,"KMW-Mittel",$Y$125:$Y$130),2) -> 0 | Y14: =ROUND(SUMIF($W$116:$W$120,"KMW-Mittel",$Z$116:$Z$120)+SUMIF($W$125:$W$130,"KMW-Mittel",$Z$125:$Z$130),2) -> 0 | Z14: =IFERROR(ROUND(S14 + X14, 2), X14) -> 0 | AA14: =IFERROR(ROUND(T14 + Y14, 2), Y14) -> 0 | AD14: KMW-Mittel | AE14: =ROUND(SUMIF($AD$116:$AD$120,"KMW-Mittel",$AF$116:$AF$120)+SUMIF($AD$125:$AD$130,"KMW-Mittel",$AF$125:$AF$130),2) -> 0 | AF14: =ROUND(SUMIF($AD$116:$AD$120,"KMW-Mittel",$AG$116:$AG$120)+SUMIF($AD$125:$AD$130,"KMW-Mittel",$AG$125:$AG$130),2) -> 0 | AG14: =IFERROR(ROUND(Z14 + AE14, 2), AE14) -> 0 | AH14: =IFERROR(ROUND(AA14 + AF14, 2), AF14) -> 0 | AK14: KMW-Mittel | AL14: =ROUND(SUMIF($AK$116:$AK$120,"KMW-Mittel",$AM$116:$AM$120)+SUMIF($AK$125:$AK$130,"KMW-Mittel",$AM$125:$AM$130),2) -> 0 | AM14: =ROUND(SUMIF($AK$116:$AK$120,"KMW-Mittel",$AN$116:$AN$120)+SUMIF($AK$125:$AK$130,"KMW-Mittel",$AN$125:$AN$130),2) -> 0 | AN14: =IFERROR(ROUND(AG14 + AL14, 2), AL14) -> 0 | AO14: =IFERROR(ROUND(AH14 + AM14, 2), AM14) -> 0 | AR14: KMW-Mittel | AS14: =ROUND(SUMIF($AR$116:$AR$120,"KMW-Mittel",$AT$116:$AT$120)+SUMIF($AR$125:$AR$130,"KMW-Mittel",$AT$125:$AT$130),2) -> 0 | AT14: =ROUND(SUMIF($AR$116:$AR$120,"KMW-Mittel",$AU$116:$AU$120)+SUMIF($AR$125:$AR$130,"KMW-Mittel",$AU$125:$AU$130),2) -> 0 | AU14: =IFERROR(ROUND(AN14 + AS14, 2), AS14) -> 0 | AV14: =IFERROR(ROUND(AO14 + AT14, 2), AT14) -> 0 | AY14: KMW-Mittel | AZ14: =ROUND(SUMIF($AY$116:$AY$120,"KMW-Mittel",$BA$116:$BA$120)+SUMIF($AY$125:$AY$130,"KMW-Mittel",$BA$125:$BA$130),2) -> 0 | BA14: =ROUND(SUMIF($AY$116:$AY$120,"KMW-Mittel",$BB$116:$BB$120)+SUMIF($AY$125:$AY$130,"KMW-Mittel",$BB$125:$BB$130),2) -> 0 | BB14: =IFERROR(ROUND(AU14 + AZ14, 2), AZ14) -> 0 | BC14: =IFERROR(ROUND(AV14 + BA14, 2), BA14) -> 0 | BF14: KMW-Mittel | BG14: =ROUND(SUMIF($BF$116:$BF$120,"KMW-Mittel",$BH$116:$BH$120)+SUMIF($BF$125:$BF$130,"KMW-Mittel",$BH$125:$BH$130),2) -> 0 | BH14: =ROUND(SUMIF($BF$116:$BF$120,"KMW-Mittel",$BI$116:$BI$120)+SUMIF($BF$125:$BF$130,"KMW-Mittel",$BI$125:$BI$130),2) -> 0 | BI14: =IFERROR(ROUND(BB14 + BG14, 2), BG14) -> 0 | BJ14: =IFERROR(ROUND(BC14 + BH14, 2), BH14) -> 0 | BM14: KMW-Mittel | BN14: =ROUND(SUMIF($BM$116:$BM$120,"KMW-Mittel",$BO$116:$BO$120)+SUMIF($BM$125:$BM$130,"KMW-Mittel",$BO$125:$BO$130),2) -> 0 | BO14: =ROUND(SUMIF($BM$116:$BM$120,"KMW-Mittel",$BP$116:$BP$120)+SUMIF($BM$125:$BM$130,"KMW-Mittel",$BP$125:$BP$130),2) -> 0 | BP14: =IFERROR(ROUND(BI14 + BN14, 2), BN14) -> 0 | BQ14: =IFERROR(ROUND(BJ14 + BO14, 2), BO14) -> 0 | BT14: KMW-Mittel | BU14: =ROUND(SUMIF($BT$116:$BT$120,"KMW-Mittel",$BV$116:$BV$120)+SUMIF($BT$125:$BT$130,"KMW-Mittel",$BV$125:$BV$130),2) -> 0 | BV14: =ROUND(SUMIF($BT$116:$BT$120,"KMW-Mittel",$BW$116:$BW$120)+SUMIF($BT$125:$BT$130,"KMW-Mittel",$BW$125:$BW$130),2) -> 0 | BW14: =IFERROR(ROUND(BP14 + BU14, 2), BU14) -> 0 | BX14: =IFERROR(ROUND(BQ14 + BV14, 2), BV14) -> 0 | CA14: KMW-Mittel | CB14: =ROUND(SUMIF($CA$116:$CA$120,"KMW-Mittel",$CC$116:$CC$120)+SUMIF($CA$125:$CA$130,"KMW-Mittel",$CC$125:$CC$130),2) -> 0 | CC14: =ROUND(SUMIF($CA$116:$CA$120,"KMW-Mittel",$CD$116:$CD$120)+SUMIF($CA$125:$CA$130,"KMW-Mittel",$CD$125:$CD$130),2) -> 0 | CD14: =IFERROR(ROUND(BW14 + CB14, 2), CB14) -> 0 | CE14: =IFERROR(ROUND(BX14 + CC14, 2), CC14) -> 0 | CH14: KMW-Mittel | CI14: =ROUND(SUMIF($CH$116:$CH$120,"KMW-Mittel",$CJ$116:$CJ$120)+SUMIF($CH$125:$CH$130,"KMW-Mittel",$CJ$125:$CJ$130),2) -> 0 | CJ14: =ROUND(SUMIF($CH$116:$CH$120,"KMW-Mittel",$CK$116:$CK$120)+SUMIF($CH$125:$CH$130,"KMW-Mittel",$CK$125:$CK$130),2) -> 0 | CK14: =IFERROR(ROUND(CD14 + CI14, 2), CI14) -> 0 | CL14: =IFERROR(ROUND(CE14 + CJ14, 2), CJ14) -> 0 | CO14: KMW-Mittel | CP14: =ROUND(SUMIF($CO$116:$CO$120,"KMW-Mittel",$CQ$116:$CQ$120)+SUMIF($CO$125:$CO$130,"KMW-Mittel",$CQ$125:$CQ$130),2) -> 0 | CQ14: =ROUND(SUMIF($CO$116:$CO$120,"KMW-Mittel",$CR$116:$CR$120)+SUMIF($CO$125:$CO$130,"KMW-Mittel",$CR$125:$CR$130),2) -> 0 | CR14: =IFERROR(ROUND(CK14 + CP14, 2), CP14) -> 0 | CS14: =IFERROR(ROUND(CL14 + CQ14, 2), CQ14) -> 0 | CV14: KMW-Mittel | CW14: =ROUND(SUMIF($CV$116:$CV$120,"KMW-Mittel",$CX$116:$CX$120)+SUMIF($CV$125:$CV$130,"KMW-Mittel",$CX$125:$CX$130),2) -> 0 | CX14: =ROUND(SUMIF($CV$116:$CV$120,"KMW-Mittel",$CY$116:$CY$120)+SUMIF($CV$125:$CV$130,"KMW-Mittel",$CY$125:$CY$130),2) -> 0 | CY14: =IFERROR(ROUND(CR14 + CW14, 2), CW14) -> 0 | CZ14: =IFERROR(ROUND(CS14 + CX14, 2), CX14) -> 0 | DC14: KMW-Mittel | DD14: =ROUND(SUMIF($DC$116:$DC$120,"KMW-Mittel",$DE$116:$DE$120)+SUMIF($DC$125:$DC$130,"KMW-Mittel",$DE$125:$DE$130),2) -> 0 | DE14: =ROUND(SUMIF($DC$116:$DC$120,"KMW-Mittel",$DF$116:$DF$120)+SUMIF($DC$125:$DC$130,"KMW-Mittel",$DF$125:$DF$130),2) -> 0 | DF14: =IFERROR(ROUND(CY14 + DD14, 2), DD14) -> 0 | DG14: =IFERROR(ROUND(CZ14 + DE14, 2), DE14) -> 0 | DJ14: KMW-Mittel | DK14: =ROUND(SUMIF($DJ$116:$DJ$120,"KMW-Mittel",$DL$116:$DL$120)+SUMIF($DJ$125:$DJ$130,"KMW-Mittel",$DL$125:$DL$130),2) -> 0 | DL14: =ROUND(SUMIF($DJ$116:$DJ$120,"KMW-Mittel",$DM$116:$DM$120)+SUMIF($DJ$125:$DJ$130,"KMW-Mittel",$DM$125:$DM$130),2) -> 0 | DM14: =IFERROR(ROUND(DF14 + DK14, 2), DK14) -> 0 | DN14: =IFERROR(ROUND(DG14 + DL14, 2), DL14) -> 0 | DQ14: KMW-Mittel | DR14: =ROUND(SUMIF($DQ$116:$DQ$120,"KMW-Mittel",$DS$116:$DS$120)+SUMIF($DQ$125:$DQ$130,"KMW-Mittel",$DS$125:$DS$130),2) -> 0 | DS14: =ROUND(SUMIF($DQ$116:$DQ$120,"KMW-Mittel",$DT$116:$DT$120)+SUMIF($DQ$125:$DQ$130,"KMW-Mittel",$DT$125:$DT$130),2) -> 0 | DT14: =IFERROR(ROUND(DM14 + DR14, 2), DR14) -> 0 | DU14: =IFERROR(ROUND(DN14 + DS14, 2), DS14) -> 0
B15: Zinsertraege | C15: =ROUND(SUMIF($B$116:$B$120,"Zinsertraege",$D$116:$D$120)+SUMIF($B$125:$B$130,"Zinsertraege",$D$125:$D$130),2) -> 0 | D15: =ROUND(SUMIF($B$116:$B$120,"Zinsertraege",$E$116:$E$120)+SUMIF($B$125:$B$130,"Zinsertraege",$E$125:$E$130),2) -> 0 | E15: =ROUND(SUMIF($B$116:$B$120,"Zinsertraege",$D$116:$D$120)+SUMIF($B$125:$B$130,"Zinsertraege",$D$125:$D$130),2) -> 0 | F15: =ROUND(SUMIF($B$116:$B$120,"Zinsertraege",$E$116:$E$120)+SUMIF($B$125:$B$130,"Zinsertraege",$E$125:$E$130),2) -> 0 | I15: Zinsertraege | J15: =ROUND(SUMIF($I$116:$I$120,"Zinsertraege",$K$116:$K$120)+SUMIF($I$125:$I$130,"Zinsertraege",$K$125:$K$130),2) -> 0 | K15: =ROUND(SUMIF($I$116:$I$120,"Zinsertraege",$L$116:$L$120)+SUMIF($I$125:$I$130,"Zinsertraege",$L$125:$L$130),2) -> 0 | L15: =IFERROR(ROUND(E15 + J15, 2), J15) -> 0 | M15: =IFERROR(ROUND(F15 + K15, 2), K15) -> 0 | P15: Zinsertraege | Q15: =ROUND(SUMIF($P$116:$P$120,"Zinsertraege",$R$116:$R$120)+SUMIF($P$125:$P$130,"Zinsertraege",$R$125:$R$130),2) -> 0 | R15: =ROUND(SUMIF($P$116:$P$120,"Zinsertraege",$S$116:$S$120)+SUMIF($P$125:$P$130,"Zinsertraege",$S$125:$S$130),2) -> 0 | S15: =IFERROR(ROUND(L15 + Q15, 2), Q15) -> 0 | T15: =IFERROR(ROUND(M15 + R15, 2), R15) -> 0 | W15: Zinsertraege | X15: =ROUND(SUMIF($W$116:$W$120,"Zinsertraege",$Y$116:$Y$120)+SUMIF($W$125:$W$130,"Zinsertraege",$Y$125:$Y$130),2) -> 0 | Y15: =ROUND(SUMIF($W$116:$W$120,"Zinsertraege",$Z$116:$Z$120)+SUMIF($W$125:$W$130,"Zinsertraege",$Z$125:$Z$130),2) -> 0 | Z15: =IFERROR(ROUND(S15 + X15, 2), X15) -> 0 | AA15: =IFERROR(ROUND(T15 + Y15, 2), Y15) -> 0 | AD15: Zinsertraege | AE15: =ROUND(SUMIF($AD$116:$AD$120,"Zinsertraege",$AF$116:$AF$120)+SUMIF($AD$125:$AD$130,"Zinsertraege",$AF$125:$AF$130),2) -> 0 | AF15: =ROUND(SUMIF($AD$116:$AD$120,"Zinsertraege",$AG$116:$AG$120)+SUMIF($AD$125:$AD$130,"Zinsertraege",$AG$125:$AG$130),2) -> 0 | AG15: =IFERROR(ROUND(Z15 + AE15, 2), AE15) -> 0 | AH15: =IFERROR(ROUND(AA15 + AF15, 2), AF15) -> 0 | AK15: Zinsertraege | AL15: =ROUND(SUMIF($AK$116:$AK$120,"Zinsertraege",$AM$116:$AM$120)+SUMIF($AK$125:$AK$130,"Zinsertraege",$AM$125:$AM$130),2) -> 0 | AM15: =ROUND(SUMIF($AK$116:$AK$120,"Zinsertraege",$AN$116:$AN$120)+SUMIF($AK$125:$AK$130,"Zinsertraege",$AN$125:$AN$130),2) -> 0 | AN15: =IFERROR(ROUND(AG15 + AL15, 2), AL15) -> 0 | AO15: =IFERROR(ROUND(AH15 + AM15, 2), AM15) -> 0 | AR15: Zinsertraege | AS15: =ROUND(SUMIF($AR$116:$AR$120,"Zinsertraege",$AT$116:$AT$120)+SUMIF($AR$125:$AR$130,"Zinsertraege",$AT$125:$AT$130),2) -> 0 | AT15: =ROUND(SUMIF($AR$116:$AR$120,"Zinsertraege",$AU$116:$AU$120)+SUMIF($AR$125:$AR$130,"Zinsertraege",$AU$125:$AU$130),2) -> 0 | AU15: =IFERROR(ROUND(AN15 + AS15, 2), AS15) -> 0 | AV15: =IFERROR(ROUND(AO15 + AT15, 2), AT15) -> 0 | AY15: Zinsertraege | AZ15: =ROUND(SUMIF($AY$116:$AY$120,"Zinsertraege",$BA$116:$BA$120)+SUMIF($AY$125:$AY$130,"Zinsertraege",$BA$125:$BA$130),2) -> 0 | BA15: =ROUND(SUMIF($AY$116:$AY$120,"Zinsertraege",$BB$116:$BB$120)+SUMIF($AY$125:$AY$130,"Zinsertraege",$BB$125:$BB$130),2) -> 0 | BB15: =IFERROR(ROUND(AU15 + AZ15, 2), AZ15) -> 0 | BC15: =IFERROR(ROUND(AV15 + BA15, 2), BA15) -> 0 | BF15: Zinsertraege | BG15: =ROUND(SUMIF($BF$116:$BF$120,"Zinsertraege",$BH$116:$BH$120)+SUMIF($BF$125:$BF$130,"Zinsertraege",$BH$125:$BH$130),2) -> 0 | BH15: =ROUND(SUMIF($BF$116:$BF$120,"Zinsertraege",$BI$116:$BI$120)+SUMIF($BF$125:$BF$130,"Zinsertraege",$BI$125:$BI$130),2) -> 0 | BI15: =IFERROR(ROUND(BB15 + BG15, 2), BG15) -> 0 | BJ15: =IFERROR(ROUND(BC15 + BH15, 2), BH15) -> 0 | BM15: Zinsertraege | BN15: =ROUND(SUMIF($BM$116:$BM$120,"Zinsertraege",$BO$116:$BO$120)+SUMIF($BM$125:$BM$130,"Zinsertraege",$BO$125:$BO$130),2) -> 0 | BO15: =ROUND(SUMIF($BM$116:$BM$120,"Zinsertraege",$BP$116:$BP$120)+SUMIF($BM$125:$BM$130,"Zinsertraege",$BP$125:$BP$130),2) -> 0 | BP15: =IFERROR(ROUND(BI15 + BN15, 2), BN15) -> 0 | BQ15: =IFERROR(ROUND(BJ15 + BO15, 2), BO15) -> 0 | BT15: Zinsertraege | BU15: =ROUND(SUMIF($BT$116:$BT$120,"Zinsertraege",$BV$116:$BV$120)+SUMIF($BT$125:$BT$130,"Zinsertraege",$BV$125:$BV$130),2) -> 0 | BV15: =ROUND(SUMIF($BT$116:$BT$120,"Zinsertraege",$BW$116:$BW$120)+SUMIF($BT$125:$BT$130,"Zinsertraege",$BW$125:$BW$130),2) -> 0 | BW15: =IFERROR(ROUND(BP15 + BU15, 2), BU15) -> 0 | BX15: =IFERROR(ROUND(BQ15 + BV15, 2), BV15) -> 0 | CA15: Zinsertraege | CB15: =ROUND(SUMIF($CA$116:$CA$120,"Zinsertraege",$CC$116:$CC$120)+SUMIF($CA$125:$CA$130,"Zinsertraege",$CC$125:$CC$130),2) -> 0 | CC15: =ROUND(SUMIF($CA$116:$CA$120,"Zinsertraege",$CD$116:$CD$120)+SUMIF($CA$125:$CA$130,"Zinsertraege",$CD$125:$CD$130),2) -> 0 | CD15: =IFERROR(ROUND(BW15 + CB15, 2), CB15) -> 0 | CE15: =IFERROR(ROUND(BX15 + CC15, 2), CC15) -> 0 | CH15: Zinsertraege | CI15: =ROUND(SUMIF($CH$116:$CH$120,"Zinsertraege",$CJ$116:$CJ$120)+SUMIF($CH$125:$CH$130,"Zinsertraege",$CJ$125:$CJ$130),2) -> 0 | CJ15: =ROUND(SUMIF($CH$116:$CH$120,"Zinsertraege",$CK$116:$CK$120)+SUMIF($CH$125:$CH$130,"Zinsertraege",$CK$125:$CK$130),2) -> 0 | CK15: =IFERROR(ROUND(CD15 + CI15, 2), CI15) -> 0 | CL15: =IFERROR(ROUND(CE15 + CJ15, 2), CJ15) -> 0 | CO15: Zinsertraege | CP15: =ROUND(SUMIF($CO$116:$CO$120,"Zinsertraege",$CQ$116:$CQ$120)+SUMIF($CO$125:$CO$130,"Zinsertraege",$CQ$125:$CQ$130),2) -> 0 | CQ15: =ROUND(SUMIF($CO$116:$CO$120,"Zinsertraege",$CR$116:$CR$120)+SUMIF($CO$125:$CO$130,"Zinsertraege",$CR$125:$CR$130),2) -> 0 | CR15: =IFERROR(ROUND(CK15 + CP15, 2), CP15) -> 0 | CS15: =IFERROR(ROUND(CL15 + CQ15, 2), CQ15) -> 0 | CV15: Zinsertraege | CW15: =ROUND(SUMIF($CV$116:$CV$120,"Zinsertraege",$CX$116:$CX$120)+SUMIF($CV$125:$CV$130,"Zinsertraege",$CX$125:$CX$130),2) -> 0 | CX15: =ROUND(SUMIF($CV$116:$CV$120,"Zinsertraege",$CY$116:$CY$120)+SUMIF($CV$125:$CV$130,"Zinsertraege",$CY$125:$CY$130),2) -> 0 | CY15: =IFERROR(ROUND(CR15 + CW15, 2), CW15) -> 0 | CZ15: =IFERROR(ROUND(CS15 + CX15, 2), CX15) -> 0 | DC15: Zinsertraege | DD15: =ROUND(SUMIF($DC$116:$DC$120,"Zinsertraege",$DE$116:$DE$120)+SUMIF($DC$125:$DC$130,"Zinsertraege",$DE$125:$DE$130),2) -> 0 | DE15: =ROUND(SUMIF($DC$116:$DC$120,"Zinsertraege",$DF$116:$DF$120)+SUMIF($DC$125:$DC$130,"Zinsertraege",$DF$125:$DF$130),2) -> 0 | DF15: =IFERROR(ROUND(CY15 + DD15, 2), DD15) -> 0 | DG15: =IFERROR(ROUND(CZ15 + DE15, 2), DE15) -> 0 | DJ15: Zinsertraege | DK15: =ROUND(SUMIF($DJ$116:$DJ$120,"Zinsertraege",$DL$116:$DL$120)+SUMIF($DJ$125:$DJ$130,"Zinsertraege",$DL$125:$DL$130),2) -> 0 | DL15: =ROUND(SUMIF($DJ$116:$DJ$120,"Zinsertraege",$DM$116:$DM$120)+SUMIF($DJ$125:$DJ$130,"Zinsertraege",$DM$125:$DM$130),2) -> 0 | DM15: =IFERROR(ROUND(DF15 + DK15, 2), DK15) -> 0 | DN15: =IFERROR(ROUND(DG15 + DL15, 2), DL15) -> 0 | DQ15: Zinsertraege | DR15: =ROUND(SUMIF($DQ$116:$DQ$120,"Zinsertraege",$DS$116:$DS$120)+SUMIF($DQ$125:$DQ$130,"Zinsertraege",$DS$125:$DS$130),2) -> 0 | DS15: =ROUND(SUMIF($DQ$116:$DQ$120,"Zinsertraege",$DT$116:$DT$120)+SUMIF($DQ$125:$DQ$130,"Zinsertraege",$DT$125:$DT$130),2) -> 0 | DT15: =IFERROR(ROUND(DM15 + DR15, 2), DR15) -> 0 | DU15: =IFERROR(ROUND(DN15 + DS15, 2), DS15) -> 0
B16: Gesamteinnahmen | C16: =ROUND(SUM(C11:C15),2) -> 0 | D16: =ROUND(SUM(D11:D15),2) -> 0 | E16: =ROUND(SUM(E11:E15),2) -> 0 | F16: =ROUND(SUM(F11:F15),2) -> 0 | I16: Gesamteinnahmen | J16: =ROUND(SUM(J11:J15),2) -> 0 | K16: =ROUND(SUM(K11:K15),2) -> 0 | L16: =ROUND(SUM(L11:L15),2) -> 0 | M16: =ROUND(SUM(M11:M15),2) -> 0 | P16: Gesamteinnahmen | Q16: =ROUND(SUM(Q11:Q15),2) -> 0 | R16: =ROUND(SUM(R11:R15),2) -> 0 | S16: =ROUND(SUM(S11:S15),2) -> 0 | T16: =ROUND(SUM(T11:T15),2) -> 0 | W16: Gesamteinnahmen | X16: =ROUND(SUM(X11:X15),2) -> 0 | Y16: =ROUND(SUM(Y11:Y15),2) -> 0 | Z16: =ROUND(SUM(Z11:Z15),2) -> 0 | AA16: =ROUND(SUM(AA11:AA15),2) -> 0 | AD16: Gesamteinnahmen | AE16: =ROUND(SUM(AE11:AE15),2) -> 0 | AF16: =ROUND(SUM(AF11:AF15),2) -> 0 | AG16: =ROUND(SUM(AG11:AG15),2) -> 0 | AH16: =ROUND(SUM(AH11:AH15),2) -> 0 | AK16: Gesamteinnahmen | AL16: =ROUND(SUM(AL11:AL15),2) -> 0 | AM16: =ROUND(SUM(AM11:AM15),2) -> 0 | AN16: =ROUND(SUM(AN11:AN15),2) -> 0 | AO16: =ROUND(SUM(AO11:AO15),2) -> 0 | AR16: Gesamteinnahmen | AS16: =ROUND(SUM(AS11:AS15),2) -> 0 | AT16: =ROUND(SUM(AT11:AT15),2) -> 0 | AU16: =ROUND(SUM(AU11:AU15),2) -> 0 | AV16: =ROUND(SUM(AV11:AV15),2) -> 0 | AY16: Gesamteinnahmen | AZ16: =ROUND(SUM(AZ11:AZ15),2) -> 0 | BA16: =ROUND(SUM(BA11:BA15),2) -> 0 | BB16: =ROUND(SUM(BB11:BB15),2) -> 0 | BC16: =ROUND(SUM(BC11:BC15),2) -> 0 | BF16: Gesamteinnahmen | BG16: =ROUND(SUM(BG11:BG15),2) -> 0 | BH16: =ROUND(SUM(BH11:BH15),2) -> 0 | BI16: =ROUND(SUM(BI11:BI15),2) -> 0 | BJ16: =ROUND(SUM(BJ11:BJ15),2) -> 0 | BM16: Gesamteinnahmen | BN16: =ROUND(SUM(BN11:BN15),2) -> 0 | BO16: =ROUND(SUM(BO11:BO15),2) -> 0 | BP16: =ROUND(SUM(BP11:BP15),2) -> 0 | BQ16: =ROUND(SUM(BQ11:BQ15),2) -> 0 | BT16: Gesamteinnahmen | BU16: =ROUND(SUM(BU11:BU15),2) -> 0 | BV16: =ROUND(SUM(BV11:BV15),2) -> 0 | BW16: =ROUND(SUM(BW11:BW15),2) -> 0 | BX16: =ROUND(SUM(BX11:BX15),2) -> 0 | CA16: Gesamteinnahmen | CB16: =ROUND(SUM(CB11:CB15),2) -> 0 | CC16: =ROUND(SUM(CC11:CC15),2) -> 0 | CD16: =ROUND(SUM(CD11:CD15),2) -> 0 | CE16: =ROUND(SUM(CE11:CE15),2) -> 0 | CH16: Gesamteinnahmen | CI16: =ROUND(SUM(CI11:CI15),2) -> 0 | CJ16: =ROUND(SUM(CJ11:CJ15),2) -> 0 | CK16: =ROUND(SUM(CK11:CK15),2) -> 0 | CL16: =ROUND(SUM(CL11:CL15),2) -> 0 | CO16: Gesamteinnahmen | CP16: =ROUND(SUM(CP11:CP15),2) -> 0 | CQ16: =ROUND(SUM(CQ11:CQ15),2) -> 0 | CR16: =ROUND(SUM(CR11:CR15),2) -> 0 | CS16: =ROUND(SUM(CS11:CS15),2) -> 0 | CV16: Gesamteinnahmen | CW16: =ROUND(SUM(CW11:CW15),2) -> 0 | CX16: =ROUND(SUM(CX11:CX15),2) -> 0 | CY16: =ROUND(SUM(CY11:CY15),2) -> 0 | CZ16: =ROUND(SUM(CZ11:CZ15),2) -> 0 | DC16: Gesamteinnahmen | DD16: =ROUND(SUM(DD11:DD15),2) -> 0 | DE16: =ROUND(SUM(DE11:DE15),2) -> 0 | DF16: =ROUND(SUM(DF11:DF15),2) -> 0 | DG16: =ROUND(SUM(DG11:DG15),2) -> 0 | DJ16: Gesamteinnahmen | DK16: =ROUND(SUM(DK11:DK15),2) -> 0 | DL16: =ROUND(SUM(DL11:DL15),2) -> 0 | DM16: =ROUND(SUM(DM11:DM15),2) -> 0 | DN16: =ROUND(SUM(DN11:DN15),2) -> 0 | DQ16: Gesamteinnahmen | DR16: =ROUND(SUM(DR11:DR15),2) -> 0 | DS16: =ROUND(SUM(DS11:DS15),2) -> 0 | DT16: =ROUND(SUM(DT11:DT15),2) -> 0 | DU16: =ROUND(SUM(DU11:DU15),2) -> 0
B17: Ausgaben | I17: Ausgaben | P17: Ausgaben | W17: Ausgaben | AD17: Ausgaben | AK17: Ausgaben | AR17: Ausgaben | AY17: Ausgaben | BF17: Ausgaben | BM17: Ausgaben | BT17: Ausgaben | CA17: Ausgaben | CH17: Ausgaben | CO17: Ausgaben | CV17: Ausgaben | DC17: Ausgaben | DJ17: Ausgaben | DQ17: Ausgaben
B18: ID | C18: Ausgaben (LC) | D18: Ausgaben (EUR) | E18: Kum. Ausgaben (LC) | F18: Kum. Ausgaben (EUR) | I18: ID | J18: Ausgaben (LC) | K18: Ausgaben (EUR) | L18: Kum. Ausgaben (LC) | M18: Kum. Ausgaben (EUR) | P18: ID | Q18: Ausgaben (LC) | R18: Ausgaben (EUR) | S18: Kum. Ausgaben (LC) | T18: Kum. Ausgaben (EUR) | W18: ID | X18: Ausgaben (LC) | Y18: Ausgaben (EUR) | Z18: Kum. Ausgaben (LC) | AA18: Kum. Ausgaben (EUR) | AD18: ID | AE18: Ausgaben (LC) | AF18: Ausgaben (EUR) | AG18: Kum. Ausgaben (LC) | AH18: Kum. Ausgaben (EUR) | AK18: ID | AL18: Ausgaben (LC) | AM18: Ausgaben (EUR) | AN18: Kum. Ausgaben (LC) | AO18: Kum. Ausgaben (EUR) | AR18: ID | AS18: Ausgaben (LC) | AT18: Ausgaben (EUR) | AU18: Kum. Ausgaben (LC) | AV18: Kum. Ausgaben (EUR) | AY18: ID | AZ18: Ausgaben (LC) | BA18: Ausgaben (EUR) | BB18: Kum. Ausgaben (LC) | BC18: Kum. Ausgaben (EUR) | BF18: ID | BG18: Ausgaben (LC) | BH18: Ausgaben (EUR) | BI18: Kum. Ausgaben (LC) | BJ18: Kum. Ausgaben (EUR) | BM18: ID | BN18: Ausgaben (LC) | BO18: Ausgaben (EUR) | BP18: Kum. Ausgaben (LC) | BQ18: Kum. Ausgaben (EUR) | BT18: ID | BU18: Ausgaben (LC) | BV18: Ausgaben (EUR) | BW18: Kum. Ausgaben (LC) | BX18: Kum. Ausgaben (EUR) | CA18: ID | CB18: Ausgaben (LC) | CC18: Ausgaben (EUR) | CD18: Kum. Ausgaben (LC) | CE18: Kum. Ausgaben (EUR) | CH18: ID | CI18: Ausgaben (LC) | CJ18: Ausgaben (EUR) | CK18: Kum. Ausgaben (LC) | CL18: Kum. Ausgaben (EUR) | CO18: ID | CP18: Ausgaben (LC) | CQ18: Ausgaben (EUR) | CR18: Kum. Ausgaben (LC) | CS18: Kum. Ausgaben (EUR) | CV18: ID | CW18: Ausgaben (LC) | CX18: Ausgaben (EUR) | CY18: Kum. Ausgaben (LC) | CZ18: Kum. Ausgaben (EUR) | DC18: ID | DD18: Ausgaben (LC) | DE18: Ausgaben (EUR) | DF18: Kum. Ausgaben (LC) | DG18: Kum. Ausgaben (EUR) | DJ18: ID | DK18: Ausgaben (LC) | DL18: Ausgaben (EUR) | DM18: Kum. Ausgaben (LC) | DN18: Kum. Ausgaben (EUR) | DQ18: ID | DR18: Ausgaben (LC) | DS18: Ausgaben (EUR) | DT18: Kum. Ausgaben (LC) | DU18: Kum. Ausgaben (EUR)
B19: 1.1 | D19: =IFERROR(ROUND(C19/FB_Kurs_1,2),0) -> 0 | E19: =ROUND(C19,2) -> 0 | F19: =ROUND(D19,2) -> 0 | I19: 1.1 | K19: =IFERROR(ROUND(J19/FB_Kurs_2,2),0) -> 0 | L19: =ROUND(J19+E19,2) -> 0 | M19: =ROUND(K19+F19,2) -> 0 | P19: 1.1 | R19: =IFERROR(ROUND(Q19/FB_Kurs_3,2),0) -> 0 | S19: =ROUND(Q19+L19,2) -> 0 | T19: =ROUND(R19+M19,2) -> 0 | W19: 1.1 | Y19: =IFERROR(ROUND(X19/FB_Kurs_4,2),0) -> 0 | Z19: =ROUND(X19+S19,2) -> 0 | AA19: =ROUND(Y19+T19,2) -> 0 | AD19: 1.1 | AF19: =IFERROR(ROUND(AE19/FB_Kurs_5,2),0) -> 0 | AG19: =ROUND(AE19+Z19,2) -> 0 | AH19: =ROUND(AF19+AA19,2) -> 0 | AK19: 1.1 | AM19: =IFERROR(ROUND(AL19/FB_Kurs_6,2),0) -> 0 | AN19: =ROUND(AL19+AG19,2) -> 0 | AO19: =ROUND(AM19+AH19,2) -> 0 | AR19: 1.1 | AT19: =IFERROR(ROUND(AS19/FB_Kurs_7,2),0) -> 0 | AU19: =ROUND(AS19+AN19,2) -> 0 | AV19: =ROUND(AT19+AO19,2) -> 0 | AY19: 1.1 | BA19: =IFERROR(ROUND(AZ19/FB_Kurs_8,2),0) -> 0 | BB19: =ROUND(AZ19+AU19,2) -> 0 | BC19: =ROUND(BA19+AV19,2) -> 0 | BF19: 1.1 | BH19: =IFERROR(ROUND(BG19/FB_Kurs_9,2),0) -> 0 | BI19: =ROUND(BG19+BB19,2) -> 0 | BJ19: =ROUND(BH19+BC19,2) -> 0 | BM19: 1.1 | BO19: =IFERROR(ROUND(BN19/FB_Kurs_10,2),0) -> 0 | BP19: =ROUND(BN19+BI19,2) -> 0 | BQ19: =ROUND(BO19+BJ19,2) -> 0 | BT19: 1.1 | BV19: =IFERROR(ROUND(BU19/FB_Kurs_11,2),0) -> 0 | BW19: =ROUND(BU19+BP19,2) -> 0 | BX19: =ROUND(BV19+BQ19,2) -> 0 | CA19: 1.1 | CC19: =IFERROR(ROUND(CB19/FB_Kurs_12,2),0) -> 0 | CD19: =ROUND(CB19+BW19,2) -> 0 | CE19: =ROUND(CC19+BX19,2) -> 0 | CH19: 1.1 | CJ19: =IFERROR(ROUND(CI19/FB_Kurs_13,2),0) -> 0 | CK19: =ROUND(CI19+CD19,2) -> 0 | CL19: =ROUND(CJ19+CE19,2) -> 0 | CO19: 1.1 | CQ19: =IFERROR(ROUND(CP19/FB_Kurs_14,2),0) -> 0 | CR19: =ROUND(CP19+CK19,2) -> 0 | CS19: =ROUND(CQ19+CL19,2) -> 0 | CV19: 1.1 | CX19: =IFERROR(ROUND(CW19/FB_Kurs_15,2),0) -> 0 | CY19: =ROUND(CW19+CR19,2) -> 0 | CZ19: =ROUND(CX19+CS19,2) -> 0 | DC19: 1.1 | DE19: =IFERROR(ROUND(DD19/FB_Kurs_16,2),0) -> 0 | DF19: =ROUND(DD19+CY19,2) -> 0 | DG19: =ROUND(DE19+CZ19,2) -> 0 | DJ19: 1.1 | DL19: =IFERROR(ROUND(DK19/FB_Kurs_17,2),0) -> 0 | DM19: =ROUND(DK19+DF19,2) -> 0 | DN19: =ROUND(DL19+DG19,2) -> 0 | DQ19: 1.1 | DS19: =IFERROR(ROUND(DR19/FB_Kurs_18,2),0) -> 0 | DT19: =ROUND(DR19+DM19,2) -> 0 | DU19: =ROUND(DS19+DN19,2) -> 0
B20: 1.2 | D20: =IFERROR(ROUND(C20/FB_Kurs_1,2),0) -> 0 | E20: =ROUND(C20,2) -> 0 | F20: =ROUND(D20,2) -> 0 | I20: 1.2 | K20: =IFERROR(ROUND(J20/FB_Kurs_2,2),0) -> 0 | L20: =ROUND(J20+E20,2) -> 0 | M20: =ROUND(K20+F20,2) -> 0 | P20: 1.2 | R20: =IFERROR(ROUND(Q20/FB_Kurs_3,2),0) -> 0 | S20: =ROUND(Q20+L20,2) -> 0 | T20: =ROUND(R20+M20,2) -> 0 | W20: 1.2 | Y20: =IFERROR(ROUND(X20/FB_Kurs_4,2),0) -> 0 | Z20: =ROUND(X20+S20,2) -> 0 | AA20: =ROUND(Y20+T20,2) -> 0 | AD20: 1.2 | AF20: =IFERROR(ROUND(AE20/FB_Kurs_5,2),0) -> 0 | AG20: =ROUND(AE20+Z20,2) -> 0 | AH20: =ROUND(AF20+AA20,2) -> 0 | AK20: 1.2 | AM20: =IFERROR(ROUND(AL20/FB_Kurs_6,2),0) -> 0 | AN20: =ROUND(AL20+AG20,2) -> 0 | AO20: =ROUND(AM20+AH20,2) -> 0 | AR20: 1.2 | AT20: =IFERROR(ROUND(AS20/FB_Kurs_7,2),0) -> 0 | AU20: =ROUND(AS20+AN20,2) -> 0 | AV20: =ROUND(AT20+AO20,2) -> 0 | AY20: 1.2 | BA20: =IFERROR(ROUND(AZ20/FB_Kurs_8,2),0) -> 0 | BB20: =ROUND(AZ20+AU20,2) -> 0 | BC20: =ROUND(BA20+AV20,2) -> 0 | BF20: 1.2 | BH20: =IFERROR(ROUND(BG20/FB_Kurs_9,2),0) -> 0 | BI20: =ROUND(BG20+BB20,2) -> 0 | BJ20: =ROUND(BH20+BC20,2) -> 0 | BM20: 1.2 | BO20: =IFERROR(ROUND(BN20/FB_Kurs_10,2),0) -> 0 | BP20: =ROUND(BN20+BI20,2) -> 0 | BQ20: =ROUND(BO20+BJ20,2) -> 0 | BT20: 1.2 | BV20: =IFERROR(ROUND(BU20/FB_Kurs_11,2),0) -> 0 | BW20: =ROUND(BU20+BP20,2) -> 0 | BX20: =ROUND(BV20+BQ20,2) -> 0 | CA20: 1.2 | CC20: =IFERROR(ROUND(CB20/FB_Kurs_12,2),0) -> 0 | CD20: =ROUND(CB20+BW20,2) -> 0 | CE20: =ROUND(CC20+BX20,2) -> 0 | CH20: 1.2 | CJ20: =IFERROR(ROUND(CI20/FB_Kurs_13,2),0) -> 0 | CK20: =ROUND(CI20+CD20,2) -> 0 | CL20: =ROUND(CJ20+CE20,2) -> 0 | CO20: 1.2 | CQ20: =IFERROR(ROUND(CP20/FB_Kurs_14,2),0) -> 0 | CR20: =ROUND(CP20+CK20,2) -> 0 | CS20: =ROUND(CQ20+CL20,2) -> 0 | CV20: 1.2 | CX20: =IFERROR(ROUND(CW20/FB_Kurs_15,2),0) -> 0 | CY20: =ROUND(CW20+CR20,2) -> 0 | CZ20: =ROUND(CX20+CS20,2) -> 0 | DC20: 1.2 | DE20: =IFERROR(ROUND(DD20/FB_Kurs_16,2),0) -> 0 | DF20: =ROUND(DD20+CY20,2) -> 0 | DG20: =ROUND(DE20+CZ20,2) -> 0 | DJ20: 1.2 | DL20: =IFERROR(ROUND(DK20/FB_Kurs_17,2),0) -> 0 | DM20: =ROUND(DK20+DF20,2) -> 0 | DN20: =ROUND(DL20+DG20,2) -> 0 | DQ20: 1.2 | DS20: =IFERROR(ROUND(DR20/FB_Kurs_18,2),0) -> 0 | DT20: =ROUND(DR20+DM20,2) -> 0 | DU20: =ROUND(DS20+DN20,2) -> 0
B21: 1.3 | D21: =IFERROR(ROUND(C21/FB_Kurs_1,2),0) -> 0 | E21: =ROUND(C21,2) -> 0 | F21: =ROUND(D21,2) -> 0 | I21: 1.3 | K21: =IFERROR(ROUND(J21/FB_Kurs_2,2),0) -> 0 | L21: =ROUND(J21+E21,2) -> 0 | M21: =ROUND(K21+F21,2) -> 0 | P21: 1.3 | R21: =IFERROR(ROUND(Q21/FB_Kurs_3,2),0) -> 0 | S21: =ROUND(Q21+L21,2) -> 0 | T21: =ROUND(R21+M21,2) -> 0 | W21: 1.3 | Y21: =IFERROR(ROUND(X21/FB_Kurs_4,2),0) -> 0 | Z21: =ROUND(X21+S21,2) -> 0 | AA21: =ROUND(Y21+T21,2) -> 0 | AD21: 1.3 | AF21: =IFERROR(ROUND(AE21/FB_Kurs_5,2),0) -> 0 | AG21: =ROUND(AE21+Z21,2) -> 0 | AH21: =ROUND(AF21+AA21,2) -> 0 | AK21: 1.3 | AM21: =IFERROR(ROUND(AL21/FB_Kurs_6,2),0) -> 0 | AN21: =ROUND(AL21+AG21,2) -> 0 | AO21: =ROUND(AM21+AH21,2) -> 0 | AR21: 1.3 | AT21: =IFERROR(ROUND(AS21/FB_Kurs_7,2),0) -> 0 | AU21: =ROUND(AS21+AN21,2) -> 0 | AV21: =ROUND(AT21+AO21,2) -> 0 | AY21: 1.3 | BA21: =IFERROR(ROUND(AZ21/FB_Kurs_8,2),0) -> 0 | BB21: =ROUND(AZ21+AU21,2) -> 0 | BC21: =ROUND(BA21+AV21,2) -> 0 | BF21: 1.3 | BH21: =IFERROR(ROUND(BG21/FB_Kurs_9,2),0) -> 0 | BI21: =ROUND(BG21+BB21,2) -> 0 | BJ21: =ROUND(BH21+BC21,2) -> 0 | BM21: 1.3 | BO21: =IFERROR(ROUND(BN21/FB_Kurs_10,2),0) -> 0 | BP21: =ROUND(BN21+BI21,2) -> 0 | BQ21: =ROUND(BO21+BJ21,2) -> 0 | BT21: 1.3 | BV21: =IFERROR(ROUND(BU21/FB_Kurs_11,2),0) -> 0 | BW21: =ROUND(BU21+BP21,2) -> 0 | BX21: =ROUND(BV21+BQ21,2) -> 0 | CA21: 1.3 | CC21: =IFERROR(ROUND(CB21/FB_Kurs_12,2),0) -> 0 | CD21: =ROUND(CB21+BW21,2) -> 0 | CE21: =ROUND(CC21+BX21,2) -> 0 | CH21: 1.3 | CJ21: =IFERROR(ROUND(CI21/FB_Kurs_13,2),0) -> 0 | CK21: =ROUND(CI21+CD21,2) -> 0 | CL21: =ROUND(CJ21+CE21,2) -> 0 | CO21: 1.3 | CQ21: =IFERROR(ROUND(CP21/FB_Kurs_14,2),0) -> 0 | CR21: =ROUND(CP21+CK21,2) -> 0 | CS21: =ROUND(CQ21+CL21,2) -> 0 | CV21: 1.3 | CX21: =IFERROR(ROUND(CW21/FB_Kurs_15,2),0) -> 0 | CY21: =ROUND(CW21+CR21,2) -> 0 | CZ21: =ROUND(CX21+CS21,2) -> 0 | DC21: 1.3 | DE21: =IFERROR(ROUND(DD21/FB_Kurs_16,2),0) -> 0 | DF21: =ROUND(DD21+CY21,2) -> 0 | DG21: =ROUND(DE21+CZ21,2) -> 0 | DJ21: 1.3 | DL21: =IFERROR(ROUND(DK21/FB_Kurs_17,2),0) -> 0 | DM21: =ROUND(DK21+DF21,2) -> 0 | DN21: =ROUND(DL21+DG21,2) -> 0 | DQ21: 1.3 | DS21: =IFERROR(ROUND(DR21/FB_Kurs_18,2),0) -> 0 | DT21: =ROUND(DR21+DM21,2) -> 0 | DU21: =ROUND(DS21+DN21,2) -> 0
B22: 1.4 | D22: =IFERROR(ROUND(C22/FB_Kurs_1,2),0) -> 0 | E22: =ROUND(C22,2) -> 0 | F22: =ROUND(D22,2) -> 0 | I22: 1.4 | K22: =IFERROR(ROUND(J22/FB_Kurs_2,2),0) -> 0 | L22: =ROUND(J22+E22,2) -> 0 | M22: =ROUND(K22+F22,2) -> 0 | P22: 1.4 | R22: =IFERROR(ROUND(Q22/FB_Kurs_3,2),0) -> 0 | S22: =ROUND(Q22+L22,2) -> 0 | T22: =ROUND(R22+M22,2) -> 0 | W22: 1.4 | Y22: =IFERROR(ROUND(X22/FB_Kurs_4,2),0) -> 0 | Z22: =ROUND(X22+S22,2) -> 0 | AA22: =ROUND(Y22+T22,2) -> 0 | AD22: 1.4 | AF22: =IFERROR(ROUND(AE22/FB_Kurs_5,2),0) -> 0 | AG22: =ROUND(AE22+Z22,2) -> 0 | AH22: =ROUND(AF22+AA22,2) -> 0 | AK22: 1.4 | AM22: =IFERROR(ROUND(AL22/FB_Kurs_6,2),0) -> 0 | AN22: =ROUND(AL22+AG22,2) -> 0 | AO22: =ROUND(AM22+AH22,2) -> 0 | AR22: 1.4 | AT22: =IFERROR(ROUND(AS22/FB_Kurs_7,2),0) -> 0 | AU22: =ROUND(AS22+AN22,2) -> 0 | AV22: =ROUND(AT22+AO22,2) -> 0 | AY22: 1.4 | BA22: =IFERROR(ROUND(AZ22/FB_Kurs_8,2),0) -> 0 | BB22: =ROUND(AZ22+AU22,2) -> 0 | BC22: =ROUND(BA22+AV22,2) -> 0 | BF22: 1.4 | BH22: =IFERROR(ROUND(BG22/FB_Kurs_9,2),0) -> 0 | BI22: =ROUND(BG22+BB22,2) -> 0 | BJ22: =ROUND(BH22+BC22,2) -> 0 | BM22: 1.4 | BO22: =IFERROR(ROUND(BN22/FB_Kurs_10,2),0) -> 0 | BP22: =ROUND(BN22+BI22,2) -> 0 | BQ22: =ROUND(BO22+BJ22,2) -> 0 | BT22: 1.4 | BV22: =IFERROR(ROUND(BU22/FB_Kurs_11,2),0) -> 0 | BW22: =ROUND(BU22+BP22,2) -> 0 | BX22: =ROUND(BV22+BQ22,2) -> 0 | CA22: 1.4 | CC22: =IFERROR(ROUND(CB22/FB_Kurs_12,2),0) -> 0 | CD22: =ROUND(CB22+BW22,2) -> 0 | CE22: =ROUND(CC22+BX22,2) -> 0 | CH22: 1.4 | CJ22: =IFERROR(ROUND(CI22/FB_Kurs_13,2),0) -> 0 | CK22: =ROUND(CI22+CD22,2) -> 0 | CL22: =ROUND(CJ22+CE22,2) -> 0 | CO22: 1.4 | CQ22: =IFERROR(ROUND(CP22/FB_Kurs_14,2),0) -> 0 | CR22: =ROUND(CP22+CK22,2) -> 0 | CS22: =ROUND(CQ22+CL22,2) -> 0 | CV22: 1.4 | CX22: =IFERROR(ROUND(CW22/FB_Kurs_15,2),0) -> 0 | CY22: =ROUND(CW22+CR22,2) -> 0 | CZ22: =ROUND(CX22+CS22,2) -> 0 | DC22: 1.4 | DE22: =IFERROR(ROUND(DD22/FB_Kurs_16,2),0) -> 0 | DF22: =ROUND(DD22+CY22,2) -> 0 | DG22: =ROUND(DE22+CZ22,2) -> 0 | DJ22: 1.4 | DL22: =IFERROR(ROUND(DK22/FB_Kurs_17,2),0) -> 0 | DM22: =ROUND(DK22+DF22,2) -> 0 | DN22: =ROUND(DL22+DG22,2) -> 0 | DQ22: 1.4 | DS22: =IFERROR(ROUND(DR22/FB_Kurs_18,2),0) -> 0 | DT22: =ROUND(DR22+DM22,2) -> 0 | DU22: =ROUND(DS22+DN22,2) -> 0
B23: 1.5 | D23: =IFERROR(ROUND(C23/FB_Kurs_1,2),0) -> 0 | E23: =ROUND(C23,2) -> 0 | F23: =ROUND(D23,2) -> 0 | I23: 1.5 | K23: =IFERROR(ROUND(J23/FB_Kurs_2,2),0) -> 0 | L23: =ROUND(J23+E23,2) -> 0 | M23: =ROUND(K23+F23,2) -> 0 | P23: 1.5 | R23: =IFERROR(ROUND(Q23/FB_Kurs_3,2),0) -> 0 | S23: =ROUND(Q23+L23,2) -> 0 | T23: =ROUND(R23+M23,2) -> 0 | W23: 1.5 | Y23: =IFERROR(ROUND(X23/FB_Kurs_4,2),0) -> 0 | Z23: =ROUND(X23+S23,2) -> 0 | AA23: =ROUND(Y23+T23,2) -> 0 | AD23: 1.5 | AF23: =IFERROR(ROUND(AE23/FB_Kurs_5,2),0) -> 0 | AG23: =ROUND(AE23+Z23,2) -> 0 | AH23: =ROUND(AF23+AA23,2) -> 0 | AK23: 1.5 | AM23: =IFERROR(ROUND(AL23/FB_Kurs_6,2),0) -> 0 | AN23: =ROUND(AL23+AG23,2) -> 0 | AO23: =ROUND(AM23+AH23,2) -> 0 | AR23: 1.5 | AT23: =IFERROR(ROUND(AS23/FB_Kurs_7,2),0) -> 0 | AU23: =ROUND(AS23+AN23,2) -> 0 | AV23: =ROUND(AT23+AO23,2) -> 0 | AY23: 1.5 | BA23: =IFERROR(ROUND(AZ23/FB_Kurs_8,2),0) -> 0 | BB23: =ROUND(AZ23+AU23,2) -> 0 | BC23: =ROUND(BA23+AV23,2) -> 0 | BF23: 1.5 | BH23: =IFERROR(ROUND(BG23/FB_Kurs_9,2),0) -> 0 | BI23: =ROUND(BG23+BB23,2) -> 0 | BJ23: =ROUND(BH23+BC23,2) -> 0 | BM23: 1.5 | BO23: =IFERROR(ROUND(BN23/FB_Kurs_10,2),0) -> 0 | BP23: =ROUND(BN23+BI23,2) -> 0 | BQ23: =ROUND(BO23+BJ23,2) -> 0 | BT23: 1.5 | BV23: =IFERROR(ROUND(BU23/FB_Kurs_11,2),0) -> 0 | BW23: =ROUND(BU23+BP23,2) -> 0 | BX23: =ROUND(BV23+BQ23,2) -> 0 | CA23: 1.5 | CC23: =IFERROR(ROUND(CB23/FB_Kurs_12,2),0) -> 0 | CD23: =ROUND(CB23+BW23,2) -> 0 | CE23: =ROUND(CC23+BX23,2) -> 0 | CH23: 1.5 | CJ23: =IFERROR(ROUND(CI23/FB_Kurs_13,2),0) -> 0 | CK23: =ROUND(CI23+CD23,2) -> 0 | CL23: =ROUND(CJ23+CE23,2) -> 0 | CO23: 1.5 | CQ23: =IFERROR(ROUND(CP23/FB_Kurs_14,2),0) -> 0 | CR23: =ROUND(CP23+CK23,2) -> 0 | CS23: =ROUND(CQ23+CL23,2) -> 0 | CV23: 1.5 | CX23: =IFERROR(ROUND(CW23/FB_Kurs_15,2),0) -> 0 | CY23: =ROUND(CW23+CR23,2) -> 0 | CZ23: =ROUND(CX23+CS23,2) -> 0 | DC23: 1.5 | DE23: =IFERROR(ROUND(DD23/FB_Kurs_16,2),0) -> 0 | DF23: =ROUND(DD23+CY23,2) -> 0 | DG23: =ROUND(DE23+CZ23,2) -> 0 | DJ23: 1.5 | DL23: =IFERROR(ROUND(DK23/FB_Kurs_17,2),0) -> 0 | DM23: =ROUND(DK23+DF23,2) -> 0 | DN23: =ROUND(DL23+DG23,2) -> 0 | DQ23: 1.5 | DS23: =IFERROR(ROUND(DR23/FB_Kurs_18,2),0) -> 0 | DT23: =ROUND(DR23+DM23,2) -> 0 | DU23: =ROUND(DS23+DN23,2) -> 0
B24: 1.6 | D24: =IFERROR(ROUND(C24/FB_Kurs_1,2),0) -> 0 | E24: =ROUND(C24,2) -> 0 | F24: =ROUND(D24,2) -> 0 | I24: 1.6 | K24: =IFERROR(ROUND(J24/FB_Kurs_2,2),0) -> 0 | L24: =ROUND(J24+E24,2) -> 0 | M24: =ROUND(K24+F24,2) -> 0 | P24: 1.6 | R24: =IFERROR(ROUND(Q24/FB_Kurs_3,2),0) -> 0 | S24: =ROUND(Q24+L24,2) -> 0 | T24: =ROUND(R24+M24,2) -> 0 | W24: 1.6 | Y24: =IFERROR(ROUND(X24/FB_Kurs_4,2),0) -> 0 | Z24: =ROUND(X24+S24,2) -> 0 | AA24: =ROUND(Y24+T24,2) -> 0 | AD24: 1.6 | AF24: =IFERROR(ROUND(AE24/FB_Kurs_5,2),0) -> 0 | AG24: =ROUND(AE24+Z24,2) -> 0 | AH24: =ROUND(AF24+AA24,2) -> 0 | AK24: 1.6 | AM24: =IFERROR(ROUND(AL24/FB_Kurs_6,2),0) -> 0 | AN24: =ROUND(AL24+AG24,2) -> 0 | AO24: =ROUND(AM24+AH24,2) -> 0 | AR24: 1.6 | AT24: =IFERROR(ROUND(AS24/FB_Kurs_7,2),0) -> 0 | AU24: =ROUND(AS24+AN24,2) -> 0 | AV24: =ROUND(AT24+AO24,2) -> 0 | AY24: 1.6 | BA24: =IFERROR(ROUND(AZ24/FB_Kurs_8,2),0) -> 0 | BB24: =ROUND(AZ24+AU24,2) -> 0 | BC24: =ROUND(BA24+AV24,2) -> 0 | BF24: 1.6 | BH24: =IFERROR(ROUND(BG24/FB_Kurs_9,2),0) -> 0 | BI24: =ROUND(BG24+BB24,2) -> 0 | BJ24: =ROUND(BH24+BC24,2) -> 0 | BM24: 1.6 | BO24: =IFERROR(ROUND(BN24/FB_Kurs_10,2),0) -> 0 | BP24: =ROUND(BN24+BI24,2) -> 0 | BQ24: =ROUND(BO24+BJ24,2) -> 0 | BT24: 1.6 | BV24: =IFERROR(ROUND(BU24/FB_Kurs_11,2),0) -> 0 | BW24: =ROUND(BU24+BP24,2) -> 0 | BX24: =ROUND(BV24+BQ24,2) -> 0 | CA24: 1.6 | CC24: =IFERROR(ROUND(CB24/FB_Kurs_12,2),0) -> 0 | CD24: =ROUND(CB24+BW24,2) -> 0 | CE24: =ROUND(CC24+BX24,2) -> 0 | CH24: 1.6 | CJ24: =IFERROR(ROUND(CI24/FB_Kurs_13,2),0) -> 0 | CK24: =ROUND(CI24+CD24,2) -> 0 | CL24: =ROUND(CJ24+CE24,2) -> 0 | CO24: 1.6 | CQ24: =IFERROR(ROUND(CP24/FB_Kurs_14,2),0) -> 0 | CR24: =ROUND(CP24+CK24,2) -> 0 | CS24: =ROUND(CQ24+CL24,2) -> 0 | CV24: 1.6 | CX24: =IFERROR(ROUND(CW24/FB_Kurs_15,2),0) -> 0 | CY24: =ROUND(CW24+CR24,2) -> 0 | CZ24: =ROUND(CX24+CS24,2) -> 0 | DC24: 1.6 | DE24: =IFERROR(ROUND(DD24/FB_Kurs_16,2),0) -> 0 | DF24: =ROUND(DD24+CY24,2) -> 0 | DG24: =ROUND(DE24+CZ24,2) -> 0 | DJ24: 1.6 | DL24: =IFERROR(ROUND(DK24/FB_Kurs_17,2),0) -> 0 | DM24: =ROUND(DK24+DF24,2) -> 0 | DN24: =ROUND(DL24+DG24,2) -> 0 | DQ24: 1.6 | DS24: =IFERROR(ROUND(DR24/FB_Kurs_18,2),0) -> 0 | DT24: =ROUND(DR24+DM24,2) -> 0 | DU24: =ROUND(DS24+DN24,2) -> 0
B25: 1.7 | D25: =IFERROR(ROUND(C25/FB_Kurs_1,2),0) -> 0 | E25: =ROUND(C25,2) -> 0 | F25: =ROUND(D25,2) -> 0 | I25: 1.7 | K25: =IFERROR(ROUND(J25/FB_Kurs_2,2),0) -> 0 | L25: =ROUND(J25+E25,2) -> 0 | M25: =ROUND(K25+F25,2) -> 0 | P25: 1.7 | R25: =IFERROR(ROUND(Q25/FB_Kurs_3,2),0) -> 0 | S25: =ROUND(Q25+L25,2) -> 0 | T25: =ROUND(R25+M25,2) -> 0 | W25: 1.7 | Y25: =IFERROR(ROUND(X25/FB_Kurs_4,2),0) -> 0 | Z25: =ROUND(X25+S25,2) -> 0 | AA25: =ROUND(Y25+T25,2) -> 0 | AD25: 1.7 | AF25: =IFERROR(ROUND(AE25/FB_Kurs_5,2),0) -> 0 | AG25: =ROUND(AE25+Z25,2) -> 0 | AH25: =ROUND(AF25+AA25,2) -> 0 | AK25: 1.7 | AM25: =IFERROR(ROUND(AL25/FB_Kurs_6,2),0) -> 0 | AN25: =ROUND(AL25+AG25,2) -> 0 | AO25: =ROUND(AM25+AH25,2) -> 0 | AR25: 1.7 | AT25: =IFERROR(ROUND(AS25/FB_Kurs_7,2),0) -> 0 | AU25: =ROUND(AS25+AN25,2) -> 0 | AV25: =ROUND(AT25+AO25,2) -> 0 | AY25: 1.7 | BA25: =IFERROR(ROUND(AZ25/FB_Kurs_8,2),0) -> 0 | BB25: =ROUND(AZ25+AU25,2) -> 0 | BC25: =ROUND(BA25+AV25,2) -> 0 | BF25: 1.7 | BH25: =IFERROR(ROUND(BG25/FB_Kurs_9,2),0) -> 0 | BI25: =ROUND(BG25+BB25,2) -> 0 | BJ25: =ROUND(BH25+BC25,2) -> 0 | BM25: 1.7 | BO25: =IFERROR(ROUND(BN25/FB_Kurs_10,2),0) -> 0 | BP25: =ROUND(BN25+BI25,2) -> 0 | BQ25: =ROUND(BO25+BJ25,2) -> 0 | BT25: 1.7 | BV25: =IFERROR(ROUND(BU25/FB_Kurs_11,2),0) -> 0 | BW25: =ROUND(BU25+BP25,2) -> 0 | BX25: =ROUND(BV25+BQ25,2) -> 0 | CA25: 1.7 | CC25: =IFERROR(ROUND(CB25/FB_Kurs_12,2),0) -> 0 | CD25: =ROUND(CB25+BW25,2) -> 0 | CE25: =ROUND(CC25+BX25,2) -> 0 | CH25: 1.7 | CJ25: =IFERROR(ROUND(CI25/FB_Kurs_13,2),0) -> 0 | CK25: =ROUND(CI25+CD25,2) -> 0 | CL25: =ROUND(CJ25+CE25,2) -> 0 | CO25: 1.7 | CQ25: =IFERROR(ROUND(CP25/FB_Kurs_14,2),0) -> 0 | CR25: =ROUND(CP25+CK25,2) -> 0 | CS25: =ROUND(CQ25+CL25,2) -> 0 | CV25: 1.7 | CX25: =IFERROR(ROUND(CW25/FB_Kurs_15,2),0) -> 0 | CY25: =ROUND(CW25+CR25,2) -> 0 | CZ25: =ROUND(CX25+CS25,2) -> 0 | DC25: 1.7 | DE25: =IFERROR(ROUND(DD25/FB_Kurs_16,2),0) -> 0 | DF25: =ROUND(DD25+CY25,2) -> 0 | DG25: =ROUND(DE25+CZ25,2) -> 0 | DJ25: 1.7 | DL25: =IFERROR(ROUND(DK25/FB_Kurs_17,2),0) -> 0 | DM25: =ROUND(DK25+DF25,2) -> 0 | DN25: =ROUND(DL25+DG25,2) -> 0 | DQ25: 1.7 | DS25: =IFERROR(ROUND(DR25/FB_Kurs_18,2),0) -> 0 | DT25: =ROUND(DR25+DM25,2) -> 0 | DU25: =ROUND(DS25+DN25,2) -> 0
B26: 1.8 | D26: =IFERROR(ROUND(C26/FB_Kurs_1,2),0) -> 0 | E26: =ROUND(C26,2) -> 0 | F26: =ROUND(D26,2) -> 0 | I26: 1.8 | K26: =IFERROR(ROUND(J26/FB_Kurs_2,2),0) -> 0 | L26: =ROUND(J26+E26,2) -> 0 | M26: =ROUND(K26+F26,2) -> 0 | P26: 1.8 | R26: =IFERROR(ROUND(Q26/FB_Kurs_3,2),0) -> 0 | S26: =ROUND(Q26+L26,2) -> 0 | T26: =ROUND(R26+M26,2) -> 0 | W26: 1.8 | Y26: =IFERROR(ROUND(X26/FB_Kurs_4,2),0) -> 0 | Z26: =ROUND(X26+S26,2) -> 0 | AA26: =ROUND(Y26+T26,2) -> 0 | AD26: 1.8 | AF26: =IFERROR(ROUND(AE26/FB_Kurs_5,2),0) -> 0 | AG26: =ROUND(AE26+Z26,2) -> 0 | AH26: =ROUND(AF26+AA26,2) -> 0 | AK26: 1.8 | AM26: =IFERROR(ROUND(AL26/FB_Kurs_6,2),0) -> 0 | AN26: =ROUND(AL26+AG26,2) -> 0 | AO26: =ROUND(AM26+AH26,2) -> 0 | AR26: 1.8 | AT26: =IFERROR(ROUND(AS26/FB_Kurs_7,2),0) -> 0 | AU26: =ROUND(AS26+AN26,2) -> 0 | AV26: =ROUND(AT26+AO26,2) -> 0 | AY26: 1.8 | BA26: =IFERROR(ROUND(AZ26/FB_Kurs_8,2),0) -> 0 | BB26: =ROUND(AZ26+AU26,2) -> 0 | BC26: =ROUND(BA26+AV26,2) -> 0 | BF26: 1.8 | BH26: =IFERROR(ROUND(BG26/FB_Kurs_9,2),0) -> 0 | BI26: =ROUND(BG26+BB26,2) -> 0 | BJ26: =ROUND(BH26+BC26,2) -> 0 | BM26: 1.8 | BO26: =IFERROR(ROUND(BN26/FB_Kurs_10,2),0) -> 0 | BP26: =ROUND(BN26+BI26,2) -> 0 | BQ26: =ROUND(BO26+BJ26,2) -> 0 | BT26: 1.8 | BV26: =IFERROR(ROUND(BU26/FB_Kurs_11,2),0) -> 0 | BW26: =ROUND(BU26+BP26,2) -> 0 | BX26: =ROUND(BV26+BQ26,2) -> 0 | CA26: 1.8 | CC26: =IFERROR(ROUND(CB26/FB_Kurs_12,2),0) -> 0 | CD26: =ROUND(CB26+BW26,2) -> 0 | CE26: =ROUND(CC26+BX26,2) -> 0 | CH26: 1.8 | CJ26: =IFERROR(ROUND(CI26/FB_Kurs_13,2),0) -> 0 | CK26: =ROUND(CI26+CD26,2) -> 0 | CL26: =ROUND(CJ26+CE26,2) -> 0 | CO26: 1.8 | CQ26: =IFERROR(ROUND(CP26/FB_Kurs_14,2),0) -> 0 | CR26: =ROUND(CP26+CK26,2) -> 0 | CS26: =ROUND(CQ26+CL26,2) -> 0 | CV26: 1.8 | CX26: =IFERROR(ROUND(CW26/FB_Kurs_15,2),0) -> 0 | CY26: =ROUND(CW26+CR26,2) -> 0 | CZ26: =ROUND(CX26+CS26,2) -> 0 | DC26: 1.8 | DE26: =IFERROR(ROUND(DD26/FB_Kurs_16,2),0) -> 0 | DF26: =ROUND(DD26+CY26,2) -> 0 | DG26: =ROUND(DE26+CZ26,2) -> 0 | DJ26: 1.8 | DL26: =IFERROR(ROUND(DK26/FB_Kurs_17,2),0) -> 0 | DM26: =ROUND(DK26+DF26,2) -> 0 | DN26: =ROUND(DL26+DG26,2) -> 0 | DQ26: 1.8 | DS26: =IFERROR(ROUND(DR26/FB_Kurs_18,2),0) -> 0 | DT26: =ROUND(DR26+DM26,2) -> 0 | DU26: =ROUND(DS26+DN26,2) -> 0
B27: 1.9 | D27: =IFERROR(ROUND(C27/FB_Kurs_1,2),0) -> 0 | E27: =ROUND(C27,2) -> 0 | F27: =ROUND(D27,2) -> 0 | I27: 1.9 | K27: =IFERROR(ROUND(J27/FB_Kurs_2,2),0) -> 0 | L27: =ROUND(J27+E27,2) -> 0 | M27: =ROUND(K27+F27,2) -> 0 | P27: 1.9 | R27: =IFERROR(ROUND(Q27/FB_Kurs_3,2),0) -> 0 | S27: =ROUND(Q27+L27,2) -> 0 | T27: =ROUND(R27+M27,2) -> 0 | W27: 1.9 | Y27: =IFERROR(ROUND(X27/FB_Kurs_4,2),0) -> 0 | Z27: =ROUND(X27+S27,2) -> 0 | AA27: =ROUND(Y27+T27,2) -> 0 | AD27: 1.9 | AF27: =IFERROR(ROUND(AE27/FB_Kurs_5,2),0) -> 0 | AG27: =ROUND(AE27+Z27,2) -> 0 | AH27: =ROUND(AF27+AA27,2) -> 0 | AK27: 1.9 | AM27: =IFERROR(ROUND(AL27/FB_Kurs_6,2),0) -> 0 | AN27: =ROUND(AL27+AG27,2) -> 0 | AO27: =ROUND(AM27+AH27,2) -> 0 | AR27: 1.9 | AT27: =IFERROR(ROUND(AS27/FB_Kurs_7,2),0) -> 0 | AU27: =ROUND(AS27+AN27,2) -> 0 | AV27: =ROUND(AT27+AO27,2) -> 0 | AY27: 1.9 | BA27: =IFERROR(ROUND(AZ27/FB_Kurs_8,2),0) -> 0 | BB27: =ROUND(AZ27+AU27,2) -> 0 | BC27: =ROUND(BA27+AV27,2) -> 0 | BF27: 1.9 | BH27: =IFERROR(ROUND(BG27/FB_Kurs_9,2),0) -> 0 | BI27: =ROUND(BG27+BB27,2) -> 0 | BJ27: =ROUND(BH27+BC27,2) -> 0 | BM27: 1.9 | BO27: =IFERROR(ROUND(BN27/FB_Kurs_10,2),0) -> 0 | BP27: =ROUND(BN27+BI27,2) -> 0 | BQ27: =ROUND(BO27+BJ27,2) -> 0 | BT27: 1.9 | BV27: =IFERROR(ROUND(BU27/FB_Kurs_11,2),0) -> 0 | BW27: =ROUND(BU27+BP27,2) -> 0 | BX27: =ROUND(BV27+BQ27,2) -> 0 | CA27: 1.9 | CC27: =IFERROR(ROUND(CB27/FB_Kurs_12,2),0) -> 0 | CD27: =ROUND(CB27+BW27,2) -> 0 | CE27: =ROUND(CC27+BX27,2) -> 0 | CH27: 1.9 | CJ27: =IFERROR(ROUND(CI27/FB_Kurs_13,2),0) -> 0 | CK27: =ROUND(CI27+CD27,2) -> 0 | CL27: =ROUND(CJ27+CE27,2) -> 0 | CO27: 1.9 | CQ27: =IFERROR(ROUND(CP27/FB_Kurs_14,2),0) -> 0 | CR27: =ROUND(CP27+CK27,2) -> 0 | CS27: =ROUND(CQ27+CL27,2) -> 0 | CV27: 1.9 | CX27: =IFERROR(ROUND(CW27/FB_Kurs_15,2),0) -> 0 | CY27: =ROUND(CW27+CR27,2) -> 0 | CZ27: =ROUND(CX27+CS27,2) -> 0 | DC27: 1.9 | DE27: =IFERROR(ROUND(DD27/FB_Kurs_16,2),0) -> 0 | DF27: =ROUND(DD27+CY27,2) -> 0 | DG27: =ROUND(DE27+CZ27,2) -> 0 | DJ27: 1.9 | DL27: =IFERROR(ROUND(DK27/FB_Kurs_17,2),0) -> 0 | DM27: =ROUND(DK27+DF27,2) -> 0 | DN27: =ROUND(DL27+DG27,2) -> 0 | DQ27: 1.9 | DS27: =IFERROR(ROUND(DR27/FB_Kurs_18,2),0) -> 0 | DT27: =ROUND(DR27+DM27,2) -> 0 | DU27: =ROUND(DS27+DN27,2) -> 0
B28: 1.10 | D28: =IFERROR(ROUND(C28/FB_Kurs_1,2),0) -> 0 | E28: =ROUND(C28,2) -> 0 | F28: =ROUND(D28,2) -> 0 | I28: 1.10 | K28: =IFERROR(ROUND(J28/FB_Kurs_2,2),0) -> 0 | L28: =ROUND(J28+E28,2) -> 0 | M28: =ROUND(K28+F28,2) -> 0 | P28: 1.10 | R28: =IFERROR(ROUND(Q28/FB_Kurs_3,2),0) -> 0 | S28: =ROUND(Q28+L28,2) -> 0 | T28: =ROUND(R28+M28,2) -> 0 | W28: 1.10 | Y28: =IFERROR(ROUND(X28/FB_Kurs_4,2),0) -> 0 | Z28: =ROUND(X28+S28,2) -> 0 | AA28: =ROUND(Y28+T28,2) -> 0 | AD28: 1.10 | AF28: =IFERROR(ROUND(AE28/FB_Kurs_5,2),0) -> 0 | AG28: =ROUND(AE28+Z28,2) -> 0 | AH28: =ROUND(AF28+AA28,2) -> 0 | AK28: 1.10 | AM28: =IFERROR(ROUND(AL28/FB_Kurs_6,2),0) -> 0 | AN28: =ROUND(AL28+AG28,2) -> 0 | AO28: =ROUND(AM28+AH28,2) -> 0 | AR28: 1.10 | AT28: =IFERROR(ROUND(AS28/FB_Kurs_7,2),0) -> 0 | AU28: =ROUND(AS28+AN28,2) -> 0 | AV28: =ROUND(AT28+AO28,2) -> 0 | AY28: 1.10 | BA28: =IFERROR(ROUND(AZ28/FB_Kurs_8,2),0) -> 0 | BB28: =ROUND(AZ28+AU28,2) -> 0 | BC28: =ROUND(BA28+AV28,2) -> 0 | BF28: 1.10 | BH28: =IFERROR(ROUND(BG28/FB_Kurs_9,2),0) -> 0 | BI28: =ROUND(BG28+BB28,2) -> 0 | BJ28: =ROUND(BH28+BC28,2) -> 0 | BM28: 1.10 | BO28: =IFERROR(ROUND(BN28/FB_Kurs_10,2),0) -> 0 | BP28: =ROUND(BN28+BI28,2) -> 0 | BQ28: =ROUND(BO28+BJ28,2) -> 0 | BT28: 1.10 | BV28: =IFERROR(ROUND(BU28/FB_Kurs_11,2),0) -> 0 | BW28: =ROUND(BU28+BP28,2) -> 0 | BX28: =ROUND(BV28+BQ28,2) -> 0 | CA28: 1.10 | CC28: =IFERROR(ROUND(CB28/FB_Kurs_12,2),0) -> 0 | CD28: =ROUND(CB28+BW28,2) -> 0 | CE28: =ROUND(CC28+BX28,2) -> 0 | CH28: 1.10 | CJ28: =IFERROR(ROUND(CI28/FB_Kurs_13,2),0) -> 0 | CK28: =ROUND(CI28+CD28,2) -> 0 | CL28: =ROUND(CJ28+CE28,2) -> 0 | CO28: 1.10 | CQ28: =IFERROR(ROUND(CP28/FB_Kurs_14,2),0) -> 0 | CR28: =ROUND(CP28+CK28,2) -> 0 | CS28: =ROUND(CQ28+CL28,2) -> 0 | CV28: 1.10 | CX28: =IFERROR(ROUND(CW28/FB_Kurs_15,2),0) -> 0 | CY28: =ROUND(CW28+CR28,2) -> 0 | CZ28: =ROUND(CX28+CS28,2) -> 0 | DC28: 1.10 | DE28: =IFERROR(ROUND(DD28/FB_Kurs_16,2),0) -> 0 | DF28: =ROUND(DD28+CY28,2) -> 0 | DG28: =ROUND(DE28+CZ28,2) -> 0 | DJ28: 1.10 | DL28: =IFERROR(ROUND(DK28/FB_Kurs_17,2),0) -> 0 | DM28: =ROUND(DK28+DF28,2) -> 0 | DN28: =ROUND(DL28+DG28,2) -> 0 | DQ28: 1.10 | DS28: =IFERROR(ROUND(DR28/FB_Kurs_18,2),0) -> 0 | DT28: =ROUND(DR28+DM28,2) -> 0 | DU28: =ROUND(DS28+DN28,2) -> 0
B29: 1.11 | D29: =IFERROR(ROUND(C29/FB_Kurs_1,2),0) -> 0 | E29: =ROUND(C29,2) -> 0 | F29: =ROUND(D29,2) -> 0 | I29: 1.11 | K29: =IFERROR(ROUND(J29/FB_Kurs_2,2),0) -> 0 | L29: =ROUND(J29+E29,2) -> 0 | M29: =ROUND(K29+F29,2) -> 0 | P29: 1.11 | R29: =IFERROR(ROUND(Q29/FB_Kurs_3,2),0) -> 0 | S29: =ROUND(Q29+L29,2) -> 0 | T29: =ROUND(R29+M29,2) -> 0 | W29: 1.11 | Y29: =IFERROR(ROUND(X29/FB_Kurs_4,2),0) -> 0 | Z29: =ROUND(X29+S29,2) -> 0 | AA29: =ROUND(Y29+T29,2) -> 0 | AD29: 1.11 | AF29: =IFERROR(ROUND(AE29/FB_Kurs_5,2),0) -> 0 | AG29: =ROUND(AE29+Z29,2) -> 0 | AH29: =ROUND(AF29+AA29,2) -> 0 | AK29: 1.11 | AM29: =IFERROR(ROUND(AL29/FB_Kurs_6,2),0) -> 0 | AN29: =ROUND(AL29+AG29,2) -> 0 | AO29: =ROUND(AM29+AH29,2) -> 0 | AR29: 1.11 | AT29: =IFERROR(ROUND(AS29/FB_Kurs_7,2),0) -> 0 | AU29: =ROUND(AS29+AN29,2) -> 0 | AV29: =ROUND(AT29+AO29,2) -> 0 | AY29: 1.11 | BA29: =IFERROR(ROUND(AZ29/FB_Kurs_8,2),0) -> 0 | BB29: =ROUND(AZ29+AU29,2) -> 0 | BC29: =ROUND(BA29+AV29,2) -> 0 | BF29: 1.11 | BH29: =IFERROR(ROUND(BG29/FB_Kurs_9,2),0) -> 0 | BI29: =ROUND(BG29+BB29,2) -> 0 | BJ29: =ROUND(BH29+BC29,2) -> 0 | BM29: 1.11 | BO29: =IFERROR(ROUND(BN29/FB_Kurs_10,2),0) -> 0 | BP29: =ROUND(BN29+BI29,2) -> 0 | BQ29: =ROUND(BO29+BJ29,2) -> 0 | BT29: 1.11 | BV29: =IFERROR(ROUND(BU29/FB_Kurs_11,2),0) -> 0 | BW29: =ROUND(BU29+BP29,2) -> 0 | BX29: =ROUND(BV29+BQ29,2) -> 0 | CA29: 1.11 | CC29: =IFERROR(ROUND(CB29/FB_Kurs_12,2),0) -> 0 | CD29: =ROUND(CB29+BW29,2) -> 0 | CE29: =ROUND(CC29+BX29,2) -> 0 | CH29: 1.11 | CJ29: =IFERROR(ROUND(CI29/FB_Kurs_13,2),0) -> 0 | CK29: =ROUND(CI29+CD29,2) -> 0 | CL29: =ROUND(CJ29+CE29,2) -> 0 | CO29: 1.11 | CQ29: =IFERROR(ROUND(CP29/FB_Kurs_14,2),0) -> 0 | CR29: =ROUND(CP29+CK29,2) -> 0 | CS29: =ROUND(CQ29+CL29,2) -> 0 | CV29: 1.11 | CX29: =IFERROR(ROUND(CW29/FB_Kurs_15,2),0) -> 0 | CY29: =ROUND(CW29+CR29,2) -> 0 | CZ29: =ROUND(CX29+CS29,2) -> 0 | DC29: 1.11 | DE29: =IFERROR(ROUND(DD29/FB_Kurs_16,2),0) -> 0 | DF29: =ROUND(DD29+CY29,2) -> 0 | DG29: =ROUND(DE29+CZ29,2) -> 0 | DJ29: 1.11 | DL29: =IFERROR(ROUND(DK29/FB_Kurs_17,2),0) -> 0 | DM29: =ROUND(DK29+DF29,2) -> 0 | DN29: =ROUND(DL29+DG29,2) -> 0 | DQ29: 1.11 | DS29: =IFERROR(ROUND(DR29/FB_Kurs_18,2),0) -> 0 | DT29: =ROUND(DR29+DM29,2) -> 0 | DU29: =ROUND(DS29+DN29,2) -> 0
B30: 1.12 | D30: =IFERROR(ROUND(C30/FB_Kurs_1,2),0) -> 0 | E30: =ROUND(C30,2) -> 0 | F30: =ROUND(D30,2) -> 0 | I30: 1.12 | K30: =IFERROR(ROUND(J30/FB_Kurs_2,2),0) -> 0 | L30: =ROUND(J30+E30,2) -> 0 | M30: =ROUND(K30+F30,2) -> 0 | P30: 1.12 | R30: =IFERROR(ROUND(Q30/FB_Kurs_3,2),0) -> 0 | S30: =ROUND(Q30+L30,2) -> 0 | T30: =ROUND(R30+M30,2) -> 0 | W30: 1.12 | Y30: =IFERROR(ROUND(X30/FB_Kurs_4,2),0) -> 0 | Z30: =ROUND(X30+S30,2) -> 0 | AA30: =ROUND(Y30+T30,2) -> 0 | AD30: 1.12 | AF30: =IFERROR(ROUND(AE30/FB_Kurs_5,2),0) -> 0 | AG30: =ROUND(AE30+Z30,2) -> 0 | AH30: =ROUND(AF30+AA30,2) -> 0 | AK30: 1.12 | AM30: =IFERROR(ROUND(AL30/FB_Kurs_6,2),0) -> 0 | AN30: =ROUND(AL30+AG30,2) -> 0 | AO30: =ROUND(AM30+AH30,2) -> 0 | AR30: 1.12 | AT30: =IFERROR(ROUND(AS30/FB_Kurs_7,2),0) -> 0 | AU30: =ROUND(AS30+AN30,2) -> 0 | AV30: =ROUND(AT30+AO30,2) -> 0 | AY30: 1.12 | BA30: =IFERROR(ROUND(AZ30/FB_Kurs_8,2),0) -> 0 | BB30: =ROUND(AZ30+AU30,2) -> 0 | BC30: =ROUND(BA30+AV30,2) -> 0 | BF30: 1.12 | BH30: =IFERROR(ROUND(BG30/FB_Kurs_9,2),0) -> 0 | BI30: =ROUND(BG30+BB30,2) -> 0 | BJ30: =ROUND(BH30+BC30,2) -> 0 | BM30: 1.12 | BO30: =IFERROR(ROUND(BN30/FB_Kurs_10,2),0) -> 0 | BP30: =ROUND(BN30+BI30,2) -> 0 | BQ30: =ROUND(BO30+BJ30,2) -> 0 | BT30: 1.12 | BV30: =IFERROR(ROUND(BU30/FB_Kurs_11,2),0) -> 0 | BW30: =ROUND(BU30+BP30,2) -> 0 | BX30: =ROUND(BV30+BQ30,2) -> 0 | CA30: 1.12 | CC30: =IFERROR(ROUND(CB30/FB_Kurs_12,2),0) -> 0 | CD30: =ROUND(CB30+BW30,2) -> 0 | CE30: =ROUND(CC30+BX30,2) -> 0 | CH30: 1.12 | CJ30: =IFERROR(ROUND(CI30/FB_Kurs_13,2),0) -> 0 | CK30: =ROUND(CI30+CD30,2) -> 0 | CL30: =ROUND(CJ30+CE30,2) -> 0 | CO30: 1.12 | CQ30: =IFERROR(ROUND(CP30/FB_Kurs_14,2),0) -> 0 | CR30: =ROUND(CP30+CK30,2) -> 0 | CS30: =ROUND(CQ30+CL30,2) -> 0 | CV30: 1.12 | CX30: =IFERROR(ROUND(CW30/FB_Kurs_15,2),0) -> 0 | CY30: =ROUND(CW30+CR30,2) -> 0 | CZ30: =ROUND(CX30+CS30,2) -> 0 | DC30: 1.12 | DE30: =IFERROR(ROUND(DD30/FB_Kurs_16,2),0) -> 0 | DF30: =ROUND(DD30+CY30,2) -> 0 | DG30: =ROUND(DE30+CZ30,2) -> 0 | DJ30: 1.12 | DL30: =IFERROR(ROUND(DK30/FB_Kurs_17,2),0) -> 0 | DM30: =ROUND(DK30+DF30,2) -> 0 | DN30: =ROUND(DL30+DG30,2) -> 0 | DQ30: 1.12 | DS30: =IFERROR(ROUND(DR30/FB_Kurs_18,2),0) -> 0 | DT30: =ROUND(DR30+DM30,2) -> 0 | DU30: =ROUND(DS30+DN30,2) -> 0
... B101: 8. | D101: =IFERROR(ROUND(C101/FB_Kurs_1,2),0) -> 0 | E101: =ROUND(C101,2) -> 0 | F101: =ROUND(D101,2) -> 0 | I101: 8. | K101: =IFERROR(ROUND(J101/FB_Kurs_2,2),0) -> 0 | L101: =ROUND(J101+E101,2) -> 0 | M101: =ROUND(K101+F101,2) -> 0 | P101: 8. | R101: =IFERROR(ROUND(Q101/FB_Kurs_3,2),0) -> 0 | S101: =ROUND(Q101+L101,2) -> 0 | T101: =ROUND(R101+M101,2) -> 0 | W101: 8. | Y101: =IFERROR(ROUND(X101/FB_Kurs_4,2),0) -> 0 | Z101: =ROUND(X101+S101,2) -> 0 | AA101: =ROUND(Y101+T101,2) -> 0 | AD101: 8. | AF101: =IFERROR(ROUND(AE101/FB_Kurs_5,2),0) -> 0 | AG101: =ROUND(AE101+Z101,2) -> 0 | AH101: =ROUND(AF101+AA101,2) -> 0 | AK101: 8. | AM101: =IFERROR(ROUND(AL101/FB_Kurs_6,2),0) -> 0 | AN101: =ROUND(AL101+AG101,2) -> 0 | AO101: =ROUND(AM101+AH101,2) -> 0 | AR101: 8. | AT101: =IFERROR(ROUND(AS101/FB_Kurs_7,2),0) -> 0 | AU101: =ROUND(AS101+AN101,2) -> 0 | AV101: =ROUND(AT101+AO101,2) -> 0 | AY101: 8. | BA101: =IFERROR(ROUND(AZ101/FB_Kurs_8,2),0) -> 0 | BB101: =ROUND(AZ101+AU101,2) -> 0 | BC101: =ROUND(BA101+AV101,2) -> 0 | BF101: 8. | BH101: =IFERROR(ROUND(BG101/FB_Kurs_9,2),0) -> 0 | BI101: =ROUND(BG101+BB101,2) -> 0 | BJ101: =ROUND(BH101+BC101,2) -> 0 | BM101: 8. | BO101: =IFERROR(ROUND(BN101/FB_Kurs_10,2),0) -> 0 | BP101: =ROUND(BN101+BI101,2) -> 0 | BQ101: =ROUND(BO101+BJ101,2) -> 0 | BT101: 8. | BV101: =IFERROR(ROUND(BU101/FB_Kurs_11,2),0) -> 0 | BW101: =ROUND(BU101+BP101,2) -> 0 | BX101: =ROUND(BV101+BQ101,2) -> 0 | CA101: 8. | CC101: =IFERROR(ROUND(CB101/FB_Kurs_12,2),0) -> 0 | CD101: =ROUND(CB101+BW101,2) -> 0 | CE101: =ROUND(CC101+BX101,2) -> 0 | CH101: 8. | CJ101: =IFERROR(ROUND(CI101/FB_Kurs_13,2),0) -> 0 | CK101: =ROUND(CI101+CD101,2) -> 0 | CL101: =ROUND(CJ101+CE101,2) -> 0 | CO101: 8. | CQ101: =IFERROR(ROUND(CP101/FB_Kurs_14,2),0) -> 0 | CR101: =ROUND(CP101+CK101,2) -> 0 | CS101: =ROUND(CQ101+CL101,2) -> 0 | CV101: 8. | CX101: =IFERROR(ROUND(CW101/FB_Kurs_15,2),0) -> 0 | CY101: =ROUND(CW101+CR101,2) -> 0 | CZ101: =ROUND(CX101+CS101,2) -> 0 | DC101: 8. | DE101: =IFERROR(ROUND(DD101/FB_Kurs_16,2),0) -> 0 | DF101: =ROUND(DD101+CY101,2) -> 0 | DG101: =ROUND(DE101+CZ101,2) -> 0 | DJ101: 8. | DL101: =IFERROR(ROUND(DK101/FB_Kurs_17,2),0) -> 0 | DM101: =ROUND(DK101+DF101,2) -> 0 | DN101: =ROUND(DL101+DG101,2) -> 0 | DQ101: 8. | DS101: =IFERROR(ROUND(DR101/FB_Kurs_18,2),0) -> 0 | DT101: =ROUND(DR101+DM101,2) -> 0 | DU101: =ROUND(DS101+DN101,2) -> 0
B102: Gesamtausgaben | C102: =ROUND(SUBTOTAL(109,$C$19:$C$101),2) -> 0 | D102: =ROUND(SUBTOTAL(109,$D$19:$D$101),2) -> 0 | E102: =ROUND(SUBTOTAL(109,$E$19:$E$101),2) -> 0 | F102: =ROUND(SUBTOTAL(109,$F$19:$F$101),2) -> 0 | I102: Gesamtausgaben | J102: =ROUND(SUBTOTAL(109,$J$19:$J$101),2) -> 0 | K102: =ROUND(SUBTOTAL(109,$K$19:$K$101),2) -> 0 | L102: =ROUND(SUBTOTAL(109,$L$19:$L$101),2) -> 0 | M102: =ROUND(SUBTOTAL(109,$M$19:$M$101),2) -> 0 | P102: Gesamtausgaben | Q102: =ROUND(SUBTOTAL(109,$Q$19:$Q$101),2) -> 0 | R102: =ROUND(SUBTOTAL(109,$R$19:$R$101),2) -> 0 | S102: =ROUND(SUBTOTAL(109,$S$19:$S$101),2) -> 0 | T102: =ROUND(SUBTOTAL(109,$T$19:$T$101),2) -> 0 | W102: Gesamtausgaben | X102: =ROUND(SUBTOTAL(109,$X$19:$X$101),2) -> 0 | Y102: =ROUND(SUBTOTAL(109,$Y$19:$Y$101),2) -> 0 | Z102: =ROUND(SUBTOTAL(109,$Z$19:$Z$101),2) -> 0 | AA102: =ROUND(SUBTOTAL(109,$AA$19:$AA$101),2) -> 0 | AD102: Gesamtausgaben | AE102: =ROUND(SUBTOTAL(109,$AE$19:$AE$101),2) -> 0 | AF102: =ROUND(SUBTOTAL(109,$AF$19:$AF$101),2) -> 0 | AG102: =ROUND(SUBTOTAL(109,$AG$19:$AG$101),2) -> 0 | AH102: =ROUND(SUBTOTAL(109,$AH$19:$AH$101),2) -> 0 | AK102: Gesamtausgaben | AL102: =ROUND(SUBTOTAL(109,$AL$19:$AL$101),2) -> 0 | AM102: =ROUND(SUBTOTAL(109,$AM$19:$AM$101),2) -> 0 | AN102: =ROUND(SUBTOTAL(109,$AN$19:$AN$101),2) -> 0 | AO102: =ROUND(SUBTOTAL(109,$AO$19:$AO$101),2) -> 0 | AR102: Gesamtausgaben | AS102: =ROUND(SUBTOTAL(109,$AS$19:$AS$101),2) -> 0 | AT102: =ROUND(SUBTOTAL(109,$AT$19:$AT$101),2) -> 0 | AU102: =ROUND(SUBTOTAL(109,$AU$19:$AU$101),2) -> 0 | AV102: =ROUND(SUBTOTAL(109,$AV$19:$AV$101),2) -> 0 | AY102: Gesamtausgaben | AZ102: =ROUND(SUBTOTAL(109,$AZ$19:$AZ$101),2) -> 0 | BA102: =ROUND(SUBTOTAL(109,$BA$19:$BA$101),2) -> 0 | BB102: =ROUND(SUBTOTAL(109,$BB$19:$BB$101),2) -> 0 | BC102: =ROUND(SUBTOTAL(109,$BC$19:$BC$101),2) -> 0 | BF102: Gesamtausgaben | BG102: =ROUND(SUBTOTAL(109,$BG$19:$BG$101),2) -> 0 | BH102: =ROUND(SUBTOTAL(109,$BH$19:$BH$101),2) -> 0 | BI102: =ROUND(SUBTOTAL(109,$BI$19:$BI$101),2) -> 0 | BJ102: =ROUND(SUBTOTAL(109,$BJ$19:$BJ$101),2) -> 0 | BM102: Gesamtausgaben | BN102: =ROUND(SUBTOTAL(109,$BN$19:$BN$101),2) -> 0 | BO102: =ROUND(SUBTOTAL(109,$BO$19:$BO$101),2) -> 0 | BP102: =ROUND(SUBTOTAL(109,$BP$19:$BP$101),2) -> 0 | BQ102: =ROUND(SUBTOTAL(109,$BQ$19:$BQ$101),2) -> 0 | BT102: Gesamtausgaben | BU102: =ROUND(SUBTOTAL(109,$BU$19:$BU$101),2) -> 0 | BV102: =ROUND(SUBTOTAL(109,$BV$19:$BV$101),2) -> 0 | BW102: =ROUND(SUBTOTAL(109,$BW$19:$BW$101),2) -> 0 | BX102: =ROUND(SUBTOTAL(109,$BX$19:$BX$101),2) -> 0 | CA102: Gesamtausgaben | CB102: =ROUND(SUBTOTAL(109,$CB$19:$CB$101),2) -> 0 | CC102: =ROUND(SUBTOTAL(109,$CC$19:$CC$101),2) -> 0 | CD102: =ROUND(SUBTOTAL(109,$CD$19:$CD$101),2) -> 0 | CE102: =ROUND(SUBTOTAL(109,$CE$19:$CE$101),2) -> 0 | CH102: Gesamtausgaben | CI102: =ROUND(SUBTOTAL(109,$CI$19:$CI$101),2) -> 0 | CJ102: =ROUND(SUBTOTAL(109,$CJ$19:$CJ$101),2) -> 0 | CK102: =ROUND(SUBTOTAL(109,$CK$19:$CK$101),2) -> 0 | CL102: =ROUND(SUBTOTAL(109,$CL$19:$CL$101),2) -> 0 | CO102: Gesamtausgaben | CP102: =ROUND(SUBTOTAL(109,$CP$19:$CP$101),2) -> 0 | CQ102: =ROUND(SUBTOTAL(109,$CQ$19:$CQ$101),2) -> 0 | CR102: =ROUND(SUBTOTAL(109,$CR$19:$CR$101),2) -> 0 | CS102: =ROUND(SUBTOTAL(109,$CS$19:$CS$101),2) -> 0 | CV102: Gesamtausgaben | CW102: =ROUND(SUBTOTAL(109,$CW$19:$CW$101),2) -> 0 | CX102: =ROUND(SUBTOTAL(109,$CX$19:$CX$101),2) -> 0 | CY102: =ROUND(SUBTOTAL(109,$CY$19:$CY$101),2) -> 0 | CZ102: =ROUND(SUBTOTAL(109,$CZ$19:$CZ$101),2) -> 0 | DC102: Gesamtausgaben | DD102: =ROUND(SUBTOTAL(109,$DD$19:$DD$101),2) -> 0 | DE102: =ROUND(SUBTOTAL(109,$DE$19:$DE$101),2) -> 0 | DF102: =ROUND(SUBTOTAL(109,$DF$19:$DF$101),2) -> 0 | DG102: =ROUND(SUBTOTAL(109,$DG$19:$DG$101),2) -> 0 | DJ102: Gesamtausgaben | DK102: =ROUND(SUBTOTAL(109,$DK$19:$DK$101),2) -> 0 | DL102: =ROUND(SUBTOTAL(109,$DL$19:$DL$101),2) -> 0 | DM102: =ROUND(SUBTOTAL(109,$DM$19:$DM$101),2) -> 0 | DN102: =ROUND(SUBTOTAL(109,$DN$19:$DN$101),2) -> 0 | DQ102: Gesamtausgaben | DR102: =ROUND(SUBTOTAL(109,$DR$19:$DR$101),2) -> 0 | DS102: =ROUND(SUBTOTAL(109,$DS$19:$DS$101),2) -> 0 | DT102: =ROUND(SUBTOTAL(109,$DT$19:$DT$101),2) -> 0 | DU102: =ROUND(SUBTOTAL(109,$DU$19:$DU$101),2) -> 0
B104: Saldo des Finanzberichts | C104: =ROUND(IFERROR(C16-$C$102,""),2) -> 0 | D104: =ROUND(IFERROR(D16-$D$102,""),2) -> 0 | E104: =ROUND(IFERROR(E16-E102,""),2) -> 0 | F104: =ROUND(IFERROR(F16-F102,""),2) -> 0 | I104: Saldo des Finanzberichts | J104: =ROUND(IFERROR(J16-$J$102,""),2) -> 0 | K104: =ROUND(IFERROR(K16-$K$102,""),2) -> 0 | L104: =ROUND(IFERROR(L16-L102,""),2) -> 0 | M104: =ROUND(IFERROR(M16-M102,""),2) -> 0 | P104: Saldo des Finanzberichts | Q104: =ROUND(IFERROR(Q16-$Q$102,""),2) -> 0 | R104: =ROUND(IFERROR(R16-$R$102,""),2) -> 0 | S104: =ROUND(IFERROR(S16-S102,""),2) -> 0 | T104: =ROUND(IFERROR(T16-T102,""),2) -> 0 | W104: Saldo des Finanzberichts | X104: =ROUND(IFERROR(X16-$X$102,""),2) -> 0 | Y104: =ROUND(IFERROR(Y16-$Y$102,""),2) -> 0 | Z104: =ROUND(IFERROR(Z16-Z102,""),2) -> 0 | AA104: =ROUND(IFERROR(AA16-AA102,""),2) -> 0 | AD104: Saldo des Finanzberichts | AE104: =ROUND(IFERROR(AE16-$AE$102,""),2) -> 0 | AF104: =ROUND(IFERROR(AF16-$AF$102,""),2) -> 0 | AG104: =ROUND(IFERROR(AG16-AG102,""),2) -> 0 | AH104: =ROUND(IFERROR(AH16-AH102,""),2) -> 0 | AK104: Saldo des Finanzberichts | AL104: =ROUND(IFERROR(AL16-$AL$102,""),2) -> 0 | AM104: =ROUND(IFERROR(AM16-$AM$102,""),2) -> 0 | AN104: =ROUND(IFERROR(AN16-AN102,""),2) -> 0 | AO104: =ROUND(IFERROR(AO16-AO102,""),2) -> 0 | AR104: Saldo des Finanzberichts | AS104: =ROUND(IFERROR(AS16-$AS$102,""),2) -> 0 | AT104: =ROUND(IFERROR(AT16-$AT$102,""),2) -> 0 | AU104: =ROUND(IFERROR(AU16-AU102,""),2) -> 0 | AV104: =ROUND(IFERROR(AV16-AV102,""),2) -> 0 | AY104: Saldo des Finanzberichts | AZ104: =ROUND(IFERROR(AZ16-$AZ$102,""),2) -> 0 | BA104: =ROUND(IFERROR(BA16-$BA$102,""),2) -> 0 | BB104: =ROUND(IFERROR(BB16-BB102,""),2) -> 0 | BC104: =ROUND(IFERROR(BC16-BC102,""),2) -> 0 | BF104: Saldo des Finanzberichts | BG104: =ROUND(IFERROR(BG16-$BG$102,""),2) -> 0 | BH104: =ROUND(IFERROR(BH16-$BH$102,""),2) -> 0 | BI104: =ROUND(IFERROR(BI16-BI102,""),2) -> 0 | BJ104: =ROUND(IFERROR(BJ16-BJ102,""),2) -> 0 | BM104: Saldo des Finanzberichts | BN104: =ROUND(IFERROR(BN16-$BN$102,""),2) -> 0 | BO104: =ROUND(IFERROR(BO16-$BO$102,""),2) -> 0 | BP104: =ROUND(IFERROR(BP16-BP102,""),2) -> 0 | BQ104: =ROUND(IFERROR(BQ16-BQ102,""),2) -> 0 | BT104: Saldo des Finanzberichts | BU104: =ROUND(IFERROR(BU16-$BU$102,""),2) -> 0 | BV104: =ROUND(IFERROR(BV16-$BV$102,""),2) -> 0 | BW104: =ROUND(IFERROR(BW16-BW102,""),2) -> 0 | BX104: =ROUND(IFERROR(BX16-BX102,""),2) -> 0 | CA104: Saldo des Finanzberichts | CB104: =ROUND(IFERROR(CB16-$CB$102,""),2) -> 0 | CC104: =ROUND(IFERROR(CC16-$CC$102,""),2) -> 0 | CD104: =ROUND(IFERROR(CD16-CD102,""),2) -> 0 | CE104: =ROUND(IFERROR(CE16-CE102,""),2) -> 0 | CH104: Saldo des Finanzberichts | CI104: =ROUND(IFERROR(CI16-$CI$102,""),2) -> 0 | CJ104: =ROUND(IFERROR(CJ16-$CJ$102,""),2) -> 0 | CK104: =ROUND(IFERROR(CK16-CK102,""),2) -> 0 | CL104: =ROUND(IFERROR(CL16-CL102,""),2) -> 0 | CO104: Saldo des Finanzberichts | CP104: =ROUND(IFERROR(CP16-$CP$102,""),2) -> 0 | CQ104: =ROUND(IFERROR(CQ16-$CQ$102,""),2) -> 0 | CR104: =ROUND(IFERROR(CR16-CR102,""),2) -> 0 | CS104: =ROUND(IFERROR(CS16-CS102,""),2) -> 0 | CV104: Saldo des Finanzberichts | CW104: =ROUND(IFERROR(CW16-$CW$102,""),2) -> 0 | CX104: =ROUND(IFERROR(CX16-$CX$102,""),2) -> 0 | CY104: =ROUND(IFERROR(CY16-CY102,""),2) -> 0 | CZ104: =ROUND(IFERROR(CZ16-CZ102,""),2) -> 0 | DC104: Saldo des Finanzberichts | DD104: =ROUND(IFERROR(DD16-$DD$102,""),2) -> 0 | DE104: =ROUND(IFERROR(DE16-$DE$102,""),2) -> 0 | DF104: =ROUND(IFERROR(DF16-DF102,""),2) -> 0 | DG104: =ROUND(IFERROR(DG16-DG102,""),2) -> 0 | DJ104: Saldo des Finanzberichts | DK104: =ROUND(IFERROR(DK16-$DK$102,""),2) -> 0 | DL104: =ROUND(IFERROR(DL16-$DL$102,""),2) -> 0 | DM104: =ROUND(IFERROR(DM16-DM102,""),2) -> 0 | DN104: =ROUND(IFERROR(DN16-DN102,""),2) -> 0 | DQ104: Saldo des Finanzberichts | DR104: =ROUND(IFERROR(DR16-$DR$102,""),2) -> 0 | DS104: =ROUND(IFERROR(DS16-$DS$102,""),2) -> 0 | DT104: =ROUND(IFERROR(DT16-DT102,""),2) -> 0 | DU104: =ROUND(IFERROR(DU16-DU102,""),2) -> 0
B106: Aufschluesselung: | I106: Aufschluesselung: | P106: Aufschluesselung: | W106: Aufschluesselung: | AD106: Aufschluesselung: | AK106: Aufschluesselung: | AR106: Aufschluesselung: | AY106: Aufschluesselung: | BF106: Aufschluesselung: | BM106: Aufschluesselung: | BT106: Aufschluesselung: | CA106: Aufschluesselung: | CH106: Aufschluesselung: | CO106: Aufschluesselung: | CV106: Aufschluesselung: | DC106: Aufschluesselung: | DJ106: Aufschluesselung: | DQ106: Aufschluesselung:
B107: Bank | D107: =IF(C107=0, 0, IF(ROUND(SUM(C108:C109), 2)=0, ROUND(D104 - 0, 2), ROUND(C107 / ROUND(SUM(C107:C109), 2) * D104, 2))) -> 0 | I107: Bank | K107: =IF(J107=0, 0, IF(ROUND(SUM(J108:J109), 2)=0, ROUND(K104 - 0, 2), ROUND(J107 / ROUND(SUM(J107:J109), 2) * K104, 2))) -> 0 | P107: Bank | R107: =IF(Q107=0, 0, IF(ROUND(SUM(Q108:Q109), 2)=0, ROUND(R104 - 0, 2), ROUND(Q107 / ROUND(SUM(Q107:Q109), 2) * R104, 2))) -> 0 | W107: Bank | Y107: =IF(X107=0, 0, IF(ROUND(SUM(X108:X109), 2)=0, ROUND(Y104 - 0, 2), ROUND(X107 / ROUND(SUM(X107:X109), 2) * Y104, 2))) -> 0 | AD107: Bank | AF107: =IF(AE107=0, 0, IF(ROUND(SUM(AE108:AE109), 2)=0, ROUND(AF104 - 0, 2), ROUND(AE107 / ROUND(SUM(AE107:AE109), 2) * AF104, 2))) -> 0 | AK107: Bank | AM107: =IF(AL107=0, 0, IF(ROUND(SUM(AL108:AL109), 2)=0, ROUND(AM104 - 0, 2), ROUND(AL107 / ROUND(SUM(AL107:AL109), 2) * AM104, 2))) -> 0 | AR107: Bank | AT107: =IF(AS107=0, 0, IF(ROUND(SUM(AS108:AS109), 2)=0, ROUND(AT104 - 0, 2), ROUND(AS107 / ROUND(SUM(AS107:AS109), 2) * AT104, 2))) -> 0 | AY107: Bank | BA107: =IF(AZ107=0, 0, IF(ROUND(SUM(AZ108:AZ109), 2)=0, ROUND(BA104 - 0, 2), ROUND(AZ107 / ROUND(SUM(AZ107:AZ109), 2) * BA104, 2))) -> 0 | BF107: Bank | BH107: =IF(BG107=0, 0, IF(ROUND(SUM(BG108:BG109), 2)=0, ROUND(BH104 - 0, 2), ROUND(BG107 / ROUND(SUM(BG107:BG109), 2) * BH104, 2))) -> 0 | BM107: Bank | BO107: =IF(BN107=0, 0, IF(ROUND(SUM(BN108:BN109), 2)=0, ROUND(BO104 - 0, 2), ROUND(BN107 / ROUND(SUM(BN107:BN109), 2) * BO104, 2))) -> 0 | BT107: Bank | BV107: =IF(BU107=0, 0, IF(ROUND(SUM(BU108:BU109), 2)=0, ROUND(BV104 - 0, 2), ROUND(BU107 / ROUND(SUM(BU107:BU109), 2) * BV104, 2))) -> 0 | CA107: Bank | CC107: =IF(CB107=0, 0, IF(ROUND(SUM(CB108:CB109), 2)=0, ROUND(CC104 - 0, 2), ROUND(CB107 / ROUND(SUM(CB107:CB109), 2) * CC104, 2))) -> 0 | CH107: Bank | CJ107: =IF(CI107=0, 0, IF(ROUND(SUM(CI108:CI109), 2)=0, ROUND(CJ104 - 0, 2), ROUND(CI107 / ROUND(SUM(CI107:CI109), 2) * CJ104, 2))) -> 0 | CO107: Bank | CQ107: =IF(CP107=0, 0, IF(ROUND(SUM(CP108:CP109), 2)=0, ROUND(CQ104 - 0, 2), ROUND(CP107 / ROUND(SUM(CP107:CP109), 2) * CQ104, 2))) -> 0 | CV107: Bank | CX107: =IF(CW107=0, 0, IF(ROUND(SUM(CW108:CW109), 2)=0, ROUND(CX104 - 0, 2), ROUND(CW107 / ROUND(SUM(CW107:CW109), 2) * CX104, 2))) -> 0 | DC107: Bank | DE107: =IF(DD107=0, 0, IF(ROUND(SUM(DD108:DD109), 2)=0, ROUND(DE104 - 0, 2), ROUND(DD107 / ROUND(SUM(DD107:DD109), 2) * DE104, 2))) -> 0 | DJ107: Bank | DL107: =IF(DK107=0, 0, IF(ROUND(SUM(DK108:DK109), 2)=0, ROUND(DL104 - 0, 2), ROUND(DK107 / ROUND(SUM(DK107:DK109), 2) * DL104, 2))) -> 0 | DQ107: Bank | DS107: =IF(DR107=0, 0, IF(ROUND(SUM(DR108:DR109), 2)=0, ROUND(DS104 - 0, 2), ROUND(DR107 / ROUND(SUM(DR107:DR109), 2) * DS104, 2))) -> 0
B108: Kasse | D108: =IF(C108=0, 0, IF(ROUND(SUM(C109:C109), 2)=0, ROUND(D104 - SUM(D107:D107), 2), ROUND(C108 / ROUND(SUM(C107:C109), 2) * D104, 2))) -> 0 | I108: Kasse | K108: =IF(J108=0, 0, IF(ROUND(SUM(J109:J109), 2)=0, ROUND(K104 - SUM(K107:K107), 2), ROUND(J108 / ROUND(SUM(J107:J109), 2) * K104, 2))) -> 0 | P108: Kasse | R108: =IF(Q108=0, 0, IF(ROUND(SUM(Q109:Q109), 2)=0, ROUND(R104 - SUM(R107:R107), 2), ROUND(Q108 / ROUND(SUM(Q107:Q109), 2) * R104, 2))) -> 0 | W108: Kasse | Y108: =IF(X108=0, 0, IF(ROUND(SUM(X109:X109), 2)=0, ROUND(Y104 - SUM(Y107:Y107), 2), ROUND(X108 / ROUND(SUM(X107:X109), 2) * Y104, 2))) -> 0 | AD108: Kasse | AF108: =IF(AE108=0, 0, IF(ROUND(SUM(AE109:AE109), 2)=0, ROUND(AF104 - SUM(AF107:AF107), 2), ROUND(AE108 / ROUND(SUM(AE107:AE109), 2) * AF104, 2))) -> 0 | AK108: Kasse | AM108: =IF(AL108=0, 0, IF(ROUND(SUM(AL109:AL109), 2)=0, ROUND(AM104 - SUM(AM107:AM107), 2), ROUND(AL108 / ROUND(SUM(AL107:AL109), 2) * AM104, 2))) -> 0 | AR108: Kasse | AT108: =IF(AS108=0, 0, IF(ROUND(SUM(AS109:AS109), 2)=0, ROUND(AT104 - SUM(AT107:AT107), 2), ROUND(AS108 / ROUND(SUM(AS107:AS109), 2) * AT104, 2))) -> 0 | AY108: Kasse | BA108: =IF(AZ108=0, 0, IF(ROUND(SUM(AZ109:AZ109), 2)=0, ROUND(BA104 - SUM(BA107:BA107), 2), ROUND(AZ108 / ROUND(SUM(AZ107:AZ109), 2) * BA104, 2))) -> 0 | BF108: Kasse | BH108: =IF(BG108=0, 0, IF(ROUND(SUM(BG109:BG109), 2)=0, ROUND(BH104 - SUM(BH107:BH107), 2), ROUND(BG108 / ROUND(SUM(BG107:BG109), 2) * BH104, 2))) -> 0 | BM108: Kasse | BO108: =IF(BN108=0, 0, IF(ROUND(SUM(BN109:BN109), 2)=0, ROUND(BO104 - SUM(BO107:BO107), 2), ROUND(BN108 / ROUND(SUM(BN107:BN109), 2) * BO104, 2))) -> 0 | BT108: Kasse | BV108: =IF(BU108=0, 0, IF(ROUND(SUM(BU109:BU109), 2)=0, ROUND(BV104 - SUM(BV107:BV107), 2), ROUND(BU108 / ROUND(SUM(BU107:BU109), 2) * BV104, 2))) -> 0 | CA108: Kasse | CC108: =IF(CB108=0, 0, IF(ROUND(SUM(CB109:CB109), 2)=0, ROUND(CC104 - SUM(CC107:CC107), 2), ROUND(CB108 / ROUND(SUM(CB107:CB109), 2) * CC104, 2))) -> 0 | CH108: Kasse | CJ108: =IF(CI108=0, 0, IF(ROUND(SUM(CI109:CI109), 2)=0, ROUND(CJ104 - SUM(CJ107:CJ107), 2), ROUND(CI108 / ROUND(SUM(CI107:CI109), 2) * CJ104, 2))) -> 0 | CO108: Kasse | CQ108: =IF(CP108=0, 0, IF(ROUND(SUM(CP109:CP109), 2)=0, ROUND(CQ104 - SUM(CQ107:CQ107), 2), ROUND(CP108 / ROUND(SUM(CP107:CP109), 2) * CQ104, 2))) -> 0 | CV108: Kasse | CX108: =IF(CW108=0, 0, IF(ROUND(SUM(CW109:CW109), 2)=0, ROUND(CX104 - SUM(CX107:CX107), 2), ROUND(CW108 / ROUND(SUM(CW107:CW109), 2) * CX104, 2))) -> 0 | DC108: Kasse | DE108: =IF(DD108=0, 0, IF(ROUND(SUM(DD109:DD109), 2)=0, ROUND(DE104 - SUM(DE107:DE107), 2), ROUND(DD108 / ROUND(SUM(DD107:DD109), 2) * DE104, 2))) -> 0 | DJ108: Kasse | DL108: =IF(DK108=0, 0, IF(ROUND(SUM(DK109:DK109), 2)=0, ROUND(DL104 - SUM(DL107:DL107), 2), ROUND(DK108 / ROUND(SUM(DK107:DK109), 2) * DL104, 2))) -> 0 | DQ108: Kasse | DS108: =IF(DR108=0, 0, IF(ROUND(SUM(DR109:DR109), 2)=0, ROUND(DS104 - SUM(DS107:DS107), 2), ROUND(DR108 / ROUND(SUM(DR107:DR109), 2) * DS104, 2))) -> 0
B109: Sonstiges | D109: =IF(C109=0, 0, ROUND(D104 - SUM(D107:D108), 2)) -> 0 | I109: Sonstiges | K109: =IF(J109=0, 0, ROUND(K104 - SUM(K107:K108), 2)) -> 0 | P109: Sonstiges | R109: =IF(Q109=0, 0, ROUND(R104 - SUM(R107:R108), 2)) -> 0 | W109: Sonstiges | Y109: =IF(X109=0, 0, ROUND(Y104 - SUM(Y107:Y108), 2)) -> 0 | AD109: Sonstiges | AF109: =IF(AE109=0, 0, ROUND(AF104 - SUM(AF107:AF108), 2)) -> 0 | AK109: Sonstiges | AM109: =IF(AL109=0, 0, ROUND(AM104 - SUM(AM107:AM108), 2)) -> 0 | AR109: Sonstiges | AT109: =IF(AS109=0, 0, ROUND(AT104 - SUM(AT107:AT108), 2)) -> 0 | AY109: Sonstiges | BA109: =IF(AZ109=0, 0, ROUND(BA104 - SUM(BA107:BA108), 2)) -> 0 | BF109: Sonstiges | BH109: =IF(BG109=0, 0, ROUND(BH104 - SUM(BH107:BH108), 2)) -> 0 | BM109: Sonstiges | BO109: =IF(BN109=0, 0, ROUND(BO104 - SUM(BO107:BO108), 2)) -> 0 | BT109: Sonstiges | BV109: =IF(BU109=0, 0, ROUND(BV104 - SUM(BV107:BV108), 2)) -> 0 | CA109: Sonstiges | CC109: =IF(CB109=0, 0, ROUND(CC104 - SUM(CC107:CC108), 2)) -> 0 | CH109: Sonstiges | CJ109: =IF(CI109=0, 0, ROUND(CJ104 - SUM(CJ107:CJ108), 2)) -> 0 | CO109: Sonstiges | CQ109: =IF(CP109=0, 0, ROUND(CQ104 - SUM(CQ107:CQ108), 2)) -> 0 | CV109: Sonstiges | CX109: =IF(CW109=0, 0, ROUND(CX104 - SUM(CX107:CX108), 2)) -> 0 | DC109: Sonstiges | DE109: =IF(DD109=0, 0, ROUND(DE104 - SUM(DE107:DE108), 2)) -> 0 | DJ109: Sonstiges | DL109: =IF(DK109=0, 0, ROUND(DL104 - SUM(DL107:DL108), 2)) -> 0 | DQ109: Sonstiges | DS109: =IF(DR109=0, 0, ROUND(DS104 - SUM(DS107:DS108), 2)) -> 0
B111: Differenz (Pruefung): | C111: =ROUND(IFERROR(C104-SUM(C107:C109),""),2) -> 0 | D111: =ROUND(IFERROR(D104-SUM(D107:D109),""),2) -> 0 | I111: Differenz (Pruefung): | J111: =ROUND(IFERROR(J104-SUM(J107:J109),""),2) -> 0 | K111: =ROUND(IFERROR(K104-SUM(K107:K109),""),2) -> 0 | P111: Differenz (Pruefung): | Q111: =ROUND(IFERROR(Q104-SUM(Q107:Q109),""),2) -> 0 | R111: =ROUND(IFERROR(R104-SUM(R107:R109),""),2) -> 0 | W111: Differenz (Pruefung): | X111: =ROUND(IFERROR(X104-SUM(X107:X109),""),2) -> 0 | Y111: =ROUND(IFERROR(Y104-SUM(Y107:Y109),""),2) -> 0 | AD111: Differenz (Pruefung): | AE111: =ROUND(IFERROR(AE104-SUM(AE107:AE109),""),2) -> 0 | AF111: =ROUND(IFERROR(AF104-SUM(AF107:AF109),""),2) -> 0 | AK111: Differenz (Pruefung): | AL111: =ROUND(IFERROR(AL104-SUM(AL107:AL109),""),2) -> 0 | AM111: =ROUND(IFERROR(AM104-SUM(AM107:AM109),""),2) -> 0 | AR111: Differenz (Pruefung): | AS111: =ROUND(IFERROR(AS104-SUM(AS107:AS109),""),2) -> 0 | AT111: =ROUND(IFERROR(AT104-SUM(AT107:AT109),""),2) -> 0 | AY111: Differenz (Pruefung): | AZ111: =ROUND(IFERROR(AZ104-SUM(AZ107:AZ109),""),2) -> 0 | BA111: =ROUND(IFERROR(BA104-SUM(BA107:BA109),""),2) -> 0 | BF111: Differenz (Pruefung): | BG111: =ROUND(IFERROR(BG104-SUM(BG107:BG109),""),2) -> 0 | BH111: =ROUND(IFERROR(BH104-SUM(BH107:BH109),""),2) -> 0 | BM111: Differenz (Pruefung): | BN111: =ROUND(IFERROR(BN104-SUM(BN107:BN109),""),2) -> 0 | BO111: =ROUND(IFERROR(BO104-SUM(BO107:BO109),""),2) -> 0 | BT111: Differenz (Pruefung): | BU111: =ROUND(IFERROR(BU104-SUM(BU107:BU109),""),2) -> 0 | BV111: =ROUND(IFERROR(BV104-SUM(BV107:BV109),""),2) -> 0 | CA111: Differenz (Pruefung): | CB111: =ROUND(IFERROR(CB104-SUM(CB107:CB109),""),2) -> 0 | CC111: =ROUND(IFERROR(CC104-SUM(CC107:CC109),""),2) -> 0 | CH111: Differenz (Pruefung): | CI111: =ROUND(IFERROR(CI104-SUM(CI107:CI109),""),2) -> 0 | CJ111: =ROUND(IFERROR(CJ104-SUM(CJ107:CJ109),""),2) -> 0 | CO111: Differenz (Pruefung): | CP111: =ROUND(IFERROR(CP104-SUM(CP107:CP109),""),2) -> 0 | CQ111: =ROUND(IFERROR(CQ104-SUM(CQ107:CQ109),""),2) -> 0 | CV111: Differenz (Pruefung): | CW111: =ROUND(IFERROR(CW104-SUM(CW107:CW109),""),2) -> 0 | CX111: =ROUND(IFERROR(CX104-SUM(CX107:CX109),""),2) -> 0 | DC111: Differenz (Pruefung): | DD111: =ROUND(IFERROR(DD104-SUM(DD107:DD109),""),2) -> 0 | DE111: =ROUND(IFERROR(DE104-SUM(DE107:DE109),""),2) -> 0 | DJ111: Differenz (Pruefung): | DK111: =ROUND(IFERROR(DK104-SUM(DK107:DK109),""),2) -> 0 | DL111: =ROUND(IFERROR(DL104-SUM(DL107:DL109),""),2) -> 0 | DQ111: Differenz (Pruefung): | DR111: =ROUND(IFERROR(DR104-SUM(DR107:DR109),""),2) -> 0 | DS111: =ROUND(IFERROR(DS104-SUM(DS107:DS109),""),2) -> 0
B114: Einnahmen (Explizite Kurseingabe) | I114: Einnahmen (Explizite Kurseingabe) | P114: Einnahmen (Explizite Kurseingabe) | W114: Einnahmen (Explizite Kurseingabe) | AD114: Einnahmen (Explizite Kurseingabe) | AK114: Einnahmen (Explizite Kurseingabe) | AR114: Einnahmen (Explizite Kurseingabe) | AY114: Einnahmen (Explizite Kurseingabe) | BF114: Einnahmen (Explizite Kurseingabe) | BM114: Einnahmen (Explizite Kurseingabe) | BT114: Einnahmen (Explizite Kurseingabe) | CA114: Einnahmen (Explizite Kurseingabe) | CH114: Einnahmen (Explizite Kurseingabe) | CO114: Einnahmen (Explizite Kurseingabe) | CV114: Einnahmen (Explizite Kurseingabe) | DC114: Einnahmen (Explizite Kurseingabe) | DJ114: Einnahmen (Explizite Kurseingabe) | DQ114: Einnahmen (Explizite Kurseingabe)
B115: Typ | C115: Geber | D115: Einnahmen (LC) | E115: Einnahmen (EUR) | F115: Kurs | I115: Typ | J115: Geber | K115: Einnahmen (LC) | L115: Einnahmen (EUR) | M115: Kurs | P115: Typ | Q115: Geber | R115: Einnahmen (LC) | S115: Einnahmen (EUR) | T115: Kurs | W115: Typ | X115: Geber | Y115: Einnahmen (LC) | Z115: Einnahmen (EUR) | AA115: Kurs | AD115: Typ | AE115: Geber | AF115: Einnahmen (LC) | AG115: Einnahmen (EUR) | AH115: Kurs | AK115: Typ | AL115: Geber | AM115: Einnahmen (LC) | AN115: Einnahmen (EUR) | AO115: Kurs | AR115: Typ | AS115: Geber | AT115: Einnahmen (LC) | AU115: Einnahmen (EUR) | AV115: Kurs | AY115: Typ | AZ115: Geber | BA115: Einnahmen (LC) | BB115: Einnahmen (EUR) | BC115: Kurs | BF115: Typ | BG115: Geber | BH115: Einnahmen (LC) | BI115: Einnahmen (EUR) | BJ115: Kurs | BM115: Typ | BN115: Geber | BO115: Einnahmen (LC) | BP115: Einnahmen (EUR) | BQ115: Kurs | BT115: Typ | BU115: Geber | BV115: Einnahmen (LC) | BW115: Einnahmen (EUR) | BX115: Kurs | CA115: Typ | CB115: Geber | CC115: Einnahmen (LC) | CD115: Einnahmen (EUR) | CE115: Kurs | CH115: Typ | CI115: Geber | CJ115: Einnahmen (LC) | CK115: Einnahmen (EUR) | CL115: Kurs | CO115: Typ | CP115: Geber | CQ115: Einnahmen (LC) | CR115: Einnahmen (EUR) | CS115: Kurs | CV115: Typ | CW115: Geber | CX115: Einnahmen (LC) | CY115: Einnahmen (EUR) | CZ115: Kurs | DC115: Typ | DD115: Geber | DE115: Einnahmen (LC) | DF115: Einnahmen (EUR) | DG115: Kurs | DJ115: Typ | DK115: Geber | DL115: Einnahmen (LC) | DM115: Einnahmen (EUR) | DN115: Kurs | DQ115: Typ | DR115: Geber | DS115: Einnahmen (LC) | DT115: Einnahmen (EUR) | DU115: Kurs
B116: Saldo des Vorprojekts | D116: =ROUND(C11,2) -> 0 | E116: =ROUND(D11,2) -> 0 | F116: =ROUND(IFERROR(D116/E116,0),6) -> 0 | I116: Saldo der Vorperiode | K116: =ROUND(J11,2) -> 0 | L116: =ROUND(K11,2) -> 0 | M116: =ROUND(IFERROR(K116/L116,0),6) -> 0 | P116: Saldo der Vorperiode | R116: =ROUND(Q11,2) -> 0 | S116: =ROUND(R11,2) -> 0 | T116: =ROUND(IFERROR(R116/S116,0),6) -> 0 | W116: Saldo der Vorperiode | Y116: =ROUND(X11,2) -> 0 | Z116: =ROUND(Y11,2) -> 0 | AA116: =ROUND(IFERROR(Y116/Z116,0),6) -> 0 | AD116: Saldo der Vorperiode | AF116: =ROUND(AE11,2) -> 0 | AG116: =ROUND(AF11,2) -> 0 | AH116: =ROUND(IFERROR(AF116/AG116,0),6) -> 0 | AK116: Saldo der Vorperiode | AM116: =ROUND(AL11,2) -> 0 | AN116: =ROUND(AM11,2) -> 0 | AO116: =ROUND(IFERROR(AM116/AN116,0),6) -> 0 | AR116: Saldo der Vorperiode | AT116: =ROUND(AS11,2) -> 0 | AU116: =ROUND(AT11,2) -> 0 | AV116: =ROUND(IFERROR(AT116/AU116,0),6) -> 0 | AY116: Saldo der Vorperiode | BA116: =ROUND(AZ11,2) -> 0 | BB116: =ROUND(BA11,2) -> 0 | BC116: =ROUND(IFERROR(BA116/BB116,0),6) -> 0 | BF116: Saldo der Vorperiode | BH116: =ROUND(BG11,2) -> 0 | BI116: =ROUND(BH11,2) -> 0 | BJ116: =ROUND(IFERROR(BH116/BI116,0),6) -> 0 | BM116: Saldo der Vorperiode | BO116: =ROUND(BN11,2) -> 0 | BP116: =ROUND(BO11,2) -> 0 | BQ116: =ROUND(IFERROR(BO116/BP116,0),6) -> 0 | BT116: Saldo der Vorperiode | BV116: =ROUND(BU11,2) -> 0 | BW116: =ROUND(BV11,2) -> 0 | BX116: =ROUND(IFERROR(BV116/BW116,0),6) -> 0 | CA116: Saldo der Vorperiode | CC116: =ROUND(CB11,2) -> 0 | CD116: =ROUND(CC11,2) -> 0 | CE116: =ROUND(IFERROR(CC116/CD116,0),6) -> 0 | CH116: Saldo der Vorperiode | CJ116: =ROUND(CI11,2) -> 0 | CK116: =ROUND(CJ11,2) -> 0 | CL116: =ROUND(IFERROR(CJ116/CK116,0),6) -> 0 | CO116: Saldo der Vorperiode | CQ116: =ROUND(CP11,2) -> 0 | CR116: =ROUND(CQ11,2) -> 0 | CS116: =ROUND(IFERROR(CQ116/CR116,0),6) -> 0 | CV116: Saldo der Vorperiode | CX116: =ROUND(CW11,2) -> 0 | CY116: =ROUND(CX11,2) -> 0 | CZ116: =ROUND(IFERROR(CX116/CY116,0),6) -> 0 | DC116: Saldo der Vorperiode | DE116: =ROUND(DD11,2) -> 0 | DF116: =ROUND(DE11,2) -> 0 | DG116: =ROUND(IFERROR(DE116/DF116,0),6) -> 0 | DJ116: Saldo der Vorperiode | DL116: =ROUND(DK11,2) -> 0 | DM116: =ROUND(DL11,2) -> 0 | DN116: =ROUND(IFERROR(DL116/DM116,0),6) -> 0 | DQ116: Saldo der Vorperiode | DS116: =ROUND(DR11,2) -> 0 | DT116: =ROUND(DS11,2) -> 0 | DU116: =ROUND(IFERROR(DS116/DT116,0),6) -> 0
B117: KMW-Mittel | F117: =ROUND(IFERROR(D117/E117,0),6) -> 0 | I117: KMW-Mittel | M117: =ROUND(IFERROR(K117/L117,0),6) -> 0 | P117: KMW-Mittel | T117: =ROUND(IFERROR(R117/S117,0),6) -> 0 | W117: KMW-Mittel | AA117: =ROUND(IFERROR(Y117/Z117,0),6) -> 0 | AD117: KMW-Mittel | AH117: =ROUND(IFERROR(AF117/AG117,0),6) -> 0 | AK117: KMW-Mittel | AO117: =ROUND(IFERROR(AM117/AN117,0),6) -> 0 | AR117: KMW-Mittel | AV117: =ROUND(IFERROR(AT117/AU117,0),6) -> 0 | AY117: KMW-Mittel | BC117: =ROUND(IFERROR(BA117/BB117,0),6) -> 0 | BF117: KMW-Mittel | BJ117: =ROUND(IFERROR(BH117/BI117,0),6) -> 0 | BM117: KMW-Mittel | BQ117: =ROUND(IFERROR(BO117/BP117,0),6) -> 0 | BT117: KMW-Mittel | BX117: =ROUND(IFERROR(BV117/BW117,0),6) -> 0 | CA117: KMW-Mittel | CE117: =ROUND(IFERROR(CC117/CD117,0),6) -> 0 | CH117: KMW-Mittel | CL117: =ROUND(IFERROR(CJ117/CK117,0),6) -> 0 | CO117: KMW-Mittel | CS117: =ROUND(IFERROR(CQ117/CR117,0),6) -> 0 | CV117: KMW-Mittel | CZ117: =ROUND(IFERROR(CX117/CY117,0),6) -> 0 | DC117: KMW-Mittel | DG117: =ROUND(IFERROR(DE117/DF117,0),6) -> 0 | DJ117: KMW-Mittel | DN117: =ROUND(IFERROR(DL117/DM117,0),6) -> 0 | DQ117: KMW-Mittel | DU117: =ROUND(IFERROR(DS117/DT117,0),6) -> 0
F118: =ROUND(IFERROR(D118/E118,0),6) -> 0 | M118: =ROUND(IFERROR(K118/L118,0),6) -> 0 | T118: =ROUND(IFERROR(R118/S118,0),6) -> 0 | AA118: =ROUND(IFERROR(Y118/Z118,0),6) -> 0 | AH118: =ROUND(IFERROR(AF118/AG118,0),6) -> 0 | AO118: =ROUND(IFERROR(AM118/AN118,0),6) -> 0 | AV118: =ROUND(IFERROR(AT118/AU118,0),6) -> 0 | BC118: =ROUND(IFERROR(BA118/BB118,0),6) -> 0 | BJ118: =ROUND(IFERROR(BH118/BI118,0),6) -> 0 | BQ118: =ROUND(IFERROR(BO118/BP118,0),6) -> 0 | BX118: =ROUND(IFERROR(BV118/BW118,0),6) -> 0 | CE118: =ROUND(IFERROR(CC118/CD118,0),6) -> 0 | CL118: =ROUND(IFERROR(CJ118/CK118,0),6) -> 0 | CS118: =ROUND(IFERROR(CQ118/CR118,0),6) -> 0 | CZ118: =ROUND(IFERROR(CX118/CY118,0),6) -> 0 | DG118: =ROUND(IFERROR(DE118/DF118,0),6) -> 0 | DN118: =ROUND(IFERROR(DL118/DM118,0),6) -> 0 | DU118: =ROUND(IFERROR(DS118/DT118,0),6) -> 0
F119: =ROUND(IFERROR(D119/E119,0),6) -> 0 | M119: =ROUND(IFERROR(K119/L119,0),6) -> 0 | T119: =ROUND(IFERROR(R119/S119,0),6) -> 0 | AA119: =ROUND(IFERROR(Y119/Z119,0),6) -> 0 | AH119: =ROUND(IFERROR(AF119/AG119,0),6) -> 0 | AO119: =ROUND(IFERROR(AM119/AN119,0),6) -> 0 | AV119: =ROUND(IFERROR(AT119/AU119,0),6) -> 0 | BC119: =ROUND(IFERROR(BA119/BB119,0),6) -> 0 | BJ119: =ROUND(IFERROR(BH119/BI119,0),6) -> 0 | BQ119: =ROUND(IFERROR(BO119/BP119,0),6) -> 0 | BX119: =ROUND(IFERROR(BV119/BW119,0),6) -> 0 | CE119: =ROUND(IFERROR(CC119/CD119,0),6) -> 0 | CL119: =ROUND(IFERROR(CJ119/CK119,0),6) -> 0 | CS119: =ROUND(IFERROR(CQ119/CR119,0),6) -> 0 | CZ119: =ROUND(IFERROR(CX119/CY119,0),6) -> 0 | DG119: =ROUND(IFERROR(DE119/DF119,0),6) -> 0 | DN119: =ROUND(IFERROR(DL119/DM119,0),6) -> 0 | DU119: =ROUND(IFERROR(DS119/DT119,0),6) -> 0
F120: =ROUND(IFERROR(D120/E120,0),6) -> 0 | M120: =ROUND(IFERROR(K120/L120,0),6) -> 0 | T120: =ROUND(IFERROR(R120/S120,0),6) -> 0 | AA120: =ROUND(IFERROR(Y120/Z120,0),6) -> 0 | AH120: =ROUND(IFERROR(AF120/AG120,0),6) -> 0 | AO120: =ROUND(IFERROR(AM120/AN120,0),6) -> 0 | AV120: =ROUND(IFERROR(AT120/AU120,0),6) -> 0 | BC120: =ROUND(IFERROR(BA120/BB120,0),6) -> 0 | BJ120: =ROUND(IFERROR(BH120/BI120,0),6) -> 0 | BQ120: =ROUND(IFERROR(BO120/BP120,0),6) -> 0 | BX120: =ROUND(IFERROR(BV120/BW120,0),6) -> 0 | CE120: =ROUND(IFERROR(CC120/CD120,0),6) -> 0 | CL120: =ROUND(IFERROR(CJ120/CK120,0),6) -> 0 | CS120: =ROUND(IFERROR(CQ120/CR120,0),6) -> 0 | CZ120: =ROUND(IFERROR(CX120/CY120,0),6) -> 0 | DG120: =ROUND(IFERROR(DE120/DF120,0),6) -> 0 | DN120: =ROUND(IFERROR(DL120/DM120,0),6) -> 0 | DU120: =ROUND(IFERROR(DS120/DT120,0),6) -> 0
B121: Gesamteinnahmen in Periode | C121: Durchschnittskurs: | D121: =ROUND(SUBTOTAL(109,$D$116:$D$120),2) -> 0 | E121: =ROUND(SUBTOTAL(109,$E$116:$E$120),2) -> 0 | F121: =ROUND(IFERROR(D121/E121,0),6) -> 0 | I121: Gesamteinnahmen in Periode | J121: Durchschnittskurs: | K121: =ROUND(SUBTOTAL(109,$K$116:$K$120),2) -> 0 | L121: =ROUND(SUBTOTAL(109,$L$116:$L$120),2) -> 0 | M121: =ROUND(IFERROR(K121/L121,0),6) -> 0 | P121: Gesamteinnahmen in Periode | Q121: Durchschnittskurs: | R121: =ROUND(SUBTOTAL(109,$R$116:$R$120),2) -> 0 | S121: =ROUND(SUBTOTAL(109,$S$116:$S$120),2) -> 0 | T121: =ROUND(IFERROR(R121/S121,0),6) -> 0 | W121: Gesamteinnahmen in Periode | X121: Durchschnittskurs: | Y121: =ROUND(SUBTOTAL(109,$Y$116:$Y$120),2) -> 0 | Z121: =ROUND(SUBTOTAL(109,$Z$116:$Z$120),2) -> 0 | AA121: =ROUND(IFERROR(Y121/Z121,0),6) -> 0 | AD121: Gesamteinnahmen in Periode | AE121: Durchschnittskurs: | AF121: =ROUND(SUBTOTAL(109,$AF$116:$AF$120),2) -> 0 | AG121: =ROUND(SUBTOTAL(109,$AG$116:$AG$120),2) -> 0 | AH121: =ROUND(IFERROR(AF121/AG121,0),6) -> 0 | AK121: Gesamteinnahmen in Periode | AL121: Durchschnittskurs: | AM121: =ROUND(SUBTOTAL(109,$AM$116:$AM$120),2) -> 0 | AN121: =ROUND(SUBTOTAL(109,$AN$116:$AN$120),2) -> 0 | AO121: =ROUND(IFERROR(AM121/AN121,0),6) -> 0 | AR121: Gesamteinnahmen in Periode | AS121: Durchschnittskurs: | AT121: =ROUND(SUBTOTAL(109,$AT$116:$AT$120),2) -> 0 | AU121: =ROUND(SUBTOTAL(109,$AU$116:$AU$120),2) -> 0 | AV121: =ROUND(IFERROR(AT121/AU121,0),6) -> 0 | AY121: Gesamteinnahmen in Periode | AZ121: Durchschnittskurs: | BA121: =ROUND(SUBTOTAL(109,$BA$116:$BA$120),2) -> 0 | BB121: =ROUND(SUBTOTAL(109,$BB$116:$BB$120),2) -> 0 | BC121: =ROUND(IFERROR(BA121/BB121,0),6) -> 0 | BF121: Gesamteinnahmen in Periode | BG121: Durchschnittskurs: | BH121: =ROUND(SUBTOTAL(109,$BH$116:$BH$120),2) -> 0 | BI121: =ROUND(SUBTOTAL(109,$BI$116:$BI$120),2) -> 0 | BJ121: =ROUND(IFERROR(BH121/BI121,0),6) -> 0 | BM121: Gesamteinnahmen in Periode | BN121: Durchschnittskurs: | BO121: =ROUND(SUBTOTAL(109,$BO$116:$BO$120),2) -> 0 | BP121: =ROUND(SUBTOTAL(109,$BP$116:$BP$120),2) -> 0 | BQ121: =ROUND(IFERROR(BO121/BP121,0),6) -> 0 | BT121: Gesamteinnahmen in Periode | BU121: Durchschnittskurs: | BV121: =ROUND(SUBTOTAL(109,$BV$116:$BV$120),2) -> 0 | BW121: =ROUND(SUBTOTAL(109,$BW$116:$BW$120),2) -> 0 | BX121: =ROUND(IFERROR(BV121/BW121,0),6) -> 0 | CA121: Gesamteinnahmen in Periode | CB121: Durchschnittskurs: | CC121: =ROUND(SUBTOTAL(109,$CC$116:$CC$120),2) -> 0 | CD121: =ROUND(SUBTOTAL(109,$CD$116:$CD$120),2) -> 0 | CE121: =ROUND(IFERROR(CC121/CD121,0),6) -> 0 | CH121: Gesamteinnahmen in Periode | CI121: Durchschnittskurs: | CJ121: =ROUND(SUBTOTAL(109,$CJ$116:$CJ$120),2) -> 0 | CK121: =ROUND(SUBTOTAL(109,$CK$116:$CK$120),2) -> 0 | CL121: =ROUND(IFERROR(CJ121/CK121,0),6) -> 0 | CO121: Gesamteinnahmen in Periode | CP121: Durchschnittskurs: | CQ121: =ROUND(SUBTOTAL(109,$CQ$116:$CQ$120),2) -> 0 | CR121: =ROUND(SUBTOTAL(109,$CR$116:$CR$120),2) -> 0 | CS121: =ROUND(IFERROR(CQ121/CR121,0),6) -> 0 | CV121: Gesamteinnahmen in Periode | CW121: Durchschnittskurs: | CX121: =ROUND(SUBTOTAL(109,$CX$116:$CX$120),2) -> 0 | CY121: =ROUND(SUBTOTAL(109,$CY$116:$CY$120),2) -> 0 | CZ121: =ROUND(IFERROR(CX121/CY121,0),6) -> 0 | DC121: Gesamteinnahmen in Periode | DD121: Durchschnittskurs: | DE121: =ROUND(SUBTOTAL(109,$DE$116:$DE$120),2) -> 0 | DF121: =ROUND(SUBTOTAL(109,$DF$116:$DF$120),2) -> 0 | DG121: =ROUND(IFERROR(DE121/DF121,0),6) -> 0 | DJ121: Gesamteinnahmen in Periode | DK121: Durchschnittskurs: | DL121: =ROUND(SUBTOTAL(109,$DL$116:$DL$120),2) -> 0 | DM121: =ROUND(SUBTOTAL(109,$DM$116:$DM$120),2) -> 0 | DN121: =ROUND(IFERROR(DL121/DM121,0),6) -> 0 | DQ121: Gesamteinnahmen in Periode | DR121: Durchschnittskurs: | DS121: =ROUND(SUBTOTAL(109,$DS$116:$DS$120),2) -> 0 | DT121: =ROUND(SUBTOTAL(109,$DT$116:$DT$120),2) -> 0 | DU121: =ROUND(IFERROR(DS121/DT121,0),6) -> 0
B123: Einnahmen (Durchschnittskurs) | I123: Einnahmen (Durchschnittskurs) | P123: Einnahmen (Durchschnittskurs) | W123: Einnahmen (Durchschnittskurs) | AD123: Einnahmen (Durchschnittskurs) | AK123: Einnahmen (Durchschnittskurs) | AR123: Einnahmen (Durchschnittskurs) | AY123: Einnahmen (Durchschnittskurs) | BF123: Einnahmen (Durchschnittskurs) | BM123: Einnahmen (Durchschnittskurs) | BT123: Einnahmen (Durchschnittskurs) | CA123: Einnahmen (Durchschnittskurs) | CH123: Einnahmen (Durchschnittskurs) | CO123: Einnahmen (Durchschnittskurs) | CV123: Einnahmen (Durchschnittskurs) | DC123: Einnahmen (Durchschnittskurs) | DJ123: Einnahmen (Durchschnittskurs) | DQ123: Einnahmen (Durchschnittskurs)
B124: Typ | C124: Geber | D124: Einnahmen (LC) | E124: Einnahmen (EUR) | F124: Kurs | I124: Typ | J124: Geber | K124: Einnahmen (LC) | L124: Einnahmen (EUR) | M124: Kurs | P124: Typ | Q124: Geber | R124: Einnahmen (LC) | S124: Einnahmen (EUR) | T124: Kurs | W124: Typ | X124: Geber | Y124: Einnahmen (LC) | Z124: Einnahmen (EUR) | AA124: Kurs | AD124: Typ | AE124: Geber | AF124: Einnahmen (LC) | AG124: Einnahmen (EUR) | AH124: Kurs | AK124: Typ | AL124: Geber | AM124: Einnahmen (LC) | AN124: Einnahmen (EUR) | AO124: Kurs | AR124: Typ | AS124: Geber | AT124: Einnahmen (LC) | AU124: Einnahmen (EUR) | AV124: Kurs | AY124: Typ | AZ124: Geber | BA124: Einnahmen (LC) | BB124: Einnahmen (EUR) | BC124: Kurs | BF124: Typ | BG124: Geber | BH124: Einnahmen (LC) | BI124: Einnahmen (EUR) | BJ124: Kurs | BM124: Typ | BN124: Geber | BO124: Einnahmen (LC) | BP124: Einnahmen (EUR) | BQ124: Kurs | BT124: Typ | BU124: Geber | BV124: Einnahmen (LC) | BW124: Einnahmen (EUR) | BX124: Kurs | CA124: Typ | CB124: Geber | CC124: Einnahmen (LC) | CD124: Einnahmen (EUR) | CE124: Kurs | CH124: Typ | CI124: Geber | CJ124: Einnahmen (LC) | CK124: Einnahmen (EUR) | CL124: Kurs | CO124: Typ | CP124: Geber | CQ124: Einnahmen (LC) | CR124: Einnahmen (EUR) | CS124: Kurs | CV124: Typ | CW124: Geber | CX124: Einnahmen (LC) | CY124: Einnahmen (EUR) | CZ124: Kurs | DC124: Typ | DD124: Geber | DE124: Einnahmen (LC) | DF124: Einnahmen (EUR) | DG124: Kurs | DJ124: Typ | DK124: Geber | DL124: Einnahmen (LC) | DM124: Einnahmen (EUR) | DN124: Kurs | DQ124: Typ | DR124: Geber | DS124: Einnahmen (LC) | DT124: Einnahmen (EUR) | DU124: Kurs
B125: Eigenmittel | E125: =IFERROR(ROUND(D125/$C$8,2),0) -> 0 | F125: =ROUND(IFERROR(D125/E125,0),6) -> 0 | I125: Eigenmittel | L125: =IFERROR(ROUND(K125/$J$8,2),0) -> 0 | M125: =ROUND(IFERROR(K125/L125,0),6) -> 0 | P125: Eigenmittel | S125: =IFERROR(ROUND(R125/$Q$8,2),0) -> 0 | T125: =ROUND(IFERROR(R125/S125,0),6) -> 0 | W125: Eigenmittel | Z125: =IFERROR(ROUND(Y125/$X$8,2),0) -> 0 | AA125: =ROUND(IFERROR(Y125/Z125,0),6) -> 0 | AD125: Eigenmittel | AG125: =IFERROR(ROUND(AF125/$AE$8,2),0) -> 0 | AH125: =ROUND(IFERROR(AF125/AG125,0),6) -> 0 | AK125: Eigenmittel | AN125: =IFERROR(ROUND(AM125/$AL$8,2),0) -> 0 | AO125: =ROUND(IFERROR(AM125/AN125,0),6) -> 0 | AR125: Eigenmittel | AU125: =IFERROR(ROUND(AT125/$AS$8,2),0) -> 0 | AV125: =ROUND(IFERROR(AT125/AU125,0),6) -> 0 | AY125: Eigenmittel | BB125: =IFERROR(ROUND(BA125/$AZ$8,2),0) -> 0 | BC125: =ROUND(IFERROR(BA125/BB125,0),6) -> 0 | BF125: Eigenmittel | BI125: =IFERROR(ROUND(BH125/$BG$8,2),0) -> 0 | BJ125: =ROUND(IFERROR(BH125/BI125,0),6) -> 0 | BM125: Eigenmittel | BP125: =IFERROR(ROUND(BO125/$BN$8,2),0) -> 0 | BQ125: =ROUND(IFERROR(BO125/BP125,0),6) -> 0 | BT125: Eigenmittel | BW125: =IFERROR(ROUND(BV125/$BU$8,2),0) -> 0 | BX125: =ROUND(IFERROR(BV125/BW125,0),6) -> 0 | CA125: Eigenmittel | CD125: =IFERROR(ROUND(CC125/$CB$8,2),0) -> 0 | CE125: =ROUND(IFERROR(CC125/CD125,0),6) -> 0 | CH125: Eigenmittel | CK125: =IFERROR(ROUND(CJ125/$CI$8,2),0) -> 0 | CL125: =ROUND(IFERROR(CJ125/CK125,0),6) -> 0 | CO125: Eigenmittel | CR125: =IFERROR(ROUND(CQ125/$CP$8,2),0) -> 0 | CS125: =ROUND(IFERROR(CQ125/CR125,0),6) -> 0 | CV125: Eigenmittel | CY125: =IFERROR(ROUND(CX125/$CW$8,2),0) -> 0 | CZ125: =ROUND(IFERROR(CX125/CY125,0),6) -> 0 | DC125: Eigenmittel | DF125: =IFERROR(ROUND(DE125/$DD$8,2),0) -> 0 | DG125: =ROUND(IFERROR(DE125/DF125,0),6) -> 0 | DJ125: Eigenmittel | DM125: =IFERROR(ROUND(DL125/$DK$8,2),0) -> 0 | DN125: =ROUND(IFERROR(DL125/DM125,0),6) -> 0 | DQ125: Eigenmittel | DT125: =IFERROR(ROUND(DS125/$DR$8,2),0) -> 0 | DU125: =ROUND(IFERROR(DS125/DT125,0),6) -> 0
B126: Drittmittel | E126: =IFERROR(ROUND(D126/$C$8,2),0) -> 0 | F126: =ROUND(IFERROR(D126/E126,0),6) -> 0 | I126: Drittmittel | L126: =IFERROR(ROUND(K126/$J$8,2),0) -> 0 | M126: =ROUND(IFERROR(K126/L126,0),6) -> 0 | P126: Drittmittel | S126: =IFERROR(ROUND(R126/$Q$8,2),0) -> 0 | T126: =ROUND(IFERROR(R126/S126,0),6) -> 0 | W126: Drittmittel | Z126: =IFERROR(ROUND(Y126/$X$8,2),0) -> 0 | AA126: =ROUND(IFERROR(Y126/Z126,0),6) -> 0 | AD126: Drittmittel | AG126: =IFERROR(ROUND(AF126/$AE$8,2),0) -> 0 | AH126: =ROUND(IFERROR(AF126/AG126,0),6) -> 0 | AK126: Drittmittel | AN126: =IFERROR(ROUND(AM126/$AL$8,2),0) -> 0 | AO126: =ROUND(IFERROR(AM126/AN126,0),6) -> 0 | AR126: Drittmittel | AU126: =IFERROR(ROUND(AT126/$AS$8,2),0) -> 0 | AV126: =ROUND(IFERROR(AT126/AU126,0),6) -> 0 | AY126: Drittmittel | BB126: =IFERROR(ROUND(BA126/$AZ$8,2),0) -> 0 | BC126: =ROUND(IFERROR(BA126/BB126,0),6) -> 0 | BF126: Drittmittel | BI126: =IFERROR(ROUND(BH126/$BG$8,2),0) -> 0 | BJ126: =ROUND(IFERROR(BH126/BI126,0),6) -> 0 | BM126: Drittmittel | BP126: =IFERROR(ROUND(BO126/$BN$8,2),0) -> 0 | BQ126: =ROUND(IFERROR(BO126/BP126,0),6) -> 0 | BT126: Drittmittel | BW126: =IFERROR(ROUND(BV126/$BU$8,2),0) -> 0 | BX126: =ROUND(IFERROR(BV126/BW126,0),6) -> 0 | CA126: Drittmittel | CD126: =IFERROR(ROUND(CC126/$CB$8,2),0) -> 0 | CE126: =ROUND(IFERROR(CC126/CD126,0),6) -> 0 | CH126: Drittmittel | CK126: =IFERROR(ROUND(CJ126/$CI$8,2),0) -> 0 | CL126: =ROUND(IFERROR(CJ126/CK126,0),6) -> 0 | CO126: Drittmittel | CR126: =IFERROR(ROUND(CQ126/$CP$8,2),0) -> 0 | CS126: =ROUND(IFERROR(CQ126/CR126,0),6) -> 0 | CV126: Drittmittel | CY126: =IFERROR(ROUND(CX126/$CW$8,2),0) -> 0 | CZ126: =ROUND(IFERROR(CX126/CY126,0),6) -> 0 | DC126: Drittmittel | DF126: =IFERROR(ROUND(DE126/$DD$8,2),0) -> 0 | DG126: =ROUND(IFERROR(DE126/DF126,0),6) -> 0 | DJ126: Drittmittel | DM126: =IFERROR(ROUND(DL126/$DK$8,2),0) -> 0 | DN126: =ROUND(IFERROR(DL126/DM126,0),6) -> 0 | DQ126: Drittmittel | DT126: =IFERROR(ROUND(DS126/$DR$8,2),0) -> 0 | DU126: =ROUND(IFERROR(DS126/DT126,0),6) -> 0
B127: Zinsertraege | E127: =IFERROR(ROUND(D127/$C$8,2),0) -> 0 | F127: =ROUND(IFERROR(D127/E127,0),6) -> 0 | I127: Zinsertraege | L127: =IFERROR(ROUND(K127/$J$8,2),0) -> 0 | M127: =ROUND(IFERROR(K127/L127,0),6) -> 0 | P127: Zinsertraege | S127: =IFERROR(ROUND(R127/$Q$8,2),0) -> 0 | T127: =ROUND(IFERROR(R127/S127,0),6) -> 0 | W127: Zinsertraege | Z127: =IFERROR(ROUND(Y127/$X$8,2),0) -> 0 | AA127: =ROUND(IFERROR(Y127/Z127,0),6) -> 0 | AD127: Zinsertraege | AG127: =IFERROR(ROUND(AF127/$AE$8,2),0) -> 0 | AH127: =ROUND(IFERROR(AF127/AG127,0),6) -> 0 | AK127: Zinsertraege | AN127: =IFERROR(ROUND(AM127/$AL$8,2),0) -> 0 | AO127: =ROUND(IFERROR(AM127/AN127,0),6) -> 0 | AR127: Zinsertraege | AU127: =IFERROR(ROUND(AT127/$AS$8,2),0) -> 0 | AV127: =ROUND(IFERROR(AT127/AU127,0),6) -> 0 | AY127: Zinsertraege | BB127: =IFERROR(ROUND(BA127/$AZ$8,2),0) -> 0 | BC127: =ROUND(IFERROR(BA127/BB127,0),6) -> 0 | BF127: Zinsertraege | BI127: =IFERROR(ROUND(BH127/$BG$8,2),0) -> 0 | BJ127: =ROUND(IFERROR(BH127/BI127,0),6) -> 0 | BM127: Zinsertraege | BP127: =IFERROR(ROUND(BO127/$BN$8,2),0) -> 0 | BQ127: =ROUND(IFERROR(BO127/BP127,0),6) -> 0 | BT127: Zinsertraege | BW127: =IFERROR(ROUND(BV127/$BU$8,2),0) -> 0 | BX127: =ROUND(IFERROR(BV127/BW127,0),6) -> 0 | CA127: Zinsertraege | CD127: =IFERROR(ROUND(CC127/$CB$8,2),0) -> 0 | CE127: =ROUND(IFERROR(CC127/CD127,0),6) -> 0 | CH127: Zinsertraege | CK127: =IFERROR(ROUND(CJ127/$CI$8,2),0) -> 0 | CL127: =ROUND(IFERROR(CJ127/CK127,0),6) -> 0 | CO127: Zinsertraege | CR127: =IFERROR(ROUND(CQ127/$CP$8,2),0) -> 0 | CS127: =ROUND(IFERROR(CQ127/CR127,0),6) -> 0 | CV127: Zinsertraege | CY127: =IFERROR(ROUND(CX127/$CW$8,2),0) -> 0 | CZ127: =ROUND(IFERROR(CX127/CY127,0),6) -> 0 | DC127: Zinsertraege | DF127: =IFERROR(ROUND(DE127/$DD$8,2),0) -> 0 | DG127: =ROUND(IFERROR(DE127/DF127,0),6) -> 0 | DJ127: Zinsertraege | DM127: =IFERROR(ROUND(DL127/$DK$8,2),0) -> 0 | DN127: =ROUND(IFERROR(DL127/DM127,0),6) -> 0 | DQ127: Zinsertraege | DT127: =IFERROR(ROUND(DS127/$DR$8,2),0) -> 0 | DU127: =ROUND(IFERROR(DS127/DT127,0),6) -> 0
E128: =IFERROR(ROUND(D128/$C$8,2),0) -> 0 | F128: =ROUND(IFERROR(D128/E128,0),6) -> 0 | L128: =IFERROR(ROUND(K128/$J$8,2),0) -> 0 | M128: =ROUND(IFERROR(K128/L128,0),6) -> 0 | S128: =IFERROR(ROUND(R128/$Q$8,2),0) -> 0 | T128: =ROUND(IFERROR(R128/S128,0),6) -> 0 | Z128: =IFERROR(ROUND(Y128/$X$8,2),0) -> 0 | AA128: =ROUND(IFERROR(Y128/Z128,0),6) -> 0 | AG128: =IFERROR(ROUND(AF128/$AE$8,2),0) -> 0 | AH128: =ROUND(IFERROR(AF128/AG128,0),6) -> 0 | AN128: =IFERROR(ROUND(AM128/$AL$8,2),0) -> 0 | AO128: =ROUND(IFERROR(AM128/AN128,0),6) -> 0 | AU128: =IFERROR(ROUND(AT128/$AS$8,2),0) -> 0 | AV128: =ROUND(IFERROR(AT128/AU128,0),6) -> 0 | BB128: =IFERROR(ROUND(BA128/$AZ$8,2),0) -> 0 | BC128: =ROUND(IFERROR(BA128/BB128,0),6) -> 0 | BI128: =IFERROR(ROUND(BH128/$BG$8,2),0) -> 0 | BJ128: =ROUND(IFERROR(BH128/BI128,0),6) -> 0 | BP128: =IFERROR(ROUND(BO128/$BN$8,2),0) -> 0 | BQ128: =ROUND(IFERROR(BO128/BP128,0),6) -> 0 | BW128: =IFERROR(ROUND(BV128/$BU$8,2),0) -> 0 | BX128: =ROUND(IFERROR(BV128/BW128,0),6) -> 0 | CD128: =IFERROR(ROUND(CC128/$CB$8,2),0) -> 0 | CE128: =ROUND(IFERROR(CC128/CD128,0),6) -> 0 | CK128: =IFERROR(ROUND(CJ128/$CI$8,2),0) -> 0 | CL128: =ROUND(IFERROR(CJ128/CK128,0),6) -> 0 | CR128: =IFERROR(ROUND(CQ128/$CP$8,2),0) -> 0 | CS128: =ROUND(IFERROR(CQ128/CR128,0),6) -> 0 | CY128: =IFERROR(ROUND(CX128/$CW$8,2),0) -> 0 | CZ128: =ROUND(IFERROR(CX128/CY128,0),6) -> 0 | DF128: =IFERROR(ROUND(DE128/$DD$8,2),0) -> 0 | DG128: =ROUND(IFERROR(DE128/DF128,0),6) -> 0 | DM128: =IFERROR(ROUND(DL128/$DK$8,2),0) -> 0 | DN128: =ROUND(IFERROR(DL128/DM128,0),6) -> 0 | DT128: =IFERROR(ROUND(DS128/$DR$8,2),0) -> 0 | DU128: =ROUND(IFERROR(DS128/DT128,0),6) -> 0
E129: =IFERROR(ROUND(D129/$C$8,2),0) -> 0 | F129: =ROUND(IFERROR(D129/E129,0),6) -> 0 | L129: =IFERROR(ROUND(K129/$J$8,2),0) -> 0 | M129: =ROUND(IFERROR(K129/L129,0),6) -> 0 | S129: =IFERROR(ROUND(R129/$Q$8,2),0) -> 0 | T129: =ROUND(IFERROR(R129/S129,0),6) -> 0 | Z129: =IFERROR(ROUND(Y129/$X$8,2),0) -> 0 | AA129: =ROUND(IFERROR(Y129/Z129,0),6) -> 0 | AG129: =IFERROR(ROUND(AF129/$AE$8,2),0) -> 0 | AH129: =ROUND(IFERROR(AF129/AG129,0),6) -> 0 | AN129: =IFERROR(ROUND(AM129/$AL$8,2),0) -> 0 | AO129: =ROUND(IFERROR(AM129/AN129,0),6) -> 0 | AU129: =IFERROR(ROUND(AT129/$AS$8,2),0) -> 0 | AV129: =ROUND(IFERROR(AT129/AU129,0),6) -> 0 | BB129: =IFERROR(ROUND(BA129/$AZ$8,2),0) -> 0 | BC129: =ROUND(IFERROR(BA129/BB129,0),6) -> 0 | BI129: =IFERROR(ROUND(BH129/$BG$8,2),0) -> 0 | BJ129: =ROUND(IFERROR(BH129/BI129,0),6) -> 0 | BP129: =IFERROR(ROUND(BO129/$BN$8,2),0) -> 0 | BQ129: =ROUND(IFERROR(BO129/BP129,0),6) -> 0 | BW129: =IFERROR(ROUND(BV129/$BU$8,2),0) -> 0 | BX129: =ROUND(IFERROR(BV129/BW129,0),6) -> 0 | CD129: =IFERROR(ROUND(CC129/$CB$8,2),0) -> 0 | CE129: =ROUND(IFERROR(CC129/CD129,0),6) -> 0 | CK129: =IFERROR(ROUND(CJ129/$CI$8,2),0) -> 0 | CL129: =ROUND(IFERROR(CJ129/CK129,0),6) -> 0 | CR129: =IFERROR(ROUND(CQ129/$CP$8,2),0) -> 0 | CS129: =ROUND(IFERROR(CQ129/CR129,0),6) -> 0 | CY129: =IFERROR(ROUND(CX129/$CW$8,2),0) -> 0 | CZ129: =ROUND(IFERROR(CX129/CY129,0),6) -> 0 | DF129: =IFERROR(ROUND(DE129/$DD$8,2),0) -> 0 | DG129: =ROUND(IFERROR(DE129/DF129,0),6) -> 0 | DM129: =IFERROR(ROUND(DL129/$DK$8,2),0) -> 0 | DN129: =ROUND(IFERROR(DL129/DM129,0),6) -> 0 | DT129: =IFERROR(ROUND(DS129/$DR$8,2),0) -> 0 | DU129: =ROUND(IFERROR(DS129/DT129,0),6) -> 0
E130: =IFERROR(ROUND(D130/$C$8,2),0) -> 0 | F130: =ROUND(IFERROR(D130/E130,0),6) -> 0 | L130: =IFERROR(ROUND(K130/$J$8,2),0) -> 0 | M130: =ROUND(IFERROR(K130/L130,0),6) -> 0 | S130: =IFERROR(ROUND(R130/$Q$8,2),0) -> 0 | T130: =ROUND(IFERROR(R130/S130,0),6) -> 0 | Z130: =IFERROR(ROUND(Y130/$X$8,2),0) -> 0 | AA130: =ROUND(IFERROR(Y130/Z130,0),6) -> 0 | AG130: =IFERROR(ROUND(AF130/$AE$8,2),0) -> 0 | AH130: =ROUND(IFERROR(AF130/AG130,0),6) -> 0 | AN130: =IFERROR(ROUND(AM130/$AL$8,2),0) -> 0 | AO130: =ROUND(IFERROR(AM130/AN130,0),6) -> 0 | AU130: =IFERROR(ROUND(AT130/$AS$8,2),0) -> 0 | AV130: =ROUND(IFERROR(AT130/AU130,0),6) -> 0 | BB130: =IFERROR(ROUND(BA130/$AZ$8,2),0) -> 0 | BC130: =ROUND(IFERROR(BA130/BB130,0),6) -> 0 | BI130: =IFERROR(ROUND(BH130/$BG$8,2),0) -> 0 | BJ130: =ROUND(IFERROR(BH130/BI130,0),6) -> 0 | BP130: =IFERROR(ROUND(BO130/$BN$8,2),0) -> 0 | BQ130: =ROUND(IFERROR(BO130/BP130,0),6) -> 0 | BW130: =IFERROR(ROUND(BV130/$BU$8,2),0) -> 0 | BX130: =ROUND(IFERROR(BV130/BW130,0),6) -> 0 | CD130: =IFERROR(ROUND(CC130/$CB$8,2),0) -> 0 | CE130: =ROUND(IFERROR(CC130/CD130,0),6) -> 0 | CK130: =IFERROR(ROUND(CJ130/$CI$8,2),0) -> 0 | CL130: =ROUND(IFERROR(CJ130/CK130,0),6) -> 0 | CR130: =IFERROR(ROUND(CQ130/$CP$8,2),0) -> 0 | CS130: =ROUND(IFERROR(CQ130/CR130,0),6) -> 0 | CY130: =IFERROR(ROUND(CX130/$CW$8,2),0) -> 0 | CZ130: =ROUND(IFERROR(CX130/CY130,0),6) -> 0 | DF130: =IFERROR(ROUND(DE130/$DD$8,2),0) -> 0 | DG130: =ROUND(IFERROR(DE130/DF130,0),6) -> 0 | DM130: =IFERROR(ROUND(DL130/$DK$8,2),0) -> 0 | DN130: =ROUND(IFERROR(DL130/DM130,0),6) -> 0 | DT130: =IFERROR(ROUND(DS130/$DR$8,2),0) -> 0 | DU130: =ROUND(IFERROR(DS130/DT130,0),6) -> 0
B131: Gesamt (Durchschnittskurs) | C131: Durchschnittskurs: | D131: =ROUND(SUBTOTAL(109,$D$125:$D$130),2) -> 0 | E131: =ROUND(SUBTOTAL(109,$E$125:$E$130),2) -> 0 | F131: =ROUND(IFERROR(D131/E131,0),6) -> 0 | I131: Gesamt (Durchschnittskurs) | J131: Durchschnittskurs: | K131: =ROUND(SUBTOTAL(109,$K$125:$K$130),2) -> 0 | L131: =ROUND(SUBTOTAL(109,$L$125:$L$130),2) -> 0 | M131: =ROUND(IFERROR(K131/L131,0),6) -> 0 | P131: Gesamt (Durchschnittskurs) | Q131: Durchschnittskurs: | R131: =ROUND(SUBTOTAL(109,$R$125:$R$130),2) -> 0 | S131: =ROUND(SUBTOTAL(109,$S$125:$S$130),2) -> 0 | T131: =ROUND(IFERROR(R131/S131,0),6) -> 0 | W131: Gesamt (Durchschnittskurs) | X131: Durchschnittskurs: | Y131: =ROUND(SUBTOTAL(109,$Y$125:$Y$130),2) -> 0 | Z131: =ROUND(SUBTOTAL(109,$Z$125:$Z$130),2) -> 0 | AA131: =ROUND(IFERROR(Y131/Z131,0),6) -> 0 | AD131: Gesamt (Durchschnittskurs) | AE131: Durchschnittskurs: | AF131: =ROUND(SUBTOTAL(109,$AF$125:$AF$130),2) -> 0 | AG131: =ROUND(SUBTOTAL(109,$AG$125:$AG$130),2) -> 0 | AH131: =ROUND(IFERROR(AF131/AG131,0),6) -> 0 | AK131: Gesamt (Durchschnittskurs) | AL131: Durchschnittskurs: | AM131: =ROUND(SUBTOTAL(109,$AM$125:$AM$130),2) -> 0 | AN131: =ROUND(SUBTOTAL(109,$AN$125:$AN$130),2) -> 0 | AO131: =ROUND(IFERROR(AM131/AN131,0),6) -> 0 | AR131: Gesamt (Durchschnittskurs) | AS131: Durchschnittskurs: | AT131: =ROUND(SUBTOTAL(109,$AT$125:$AT$130),2) -> 0 | AU131: =ROUND(SUBTOTAL(109,$AU$125:$AU$130),2) -> 0 | AV131: =ROUND(IFERROR(AT131/AU131,0),6) -> 0 | AY131: Gesamt (Durchschnittskurs) | AZ131: Durchschnittskurs: | BA131: =ROUND(SUBTOTAL(109,$BA$125:$BA$130),2) -> 0 | BB131: =ROUND(SUBTOTAL(109,$BB$125:$BB$130),2) -> 0 | BC131: =ROUND(IFERROR(BA131/BB131,0),6) -> 0 | BF131: Gesamt (Durchschnittskurs) | BG131: Durchschnittskurs: | BH131: =ROUND(SUBTOTAL(109,$BH$125:$BH$130),2) -> 0 | BI131: =ROUND(SUBTOTAL(109,$BI$125:$BI$130),2) -> 0 | BJ131: =ROUND(IFERROR(BH131/BI131,0),6) -> 0 | BM131: Gesamt (Durchschnittskurs) | BN131: Durchschnittskurs: | BO131: =ROUND(SUBTOTAL(109,$BO$125:$BO$130),2) -> 0 | BP131: =ROUND(SUBTOTAL(109,$BP$125:$BP$130),2) -> 0 | BQ131: =ROUND(IFERROR(BO131/BP131,0),6) -> 0 | BT131: Gesamt (Durchschnittskurs) | BU131: Durchschnittskurs: | BV131: =ROUND(SUBTOTAL(109,$BV$125:$BV$130),2) -> 0 | BW131: =ROUND(SUBTOTAL(109,$BW$125:$BW$130),2) -> 0 | BX131: =ROUND(IFERROR(BV131/BW131,0),6) -> 0 | CA131: Gesamt (Durchschnittskurs) | CB131: Durchschnittskurs: | CC131: =ROUND(SUBTOTAL(109,$CC$125:$CC$130),2) -> 0 | CD131: =ROUND(SUBTOTAL(109,$CD$125:$CD$130),2) -> 0 | CE131: =ROUND(IFERROR(CC131/CD131,0),6) -> 0 | CH131: Gesamt (Durchschnittskurs) | CI131: Durchschnittskurs: | CJ131: =ROUND(SUBTOTAL(109,$CJ$125:$CJ$130),2) -> 0 | CK131: =ROUND(SUBTOTAL(109,$CK$125:$CK$130),2) -> 0 | CL131: =ROUND(IFERROR(CJ131/CK131,0),6) -> 0 | CO131: Gesamt (Durchschnittskurs) | CP131: Durchschnittskurs: | CQ131: =ROUND(SUBTOTAL(109,$CQ$125:$CQ$130),2) -> 0 | CR131: =ROUND(SUBTOTAL(109,$CR$125:$CR$130),2) -> 0 | CS131: =ROUND(IFERROR(CQ131/CR131,0),6) -> 0 | CV131: Gesamt (Durchschnittskurs) | CW131: Durchschnittskurs: | CX131: =ROUND(SUBTOTAL(109,$CX$125:$CX$130),2) -> 0 | CY131: =ROUND(SUBTOTAL(109,$CY$125:$CY$130),2) -> 0 | CZ131: =ROUND(IFERROR(CX131/CY131,0),6) -> 0 | DC131: Gesamt (Durchschnittskurs) | DD131: Durchschnittskurs: | DE131: =ROUND(SUBTOTAL(109,$DE$125:$DE$130),2) -> 0 | DF131: =ROUND(SUBTOTAL(109,$DF$125:$DF$130),2) -> 0 | DG131: =ROUND(IFERROR(DE131/DF131,0),6) -> 0 | DJ131: Gesamt (Durchschnittskurs) | DK131: Durchschnittskurs: | DL131: =ROUND(SUBTOTAL(109,$DL$125:$DL$130),2) -> 0 | DM131: =ROUND(SUBTOTAL(109,$DM$125:$DM$130),2) -> 0 | DN131: =ROUND(IFERROR(DL131/DM131,0),6) -> 0 | DQ131: Gesamt (Durchschnittskurs) | DR131: Durchschnittskurs: | DS131: =ROUND(SUBTOTAL(109,$DS$125:$DS$130),2) -> 0 | DT131: =ROUND(SUBTOTAL(109,$DT$125:$DT$130),2) -> 0 | DU131: =ROUND(IFERROR(DS131/DT131,0),6) -> 0

Sheet IV. MA
E3: ➤ | I3: ➤ | M3: ➤ | Q3: ➤ | U3: ➤ | Y3: ➤ | AC3: ➤ | AG3: ➤ | AK3: ➤ | AO3: ➤ | AS3: ➤ | AW3: ➤ | BA3: ➤ | BE3: ➤ | BI3: ➤ | BM3: ➤ | BQ3: ➤
B4: Periode: | C4: Periode 1 | F4: Periode: | G4: Periode 2 | J4: Periode: | K4: Periode 3 | N4: Periode: | O4: Periode 4 | R4: Periode: | S4: Periode 5 | V4: Periode: | W4: Periode 6 | Z4: Periode: | AA4: Periode 7 | AD4: Periode: | AE4: Periode 8 | AH4: Periode: | AI4: Periode 9 | AL4: Periode: | AM4: Periode 10 | AP4: Periode: | AQ4: Periode 11 | AT4: Periode: | AU4: Periode 12 | AX4: Periode: | AY4: Periode 13 | BB4: Periode: | BC4: Periode 14 | BF4: Periode: | BG4: Periode 15 | BJ4: Periode: | BK4: Periode 16 | BN4: Periode: | BO4: Periode 17 | BR4: Periode: | BS4: Periode 18
B5: Von: | F5: Von: | J5: Von: | N5: Von: | R5: Von: | V5: Von: | Z5: Von: | AD5: Von: | AH5: Von: | AL5: Von: | AP5: Von: | AT5: Von: | AX5: Von: | BB5: Von: | BF5: Von: | BJ5: Von: | BN5: Von: | BR5: Von:
B6: Bis: | F6: Bis: | J6: Bis: | N6: Bis: | R6: Bis: | V6: Bis: | Z6: Bis: | AD6: Bis: | AH6: Bis: | AL6: Bis: | AP6: Bis: | AT6: Bis: | AX6: Bis: | BB6: Bis: | BF6: Bis: | BJ6: Bis: | BN6: Bis: | BR6: Bis:
B7: Zeitraum: | C7: =IF(OR(C5="",C6=""),"",DATEDIF(C5,C6,"m")+1) | F7: Zeitraum: | G7: =IF(OR(G5="",G6=""),"",DATEDIF(G5,G6,"m")+1) | J7: Zeitraum: | K7: =IF(OR(K5="",K6=""),"",DATEDIF(K5,K6,"m")+1) | N7: Zeitraum: | O7: =IF(OR(O5="",O6=""),"",DATEDIF(O5,O6,"m")+1) | R7: Zeitraum: | S7: =IF(OR(S5="",S6=""),"",DATEDIF(S5,S6,"m")+1) | V7: Zeitraum: | W7: =IF(OR(W5="",W6=""),"",DATEDIF(W5,W6,"m")+1) | Z7: Zeitraum: | AA7: =IF(OR(AA5="",AA6=""),"",DATEDIF(AA5,AA6,"m")+1) | AD7: Zeitraum: | AE7: =IF(OR(AE5="",AE6=""),"",DATEDIF(AE5,AE6,"m")+1) | AH7: Zeitraum: | AI7: =IF(OR(AI5="",AI6=""),"",DATEDIF(AI5,AI6,"m")+1) | AL7: Zeitraum: | AM7: =IF(OR(AM5="",AM6=""),"",DATEDIF(AM5,AM6,"m")+1) | AP7: Zeitraum: | AQ7: =IF(OR(AQ5="",AQ6=""),"",DATEDIF(AQ5,AQ6,"m")+1) | AT7: Zeitraum: | AU7: =IF(OR(AU5="",AU6=""),"",DATEDIF(AU5,AU6,"m")+1) | AX7: Zeitraum: | AY7: =IF(OR(AY5="",AY6=""),"",DATEDIF(AY5,AY6,"m")+1) | BB7: Zeitraum: | BC7: =IF(OR(BC5="",BC6=""),"",DATEDIF(BC5,BC6,"m")+1) | BF7: Zeitraum: | BG7: =IF(OR(BG5="",BG6=""),"",DATEDIF(BG5,BG6,"m")+1) | BJ7: Zeitraum: | BK7: =IF(OR(BK5="",BK6=""),"",DATEDIF(BK5,BK6,"m")+1) | BN7: Zeitraum: | BO7: =IF(OR(BO5="",BO6=""),"",DATEDIF(BO5,BO6,"m")+1) | BR7: Zeitraum: | BS7: =IF(OR(BS5="",BS6=""),"",DATEDIF(BS5,BS6,"m")+1)
B8: OANDA-Kurs: | F8: OANDA-Kurs: | J8: OANDA-Kurs: | N8: OANDA-Kurs: | R8: OANDA-Kurs: | V8: OANDA-Kurs: | Z8: OANDA-Kurs: | AD8: OANDA-Kurs: | AH8: OANDA-Kurs: | AL8: OANDA-Kurs: | AP8: OANDA-Kurs: | AT8: OANDA-Kurs: | AX8: OANDA-Kurs: | BB8: OANDA-Kurs: | BF8: OANDA-Kurs: | BJ8: OANDA-Kurs: | BN8: OANDA-Kurs: | BR8: OANDA-Kurs:
B9: Kostenkategorie | C9: Angefordert (LC) | D9: Angefordert (EUR) | F9: Kostenkategorie | G9: Angefordert (LC) | H9: Angefordert (EUR) | J9: Kostenkategorie | K9: Angefordert (LC) | L9: Angefordert (EUR) | N9: Kostenkategorie | O9: Angefordert (LC) | P9: Angefordert (EUR) | R9: Kostenkategorie | S9: Angefordert (LC) | T9: Angefordert (EUR) | V9: Kostenkategorie | W9: Angefordert (LC) | X9: Angefordert (EUR) | Z9: Kostenkategorie | AA9: Angefordert (LC) | AB9: Angefordert (EUR) | AD9: Kostenkategorie | AE9: Angefordert (LC) | AF9: Angefordert (EUR) | AH9: Kostenkategorie | AI9: Angefordert (LC) | AJ9: Angefordert (EUR) | AL9: Kostenkategorie | AM9: Angefordert (LC) | AN9: Angefordert (EUR) | AP9: Kostenkategorie | AQ9: Angefordert (LC) | AR9: Angefordert (EUR) | AT9: Kostenkategorie | AU9: Angefordert (LC) | AV9: Angefordert (EUR) | AX9: Kostenkategorie | AY9: Angefordert (LC) | AZ9: Angefordert (EUR) | BB9: Kostenkategorie | BC9: Angefordert (LC) | BD9: Angefordert (EUR) | BF9: Kostenkategorie | BG9: Angefordert (LC) | BH9: Angefordert (EUR) | BJ9: Kostenkategorie | BK9: Angefordert (LC) | BL9: Angefordert (EUR) | BN9: Kostenkategorie | BO9: Angefordert (LC) | BP9: Angefordert (EUR) | BR9: Kostenkategorie | BS9: Angefordert (LC) | BT9: Angefordert (EUR)
B10: Bauausgaben | D10: =IFERROR(ROUND(C10/MA_Kurs_1,2),0) -> 0 | F10: Bauausgaben | H10: =IFERROR(ROUND(G10/MA_Kurs_2,2),0) -> 0 | J10: Bauausgaben | L10: =IFERROR(ROUND(K10/MA_Kurs_3,2),0) -> 0 | N10: Bauausgaben | P10: =IFERROR(ROUND(O10/MA_Kurs_4,2),0) -> 0 | R10: Bauausgaben | T10: =IFERROR(ROUND(S10/MA_Kurs_5,2),0) -> 0 | V10: Bauausgaben | X10: =IFERROR(ROUND(W10/MA_Kurs_6,2),0) -> 0 | Z10: Bauausgaben | AB10: =IFERROR(ROUND(AA10/MA_Kurs_7,2),0) -> 0 | AD10: Bauausgaben | AF10: =IFERROR(ROUND(AE10/MA_Kurs_8,2),0) -> 0 | AH10: Bauausgaben | AJ10: =IFERROR(ROUND(AI10/MA_Kurs_9,2),0) -> 0 | AL10: Bauausgaben | AN10: =IFERROR(ROUND(AM10/MA_Kurs_10,2),0) -> 0 | AP10: Bauausgaben | AR10: =IFERROR(ROUND(AQ10/MA_Kurs_11,2),0) -> 0 | AT10: Bauausgaben | AV10: =IFERROR(ROUND(AU10/MA_Kurs_12,2),0) -> 0 | AX10: Bauausgaben | AZ10: =IFERROR(ROUND(AY10/MA_Kurs_13,2),0) -> 0 | BB10: Bauausgaben | BD10: =IFERROR(ROUND(BC10/MA_Kurs_14,2),0) -> 0 | BF10: Bauausgaben | BH10: =IFERROR(ROUND(BG10/MA_Kurs_15,2),0) -> 0 | BJ10: Bauausgaben | BL10: =IFERROR(ROUND(BK10/MA_Kurs_16,2),0) -> 0 | BN10: Bauausgaben | BP10: =IFERROR(ROUND(BO10/MA_Kurs_17,2),0) -> 0 | BR10: Bauausgaben | BT10: =IFERROR(ROUND(BS10/MA_Kurs_18,2),0) -> 0
B11: Investitionen | D11: =IFERROR(ROUND(C11/MA_Kurs_1,2),0) -> 0 | F11: Investitionen | H11: =IFERROR(ROUND(G11/MA_Kurs_2,2),0) -> 0 | J11: Investitionen | L11: =IFERROR(ROUND(K11/MA_Kurs_3,2),0) -> 0 | N11: Investitionen | P11: =IFERROR(ROUND(O11/MA_Kurs_4,2),0) -> 0 | R11: Investitionen | T11: =IFERROR(ROUND(S11/MA_Kurs_5,2),0) -> 0 | V11: Investitionen | X11: =IFERROR(ROUND(W11/MA_Kurs_6,2),0) -> 0 | Z11: Investitionen | AB11: =IFERROR(ROUND(AA11/MA_Kurs_7,2),0) -> 0 | AD11: Investitionen | AF11: =IFERROR(ROUND(AE11/MA_Kurs_8,2),0) -> 0 | AH11: Investitionen | AJ11: =IFERROR(ROUND(AI11/MA_Kurs_9,2),0) -> 0 | AL11: Investitionen | AN11: =IFERROR(ROUND(AM11/MA_Kurs_10,2),0) -> 0 | AP11: Investitionen | AR11: =IFERROR(ROUND(AQ11/MA_Kurs_11,2),0) -> 0 | AT11: Investitionen | AV11: =IFERROR(ROUND(AU11/MA_Kurs_12,2),0) -> 0 | AX11: Investitionen | AZ11: =IFERROR(ROUND(AY11/MA_Kurs_13,2),0) -> 0 | BB11: Investitionen | BD11: =IFERROR(ROUND(BC11/MA_Kurs_14,2),0) -> 0 | BF11: Investitionen | BH11: =IFERROR(ROUND(BG11/MA_Kurs_15,2),0) -> 0 | BJ11: Investitionen | BL11: =IFERROR(ROUND(BK11/MA_Kurs_16,2),0) -> 0 | BN11: Investitionen | BP11: =IFERROR(ROUND(BO11/MA_Kurs_17,2),0) -> 0 | BR11: Investitionen | BT11: =IFERROR(ROUND(BS11/MA_Kurs_18,2),0) -> 0
B12: Personalkosten | D12: =IFERROR(ROUND(C12/MA_Kurs_1,2),0) -> 0 | F12: Personalkosten | H12: =IFERROR(ROUND(G12/MA_Kurs_2,2),0) -> 0 | J12: Personalkosten | L12: =IFERROR(ROUND(K12/MA_Kurs_3,2),0) -> 0 | N12: Personalkosten | P12: =IFERROR(ROUND(O12/MA_Kurs_4,2),0) -> 0 | R12: Personalkosten | T12: =IFERROR(ROUND(S12/MA_Kurs_5,2),0) -> 0 | V12: Personalkosten | X12: =IFERROR(ROUND(W12/MA_Kurs_6,2),0) -> 0 | Z12: Personalkosten | AB12: =IFERROR(ROUND(AA12/MA_Kurs_7,2),0) -> 0 | AD12: Personalkosten | AF12: =IFERROR(ROUND(AE12/MA_Kurs_8,2),0) -> 0 | AH12: Personalkosten | AJ12: =IFERROR(ROUND(AI12/MA_Kurs_9,2),0) -> 0 | AL12: Personalkosten | AN12: =IFERROR(ROUND(AM12/MA_Kurs_10,2),0) -> 0 | AP12: Personalkosten | AR12: =IFERROR(ROUND(AQ12/MA_Kurs_11,2),0) -> 0 | AT12: Personalkosten | AV12: =IFERROR(ROUND(AU12/MA_Kurs_12,2),0) -> 0 | AX12: Personalkosten | AZ12: =IFERROR(ROUND(AY12/MA_Kurs_13,2),0) -> 0 | BB12: Personalkosten | BD12: =IFERROR(ROUND(BC12/MA_Kurs_14,2),0) -> 0 | BF12: Personalkosten | BH12: =IFERROR(ROUND(BG12/MA_Kurs_15,2),0) -> 0 | BJ12: Personalkosten | BL12: =IFERROR(ROUND(BK12/MA_Kurs_16,2),0) -> 0 | BN12: Personalkosten | BP12: =IFERROR(ROUND(BO12/MA_Kurs_17,2),0) -> 0 | BR12: Personalkosten | BT12: =IFERROR(ROUND(BS12/MA_Kurs_18,2),0) -> 0
B13: Projektaktivitaeten | D13: =IFERROR(ROUND(C13/MA_Kurs_1,2),0) -> 0 | F13: Projektaktivitaeten | H13: =IFERROR(ROUND(G13/MA_Kurs_2,2),0) -> 0 | J13: Projektaktivitaeten | L13: =IFERROR(ROUND(K13/MA_Kurs_3,2),0) -> 0 | N13: Projektaktivitaeten | P13: =IFERROR(ROUND(O13/MA_Kurs_4,2),0) -> 0 | R13: Projektaktivitaeten | T13: =IFERROR(ROUND(S13/MA_Kurs_5,2),0) -> 0 | V13: Projektaktivitaeten | X13: =IFERROR(ROUND(W13/MA_Kurs_6,2),0) -> 0 | Z13: Projektaktivitaeten | AB13: =IFERROR(ROUND(AA13/MA_Kurs_7,2),0) -> 0 | AD13: Projektaktivitaeten | AF13: =IFERROR(ROUND(AE13/MA_Kurs_8,2),0) -> 0 | AH13: Projektaktivitaeten | AJ13: =IFERROR(ROUND(AI13/MA_Kurs_9,2),0) -> 0 | AL13: Projektaktivitaeten | AN13: =IFERROR(ROUND(AM13/MA_Kurs_10,2),0) -> 0 | AP13: Projektaktivitaeten | AR13: =IFERROR(ROUND(AQ13/MA_Kurs_11,2),0) -> 0 | AT13: Projektaktivitaeten | AV13: =IFERROR(ROUND(AU13/MA_Kurs_12,2),0) -> 0 | AX13: Projektaktivitaeten | AZ13: =IFERROR(ROUND(AY13/MA_Kurs_13,2),0) -> 0 | BB13: Projektaktivitaeten | BD13: =IFERROR(ROUND(BC13/MA_Kurs_14,2),0) -> 0 | BF13: Projektaktivitaeten | BH13: =IFERROR(ROUND(BG13/MA_Kurs_15,2),0) -> 0 | BJ13: Projektaktivitaeten | BL13: =IFERROR(ROUND(BK13/MA_Kurs_16,2),0) -> 0 | BN13: Projektaktivitaeten | BP13: =IFERROR(ROUND(BO13/MA_Kurs_17,2),0) -> 0 | BR13: Projektaktivitaeten | BT13: =IFERROR(ROUND(BS13/MA_Kurs_18,2),0) -> 0
B14: Projektverwaltung | D14: =IFERROR(ROUND(C14/MA_Kurs_1,2),0) -> 0 | F14: Projektverwaltung | H14: =IFERROR(ROUND(G14/MA_Kurs_2,2),0) -> 0 | J14: Projektverwaltung | L14: =IFERROR(ROUND(K14/MA_Kurs_3,2),0) -> 0 | N14: Projektverwaltung | P14: =IFERROR(ROUND(O14/MA_Kurs_4,2),0) -> 0 | R14: Projektverwaltung | T14: =IFERROR(ROUND(S14/MA_Kurs_5,2),0) -> 0 | V14: Projektverwaltung | X14: =IFERROR(ROUND(W14/MA_Kurs_6,2),0) -> 0 | Z14: Projektverwaltung | AB14: =IFERROR(ROUND(AA14/MA_Kurs_7,2),0) -> 0 | AD14: Projektverwaltung | AF14: =IFERROR(ROUND(AE14/MA_Kurs_8,2),0) -> 0 | AH14: Projektverwaltung | AJ14: =IFERROR(ROUND(AI14/MA_Kurs_9,2),0) -> 0 | AL14: Projektverwaltung | AN14: =IFERROR(ROUND(AM14/MA_Kurs_10,2),0) -> 0 | AP14: Projektverwaltung | AR14: =IFERROR(ROUND(AQ14/MA_Kurs_11,2),0) -> 0 | AT14: Projektverwaltung | AV14: =IFERROR(ROUND(AU14/MA_Kurs_12,2),0) -> 0 | AX14: Projektverwaltung | AZ14: =IFERROR(ROUND(AY14/MA_Kurs_13,2),0) -> 0 | BB14: Projektverwaltung | BD14: =IFERROR(ROUND(BC14/MA_Kurs_14,2),0) -> 0 | BF14: Projektverwaltung | BH14: =IFERROR(ROUND(BG14/MA_Kurs_15,2),0) -> 0 | BJ14: Projektverwaltung | BL14: =IFERROR(ROUND(BK14/MA_Kurs_16,2),0) -> 0 | BN14: Projektverwaltung | BP14: =IFERROR(ROUND(BO14/MA_Kurs_17,2),0) -> 0 | BR14: Projektverwaltung | BT14: =IFERROR(ROUND(BS14/MA_Kurs_18,2),0) -> 0
B15: Evaluierung | D15: =IFERROR(ROUND(C15/MA_Kurs_1,2),0) -> 0 | F15: Evaluierung | H15: =IFERROR(ROUND(G15/MA_Kurs_2,2),0) -> 0 | J15: Evaluierung | L15: =IFERROR(ROUND(K15/MA_Kurs_3,2),0) -> 0 | N15: Evaluierung | P15: =IFERROR(ROUND(O15/MA_Kurs_4,2),0) -> 0 | R15: Evaluierung | T15: =IFERROR(ROUND(S15/MA_Kurs_5,2),0) -> 0 | V15: Evaluierung | X15: =IFERROR(ROUND(W15/MA_Kurs_6,2),0) -> 0 | Z15: Evaluierung | AB15: =IFERROR(ROUND(AA15/MA_Kurs_7,2),0) -> 0 | AD15: Evaluierung | AF15: =IFERROR(ROUND(AE15/MA_Kurs_8,2),0) -> 0 | AH15: Evaluierung | AJ15: =IFERROR(ROUND(AI15/MA_Kurs_9,2),0) -> 0 | AL15: Evaluierung | AN15: =IFERROR(ROUND(AM15/MA_Kurs_10,2),0) -> 0 | AP15: Evaluierung | AR15: =IFERROR(ROUND(AQ15/MA_Kurs_11,2),0) -> 0 | AT15: Evaluierung | AV15: =IFERROR(ROUND(AU15/MA_Kurs_12,2),0) -> 0 | AX15: Evaluierung | AZ15: =IFERROR(ROUND(AY15/MA_Kurs_13,2),0) -> 0 | BB15: Evaluierung | BD15: =IFERROR(ROUND(BC15/MA_Kurs_14,2),0) -> 0 | BF15: Evaluierung | BH15: =IFERROR(ROUND(BG15/MA_Kurs_15,2),0) -> 0 | BJ15: Evaluierung | BL15: =IFERROR(ROUND(BK15/MA_Kurs_16,2),0) -> 0 | BN15: Evaluierung | BP15: =IFERROR(ROUND(BO15/MA_Kurs_17,2),0) -> 0 | BR15: Evaluierung | BT15: =IFERROR(ROUND(BS15/MA_Kurs_18,2),0) -> 0
B16: Audit | D16: =IFERROR(ROUND(C16/MA_Kurs_1,2),0) -> 0 | F16: Audit | H16: =IFERROR(ROUND(G16/MA_Kurs_2,2),0) -> 0 | J16: Audit | L16: =IFERROR(ROUND(K16/MA_Kurs_3,2),0) -> 0 | N16: Audit | P16: =IFERROR(ROUND(O16/MA_Kurs_4,2),0) -> 0 | R16: Audit | T16: =IFERROR(ROUND(S16/MA_Kurs_5,2),0) -> 0 | V16: Audit | X16: =IFERROR(ROUND(W16/MA_Kurs_6,2),0) -> 0 | Z16: Audit | AB16: =IFERROR(ROUND(AA16/MA_Kurs_7,2),0) -> 0 | AD16: Audit | AF16: =IFERROR(ROUND(AE16/MA_Kurs_8,2),0) -> 0 | AH16: Audit | AJ16: =IFERROR(ROUND(AI16/MA_Kurs_9,2),0) -> 0 | AL16: Audit | AN16: =IFERROR(ROUND(AM16/MA_Kurs_10,2),0) -> 0 | AP16: Audit | AR16: =IFERROR(ROUND(AQ16/MA_Kurs_11,2),0) -> 0 | AT16: Audit | AV16: =IFERROR(ROUND(AU16/MA_Kurs_12,2),0) -> 0 | AX16: Audit | AZ16: =IFERROR(ROUND(AY16/MA_Kurs_13,2),0) -> 0 | BB16: Audit | BD16: =IFERROR(ROUND(BC16/MA_Kurs_14,2),0) -> 0 | BF16: Audit | BH16: =IFERROR(ROUND(BG16/MA_Kurs_15,2),0) -> 0 | BJ16: Audit | BL16: =IFERROR(ROUND(BK16/MA_Kurs_16,2),0) -> 0 | BN16: Audit | BP16: =IFERROR(ROUND(BO16/MA_Kurs_17,2),0) -> 0 | BR16: Audit | BT16: =IFERROR(ROUND(BS16/MA_Kurs_18,2),0) -> 0
B17: Reserve | D17: =IFERROR(ROUND(C17/MA_Kurs_1,2),0) -> 0 | F17: Reserve | H17: =IFERROR(ROUND(G17/MA_Kurs_2,2),0) -> 0 | J17: Reserve | L17: =IFERROR(ROUND(K17/MA_Kurs_3,2),0) -> 0 | N17: Reserve | P17: =IFERROR(ROUND(O17/MA_Kurs_4,2),0) -> 0 | R17: Reserve | T17: =IFERROR(ROUND(S17/MA_Kurs_5,2),0) -> 0 | V17: Reserve | X17: =IFERROR(ROUND(W17/MA_Kurs_6,2),0) -> 0 | Z17: Reserve | AB17: =IFERROR(ROUND(AA17/MA_Kurs_7,2),0) -> 0 | AD17: Reserve | AF17: =IFERROR(ROUND(AE17/MA_Kurs_8,2),0) -> 0 | AH17: Reserve | AJ17: =IFERROR(ROUND(AI17/MA_Kurs_9,2),0) -> 0 | AL17: Reserve | AN17: =IFERROR(ROUND(AM17/MA_Kurs_10,2),0) -> 0 | AP17: Reserve | AR17: =IFERROR(ROUND(AQ17/MA_Kurs_11,2),0) -> 0 | AT17: Reserve | AV17: =IFERROR(ROUND(AU17/MA_Kurs_12,2),0) -> 0 | AX17: Reserve | AZ17: =IFERROR(ROUND(AY17/MA_Kurs_13,2),0) -> 0 | BB17: Reserve | BD17: =IFERROR(ROUND(BC17/MA_Kurs_14,2),0) -> 0 | BF17: Reserve | BH17: =IFERROR(ROUND(BG17/MA_Kurs_15,2),0) -> 0 | BJ17: Reserve | BL17: =IFERROR(ROUND(BK17/MA_Kurs_16,2),0) -> 0 | BN17: Reserve | BP17: =IFERROR(ROUND(BO17/MA_Kurs_17,2),0) -> 0 | BR17: Reserve | BT17: =IFERROR(ROUND(BS17/MA_Kurs_18,2),0) -> 0
B18: SUMME | C18: =ROUND(SUBTOTAL(109,MA_1[Angefordert (LC)]),2) -> 0 | D18: =ROUND(SUBTOTAL(109,MA_1[Angefordert (EUR)]),2) -> 0 | F18: SUMME | G18: =ROUND(SUBTOTAL(109,MA_2[Angefordert (LC)]),2) -> 0 | H18: =ROUND(SUBTOTAL(109,MA_2[Angefordert (EUR)]),2) -> 0 | J18: SUMME | K18: =ROUND(SUBTOTAL(109,MA_3[Angefordert (LC)]),2) -> 0 | L18: =ROUND(SUBTOTAL(109,MA_3[Angefordert (EUR)]),2) -> 0 | N18: SUMME | O18: =ROUND(SUBTOTAL(109,MA_4[Angefordert (LC)]),2) -> 0 | P18: =ROUND(SUBTOTAL(109,MA_4[Angefordert (EUR)]),2) -> 0 | R18: SUMME | S18: =ROUND(SUBTOTAL(109,MA_5[Angefordert (LC)]),2) -> 0 | T18: =ROUND(SUBTOTAL(109,MA_5[Angefordert (EUR)]),2) -> 0 | V18: SUMME | W18: =ROUND(SUBTOTAL(109,MA_6[Angefordert (LC)]),2) -> 0 | X18: =ROUND(SUBTOTAL(109,MA_6[Angefordert (EUR)]),2) -> 0 | Z18: SUMME | AA18: =ROUND(SUBTOTAL(109,MA_7[Angefordert (LC)]),2) -> 0 | AB18: =ROUND(SUBTOTAL(109,MA_7[Angefordert (EUR)]),2) -> 0 | AD18: SUMME | AE18: =ROUND(SUBTOTAL(109,MA_8[Angefordert (LC)]),2) -> 0 | AF18: =ROUND(SUBTOTAL(109,MA_8[Angefordert (EUR)]),2) -> 0 | AH18: SUMME | AI18: =ROUND(SUBTOTAL(109,MA_9[Angefordert (LC)]),2) -> 0 | AJ18: =ROUND(SUBTOTAL(109,MA_9[Angefordert (EUR)]),2) -> 0 | AL18: SUMME | AM18: =ROUND(SUBTOTAL(109,MA_10[Angefordert (LC)]),2) -> 0 | AN18: =ROUND(SUBTOTAL(109,MA_10[Angefordert (EUR)]),2) -> 0 | AP18: SUMME | AQ18: =ROUND(SUBTOTAL(109,MA_11[Angefordert (LC)]),2) -> 0 | AR18: =ROUND(SUBTOTAL(109,MA_11[Angefordert (EUR)]),2) -> 0 | AT18: SUMME | AU18: =ROUND(SUBTOTAL(109,MA_12[Angefordert (LC)]),2) -> 0 | AV18: =ROUND(SUBTOTAL(109,MA_12[Angefordert (EUR)]),2) -> 0 | AX18: SUMME | AY18: =ROUND(SUBTOTAL(109,MA_13[Angefordert (LC)]),2) -> 0 | AZ18: =ROUND(SUBTOTAL(109,MA_13[Angefordert (EUR)]),2) -> 0 | BB18: SUMME | BC18: =ROUND(SUBTOTAL(109,MA_14[Angefordert (LC)]),2) -> 0 | BD18: =ROUND(SUBTOTAL(109,MA_14[Angefordert (EUR)]),2) -> 0 | BF18: SUMME | BG18: =ROUND(SUBTOTAL(109,MA_15[Angefordert (LC)]),2) -> 0 | BH18: =ROUND(SUBTOTAL(109,MA_15[Angefordert (EUR)]),2) -> 0 | BJ18: SUMME | BK18: =ROUND(SUBTOTAL(109,MA_16[Angefordert (LC)]),2) -> 0 | BL18: =ROUND(SUBTOTAL(109,MA_16[Angefordert (EUR)]),2) -> 0 | BN18: SUMME | BO18: =ROUND(SUBTOTAL(109,MA_17[Angefordert (LC)]),2) -> 0 | BP18: =ROUND(SUBTOTAL(109,MA_17[Angefordert (EUR)]),2) -> 0 | BR18: SUMME | BS18: =ROUND(SUBTOTAL(109,MA_18[Angefordert (LC)]),2) -> 0 | BT18: =ROUND(SUBTOTAL(109,MA_18[Angefordert (EUR)]),2) -> 0
B20: Gesamtbedarf an Mitteln: | C20: =ROUND($C$18,2) -> 0 | D20: =ROUND($D$18,2) -> 0 | F20: Gesamtbedarf an Mitteln: | G20: =ROUND($G$18,2) -> 0 | H20: =ROUND($H$18,2) -> 0 | J20: Gesamtbedarf an Mitteln: | K20: =ROUND($K$18,2) -> 0 | L20: =ROUND($L$18,2) -> 0 | N20: Gesamtbedarf an Mitteln: | O20: =ROUND($O$18,2) -> 0 | P20: =ROUND($P$18,2) -> 0 | R20: Gesamtbedarf an Mitteln: | S20: =ROUND($S$18,2) -> 0 | T20: =ROUND($T$18,2) -> 0 | V20: Gesamtbedarf an Mitteln: | W20: =ROUND($W$18,2) -> 0 | X20: =ROUND($X$18,2) -> 0 | Z20: Gesamtbedarf an Mitteln: | AA20: =ROUND($AA$18,2) -> 0 | AB20: =ROUND($AB$18,2) -> 0 | AD20: Gesamtbedarf an Mitteln: | AE20: =ROUND($AE$18,2) -> 0 | AF20: =ROUND($AF$18,2) -> 0 | AH20: Gesamtbedarf an Mitteln: | AI20: =ROUND($AI$18,2) -> 0 | AJ20: =ROUND($AJ$18,2) -> 0 | AL20: Gesamtbedarf an Mitteln: | AM20: =ROUND($AM$18,2) -> 0 | AN20: =ROUND($AN$18,2) -> 0 | AP20: Gesamtbedarf an Mitteln: | AQ20: =ROUND($AQ$18,2) -> 0 | AR20: =ROUND($AR$18,2) -> 0 | AT20: Gesamtbedarf an Mitteln: | AU20: =ROUND($AU$18,2) -> 0 | AV20: =ROUND($AV$18,2) -> 0 | AX20: Gesamtbedarf an Mitteln: | AY20: =ROUND($AY$18,2) -> 0 | AZ20: =ROUND($AZ$18,2) -> 0 | BB20: Gesamtbedarf an Mitteln: | BC20: =ROUND($BC$18,2) -> 0 | BD20: =ROUND($BD$18,2) -> 0 | BF20: Gesamtbedarf an Mitteln: | BG20: =ROUND($BG$18,2) -> 0 | BH20: =ROUND($BH$18,2) -> 0 | BJ20: Gesamtbedarf an Mitteln: | BK20: =ROUND($BK$18,2) -> 0 | BL20: =ROUND($BL$18,2) -> 0 | BN20: Gesamtbedarf an Mitteln: | BO20: =ROUND($BO$18,2) -> 0 | BP20: =ROUND($BP$18,2) -> 0 | BR20: Gesamtbedarf an Mitteln: | BS20: =ROUND($BS$18,2) -> 0 | BT20: =ROUND($BT$18,2) -> 0
B21: abzueglich Eigenmittel: | D21: =IFERROR(ROUND($C$21/$C$8,2),0) -> 0 | F21: abzueglich Eigenmittel: | H21: =IFERROR(ROUND($G$21/$G$8,2),0) -> 0 | J21: abzueglich Eigenmittel: | L21: =IFERROR(ROUND($K$21/$K$8,2),0) -> 0 | N21: abzueglich Eigenmittel: | P21: =IFERROR(ROUND($O$21/$O$8,2),0) -> 0 | R21: abzueglich Eigenmittel: | T21: =IFERROR(ROUND($S$21/$S$8,2),0) -> 0 | V21: abzueglich Eigenmittel: | X21: =IFERROR(ROUND($W$21/$W$8,2),0) -> 0 | Z21: abzueglich Eigenmittel: | AB21: =IFERROR(ROUND($AA$21/$AA$8,2),0) -> 0 | AD21: abzueglich Eigenmittel: | AF21: =IFERROR(ROUND($AE$21/$AE$8,2),0) -> 0 | AH21: abzueglich Eigenmittel: | AJ21: =IFERROR(ROUND($AI$21/$AI$8,2),0) -> 0 | AL21: abzueglich Eigenmittel: | AN21: =IFERROR(ROUND($AM$21/$AM$8,2),0) -> 0 | AP21: abzueglich Eigenmittel: | AR21: =IFERROR(ROUND($AQ$21/$AQ$8,2),0) -> 0 | AT21: abzueglich Eigenmittel: | AV21: =IFERROR(ROUND($AU$21/$AU$8,2),0) -> 0 | AX21: abzueglich Eigenmittel: | AZ21: =IFERROR(ROUND($AY$21/$AY$8,2),0) -> 0 | BB21: abzueglich Eigenmittel: | BD21: =IFERROR(ROUND($BC$21/$BC$8,2),0) -> 0 | BF21: abzueglich Eigenmittel: | BH21: =IFERROR(ROUND($BG$21/$BG$8,2),0) -> 0 | BJ21: abzueglich Eigenmittel: | BL21: =IFERROR(ROUND($BK$21/$BK$8,2),0) -> 0 | BN21: abzueglich Eigenmittel: | BP21: =IFERROR(ROUND($BO$21/$BO$8,2),0) -> 0 | BR21: abzueglich Eigenmittel: | BT21: =IFERROR(ROUND($BS$21/$BS$8,2),0) -> 0
B22: abzueglich Drittmittel: | D22: =IFERROR(ROUND($C$22/$C$8,2),0) -> 0 | F22: abzueglich Drittmittel: | H22: =IFERROR(ROUND($G$22/$G$8,2),0) -> 0 | J22: abzueglich Drittmittel: | L22: =IFERROR(ROUND($K$22/$K$8,2),0) -> 0 | N22: abzueglich Drittmittel: | P22: =IFERROR(ROUND($O$22/$O$8,2),0) -> 0 | R22: abzueglich Drittmittel: | T22: =IFERROR(ROUND($S$22/$S$8,2),0) -> 0 | V22: abzueglich Drittmittel: | X22: =IFERROR(ROUND($W$22/$W$8,2),0) -> 0 | Z22: abzueglich Drittmittel: | AB22: =IFERROR(ROUND($AA$22/$AA$8,2),0) -> 0 | AD22: abzueglich Drittmittel: | AF22: =IFERROR(ROUND($AE$22/$AE$8,2),0) -> 0 | AH22: abzueglich Drittmittel: | AJ22: =IFERROR(ROUND($AI$22/$AI$8,2),0) -> 0 | AL22: abzueglich Drittmittel: | AN22: =IFERROR(ROUND($AM$22/$AM$8,2),0) -> 0 | AP22: abzueglich Drittmittel: | AR22: =IFERROR(ROUND($AQ$22/$AQ$8,2),0) -> 0 | AT22: abzueglich Drittmittel: | AV22: =IFERROR(ROUND($AU$22/$AU$8,2),0) -> 0 | AX22: abzueglich Drittmittel: | AZ22: =IFERROR(ROUND($AY$22/$AY$8,2),0) -> 0 | BB22: abzueglich Drittmittel: | BD22: =IFERROR(ROUND($BC$22/$BC$8,2),0) -> 0 | BF22: abzueglich Drittmittel: | BH22: =IFERROR(ROUND($BG$22/$BG$8,2),0) -> 0 | BJ22: abzueglich Drittmittel: | BL22: =IFERROR(ROUND($BK$22/$BK$8,2),0) -> 0 | BN22: abzueglich Drittmittel: | BP22: =IFERROR(ROUND($BO$22/$BO$8,2),0) -> 0 | BR22: abzueglich Drittmittel: | BT22: =IFERROR(ROUND($BS$22/$BS$8,2),0) -> 0
B23: abzueglich Saldo Vorprojekt: | C23: =ROUND(IF(Saldovortrag_LW="",0,Saldovortrag_LW),2) -> 0 | D23: =IFERROR(ROUND($C$23/$C$8,2),0) -> 0 | F23: abzueglich Saldo Vorperiode (FB): | G23: =ROUND(IFERROR(FB_SaldoLC_1,0),2) -> 0 | H23: =IFERROR(ROUND($G$23/$G$8,2),0) -> 0 | J23: abzueglich Saldo Vorperiode (FB): | K23: =ROUND(IFERROR(FB_SaldoLC_2,0),2) -> 0 | L23: =IFERROR(ROUND($K$23/$K$8,2),0) -> 0 | N23: abzueglich Saldo Vorperiode (FB): | O23: =ROUND(IFERROR(FB_SaldoLC_3,0),2) -> 0 | P23: =IFERROR(ROUND($O$23/$O$8,2),0) -> 0 | R23: abzueglich Saldo Vorperiode (FB): | S23: =ROUND(IFERROR(FB_SaldoLC_4,0),2) -> 0 | T23: =IFERROR(ROUND($S$23/$S$8,2),0) -> 0 | V23: abzueglich Saldo Vorperiode (FB): | W23: =ROUND(IFERROR(FB_SaldoLC_5,0),2) -> 0 | X23: =IFERROR(ROUND($W$23/$W$8,2),0) -> 0 | Z23: abzueglich Saldo Vorperiode (FB): | AA23: =ROUND(IFERROR(FB_SaldoLC_6,0),2) -> 0 | AB23: =IFERROR(ROUND($AA$23/$AA$8,2),0) -> 0 | AD23: abzueglich Saldo Vorperiode (FB): | AE23: =ROUND(IFERROR(FB_SaldoLC_7,0),2) -> 0 | AF23: =IFERROR(ROUND($AE$23/$AE$8,2),0) -> 0 | AH23: abzueglich Saldo Vorperiode (FB): | AI23: =ROUND(IFERROR(FB_SaldoLC_8,0),2) -> 0 | AJ23: =IFERROR(ROUND($AI$23/$AI$8,2),0) -> 0 | AL23: abzueglich Saldo Vorperiode (FB): | AM23: =ROUND(IFERROR(FB_SaldoLC_9,0),2) -> 0 | AN23: =IFERROR(ROUND($AM$23/$AM$8,2),0) -> 0 | AP23: abzueglich Saldo Vorperiode (FB): | AQ23: =ROUND(IFERROR(FB_SaldoLC_10,0),2) -> 0 | AR23: =IFERROR(ROUND($AQ$23/$AQ$8,2),0) -> 0 | AT23: abzueglich Saldo Vorperiode (FB): | AU23: =ROUND(IFERROR(FB_SaldoLC_11,0),2) -> 0 | AV23: =IFERROR(ROUND($AU$23/$AU$8,2),0) -> 0 | AX23: abzueglich Saldo Vorperiode (FB): | AY23: =ROUND(IFERROR(FB_SaldoLC_12,0),2) -> 0 | AZ23: =IFERROR(ROUND($AY$23/$AY$8,2),0) -> 0 | BB23: abzueglich Saldo Vorperiode (FB): | BC23: =ROUND(IFERROR(FB_SaldoLC_13,0),2) -> 0 | BD23: =IFERROR(ROUND($BC$23/$BC$8,2),0) -> 0 | BF23: abzueglich Saldo Vorperiode (FB): | BG23: =ROUND(IFERROR(FB_SaldoLC_14,0),2) -> 0 | BH23: =IFERROR(ROUND($BG$23/$BG$8,2),0) -> 0 | BJ23: abzueglich Saldo Vorperiode (FB): | BK23: =ROUND(IFERROR(FB_SaldoLC_15,0),2) -> 0 | BL23: =IFERROR(ROUND($BK$23/$BK$8,2),0) -> 0 | BN23: abzueglich Saldo Vorperiode (FB): | BO23: =ROUND(IFERROR(FB_SaldoLC_16,0),2) -> 0 | BP23: =IFERROR(ROUND($BO$23/$BO$8,2),0) -> 0 | BR23: abzueglich Saldo Vorperiode (FB): | BS23: =ROUND(IFERROR(FB_SaldoLC_17,0),2) -> 0 | BT23: =IFERROR(ROUND($BS$23/$BS$8,2),0) -> 0
B25: KMW-Mittel Anforderung: | C25: =IFERROR(ROUND($C$18-$C$21-$C$22-$C$23,2),0) -> 0 | D25: =IFERROR(ROUND($D$18-$D$21-$D$22-$D$23,2),0) -> 0 | F25: KMW-Mittel Anforderung: | G25: =IFERROR(ROUND($G$18-$G$21-$G$22-$G$23,2),0) -> 0 | H25: =IFERROR(ROUND($H$18-$H$21-$H$22-$H$23,2),0) -> 0 | J25: KMW-Mittel Anforderung: | K25: =IFERROR(ROUND($K$18-$K$21-$K$22-$K$23,2),0) -> 0 | L25: =IFERROR(ROUND($L$18-$L$21-$L$22-$L$23,2),0) -> 0 | N25: KMW-Mittel Anforderung: | O25: =IFERROR(ROUND($O$18-$O$21-$O$22-$O$23,2),0) -> 0 | P25: =IFERROR(ROUND($P$18-$P$21-$P$22-$P$23,2),0) -> 0 | R25: KMW-Mittel Anforderung: | S25: =IFERROR(ROUND($S$18-$S$21-$S$22-$S$23,2),0) -> 0 | T25: =IFERROR(ROUND($T$18-$T$21-$T$22-$T$23,2),0) -> 0 | V25: KMW-Mittel Anforderung: | W25: =IFERROR(ROUND($W$18-$W$21-$W$22-$W$23,2),0) -> 0 | X25: =IFERROR(ROUND($X$18-$X$21-$X$22-$X$23,2),0) -> 0 | Z25: KMW-Mittel Anforderung: | AA25: =IFERROR(ROUND($AA$18-$AA$21-$AA$22-$AA$23,2),0) -> 0 | AB25: =IFERROR(ROUND($AB$18-$AB$21-$AB$22-$AB$23,2),0) -> 0 | AD25: KMW-Mittel Anforderung: | AE25: =IFERROR(ROUND($AE$18-$AE$21-$AE$22-$AE$23,2),0) -> 0 | AF25: =IFERROR(ROUND($AF$18-$AF$21-$AF$22-$AF$23,2),0) -> 0 | AH25: KMW-Mittel Anforderung: | AI25: =IFERROR(ROUND($AI$18-$AI$21-$AI$22-$AI$23,2),0) -> 0 | AJ25: =IFERROR(ROUND($AJ$18-$AJ$21-$AJ$22-$AJ$23,2),0) -> 0 | AL25: KMW-Mittel Anforderung: | AM25: =IFERROR(ROUND($AM$18-$AM$21-$AM$22-$AM$23,2),0) -> 0 | AN25: =IFERROR(ROUND($AN$18-$AN$21-$AN$22-$AN$23,2),0) -> 0 | AP25: KMW-Mittel Anforderung: | AQ25: =IFERROR(ROUND($AQ$18-$AQ$21-$AQ$22-$AQ$23,2),0) -> 0 | AR25: =IFERROR(ROUND($AR$18-$AR$21-$AR$22-$AR$23,2),0) -> 0 | AT25: KMW-Mittel Anforderung: | AU25: =IFERROR(ROUND($AU$18-$AU$21-$AU$22-$AU$23,2),0) -> 0 | AV25: =IFERROR(ROUND($AV$18-$AV$21-$AV$22-$AV$23,2),0) -> 0 | AX25: KMW-Mittel Anforderung: | AY25: =IFERROR(ROUND($AY$18-$AY$21-$AY$22-$AY$23,2),0) -> 0 | AZ25: =IFERROR(ROUND($AZ$18-$AZ$21-$AZ$22-$AZ$23,2),0) -> 0 | BB25: KMW-Mittel Anforderung: | BC25: =IFERROR(ROUND($BC$18-$BC$21-$BC$22-$BC$23,2),0) -> 0 | BD25: =IFERROR(ROUND($BD$18-$BD$21-$BD$22-$BD$23,2),0) -> 0 | BF25: KMW-Mittel Anforderung: | BG25: =IFERROR(ROUND($BG$18-$BG$21-$BG$22-$BG$23,2),0) -> 0 | BH25: =IFERROR(ROUND($BH$18-$BH$21-$BH$22-$BH$23,2),0) -> 0 | BJ25: KMW-Mittel Anforderung: | BK25: =IFERROR(ROUND($BK$18-$BK$21-$BK$22-$BK$23,2),0) -> 0 | BL25: =IFERROR(ROUND($BL$18-$BL$21-$BL$22-$BL$23,2),0) -> 0 | BN25: KMW-Mittel Anforderung: | BO25: =IFERROR(ROUND($BO$18-$BO$21-$BO$22-$BO$23,2),0) -> 0 | BP25: =IFERROR(ROUND($BP$18-$BP$21-$BP$22-$BP$23,2),0) -> 0 | BR25: KMW-Mittel Anforderung: | BS25: =IFERROR(ROUND($BS$18-$BS$21-$BS$22-$BS$23,2),0) -> 0 | BT25: =IFERROR(ROUND($BT$18-$BT$21-$BT$22-$BT$23,2),0) -> 0
B27: Manueller Betrag (EUR): | F27: Manueller Betrag (EUR): | J27: Manueller Betrag (EUR): | N27: Manueller Betrag (EUR): | R27: Manueller Betrag (EUR): | V27: Manueller Betrag (EUR): | Z27: Manueller Betrag (EUR): | AD27: Manueller Betrag (EUR): | AH27: Manueller Betrag (EUR): | AL27: Manueller Betrag (EUR): | AP27: Manueller Betrag (EUR): | AT27: Manueller Betrag (EUR): | AX27: Manueller Betrag (EUR): | BB27: Manueller Betrag (EUR): | BF27: Manueller Betrag (EUR): | BJ27: Manueller Betrag (EUR): | BN27: Manueller Betrag (EUR): | BR27: Manueller Betrag (EUR):

Sheet V. AUSWERTUNG
B2: V. AUSWERTUNG
B3: Automatische Prüfung von Mittelanforderung und Finanzberichten
B5: MITTELANFORDERUNGSPRÜFUNG | L5: =IF(E11=0,"Aktuelle Mittelanforderung (keine gewählt)","Aktuelle Mittelanforderung – Periode "&E10&" (#"&E11&")") -> Aktuelle Mittelanforderung (keine gewählt) | AD5: =IFERROR(SUMPRODUCT('Daten'!$BA$1:$BA$18,('Daten'!$BB$1:$BB$18=E10)*('Daten'!$BD$1:$BD$18=E11)),0) -> 1
B6: Basis: ausgewählte Mittelanforderung (Folgeperiode des Finanzberichts) | L6: Periode: | M6: =IFERROR(CHOOSE($AD$5,'IV. MA'!$C$4,'IV. MA'!$G$4,'IV. MA'!$K$4,'IV. MA'!$O$4,'IV. MA'!$S$4,'IV. MA'!$W$4,'IV. MA'!$AA$4,'IV. MA'!$AE$4,'IV. MA'!$AI$4,'IV. MA'!$AM$4,'IV. MA'!$AQ$4,'IV. MA'!$AU$4,'IV. MA'!$AY$4,'IV. MA'!$BC$4,'IV. MA'!$BG$4,'IV. MA'!$BK$4,'IV. MA'!$BO$4,'IV. MA'!$BS$4),"") -> Periode 1
L7: Von: | M7: =IFERROR(CHOOSE($AD$5,'IV. MA'!$C$5,'IV. MA'!$G$5,'IV. MA'!$K$5,'IV. MA'!$O$5,'IV. MA'!$S$5,'IV. MA'!$W$5,'IV. MA'!$AA$5,'IV. MA'!$AE$5,'IV. MA'!$AI$5,'IV. MA'!$AM$5,'IV. MA'!$AQ$5,'IV. MA'!$AU$5,'IV. MA'!$AY$5,'IV. MA'!$BC$5,'IV. MA'!$BG$5,'IV. MA'!$BK$5,'IV. MA'!$BO$5,'IV. MA'!$BS$5),"") -> 0
C8: Mittelanforderung auswählen | L8: Bis: | M8: =IFERROR(CHOOSE($AD$5,'IV. MA'!$C$6,'IV. MA'!$G$6,'IV. MA'!$K$6,'IV. MA'!$O$6,'IV. MA'!$S$6,'IV. MA'!$W$6,'IV. MA'!$AA$6,'IV. MA'!$AE$6,'IV. MA'!$AI$6,'IV. MA'!$AM$6,'IV. MA'!$AQ$6,'IV. MA'!$AU$6,'IV. MA'!$AY$6,'IV. MA'!$BC$6,'IV. MA'!$BG$6,'IV. MA'!$BK$6,'IV. MA'!$BO$6,'IV. MA'!$BS$6),"") -> 0
C9: Auswahl: | E9: Neuste MA | L9: Zeitraum: | M9: =IFERROR(CHOOSE($AD$5,'IV. MA'!$C$7,'IV. MA'!$G$7,'IV. MA'!$K$7,'IV. MA'!$O$7,'IV. MA'!$S$7,'IV. MA'!$W$7,'IV. MA'!$AA$7,'IV. MA'!$AE$7,'IV. MA'!$AI$7,'IV. MA'!$AM$7,'IV. MA'!$AQ$7,'IV. MA'!$AU$7,'IV. MA'!$AY$7,'IV. MA'!$BC$7,'IV. MA'!$BG$7,'IV. MA'!$BK$7,'IV. MA'!$BO$7,'IV. MA'!$BS$7),"")
C10: Geprüfte Periode | E10: =E81+1 -> 1 | L10: OANDA-Kurs: | M10: =IFERROR(CHOOSE($AD$5,'IV. MA'!$C$8,'IV. MA'!$G$8,'IV. MA'!$K$8,'IV. MA'!$O$8,'IV. MA'!$S$8,'IV. MA'!$W$8,'IV. MA'!$AA$8,'IV. MA'!$AE$8,'IV. MA'!$AI$8,'IV. MA'!$AM$8,'IV. MA'!$AQ$8,'IV. MA'!$AU$8,'IV. MA'!$AY$8,'IV. MA'!$BC$8,'IV. MA'!$BG$8,'IV. MA'!$BK$8,'IV. MA'!$BO$8,'IV. MA'!$BS$8),"") -> 0
C11: Ausgewählte Anforderung (#) | E11: =IF(E9="Neuste MA",IFERROR(SUMPRODUCT(MAX(('Daten'!$BB$1:$BB$18=E10)*('Daten'!$BC$1:$BC$18=1)*'Daten'!$BD$1:$BD$18)),0),IFERROR(VALUE(MID(E9,FIND("(#",E9)+2,FIND(")",E9)-FIND("(#",E9)-2)),0)) -> 0
C12: Einbezogene Anforderungen | L12: Kostenkategorie | M12: Angefordert (LC) | N12: Angefordert (EUR)
C13: =IF(1<=E11,"Periode "&E10&" (#1)","") | E13: =IF(1<=E11,IFERROR(SUMIFS('Daten'!$BF$1:$BF$18,'Daten'!$BB$1:$BB$18,E10,'Daten'!$BD$1:$BD$18,1),0),"") | G13: =IF(1<=E11,IFERROR(SUMIFS('Daten'!$BG$1:$BG$18,'Daten'!$BB$1:$BB$18,E10,'Daten'!$BD$1:$BD$18,1),0),"") | L13: Bauausgaben | M13: =IFERROR(CHOOSE($AD$5,'IV. MA'!$C$10,'IV. MA'!$G$10,'IV. MA'!$K$10,'IV. MA'!$O$10,'IV. MA'!$S$10,'IV. MA'!$W$10,'IV. MA'!$AA$10,'IV. MA'!$AE$10,'IV. MA'!$AI$10,'IV. MA'!$AM$10,'IV. MA'!$AQ$10,'IV. MA'!$AU$10,'IV. MA'!$AY$10,'IV. MA'!$BC$10,'IV. MA'!$BG$10,'IV. MA'!$BK$10,'IV. MA'!$BO$10,'IV. MA'!$BS$10),"") -> 0 | N13: =IFERROR(CHOOSE($AD$5,'IV. MA'!$D$10,'IV. MA'!$H$10,'IV. MA'!$L$10,'IV. MA'!$P$10,'IV. MA'!$T$10,'IV. MA'!$X$10,'IV. MA'!$AB$10,'IV. MA'!$AF$10,'IV. MA'!$AJ$10,'IV. MA'!$AN$10,'IV. MA'!$AR$10,'IV. MA'!$AV$10,'IV. MA'!$AZ$10,'IV. MA'!$BD$10,'IV. MA'!$BH$10,'IV. MA'!$BL$10,'IV. MA'!$BP$10,'IV. MA'!$BT$10),"") -> 0
C14: =IF(2<=E11,"Periode "&E10&" (#2)","") | E14: =IF(2<=E11,IFERROR(SUMIFS('Daten'!$BF$1:$BF$18,'Daten'!$BB$1:$BB$18,E10,'Daten'!$BD$1:$BD$18,2),0),"") | G14: =IF(2<=E11,IFERROR(SUMIFS('Daten'!$BG$1:$BG$18,'Daten'!$BB$1:$BB$18,E10,'Daten'!$BD$1:$BD$18,2),0),"") | L14: Investitionen | M14: =IFERROR(CHOOSE($AD$5,'IV. MA'!$C$11,'IV. MA'!$G$11,'IV. MA'!$K$11,'IV. MA'!$O$11,'IV. MA'!$S$11,'IV. MA'!$W$11,'IV. MA'!$AA$11,'IV. MA'!$AE$11,'IV. MA'!$AI$11,'IV. MA'!$AM$11,'IV. MA'!$AQ$11,'IV. MA'!$AU$11,'IV. MA'!$AY$11,'IV. MA'!$BC$11,'IV. MA'!$BG$11,'IV. MA'!$BK$11,'IV. MA'!$BO$11,'IV. MA'!$BS$11),"") -> 0 | N14: =IFERROR(CHOOSE($AD$5,'IV. MA'!$D$11,'IV. MA'!$H$11,'IV. MA'!$L$11,'IV. MA'!$P$11,'IV. MA'!$T$11,'IV. MA'!$X$11,'IV. MA'!$AB$11,'IV. MA'!$AF$11,'IV. MA'!$AJ$11,'IV. MA'!$AN$11,'IV. MA'!$AR$11,'IV. MA'!$AV$11,'IV. MA'!$AZ$11,'IV. MA'!$BD$11,'IV. MA'!$BH$11,'IV. MA'!$BL$11,'IV. MA'!$BP$11,'IV. MA'!$BT$11),"") -> 0
C15: =IF(3<=E11,"Periode "&E10&" (#3)","") | E15: =IF(3<=E11,IFERROR(SUMIFS('Daten'!$BF$1:$BF$18,'Daten'!$BB$1:$BB$18,E10,'Daten'!$BD$1:$BD$18,3),0),"") | G15: =IF(3<=E11,IFERROR(SUMIFS('Daten'!$BG$1:$BG$18,'Daten'!$BB$1:$BB$18,E10,'Daten'!$BD$1:$BD$18,3),0),"") | L15: Personalkosten | M15: =IFERROR(CHOOSE($AD$5,'IV. MA'!$C$12,'IV. MA'!$G$12,'IV. MA'!$K$12,'IV. MA'!$O$12,'IV. MA'!$S$12,'IV. MA'!$W$12,'IV. MA'!$AA$12,'IV. MA'!$AE$12,'IV. MA'!$AI$12,'IV. MA'!$AM$12,'IV. MA'!$AQ$12,'IV. MA'!$AU$12,'IV. MA'!$AY$12,'IV. MA'!$BC$12,'IV. MA'!$BG$12,'IV. MA'!$BK$12,'IV. MA'!$BO$12,'IV. MA'!$BS$12),"") -> 0 | N15: =IFERROR(CHOOSE($AD$5,'IV. MA'!$D$12,'IV. MA'!$H$12,'IV. MA'!$L$12,'IV. MA'!$P$12,'IV. MA'!$T$12,'IV. MA'!$X$12,'IV. MA'!$AB$12,'IV. MA'!$AF$12,'IV. MA'!$AJ$12,'IV. MA'!$AN$12,'IV. MA'!$AR$12,'IV. MA'!$AV$12,'IV. MA'!$AZ$12,'IV. MA'!$BD$12,'IV. MA'!$BH$12,'IV. MA'!$BL$12,'IV. MA'!$BP$12,'IV. MA'!$BT$12),"") -> 0
C16: =IF(4<=E11,"Periode "&E10&" (#4)","") | E16: =IF(4<=E11,IFERROR(SUMIFS('Daten'!$BF$1:$BF$18,'Daten'!$BB$1:$BB$18,E10,'Daten'!$BD$1:$BD$18,4),0),"") | G16: =IF(4<=E11,IFERROR(SUMIFS('Daten'!$BG$1:$BG$18,'Daten'!$BB$1:$BB$18,E10,'Daten'!$BD$1:$BD$18,4),0),"") | L16: Projektaktivitaeten | M16: =IFERROR(CHOOSE($AD$5,'IV. MA'!$C$13,'IV. MA'!$G$13,'IV. MA'!$K$13,'IV. MA'!$O$13,'IV. MA'!$S$13,'IV. MA'!$W$13,'IV. MA'!$AA$13,'IV. MA'!$AE$13,'IV. MA'!$AI$13,'IV. MA'!$AM$13,'IV. MA'!$AQ$13,'IV. MA'!$AU$13,'IV. MA'!$AY$13,'IV. MA'!$BC$13,'IV. MA'!$BG$13,'IV. MA'!$BK$13,'IV. MA'!$BO$13,'IV. MA'!$BS$13),"") -> 0 | N16: =IFERROR(CHOOSE($AD$5,'IV. MA'!$D$13,'IV. MA'!$H$13,'IV. MA'!$L$13,'IV. MA'!$P$13,'IV. MA'!$T$13,'IV. MA'!$X$13,'IV. MA'!$AB$13,'IV. MA'!$AF$13,'IV. MA'!$AJ$13,'IV. MA'!$AN$13,'IV. MA'!$AR$13,'IV. MA'!$AV$13,'IV. MA'!$AZ$13,'IV. MA'!$BD$13,'IV. MA'!$BH$13,'IV. MA'!$BL$13,'IV. MA'!$BP$13,'IV. MA'!$BT$13),"") -> 0
C17: =IF(5<=E11,"Periode "&E10&" (#5)","") | E17: =IF(5<=E11,IFERROR(SUMIFS('Daten'!$BF$1:$BF$18,'Daten'!$BB$1:$BB$18,E10,'Daten'!$BD$1:$BD$18,5),0),"") | G17: =IF(5<=E11,IFERROR(SUMIFS('Daten'!$BG$1:$BG$18,'Daten'!$BB$1:$BB$18,E10,'Daten'!$BD$1:$BD$18,5),0),"") | L17: Projektverwaltung | M17: =IFERROR(CHOOSE($AD$5,'IV. MA'!$C$14,'IV. MA'!$G$14,'IV. MA'!$K$14,'IV. MA'!$O$14,'IV. MA'!$S$14,'IV. MA'!$W$14,'IV. MA'!$AA$14,'IV. MA'!$AE$14,'IV. MA'!$AI$14,'IV. MA'!$AM$14,'IV. MA'!$AQ$14,'IV. MA'!$AU$14,'IV. MA'!$AY$14,'IV. MA'!$BC$14,'IV. MA'!$BG$14,'IV. MA'!$BK$14,'IV. MA'!$BO$14,'IV. MA'!$BS$14),"") -> 0 | N17: =IFERROR(CHOOSE($AD$5,'IV. MA'!$D$14,'IV. MA'!$H$14,'IV. MA'!$L$14,'IV. MA'!$P$14,'IV. MA'!$T$14,'IV. MA'!$X$14,'IV. MA'!$AB$14,'IV. MA'!$AF$14,'IV. MA'!$AJ$14,'IV. MA'!$AN$14,'IV. MA'!$AR$14,'IV. MA'!$AV$14,'IV. MA'!$AZ$14,'IV. MA'!$BD$14,'IV. MA'!$BH$14,'IV. MA'!$BL$14,'IV. MA'!$BP$14,'IV. MA'!$BT$14),"") -> 0
C18: =IF(6<=E11,"Periode "&E10&" (#6)","") | E18: =IF(6<=E11,IFERROR(SUMIFS('Daten'!$BF$1:$BF$18,'Daten'!$BB$1:$BB$18,E10,'Daten'!$BD$1:$BD$18,6),0),"") | G18: =IF(6<=E11,IFERROR(SUMIFS('Daten'!$BG$1:$BG$18,'Daten'!$BB$1:$BB$18,E10,'Daten'!$BD$1:$BD$18,6),0),"") | L18: Evaluierung | M18: =IFERROR(CHOOSE($AD$5,'IV. MA'!$C$15,'IV. MA'!$G$15,'IV. MA'!$K$15,'IV. MA'!$O$15,'IV. MA'!$S$15,'IV. MA'!$W$15,'IV. MA'!$AA$15,'IV. MA'!$AE$15,'IV. MA'!$AI$15,'IV. MA'!$AM$15,'IV. MA'!$AQ$15,'IV. MA'!$AU$15,'IV. MA'!$AY$15,'IV. MA'!$BC$15,'IV. MA'!$BG$15,'IV. MA'!$BK$15,'IV. MA'!$BO$15,'IV. MA'!$BS$15),"") -> 0 | N18: =IFERROR(CHOOSE($AD$5,'IV. MA'!$D$15,'IV. MA'!$H$15,'IV. MA'!$L$15,'IV. MA'!$P$15,'IV. MA'!$T$15,'IV. MA'!$X$15,'IV. MA'!$AB$15,'IV. MA'!$AF$15,'IV. MA'!$AJ$15,'IV. MA'!$AN$15,'IV. MA'!$AR$15,'IV. MA'!$AV$15,'IV. MA'!$AZ$15,'IV. MA'!$BD$15,'IV. MA'!$BH$15,'IV. MA'!$BL$15,'IV. MA'!$BP$15,'IV. MA'!$BT$15),"") -> 0
L19: Audit | M19: =IFERROR(CHOOSE($AD$5,'IV. MA'!$C$16,'IV. MA'!$G$16,'IV. MA'!$K$16,'IV. MA'!$O$16,'IV. MA'!$S$16,'IV. MA'!$W$16,'IV. MA'!$AA$16,'IV. MA'!$AE$16,'IV. MA'!$AI$16,'IV. MA'!$AM$16,'IV. MA'!$AQ$16,'IV. MA'!$AU$16,'IV. MA'!$AY$16,'IV. MA'!$BC$16,'IV. MA'!$BG$16,'IV. MA'!$BK$16,'IV. MA'!$BO$16,'IV. MA'!$BS$16),"") -> 0 | N19: =IFERROR(CHOOSE($AD$5,'IV. MA'!$D$16,'IV. MA'!$H$16,'IV. MA'!$L$16,'IV. MA'!$P$16,'IV. MA'!$T$16,'IV. MA'!$X$16,'IV. MA'!$AB$16,'IV. MA'!$AF$16,'IV. MA'!$AJ$16,'IV. MA'!$AN$16,'IV. MA'!$AR$16,'IV. MA'!$AV$16,'IV. MA'!$AZ$16,'IV. MA'!$BD$16,'IV. MA'!$BH$16,'IV. MA'!$BL$16,'IV. MA'!$BP$16,'IV. MA'!$BT$16),"") -> 0
B20: KMW-Mittelprüfung (Mittelanforderung) | L20: Reserve | M20: =IFERROR(CHOOSE($AD$5,'IV. MA'!$C$17,'IV. MA'!$G$17,'IV. MA'!$K$17,'IV. MA'!$O$17,'IV. MA'!$S$17,'IV. MA'!$W$17,'IV. MA'!$AA$17,'IV. MA'!$AE$17,'IV. MA'!$AI$17,'IV. MA'!$AM$17,'IV. MA'!$AQ$17,'IV. MA'!$AU$17,'IV. MA'!$AY$17,'IV. MA'!$BC$17,'IV. MA'!$BG$17,'IV. MA'!$BK$17,'IV. MA'!$BO$17,'IV. MA'!$BS$17),"") -> 0 | N20: =IFERROR(CHOOSE($AD$5,'IV. MA'!$D$17,'IV. MA'!$H$17,'IV. MA'!$L$17,'IV. MA'!$P$17,'IV. MA'!$T$17,'IV. MA'!$X$17,'IV. MA'!$AB$17,'IV. MA'!$AF$17,'IV. MA'!$AJ$17,'IV. MA'!$AN$17,'IV. MA'!$AR$17,'IV. MA'!$AV$17,'IV. MA'!$AZ$17,'IV. MA'!$BD$17,'IV. MA'!$BH$17,'IV. MA'!$BL$17,'IV. MA'!$BP$17,'IV. MA'!$BT$17),"") -> 0
L21: SUMME | M21: =IFERROR(CHOOSE($AD$5,'IV. MA'!$C$18,'IV. MA'!$G$18,'IV. MA'!$K$18,'IV. MA'!$O$18,'IV. MA'!$S$18,'IV. MA'!$W$18,'IV. MA'!$AA$18,'IV. MA'!$AE$18,'IV. MA'!$AI$18,'IV. MA'!$AM$18,'IV. MA'!$AQ$18,'IV. MA'!$AU$18,'IV. MA'!$AY$18,'IV. MA'!$BC$18,'IV. MA'!$BG$18,'IV. MA'!$BK$18,'IV. MA'!$BO$18,'IV. MA'!$BS$18),"") -> 0 | N21: =IFERROR(CHOOSE($AD$5,'IV. MA'!$D$18,'IV. MA'!$H$18,'IV. MA'!$L$18,'IV. MA'!$P$18,'IV. MA'!$T$18,'IV. MA'!$X$18,'IV. MA'!$AB$18,'IV. MA'!$AF$18,'IV. MA'!$AJ$18,'IV. MA'!$AN$18,'IV. MA'!$AR$18,'IV. MA'!$AV$18,'IV. MA'!$AZ$18,'IV. MA'!$BD$18,'IV. MA'!$BH$18,'IV. MA'!$BL$18,'IV. MA'!$BP$18,'IV. MA'!$BT$18),"") -> 0
B22: Bewilligte KMW-Mittel | D22: =IFERROR(ROUND(KMW_Mittel_EUR,2),0) -> 794500 | F22: Abzugsoptionen KMW-Mittel
B23: Davon Reserve | D23: =IFERROR(ROUND(Kosten_Reserve_EUR,2),0) -> 39500 | F23: Abzug | G23: Saldovortrag | I23: =IFERROR(ROUND(Saldovortrag_EUR,2),0) -> 0 | L23: Gesamtbedarf an Mitteln: | M23: =IFERROR(CHOOSE($AD$5,'IV. MA'!$C$20,'IV. MA'!$G$20,'IV. MA'!$K$20,'IV. MA'!$O$20,'IV. MA'!$S$20,'IV. MA'!$W$20,'IV. MA'!$AA$20,'IV. MA'!$AE$20,'IV. MA'!$AI$20,'IV. MA'!$AM$20,'IV. MA'!$AQ$20,'IV. MA'!$AU$20,'IV. MA'!$AY$20,'IV. MA'!$BC$20,'IV. MA'!$BG$20,'IV. MA'!$BK$20,'IV. MA'!$BO$20,'IV. MA'!$BS$20),"") -> 0 | N23: =IFERROR(CHOOSE($AD$5,'IV. MA'!$D$20,'IV. MA'!$H$20,'IV. MA'!$L$20,'IV. MA'!$P$20,'IV. MA'!$T$20,'IV. MA'!$X$20,'IV. MA'!$AB$20,'IV. MA'!$AF$20,'IV. MA'!$AJ$20,'IV. MA'!$AN$20,'IV. MA'!$AR$20,'IV. MA'!$AV$20,'IV. MA'!$AZ$20,'IV. MA'!$BD$20,'IV. MA'!$BH$20,'IV. MA'!$BL$20,'IV. MA'!$BP$20,'IV. MA'!$BT$20),"") -> 0
B24: =IF(Reserve_Freigabe="Ja","Operatives Budget (Reserve freigegeben)","Operatives Budget (abzgl. Reserve)") -> Operatives Budget (abzgl. Reserve) | D24: =IF(Reserve_Freigabe="Ja",ROUND($D$22,2),ROUND($D$22-$D$23,2)) -> 755000 | F24: Abzug | G24: Mehreinnahmen | I24: =I87 -> 0 | L24: abzüglich Eigenmittel: | M24: =IFERROR(CHOOSE($AD$5,'IV. MA'!$C$21,'IV. MA'!$G$21,'IV. MA'!$K$21,'IV. MA'!$O$21,'IV. MA'!$S$21,'IV. MA'!$W$21,'IV. MA'!$AA$21,'IV. MA'!$AE$21,'IV. MA'!$AI$21,'IV. MA'!$AM$21,'IV. MA'!$AQ$21,'IV. MA'!$AU$21,'IV. MA'!$AY$21,'IV. MA'!$BC$21,'IV. MA'!$BG$21,'IV. MA'!$BK$21,'IV. MA'!$BO$21,'IV. MA'!$BS$21),"") -> 0 | N24: =IFERROR(CHOOSE($AD$5,'IV. MA'!$D$21,'IV. MA'!$H$21,'IV. MA'!$L$21,'IV. MA'!$P$21,'IV. MA'!$T$21,'IV. MA'!$X$21,'IV. MA'!$AB$21,'IV. MA'!$AF$21,'IV. MA'!$AJ$21,'IV. MA'!$AN$21,'IV. MA'!$AR$21,'IV. MA'!$AV$21,'IV. MA'!$AZ$21,'IV. MA'!$BD$21,'IV. MA'!$BH$21,'IV. MA'!$BL$21,'IV. MA'!$BP$21,'IV. MA'!$BT$21),"") -> 0
B25: Bereitgestellte KMW-Mittel | D25: =IFERROR(ROUND(SUBTOTAL(109,TblKMWMittel[Betrag]),2),0) -> 0 | F25: Abzug | G25: Prognostizierte Mehreinnahmen | I25: =ROUND(MAX(0,MAX(0,(SUM($G$96:$G$99)-$G$98)+SUMIFS('Daten'!$BH$1:$BH$18,'Daten'!$BB$1:$BB$18,E10,'Daten'!$BD$1:$BD$18,"<="&E11,'Daten'!$BD$1:$BD$18,">=1")-(SUM($H$96:$H$99)-$H$98))-I87),2) -> 0 | L25: abzüglich Drittmittel: | M25: =IFERROR(CHOOSE($AD$5,'IV. MA'!$C$22,'IV. MA'!$G$22,'IV. MA'!$K$22,'IV. MA'!$O$22,'IV. MA'!$S$22,'IV. MA'!$W$22,'IV. MA'!$AA$22,'IV. MA'!$AE$22,'IV. MA'!$AI$22,'IV. MA'!$AM$22,'IV. MA'!$AQ$22,'IV. MA'!$AU$22,'IV. MA'!$AY$22,'IV. MA'!$BC$22,'IV. MA'!$BG$22,'IV. MA'!$BK$22,'IV. MA'!$BO$22,'IV. MA'!$BS$22),"") -> 0 | N25: =IFERROR(CHOOSE($AD$5,'IV. MA'!$D$22,'IV. MA'!$H$22,'IV. MA'!$L$22,'IV. MA'!$P$22,'IV. MA'!$T$22,'IV. MA'!$X$22,'IV. MA'!$AB$22,'IV. MA'!$AF$22,'IV. MA'!$AJ$22,'IV. MA'!$AN$22,'IV. MA'!$AR$22,'IV. MA'!$AV$22,'IV. MA'!$AZ$22,'IV. MA'!$BD$22,'IV. MA'!$BH$22,'IV. MA'!$BL$22,'IV. MA'!$BP$22,'IV. MA'!$BT$22),"") -> 0
B26: Verfügbare KMW-Mittel | D26: =ROUND($D$24-$D$25,2) -> 755000 | G26: Abzugsoptionen KMW insgesamt | I26: =ROUND(IF($F$23="Abzug",MAX(0,$I$23),0)+IF($F$24="Abzug",MAX(0,$I$24),0)+IF($F$25="Abzug",MAX(0,$I$25),0),2) -> 0 | L26: =IFERROR(CHOOSE($AD$5,'IV. MA'!$B$23,'IV. MA'!$F$23,'IV. MA'!$J$23,'IV. MA'!$N$23,'IV. MA'!$R$23,'IV. MA'!$V$23,'IV. MA'!$Z$23,'IV. MA'!$AD$23,'IV. MA'!$AH$23,'IV. MA'!$AL$23,'IV. MA'!$AP$23,'IV. MA'!$AT$23,'IV. MA'!$AX$23,'IV. MA'!$BB$23,'IV. MA'!$BF$23,'IV. MA'!$BJ$23,'IV. MA'!$BN$23,'IV. MA'!$BR$23),"") -> abzueglich Saldo Vorprojekt: | M26: =IFERROR(CHOOSE($AD$5,'IV. MA'!$C$23,'IV. MA'!$G$23,'IV. MA'!$K$23,'IV. MA'!$O$23,'IV. MA'!$S$23,'IV. MA'!$W$23,'IV. MA'!$AA$23,'IV. MA'!$AE$23,'IV. MA'!$AI$23,'IV. MA'!$AM$23,'IV. MA'!$AQ$23,'IV. MA'!$AU$23,'IV. MA'!$AY$23,'IV. MA'!$BC$23,'IV. MA'!$BG$23,'IV. MA'!$BK$23,'IV. MA'!$BO$23,'IV. MA'!$BS$23),"") -> 0 | N26: =IFERROR(CHOOSE($AD$5,'IV. MA'!$D$23,'IV. MA'!$H$23,'IV. MA'!$L$23,'IV. MA'!$P$23,'IV. MA'!$T$23,'IV. MA'!$X$23,'IV. MA'!$AB$23,'IV. MA'!$AF$23,'IV. MA'!$AJ$23,'IV. MA'!$AN$23,'IV. MA'!$AR$23,'IV. MA'!$AV$23,'IV. MA'!$AZ$23,'IV. MA'!$BD$23,'IV. MA'!$BH$23,'IV. MA'!$BL$23,'IV. MA'!$BP$23,'IV. MA'!$BT$23),"") -> 0
G27: Verfügbare KMW-Mittel (bereinigt) | I27: =ROUND($D$26-$I$26,2) -> 755000
L28: KMW-Mittel Anforderung: | M28: =IFERROR(CHOOSE($AD$5,'IV. MA'!$C$25,'IV. MA'!$G$25,'IV. MA'!$K$25,'IV. MA'!$O$25,'IV. MA'!$S$25,'IV. MA'!$W$25,'IV. MA'!$AA$25,'IV. MA'!$AE$25,'IV. MA'!$AI$25,'IV. MA'!$AM$25,'IV. MA'!$AQ$25,'IV. MA'!$AU$25,'IV. MA'!$AY$25,'IV. MA'!$BC$25,'IV. MA'!$BG$25,'IV. MA'!$BK$25,'IV. MA'!$BO$25,'IV. MA'!$BS$25),"") -> 0 | N28: =IFERROR(CHOOSE($AD$5,'IV. MA'!$D$25,'IV. MA'!$H$25,'IV. MA'!$L$25,'IV. MA'!$P$25,'IV. MA'!$T$25,'IV. MA'!$X$25,'IV. MA'!$AB$25,'IV. MA'!$AF$25,'IV. MA'!$AJ$25,'IV. MA'!$AN$25,'IV. MA'!$AR$25,'IV. MA'!$AV$25,'IV. MA'!$AZ$25,'IV. MA'!$BD$25,'IV. MA'!$BH$25,'IV. MA'!$BL$25,'IV. MA'!$BP$25,'IV. MA'!$BT$25),"") -> 0
B29: Abzüglich aktuelle Anforderung | D29: =IFERROR(ROUND(SUMIFS('Daten'!$BV$1:$BV$198,'Daten'!$BT$1:$BT$198,"KMW-Mittel",'Daten'!$BR$1:$BR$198,E10,'Daten'!$BS$1:$BS$198,E11),2),0) -> 0 | F29: Abzüglich aktuelle Anforderung | I29: =IFERROR(ROUND(SUMIFS('Daten'!$BV$1:$BV$198,'Daten'!$BT$1:$BT$198,"KMW-Mittel",'Daten'!$BR$1:$BR$198,E10,'Daten'!$BS$1:$BS$198,E11),2),0) -> 0
B30: Verbleibende KMW-Mittel | D30: =ROUND($D$26-MAX(0,$D$29),2) -> 755000 | F30: Verbleibende KMW-Mittel (bereinigt) | I30: =ROUND($I$27-MAX(0,$I$29),2) -> 755000
B32: Abzüglich manueller Betrag | D32: =IFERROR(CHOOSE(E10,MA_ManBetrag_1,MA_ManBetrag_2,MA_ManBetrag_3,MA_ManBetrag_4,MA_ManBetrag_5,MA_ManBetrag_6,MA_ManBetrag_7,MA_ManBetrag_8,MA_ManBetrag_9,MA_ManBetrag_10,MA_ManBetrag_11,MA_ManBetrag_12,MA_ManBetrag_13,MA_ManBetrag_14,MA_ManBetrag_15,MA_ManBetrag_16,MA_ManBetrag_17,MA_ManBetrag_18),0) -> 0 | F32: Abzüglich manueller Betrag | I32: =IFERROR(CHOOSE(E10,MA_ManBetrag_1,MA_ManBetrag_2,MA_ManBetrag_3,MA_ManBetrag_4,MA_ManBetrag_5,MA_ManBetrag_6,MA_ManBetrag_7,MA_ManBetrag_8,MA_ManBetrag_9,MA_ManBetrag_10,MA_ManBetrag_11,MA_ManBetrag_12,MA_ManBetrag_13,MA_ManBetrag_14,MA_ManBetrag_15,MA_ManBetrag_16,MA_ManBetrag_17,MA_ManBetrag_18),0) -> 0
B33: Verbleibende KMW-Mittel | D33: =ROUND(MAX(0,$D$26-MAX(0,$D$32)),2) -> 755000 | F33: Verbleibende KMW-Mittel (bereinigt) | I33: =ROUND(MAX(0,$I$27-MAX(0,$I$32)),2) -> 755000
B36: Monatslimit-Prüfung
C38: Lokalwährung | D38: Monate (von 12) | E38: Euro
B39: Anforderungshöhe | C39: =IFERROR(ROUND(SUMIFS('Daten'!$BF$1:$BF$18,'Daten'!$BB$1:$BB$18,E10,'Daten'!$BD$1:$BD$18,"<="&E11,'Daten'!$BD$1:$BD$18,">=1"),2),0) -> 0 | E39: =IFERROR(ROUND(SUMIFS('Daten'!$BG$1:$BG$18,'Daten'!$BB$1:$BB$18,E10,'Daten'!$BD$1:$BD$18,"<="&E11,'Daten'!$BD$1:$BD$18,">=1"),2),0) -> 0
B40: Jahresbudget Jahr 1 | C40: =IFERROR(ROUND(SUBTOTAL(109,TblBudgetAusgaben[Jahr 1]),2),0) -> 1659000 | D40: 8 | E40: =IFERROR(ROUND($C$40/Budget_Kurs,2),0) -> 829500
B41: Jahresbudget Jahr 2 | C41: =IFERROR(ROUND(SUBTOTAL(109,TblBudgetAusgaben[Jahr 2]),2),0) -> 0 | D41: 0 | E41: =IFERROR(ROUND($C$41/Budget_Kurs,2),0) -> 0
B42: Jahresbudget Jahr 3 | C42: =IFERROR(ROUND(SUBTOTAL(109,TblBudgetAusgaben[Jahr 3]),2),0) -> 0 | D42: 0 | E42: =IFERROR(ROUND($C$42/Budget_Kurs,2),0) -> 0
B43: Limit-Monate (Summe Anteile) | C43: =$D$40+$D$41+$D$42 -> 8
B44: Bezugszeitraum (Monate, aus MA) | C44: =IFERROR(CHOOSE(IFERROR(SUMPRODUCT('Daten'!$BA$1:$BA$18,('Daten'!$BB$1:$BB$18=E10)*('Daten'!$BD$1:$BD$18=E11)),0),'IV. MA'!$C$7,'IV. MA'!$G$7,'IV. MA'!$K$7,'IV. MA'!$O$7,'IV. MA'!$S$7,'IV. MA'!$W$7,'IV. MA'!$AA$7,'IV. MA'!$AE$7,'IV. MA'!$AI$7,'IV. MA'!$AM$7,'IV. MA'!$AQ$7,'IV. MA'!$AU$7,'IV. MA'!$AY$7,'IV. MA'!$BC$7,'IV. MA'!$BG$7,'IV. MA'!$BK$7,'IV. MA'!$BO$7,'IV. MA'!$BS$7),0)
B45: Monatslimit (anteilig) | C45: =IFERROR(ROUND($C$40*$D$40/12+$C$41*$D$41/12+$C$42*$D$42/12,2),0) -> 1106000 | E45: =IFERROR(ROUND($E$40*$D$40/12+$E$41*$D$41/12+$E$42*$D$42/12,2),0) -> 553000
B46: Status | C46: =IF($C$39<=$C$45,"OK","ÜBERSCHRITTEN") -> OK | E46: =IF($E$39<=$E$45,"OK","ÜBERSCHRITTEN") -> OK
B47: Überschreitung | C47: =ROUND(MAX(0,$C$39-$C$45),2) -> 0 | E47: =ROUND(MAX(0,$E$39-$E$45),2) -> 0
B48: Auslastung % | C48: =IFERROR($C$39/$C$45,0) -> 0 | E48: =IFERROR($E$39/$E$45,0) -> 0
B50: Prognostizierte Finanzierungsanteile
B52: Kategorie | C52: Prognose (LC) | D52: Budget (LC) | E52: Differenz (LC) | F52: Abweichung (LC) | G52: Prognose (EUR) | H52: Budget (EUR) | I52: Differenz (EUR) | J52: Abweichung (EUR)
B53: Eigenmittel | C53: =IFERROR(ROUND(SUMIFS('Daten'!$BU$1:$BU$198,'Daten'!$BT$1:$BT$198,"Eigenmittel",'Daten'!$BR$1:$BR$198,E10,'Daten'!$BS$1:$BS$198,"<="&E11,'Daten'!$BS$1:$BS$198,">=1"),2),0) -> 0 | D53: =IFERROR(ROUND(Eigenmittel_LW,2),0) -> 40000 | E53: =ROUND(IFERROR($C$53-$D$53,0),2) -> -40000 | F53: =ROUND(IFERROR(($C$53/$D$53)-1,0),4) -> -1 | G53: =IFERROR(ROUND(SUMIFS('Daten'!$BV$1:$BV$198,'Daten'!$BT$1:$BT$198,"Eigenmittel",'Daten'!$BR$1:$BR$198,E10,'Daten'!$BS$1:$BS$198,"<="&E11,'Daten'!$BS$1:$BS$198,">=1"),2),0) -> 0 | H53: =IFERROR(ROUND(Eigenmittel_EUR,2),0) -> 20000 | I53: =ROUND(IFERROR($G$53-$H$53,0),2) -> -20000 | J53: =ROUND(IFERROR(($G$53/$H$53)-1,0),4) -> -1
B54: Drittmittel | C54: =IFERROR(ROUND(SUMIFS('Daten'!$BU$1:$BU$198,'Daten'!$BT$1:$BT$198,"Drittmittel",'Daten'!$BR$1:$BR$198,E10,'Daten'!$BS$1:$BS$198,"<="&E11,'Daten'!$BS$1:$BS$198,">=1"),2),0) -> 0 | D54: =IFERROR(ROUND(Drittmittel_LW,2),0) -> 30000 | E54: =ROUND(IFERROR($C$54-$D$54,0),2) -> -30000 | F54: =ROUND(IFERROR(($C$54/$D$54)-1,0),4) -> -1 | G54: =IFERROR(ROUND(SUMIFS('Daten'!$BV$1:$BV$198,'Daten'!$BT$1:$BT$198,"Drittmittel",'Daten'!$BR$1:$BR$198,E10,'Daten'!$BS$1:$BS$198,"<="&E11,'Daten'!$BS$1:$BS$198,">=1"),2),0) -> 0 | H54: =IFERROR(ROUND(Drittmittel_EUR,2),0) -> 15000 | I54: =ROUND(IFERROR($G$54-$H$54,0),2) -> -15000 | J54: =ROUND(IFERROR(($G$54/$H$54)-1,0),4) -> -1
B55: KMW-Mittel | C55: =IFERROR(ROUND(SUMIFS('Daten'!$BU$1:$BU$198,'Daten'!$BT$1:$BT$198,"KMW-Mittel",'Daten'!$BR$1:$BR$198,E10,'Daten'!$BS$1:$BS$198,"<="&E11,'Daten'!$BS$1:$BS$198,">=1"),2),0) -> 0 | D55: =IFERROR(ROUND(KMW_Mittel_LW,2),0) -> 1589000 | E55: =ROUND(IFERROR($C$55-$D$55,0),2) -> -1589000 | F55: =ROUND(IFERROR(($C$55/$D$55)-1,0),4) -> -1 | G55: =IFERROR(ROUND(SUMIFS('Daten'!$BV$1:$BV$198,'Daten'!$BT$1:$BT$198,"KMW-Mittel",'Daten'!$BR$1:$BR$198,E10,'Daten'!$BS$1:$BS$198,"<="&E11,'Daten'!$BS$1:$BS$198,">=1"),2),0) -> 0 | H55: =IFERROR(ROUND(KMW_Mittel_EUR,2),0) -> 794500 | I55: =ROUND(IFERROR($G$55-$H$55,0),2) -> -794500 | J55: =ROUND(IFERROR(($G$55/$H$55)-1,0),4) -> -1
B56: Zinsertraege | C56: =IFERROR(ROUND(SUMIFS('Daten'!$BU$1:$BU$198,'Daten'!$BT$1:$BT$198,"Zinsertraege",'Daten'!$BR$1:$BR$198,E10,'Daten'!$BS$1:$BS$198,"<="&E11,'Daten'!$BS$1:$BS$198,">=1"),2),0) -> 0 | D56: =IFERROR(ROUND(0,2),0) -> 0 | E56: =ROUND(IFERROR($C$56-$D$56,0),2) -> 0 | F56: =ROUND(IFERROR(($C$56/$D$56)-1,0),4) -> 0 | G56: =IFERROR(ROUND(SUMIFS('Daten'!$BV$1:$BV$198,'Daten'!$BT$1:$BT$198,"Zinsertraege",'Daten'!$BR$1:$BR$198,E10,'Daten'!$BS$1:$BS$198,"<="&E11,'Daten'!$BS$1:$BS$198,">=1"),2),0) -> 0 | H56: =IFERROR(ROUND(0,2),0) -> 0 | I56: =ROUND(IFERROR($G$56-$H$56,0),2) -> 0 | J56: =ROUND(IFERROR(($G$56/$H$56)-1,0),4) -> 0
B57: GESAMT | C57: =ROUND(SUM($C$53:$C$56),2) -> 0 | D57: =ROUND(SUM($D$53:$D$56),2) -> 1659000 | E57: =ROUND(SUM($E$53:$E$56),2) -> -1659000 | F57: =ROUND(IFERROR(($C$57/$D$57)-1,0),4) -> -1 | G57: =ROUND(SUM($G$53:$G$56),2) -> 0 | H57: =ROUND(SUM($H$53:$H$56),2) -> 829500 | I57: =ROUND(SUM($I$53:$I$56),2) -> -829500 | J57: =ROUND(IFERROR(($G$57/$H$57)-1,0),4) -> -1
B59: Prognoseprüfung (Ausgaben)
B61: Kategorie | C61: Prognose (LC) | D61: Budget (LC) | E61: Differenz (LC) | F61: Abweichung (LC) | G61: Prognose (EUR) | H61: Budget (EUR) | I61: Differenz (EUR) | J61: Abweichung (EUR)
B62: Bauausgaben | C62: =IFERROR(ROUND(SUMIFS('Daten'!$BU$1:$BU$198,'Daten'!$BT$1:$BT$198,"Bauausgaben",'Daten'!$BR$1:$BR$198,E10,'Daten'!$BS$1:$BS$198,"<="&E11,'Daten'!$BS$1:$BS$198,">=1"),2),0) -> 0 | D62: =IFERROR(ROUND(Kosten_Bauausgaben_LW,2),0) -> 390000 | E62: =ROUND(IFERROR($C$62-$D$62,0),2) -> -390000 | F62: =ROUND(IFERROR(($C$62/$D$62)-1,0),4) -> -1 | G62: =IFERROR(ROUND(SUMIFS('Daten'!$BV$1:$BV$198,'Daten'!$BT$1:$BT$198,"Bauausgaben",'Daten'!$BR$1:$BR$198,E10,'Daten'!$BS$1:$BS$198,"<="&E11,'Daten'!$BS$1:$BS$198,">=1"),2),0) -> 0 | H62: =IFERROR(ROUND(Kosten_Bauausgaben_EUR,2),0) -> 195000 | I62: =ROUND(IFERROR($G$62-$H$62,0),2) -> -195000 | J62: =ROUND(IFERROR(($G$62/$H$62)-1,0),4) -> -1
B63: Investitionen | C63: =IFERROR(ROUND(SUMIFS('Daten'!$BU$1:$BU$198,'Daten'!$BT$1:$BT$198,"Investitionen",'Daten'!$BR$1:$BR$198,E10,'Daten'!$BS$1:$BS$198,"<="&E11,'Daten'!$BS$1:$BS$198,">=1"),2),0) -> 0 | D63: =IFERROR(ROUND(Kosten_Investitionen_LW,2),0) -> 390000 | E63: =ROUND(IFERROR($C$63-$D$63,0),2) -> -390000 | F63: =ROUND(IFERROR(($C$63/$D$63)-1,0),4) -> -1 | G63: =IFERROR(ROUND(SUMIFS('Daten'!$BV$1:$BV$198,'Daten'!$BT$1:$BT$198,"Investitionen",'Daten'!$BR$1:$BR$198,E10,'Daten'!$BS$1:$BS$198,"<="&E11,'Daten'!$BS$1:$BS$198,">=1"),2),0) -> 0 | H63: =IFERROR(ROUND(Kosten_Investitionen_EUR,2),0) -> 195000 | I63: =ROUND(IFERROR($G$63-$H$63,0),2) -> -195000 | J63: =ROUND(IFERROR(($G$63/$H$63)-1,0),4) -> -1
B64: Personalkosten | C64: =IFERROR(ROUND(SUMIFS('Daten'!$BU$1:$BU$198,'Daten'!$BT$1:$BT$198,"Personalkosten",'Daten'!$BR$1:$BR$198,E10,'Daten'!$BS$1:$BS$198,"<="&E11,'Daten'!$BS$1:$BS$198,">=1"),2),0) -> 0 | D64: =IFERROR(ROUND(Kosten_Personalkosten_LW,2),0) -> 0 | E64: =ROUND(IFERROR($C$64-$D$64,0),2) -> 0 | F64: =ROUND(IFERROR(($C$64/$D$64)-1,0),4) -> 0 | G64: =IFERROR(ROUND(SUMIFS('Daten'!$BV$1:$BV$198,'Daten'!$BT$1:$BT$198,"Personalkosten",'Daten'!$BR$1:$BR$198,E10,'Daten'!$BS$1:$BS$198,"<="&E11,'Daten'!$BS$1:$BS$198,">=1"),2),0) -> 0 | H64: =IFERROR(ROUND(Kosten_Personalkosten_EUR,2),0) -> 0 | I64: =ROUND(IFERROR($G$64-$H$64,0),2) -> 0 | J64: =ROUND(IFERROR(($G$64/$H$64)-1,0),4) -> 0
B65: Projektaktivitaeten | C65: =IFERROR(ROUND(SUMIFS('Daten'!$BU$1:$BU$198,'Daten'!$BT$1:$BT$198,"Projektaktivitaeten",'Daten'!$BR$1:$BR$198,E10,'Daten'!$BS$1:$BS$198,"<="&E11,'Daten'!$BS$1:$BS$198,">=1"),2),0) -> 0 | D65: =IFERROR(ROUND(Kosten_Projektaktivitaeten_LW,2),0) -> 390000 | E65: =ROUND(IFERROR($C$65-$D$65,0),2) -> -390000 | F65: =ROUND(IFERROR(($C$65/$D$65)-1,0),4) -> -1 | G65: =IFERROR(ROUND(SUMIFS('Daten'!$BV$1:$BV$198,'Daten'!$BT$1:$BT$198,"Projektaktivitaeten",'Daten'!$BR$1:$BR$198,E10,'Daten'!$BS$1:$BS$198,"<="&E11,'Daten'!$BS$1:$BS$198,">=1"),2),0) -> 0 | H65: =IFERROR(ROUND(Kosten_Projektaktivitaeten_EUR,2),0) -> 195000 | I65: =ROUND(IFERROR($G$65-$H$65,0),2) -> -195000 | J65: =ROUND(IFERROR(($G$65/$H$65)-1,0),4) -> -1
B66: Projektverwaltung | C66: =IFERROR(ROUND(SUMIFS('Daten'!$BU$1:$BU$198,'Daten'!$BT$1:$BT$198,"Projektverwaltung",'Daten'!$BR$1:$BR$198,E10,'Daten'!$BS$1:$BS$198,"<="&E11,'Daten'!$BS$1:$BS$198,">=1"),2),0) -> 0 | D66: =IFERROR(ROUND(Kosten_Projektverwaltung_LW,2),0) -> 390000 | E66: =ROUND(IFERROR($C$66-$D$66,0),2) -> -390000 | F66: =ROUND(IFERROR(($C$66/$D$66)-1,0),4) -> -1 | G66: =IFERROR(ROUND(SUMIFS('Daten'!$BV$1:$BV$198,'Daten'!$BT$1:$BT$198,"Projektverwaltung",'Daten'!$BR$1:$BR$198,E10,'Daten'!$BS$1:$BS$198,"<="&E11,'Daten'!$BS$1:$BS$198,">=1"),2),0) -> 0 | H66: =IFERROR(ROUND(Kosten_Projektverwaltung_EUR,2),0) -> 195000 | I66: =ROUND(IFERROR($G$66-$H$66,0),2) -> -195000 | J66: =ROUND(IFERROR(($G$66/$H$66)-1,0),4) -> -1
B67: Evaluierung | C67: =IFERROR(ROUND(SUMIFS('Daten'!$BU$1:$BU$198,'Daten'!$BT$1:$BT$198,"Evaluierung",'Daten'!$BR$1:$BR$198,E10,'Daten'!$BS$1:$BS$198,"<="&E11,'Daten'!$BS$1:$BS$198,">=1"),2),0) -> 0 | D67: =IFERROR(ROUND(Kosten_Evaluierung_LW,2),0) -> 10000 | E67: =ROUND(IFERROR($C$67-$D$67,0),2) -> -10000 | F67: =ROUND(IFERROR(($C$67/$D$67)-1,0),4) -> -1 | G67: =IFERROR(ROUND(SUMIFS('Daten'!$BV$1:$BV$198,'Daten'!$BT$1:$BT$198,"Evaluierung",'Daten'!$BR$1:$BR$198,E10,'Daten'!$BS$1:$BS$198,"<="&E11,'Daten'!$BS$1:$BS$198,">=1"),2),0) -> 0 | H67: =IFERROR(ROUND(Kosten_Evaluierung_EUR,2),0) -> 5000 | I67: =ROUND(IFERROR($G$67-$H$67,0),2) -> -5000 | J67: =ROUND(IFERROR(($G$67/$H$67)-1,0),4) -> -1
B68: Audit | C68: =IFERROR(ROUND(SUMIFS('Daten'!$BU$1:$BU$198,'Daten'!$BT$1:$BT$198,"Audit",'Daten'!$BR$1:$BR$198,E10,'Daten'!$BS$1:$BS$198,"<="&E11,'Daten'!$BS$1:$BS$198,">=1"),2),0) -> 0 | D68: =IFERROR(ROUND(Kosten_Audit_LW,2),0) -> 10000 | E68: =ROUND(IFERROR($C$68-$D$68,0),2) -> -10000 | F68: =ROUND(IFERROR(($C$68/$D$68)-1,0),4) -> -1 | G68: =IFERROR(ROUND(SUMIFS('Daten'!$BV$1:$BV$198,'Daten'!$BT$1:$BT$198,"Audit",'Daten'!$BR$1:$BR$198,E10,'Daten'!$BS$1:$BS$198,"<="&E11,'Daten'!$BS$1:$BS$198,">=1"),2),0) -> 0 | H68: =IFERROR(ROUND(Kosten_Audit_EUR,2),0) -> 5000 | I68: =ROUND(IFERROR($G$68-$H$68,0),2) -> -5000 | J68: =ROUND(IFERROR(($G$68/$H$68)-1,0),4) -> -1
B69: Reserve | C69: =IFERROR(ROUND(SUMIFS('Daten'!$BU$1:$BU$198,'Daten'!$BT$1:$BT$198,"Reserve",'Daten'!$BR$1:$BR$198,E10,'Daten'!$BS$1:$BS$198,"<="&E11,'Daten'!$BS$1:$BS$198,">=1"),2),0) -> 0 | D69: =IFERROR(ROUND(Kosten_Reserve_LW,2),0) -> 79000 | E69: =ROUND(IFERROR($C$69-$D$69,0),2) -> -79000 | F69: =ROUND(IFERROR(($C$69/$D$69)-1,0),4) -> -1 | G69: =IFERROR(ROUND(SUMIFS('Daten'!$BV$1:$BV$198,'Daten'!$BT$1:$BT$198,"Reserve",'Daten'!$BR$1:$BR$198,E10,'Daten'!$BS$1:$BS$198,"<="&E11,'Daten'!$BS$1:$BS$198,">=1"),2),0) -> 0 | H69: =IFERROR(ROUND(Kosten_Reserve_EUR,2),0) -> 39500 | I69: =ROUND(IFERROR($G$69-$H$69,0),2) -> -39500 | J69: =ROUND(IFERROR(($G$69/$H$69)-1,0),4) -> -1
B70: GESAMT | C70: =ROUND(SUM($C$62:$C$69),2) -> 0 | D70: =ROUND(SUM($D$62:$D$69),2) -> 1659000 | E70: =ROUND(SUM($E$62:$E$69),2) -> -1659000 | F70: =ROUND(IFERROR(($C$70/$D$70)-1,0),4) -> -1 | G70: =ROUND(SUM($G$62:$G$69),2) -> 0 | H70: =ROUND(SUM($H$62:$H$69),2) -> 829500 | I70: =ROUND(SUM($I$62:$I$69),2) -> -829500 | J70: =ROUND(IFERROR(($G$70/$H$70)-1,0),4) -> -1
B76: FINANZBERICHTSPRÜFUNG | L76: =IF(E81=0,"Aktueller Finanzbericht (keiner gewählt)","Aktueller Finanzbericht – Periode "&E81) -> Aktueller Finanzbericht (keiner gewählt)
B77: Basis: ausgewählter Finanzbericht (kumulativ bis zur Periode) | L77: Periode: | M77: =IFERROR(CHOOSE(E81,'III. Finanzberichte'!$C$4,'III. Finanzberichte'!$J$4,'III. Finanzberichte'!$Q$4,'III. Finanzberichte'!$X$4,'III. Finanzberichte'!$AE$4,'III. Finanzberichte'!$AL$4,'III. Finanzberichte'!$AS$4,'III. Finanzberichte'!$AZ$4,'III. Finanzberichte'!$BG$4,'III. Finanzberichte'!$BN$4,'III. Finanzberichte'!$BU$4,'III. Finanzberichte'!$CB$4,'III. Finanzberichte'!$CI$4,'III. Finanzberichte'!$CP$4,'III. Finanzberichte'!$CW$4,'III. Finanzberichte'!$DD$4,'III. Finanzberichte'!$DK$4,'III. Finanzberichte'!$DR$4),"")
L78: Von: | M78: =IFERROR(CHOOSE(E81,'III. Finanzberichte'!$C$5,'III. Finanzberichte'!$J$5,'III. Finanzberichte'!$Q$5,'III. Finanzberichte'!$X$5,'III. Finanzberichte'!$AE$5,'III. Finanzberichte'!$AL$5,'III. Finanzberichte'!$AS$5,'III. Finanzberichte'!$AZ$5,'III. Finanzberichte'!$BG$5,'III. Finanzberichte'!$BN$5,'III. Finanzberichte'!$BU$5,'III. Finanzberichte'!$CB$5,'III. Finanzberichte'!$CI$5,'III. Finanzberichte'!$CP$5,'III. Finanzberichte'!$CW$5,'III. Finanzberichte'!$DD$5,'III. Finanzberichte'!$DK$5,'III. Finanzberichte'!$DR$5),"")
C79: Finanzbericht auswählen | L79: Bis: | M79: =IFERROR(CHOOSE(E81,'III. Finanzberichte'!$C$6,'III. Finanzberichte'!$J$6,'III. Finanzberichte'!$Q$6,'III. Finanzberichte'!$X$6,'III. Finanzberichte'!$AE$6,'III. Finanzberichte'!$AL$6,'III. Finanzberichte'!$AS$6,'III. Finanzberichte'!$AZ$6,'III. Finanzberichte'!$BG$6,'III. Finanzberichte'!$BN$6,'III. Finanzberichte'!$BU$6,'III. Finanzberichte'!$CB$6,'III. Finanzberichte'!$CI$6,'III. Finanzberichte'!$CP$6,'III. Finanzberichte'!$CW$6,'III. Finanzberichte'!$DD$6,'III. Finanzberichte'!$DK$6,'III. Finanzberichte'!$DR$6),"")
C80: Auswahl: | E80: Neuester FB | L80: Zeitraum: | M80: =IFERROR(CHOOSE(E81,'III. Finanzberichte'!$C$7,'III. Finanzberichte'!$J$7,'III. Finanzberichte'!$Q$7,'III. Finanzberichte'!$X$7,'III. Finanzberichte'!$AE$7,'III. Finanzberichte'!$AL$7,'III. Finanzberichte'!$AS$7,'III. Finanzberichte'!$AZ$7,'III. Finanzberichte'!$BG$7,'III. Finanzberichte'!$BN$7,'III. Finanzberichte'!$BU$7,'III. Finanzberichte'!$CB$7,'III. Finanzberichte'!$CI$7,'III. Finanzberichte'!$CP$7,'III. Finanzberichte'!$CW$7,'III. Finanzberichte'!$DD$7,'III. Finanzberichte'!$DK$7,'III. Finanzberichte'!$DR$7),"")
C81: Geprüfte Periode | E81: =IF(E80="Neuester FB",IFERROR(SUMPRODUCT(MAX(('Daten'!$BK$1:$BK$18=1)*'Daten'!$BJ$1:$BJ$18)),0),IF(LEFT(E80,8)="Periode ",IFERROR(VALUE(TRIM(MID(E80,9,5))),0),0)) -> 0 | L81: Durchschnittskurs: | M81: =IFERROR(CHOOSE(E81,'III. Finanzberichte'!$C$8,'III. Finanzberichte'!$J$8,'III. Finanzberichte'!$Q$8,'III. Finanzberichte'!$X$8,'III. Finanzberichte'!$AE$8,'III. Finanzberichte'!$AL$8,'III. Finanzberichte'!$AS$8,'III. Finanzberichte'!$AZ$8,'III. Finanzberichte'!$BG$8,'III. Finanzberichte'!$BN$8,'III. Finanzberichte'!$BU$8,'III. Finanzberichte'!$CB$8,'III. Finanzberichte'!$CI$8,'III. Finanzberichte'!$CP$8,'III. Finanzberichte'!$CW$8,'III. Finanzberichte'!$DD$8,'III. Finanzberichte'!$DK$8,'III. Finanzberichte'!$DR$8),"")
B83: KMW-Mittelprüfung | L83: Einnahmen
L84: Typ / ID | M84: Einnahmen (LC) | N84: Einnahmen (EUR) | O84: Kum. Einnahmen (LC) | P84: Kum. Einnahmen (EUR)
B85: Bewilligte KMW-Mittel | D85: =IFERROR(ROUND(KMW_Mittel_EUR,2),0) -> 794500 | F85: Abzugsoptionen KMW-Mittel | L85: =IFERROR(CHOOSE(E81,'III. Finanzberichte'!$B$11,'III. Finanzberichte'!$I$11,'III. Finanzberichte'!$P$11,'III. Finanzberichte'!$W$11,'III. Finanzberichte'!$AD$11,'III. Finanzberichte'!$AK$11,'III. Finanzberichte'!$AR$11,'III. Finanzberichte'!$AY$11,'III. Finanzberichte'!$BF$11,'III. Finanzberichte'!$BM$11,'III. Finanzberichte'!$BT$11,'III. Finanzberichte'!$CA$11,'III. Finanzberichte'!$CH$11,'III. Finanzberichte'!$CO$11,'III. Finanzberichte'!$CV$11,'III. Finanzberichte'!$DC$11,'III. Finanzberichte'!$DJ$11,'III. Finanzberichte'!$DQ$11),"") | M85: =IFERROR(CHOOSE(E81,'III. Finanzberichte'!$C$11,'III. Finanzberichte'!$J$11,'III. Finanzberichte'!$Q$11,'III. Finanzberichte'!$X$11,'III. Finanzberichte'!$AE$11,'III. Finanzberichte'!$AL$11,'III. Finanzberichte'!$AS$11,'III. Finanzberichte'!$AZ$11,'III. Finanzberichte'!$BG$11,'III. Finanzberichte'!$BN$11,'III. Finanzberichte'!$BU$11,'III. Finanzberichte'!$CB$11,'III. Finanzberichte'!$CI$11,'III. Finanzberichte'!$CP$11,'III. Finanzberichte'!$CW$11,'III. Finanzberichte'!$DD$11,'III. Finanzberichte'!$DK$11,'III. Finanzberichte'!$DR$11),"") | N85: =IFERROR(CHOOSE(E81,'III. Finanzberichte'!$D$11,'III. Finanzberichte'!$K$11,'III. Finanzberichte'!$R$11,'III. Finanzberichte'!$Y$11,'III. Finanzberichte'!$AF$11,'III. Finanzberichte'!$AM$11,'III. Finanzberichte'!$AT$11,'III. Finanzberichte'!$BA$11,'III. Finanzberichte'!$BH$11,'III. Finanzberichte'!$BO$11,'III. Finanzberichte'!$BV$11,'III. Finanzberichte'!$CC$11,'III. Finanzberichte'!$CJ$11,'III. Finanzberichte'!$CQ$11,'III. Finanzberichte'!$CX$11,'III. Finanzberichte'!$DE$11,'III. Finanzberichte'!$DL$11,'III. Finanzberichte'!$DS$11),"") | O85: =IFERROR(CHOOSE(E81,'III. Finanzberichte'!$E$11,'III. Finanzberichte'!$L$11,'III. Finanzberichte'!$S$11,'III. Finanzberichte'!$Z$11,'III. Finanzberichte'!$AG$11,'III. Finanzberichte'!$AN$11,'III. Finanzberichte'!$AU$11,'III. Finanzberichte'!$BB$11,'III. Finanzberichte'!$BI$11,'III. Finanzberichte'!$BP$11,'III. Finanzberichte'!$BW$11,'III. Finanzberichte'!$CD$11,'III. Finanzberichte'!$CK$11,'III. Finanzberichte'!$CR$11,'III. Finanzberichte'!$CY$11,'III. Finanzberichte'!$DF$11,'III. Finanzberichte'!$DM$11,'III. Finanzberichte'!$DT$11),"") | P85: =IFERROR(CHOOSE(E81,'III. Finanzberichte'!$F$11,'III. Finanzberichte'!$M$11,'III. Finanzberichte'!$T$11,'III. Finanzberichte'!$AA$11,'III. Finanzberichte'!$AH$11,'III. Finanzberichte'!$AO$11,'III. Finanzberichte'!$AV$11,'III. Finanzberichte'!$BC$11,'III. Finanzberichte'!$BJ$11,'III. Finanzberichte'!$BQ$11,'III. Finanzberichte'!$BX$11,'III. Finanzberichte'!$CE$11,'III. Finanzberichte'!$CL$11,'III. Finanzberichte'!$CS$11,'III. Finanzberichte'!$CZ$11,'III. Finanzberichte'!$DG$11,'III. Finanzberichte'!$DN$11,'III. Finanzberichte'!$DU$11),"")
B86: Davon Reserve | D86: =IFERROR(ROUND(Kosten_Reserve_EUR,2),0) -> 39500 | F86: Abzug | G86: Saldovortrag | I86: =IFERROR(ROUND(Saldovortrag_EUR,2),0) -> 0 | L86: Eigenmittel | M86: =IFERROR(CHOOSE(E81,'III. Finanzberichte'!$C$12,'III. Finanzberichte'!$J$12,'III. Finanzberichte'!$Q$12,'III. Finanzberichte'!$X$12,'III. Finanzberichte'!$AE$12,'III. Finanzberichte'!$AL$12,'III. Finanzberichte'!$AS$12,'III. Finanzberichte'!$AZ$12,'III. Finanzberichte'!$BG$12,'III. Finanzberichte'!$BN$12,'III. Finanzberichte'!$BU$12,'III. Finanzberichte'!$CB$12,'III. Finanzberichte'!$CI$12,'III. Finanzberichte'!$CP$12,'III. Finanzberichte'!$CW$12,'III. Finanzberichte'!$DD$12,'III. Finanzberichte'!$DK$12,'III. Finanzberichte'!$DR$12),"") | N86: =IFERROR(CHOOSE(E81,'III. Finanzberichte'!$D$12,'III. Finanzberichte'!$K$12,'III. Finanzberichte'!$R$12,'III. Finanzberichte'!$Y$12,'III. Finanzberichte'!$AF$12,'III. Finanzberichte'!$AM$12,'III. Finanzberichte'!$AT$12,'III. Finanzberichte'!$BA$12,'III. Finanzberichte'!$BH$12,'III. Finanzberichte'!$BO$12,'III. Finanzberichte'!$BV$12,'III. Finanzberichte'!$CC$12,'III. Finanzberichte'!$CJ$12,'III. Finanzberichte'!$CQ$12,'III. Finanzberichte'!$CX$12,'III. Finanzberichte'!$DE$12,'III. Finanzberichte'!$DL$12,'III. Finanzberichte'!$DS$12),"") | O86: =IFERROR(CHOOSE(E81,'III. Finanzberichte'!$E$12,'III. Finanzberichte'!$L$12,'III. Finanzberichte'!$S$12,'III. Finanzberichte'!$Z$12,'III. Finanzberichte'!$AG$12,'III. Finanzberichte'!$AN$12,'III. Finanzberichte'!$AU$12,'III. Finanzberichte'!$BB$12,'III. Finanzberichte'!$BI$12,'III. Finanzberichte'!$BP$12,'III. Finanzberichte'!$BW$12,'III. Finanzberichte'!$CD$12,'III. Finanzberichte'!$CK$12,'III. Finanzberichte'!$CR$12,'III. Finanzberichte'!$CY$12,'III. Finanzberichte'!$DF$12,'III. Finanzberichte'!$DM$12,'III. Finanzberichte'!$DT$12),"") | P86: =IFERROR(CHOOSE(E81,'III. Finanzberichte'!$F$12,'III. Finanzberichte'!$M$12,'III. Finanzberichte'!$T$12,'III. Finanzberichte'!$AA$12,'III. Finanzberichte'!$AH$12,'III. Finanzberichte'!$AO$12,'III. Finanzberichte'!$AV$12,'III. Finanzberichte'!$BC$12,'III. Finanzberichte'!$BJ$12,'III. Finanzberichte'!$BQ$12,'III. Finanzberichte'!$BX$12,'III. Finanzberichte'!$CE$12,'III. Finanzberichte'!$CL$12,'III. Finanzberichte'!$CS$12,'III. Finanzberichte'!$CZ$12,'III. Finanzberichte'!$DG$12,'III. Finanzberichte'!$DN$12,'III. Finanzberichte'!$DU$12),"")
B87: =IF(Reserve_Freigabe="Ja","Operatives Budget (Reserve freigegeben)","Operatives Budget (abzgl. Reserve)") -> Operatives Budget (abzgl. Reserve) | D87: =IF(Reserve_Freigabe="Ja",ROUND($D$85,2),ROUND($D$85-$D$86,2)) -> 755000 | F87: Abzug | G87: Mehreinnahmen | I87: =IFERROR(ROUND(MAX(0,(SUM($G$96:$G$99)-$G$98)-(SUM($H$96:$H$99)-$H$98)),2),0) -> 0 | L87: Drittmittel | M87: =IFERROR(CHOOSE(E81,'III. Finanzberichte'!$C$13,'III. Finanzberichte'!$J$13,'III. Finanzberichte'!$Q$13,'III. Finanzberichte'!$X$13,'III. Finanzberichte'!$AE$13,'III. Finanzberichte'!$AL$13,'III. Finanzberichte'!$AS$13,'III. Finanzberichte'!$AZ$13,'III. Finanzberichte'!$BG$13,'III. Finanzberichte'!$BN$13,'III. Finanzberichte'!$BU$13,'III. Finanzberichte'!$CB$13,'III. Finanzberichte'!$CI$13,'III. Finanzberichte'!$CP$13,'III. Finanzberichte'!$CW$13,'III. Finanzberichte'!$DD$13,'III. Finanzberichte'!$DK$13,'III. Finanzberichte'!$DR$13),"") | N87: =IFERROR(CHOOSE(E81,'III. Finanzberichte'!$D$13,'III. Finanzberichte'!$K$13,'III. Finanzberichte'!$R$13,'III. Finanzberichte'!$Y$13,'III. Finanzberichte'!$AF$13,'III. Finanzberichte'!$AM$13,'III. Finanzberichte'!$AT$13,'III. Finanzberichte'!$BA$13,'III. Finanzberichte'!$BH$13,'III. Finanzberichte'!$BO$13,'III. Finanzberichte'!$BV$13,'III. Finanzberichte'!$CC$13,'III. Finanzberichte'!$CJ$13,'III. Finanzberichte'!$CQ$13,'III. Finanzberichte'!$CX$13,'III. Finanzberichte'!$DE$13,'III. Finanzberichte'!$DL$13,'III. Finanzberichte'!$DS$13),"") | O87: =IFERROR(CHOOSE(E81,'III. Finanzberichte'!$E$13,'III. Finanzberichte'!$L$13,'III. Finanzberichte'!$S$13,'III. Finanzberichte'!$Z$13,'III. Finanzberichte'!$AG$13,'III. Finanzberichte'!$AN$13,'III. Finanzberichte'!$AU$13,'III. Finanzberichte'!$BB$13,'III. Finanzberichte'!$BI$13,'III. Finanzberichte'!$BP$13,'III. Finanzberichte'!$BW$13,'III. Finanzberichte'!$CD$13,'III. Finanzberichte'!$CK$13,'III. Finanzberichte'!$CR$13,'III. Finanzberichte'!$CY$13,'III. Finanzberichte'!$DF$13,'III. Finanzberichte'!$DM$13,'III. Finanzberichte'!$DT$13),"") | P87: =IFERROR(CHOOSE(E81,'III. Finanzberichte'!$F$13,'III. Finanzberichte'!$M$13,'III. Finanzberichte'!$T$13,'III. Finanzberichte'!$AA$13,'III. Finanzberichte'!$AH$13,'III. Finanzberichte'!$AO$13,'III. Finanzberichte'!$AV$13,'III. Finanzberichte'!$BC$13,'III. Finanzberichte'!$BJ$13,'III. Finanzberichte'!$BQ$13,'III. Finanzberichte'!$BX$13,'III. Finanzberichte'!$CE$13,'III. Finanzberichte'!$CL$13,'III. Finanzberichte'!$CS$13,'III. Finanzberichte'!$CZ$13,'III. Finanzberichte'!$DG$13,'III. Finanzberichte'!$DN$13,'III. Finanzberichte'!$DU$13),"")
B88: Bereitgestellte KMW-Mittel | D88: =IFERROR(ROUND(SUBTOTAL(109,TblKMWMittel[Betrag]),2),0) -> 0 | G88: Abzugsoptionen KMW insgesamt | I88: =ROUND(IF($F$86="Abzug",MAX(0,$I$86),0)+IF($F$87="Abzug",MAX(0,$I$87),0),2) -> 0 | L88: KMW-Mittel | M88: =IFERROR(CHOOSE(E81,'III. Finanzberichte'!$C$14,'III. Finanzberichte'!$J$14,'III. Finanzberichte'!$Q$14,'III. Finanzberichte'!$X$14,'III. Finanzberichte'!$AE$14,'III. Finanzberichte'!$AL$14,'III. Finanzberichte'!$AS$14,'III. Finanzberichte'!$AZ$14,'III. Finanzberichte'!$BG$14,'III. Finanzberichte'!$BN$14,'III. Finanzberichte'!$BU$14,'III. Finanzberichte'!$CB$14,'III. Finanzberichte'!$CI$14,'III. Finanzberichte'!$CP$14,'III. Finanzberichte'!$CW$14,'III. Finanzberichte'!$DD$14,'III. Finanzberichte'!$DK$14,'III. Finanzberichte'!$DR$14),"") | N88: =IFERROR(CHOOSE(E81,'III. Finanzberichte'!$D$14,'III. Finanzberichte'!$K$14,'III. Finanzberichte'!$R$14,'III. Finanzberichte'!$Y$14,'III. Finanzberichte'!$AF$14,'III. Finanzberichte'!$AM$14,'III. Finanzberichte'!$AT$14,'III. Finanzberichte'!$BA$14,'III. Finanzberichte'!$BH$14,'III. Finanzberichte'!$BO$14,'III. Finanzberichte'!$BV$14,'III. Finanzberichte'!$CC$14,'III. Finanzberichte'!$CJ$14,'III. Finanzberichte'!$CQ$14,'III. Finanzberichte'!$CX$14,'III. Finanzberichte'!$DE$14,'III. Finanzberichte'!$DL$14,'III. Finanzberichte'!$DS$14),"") | O88: =IFERROR(CHOOSE(E81,'III. Finanzberichte'!$E$14,'III. Finanzberichte'!$L$14,'III. Finanzberichte'!$S$14,'III. Finanzberichte'!$Z$14,'III. Finanzberichte'!$AG$14,'III. Finanzberichte'!$AN$14,'III. Finanzberichte'!$AU$14,'III. Finanzberichte'!$BB$14,'III. Finanzberichte'!$BI$14,'III. Finanzberichte'!$BP$14,'III. Finanzberichte'!$BW$14,'III. Finanzberichte'!$CD$14,'III. Finanzberichte'!$CK$14,'III. Finanzberichte'!$CR$14,'III. Finanzberichte'!$CY$14,'III. Finanzberichte'!$DF$14,'III. Finanzberichte'!$DM$14,'III. Finanzberichte'!$DT$14),"") | P88: =IFERROR(CHOOSE(E81,'III. Finanzberichte'!$F$14,'III. Finanzberichte'!$M$14,'III. Finanzberichte'!$T$14,'III. Finanzberichte'!$AA$14,'III. Finanzberichte'!$AH$14,'III. Finanzberichte'!$AO$14,'III. Finanzberichte'!$AV$14,'III. Finanzberichte'!$BC$14,'III. Finanzberichte'!$BJ$14,'III. Finanzberichte'!$BQ$14,'III. Finanzberichte'!$BX$14,'III. Finanzberichte'!$CE$14,'III. Finanzberichte'!$CL$14,'III. Finanzberichte'!$CS$14,'III. Finanzberichte'!$CZ$14,'III. Finanzberichte'!$DG$14,'III. Finanzberichte'!$DN$14,'III. Finanzberichte'!$DU$14),"")
