Workbook
Name Saldovortrag_LW: 'Dashboard'!$C$13
Name Saldovortrag_EUR: 'Dashboard'!$E$13
Name Budget_Kurs: 'I. Budget'!$H$4
Name Eigenmittel_LW: 'I. Budget'!$E$7
Name Eigenmittel_EUR: 'I. Budget'!$I$7
Name Drittmittel_LW: 'I. Budget'!$E$10
Name Drittmittel_EUR: 'I. Budget'!$I$10
Name KMW_Mittel_LW: 'I. Budget'!$E$13
Name KMW_Mittel_EUR: 'I. Budget'!$I$13
Name Gesamtprojektmittel_LW: 'I. Budget'!$E$15
Name Gesamtprojektmittel_EUR: 'I. Budget'!$I$15
Name Kosten_Bauausgaben_LW: 'I. Budget'!$O$4
Name Kosten_Bauausgaben_EUR: 'I. Budget'!$P$4
Name Kosten_Investitionen_LW: 'I. Budget'!$O$5
Name Kosten_Investitionen_EUR: 'I. Budget'!$P$5
Name Kosten_Personalkosten_LW: 'I. Budget'!$O$6
Name Kosten_Personalkosten_EUR: 'I. Budget'!$P$6
Name Kosten_Projektaktivitaeten_LW: 'I. Budget'!$O$7
Name Kosten_Projektaktivitaeten_EUR: 'I. Budget'!$P$7
Name Kosten_Projektverwaltung_LW: 'I. Budget'!$O$8
Name Kosten_Projektverwaltung_EUR: 'I. Budget'!$P$8
Name Kosten_Evaluierung_LW: 'I. Budget'!$O$9
Name Kosten_Evaluierung_EUR: 'I. Budget'!$P$9
Name Kosten_Audit_LW: 'I. Budget'!$O$10
Name Kosten_Audit_EUR: 'I. Budget'!$P$10
Name Kosten_Reserve_LW: 'I. Budget'!$O$11
Name Kosten_Reserve_EUR: 'I. Budget'!$P$11
Name Gesamtausgaben_LW: 'I. Budget'!$O$12
Name Gesamtausgaben_EUR: 'I. Budget'!$P$12
Name Geber_Liste: OFFSET('I. Budget'!$R$1, 0, 0, COUNTA('I. Budget'!R:R), 1)
Name Budget_ID_Liste: OFFSET('I. Budget'!$S$1, 0, 0, COUNTA('I. Budget'!S:S), 1)
Name Reserve_Freigabe: 'I. Budget'!$K$5
Name FB_Kurs_1: 'III. Finanzberichte'!$C$8
Name FB_SaldoLC_1: 'III. Finanzberichte'!$C$31
Name FB_SaldoEUR_1: 'III. Finanzberichte'!$D$31
Name FB_Kurs_2: 'III. Finanzberichte'!$J$8
Name FB_SaldoLC_2: 'III. Finanzberichte'!$J$31
Name FB_SaldoEUR_2: 'III. Finanzberichte'!$K$31
Name FB_Kurs_3: 'III. Finanzberichte'!$Q$8
Name FB_SaldoLC_3: 'III. Finanzberichte'!$Q$31
Name FB_SaldoEUR_3: 'III. Finanzberichte'!$R$31
Name FB_Kurs_4: 'III. Finanzberichte'!$X$8
Name FB_SaldoLC_4: 'III. Finanzberichte'!$X$31
Name FB_SaldoEUR_4: 'III. Finanzberichte'!$Y$31
Name FB_Kurs_5: 'III. Finanzberichte'!$AE$8
Name FB_SaldoLC_5: 'III. Finanzberichte'!$AE$31
Name FB_SaldoEUR_5: 'III. Finanzberichte'!$AF$31
Name FB_Kurs_6: 'III. Finanzberichte'!$AL$8
Name FB_SaldoLC_6: 'III. Finanzberichte'!$AL$31
Name FB_SaldoEUR_6: 'III. Finanzberichte'!$AM$31
Name FB_Kurs_7: 'III. Finanzberichte'!$AS$8
Name FB_SaldoLC_7: 'III. Finanzberichte'!$AS$31
Name FB_SaldoEUR_7: 'III. Finanzberichte'!$AT$31
Name FB_Kurs_8: 'III. Finanzberichte'!$AZ$8
Name FB_SaldoLC_8: 'III. Finanzberichte'!$AZ$31
Name FB_SaldoEUR_8: 'III. Finanzberichte'!$BA$31
Name FB_Kurs_9: 'III. Finanzberichte'!$BG$8
Name FB_SaldoLC_9: 'III. Finanzberichte'!$BG$31
Name FB_SaldoEUR_9: 'III. Finanzberichte'!$BH$31
Name FB_Kurs_10: 'III. Finanzberichte'!$BN$8

Sheet Dashboard
AA1: AED
B2: DASHBOARD (v1.0) | AA2: AFN
AA3: ALL
B4: Statische Projektinformationen | AA4: AMD
B5: Projektnummer | C5: PRJ-2025-042 | D5: Vorprojekt vorhanden | E5: Ja | AA5: AOA
B6: Projekttitel | C6: Aufbau Gemeindezentrum Beispielstadt | AA6: ARS
B7: Projekttraeger | C7: Beispiel Hilfswerk e.V. | D7: Berichtswaehrung | E7: USD | AA7: AUD
B8: Projektlaufzeit (geplant) | C8: 01.01.2025 - 31.12.2027 | D8: In Monate | E8: ==IFERROR(LET(AllNums, TEXTJOIN("", TRUE, IFERROR(MID(C8, SEQUENCE(LEN(C8)), 1) * 1, "")), StartDate, DATE(MID(AllNums, 5, 4), MID(AllNums, 3, 2), LEFT(AllNums, 2)), EndDate, DATE(MID(AllNums, 13, 4), MID(AllNums, 11, 2), MID(AllNums, 9, 2)), DATEDIF(StartDate, EndDate + 1, "M")), "") | AA8: AWG
B9: Vorprojektnummer | C9: PRJ-2022-017 | D9: VP-Berichtswaehrung | E9: USD | AA9: AZN
B10: Vorprojektende | C10: 45657 | D10: Wechselkurs | E10: 125 | AA10: BAM
B11: Saldo (LW) | C11: 200000 | D11: Saldo (EUR) | E11: 1600 | AA11: BBD
B12: Folgeprojektstart | C12: 45658 | D12: Wechselkurs | E12: 125 | AA12: BDT
B13: Saldovortrag (LW) | C13: 200000 | D13: Saldovortrag (EUR) | E13: 1600 | AA13: BHD
AA14: BIF
B15: Folgende Dokumente liegen vor: | D15: Ja | E15: Vorprojektsaldo (Nachweis) | AA15: BMD
D16: Ja | E16: Vertrag | AA16: BND
D17: Ja | E17: Budget | AA17: BOB
D18: Ja | E18: Bankbelege | AA18: BRL
D19: Ja | E19: Finanzbericht(e) | AA19: BSD
D20: Ja | E20: Einzelbelege und Beleglisten | AA20: BTN
D21: Ja | E21: Narrativer Bericht | AA21: BWP
AA22: BYN
AA23: BZD
AA24: CAD
AA25: CDF
AA26: CHF
AA27: CLP
AA28: CNY
AA29: COP
AA30: CRC
AA31: CUP
AA32: CVE
AA33: CZK
... AA155: ZWG

Sheet I. Budget
R1: {=_xlfn.VSTACK({"Projektpartner";"Bank"},IFERROR(_xlfn._xlws.FILTER(TblDrittmittel[Name des Gebers],TblDrittmittel[Name des Gebers]<>""),""))} -> 0 | S1: {=IFERROR(_xlfn._xlws.FILTER(TblBudgetAusgaben[ID],TblBudgetAusgaben[ID]<>""),"")} -> 0
B2: I. KERNDATEN BUDGET | K2: Reserve Freigabe
K3: ==$P$11
B4: 1. GEPLANTE EINNAHMEN / FINANZIERUNG | G4: € Budget-Kurs: | H4: ==IFERROR($E$15/$I$15,0) | K4: Reserve freigeben: | O4: ==SUMIFS(TblBudgetAusgaben[Betrag (LC)],TblBudgetAusgaben[Kostenkategorie],"Bauausgaben") | P4: ==SUMIFS(TblBudgetAusgaben[Betrag (EUR)],TblBudgetAusgaben[Kostenkategorie],"Bauausgaben")
B5: Finanzierungsquelle | E5: Betrag (LC) | F5: Jahr 1 | G5: Jahr 2 | H5: Jahr 3 | I5: Betrag (EUR) | K5: Nein | O5: ==SUMIFS(TblBudgetAusgaben[Betrag (LC)],TblBudgetAusgaben[Kostenkategorie],"Investitionen") | P5: ==SUMIFS(TblBudgetAusgaben[Betrag (EUR)],TblBudgetAusgaben[Kostenkategorie],"Investitionen")
B6: 1.1 Eigenmittel | K6: ==IF($K$5="Ja","FREIGEGEBEN","NICHT FREIGEGEBEN") | O6: ==SUMIFS(TblBudgetAusgaben[Betrag (LC)],TblBudgetAusgaben[Kostenkategorie],"Personalkosten") | P6: ==SUMIFS(TblBudgetAusgaben[Betrag (EUR)],TblBudgetAusgaben[Kostenkategorie],"Personalkosten")
B7: Eigenmittel | E7: 1250000 | F7: 500000 | G7: 437500 | H7: 312500 | I7: 10000 | O7: ==SUMIFS(TblBudgetAusgaben[Betrag (LC)],TblBudgetAusgaben[Kostenkategorie],"Projektaktivitaeten") | P7: ==SUMIFS(TblBudgetAusgaben[Betrag (EUR)],TblBudgetAusgaben[Kostenkategorie],"Projektaktivitaeten")
K8: Begruendung | O8: ==SUMIFS(TblBudgetAusgaben[Betrag (LC)],TblBudgetAusgaben[Kostenkategorie],"Projektverwaltung") | P8: ==SUMIFS(TblBudgetAusgaben[Betrag (EUR)],TblBudgetAusgaben[Kostenkategorie],"Projektverwaltung")
B9: 1.2 Drittmittel | O9: ==SUMIFS(TblBudgetAusgaben[Betrag (LC)],TblBudgetAusgaben[Kostenkategorie],"Evaluierung") | P9: ==SUMIFS(TblBudgetAusgaben[Betrag (EUR)],TblBudgetAusgaben[Kostenkategorie],"Evaluierung")
B10: Drittmittel (Summe): | D10: Aufstellung je Geber → Tabelle rechts | E10: ==SUM(TblDrittmittel[Betrag (LC)]) | F10: 1500000 | G10: 1250000 | H10: 1000000 | I10: ==SUM(TblDrittmittel[Betrag (EUR)]) | O10: ==SUMIFS(TblBudgetAusgaben[Betrag (LC)],TblBudgetAusgaben[Kostenkategorie],"Audit") | P10: ==SUMIFS(TblBudgetAusgaben[Betrag (EUR)],TblBudgetAusgaben[Kostenkategorie],"Audit")
O11: ==SUMIFS(TblBudgetAusgaben[Betrag (LC)],TblBudgetAusgaben[Kostenkategorie],"Reserve") | P11: ==SUMIFS(TblBudgetAusgaben[Betrag (EUR)],TblBudgetAusgaben[Kostenkategorie],"Reserve")
B12: 1.3 KMW-Mittel | O12: ==SUBTOTAL(109,TblBudgetAusgaben[Betrag (LC)]) | P12: ==SUBTOTAL(109,TblBudgetAusgaben[Betrag (EUR)])
B13: KMW-Mittel | E13: 7500000 | F13: 3000000 | G13: 2500000 | H13: 2000000 | I13: 60000
B15: GESAMTPROJEKTMITTEL | E15: ==E7+E10+E13 | F15: ==F7+F10+F13 | G15: ==G7+G10+G13 | H15: ==H7+H10+H13 | I15: ==I7+I10+I13
B17: 2. GEPLANTE AUSGABEN | K17: Drittmittel – Aufstellung je Geber
B18: Kostenkategorie | C18: ID | D18: Kostenposition | E18: Betrag (LC) | F18: Jahr 1 | G18: Jahr 2 | H18: Jahr 3 | I18: Betrag (EUR) | K18: Name des Gebers | L18: Betrag (LC) | M18: Betrag (EUR)
B19: Bauausgaben | C19: 1.1 | D19: Rohbau | E19: 2500000 | F19: 1500000 | G19: 1000000 | H19: 0 | I19: 20000 | K19: Projektpartner A | L19: 2500000 | M19: 20000
B20: Bauausgaben | C20: 1.2 | D20: Innenausbau | E20: 1250000 | F20: 0 | G20: 750000 | H20: 500000 | I20: 10000 | K20: Bank XY | L20: 1250000 | M20: 10000
B21: Investitionen | C21: 2.1 | D21: Fahrzeuge | E21: 1000000 | F21: 1000000 | G21: 0 | H21: 0 | I21: 8000
B22: Personalkosten | C22: 3.1 | D22: Projektleitung | E22: 1875000 | F22: 625000 | G22: 625000 | H22: 625000 | I22: 15000
B23: Personalkosten | C23: 3.2 | D23: Fachkraefte | E23: 1500000 | F23: 500000 | G23: 500000 | H23: 500000 | I23: 12000
B24: Projektaktivitaeten | C24: 4.1 | D24: Schulungen | E24: 1250000 | F24: 500000 | G24: 375000 | H24: 375000 | I24: 10000
B25: Projektverwaltung | C25: 5.1 | D25: Buero | E25: 625000 | F25: 250000 | G25: 250000 | H25: 125000 | I25: 5000
B26: Evaluierung | C26: 6.1 | D26: Zwischenbewertung | E26: 250000 | F26: 0 | G26: 250000 | H26: 0 | I26: 2000
B27: Audit | C27: 7.1 | D27: Jahresabschluss | E27: 250000 | F27: 125000 | G27: 62500 | H27: 62500 | I27: 2000
B28: Reserve | C28: 8.1 | D28: Reserve | E28: 2000000 | F28: 625000 | G28: 625000 | H28: 750000 | I28: 16000
B29: Geplante Gesamtausgaben | E29: ==SUBTOTAL(109,TblBudgetAusgaben[Betrag (LC)]) | F29: ==SUBTOTAL(109,TblBudgetAusgaben[Jahr 1]) | G29: ==SUBTOTAL(109,TblBudgetAusgaben[Jahr 2]) | H29: ==SUBTOTAL(109,TblBudgetAusgaben[Jahr 3]) | I29: ==SUBTOTAL(109,TblBudgetAusgaben[Betrag (EUR)])
B31: Budgetpruefung
B32: Einnahmen = Ausgaben (LC) | E32: ==IF(ROUND($E$15-$O$12,2)=0,"OK","Abweichung")
B33: Einnahmen = Ausgaben (EUR) | E33: ==IF(ROUND($I$15-$P$12,2)=0,"OK","Abweichung")
B34: Gleicher Budget-Kurs | E34: ==IF(ROUND($H$4,4)=ROUND(IFERROR($O$12/$P$12,0),4),"OK","Abweichung")
B35: Einnahmen: Jahre = Gesamt (LC) | E35: ==IF(ROUND(($F$15+$G$15+$H$15)-$E$15,2)=0,"OK","Abweichung")
B36: Ausgaben: Jahre = Gesamt (LC) | E36: ==IF(ROUND(($F$29+$G$29+$H$29)-$O$12,2)=0,"OK","Abweichung")

Sheet II. KMW-Mittel
Z1: Periode 1
B2: II. KMW-MITTEL BEREITGESTELLT | Z2: Periode 2
Z3: Periode 3
B4: Periode | C4: Waehrung | D4: Betrag | E4: Datum | Z4: Periode 4
B5: Periode 1 | C5: EUR | D5: 10000 | E5: 45672 | Z5: Periode 5
B6: Periode 1 | C6: EUR | D6: 8000 | E6: 45762 | Z6: Periode 6
B7: Periode 2 | C7: EUR | D7: 9000 | E7: 45853 | Z7: Periode 7
Z8: Periode 8
Z9: Periode 9
Z10: Periode 10
Z11: Periode 11
Z12: Periode 12
Z13: Periode 13
Z14: Periode 14
Z15: Periode 15
Z16: Periode 16
Z17: Periode 17
Z18: Periode 18
Z19: Periode 19
... Z22: Periode 22
B23: GESAMT | D23: ==SUBTOTAL(109,TblKMWMittel[Betrag]) | Z23: Periode 23
Z24: Periode 24
Z25: Periode 25
Z26: Periode 26
Z27: Periode 27
Z28: Periode 28
Z29: Periode 29
Z30: Periode 30
Z31: Periode 31
Z32: Periode 32
Z33: Periode 33
Z34: Periode 34
Z35: Periode 35
Z36: Periode 36

Sheet III. Finanzberichte
H3: ➤ | O3: ➤ | V3: ➤ | AC3: ➤ | AJ3: ➤ | AQ3: ➤ | AX3: ➤ | BE3: ➤ | BL3: ➤ | BS3: ➤ | BZ3: ➤ | CG3: ➤ | CN3: ➤ | CU3: ➤ | DB3: ➤ | DI3: ➤ | DP3: ➤
B4: Periode: | C4: Periode 1 | I4: Periode: | J4: Periode 2 | P4: Periode: | Q4: Periode 3 | W4: Periode: | X4: Periode 4 | AD4: Periode: | AE4: Periode 5 | AK4: Periode: | AL4: Periode 6 | AR4: Periode: | AS4: Periode 7 | AY4: Periode: | AZ4: Periode 8 | BF4: Periode: | BG4: Periode 9 | BM4: Periode: | BN4: Periode 10 | BT4: Periode: | BU4: Periode 11 | CA4: Periode: | CB4: Periode 12 | CH4: Periode: | CI4: Periode 13 | CO4: Periode: | CP4: Periode 14 | CV4: Periode: | CW4: Periode 15 | DC4: Periode: | DD4: Periode 16 | DJ4: Periode: | DK4: Periode 17 | DQ4: Periode: | DR4: Periode 18
B5: Von: | C5: 45658 | I5: Von: | J5: 45839 | P5: Von: | W5: Von: | AD5: Von: | AK5: Von: | AR5: Von: | AY5: Von: | BF5: Von: | BM5: Von: | BT5: Von: | CA5: Von: | CH5: Von: | CO5: Von: | CV5: Von: | DC5: Von: | DJ5: Von: | DQ5: Von:
B6: Bis: | C6: 45838 | I6: Bis: | J6: 46022 | P6: Bis: | W6: Bis: | AD6: Bis: | AK6: Bis: | AR6: Bis: | AY6: Bis: | BF6: Bis: | BM6: Bis: | BT6: Bis: | CA6: Bis: | CH6: Bis: | CO6: Bis: | CV6: Bis: | DC6: Bis: | DJ6: Bis: | DQ6: Bis:
B7: Zeitraum: | C7: ==IF(OR(C5="",C6=""),"",DATEDIF(C5,C6,"m")+1) -> 158 | I7: Zeitraum: | J7: ==IF(OR(J5="",J6=""),"",DATEDIF(J5,J6,"m")+1) -> 158 | P7: Zeitraum: | Q7: ==IF(OR(Q5="",Q6=""),"",DATEDIF(Q5,Q6,"m")+1) -> 158 | W7: Zeitraum: | X7: ==IF(OR(X5="",X6=""),"",DATEDIF(X5,X6,"m")+1) -> 158 | AD7: Zeitraum: | AE7: ==IF(OR(AE5="",AE6=""),"",DATEDIF(AE5,AE6,"m")+1) -> 158 | AK7: Zeitraum: | AL7: ==IF(OR(AL5="",AL6=""),"",DATEDIF(AL5,AL6,"m")+1) -> 158 | AR7: Zeitraum: | AS7: ==IF(OR(AS5="",AS6=""),"",DATEDIF(AS5,AS6,"m")+1) -> 158 | AY7: Zeitraum: | AZ7: ==IF(OR(AZ5="",AZ6=""),"",DATEDIF(AZ5,AZ6,"m")+1) -> 158 | BF7: Zeitraum: | BG7: ==IF(OR(BG5="",BG6=""),"",DATEDIF(BG5,BG6,"m")+1) -> 158 | BM7: Zeitraum: | BN7: ==IF(OR(BN5="",BN6=""),"",DATEDIF(BN5,BN6,"m")+1) -> 158 | BT7: Zeitraum: | BU7: ==IF(OR(BU5="",BU6=""),"",DATEDIF(BU5,BU6,"m")+1) -> 158 | CA7: Zeitraum: | CB7: ==IF(OR(CB5="",CB6=""),"",DATEDIF(CB5,CB6,"m")+1) -> 158 | CH7: Zeitraum: | CI7: ==IF(OR(CI5="",CI6=""),"",DATEDIF(CI5,CI6,"m")+1) -> 158 | CO7: Zeitraum: | CP7: ==IF(OR(CP5="",CP6=""),"",DATEDIF(CP5,CP6,"m")+1) -> 158 | CV7: Zeitraum: | CW7: ==IF(OR(CW5="",CW6=""),"",DATEDIF(CW5,CW6,"m")+1) -> 158 | DC7: Zeitraum: | DD7: ==IF(OR(DD5="",DD6=""),"",DATEDIF(DD5,DD6,"m")+1) -> 158 | DJ7: Zeitraum: | DK7: ==IF(OR(DK5="",DK6=""),"",DATEDIF(DK5,DK6,"m")+1) -> 158 | DQ7: Zeitraum: | DR7: ==IF(OR(DR5="",DR6=""),"",DATEDIF(DR5,DR6,"m")+1) -> 158
B8: Durchschnittskurs: | C8: ==ROUND(IFERROR(F48,0),6) -> 158 | I8: Durchschnittskurs: | J8: ==ROUND(IFERROR(M48,0),6) -> 158 | P8: Durchschnittskurs: | Q8: ==ROUND(IFERROR(T48,0),6) -> 158 | W8: Durchschnittskurs: | X8: ==ROUND(IFERROR(AA48,0),6) -> 158 | AD8: Durchschnittskurs: | AE8: ==ROUND(IFERROR(AH48,0),6) -> 158 | AK8: Durchschnittskurs: | AL8: ==ROUND(IFERROR(AO48,0),6) -> 158 | AR8: Durchschnittskurs: | AS8: ==ROUND(IFERROR(AV48,0),6) -> 158 | AY8: Durchschnittskurs: | AZ8: ==ROUND(IFERROR(BC48,0),6) -> 158 | BF8: Durchschnittskurs: | BG8: ==ROUND(IFERROR(BJ48,0),6) -> 158 | BM8: Durchschnittskurs: | BN8: ==ROUND(IFERROR(BQ48,0),6) -> 158 | BT8: Durchschnittskurs: | BU8: ==ROUND(IFERROR(BX48,0),6) -> 158 | CA8: Durchschnittskurs: | CB8: ==ROUND(IFERROR(CE48,0),6) -> 158 | CH8: Durchschnittskurs: | CI8: ==ROUND(IFERROR(CL48,0),6) -> 158 | CO8: Durchschnittskurs: | CP8: ==ROUND(IFERROR(CS48,0),6) -> 158 | CV8: Durchschnittskurs: | CW8: ==ROUND(IFERROR(CZ48,0),6) -> 158 | DC8: Durchschnittskurs: | DD8: ==ROUND(IFERROR(DG48,0),6) -> 158 | DJ8: Durchschnittskurs: | DK8: ==ROUND(IFERROR(DN48,0),6) -> 158 | DQ8: Durchschnittskurs: | DR8: ==ROUND(IFERROR(DU48,0),6) -> 158
B9: Einnahmen | I9: Einnahmen | P9: Einnahmen | W9: Einnahmen | AD9: Einnahmen | AK9: Einnahmen | AR9: Einnahmen | AY9: Einnahmen | BF9: Einnahmen | BM9: Einnahmen | BT9: Einnahmen | CA9: Einnahmen | CH9: Einnahmen | CO9: Einnahmen | CV9: Einnahmen | DC9: Einnahmen | DJ9: Einnahmen | DQ9: Einnahmen
B10: Typ / ID | C10: Einnahmen (LC) | D10: Einnahmen (EUR) | E10: Kum. Einnahmen (LC) | F10: Kum. Einnahmen (EUR) | I10: Typ / ID | J10: Einnahmen (LC) | K10: Einnahmen (EUR) | L10: Kum. Einnahmen (LC) | M10: Kum. Einnahmen (EUR) | P10: Typ / ID | Q10: Einnahmen (LC) | R10: Einnahmen (EUR) | S10: Kum. Einnahmen (LC) | T10: Kum. Einnahmen (EUR) | W10: Typ / ID | X10: Einnahmen (LC) | Y10: Einnahmen (EUR) | Z10: Kum. Einnahmen (LC) | AA10: Kum. Einnahmen (EUR) | AD10: Typ / ID | AE10: Einnahmen (LC) | AF10: Einnahmen (EUR) | AG10: Kum. Einnahmen (LC) | AH10: Kum. Einnahmen (EUR) | AK10: Typ / ID | AL10: Einnahmen (LC) | AM10: Einnahmen (EUR) | AN10: Kum. Einnahmen (LC) | AO10: Kum. Einnahmen (EUR) | AR10: Typ / ID | AS10: Einnahmen (LC) | AT10: Einnahmen (EUR) | AU10: Kum. Einnahmen (LC) | AV10: Kum. Einnahmen (EUR) | AY10: Typ / ID | AZ10: Einnahmen (LC) | BA10: Einnahmen (EUR) | BB10: Kum. Einnahmen (LC) | BC10: Kum. Einnahmen (EUR) | BF10: Typ / ID | BG10: Einnahmen (LC) | BH10: Einnahmen (EUR) | BI10: Kum. Einnahmen (LC) | BJ10: Kum. Einnahmen (EUR) | BM10: Typ / ID | BN10: Einnahmen (LC) | BO10: Einnahmen (EUR) | BP10: Kum. Einnahmen (LC) | BQ10: Kum. Einnahmen (EUR) | BT10: Typ / ID | BU10: Einnahmen (LC) | BV10: Einnahmen (EUR) | BW10: Kum. Einnahmen (LC) | BX10: Kum. Einnahmen (EUR) | CA10: Typ / ID | CB10: Einnahmen (LC) | CC10: Einnahmen (EUR) | CD10: Kum. Einnahmen (LC) | CE10: Kum. Einnahmen (EUR) | CH10: Typ / ID | CI10: Einnahmen (LC) | CJ10: Einnahmen (EUR) | CK10: Kum. Einnahmen (LC) | CL10: Kum. Einnahmen (EUR) | CO10: Typ / ID | CP10: Einnahmen (LC) | CQ10: Einnahmen (EUR) | CR10: Kum. Einnahmen (LC) | CS10: Kum. Einnahmen (EUR) | CV10: Typ / ID | CW10: Einnahmen (LC) | CX10: Einnahmen (EUR) | CY10: Kum. Einnahmen (LC) | CZ10: Kum. Einnahmen (EUR) | DC10: Typ / ID | DD10: Einnahmen (LC) | DE10: Einnahmen (EUR) | DF10: Kum. Einnahmen (LC) | DG10: Kum. Einnahmen (EUR) | DJ10: Typ / ID | DK10: Einnahmen (LC) | DL10: Einnahmen (EUR) | DM10: Kum. Einnahmen (LC) | DN10: Kum. Einnahmen (EUR) | DQ10: Typ / ID | DR10: Einnahmen (LC) | DS10: Einnahmen (EUR) | DT10: Kum. Einnahmen (LC) | DU10: Kum. Einnahmen (EUR)
B11: Vorprojektsaldo | C11: ==ROUND(IF(Saldovortrag_LW="",0,Saldovortrag_LW),2) | D11: ==ROUND(IF(Saldovortrag_EUR="",0,Saldovortrag_EUR),2) | E11: ==ROUND(IF(Saldovortrag_LW="",0,Saldovortrag_LW),2) | F11: ==ROUND(IF(Saldovortrag_EUR="",0,Saldovortrag_EUR),2) | I11: Vorperiodensaldo | J11: ==ROUND(FB_SaldoLC_1,2) | K11: ==ROUND(FB_SaldoEUR_1,2) | L11: ==ROUND(FB_SaldoLC_1,2) | M11: ==ROUND(FB_SaldoEUR_1,2) | P11: Vorperiodensaldo | Q11: ==ROUND(FB_SaldoLC_2,2) | R11: ==ROUND(FB_SaldoEUR_2,2) | S11: ==ROUND(FB_SaldoLC_2,2) | T11: ==ROUND(FB_SaldoEUR_2,2) | W11: Vorperiodensaldo | X11: ==ROUND(FB_SaldoLC_3,2) | Y11: ==ROUND(FB_SaldoEUR_3,2) | Z11: ==ROUND(FB_SaldoLC_3,2) | AA11: ==ROUND(FB_SaldoEUR_3,2) | AD11: Vorperiodensaldo | AE11: ==ROUND(FB_SaldoLC_4,2) | AF11: ==ROUND(FB_SaldoEUR_4,2) | AG11: ==ROUND(FB_SaldoLC_4,2) | AH11: ==ROUND(FB_SaldoEUR_4,2) | AK11: Vorperiodensaldo | AL11: ==ROUND(FB_SaldoLC_5,2) | AM11: ==ROUND(FB_SaldoEUR_5,2) | AN11: ==ROUND(FB_SaldoLC_5,2) | AO11: ==ROUND(FB_SaldoEUR_5,2) | AR11: Vorperiodensaldo | AS11: ==ROUND(FB_SaldoLC_6,2) | AT11: ==ROUND(FB_SaldoEUR_6,2) | AU11: ==ROUND(FB_SaldoLC_6,2) | AV11: ==ROUND(FB_SaldoEUR_6,2) | AY11: Vorperiodensaldo | AZ11: ==ROUND(FB_SaldoLC_7,2) | BA11: ==ROUND(FB_SaldoEUR_7,2) | BB11: ==ROUND(FB_SaldoLC_7,2) | BC11: ==ROUND(FB_SaldoEUR_7,2) | BF11: Vorperiodensaldo | BG11: ==ROUND(FB_SaldoLC_8,2) | BH11: ==ROUND(FB_SaldoEUR_8,2) | BI11: ==ROUND(FB_SaldoLC_8,2) | BJ11: ==ROUND(FB_SaldoEUR_8,2) | BM11: Vorperiodensaldo | BN11: ==ROUND(FB_SaldoLC_9,2) | BO11: ==ROUND(FB_SaldoEUR_9,2) | BP11: ==ROUND(FB_SaldoLC_9,2) | BQ11: ==ROUND(FB_SaldoEUR_9,2) | BT11: Vorperiodensaldo | BU11: ==ROUND(FB_SaldoLC_10,2) | BV11: ==ROUND(FB_SaldoEUR_10,2) | BW11: ==ROUND(FB_SaldoLC_10,2) | BX11: ==ROUND(FB_SaldoEUR_10,2) | CA11: Vorperiodensaldo | CB11: ==ROUND(FB_SaldoLC_11,2) | CC11: ==ROUND(FB_SaldoEUR_11,2) | CD11: ==ROUND(FB_SaldoLC_11,2) | CE11: ==ROUND(FB_SaldoEUR_11,2) | CH11: Vorperiodensaldo | CI11: ==ROUND(FB_SaldoLC_12,2) | CJ11: ==ROUND(FB_SaldoEUR_12,2) | CK11: ==ROUND(FB_SaldoLC_12,2) | CL11: ==ROUND(FB_SaldoEUR_12,2) | CO11: Vorperiodensaldo | CP11: ==ROUND(FB_SaldoLC_13,2) | CQ11: ==ROUND(FB_SaldoEUR_13,2) | CR11: ==ROUND(FB_SaldoLC_13,2) | CS11: ==ROUND(FB_SaldoEUR_13,2) | CV11: Vorperiodensaldo | CW11: ==ROUND(FB_SaldoLC_14,2) | CX11: ==ROUND(FB_SaldoEUR_14,2) | CY11: ==ROUND(FB_SaldoLC_14,2) | CZ11: ==ROUND(FB_SaldoEUR_14,2) | DC11: Vorperiodensaldo | DD11: ==ROUND(FB_SaldoLC_15,2) | DE11: ==ROUND(FB_SaldoEUR_15,2) | DF11: ==ROUND(FB_SaldoLC_15,2) | DG11: ==ROUND(FB_SaldoEUR_15,2) | DJ11: Vorperiodensaldo | DK11: ==ROUND(FB_SaldoLC_16,2) | DL11: ==ROUND(FB_SaldoEUR_16,2) | DM11: ==ROUND(FB_SaldoLC_16,2) | DN11: ==ROUND(FB_SaldoEUR_16,2) | DQ11: Vorperiodensaldo | DR11: ==ROUND(FB_SaldoLC_17,2) | DS11: ==ROUND(FB_SaldoEUR_17,2) | DT11: ==ROUND(FB_SaldoLC_17,2) | DU11: ==ROUND(FB_SaldoEUR_17,2)
B12: Eigenmittel | C12: ==ROUND(SUMIF($B$43:$B$47,"Eigenmittel",$D$43:$D$47)+SUMIF($B$52:$B$57,"Eigenmittel",$D$52:$D$57),2) | D12: ==ROUND(SUMIF($B$43:$B$47,"Eigenmittel",$E$43:$E$47)+SUMIF($B$52:$B$57,"Eigenmittel",$E$52:$E$57),2) | E12: ==ROUND(SUMIF($B$43:$B$47,"Eigenmittel",$D$43:$D$47)+SUMIF($B$52:$B$57,"Eigenmittel",$D$52:$D$57),2) | F12: ==ROUND(SUMIF($B$43:$B$47,"Eigenmittel",$E$43:$E$47)+SUMIF($B$52:$B$57,"Eigenmittel",$E$52:$E$57),2) | I12: Eigenmittel | J12: ==ROUND(SUMIF($I$43:$I$47,"Eigenmittel",$K$43:$K$47)+SUMIF($I$52:$I$57,"Eigenmittel",$K$52:$K$57),2) | K12: ==ROUND(SUMIF($I$43:$I$47,"Eigenmittel",$L$43:$L$47)+SUMIF($I$52:$I$57,"Eigenmittel",$L$52:$L$57),2) | L12: ==IFERROR(ROUND(E12 + J12, 2), J12) | M12: ==IFERROR(ROUND(F12 + K12, 2), K12) | P12: Eigenmittel | Q12: ==ROUND(SUMIF($P$43:$P$47,"Eigenmittel",$R$43:$R$47)+SUMIF($P$52:$P$57,"Eigenmittel",$R$52:$R$57),2) | R12: ==ROUND(SUMIF($P$43:$P$47,"Eigenmittel",$S$43:$S$47)+SUMIF($P$52:$P$57,"Eigenmittel",$S$52:$S$57),2) | S12: ==IFERROR(ROUND(L12 + Q12, 2), Q12) | T12: ==IFERROR(ROUND(M12 + R12, 2), R12) | W12: Eigenmittel | X12: ==ROUND(SUMIF($W$43:$W$47,"Eigenmittel",$Y$43:$Y$47)+SUMIF($W$52:$W$57,"Eigenmittel",$Y$52:$Y$57),2) | Y12: ==ROUND(SUMIF($W$43:$W$47,"Eigenmittel",$Z$43:$Z$47)+SUMIF($W$52:$W$57,"Eigenmittel",$Z$52:$Z$57),2) | Z12: ==IFERROR(ROUND(S12 + X12, 2), X12) | AA12: ==IFERROR(ROUND(T12 + Y12, 2), Y12) | AD12: Eigenmittel | AE12: ==ROUND(SUMIF($AD$43:$AD$47,"Eigenmittel",$AF$43:$AF$47)+SUMIF($AD$52:$AD$57,"Eigenmittel",$AF$52:$AF$57),2) | AF12: ==ROUND(SUMIF($AD$43:$AD$47,"Eigenmittel",$AG$43:$AG$47)+SUMIF($AD$52:$AD$57,"Eigenmittel",$AG$52:$AG$57),2) | AG12: ==IFERROR(ROUND(Z12 + AE12, 2), AE12) | AH12: ==IFERROR(ROUND(AA12 + AF12, 2), AF12) | AK12: Eigenmittel | AL12: ==ROUND(SUMIF($AK$43:$AK$47,"Eigenmittel",$AM$43:$AM$47)+SUMIF($AK$52:$AK$57,"Eigenmittel",$AM$52:$AM$57),2) | AM12: ==ROUND(SUMIF($AK$43:$AK$47,"Eigenmittel",$AN$43:$AN$47)+SUMIF($AK$52:$AK$57,"Eigenmittel",$AN$52:$AN$57),2) | AN12: ==IFERROR(ROUND(AG12 + AL12, 2), AL12) | AO12: ==IFERROR(ROUND(AH12 + AM12, 2), AM12) | AR12: Eigenmittel | AS12: ==ROUND(SUMIF($AR$43:$AR$47,"Eigenmittel",$AT$43:$AT$47)+SUMIF($AR$52:$AR$57,"Eigenmittel",$AT$52:$AT$57),2) | AT12: ==ROUND(SUMIF($AR$43:$AR$47,"Eigenmittel",$AU$43:$AU$47)+SUMIF($AR$52:$AR$57,"Eigenmittel",$AU$52:$AU$57),2) | AU12: ==IFERROR(ROUND(AN12 + AS12, 2), AS12) | AV12: ==IFERROR(ROUND(AO12 + AT12, 2), AT12) | AY12: Eigenmittel | AZ12: ==ROUND(SUMIF($AY$43:$AY$47,"Eigenmittel",$BA$43:$BA$47)+SUMIF($AY$52:$AY$57,"Eigenmittel",$BA$52:$BA$57),2) | BA12: ==ROUND(SUMIF($AY$43:$AY$47,"Eigenmittel",$BB$43:$BB$47)+SUMIF($AY$52:$AY$57,"Eigenmittel",$BB$52:$BB$57),2) | BB12: ==IFERROR(ROUND(AU12 + AZ12, 2), AZ12) | BC12: ==IFERROR(ROUND(AV12 + BA12, 2), BA12) | BF12: Eigenmittel | BG12: ==ROUND(SUMIF($BF$43:$BF$47,"Eigenmittel",$BH$43:$BH$47)+SUMIF($BF$52:$BF$57,"Eigenmittel",$BH$52:$BH$57),2) | BH12: ==ROUND(SUMIF($BF$43:$BF$47,"Eigenmittel",$BI$43:$BI$47)+SUMIF($BF$52:$BF$57,"Eigenmittel",$BI$52:$BI$57),2) | BI12: ==IFERROR(ROUND(BB12 + BG12, 2), BG12) | BJ12: ==IFERROR(ROUND(BC12 + BH12, 2), BH12) | BM12: Eigenmittel | BN12: ==ROUND(SUMIF($BM$43:$BM$47,"Eigenmittel",$BO$43:$BO$47)+SUMIF($BM$52:$BM$57,"Eigenmittel",$BO$52:$BO$57),2) | BO12: ==ROUND(SUMIF($BM$43:$BM$47,"Eigenmittel",$BP$43:$BP$47)+SUMIF($BM$52:$BM$57,"Eigenmittel",$BP$52:$BP$57),2) | BP12: ==IFERROR(ROUND(BI12 + BN12, 2), BN12) | BQ12: ==IFERROR(ROUND(BJ12 + BO12, 2), BO12) | BT12: Eigenmittel | BU12: ==ROUND(SUMIF($BT$43:$BT$47,"Eigenmittel",$BV$43:$BV$47)+SUMIF($BT$52:$BT$57,"Eigenmittel",$BV$52:$BV$57),2) | BV12: ==ROUND(SUMIF($BT$43:$BT$47,"Eigenmittel",$BW$43:$BW$47)+SUMIF($BT$52:$BT$57,"Eigenmittel",$BW$52:$BW$57),2) | BW12: ==IFERROR(ROUND(BP12 + BU12, 2), BU12) | BX12: ==IFERROR(ROUND(BQ12 + BV12, 2), BV12) | CA12: Eigenmittel | CB12: ==ROUND(SUMIF($CA$43:$CA$47,"Eigenmittel",$CC$43:$CC$47)+SUMIF($CA$52:$CA$57,"Eigenmittel",$CC$52:$CC$57),2) | CC12: ==ROUND(SUMIF($CA$43:$CA$47,"Eigenmittel",$CD$43:$CD$47)+SUMIF($CA$52:$CA$57,"Eigenmittel",$CD$52:$CD$57),2) | CD12: ==IFERROR(ROUND(BW12 + CB12, 2), CB12) | CE12: ==IFERROR(ROUND(BX12 + CC12, 2), CC12) | CH12: Eigenmittel | CI12: ==ROUND(SUMIF($CH$43:$CH$47,"Eigenmittel",$CJ$43:$CJ$47)+SUMIF($CH$52:$CH$57,"Eigenmittel",$CJ$52:$CJ$57),2) | CJ12: ==ROUND(SUMIF($CH$43:$CH$47,"Eigenmittel",$CK$43:$CK$47)+SUMIF($CH$52:$CH$57,"Eigenmittel",$CK$52:$CK$57),2) | CK12: ==IFERROR(ROUND(CD12 + CI12, 2), CI12) | CL12: ==IFERROR(ROUND(CE12 + CJ12, 2), CJ12) | CO12: Eigenmittel | CP12: ==ROUND(SUMIF($CO$43:$CO$47,"Eigenmittel",$CQ$43:$CQ$47)+SUMIF($CO$52:$CO$57,"Eigenmittel",$CQ$52:$CQ$57),2) | CQ12: ==ROUND(SUMIF($CO$43:$CO$47,"Eigenmittel",$CR$43:$CR$47)+SUMIF($CO$52:$CO$57,"Eigenmittel",$CR$52:$CR$57),2) | CR12: ==IFERROR(ROUND(CK12 + CP12, 2), CP12) | CS12: ==IFERROR(ROUND(CL12 + CQ12, 2), CQ12) | CV12: Eigenmittel | CW12: ==ROUND(SUMIF($CV$43:$CV$47,"Eigenmittel",$CX$43:$CX$47)+SUMIF($CV$52:$CV$57,"Eigenmittel",$CX$52:$CX$57),2) | CX12: ==ROUND(SUMIF($CV$43:$CV$47,"Eigenmittel",$CY$43:$CY$47)+SUMIF($CV$52:$CV$57,"Eigenmittel",$CY$52:$CY$57),2) | CY12: ==IFERROR(ROUND(CR12 + CW12, 2), CW12) | CZ12: ==IFERROR(ROUND(CS12 + CX12, 2), CX12) | DC12: Eigenmittel | DD12: ==ROUND(SUMIF($DC$43:$DC$47,"Eigenmittel",$DE$43:$DE$47)+SUMIF($DC$52:$DC$57,"Eigenmittel",$DE$52:$DE$57),2) | DE12: ==ROUND(SUMIF($DC$43:$DC$47,"Eigenmittel",$DF$43:$DF$47)+SUMIF($DC$52:$DC$57,"Eigenmittel",$DF$52:$DF$57),2) | DF12: ==IFERROR(ROUND(CY12 + DD12, 2), DD12) | DG12: ==IFERROR(ROUND(CZ12 + DE12, 2), DE12) | DJ12: Eigenmittel | DK12: ==ROUND(SUMIF($DJ$43:$DJ$47,"Eigenmittel",$DL$43:$DL$47)+SUMIF($DJ$52:$DJ$57,"Eigenmittel",$DL$52:$DL$57),2) | DL12: ==ROUND(SUMIF($DJ$43:$DJ$47,"Eigenmittel",$DM$43:$DM$47)+SUMIF($DJ$52:$DJ$57,"Eigenmittel",$DM$52:$DM$57),2) | DM12: ==IFERROR(ROUND(DF12 + DK12, 2), DK12) | DN12: ==IFERROR(ROUND(DG12 + DL12, 2), DL12) | DQ12: Eigenmittel | DR12: ==ROUND(SUMIF($DQ$43:$DQ$47,"Eigenmittel",$DS$43:$DS$47)+SUMIF($DQ$52:$DQ$57,"Eigenmittel",$DS$52:$DS$57),2) | DS12: ==ROUND(SUMIF($DQ$43:$DQ$47,"Eigenmittel",$DT$43:$DT$47)+SUMIF($DQ$52:$DQ$57,"Eigenmittel",$DT$52:$DT$57),2) | DT12: ==IFERROR(ROUND(DM12 + DR12, 2), DR12) | DU12: ==IFERROR(ROUND(DN12 + DS12, 2), DS12)
B13: Drittmittel | C13: ==ROUND(SUMIF($B$43:$B$47,"Drittmittel",$D$43:$D$47)+SUMIF($B$52:$B$57,"Drittmittel",$D$52:$D$57),2) | D13: ==ROUND(SUMIF($B$43:$B$47,"Drittmittel",$E$43:$E$47)+SUMIF($B$52:$B$57,"Drittmittel",$E$52:$E$57),2) | E13: ==ROUND(SUMIF($B$43:$B$47,"Drittmittel",$D$43:$D$47)+SUMIF($B$52:$B$57,"Drittmittel",$D$52:$D$57),2) | F13: ==ROUND(SUMIF($B$43:$B$47,"Drittmittel",$E$43:$E$47)+SUMIF($B$52:$B$57,"Drittmittel",$E$52:$E$57),2) | I13: Drittmittel | J13: ==ROUND(SUMIF($I$43:$I$47,"Drittmittel",$K$43:$K$47)+SUMIF($I$52:$I$57,"Drittmittel",$K$52:$K$57),2) | K13: ==ROUND(SUMIF($I$43:$I$47,"Drittmittel",$L$43:$L$47)+SUMIF($I$52:$I$57,"Drittmittel",$L$52:$L$57),2) | L13: ==IFERROR(ROUND(E13 + J13, 2), J13) | M13: ==IFERROR(ROUND(F13 + K13, 2), K13) | P13: Drittmittel | Q13: ==ROUND(SUMIF($P$43:$P$47,"Drittmittel",$R$43:$R$47)+SUMIF($P$52:$P$57,"Drittmittel",$R$52:$R$57),2) | R13: ==ROUND(SUMIF($P$43:$P$47,"Drittmittel",$S$43:$S$47)+SUMIF($P$52:$P$57,"Drittmittel",$S$52:$S$57),2) | S13: ==IFERROR(ROUND(L13 + Q13, 2), Q13) | T13: ==IFERROR(ROUND(M13 + R13, 2), R13) | W13: Drittmittel | X13: ==ROUND(SUMIF($W$43:$W$47,"Drittmittel",$Y$43:$Y$47)+SUMIF($W$52:$W$57,"Drittmittel",$Y$52:$Y$57),2) | Y13: ==ROUND(SUMIF($W$43:$W$47,"Drittmittel",$Z$43:$Z$47)+SUMIF($W$52:$W$57,"Drittmittel",$Z$52:$Z$57),2) | Z13: ==IFERROR(ROUND(S13 + X13, 2), X13) | AA13: ==IFERROR(ROUND(T13 + Y13, 2), Y13) | AD13: Drittmittel | AE13: ==ROUND(SUMIF($AD$43:$AD$47,"Drittmittel",$AF$43:$AF$47)+SUMIF($AD$52:$AD$57,"Drittmittel",$AF$52:$AF$57),2) | AF13: ==ROUND(SUMIF($AD$43:$AD$47,"Drittmittel",$AG$43:$AG$47)+SUMIF($AD$52:$AD$57,"Drittmittel",$AG$52:$AG$57),2) | AG13: ==IFERROR(ROUND(Z13 + AE13, 2), AE13) | AH13: ==IFERROR(ROUND(AA13 + AF13, 2), AF13) | AK13: Drittmittel | AL13: ==ROUND(SUMIF($AK$43:$AK$47,"Drittmittel",$AM$43:$AM$47)+SUMIF($AK$52:$AK$57,"Drittmittel",$AM$52:$AM$57),2) | AM13: ==ROUND(SUMIF($AK$43:$AK$47,"Drittmittel",$AN$43:$AN$47)+SUMIF($AK$52:$AK$57,"Drittmittel",$AN$52:$AN$57),2) | AN13: ==IFERROR(ROUND(AG13 + AL13, 2), AL13) | AO13: ==IFERROR(ROUND(AH13 + AM13, 2), AM13) | AR13: Drittmittel | AS13: ==ROUND(SUMIF($AR$43:$AR$47,"Drittmittel",$AT$43:$AT$47)+SUMIF($AR$52:$AR$57,"Drittmittel",$AT$52:$AT$57),2) | AT13: ==ROUND(SUMIF($AR$43:$AR$47,"Drittmittel",$AU$43:$AU$47)+SUMIF($AR$52:$AR$57,"Drittmittel",$AU$52:$AU$57),2) | AU13: ==IFERROR(ROUND(AN13 + AS13, 2), AS13) | AV13: ==IFERROR(ROUND(AO13 + AT13, 2), AT13) | AY13: Drittmittel | AZ13: ==ROUND(SUMIF($AY$43:$AY$47,"Drittmittel",$BA$43:$BA$47)+SUMIF($AY$52:$AY$57,"Drittmittel",$BA$52:$BA$57),2) | BA13: ==ROUND(SUMIF($AY$43:$AY$47,"Drittmittel",$BB$43:$BB$47)+SUMIF($AY$52:$AY$57,"Drittmittel",$BB$52:$BB$57),2) | BB13: ==IFERROR(ROUND(AU13 + AZ13, 2), AZ13) | BC13: ==IFERROR(ROUND(AV13 + BA13, 2), BA13) | BF13: Drittmittel | BG13: ==ROUND(SUMIF($BF$43:$BF$47,"Drittmittel",$BH$43:$BH$47)+SUMIF($BF$52:$BF$57,"Drittmittel",$BH$52:$BH$57),2) | BH13: ==ROUND(SUMIF($BF$43:$BF$47,"Drittmittel",$BI$43:$BI$47)+SUMIF($BF$52:$BF$57,"Drittmittel",$BI$52:$BI$57),2) | BI13: ==IFERROR(ROUND(BB13 + BG13, 2), BG13) | BJ13: ==IFERROR(ROUND(BC13 + BH13, 2), BH13) | BM13: Drittmittel | BN13: ==ROUND(SUMIF($BM$43:$BM$47,"Drittmittel",$BO$43:$BO$47)+SUMIF($BM$52:$BM$57,"Drittmittel",$BO$52:$BO$57),2) | BO13: ==ROUND(SUMIF($BM$43:$BM$47,"Drittmittel",$BP$43:$BP$47)+SUMIF($BM$52:$BM$57,"Drittmittel",$BP$52:$BP$57),2) | BP13: ==IFERROR(ROUND(BI13 + BN13, 2), BN13) | BQ13: ==IFERROR(ROUND(BJ13 + BO13, 2), BO13) | BT13: Drittmittel | BU13: ==ROUND(SUMIF($BT$43:$BT$47,"Drittmittel",$BV$43:$BV$47)+SUMIF($BT$52:$BT$57,"Drittmittel",$BV$52:$BV$57),2) | BV13: ==ROUND(SUMIF($BT$43:$BT$47,"Drittmittel",$BW$43:$BW$47)+SUMIF($BT$52:$BT$57,"Drittmittel",$BW$52:$BW$57),2) | BW13: ==IFERROR(ROUND(BP13 + BU13, 2), BU13) | BX13: ==IFERROR(ROUND(BQ13 + BV13, 2), BV13) | CA13: Drittmittel | CB13: ==ROUND(SUMIF($CA$43:$CA$47,"Drittmittel",$CC$43:$CC$47)+SUMIF($CA$52:$CA$57,"Drittmittel",$CC$52:$CC$57),2) | CC13: ==ROUND(SUMIF($CA$43:$CA$47,"Drittmittel",$CD$43:$CD$47)+SUMIF($CA$52:$CA$57,"Drittmittel",$CD$52:$CD$57),2) | CD13: ==IFERROR(ROUND(BW13 + CB13, 2), CB13) | CE13: ==IFERROR(ROUND(BX13 + CC13, 2), CC13) | CH13: Drittmittel | CI13: ==ROUND(SUMIF($CH$43:$CH$47,"Drittmittel",$CJ$43:$CJ$47)+SUMIF($CH$52:$CH$57,"Drittmittel",$CJ$52:$CJ$57),2) | CJ13: ==ROUND(SUMIF($CH$43:$CH$47,"Drittmittel",$CK$43:$CK$47)+SUMIF($CH$52:$CH$57,"Drittmittel",$CK$52:$CK$57),2) | CK13: ==IFERROR(ROUND(CD13 + CI13, 2), CI13) | CL13: ==IFERROR(ROUND(CE13 + CJ13, 2), CJ13) | CO13: Drittmittel | CP13: ==ROUND(SUMIF($CO$43:$CO$47,"Drittmittel",$CQ$43:$CQ$47)+SUMIF($CO$52:$CO$57,"Drittmittel",$CQ$52:$CQ$57),2) | CQ13: ==ROUND(SUMIF($CO$43:$CO$47,"Drittmittel",$CR$43:$CR$47)+SUMIF($CO$52:$CO$57,"Drittmittel",$CR$52:$CR$57),2) | CR13: ==IFERROR(ROUND(CK13 + CP13, 2), CP13) | CS13: ==IFERROR(ROUND(CL13 + CQ13, 2), CQ13) | CV13: Drittmittel | CW13: ==ROUND(SUMIF($CV$43:$CV$47,"Drittmittel",$CX$43:$CX$47)+SUMIF($CV$52:$CV$57,"Drittmittel",$CX$52:$CX$57),2) | CX13: ==ROUND(SUMIF($CV$43:$CV$47,"Drittmittel",$CY$43:$CY$47)+SUMIF($CV$52:$CV$57,"Drittmittel",$CY$52:$CY$57),2) | CY13: ==IFERROR(ROUND(CR13 + CW13, 2), CW13) | CZ13: ==IFERROR(ROUND(CS13 + CX13, 2), CX13) | DC13: Drittmittel | DD13: ==ROUND(SUMIF($DC$43:$DC$47,"Drittmittel",$DE$43:$DE$47)+SUMIF($DC$52:$DC$57,"Drittmittel",$DE$52:$DE$57),2) | DE13: ==ROUND(SUMIF($DC$43:$DC$47,"Drittmittel",$DF$43:$DF$47)+SUMIF($DC$52:$DC$57,"Drittmittel",$DF$52:$DF$57),2) | DF13: ==IFERROR(ROUND(CY13 + DD13, 2), DD13) | DG13: ==IFERROR(ROUND(CZ13 + DE13, 2), DE13) | DJ13: Drittmittel | DK13: ==ROUND(SUMIF($DJ$43:$DJ$47,"Drittmittel",$DL$43:$DL$47)+SUMIF($DJ$52:$DJ$57,"Drittmittel",$DL$52:$DL$57),2) | DL13: ==ROUND(SUMIF($DJ$43:$DJ$47,"Drittmittel",$DM$43:$DM$47)+SUMIF($DJ$52:$DJ$57,"Drittmittel",$DM$52:$DM$57),2) | DM13: ==IFERROR(ROUND(DF13 + DK13, 2), DK13) | DN13: ==IFERROR(ROUND(DG13 + DL13, 2), DL13) | DQ13: Drittmittel | DR13: ==ROUND(SUMIF($DQ$43:$DQ$47,"Drittmittel",$DS$43:$DS$47)+SUMIF($DQ$52:$DQ$57,"Drittmittel",$DS$52:$DS$57),2) | DS13: ==ROUND(SUMIF($DQ$43:$DQ$47,"Drittmittel",$DT$43:$DT$47)+SUMIF($DQ$52:$DQ$57,"Drittmittel",$DT$52:$DT$57),2) | DT13: ==IFERROR(ROUND(DM13 + DR13, 2), DR13) | DU13: ==IFERROR(ROUND(DN13 + DS13, 2), DS13)
B14: KMW-Mittel | C14: ==ROUND(SUMIF($B$43:$B$47,"KMW-Mittel",$D$43:$D$47)+SUMIF($B$52:$B$57,"KMW-Mittel",$D$52:$D$57),2) | D14: ==ROUND(SUMIF($B$43:$B$47,"KMW-Mittel",$E$43:$E$47)+SUMIF($B$52:$B$57,"KMW-Mittel",$E$52:$E$57),2) | E14: ==ROUND(SUMIF($B$43:$B$47,"KMW-Mittel",$D$43:$D$47)+SUMIF($B$52:$B$57,"KMW-Mittel",$D$52:$D$57),2) | F14: ==ROUND(SUMIF($B$43:$B$47,"KMW-Mittel",$E$43:$E$47)+SUMIF($B$52:$B$57,"KMW-Mittel",$E$52:$E$57),2) | I14: KMW-Mittel | J14: ==ROUND(SUMIF($I$43:$I$47,"KMW-Mittel",$K$43:$K$47)+SUMIF($I$52:$I$57,"KMW-Mittel",$K$52:$K$57),2) | K14: ==ROUND(SUMIF($I$43:$I$47,"KMW-Mittel",$L$43:$L$47)+SUMIF($I$52:$I$57,"KMW-Mittel",$L$52:$L$57),2) | L14: ==IFERROR(ROUND(E14 + J14, 2), J14) | M14: ==IFERROR(ROUND(F14 + K14, 2), K14) | P14: KMW-Mittel | Q14: ==ROUND(SUMIF($P$43:$P$47,"KMW-Mittel",$R$43:$R$47)+SUMIF($P$52:$P$57,"KMW-Mittel",$R$52:$R$57),2) | R14: ==ROUND(SUMIF($P$43:$P$47,"KMW-Mittel",$S$43:$S$47)+SUMIF($P$52:$P$57,"KMW-Mittel",$S$52:$S$57),2) | S14: ==IFERROR(ROUND(L14 + Q14, 2), Q14) | T14: ==IFERROR(ROUND(M14 + R14, 2), R14) | W14: KMW-Mittel | X14: ==ROUND(SUMIF($W$43:$W$47,"KMW-Mittel",$Y$43:$Y$47)+SUMIF($W$52:$W$57,"KMW-Mittel",$Y$52:$Y$57),2) | Y14: ==ROUND(SUMIF($W$43:$W$47,"KMW-Mittel",$Z$43:$Z$47)+SUMIF($W$52:$W$57,"KMW-Mittel",$Z$52:$Z$57),2) | Z14: ==IFERROR(ROUND(S14 + X14, 2), X14) | AA14: ==IFERROR(ROUND(T14 + Y14, 2), Y14) | AD14: KMW-Mittel | AE14: ==ROUND(SUMIF($AD$43:$AD$47,"KMW-Mittel",$AF$43:$AF$47)+SUMIF($AD$52:$AD$57,"KMW-Mittel",$AF$52:$AF$57),2) | AF14: ==ROUND(SUMIF($AD$43:$AD$47,"KMW-Mittel",$AG$43:$AG$47)+SUMIF($AD$52:$AD$57,"KMW-Mittel",$AG$52:$AG$57),2) | AG14: ==IFERROR(ROUND(Z14 + AE14, 2), AE14) | AH14: ==IFERROR(ROUND(AA14 + AF14, 2), AF14) | AK14: KMW-Mittel | AL14: ==ROUND(SUMIF($AK$43:$AK$47,"KMW-Mittel",$AM$43:$AM$47)+SUMIF($AK$52:$AK$57,"KMW-Mittel",$AM$52:$AM$57),2) | AM14: ==ROUND(SUMIF($AK$43:$AK$47,"KMW-Mittel",$AN$43:$AN$47)+SUMIF($AK$52:$AK$57,"KMW-Mittel",$AN$52:$AN$57),2) | AN14: ==IFERROR(ROUND(AG14 + AL14, 2), AL14) | AO14: ==IFERROR(ROUND(AH14 + AM14, 2), AM14) | AR14: KMW-Mittel | AS14: ==ROUND(SUMIF($AR$43:$AR$47,"KMW-Mittel",$AT$43:$AT$47)+SUMIF($AR$52:$AR$57,"KMW-Mittel",$AT$52:$AT$57),2) | AT14: ==ROUND(SUMIF($AR$43:$AR$47,"KMW-Mittel",$AU$43:$AU$47)+SUMIF($AR$52:$AR$57,"KMW-Mittel",$AU$52:$AU$57),2) | AU14: ==IFERROR(ROUND(AN14 + AS14, 2), AS14) | AV14: ==IFERROR(ROUND(AO14 + AT14, 2), AT14) | AY14: KMW-Mittel | AZ14: ==ROUND(SUMIF($AY$43:$AY$47,"KMW-Mittel",$BA$43:$BA$47)+SUMIF($AY$52:$AY$57,"KMW-Mittel",$BA$52:$BA$57),2) | BA14: ==ROUND(SUMIF($AY$43:$AY$47,"KMW-Mittel",$BB$43:$BB$47)+SUMIF($AY$52:$AY$57,"KMW-Mittel",$BB$52:$BB$57),2) | BB14: ==IFERROR(ROUND(AU14 + AZ14, 2), AZ14) | BC14: ==IFERROR(ROUND(AV14 + BA14, 2), BA14) | BF14: KMW-Mittel | BG14: ==ROUND(SUMIF($BF$43:$BF$47,"KMW-Mittel",$BH$43:$BH$47)+SUMIF($BF$52:$BF$57,"KMW-Mittel",$BH$52:$BH$57),2) | BH14: ==ROUND(SUMIF($BF$43:$BF$47,"KMW-Mittel",$BI$43:$BI$47)+SUMIF($BF$52:$BF$57,"KMW-Mittel",$BI$52:$BI$57),2) | BI14: ==IFERROR(ROUND(BB14 + BG14, 2), BG14) | BJ14: ==IFERROR(ROUND(BC14 + BH14, 2), BH14) | BM14: KMW-Mittel | BN14: ==ROUND(SUMIF($BM$43:$BM$47,"KMW-Mittel",$BO$43:$BO$47)+SUMIF($BM$52:$BM$57,"KMW-Mittel",$BO$52:$BO$57),2) | BO14: ==ROUND(SUMIF($BM$43:$BM$47,"KMW-Mittel",$BP$43:$BP$47)+SUMIF($BM$52:$BM$57,"KMW-Mittel",$BP$52:$BP$57),2) | BP14: ==IFERROR(ROUND(BI14 + BN14, 2), BN14) | BQ14: ==IFERROR(ROUND(BJ14 + BO14, 2), BO14) | BT14: KMW-Mittel | BU14: ==ROUND(SUMIF($BT$43:$BT$47,"KMW-Mittel",$BV$43:$BV$47)+SUMIF($BT$52:$BT$57,"KMW-Mittel",$BV$52:$BV$57),2) | BV14: ==ROUND(SUMIF($BT$43:$BT$47,"KMW-Mittel",$BW$43:$BW$47)+SUMIF($BT$52:$BT$57,"KMW-Mittel",$BW$52:$BW$57),2) | BW14: ==IFERROR(ROUND(BP14 + BU14, 2), BU14) | BX14: ==IFERROR(ROUND(BQ14 + BV14, 2), BV14) | CA14: KMW-Mittel | CB14: ==ROUND(SUMIF($CA$43:$CA$47,"KMW-Mittel",$CC$43:$CC$47)+SUMIF($CA$52:$CA$57,"KMW-Mittel",$CC$52:$CC$57),2) | CC14: ==ROUND(SUMIF($CA$43:$CA$47,"KMW-Mittel",$CD$43:$CD$47)+SUMIF($CA$52:$CA$57,"KMW-Mittel",$CD$52:$CD$57),2) | CD14: ==IFERROR(ROUND(BW14 + CB14, 2), CB14) | CE14: ==IFERROR(ROUND(BX14 + CC14, 2), CC14) | CH14: KMW-Mittel | CI14: ==ROUND(SUMIF($CH$43:$CH$47,"KMW-Mittel",$CJ$43:$CJ$47)+SUMIF($CH$52:$CH$57,"KMW-Mittel",$CJ$52:$CJ$57),2) | CJ14: ==ROUND(SUMIF($CH$43:$CH$47,"KMW-Mittel",$CK$43:$CK$47)+SUMIF($CH$52:$CH$57,"KMW-Mittel",$CK$52:$CK$57),2) | CK14: ==IFERROR(ROUND(CD14 + CI14, 2), CI14) | CL14: ==IFERROR(ROUND(CE14 + CJ14, 2), CJ14) | CO14: KMW-Mittel | CP14: ==ROUND(SUMIF($CO$43:$CO$47,"KMW-Mittel",$CQ$43:$CQ$47)+SUMIF($CO$52:$CO$57,"KMW-Mittel",$CQ$52:$CQ$57),2) | CQ14: ==ROUND(SUMIF($CO$43:$CO$47,"KMW-Mittel",$CR$43:$CR$47)+SUMIF($CO$52:$CO$57,"KMW-Mittel",$CR$52:$CR$57),2) | CR14: ==IFERROR(ROUND(CK14 + CP14, 2), CP14) | CS14: ==IFERROR(ROUND(CL14 + CQ14, 2), CQ14) | CV14: KMW-Mittel | CW14: ==ROUND(SUMIF($CV$43:$CV$47,"KMW-Mittel",$CX$43:$CX$47)+SUMIF($CV$52:$CV$57,"KMW-Mittel",$CX$52:$CX$57),2) | CX14: ==ROUND(SUMIF($CV$43:$CV$47,"KMW-Mittel",$CY$43:$CY$47)+SUMIF($CV$52:$CV$57,"KMW-Mittel",$CY$52:$CY$57),2) | CY14: ==IFERROR(ROUND(CR14 + CW14, 2), CW14) | CZ14: ==IFERROR(ROUND(CS14 + CX14, 2), CX14) | DC14: KMW-Mittel | DD14: ==ROUND(SUMIF($DC$43:$DC$47,"KMW-Mittel",$DE$43:$DE$47)+SUMIF($DC$52:$DC$57,"KMW-Mittel",$DE$52:$DE$57),2) | DE14: ==ROUND(SUMIF($DC$43:$DC$47,"KMW-Mittel",$DF$43:$DF$47)+SUMIF($DC$52:$DC$57,"KMW-Mittel",$DF$52:$DF$57),2) | DF14: ==IFERROR(ROUND(CY14 + DD14, 2), DD14) | DG14: ==IFERROR(ROUND(CZ14 + DE14, 2), DE14) | DJ14: KMW-Mittel | DK14: ==ROUND(SUMIF($DJ$43:$DJ$47,"KMW-Mittel",$DL$43:$DL$47)+SUMIF($DJ$52:$DJ$57,"KMW-Mittel",$DL$52:$DL$57),2) | DL14: ==ROUND(SUMIF($DJ$43:$DJ$47,"KMW-Mittel",$DM$43:$DM$47)+SUMIF($DJ$52:$DJ$57,"KMW-Mittel",$DM$52:$DM$57),2) | DM14: ==IFERROR(ROUND(DF14 + DK14, 2), DK14) | DN14: ==IFERROR(ROUND(DG14 + DL14, 2), DL14) | DQ14: KMW-Mittel | DR14: ==ROUND(SUMIF($DQ$43:$DQ$47,"KMW-Mittel",$DS$43:$DS$47)+SUMIF($DQ$52:$DQ$57,"KMW-Mittel",$DS$52:$DS$57),2) | DS14: ==ROUND(SUMIF($DQ$43:$DQ$47,"KMW-Mittel",$DT$43:$DT$47)+SUMIF($DQ$52:$DQ$57,"KMW-Mittel",$DT$52:$DT$57),2) | DT14: ==IFERROR(ROUND(DM14 + DR14, 2), DR14) | DU14: ==IFERROR(ROUND(DN14 + DS14, 2), DS14)
B15: Zinsertraege | C15: ==ROUND(SUMIF($B$43:$B$47,"Zinsertraege",$D$43:$D$47)+SUMIF($B$52:$B$57,"Zinsertraege",$D$52:$D$57),2) | D15: ==ROUND(SUMIF($B$43:$B$47,"Zinsertraege",$E$43:$E$47)+SUMIF($B$52:$B$57,"Zinsertraege",$E$52:$E$57),2) | E15: ==ROUND(SUMIF($B$43:$B$47,"Zinsertraege",$D$43:$D$47)+SUMIF($B$52:$B$57,"Zinsertraege",$D$52:$D$57),2) | F15: ==ROUND(SUMIF($B$43:$B$47,"Zinsertraege",$E$43:$E$47)+SUMIF($B$52:$B$57,"Zinsertraege",$E$52:$E$57),2) | I15: Zinsertraege | J15: ==ROUND(SUMIF($I$43:$I$47,"Zinsertraege",$K$43:$K$47)+SUMIF($I$52:$I$57,"Zinsertraege",$K$52:$K$57),2) | K15: ==ROUND(SUMIF($I$43:$I$47,"Zinsertraege",$L$43:$L$47)+SUMIF($I$52:$I$57,"Zinsertraege",$L$52:$L$57),2) | L15: ==IFERROR(ROUND(E15 + J15, 2), J15) | M15: ==IFERROR(ROUND(F15 + K15, 2), K15) | P15: Zinsertraege | Q15: ==ROUND(SUMIF($P$43:$P$47,"Zinsertraege",$R$43:$R$47)+SUMIF($P$52:$P$57,"Zinsertraege",$R$52:$R$57),2) | R15: ==ROUND(SUMIF($P$43:$P$47,"Zinsertraege",$S$43:$S$47)+SUMIF($P$52:$P$57,"Zinsertraege",$S$52:$S$57),2) | S15: ==IFERROR(ROUND(L15 + Q15, 2), Q15) | T15: ==IFERROR(ROUND(M15 + R15, 2), R15) | W15: Zinsertraege | X15: ==ROUND(SUMIF($W$43:$W$47,"Zinsertraege",$Y$43:$Y$47)+SUMIF($W$52:$W$57,"Zinsertraege",$Y$52:$Y$57),2) | Y15: ==ROUND(SUMIF($W$43:$W$47,"Zinsertraege",$Z$43:$Z$47)+SUMIF($W$52:$W$57,"Zinsertraege",$Z$52:$Z$57),2) | Z15: ==IFERROR(ROUND(S15 + X15, 2), X15) | AA15: ==IFERROR(ROUND(T15 + Y15, 2), Y15) | AD15: Zinsertraege | AE15: ==ROUND(SUMIF($AD$43:$AD$47,"Zinsertraege",$AF$43:$AF$47)+SUMIF($AD$52:$AD$57,"Zinsertraege",$AF$52:$AF$57),2) | AF15: ==ROUND(SUMIF($AD$43:$AD$47,"Zinsertraege",$AG$43:$AG$47)+SUMIF($AD$52:$AD$57,"Zinsertraege",$AG$52:$AG$57),2) | AG15: ==IFERROR(ROUND(Z15 + AE15, 2), AE15) | AH15: ==IFERROR(ROUND(AA15 + AF15, 2), AF15) | AK15: Zinsertraege | AL15: ==ROUND(SUMIF($AK$43:$AK$47,"Zinsertraege",$AM$43:$AM$47)+SUMIF($AK$52:$AK$57,"Zinsertraege",$AM$52:$AM$57),2) | AM15: ==ROUND(SUMIF($AK$43:$AK$47,"Zinsertraege",$AN$43:$AN$47)+SUMIF($AK$52:$AK$57,"Zinsertraege",$AN$52:$AN$57),2) | AN15: ==IFERROR(ROUND(AG15 + AL15, 2), AL15) | AO15: ==IFERROR(ROUND(AH15 + AM15, 2), AM15) | AR15: Zinsertraege | AS15: ==ROUND(SUMIF($AR$43:$AR$47,"Zinsertraege",$AT$43:$AT$47)+SUMIF($AR$52:$AR$57,"Zinsertraege",$AT$52:$AT$57),2) | AT15: ==ROUND(SUMIF($AR$43:$AR$47,"Zinsertraege",$AU$43:$AU$47)+SUMIF($AR$52:$AR$57,"Zinsertraege",$AU$52:$AU$57),2) | AU15: ==IFERROR(ROUND(AN15 + AS15, 2), AS15) | AV15: ==IFERROR(ROUND(AO15 + AT15, 2), AT15) | AY15: Zinsertraege | AZ15: ==ROUND(SUMIF($AY$43:$AY$47,"Zinsertraege",$BA$43:$BA$47)+SUMIF($AY$52:$AY$57,"Zinsertraege",$BA$52:$BA$57),2) | BA15: ==ROUND(SUMIF($AY$43:$AY$47,"Zinsertraege",$BB$43:$BB$47)+SUMIF($AY$52:$AY$57,"Zinsertraege",$BB$52:$BB$57),2) | BB15: ==IFERROR(ROUND(AU15 + AZ15, 2), AZ15) | BC15: ==IFERROR(ROUND(AV15 + BA15, 2), BA15) | BF15: Zinsertraege | BG15: ==ROUND(SUMIF($BF$43:$BF$47,"Zinsertraege",$BH$43:$BH$47)+SUMIF($BF$52:$BF$57,"Zinsertraege",$BH$52:$BH$57),2) | BH15: ==ROUND(SUMIF($BF$43:$BF$47,"Zinsertraege",$BI$43:$BI$47)+SUMIF($BF$52:$BF$57,"Zinsertraege",$BI$52:$BI$57),2) | BI15: ==IFERROR(ROUND(BB15 + BG15, 2), BG15) | BJ15: ==IFERROR(ROUND(BC15 + BH15, 2), BH15) | BM15: Zinsertraege | BN15: ==ROUND(SUMIF($BM$43:$BM$47,"Zinsertraege",$BO$43:$BO$47)+SUMIF($BM$52:$BM$57,"Zinsertraege",$BO$52:$BO$57),2) | BO15: ==ROUND(SUMIF($BM$43:$BM$47,"Zinsertraege",$BP$43:$BP$47)+SUMIF($BM$52:$BM$57,"Zinsertraege",$BP$52:$BP$57),2) | BP15: ==IFERROR(ROUND(BI15 + BN15, 2), BN15) | BQ15: ==IFERROR(ROUND(BJ15 + BO15, 2), BO15) | BT15: Zinsertraege | BU15: ==ROUND(SUMIF($BT$43:$BT$47,"Zinsertraege",$BV$43:$BV$47)+SUMIF($BT$52:$BT$57,"Zinsertraege",$BV$52:$BV$57),2) | BV15: ==ROUND(SUMIF($BT$43:$BT$47,"Zinsertraege",$BW$43:$BW$47)+SUMIF($BT$52:$BT$57,"Zinsertraege",$BW$52:$BW$57),2) | BW15: ==IFERROR(ROUND(BP15 + BU15, 2), BU15) | BX15: ==IFERROR(ROUND(BQ15 + BV15, 2), BV15) | CA15: Zinsertraege | CB15: ==ROUND(SUMIF($CA$43:$CA$47,"Zinsertraege",$CC$43:$CC$47)+SUMIF($CA$52:$CA$57,"Zinsertraege",$CC$52:$CC$57),2) | CC15: ==ROUND(SUMIF($CA$43:$CA$47,"Zinsertraege",$CD$43:$CD$47)+SUMIF($CA$52:$CA$57,"Zinsertraege",$CD$52:$CD$57),2) | CD15: ==IFERROR(ROUND(BW15 + CB15, 2), CB15) | CE15: ==IFERROR(ROUND(BX15 + CC15, 2), CC15) | CH15: Zinsertraege | CI15: ==ROUND(SUMIF($CH$43:$CH$47,"Zinsertraege",$CJ$43:$CJ$47)+SUMIF($CH$52:$CH$57,"Zinsertraege",$CJ$52:$CJ$57),2) | CJ15: ==ROUND(SUMIF($CH$43:$CH$47,"Zinsertraege",$CK$43:$CK$47)+SUMIF($CH$52:$CH$57,"Zinsertraege",$CK$52:$CK$57),2) | CK15: ==IFERROR(ROUND(CD15 + CI15, 2), CI15) | CL15: ==IFERROR(ROUND(CE15 + CJ15, 2), CJ15) | CO15: Zinsertraege | CP15: ==ROUND(SUMIF($CO$43:$CO$47,"Zinsertraege",$CQ$43:$CQ$47)+SUMIF($CO$52:$CO$57,"Zinsertraege",$CQ$52:$CQ$57),2) | CQ15: ==ROUND(SUMIF($CO$43:$CO$47,"Zinsertraege",$CR$43:$CR$47)+SUMIF($CO$52:$CO$57,"Zinsertraege",$CR$52:$CR$57),2) | CR15: ==IFERROR(ROUND(CK15 + CP15, 2), CP15) | CS15: ==IFERROR(ROUND(CL15 + CQ15, 2), CQ15) | CV15: Zinsertraege | CW15: ==ROUND(SUMIF($CV$43:$CV$47,"Zinsertraege",$CX$43:$CX$47)+SUMIF($CV$52:$CV$57,"Zinsertraege",$CX$52:$CX$57),2) | CX15: ==ROUND(SUMIF($CV$43:$CV$47,"Zinsertraege",$CY$43:$CY$47)+SUMIF($CV$52:$CV$57,"Zinsertraege",$CY$52:$CY$57),2) | CY15: ==IFERROR(ROUND(CR15 + CW15, 2), CW15) | CZ15: ==IFERROR(ROUND(CS15 + CX15, 2), CX15) | DC15: Zinsertraege | DD15: ==ROUND(SUMIF($DC$43:$DC$47,"Zinsertraege",$DE$43:$DE$47)+SUMIF($DC$52:$DC$57,"Zinsertraege",$DE$52:$DE$57),2) | DE15: ==ROUND(SUMIF($DC$43:$DC$47,"Zinsertraege",$DF$43:$DF$47)+SUMIF($DC$52:$DC$57,"Zinsertraege",$DF$52:$DF$57),2) | DF15: ==IFERROR(ROUND(CY15 + DD15, 2), DD15) | DG15: ==IFERROR(ROUND(CZ15 + DE15, 2), DE15) | DJ15: Zinsertraege | DK15: ==ROUND(SUMIF($DJ$43:$DJ$47,"Zinsertraege",$DL$43:$DL$47)+SUMIF($DJ$52:$DJ$57,"Zinsertraege",$DL$52:$DL$57),2) | DL15: ==ROUND(SUMIF($DJ$43:$DJ$47,"Zinsertraege",$DM$43:$DM$47)+SUMIF($DJ$52:$DJ$57,"Zinsertraege",$DM$52:$DM$57),2) | DM15: ==IFERROR(ROUND(DF15 + DK15, 2), DK15) | DN15: ==IFERROR(ROUND(DG15 + DL15, 2), DL15) | DQ15: Zinsertraege | DR15: ==ROUND(SUMIF($DQ$43:$DQ$47,"Zinsertraege",$DS$43:$DS$47)+SUMIF($DQ$52:$DQ$57,"Zinsertraege",$DS$52:$DS$57),2) | DS15: ==ROUND(SUMIF($DQ$43:$DQ$47,"Zinsertraege",$DT$43:$DT$47)+SUMIF($DQ$52:$DQ$57,"Zinsertraege",$DT$52:$DT$57),2) | DT15: ==IFERROR(ROUND(DM15 + DR15, 2), DR15) | DU15: ==IFERROR(ROUND(DN15 + DS15, 2), DS15)
B16: Gesamteinnahmen | C16: ==ROUND(SUM(C11:C15),2) | D16: ==ROUND(SUM(D11:D15),2) | E16: ==ROUND(SUM(E11:E15),2) | F16: ==ROUND(SUM(F11:F15),2) | I16: Gesamteinnahmen | J16: ==ROUND(SUM(J11:J15),2) | K16: ==ROUND(SUM(K11:K15),2) | L16: ==ROUND(SUM(L11:L15),2) | M16: ==ROUND(SUM(M11:M15),2) | P16: Gesamteinnahmen | Q16: ==ROUND(SUM(Q11:Q15),2) | R16: ==ROUND(SUM(R11:R15),2) | S16: ==ROUND(SUM(S11:S15),2) | T16: ==ROUND(SUM(T11:T15),2) | W16: Gesamteinnahmen | X16: ==ROUND(SUM(X11:X15),2) | Y16: ==ROUND(SUM(Y11:Y15),2) | Z16: ==ROUND(SUM(Z11:Z15),2) | AA16: ==ROUND(SUM(AA11:AA15),2) | AD16: Gesamteinnahmen | AE16: ==ROUND(SUM(AE11:AE15),2) | AF16: ==ROUND(SUM(AF11:AF15),2) | AG16: ==ROUND(SUM(AG11:AG15),2) | AH16: ==ROUND(SUM(AH11:AH15),2) | AK16: Gesamteinnahmen | AL16: ==ROUND(SUM(AL11:AL15),2) | AM16: ==ROUND(SUM(AM11:AM15),2) | AN16: ==ROUND(SUM(AN11:AN15),2) | AO16: ==ROUND(SUM(AO11:AO15),2) | AR16: Gesamteinnahmen | AS16: ==ROUND(SUM(AS11:AS15),2) | AT16: ==ROUND(SUM(AT11:AT15),2) | AU16: ==ROUND(SUM(AU11:AU15),2) | AV16: ==ROUND(SUM(AV11:AV15),2) | AY16: Gesamteinnahmen | AZ16: ==ROUND(SUM(AZ11:AZ15),2) | BA16: ==ROUND(SUM(BA11:BA15),2) | BB16: ==ROUND(SUM(BB11:BB15),2) | BC16: ==ROUND(SUM(BC11:BC15),2) | BF16: Gesamteinnahmen | BG16: ==ROUND(SUM(BG11:BG15),2) | BH16: ==ROUND(SUM(BH11:BH15),2) | BI16: ==ROUND(SUM(BI11:BI15),2) | BJ16: ==ROUND(SUM(BJ11:BJ15),2) | BM16: Gesamteinnahmen | BN16: ==ROUND(SUM(BN11:BN15),2) | BO16: ==ROUND(SUM(BO11:BO15),2) | BP16: ==ROUND(SUM(BP11:BP15),2) | BQ16: ==ROUND(SUM(BQ11:BQ15),2) | BT16: Gesamteinnahmen | BU16: ==ROUND(SUM(BU11:BU15),2) | BV16: ==ROUND(SUM(BV11:BV15),2) | BW16: ==ROUND(SUM(BW11:BW15),2) | BX16: ==ROUND(SUM(BX11:BX15),2) | CA16: Gesamteinnahmen | CB16: ==ROUND(SUM(CB11:CB15),2) | CC16: ==ROUND(SUM(CC11:CC15),2) | CD16: ==ROUND(SUM(CD11:CD15),2) | CE16: ==ROUND(SUM(CE11:CE15),2) | CH16: Gesamteinnahmen | CI16: ==ROUND(SUM(CI11:CI15),2) | CJ16: ==ROUND(SUM(CJ11:CJ15),2) | CK16: ==ROUND(SUM(CK11:CK15),2) | CL16: ==ROUND(SUM(CL11:CL15),2) | CO16: Gesamteinnahmen | CP16: ==ROUND(SUM(CP11:CP15),2) | CQ16: ==ROUND(SUM(CQ11:CQ15),2) | CR16: ==ROUND(SUM(CR11:CR15),2) | CS16: ==ROUND(SUM(CS11:CS15),2) | CV16: Gesamteinnahmen | CW16: ==ROUND(SUM(CW11:CW15),2) | CX16: ==ROUND(SUM(CX11:CX15),2) | CY16: ==ROUND(SUM(CY11:CY15),2) | CZ16: ==ROUND(SUM(CZ11:CZ15),2) | DC16: Gesamteinnahmen | DD16: ==ROUND(SUM(DD11:DD15),2) | DE16: ==ROUND(SUM(DE11:DE15),2) | DF16: ==ROUND(SUM(DF11:DF15),2) | DG16: ==ROUND(SUM(DG11:DG15),2) | DJ16: Gesamteinnahmen | DK16: ==ROUND(SUM(DK11:DK15),2) | DL16: ==ROUND(SUM(DL11:DL15),2) | DM16: ==ROUND(SUM(DM11:DM15),2) | DN16: ==ROUND(SUM(DN11:DN15),2) | DQ16: Gesamteinnahmen | DR16: ==ROUND(SUM(DR11:DR15),2) | DS16: ==ROUND(SUM(DS11:DS15),2) | DT16: ==ROUND(SUM(DT11:DT15),2) | DU16: ==ROUND(SUM(DU11:DU15),2)
B17: Ausgaben | I17: Ausgaben | P17: Ausgaben | W17: Ausgaben | AD17: Ausgaben | AK17: Ausgaben | AR17: Ausgaben | AY17: Ausgaben | BF17: Ausgaben | BM17: Ausgaben | BT17: Ausgaben | CA17: Ausgaben | CH17: Ausgaben | CO17: Ausgaben | CV17: Ausgaben | DC17: Ausgaben | DJ17: Ausgaben | DQ17: Ausgaben
B18: ID | C18: Ausgaben (LC) | D18: Ausgaben (EUR) | E18: Kum. Ausgaben (LC) | F18: Kum. Ausgaben (EUR) | I18: ID | J18: Ausgaben (LC) | K18: Ausgaben (EUR) | L18: Kum. Ausgaben (LC) | M18: Kum. Ausgaben (EUR) | P18: ID | Q18: Ausgaben (LC) | R18: Ausgaben (EUR) | S18: Kum. Ausgaben (LC) | T18: Kum. Ausgaben (EUR) | W18: ID | X18: Ausgaben (LC) | Y18: Ausgaben (EUR) | Z18: Kum. Ausgaben (LC) | AA18: Kum. Ausgaben (EUR) | AD18: ID | AE18: Ausgaben (LC) | AF18: Ausgaben (EUR) | AG18: Kum. Ausgaben (LC) | AH18: Kum. Ausgaben (EUR) | AK18: ID | AL18: Ausgaben (LC) | AM18: Ausgaben (EUR) | AN18: Kum. Ausgaben (LC) | AO18: Kum. Ausgaben (EUR) | AR18: ID | AS18: Ausgaben (LC) | AT18: Ausgaben (EUR) | AU18: Kum. Ausgaben (LC) | AV18: Kum. Ausgaben (EUR) | AY18: ID | AZ18: Ausgaben (LC) | BA18: Ausgaben (EUR) | BB18: Kum. Ausgaben (LC) | BC18: Kum. Ausgaben (EUR) | BF18: ID | BG18: Ausgaben (LC) | BH18: Ausgaben (EUR) | BI18: Kum. Ausgaben (LC) | BJ18: Kum. Ausgaben (EUR) | BM18: ID | BN18: Ausgaben (LC) | BO18: Ausgaben (EUR) | BP18: Kum. Ausgaben (LC) | BQ18: Kum. Ausgaben (EUR) | BT18: ID | BU18: Ausgaben (LC) | BV18: Ausgaben (EUR) | BW18: Kum. Ausgaben (LC) | BX18: Kum. Ausgaben (EUR) | CA18: ID | CB18: Ausgaben (LC) | CC18: Ausgaben (EUR) | CD18: Kum. Ausgaben (LC) | CE18: Kum. Ausgaben (EUR) | CH18: ID | CI18: Ausgaben (LC) | CJ18: Ausgaben (EUR) | CK18: Kum. Ausgaben (LC) | CL18: Kum. Ausgaben (EUR) | CO18: ID | CP18: Ausgaben (LC) | CQ18: Ausgaben (EUR) | CR18: Kum. Ausgaben (LC) | CS18: Kum. Ausgaben (EUR) | CV18: ID | CW18: Ausgaben (LC) | CX18: Ausgaben (EUR) | CY18: Kum. Ausgaben (LC) | CZ18: Kum. Ausgaben (EUR) | DC18: ID | DD18: Ausgaben (LC) | DE18: Ausgaben (EUR) | DF18: Kum. Ausgaben (LC) | DG18: Kum. Ausgaben (EUR) | DJ18: ID | DK18: Ausgaben (LC) | DL18: Ausgaben (EUR) | DM18: Kum. Ausgaben (LC) | DN18: Kum. Ausgaben (EUR) | DQ18: ID | DR18: Ausgaben (LC) | DS18: Ausgaben (EUR) | DT18: Kum. Ausgaben (LC) | DU18: Kum. Ausgaben (EUR)
B19: 1.1 | C19: 600000 | D19: ==IFERROR(ROUND(C19/FB_Kurs_1,2),0) | E19: ==ROUND(C19,2) | F19: ==ROUND(D19,2) | I19: 1.1 | J19: 400000 | K19: ==IFERROR(ROUND(J19/FB_Kurs_2,2),0) | L19: ==ROUND(J19+E19,2) | M19: ==ROUND(K19+F19,2) | P19: 1.1 | R19: ==IFERROR(ROUND(Q19/FB_Kurs_3,2),0) | S19: ==ROUND(Q19+L19,2) | T19: ==ROUND(R19+M19,2) | W19: 1.1 | Y19: ==IFERROR(ROUND(X19/FB_Kurs_4,2),0) | Z19: ==ROUND(X19+S19,2) | AA19: ==ROUND(Y19+T19,2) | AD19: 1.1 | AF19: ==IFERROR(ROUND(AE19/FB_Kurs_5,2),0) | AG19: ==ROUND(AE19+Z19,2) | AH19: ==ROUND(AF19+AA19,2) | AK19: 1.1 | AM19: ==IFERROR(ROUND(AL19/FB_Kurs_6,2),0) | AN19: ==ROUND(AL19+AG19,2) | AO19: ==ROUND(AM19+AH19,2) | AR19: 1.1 | AT19: ==IFERROR(ROUND(AS19/FB_Kurs_7,2),0) | AU19: ==ROUND(AS19+AN19,2) | AV19: ==ROUND(AT19+AO19,2) | AY19: 1.1 | BA19: ==IFERROR(ROUND(AZ19/FB_Kurs_8,2),0) | BB19: ==ROUND(AZ19+AU19,2) | BC19: ==ROUND(BA19+AV19,2) | BF19: 1.1 | BH19: ==IFERROR(ROUND(BG19/FB_Kurs_9,2),0) | BI19: ==ROUND(BG19+BB19,2) | BJ19: ==ROUND(BH19+BC19,2) | BM19: 1.1 | BO19: ==IFERROR(ROUND(BN19/FB_Kurs_10,2),0) | BP19: ==ROUND(BN19+BI19,2) | BQ19: ==ROUND(BO19+BJ19,2) | BT19: 1.1 | BV19: ==IFERROR(ROUND(BU19/FB_Kurs_11,2),0) | BW19: ==ROUND(BU19+BP19,2) | BX19: ==ROUND(BV19+BQ19,2) | CA19: 1.1 | CC19: ==IFERROR(ROUND(CB19/FB_Kurs_12,2),0) | CD19: ==ROUND(CB19+BW19,2) | CE19: ==ROUND(CC19+BX19,2) | CH19: 1.1 | CJ19: ==IFERROR(ROUND(CI19/FB_Kurs_13,2),0) | CK19: ==ROUND(CI19+CD19,2) | CL19: ==ROUND(CJ19+CE19,2) | CO19: 1.1 | CQ19: ==IFERROR(ROUND(CP19/FB_Kurs_14,2),0) | CR19: ==ROUND(CP19+CK19,2) | CS19: ==ROUND(CQ19+CL19,2) | CV19: 1.1 | CX19: ==IFERROR(ROUND(CW19/FB_Kurs_15,2),0) | CY19: ==ROUND(CW19+CR19,2) | CZ19: ==ROUND(CX19+CS19,2) | DC19: 1.1 | DE19: ==IFERROR(ROUND(DD19/FB_Kurs_16,2),0) | DF19: ==ROUND(DD19+CY19,2) | DG19: ==ROUND(DE19+CZ19,2) | DJ19: 1.1 | DL19: ==IFERROR(ROUND(DK19/FB_Kurs_17,2),0) | DM19: ==ROUND(DK19+DF19,2) | DN19: ==ROUND(DL19+DG19,2) | DQ19: 1.1 | DS19: ==IFERROR(ROUND(DR19/FB_Kurs_18,2),0) | DT19: ==ROUND(DR19+DM19,2) | DU19: ==ROUND(DS19+DN19,2)
B20: 1.2 | D20: ==IFERROR(ROUND(C20/FB_Kurs_1,2),0) | E20: ==ROUND(C20,2) | F20: ==ROUND(D20,2) | I20: 1.2 | J20: 300000 | K20: ==IFERROR(ROUND(J20/FB_Kurs_2,2),0) | L20: ==ROUND(J20+E20,2) | M20: ==ROUND(K20+F20,2) | P20: 1.2 | R20: ==IFERROR(ROUND(Q20/FB_Kurs_3,2),0) | S20: ==ROUND(Q20+L20,2) | T20: ==ROUND(R20+M20,2) | W20: 1.2 | Y20: ==IFERROR(ROUND(X20/FB_Kurs_4,2),0) | Z20: ==ROUND(X20+S20,2) | AA20: ==ROUND(Y20+T20,2) | AD20: 1.2 | AF20: ==IFERROR(ROUND(AE20/FB_Kurs_5,2),0) | AG20: ==ROUND(AE20+Z20,2) | AH20: ==ROUND(AF20+AA20,2) | AK20: 1.2 | AM20: ==IFERROR(ROUND(AL20/FB_Kurs_6,2),0) | AN20: ==ROUND(AL20+AG20,2) | AO20: ==ROUND(AM20+AH20,2) | AR20: 1.2 | AT20: ==IFERROR(ROUND(AS20/FB_Kurs_7,2),0) | AU20: ==ROUND(AS20+AN20,2) | AV20: ==ROUND(AT20+AO20,2) | AY20: 1.2 | BA20: ==IFERROR(ROUND(AZ20/FB_Kurs_8,2),0) | BB20: ==ROUND(AZ20+AU20,2) | BC20: ==ROUND(BA20+AV20,2) | BF20: 1.2 | BH20: ==IFERROR(ROUND(BG20/FB_Kurs_9,2),0) | BI20: ==ROUND(BG20+BB20,2) | BJ20: ==ROUND(BH20+BC20,2) | BM20: 1.2 | BO20: ==IFERROR(ROUND(BN20/FB_Kurs_10,2),0) | BP20: ==ROUND(BN20+BI20,2) | BQ20: ==ROUND(BO20+BJ20,2) | BT20: 1.2 | BV20: ==IFERROR(ROUND(BU20/FB_Kurs_11,2),0) | BW20: ==ROUND(BU20+BP20,2) | BX20: ==ROUND(BV20+BQ20,2) | CA20: 1.2 | CC20: ==IFERROR(ROUND(CB20/FB_Kurs_12,2),0) | CD20: ==ROUND(CB20+BW20,2) | CE20: ==ROUND(CC20+BX20,2) | CH20: 1.2 | CJ20: ==IFERROR(ROUND(CI20/FB_Kurs_13,2),0) | CK20: ==ROUND(CI20+CD20,2) | CL20: ==ROUND(CJ20+CE20,2) | CO20: 1.2 | CQ20: ==IFERROR(ROUND(CP20/FB_Kurs_14,2),0) | CR20: ==ROUND(CP20+CK20,2) | CS20: ==ROUND(CQ20+CL20,2) | CV20: 1.2 | CX20: ==IFERROR(ROUND(CW20/FB_Kurs_15,2),0) | CY20: ==ROUND(CW20+CR20,2) | CZ20: ==ROUND(CX20+CS20,2) | DC20: 1.2 | DE20: ==IFERROR(ROUND(DD20/FB_Kurs_16,2),0) | DF20: ==ROUND(DD20+CY20,2) | DG20: ==ROUND(DE20+CZ20,2) | DJ20: 1.2 | DL20: ==IFERROR(ROUND(DK20/FB_Kurs_17,2),0) | DM20: ==ROUND(DK20+DF20,2) | DN20: ==ROUND(DL20+DG20,2) | DQ20: 1.2 | DS20: ==IFERROR(ROUND(DR20/FB_Kurs_18,2),0) | DT20: ==ROUND(DR20+DM20,2) | DU20: ==ROUND(DS20+DN20,2)
B21: 2.1 | C21: 300000 | D21: ==IFERROR(ROUND(C21/FB_Kurs_1,2),0) | E21: ==ROUND(C21,2) | F21: ==ROUND(D21,2) | I21: 2.1 | K21: ==IFERROR(ROUND(J21/FB_Kurs_2,2),0) | L21: ==ROUND(J21+E21,2) | M21: ==ROUND(K21+F21,2) | P21: 2.1 | R21: ==IFERROR(ROUND(Q21/FB_Kurs_3,2),0) | S21: ==ROUND(Q21+L21,2) | T21: ==ROUND(R21+M21,2) | W21: 2.1 | Y21: ==IFERROR(ROUND(X21/FB_Kurs_4,2),0) | Z21: ==ROUND(X21+S21,2) | AA21: ==ROUND(Y21+T21,2) | AD21: 2.1 | AF21: ==IFERROR(ROUND(AE21/FB_Kurs_5,2),0) | AG21: ==ROUND(AE21+Z21,2) | AH21: ==ROUND(AF21+AA21,2) | AK21: 2.1 | AM21: ==IFERROR(ROUND(AL21/FB_Kurs_6,2),0) | AN21: ==ROUND(AL21+AG21,2) | AO21: ==ROUND(AM21+AH21,2) | AR21: 2.1 | AT21: ==IFERROR(ROUND(AS21/FB_Kurs_7,2),0) | AU21: ==ROUND(AS21+AN21,2) | AV21: ==ROUND(AT21+AO21,2) | AY21: 2.1 | BA21: ==IFERROR(ROUND(AZ21/FB_Kurs_8,2),0) | BB21: ==ROUND(AZ21+AU21,2) | BC21: ==ROUND(BA21+AV21,2) | BF21: 2.1 | BH21: ==IFERROR(ROUND(BG21/FB_Kurs_9,2),0) | BI21: ==ROUND(BG21+BB21,2) | BJ21: ==ROUND(BH21+BC21,2) | BM21: 2.1 | BO21: ==IFERROR(ROUND(BN21/FB_Kurs_10,2),0) | BP21: ==ROUND(BN21+BI21,2) | BQ21: ==ROUND(BO21+BJ21,2) | BT21: 2.1 | BV21: ==IFERROR(ROUND(BU21/FB_Kurs_11,2),0) | BW21: ==ROUND(BU21+BP21,2) | BX21: ==ROUND(BV21+BQ21,2) | CA21: 2.1 | CC21: ==IFERROR(ROUND(CB21/FB_Kurs_12,2),0) | CD21: ==ROUND(CB21+BW21,2) | CE21: ==ROUND(CC21+BX21,2) | CH21: 2.1 | CJ21: ==IFERROR(ROUND(CI21/FB_Kurs_13,2),0) | CK21: ==ROUND(CI21+CD21,2) | CL21: ==ROUND(CJ21+CE21,2) | CO21: 2.1 | CQ21: ==IFERROR(ROUND(CP21/FB_Kurs_14,2),0) | CR21: ==ROUND(CP21+CK21,2) | CS21: ==ROUND(CQ21+CL21,2) | CV21: 2.1 | CX21: ==IFERROR(ROUND(CW21/FB_Kurs_15,2),0) | CY21: ==ROUND(CW21+CR21,2) | CZ21: ==ROUND(CX21+CS21,2) | DC21: 2.1 | DE21: ==IFERROR(ROUND(DD21/FB_Kurs_16,2),0) | DF21: ==ROUND(DD21+CY21,2) | DG21: ==ROUND(DE21+CZ21,2) | DJ21: 2.1 | DL21: ==IFERROR(ROUND(DK21/FB_Kurs_17,2),0) | DM21: ==ROUND(DK21+DF21,2) | DN21: ==ROUND(DL21+DG21,2) | DQ21: 2.1 | DS21: ==IFERROR(ROUND(DR21/FB_Kurs_18,2),0) | DT21: ==ROUND(DR21+DM21,2) | DU21: ==ROUND(DS21+DN21,2)
B22: 3.1 | C22: 200000 | D22: ==IFERROR(ROUND(C22/FB_Kurs_1,2),0) | E22: ==ROUND(C22,2) | F22: ==ROUND(D22,2) | I22: 3.1 | J22: 200000 | K22: ==IFERROR(ROUND(J22/FB_Kurs_2,2),0) | L22: ==ROUND(J22+E22,2) | M22: ==ROUND(K22+F22,2) | P22: 3.1 | R22: ==IFERROR(ROUND(Q22/FB_Kurs_3,2),0) | S22: ==ROUND(Q22+L22,2) | T22: ==ROUND(R22+M22,2) | W22: 3.1 | Y22: ==IFERROR(ROUND(X22/FB_Kurs_4,2),0) | Z22: ==ROUND(X22+S22,2) | AA22: ==ROUND(Y22+T22,2) | AD22: 3.1 | AF22: ==IFERROR(ROUND(AE22/FB_Kurs_5,2),0) | AG22: ==ROUND(AE22+Z22,2) | AH22: ==ROUND(AF22+AA22,2) | AK22: 3.1 | AM22: ==IFERROR(ROUND(AL22/FB_Kurs_6,2),0) | AN22: ==ROUND(AL22+AG22,2) | AO22: ==ROUND(AM22+AH22,2) | AR22: 3.1 | AT22: ==IFERROR(ROUND(AS22/FB_Kurs_7,2),0) | AU22: ==ROUND(AS22+AN22,2) | AV22: ==ROUND(AT22+AO22,2) | AY22: 3.1 | BA22: ==IFERROR(ROUND(AZ22/FB_Kurs_8,2),0) | BB22: ==ROUND(AZ22+AU22,2) | BC22: ==ROUND(BA22+AV22,2) | BF22: 3.1 | BH22: ==IFERROR(ROUND(BG22/FB_Kurs_9,2),0) | BI22: ==ROUND(BG22+BB22,2) | BJ22: ==ROUND(BH22+BC22,2) | BM22: 3.1 | BO22: ==IFERROR(ROUND(BN22/FB_Kurs_10,2),0) | BP22: ==ROUND(BN22+BI22,2) | BQ22: ==ROUND(BO22+BJ22,2) | BT22: 3.1 | BV22: ==IFERROR(ROUND(BU22/FB_Kurs_11,2),0) | BW22: ==ROUND(BU22+BP22,2) | BX22: ==ROUND(BV22+BQ22,2) | CA22: 3.1 | CC22: ==IFERROR(ROUND(CB22/FB_Kurs_12,2),0) | CD22: ==ROUND(CB22+BW22,2) | CE22: ==ROUND(CC22+BX22,2) | CH22: 3.1 | CJ22: ==IFERROR(ROUND(CI22/FB_Kurs_13,2),0) | CK22: ==ROUND(CI22+CD22,2) | CL22: ==ROUND(CJ22+CE22,2) | CO22: 3.1 | CQ22: ==IFERROR(ROUND(CP22/FB_Kurs_14,2),0) | CR22: ==ROUND(CP22+CK22,2) | CS22: ==ROUND(CQ22+CL22,2) | CV22: 3.1 | CX22: ==IFERROR(ROUND(CW22/FB_Kurs_15,2),0) | CY22: ==ROUND(CW22+CR22,2) | CZ22: ==ROUND(CX22+CS22,2) | DC22: 3.1 | DE22: ==IFERROR(ROUND(DD22/FB_Kurs_16,2),0) | DF22: ==ROUND(DD22+CY22,2) | DG22: ==ROUND(DE22+CZ22,2) | DJ22: 3.1 | DL22: ==IFERROR(ROUND(DK22/FB_Kurs_17,2),0) | DM22: ==ROUND(DK22+DF22,2) | DN22: ==ROUND(DL22+DG22,2) | DQ22: 3.1 | DS22: ==IFERROR(ROUND(DR22/FB_Kurs_18,2),0) | DT22: ==ROUND(DR22+DM22,2) | DU22: ==ROUND(DS22+DN22,2)
B23: 3.2 | C23: 150000 | D23: ==IFERROR(ROUND(C23/FB_Kurs_1,2),0) | E23: ==ROUND(C23,2) | F23: ==ROUND(D23,2) | I23: 3.2 | J23: 150000 | K23: ==IFERROR(ROUND(J23/FB_Kurs_2,2),0) | L23: ==ROUND(J23+E23,2) | M23: ==ROUND(K23+F23,2) | P23: 3.2 | R23: ==IFERROR(ROUND(Q23/FB_Kurs_3,2),0) | S23: ==ROUND(Q23+L23,2) | T23: ==ROUND(R23+M23,2) | W23: 3.2 | Y23: ==IFERROR(ROUND(X23/FB_Kurs_4,2),0) | Z23: ==ROUND(X23+S23,2) | AA23: ==ROUND(Y23+T23,2) | AD23: 3.2 | AF23: ==IFERROR(ROUND(AE23/FB_Kurs_5,2),0) | AG23: ==ROUND(AE23+Z23,2) | AH23: ==ROUND(AF23+AA23,2) | AK23: 3.2 | AM23: ==IFERROR(ROUND(AL23/FB_Kurs_6,2),0) | AN23: ==ROUND(AL23+AG23,2) | AO23: ==ROUND(AM23+AH23,2) | AR23: 3.2 | AT23: ==IFERROR(ROUND(AS23/FB_Kurs_7,2),0) | AU23: ==ROUND(AS23+AN23,2) | AV23: ==ROUND(AT23+AO23,2) | AY23: 3.2 | BA23: ==IFERROR(ROUND(AZ23/FB_Kurs_8,2),0) | BB23: ==ROUND(AZ23+AU23,2) | BC23: ==ROUND(BA23+AV23,2) | BF23: 3.2 | BH23: ==IFERROR(ROUND(BG23/FB_Kurs_9,2),0) | BI23: ==ROUND(BG23+BB23,2) | BJ23: ==ROUND(BH23+BC23,2) | BM23: 3.2 | BO23: ==IFERROR(ROUND(BN23/FB_Kurs_10,2),0) | BP23: ==ROUND(BN23+BI23,2) | BQ23: ==ROUND(BO23+BJ23,2) | BT23: 3.2 | BV23: ==IFERROR(ROUND(BU23/FB_Kurs_11,2),0) | BW23: ==ROUND(BU23+BP23,2) | BX23: ==ROUND(BV23+BQ23,2) | CA23: 3.2 | CC23: ==IFERROR(ROUND(CB23/FB_Kurs_12,2),0) | CD23: ==ROUND(CB23+BW23,2) | CE23: ==ROUND(CC23+BX23,2) | CH23: 3.2 | CJ23: ==IFERROR(ROUND(CI23/FB_Kurs_13,2),0) | CK23: ==ROUND(CI23+CD23,2) | CL23: ==ROUND(CJ23+CE23,2) | CO23: 3.2 | CQ23: ==IFERROR(ROUND(CP23/FB_Kurs_14,2),0) | CR23: ==ROUND(CP23+CK23,2) | CS23: ==ROUND(CQ23+CL23,2) | CV23: 3.2 | CX23: ==IFERROR(ROUND(CW23/FB_Kurs_15,2),0) | CY23: ==ROUND(CW23+CR23,2) | CZ23: ==ROUND(CX23+CS23,2) | DC23: 3.2 | DE23: ==IFERROR(ROUND(DD23/FB_Kurs_16,2),0) | DF23: ==ROUND(DD23+CY23,2) | DG23: ==ROUND(DE23+CZ23,2) | DJ23: 3.2 | DL23: ==IFERROR(ROUND(DK23/FB_Kurs_17,2),0) | DM23: ==ROUND(DK23+DF23,2) | DN23: ==ROUND(DL23+DG23,2) | DQ23: 3.2 | DS23: ==IFERROR(ROUND(DR23/FB_Kurs_18,2),0) | DT23: ==ROUND(DR23+DM23,2) | DU23: ==ROUND(DS23+DN23,2)
B24: 4.1 | C24: 120000 | D24: ==IFERROR(ROUND(C24/FB_Kurs_1,2),0) | E24: ==ROUND(C24,2) | F24: ==ROUND(D24,2) | I24: 4.1 | J24: 100000 | K24: ==IFERROR(ROUND(J24/FB_Kurs_2,2),0) | L24: ==ROUND(J24+E24,2) | M24: ==ROUND(K24+F24,2) | P24: 4.1 | R24: ==IFERROR(ROUND(Q24/FB_Kurs_3,2),0) | S24: ==ROUND(Q24+L24,2) | T24: ==ROUND(R24+M24,2) | W24: 4.1 | Y24: ==IFERROR(ROUND(X24/FB_Kurs_4,2),0) | Z24: ==ROUND(X24+S24,2) | AA24: ==ROUND(Y24+T24,2) | AD24: 4.1 | AF24: ==IFERROR(ROUND(AE24/FB_Kurs_5,2),0) | AG24: ==ROUND(AE24+Z24,2) | AH24: ==ROUND(AF24+AA24,2) | AK24: 4.1 | AM24: ==IFERROR(ROUND(AL24/FB_Kurs_6,2),0) | AN24: ==ROUND(AL24+AG24,2) | AO24: ==ROUND(AM24+AH24,2) | AR24: 4.1 | AT24: ==IFERROR(ROUND(AS24/FB_Kurs_7,2),0) | AU24: ==ROUND(AS24+AN24,2) | AV24: ==ROUND(AT24+AO24,2) | AY24: 4.1 | BA24: ==IFERROR(ROUND(AZ24/FB_Kurs_8,2),0) | BB24: ==ROUND(AZ24+AU24,2) | BC24: ==ROUND(BA24+AV24,2) | BF24: 4.1 | BH24: ==IFERROR(ROUND(BG24/FB_Kurs_9,2),0) | BI24: ==ROUND(BG24+BB24,2) | BJ24: ==ROUND(BH24+BC24,2) | BM24: 4.1 | BO24: ==IFERROR(ROUND(BN24/FB_Kurs_10,2),0) | BP24: ==ROUND(BN24+BI24,2) | BQ24: ==ROUND(BO24+BJ24,2) | BT24: 4.1 | BV24: ==IFERROR(ROUND(BU24/FB_Kurs_11,2),0) | BW24: ==ROUND(BU24+BP24,2) | BX24: ==ROUND(BV24+BQ24,2) | CA24: 4.1 | CC24: ==IFERROR(ROUND(CB24/FB_Kurs_12,2),0) | CD24: ==ROUND(CB24+BW24,2) | CE24: ==ROUND(CC24+BX24,2) | CH24: 4.1 | CJ24: ==IFERROR(ROUND(CI24/FB_Kurs_13,2),0) | CK24: ==ROUND(CI24+CD24,2) | CL24: ==ROUND(CJ24+CE24,2) | CO24: 4.1 | CQ24: ==IFERROR(ROUND(CP24/FB_Kurs_14,2),0) | CR24: ==ROUND(CP24+CK24,2) | CS24: ==ROUND(CQ24+CL24,2) | CV24: 4.1 | CX24: ==IFERROR(ROUND(CW24/FB_Kurs_15,2),0) | CY24: ==ROUND(CW24+CR24,2) | CZ24: ==ROUND(CX24+CS24,2) | DC24: 4.1 | DE24: ==IFERROR(ROUND(DD24/FB_Kurs_16,2),0) | DF24: ==ROUND(DD24+CY24,2) | DG24: ==ROUND(DE24+CZ24,2) | DJ24: 4.1 | DL24: ==IFERROR(ROUND(DK24/FB_Kurs_17,2),0) | DM24: ==ROUND(DK24+DF24,2) | DN24: ==ROUND(DL24+DG24,2) | DQ24: 4.1 | DS24: ==IFERROR(ROUND(DR24/FB_Kurs_18,2),0) | DT24: ==ROUND(DR24+DM24,2) | DU24: ==ROUND(DS24+DN24,2)
B25: 5.1 | C25: 80000 | D25: ==IFERROR(ROUND(C25/FB_Kurs_1,2),0) | E25: ==ROUND(C25,2) | F25: ==ROUND(D25,2) | I25: 5.1 | J25: 70000 | K25: ==IFERROR(ROUND(J25/FB_Kurs_2,2),0) | L25: ==ROUND(J25+E25,2) | M25: ==ROUND(K25+F25,2) | P25: 5.1 | R25: ==IFERROR(ROUND(Q25/FB_Kurs_3,2),0) | S25: ==ROUND(Q25+L25,2) | T25: ==ROUND(R25+M25,2) | W25: 5.1 | Y25: ==IFERROR(ROUND(X25/FB_Kurs_4,2),0) | Z25: ==ROUND(X25+S25,2) | AA25: ==ROUND(Y25+T25,2) | AD25: 5.1 | AF25: ==IFERROR(ROUND(AE25/FB_Kurs_5,2),0) | AG25: ==ROUND(AE25+Z25,2) | AH25: ==ROUND(AF25+AA25,2) | AK25: 5.1 | AM25: ==IFERROR(ROUND(AL25/FB_Kurs_6,2),0) | AN25: ==ROUND(AL25+AG25,2) | AO25: ==ROUND(AM25+AH25,2) | AR25: 5.1 | AT25: ==IFERROR(ROUND(AS25/FB_Kurs_7,2),0) | AU25: ==ROUND(AS25+AN25,2) | AV25: ==ROUND(AT25+AO25,2) | AY25: 5.1 | BA25: ==IFERROR(ROUND(AZ25/FB_Kurs_8,2),0) | BB25: ==ROUND(AZ25+AU25,2) | BC25: ==ROUND(BA25+AV25,2) | BF25: 5.1 | BH25: ==IFERROR(ROUND(BG25/FB_Kurs_9,2),0) | BI25: ==ROUND(BG25+BB25,2) | BJ25: ==ROUND(BH25+BC25,2) | BM25: 5.1 | BO25: ==IFERROR(ROUND(BN25/FB_Kurs_10,2),0) | BP25: ==ROUND(BN25+BI25,2) | BQ25: ==ROUND(BO25+BJ25,2) | BT25: 5.1 | BV25: ==IFERROR(ROUND(BU25/FB_Kurs_11,2),0) | BW25: ==ROUND(BU25+BP25,2) | BX25: ==ROUND(BV25+BQ25,2) | CA25: 5.1 | CC25: ==IFERROR(ROUND(CB25/FB_Kurs_12,2),0) | CD25: ==ROUND(CB25+BW25,2) | CE25: ==ROUND(CC25+BX25,2) | CH25: 5.1 | CJ25: ==IFERROR(ROUND(CI25/FB_Kurs_13,2),0) | CK25: ==ROUND(CI25+CD25,2) | CL25: ==ROUND(CJ25+CE25,2) | CO25: 5.1 | CQ25: ==IFERROR(ROUND(CP25/FB_Kurs_14,2),0) | CR25: ==ROUND(CP25+CK25,2) | CS25: ==ROUND(CQ25+CL25,2) | CV25: 5.1 | CX25: ==IFERROR(ROUND(CW25/FB_Kurs_15,2),0) | CY25: ==ROUND(CW25+CR25,2) | CZ25: ==ROUND(CX25+CS25,2) | DC25: 5.1 | DE25: ==IFERROR(ROUND(DD25/FB_Kurs_16,2),0) | DF25: ==ROUND(DD25+CY25,2) | DG25: ==ROUND(DE25+CZ25,2) | DJ25: 5.1 | DL25: ==IFERROR(ROUND(DK25/FB_Kurs_17,2),0) | DM25: ==ROUND(DK25+DF25,2) | DN25: ==ROUND(DL25+DG25,2) | DQ25: 5.1 | DS25: ==IFERROR(ROUND(DR25/FB_Kurs_18,2),0) | DT25: ==ROUND(DR25+DM25,2) | DU25: ==ROUND(DS25+DN25,2)
B26: 6.1 | D26: ==IFERROR(ROUND(C26/FB_Kurs_1,2),0) | E26: ==ROUND(C26,2) | F26: ==ROUND(D26,2) | I26: 6.1 | K26: ==IFERROR(ROUND(J26/FB_Kurs_2,2),0) | L26: ==ROUND(J26+E26,2) | M26: ==ROUND(K26+F26,2) | P26: 6.1 | R26: ==IFERROR(ROUND(Q26/FB_Kurs_3,2),0) | S26: ==ROUND(Q26+L26,2) | T26: ==ROUND(R26+M26,2) | W26: 6.1 | Y26: ==IFERROR(ROUND(X26/FB_Kurs_4,2),0) | Z26: ==ROUND(X26+S26,2) | AA26: ==ROUND(Y26+T26,2) | AD26: 6.1 | AF26: ==IFERROR(ROUND(AE26/FB_Kurs_5,2),0) | AG26: ==ROUND(AE26+Z26,2) | AH26: ==ROUND(AF26+AA26,2) | AK26: 6.1 | AM26: ==IFERROR(ROUND(AL26/FB_Kurs_6,2),0) | AN26: ==ROUND(AL26+AG26,2) | AO26: ==ROUND(AM26+AH26,2) | AR26: 6.1 | AT26: ==IFERROR(ROUND(AS26/FB_Kurs_7,2),0) | AU26: ==ROUND(AS26+AN26,2) | AV26: ==ROUND(AT26+AO26,2) | AY26: 6.1 | BA26: ==IFERROR(ROUND(AZ26/FB_Kurs_8,2),0) | BB26: ==ROUND(AZ26+AU26,2) | BC26: ==ROUND(BA26+AV26,2) | BF26: 6.1 | BH26: ==IFERROR(ROUND(BG26/FB_Kurs_9,2),0) | BI26: ==ROUND(BG26+BB26,2) | BJ26: ==ROUND(BH26+BC26,2) | BM26: 6.1 | BO26: ==IFERROR(ROUND(BN26/FB_Kurs_10,2),0) | BP26: ==ROUND(BN26+BI26,2) | BQ26: ==ROUND(BO26+BJ26,2) | BT26: 6.1 | BV26: ==IFERROR(ROUND(BU26/FB_Kurs_11,2),0) | BW26: ==ROUND(BU26+BP26,2) | BX26: ==ROUND(BV26+BQ26,2) | CA26: 6.1 | CC26: ==IFERROR(ROUND(CB26/FB_Kurs_12,2),0) | CD26: ==ROUND(CB26+BW26,2) | CE26: ==ROUND(CC26+BX26,2) | CH26: 6.1 | CJ26: ==IFERROR(ROUND(CI26/FB_Kurs_13,2),0) | CK26: ==ROUND(CI26+CD26,2) | CL26: ==ROUND(CJ26+CE26,2) | CO26: 6.1 | CQ26: ==IFERROR(ROUND(CP26/FB_Kurs_14,2),0) | CR26: ==ROUND(CP26+CK26,2) | CS26: ==ROUND(CQ26+CL26,2) | CV26: 6.1 | CX26: ==IFERROR(ROUND(CW26/FB_Kurs_15,2),0) | CY26: ==ROUND(CW26+CR26,2) | CZ26: ==ROUND(CX26+CS26,2) | DC26: 6.1 | DE26: ==IFERROR(ROUND(DD26/FB_Kurs_16,2),0) | DF26: ==ROUND(DD26+CY26,2) | DG26: ==ROUND(DE26+CZ26,2) | DJ26: 6.1 | DL26: ==IFERROR(ROUND(DK26/FB_Kurs_17,2),0) | DM26: ==ROUND(DK26+DF26,2) | DN26: ==ROUND(DL26+DG26,2) | DQ26: 6.1 | DS26: ==IFERROR(ROUND(DR26/FB_Kurs_18,2),0) | DT26: ==ROUND(DR26+DM26,2) | DU26: ==ROUND(DS26+DN26,2)
B27: 7.1 | C27: 50000 | D27: ==IFERROR(ROUND(C27/FB_Kurs_1,2),0) | E27: ==ROUND(C27,2) | F27: ==ROUND(D27,2) | I27: 7.1 | J27: 30000 | K27: ==IFERROR(ROUND(J27/FB_Kurs_2,2),0) | L27: ==ROUND(J27+E27,2) | M27: ==ROUND(K27+F27,2) | P27: 7.1 | R27: ==IFERROR(ROUND(Q27/FB_Kurs_3,2),0) | S27: ==ROUND(Q27+L27,2) | T27: ==ROUND(R27+M27,2) | W27: 7.1 | Y27: ==IFERROR(ROUND(X27/FB_Kurs_4,2),0) | Z27: ==ROUND(X27+S27,2) | AA27: ==ROUND(Y27+T27,2) | AD27: 7.1 | AF27: ==IFERROR(ROUND(AE27/FB_Kurs_5,2),0) | AG27: ==ROUND(AE27+Z27,2) | AH27: ==ROUND(AF27+AA27,2) | AK27: 7.1 | AM27: ==IFERROR(ROUND(AL27/FB_Kurs_6,2),0) | AN27: ==ROUND(AL27+AG27,2) | AO27: ==ROUND(AM27+AH27,2) | AR27: 7.1 | AT27: ==IFERROR(ROUND(AS27/FB_Kurs_7,2),0) | AU27: ==ROUND(AS27+AN27,2) | AV27: ==ROUND(AT27+AO27,2) | AY27: 7.1 | BA27: ==IFERROR(ROUND(AZ27/FB_Kurs_8,2),0) | BB27: ==ROUND(AZ27+AU27,2) | BC27: ==ROUND(BA27+AV27,2) | BF27: 7.1 | BH27: ==IFERROR(ROUND(BG27/FB_Kurs_9,2),0) | BI27: ==ROUND(BG27+BB27,2) | BJ27: ==ROUND(BH27+BC27,2) | BM27: 7.1 | BO27: ==IFERROR(ROUND(BN27/FB_Kurs_10,2),0) | BP27: ==ROUND(BN27+BI27,2) | BQ27: ==ROUND(BO27+BJ27,2) | BT27: 7.1 | BV27: ==IFERROR(ROUND(BU27/FB_Kurs_11,2),0) | BW27: ==ROUND(BU27+BP27,2) | BX27: ==ROUND(BV27+BQ27,2) | CA27: 7.1 | CC27: ==IFERROR(ROUND(CB27/FB_Kurs_12,2),0) | CD27: ==ROUND(CB27+BW27,2) | CE27: ==ROUND(CC27+BX27,2) | CH27: 7.1 | CJ27: ==IFERROR(ROUND(CI27/FB_Kurs_13,2),0) | CK27: ==ROUND(CI27+CD27,2) | CL27: ==ROUND(CJ27+CE27,2) | CO27: 7.1 | CQ27: ==IFERROR(ROUND(CP27/FB_Kurs_14,2),0) | CR27: ==ROUND(CP27+CK27,2) | CS27: ==ROUND(CQ27+CL27,2) | CV27: 7.1 | CX27: ==IFERROR(ROUND(CW27/FB_Kurs_15,2),0) | CY27: ==ROUND(CW27+CR27,2) | CZ27: ==ROUND(CX27+CS27,2) | DC27: 7.1 | DE27: ==IFERROR(ROUND(DD27/FB_Kurs_16,2),0) | DF27: ==ROUND(DD27+CY27,2) | DG27: ==ROUND(DE27+CZ27,2) | DJ27: 7.1 | DL27: ==IFERROR(ROUND(DK27/FB_Kurs_17,2),0) | DM27: ==ROUND(DK27+DF27,2) | DN27: ==ROUND(DL27+DG27,2) | DQ27: 7.1 | DS27: ==IFERROR(ROUND(DR27/FB_Kurs_18,2),0) | DT27: ==ROUND(DR27+DM27,2) | DU27: ==ROUND(DS27+DN27,2)
B28: 8.1 | D28: ==IFERROR(ROUND(C28/FB_Kurs_1,2),0) | E28: ==ROUND(C28,2) | F28: ==ROUND(D28,2) | I28: 8.1 | K28: ==IFERROR(ROUND(J28/FB_Kurs_2,2),0) | L28: ==ROUND(J28+E28,2) | M28: ==ROUND(K28+F28,2) | P28: 8.1 | R28: ==IFERROR(ROUND(Q28/FB_Kurs_3,2),0) | S28: ==ROUND(Q28+L28,2) | T28: ==ROUND(R28+M28,2) | W28: 8.1 | Y28: ==IFERROR(ROUND(X28/FB_Kurs_4,2),0) | Z28: ==ROUND(X28+S28,2) | AA28: ==ROUND(Y28+T28,2) | AD28: 8.1 | AF28: ==IFERROR(ROUND(AE28/FB_Kurs_5,2),0) | AG28: ==ROUND(AE28+Z28,2) | AH28: ==ROUND(AF28+AA28,2) | AK28: 8.1 | AM28: ==IFERROR(ROUND(AL28/FB_Kurs_6,2),0) | AN28: ==ROUND(AL28+AG28,2) | AO28: ==ROUND(AM28+AH28,2) | AR28: 8.1 | AT28: ==IFERROR(ROUND(AS28/FB_Kurs_7,2),0) | AU28: ==ROUND(AS28+AN28,2) | AV28: ==ROUND(AT28+AO28,2) | AY28: 8.1 | BA28: ==IFERROR(ROUND(AZ28/FB_Kurs_8,2),0) | BB28: ==ROUND(AZ28+AU28,2) | BC28: ==ROUND(BA28+AV28,2) | BF28: 8.1 | BH28: ==IFERROR(ROUND(BG28/FB_Kurs_9,2),0) | BI28: ==ROUND(BG28+BB28,2) | BJ28: ==ROUND(BH28+BC28,2) | BM28: 8.1 | BO28: ==IFERROR(ROUND(BN28/FB_Kurs_10,2),0) | BP28: ==ROUND(BN28+BI28,2) | BQ28: ==ROUND(BO28+BJ28,2) | BT28: 8.1 | BV28: ==IFERROR(ROUND(BU28/FB_Kurs_11,2),0) | BW28: ==ROUND(BU28+BP28,2) | BX28: ==ROUND(BV28+BQ28,2) | CA28: 8.1 | CC28: ==IFERROR(ROUND(CB28/FB_Kurs_12,2),0) | CD28: ==ROUND(CB28+BW28,2) | CE28: ==ROUND(CC28+BX28,2) | CH28: 8.1 | CJ28: ==IFERROR(ROUND(CI28/FB_Kurs_13,2),0) | CK28: ==ROUND(CI28+CD28,2) | CL28: ==ROUND(CJ28+CE28,2) | CO28: 8.1 | CQ28: ==IFERROR(ROUND(CP28/FB_Kurs_14,2),0) | CR28: ==ROUND(CP28+CK28,2) | CS28: ==ROUND(CQ28+CL28,2) | CV28: 8.1 | CX28: ==IFERROR(ROUND(CW28/FB_Kurs_15,2),0) | CY28: ==ROUND(CW28+CR28,2) | CZ28: ==ROUND(CX28+CS28,2) | DC28: 8.1 | DE28: ==IFERROR(ROUND(DD28/FB_Kurs_16,2),0) | DF28: ==ROUND(DD28+CY28,2) | DG28: ==ROUND(DE28+CZ28,2) | DJ28: 8.1 | DL28: ==IFERROR(ROUND(DK28/FB_Kurs_17,2),0) | DM28: ==ROUND(DK28+DF28,2) | DN28: ==ROUND(DL28+DG28,2) | DQ28: 8.1 | DS28: ==IFERROR(ROUND(DR28/FB_Kurs_18,2),0) | DT28: ==ROUND(DR28+DM28,2) | DU28: ==ROUND(DS28+DN28,2)
B29: Gesamtausgaben | C29: ==ROUND(SUBTOTAL(109,$C$19:$C$28),2) | D29: ==ROUND(SUBTOTAL(109,$D$19:$D$28),2) | E29: ==ROUND(SUBTOTAL(109,$E$19:$E$28),2) | F29: ==ROUND(SUBTOTAL(109,$F$19:$F$28),2) | I29: Gesamtausgaben | J29: ==ROUND(SUBTOTAL(109,$J$19:$J$28),2) | K29: ==ROUND(SUBTOTAL(109,$K$19:$K$28),2) | L29: ==ROUND(SUBTOTAL(109,$L$19:$L$28),2) | M29: ==ROUND(SUBTOTAL(109,$M$19:$M$28),2) | P29: Gesamtausgaben | Q29: ==ROUND(SUBTOTAL(109,$Q$19:$Q$28),2) | R29: ==ROUND(SUBTOTAL(109,$R$19:$R$28),2) | S29: ==ROUND(SUBTOTAL(109,$S$19:$S$28),2) | T29: ==ROUND(SUBTOTAL(109,$T$19:$T$28),2) | W29: Gesamtausgaben | X29: ==ROUND(SUBTOTAL(109,$X$19:$X$28),2) | Y29: ==ROUND(SUBTOTAL(109,$Y$19:$Y$28),2) | Z29: ==ROUND(SUBTOTAL(109,$Z$19:$Z$28),2) | AA29: ==ROUND(SUBTOTAL(109,$AA$19:$AA$28),2) | AD29: Gesamtausgaben | AE29: ==ROUND(SUBTOTAL(109,$AE$19:$AE$28),2) | AF29: ==ROUND(SUBTOTAL(109,$AF$19:$AF$28),2) | AG29: ==ROUND(SUBTOTAL(109,$AG$19:$AG$28),2) | AH29: ==ROUND(SUBTOTAL(109,$AH$19:$AH$28),2) | AK29: Gesamtausgaben | AL29: ==ROUND(SUBTOTAL(109,$AL$19:$AL$28),2) | AM29: ==ROUND(SUBTOTAL(109,$AM$19:$AM$28),2) | AN29: ==ROUND(SUBTOTAL(109,$AN$19:$AN$28),2) | AO29: ==ROUND(SUBTOTAL(109,$AO$19:$AO$28),2) | AR29: Gesamtausgaben | AS29: ==ROUND(SUBTOTAL(109,$AS$19:$AS$28),2) | AT29: ==ROUND(SUBTOTAL(109,$AT$19:$AT$28),2) | AU29: ==ROUND(SUBTOTAL(109,$AU$19:$AU$28),2) | AV29: ==ROUND(SUBTOTAL(109,$AV$19:$AV$28),2) | AY29: Gesamtausgaben | AZ29: ==ROUND(SUBTOTAL(109,$AZ$19:$AZ$28),2) | BA29: ==ROUND(SUBTOTAL(109,$BA$19:$BA$28),2) | BB29: ==ROUND(SUBTOTAL(109,$BB$19:$BB$28),2) | BC29: ==ROUND(SUBTOTAL(109,$BC$19:$BC$28),2) | BF29: Gesamtausgaben | BG29: ==ROUND(SUBTOTAL(109,$BG$19:$BG$28),2) | BH29: ==ROUND(SUBTOTAL(109,$BH$19:$BH$28),2) | BI29: ==ROUND(SUBTOTAL(109,$BI$19:$BI$28),2) | BJ29: ==ROUND(SUBTOTAL(109,$BJ$19:$BJ$28),2) | BM29: Gesamtausgaben | BN29: ==ROUND(SUBTOTAL(109,$BN$19:$BN$28),2) | BO29: ==ROUND(SUBTOTAL(109,$BO$19:$BO$28),2) | BP29: ==ROUND(SUBTOTAL(109,$BP$19:$BP$28),2) | BQ29: ==ROUND(SUBTOTAL(109,$BQ$19:$BQ$28),2) | BT29: Gesamtausgaben | BU29: ==ROUND(SUBTOTAL(109,$BU$19:$BU$28),2) | BV29: ==ROUND(SUBTOTAL(109,$BV$19:$BV$28),2) | BW29: ==ROUND(SUBTOTAL(109,$BW$19:$BW$28),2) | BX29: ==ROUND(SUBTOTAL(109,$BX$19:$BX$28),2) | CA29: Gesamtausgaben | CB29: ==ROUND(SUBTOTAL(109,$CB$19:$CB$28),2) | CC29: ==ROUND(SUBTOTAL(109,$CC$19:$CC$28),2) | CD29: ==ROUND(SUBTOTAL(109,$CD$19:$CD$28),2) | CE29: ==ROUND(SUBTOTAL(109,$CE$19:$CE$28),2) | CH29: Gesamtausgaben | CI29: ==ROUND(SUBTOTAL(109,$CI$19:$CI$28),2) | CJ29: ==ROUND(SUBTOTAL(109,$CJ$19:$CJ$28),2) | CK29: ==ROUND(SUBTOTAL(109,$CK$19:$CK$28),2) | CL29: ==ROUND(SUBTOTAL(109,$CL$19:$CL$28),2) | CO29: Gesamtausgaben | CP29: ==ROUND(SUBTOTAL(109,$CP$19:$CP$28),2) | CQ29: ==ROUND(SUBTOTAL(109,$CQ$19:$CQ$28),2) | CR29: ==ROUND(SUBTOTAL(109,$CR$19:$CR$28),2) | CS29: ==ROUND(SUBTOTAL(109,$CS$19:$CS$28),2) | CV29: Gesamtausgaben | CW29: ==ROUND(SUBTOTAL(109,$CW$19:$CW$28),2) | CX29: ==ROUND(SUBTOTAL(109,$CX$19:$CX$28),2) | CY29: ==ROUND(SUBTOTAL(109,$CY$19:$CY$28),2) | CZ29: ==ROUND(SUBTOTAL(109,$CZ$19:$CZ$28),2) | DC29: Gesamtausgaben | DD29: ==ROUND(SUBTOTAL(109,$DD$19:$DD$28),2) | DE29: ==ROUND(SUBTOTAL(109,$DE$19:$DE$28),2) | DF29: ==ROUND(SUBTOTAL(109,$DF$19:$DF$28),2) | DG29: ==ROUND(SUBTOTAL(109,$DG$19:$DG$28),2) | DJ29: Gesamtausgaben | DK29: ==ROUND(SUBTOTAL(109,$DK$19:$DK$28),2) | DL29: ==ROUND(SUBTOTAL(109,$DL$19:$DL$28),2) | DM29: ==ROUND(SUBTOTAL(109,$DM$19:$DM$28),2) | DN29: ==ROUND(SUBTOTAL(109,$DN$19:$DN$28),2) | DQ29: Gesamtausgaben | DR29: ==ROUND(SUBTOTAL(109,$DR$19:$DR$28),2) | DS29: ==ROUND(SUBTOTAL(109,$DS$19:$DS$28),2) | DT29: ==ROUND(SUBTOTAL(109,$DT$19:$DT$28),2) | DU29: ==ROUND(SUBTOTAL(109,$DU$19:$DU$28),2)
B31: Saldo des Finanzberichts | C31: ==ROUND(IFERROR(C16-$C$29,""),2) | D31: ==ROUND(IFERROR(D16-$D$29,""),2) | E31: ==ROUND(IFERROR(E16-E29,""),2) | F31: ==ROUND(IFERROR(F16-F29,""),2) | I31: Saldo des Finanzberichts | J31: ==ROUND(IFERROR(J16-$J$29,""),2) | K31: ==ROUND(IFERROR(K16-$K$29,""),2) | L31: ==ROUND(IFERROR(L16-L29,""),2) | M31: ==ROUND(IFERROR(M16-M29,""),2) | P31: Saldo des Finanzberichts | Q31: ==ROUND(IFERROR(Q16-$Q$29,""),2) | R31: ==ROUND(IFERROR(R16-$R$29,""),2) | S31: ==ROUND(IFERROR(S16-S29,""),2) | T31: ==ROUND(IFERROR(T16-T29,""),2) | W31: Saldo des Finanzberichts | X31: ==ROUND(IFERROR(X16-$X$29,""),2) | Y31: ==ROUND(IFERROR(Y16-$Y$29,""),2) | Z31: ==ROUND(IFERROR(Z16-Z29,""),2) | AA31: ==ROUND(IFERROR(AA16-AA29,""),2) | AD31: Saldo des Finanzberichts | AE31: ==ROUND(IFERROR(AE16-$AE$29,""),2) | AF31: ==ROUND(IFERROR(AF16-$AF$29,""),2) | AG31: ==ROUND(IFERROR(AG16-AG29,""),2) | AH31: ==ROUND(IFERROR(AH16-AH29,""),2) | AK31: Saldo des Finanzberichts | AL31: ==ROUND(IFERROR(AL16-$AL$29,""),2) | AM31: ==ROUND(IFERROR(AM16-$AM$29,""),2) | AN31: ==ROUND(IFERROR(AN16-AN29,""),2) | AO31: ==ROUND(IFERROR(AO16-AO29,""),2) | AR31: Saldo des Finanzberichts | AS31: ==ROUND(IFERROR(AS16-$AS$29,""),2) | AT31: ==ROUND(IFERROR(AT16-$AT$29,""),2) | AU31: ==ROUND(IFERROR(AU16-AU29,""),2) | AV31: ==ROUND(IFERROR(AV16-AV29,""),2) | AY31: Saldo des Finanzberichts | AZ31: ==ROUND(IFERROR(AZ16-$AZ$29,""),2) | BA31: ==ROUND(IFERROR(BA16-$BA$29,""),2) | BB31: ==ROUND(IFERROR(BB16-BB29,""),2) | BC31: ==ROUND(IFERROR(BC16-BC29,""),2) | BF31: Saldo des Finanzberichts | BG31: ==ROUND(IFERROR(BG16-$BG$29,""),2) | BH31: ==ROUND(IFERROR(BH16-$BH$29,""),2) | BI31: ==ROUND(IFERROR(BI16-BI29,""),2) | BJ31: ==ROUND(IFERROR(BJ16-BJ29,""),2) | BM31: Saldo des Finanzberichts | BN31: ==ROUND(IFERROR(BN16-$BN$29,""),2) | BO31: ==ROUND(IFERROR(BO16-$BO$29,""),2) | BP31: ==ROUND(IFERROR(BP16-BP29,""),2) | BQ31: ==ROUND(IFERROR(BQ16-BQ29,""),2) | BT31: Saldo des Finanzberichts | BU31: ==ROUND(IFERROR(BU16-$BU$29,""),2) | BV31: ==ROUND(IFERROR(BV16-$BV$29,""),2) | BW31: ==ROUND(IFERROR(BW16-BW29,""),2) | BX31: ==ROUND(IFERROR(BX16-BX29,""),2) | CA31: Saldo des Finanzberichts | CB31: ==ROUND(IFERROR(CB16-$CB$29,""),2) | CC31: ==ROUND(IFERROR(CC16-$CC$29,""),2) | CD31: ==ROUND(IFERROR(CD16-CD29,""),2) | CE31: ==ROUND(IFERROR(CE16-CE29,""),2) | CH31: Saldo des Finanzberichts | CI31: ==ROUND(IFERROR(CI16-$CI$29,""),2) | CJ31: ==ROUND(IFERROR(CJ16-$CJ$29,""),2) | CK31: ==ROUND(IFERROR(CK16-CK29,""),2) | CL31: ==ROUND(IFERROR(CL16-CL29,""),2) | CO31: Saldo des Finanzberichts | CP31: ==ROUND(IFERROR(CP16-$CP$29,""),2) | CQ31: ==ROUND(IFERROR(CQ16-$CQ$29,""),2) | CR31: ==ROUND(IFERROR(CR16-CR29,""),2) | CS31: ==ROUND(IFERROR(CS16-CS29,""),2) | CV31: Saldo des Finanzberichts | CW31: ==ROUND(IFERROR(CW16-$CW$29,""),2) | CX31: ==ROUND(IFERROR(CX16-$CX$29,""),2) | CY31: ==ROUND(IFERROR(CY16-CY29,""),2) | CZ31: ==ROUND(IFERROR(CZ16-CZ29,""),2) | DC31: Saldo des Finanzberichts | DD31: ==ROUND(IFERROR(DD16-$DD$29,""),2) | DE31: ==ROUND(IFERROR(DE16-$DE$29,""),2) | DF31: ==ROUND(IFERROR(DF16-DF29,""),2) | DG31: ==ROUND(IFERROR(DG16-DG29,""),2) | DJ31: Saldo des Finanzberichts | DK31: ==ROUND(IFERROR(DK16-$DK$29,""),2) | DL31: ==ROUND(IFERROR(DL16-$DL$29,""),2) | DM31: ==ROUND(IFERROR(DM16-DM29,""),2) | DN31: ==ROUND(IFERROR(DN16-DN29,""),2) | DQ31: Saldo des Finanzberichts | DR31: ==ROUND(IFERROR(DR16-$DR$29,""),2) | DS31: ==ROUND(IFERROR(DS16-$DS$29,""),2) | DT31: ==ROUND(IFERROR(DT16-DT29,""),2) | DU31: ==ROUND(IFERROR(DU16-DU29,""),2)
B33: Aufschluesselung: | I33: Aufschluesselung: | P33: Aufschluesselung: | W33: Aufschluesselung: | AD33: Aufschluesselung: | AK33: Aufschluesselung: | AR33: Aufschluesselung: | AY33: Aufschluesselung: | BF33: Aufschluesselung: | BM33: Aufschluesselung: | BT33: Aufschluesselung: | CA33: Aufschluesselung: | CH33: Aufschluesselung: | CO33: Aufschluesselung: | CV33: Aufschluesselung: | DC33: Aufschluesselung: | DJ33: Aufschluesselung: | DQ33: Aufschluesselung:
B34: Bank | C34: 325000 | D34: ==IF(C34=0, 0, IF(ROUND(SUM(C35:C36), 2)=0, ROUND(D31 - 0, 2), ROUND(C34 / ROUND(SUM(C34:C36), 2) * D31, 2))) | I34: Bank | J34: 375000 | K34: ==IF(J34=0, 0, IF(ROUND(SUM(J35:J36), 2)=0, ROUND(K31 - 0, 2), ROUND(J34 / ROUND(SUM(J34:J36), 2) * K31, 2))) | P34: Bank | R34: ==IF(Q34=0, 0, IF(ROUND(SUM(Q35:Q36), 2)=0, ROUND(R31 - 0, 2), ROUND(Q34 / ROUND(SUM(Q34:Q36), 2) * R31, 2))) | W34: Bank | Y34: ==IF(X34=0, 0, IF(ROUND(SUM(X35:X36), 2)=0, ROUND(Y31 - 0, 2), ROUND(X34 / ROUND(SUM(X34:X36), 2) * Y31, 2))) | AD34: Bank | AF34: ==IF(AE34=0, 0, IF(ROUND(SUM(AE35:AE36), 2)=0, ROUND(AF31 - 0, 2), ROUND(AE34 / ROUND(SUM(AE34:AE36), 2) * AF31, 2))) | AK34: Bank | AM34: ==IF(AL34=0, 0, IF(ROUND(SUM(AL35:AL36), 2)=0, ROUND(AM31 - 0, 2), ROUND(AL34 / ROUND(SUM(AL34:AL36), 2) * AM31, 2))) | AR34: Bank | AT34: ==IF(AS34=0, 0, IF(ROUND(SUM(AS35:AS36), 2)=0, ROUND(AT31 - 0, 2), ROUND(AS34 / ROUND(SUM(AS34:AS36), 2) * AT31, 2))) | AY34: Bank | BA34: ==IF(AZ34=0, 0, IF(ROUND(SUM(AZ35:AZ36), 2)=0, ROUND(BA31 - 0, 2), ROUND(AZ34 / ROUND(SUM(AZ34:AZ36), 2) * BA31, 2))) | BF34: Bank | BH34: ==IF(BG34=0, 0, IF(ROUND(SUM(BG35:BG36), 2)=0, ROUND(BH31 - 0, 2), ROUND(BG34 / ROUND(SUM(BG34:BG36), 2) * BH31, 2))) | BM34: Bank | BO34: ==IF(BN34=0, 0, IF(ROUND(SUM(BN35:BN36), 2)=0, ROUND(BO31 - 0, 2), ROUND(BN34 / ROUND(SUM(BN34:BN36), 2) * BO31, 2))) | BT34: Bank | BV34: ==IF(BU34=0, 0, IF(ROUND(SUM(BU35:BU36), 2)=0, ROUND(BV31 - 0, 2), ROUND(BU34 / ROUND(SUM(BU34:BU36), 2) * BV31, 2))) | CA34: Bank | CC34: ==IF(CB34=0, 0, IF(ROUND(SUM(CB35:CB36), 2)=0, ROUND(CC31 - 0, 2), ROUND(CB34 / ROUND(SUM(CB34:CB36), 2) * CC31, 2))) | CH34: Bank | CJ34: ==IF(CI34=0, 0, IF(ROUND(SUM(CI35:CI36), 2)=0, ROUND(CJ31 - 0, 2), ROUND(CI34 / ROUND(SUM(CI34:CI36), 2) * CJ31, 2))) | CO34: Bank | CQ34: ==IF(CP34=0, 0, IF(ROUND(SUM(CP35:CP36), 2)=0, ROUND(CQ31 - 0, 2), ROUND(CP34 / ROUND(SUM(CP34:CP36), 2) * CQ31, 2))) | CV34: Bank | CX34: ==IF(CW34=0, 0, IF(ROUND(SUM(CW35:CW36), 2)=0, ROUND(CX31 - 0, 2), ROUND(CW34 / ROUND(SUM(CW34:CW36), 2) * CX31, 2))) | DC34: Bank | DE34: ==IF(DD34=0, 0, IF(ROUND(SUM(DD35:DD36), 2)=0, ROUND(DE31 - 0, 2), ROUND(DD34 / ROUND(SUM(DD34:DD36), 2) * DE31, 2))) | DJ34: Bank | DL34: ==IF(DK34=0, 0, IF(ROUND(SUM(DK35:DK36), 2)=0, ROUND(DL31 - 0, 2), ROUND(DK34 / ROUND(SUM(DK34:DK36), 2) * DL31, 2))) | DQ34: Bank | DS34: ==IF(DR34=0, 0, IF(ROUND(SUM(DR35:DR36), 2)=0, ROUND(DS31 - 0, 2), ROUND(DR34 / ROUND(SUM(DR34:DR36), 2) * DS31, 2)))
B35: Kasse | D35: ==IF(C35=0, 0, IF(ROUND(SUM(C36:C36), 2)=0, ROUND(D31 - SUM(D34:D34), 2), ROUND(C35 / ROUND(SUM(C34:C36), 2) * D31, 2))) | I35: Kasse | K35: ==IF(J35=0, 0, IF(ROUND(SUM(J36:J36), 2)=0, ROUND(K31 - SUM(K34:K34), 2), ROUND(J35 / ROUND(SUM(J34:J36), 2) * K31, 2))) | P35: Kasse | R35: ==IF(Q35=0, 0, IF(ROUND(SUM(Q36:Q36), 2)=0, ROUND(R31 - SUM(R34:R34), 2), ROUND(Q35 / ROUND(SUM(Q34:Q36), 2) * R31, 2))) | W35: Kasse | Y35: ==IF(X35=0, 0, IF(ROUND(SUM(X36:X36), 2)=0, ROUND(Y31 - SUM(Y34:Y34), 2), ROUND(X35 / ROUND(SUM(X34:X36), 2) * Y31, 2))) | AD35: Kasse | AF35: ==IF(AE35=0, 0, IF(ROUND(SUM(AE36:AE36), 2)=0, ROUND(AF31 - SUM(AF34:AF34), 2), ROUND(AE35 / ROUND(SUM(AE34:AE36), 2) * AF31, 2))) | AK35: Kasse | AM35: ==IF(AL35=0, 0, IF(ROUND(SUM(AL36:AL36), 2)=0, ROUND(AM31 - SUM(AM34:AM34), 2), ROUND(AL35 / ROUND(SUM(AL34:AL36), 2) * AM31, 2))) | AR35: Kasse | AT35: ==IF(AS35=0, 0, IF(ROUND(SUM(AS36:AS36), 2)=0, ROUND(AT31 - SUM(AT34:AT34), 2), ROUND(AS35 / ROUND(SUM(AS34:AS36), 2) * AT31, 2))) | AY35: Kasse | BA35: ==IF(AZ35=0, 0, IF(ROUND(SUM(AZ36:AZ36), 2)=0, ROUND(BA31 - SUM(BA34:BA34), 2), ROUND(AZ35 / ROUND(SUM(AZ34:AZ36), 2) * BA31, 2))) | BF35: Kasse | BH35: ==IF(BG35=0, 0, IF(ROUND(SUM(BG36:BG36), 2)=0, ROUND(BH31 - SUM(BH34:BH34), 2), ROUND(BG35 / ROUND(SUM(BG34:BG36), 2) * BH31, 2))) | BM35: Kasse | BO35: ==IF(BN35=0, 0, IF(ROUND(SUM(BN36:BN36), 2)=0, ROUND(BO31 - SUM(BO34:BO34), 2), ROUND(BN35 / ROUND(SUM(BN34:BN36), 2) * BO31, 2))) | BT35: Kasse | BV35: ==IF(BU35=0, 0, IF(ROUND(SUM(BU36:BU36), 2)=0, ROUND(BV31 - SUM(BV34:BV34), 2), ROUND(BU35 / ROUND(SUM(BU34:BU36), 2) * BV31, 2))) | CA35: Kasse | CC35: ==IF(CB35=0, 0, IF(ROUND(SUM(CB36:CB36), 2)=0, ROUND(CC31 - SUM(CC34:CC34), 2), ROUND(CB35 / ROUND(SUM(CB34:CB36), 2) * CC31, 2))) | CH35: Kasse | CJ35: ==IF(CI35=0, 0, IF(ROUND(SUM(CI36:CI36), 2)=0, ROUND(CJ31 - SUM(CJ34:CJ34), 2), ROUND(CI35 / ROUND(SUM(CI34:CI36), 2) * CJ31, 2))) | CO35: Kasse | CQ35: ==IF(CP35=0, 0, IF(ROUND(SUM(CP36:CP36), 2)=0, ROUND(CQ31 - SUM(CQ34:CQ34), 2), ROUND(CP35 / ROUND(SUM(CP34:CP36), 2) * CQ31, 2))) | CV35: Kasse | CX35: ==IF(CW35=0, 0, IF(ROUND(SUM(CW36:CW36), 2)=0, ROUND(CX31 - SUM(CX34:CX34), 2), ROUND(CW35 / ROUND(SUM(CW34:CW36), 2) * CX31, 2))) | DC35: Kasse | DE35: ==IF(DD35=0, 0, IF(ROUND(SUM(DD36:DD36), 2)=0, ROUND(DE31 - SUM(DE34:DE34), 2), ROUND(DD35 / ROUND(SUM(DD34:DD36), 2) * DE31, 2))) | DJ35: Kasse | DL35: ==IF(DK35=0, 0, IF(ROUND(SUM(DK36:DK36), 2)=0, ROUND(DL31 - SUM(DL34:DL34), 2), ROUND(DK35 / ROUND(SUM(DK34:DK36), 2) * DL31, 2))) | DQ35: Kasse | DS35: ==IF(DR35=0, 0, IF(ROUND(SUM(DR36:DR36), 2)=0, ROUND(DS31 - SUM(DS34:DS34), 2), ROUND(DR35 / ROUND(SUM(DR34:DR36), 2) * DS31, 2)))
B36: Sonstiges | D36: ==IF(C36=0, 0, ROUND(D31 - SUM(D34:D35), 2)) | I36: Sonstiges | K36: ==IF(J36=0, 0, ROUND(K31 - SUM(K34:K35), 2)) | P36: Sonstiges | R36: ==IF(Q36=0, 0, ROUND(R31 - SUM(R34:R35), 2)) | W36: Sonstiges | Y36: ==IF(X36=0, 0, ROUND(Y31 - SUM(Y34:Y35), 2)) | AD36: Sonstiges | AF36: ==IF(AE36=0, 0, ROUND(AF31 - SUM(AF34:AF35), 2)) | AK36: Sonstiges | AM36: ==IF(AL36=0, 0, ROUND(AM31 - SUM(AM34:AM35), 2)) | AR36: Sonstiges | AT36: ==IF(AS36=0, 0, ROUND(AT31 - SUM(AT34:AT35), 2)) | AY36: Sonstiges | BA36: ==IF(AZ36=0, 0, ROUND(BA31 - SUM(BA34:BA35), 2)) | BF36: Sonstiges | BH36: ==IF(BG36=0, 0, ROUND(BH31 - SUM(BH34:BH35), 2)) | BM36: Sonstiges | BO36: ==IF(BN36=0, 0, ROUND(BO31 - SUM(BO34:BO35), 2)) | BT36: Sonstiges | BV36: ==IF(BU36=0, 0, ROUND(BV31 - SUM(BV34:BV35), 2)) | CA36: Sonstiges | CC36: ==IF(CB36=0, 0, ROUND(CC31 - SUM(CC34:CC35), 2)) | CH36: Sonstiges | CJ36: ==IF(CI36=0, 0, ROUND(CJ31 - SUM(CJ34:CJ35), 2)) | CO36: Sonstiges | CQ36: ==IF(CP36=0, 0, ROUND(CQ31 - SUM(CQ34:CQ35), 2)) | CV36: Sonstiges | CX36: ==IF(CW36=0, 0, ROUND(CX31 - SUM(CX34:CX35), 2)) | DC36: Sonstiges | DE36: ==IF(DD36=0, 0, ROUND(DE31 - SUM(DE34:DE35), 2)) | DJ36: Sonstiges | DL36: ==IF(DK36=0, 0, ROUND(DL31 - SUM(DL34:DL35), 2)) | DQ36: Sonstiges | DS36: ==IF(DR36=0, 0, ROUND(DS31 - SUM(DS34:DS35), 2))
B38: Differenz (Pruefung): | C38: ==ROUND(IFERROR(C31-SUM(C34:C36),""),2) | D38: ==ROUND(IFERROR(D31-SUM(D34:D36),""),2) | I38: Differenz (Pruefung): | J38: ==ROUND(IFERROR(J31-SUM(J34:J36),""),2) | K38: ==ROUND(IFERROR(K31-SUM(K34:K36),""),2) | P38: Differenz (Pruefung): | Q38: ==ROUND(IFERROR(Q31-SUM(Q34:Q36),""),2) | R38: ==ROUND(IFERROR(R31-SUM(R34:R36),""),2) | W38: Differenz (Pruefung): | X38: ==ROUND(IFERROR(X31-SUM(X34:X36),""),2) | Y38: ==ROUND(IFERROR(Y31-SUM(Y34:Y36),""),2) | AD38: Differenz (Pruefung): | AE38: ==ROUND(IFERROR(AE31-SUM(AE34:AE36),""),2) | AF38: ==ROUND(IFERROR(AF31-SUM(AF34:AF36),""),2) | AK38: Differenz (Pruefung): | AL38: ==ROUND(IFERROR(AL31-SUM(AL34:AL36),""),2) | AM38: ==ROUND(IFERROR(AM31-SUM(AM34:AM36),""),2) | AR38: Differenz (Pruefung): | AS38: ==ROUND(IFERROR(AS31-SUM(AS34:AS36),""),2) | AT38: ==ROUND(IFERROR(AT31-SUM(AT34:AT36),""),2) | AY38: Differenz (Pruefung): | AZ38: ==ROUND(IFERROR(AZ31-SUM(AZ34:AZ36),""),2) | BA38: ==ROUND(IFERROR(BA31-SUM(BA34:BA36),""),2) | BF38: Differenz (Pruefung): | BG38: ==ROUND(IFERROR(BG31-SUM(BG34:BG36),""),2) | BH38: ==ROUND(IFERROR(BH31-SUM(BH34:BH36),""),2) | BM38: Differenz (Pruefung): | BN38: ==ROUND(IFERROR(BN31-SUM(BN34:BN36),""),2) | BO38: ==ROUND(IFERROR(BO31-SUM(BO34:BO36),""),2) | BT38: Differenz (Pruefung): | BU38: ==ROUND(IFERROR(BU31-SUM(BU34:BU36),""),2) | BV38: ==ROUND(IFERROR(BV31-SUM(BV34:BV36),""),2) | CA38: Differenz (Pruefung): | CB38: ==ROUND(IFERROR(CB31-SUM(CB34:CB36),""),2) | CC38: ==ROUND(IFERROR(CC31-SUM(CC34:CC36),""),2) | CH38: Differenz (Pruefung): | CI38: ==ROUND(IFERROR(CI31-SUM(CI34:CI36),""),2) | CJ38: ==ROUND(IFERROR(CJ31-SUM(CJ34:CJ36),""),2) | CO38: Differenz (Pruefung): | CP38: ==ROUND(IFERROR(CP31-SUM(CP34:CP36),""),2) | CQ38: ==ROUND(IFERROR(CQ31-SUM(CQ34:CQ36),""),2) | CV38: Differenz (Pruefung): | CW38: ==ROUND(IFERROR(CW31-SUM(CW34:CW36),""),2) | CX38: ==ROUND(IFERROR(CX31-SUM(CX34:CX36),""),2) | DC38: Differenz (Pruefung): | DD38: ==ROUND(IFERROR(DD31-SUM(DD34:DD36),""),2) | DE38: ==ROUND(IFERROR(DE31-SUM(DE34:DE36),""),2) | DJ38: Differenz (Pruefung): | DK38: ==ROUND(IFERROR(DK31-SUM(DK34:DK36),""),2) | DL38: ==ROUND(IFERROR(DL31-SUM(DL34:DL36),""),2) | DQ38: Differenz (Pruefung): | DR38: ==ROUND(IFERROR(DR31-SUM(DR34:DR36),""),2) | DS38: ==ROUND(IFERROR(DS31-SUM(DS34:DS36),""),2)
B41: Einnahmen (Explizite Kurseingabe) | I41: Einnahmen (Explizite Kurseingabe) | P41: Einnahmen (Explizite Kurseingabe) | W41: Einnahmen (Explizite Kurseingabe) | AD41: Einnahmen (Explizite Kurseingabe) | AK41: Einnahmen (Explizite Kurseingabe) | AR41: Einnahmen (Explizite Kurseingabe) | AY41: Einnahmen (Explizite Kurseingabe) | BF41: Einnahmen (Explizite Kurseingabe) | BM41: Einnahmen (Explizite Kurseingabe) | BT41: Einnahmen (Explizite Kurseingabe) | CA41: Einnahmen (Explizite Kurseingabe) | CH41: Einnahmen (Explizite Kurseingabe) | CO41: Einnahmen (Explizite Kurseingabe) | CV41: Einnahmen (Explizite Kurseingabe) | DC41: Einnahmen (Explizite Kurseingabe) | DJ41: Einnahmen (Explizite Kurseingabe) | DQ41: Einnahmen (Explizite Kurseingabe)
B42: Typ | C42: Geber | D42: Einnahmen (LC) | E42: Einnahmen (EUR) | F42: Kurs | I42: Typ | J42: Geber | K42: Einnahmen (LC) | L42: Einnahmen (EUR) | M42: Kurs | P42: Typ | Q42: Geber | R42: Einnahmen (LC) | S42: Einnahmen (EUR) | T42: Kurs | W42: Typ | X42: Geber | Y42: Einnahmen (LC) | Z42: Einnahmen (EUR) | AA42: Kurs | AD42: Typ | AE42: Geber | AF42: Einnahmen (LC) | AG42: Einnahmen (EUR) | AH42: Kurs | AK42: Typ | AL42: Geber | AM42: Einnahmen (LC) | AN42: Einnahmen (EUR) | AO42: Kurs | AR42: Typ | AS42: Geber | AT42: Einnahmen (LC) | AU42: Einnahmen (EUR) | AV42: Kurs | AY42: Typ | AZ42: Geber | BA42: Einnahmen (LC) | BB42: Einnahmen (EUR) | BC42: Kurs | BF42: Typ | BG42: Geber | BH42: Einnahmen (LC) | BI42: Einnahmen (EUR) | BJ42: Kurs | BM42: Typ | BN42: Geber | BO42: Einnahmen (LC) | BP42: Einnahmen (EUR) | BQ42: Kurs | BT42: Typ | BU42: Geber | BV42: Einnahmen (LC) | BW42: Einnahmen (EUR) | BX42: Kurs | CA42: Typ | CB42: Geber | CC42: Einnahmen (LC) | CD42: Einnahmen (EUR) | CE42: Kurs | CH42: Typ | CI42: Geber | CJ42: Einnahmen (LC) | CK42: Einnahmen (EUR) | CL42: Kurs | CO42: Typ | CP42: Geber | CQ42: Einnahmen (LC) | CR42: Einnahmen (EUR) | CS42: Kurs | CV42: Typ | CW42: Geber | CX42: Einnahmen (LC) | CY42: Einnahmen (EUR) | CZ42: Kurs | DC42: Typ | DD42: Geber | DE42: Einnahmen (LC) | DF42: Einnahmen (EUR) | DG42: Kurs | DJ42: Typ | DK42: Geber | DL42: Einnahmen (LC) | DM42: Einnahmen (EUR) | DN42: Kurs | DQ42: Typ | DR42: Geber | DS42: Einnahmen (LC) | DT42: Einnahmen (EUR) | DU42: Kurs
B43: Saldo des Vorprojekts | D43: ==ROUND(C11,2) | E43: ==ROUND(D11,2) | F43: ==ROUND(IFERROR(D43/E43,0),6) | I43: Saldo der Vorperiode | K43: ==ROUND(J11,2) | L43: ==ROUND(K11,2) | M43: ==ROUND(IFERROR(K43/L43,0),6) | P43: Saldo der Vorperiode | R43: ==ROUND(Q11,2) | S43: ==ROUND(R11,2) | T43: ==ROUND(IFERROR(R43/S43,0),6) | W43: Saldo der Vorperiode | Y43: ==ROUND(X11,2) | Z43: ==ROUND(Y11,2) | AA43: ==ROUND(IFERROR(Y43/Z43,0),6) | AD43: Saldo der Vorperiode | AF43: ==ROUND(AE11,2) | AG43: ==ROUND(AF11,2) | AH43: ==ROUND(IFERROR(AF43/AG43,0),6) | AK43: Saldo der Vorperiode | AM43: ==ROUND(AL11,2) | AN43: ==ROUND(AM11,2) | AO43: ==ROUND(IFERROR(AM43/AN43,0),6) | AR43: Saldo der Vorperiode | AT43: ==ROUND(AS11,2) | AU43: ==ROUND(AT11,2) | AV43: ==ROUND(IFERROR(AT43/AU43,0),6) | AY43: Saldo der Vorperiode | BA43: ==ROUND(AZ11,2) | BB43: ==ROUND(BA11,2) | BC43: ==ROUND(IFERROR(BA43/BB43,0),6) | BF43: Saldo der Vorperiode | BH43: ==ROUND(BG11,2) | BI43: ==ROUND(BH11,2) | BJ43: ==ROUND(IFERROR(BH43/BI43,0),6) | BM43: Saldo der Vorperiode | BO43: ==ROUND(BN11,2) | BP43: ==ROUND(BO11,2) | BQ43: ==ROUND(IFERROR(BO43/BP43,0),6) | BT43: Saldo der Vorperiode | BV43: ==ROUND(BU11,2) | BW43: ==ROUND(BV11,2) | BX43: ==ROUND(IFERROR(BV43/BW43,0),6) | CA43: Saldo der Vorperiode | CC43: ==ROUND(CB11,2) | CD43: ==ROUND(CC11,2) | CE43: ==ROUND(IFERROR(CC43/CD43,0),6) | CH43: Saldo der Vorperiode | CJ43: ==ROUND(CI11,2) | CK43: ==ROUND(CJ11,2) | CL43: ==ROUND(IFERROR(CJ43/CK43,0),6) | CO43: Saldo der Vorperiode | CQ43: ==ROUND(CP11,2) | CR43: ==ROUND(CQ11,2) | CS43: ==ROUND(IFERROR(CQ43/CR43,0),6) | CV43: Saldo der Vorperiode | CX43: ==ROUND(CW11,2) | CY43: ==ROUND(CX11,2) | CZ43: ==ROUND(IFERROR(CX43/CY43,0),6) | DC43: Saldo der Vorperiode | DE43: ==ROUND(DD11,2) | DF43: ==ROUND(DE11,2) | DG43: ==ROUND(IFERROR(DE43/DF43,0),6) | DJ43: Saldo der Vorperiode | DL43: ==ROUND(DK11,2) | DM43: ==ROUND(DL11,2) | DN43: ==ROUND(IFERROR(DL43/DM43,0),6) | DQ43: Saldo der Vorperiode | DS43: ==ROUND(DR11,2) | DT43: ==ROUND(DS11,2) | DU43: ==ROUND(IFERROR(DS43/DT43,0),6)
B44: KMW-Mittel | C44: KMW | D44: 1250000 | E44: 10000 | F44: ==ROUND(IFERROR(D44/E44,0),6) | I44: KMW-Mittel | J44: KMW | K44: 1000000 | L44: 8000 | M44: ==ROUND(IFERROR(K44/L44,0),6) | P44: KMW-Mittel | Q44: KMW | T44: ==ROUND(IFERROR(R44/S44,0),6) | W44: KMW-Mittel | X44: KMW | AA44: ==ROUND(IFERROR(Y44/Z44,0),6) | AD44: KMW-Mittel | AE44: KMW | AH44: ==ROUND(IFERROR(AF44/AG44,0),6) | AK44: KMW-Mittel | AL44: KMW | AO44: ==ROUND(IFERROR(AM44/AN44,0),6) | AR44: KMW-Mittel | AS44: KMW | AV44: ==ROUND(IFERROR(AT44/AU44,0),6) | AY44: KMW-Mittel | AZ44: KMW | BC44: ==ROUND(IFERROR(BA44/BB44,0),6) | BF44: KMW-Mittel | BG44: KMW | BJ44: ==ROUND(IFERROR(BH44/BI44,0),6) | BM44: KMW-Mittel | BN44: KMW | BQ44: ==ROUND(IFERROR(BO44/BP44,0),6) | BT44: KMW-Mittel | BU44: KMW | BX44: ==ROUND(IFERROR(BV44/BW44,0),6) | CA44: KMW-Mittel | CB44: KMW | CE44: ==ROUND(IFERROR(CC44/CD44,0),6) | CH44: KMW-Mittel | CI44: KMW | CL44: ==ROUND(IFERROR(CJ44/CK44,0),6) | CO44: KMW-Mittel | CP44: KMW | CS44: ==ROUND(IFERROR(CQ44/CR44,0),6) | CV44: KMW-Mittel | CW44: KMW | CZ44: ==ROUND(IFERROR(CX44/CY44,0),6) | DC44: KMW-Mittel | DD44: KMW | DG44: ==ROUND(IFERROR(DE44/DF44,0),6) | DJ44: KMW-Mittel | DK44: KMW | DN44: ==ROUND(IFERROR(DL44/DM44,0),6) | DQ44: KMW-Mittel | DR44: KMW | DU44: ==ROUND(IFERROR(DS44/DT44,0),6)
F45: ==ROUND(IFERROR(D45/E45,0),6) | M45: ==ROUND(IFERROR(K45/L45,0),6) | T45: ==ROUND(IFERROR(R45/S45,0),6) | AA45: ==ROUND(IFERROR(Y45/Z45,0),6) | AH45: ==ROUND(IFERROR(AF45/AG45,0),6) | AO45: ==ROUND(IFERROR(AM45/AN45,0),6) | AV45: ==ROUND(IFERROR(AT45/AU45,0),6) | BC45: ==ROUND(IFERROR(BA45/BB45,0),6) | BJ45: ==ROUND(IFERROR(BH45/BI45,0),6) | BQ45: ==ROUND(IFERROR(BO45/BP45,0),6) | BX45: ==ROUND(IFERROR(BV45/BW45,0),6) | CE45: ==ROUND(IFERROR(CC45/CD45,0),6) | CL45: ==ROUND(IFERROR(CJ45/CK45,0),6) | CS45: ==ROUND(IFERROR(CQ45/CR45,0),6) | CZ45: ==ROUND(IFERROR(CX45/CY45,0),6) | DG45: ==ROUND(IFERROR(DE45/DF45,0),6) | DN45: ==ROUND(IFERROR(DL45/DM45,0),6) | DU45: ==ROUND(IFERROR(DS45/DT45,0),6)
F46: ==ROUND(IFERROR(D46/E46,0),6) | M46: ==ROUND(IFERROR(K46/L46,0),6) | T46: ==ROUND(IFERROR(R46/S46,0),6) | AA46: ==ROUND(IFERROR(Y46/Z46,0),6) | AH46: ==ROUND(IFERROR(AF46/AG46,0),6) | AO46: ==ROUND(IFERROR(AM46/AN46,0),6) | AV46: ==ROUND(IFERROR(AT46/AU46,0),6) | BC46: ==ROUND(IFERROR(BA46/BB46,0),6) | BJ46: ==ROUND(IFERROR(BH46/BI46,0),6) | BQ46: ==ROUND(IFERROR(BO46/BP46,0),6) | BX46: ==ROUND(IFERROR(BV46/BW46,0),6) | CE46: ==ROUND(IFERROR(CC46/CD46,0),6) | CL46: ==ROUND(IFERROR(CJ46/CK46,0),6) | CS46: ==ROUND(IFERROR(CQ46/CR46,0),6) | CZ46: ==ROUND(IFERROR(CX46/CY46,0),6) | DG46: ==ROUND(IFERROR(DE46/DF46,0),6) | DN46: ==ROUND(IFERROR(DL46/DM46,0),6) | DU46: ==ROUND(IFERROR(DS46/DT46,0),6)
F47: ==ROUND(IFERROR(D47/E47,0),6) | M47: ==ROUND(IFERROR(K47/L47,0),6) | T47: ==ROUND(IFERROR(R47/S47,0),6) | AA47: ==ROUND(IFERROR(Y47/Z47,0),6) | AH47: ==ROUND(IFERROR(AF47/AG47,0),6) | AO47: ==ROUND(IFERROR(AM47/AN47,0),6) | AV47: ==ROUND(IFERROR(AT47/AU47,0),6) | BC47: ==ROUND(IFERROR(BA47/BB47,0),6) | BJ47: ==ROUND(IFERROR(BH47/BI47,0),6) | BQ47: ==ROUND(IFERROR(BO47/BP47,0),6) | BX47: ==ROUND(IFERROR(BV47/BW47,0),6) | CE47: ==ROUND(IFERROR(CC47/CD47,0),6) | CL47: ==ROUND(IFERROR(CJ47/CK47,0),6) | CS47: ==ROUND(IFERROR(CQ47/CR47,0),6) | CZ47: ==ROUND(IFERROR(CX47/CY47,0),6) | DG47: ==ROUND(IFERROR(DE47/DF47,0),6) | DN47: ==ROUND(IFERROR(DL47/DM47,0),6) | DU47: ==ROUND(IFERROR(DS47/DT47,0),6)
B48: Gesamteinnahmen in Periode | C48: Durchschnittskurs: | D48: ==ROUND(SUBTOTAL(109,$D$43:$D$47),2) | E48: ==ROUND(SUBTOTAL(109,$E$43:$E$47),2) | F48: ==ROUND(IFERROR(D48/E48,0),6) | I48: Gesamteinnahmen in Periode | J48: Durchschnittskurs: | K48: ==ROUND(SUBTOTAL(109,$K$43:$K$47),2) | L48: ==ROUND(SUBTOTAL(109,$L$43:$L$47),2) | M48: ==ROUND(IFERROR(K48/L48,0),6) | P48: Gesamteinnahmen in Periode | Q48: Durchschnittskurs: | R48: ==ROUND(SUBTOTAL(109,$R$43:$R$47),2) | S48: ==ROUND(SUBTOTAL(109,$S$43:$S$47),2) | T48: ==ROUND(IFERROR(R48/S48,0),6) | W48: Gesamteinnahmen in Periode | X48: Durchschnittskurs: | Y48: ==ROUND(SUBTOTAL(109,$Y$43:$Y$47),2) | Z48: ==ROUND(SUBTOTAL(109,$Z$43:$Z$47),2) | AA48: ==ROUND(IFERROR(Y48/Z48,0),6) | AD48: Gesamteinnahmen in Periode | AE48: Durchschnittskurs: | AF48: ==ROUND(SUBTOTAL(109,$AF$43:$AF$47),2) | AG48: ==ROUND(SUBTOTAL(109,$AG$43:$AG$47),2) | AH48: ==ROUND(IFERROR(AF48/AG48,0),6) | AK48: Gesamteinnahmen in Periode | AL48: Durchschnittskurs: | AM48: ==ROUND(SUBTOTAL(109,$AM$43:$AM$47),2) | AN48: ==ROUND(SUBTOTAL(109,$AN$43:$AN$47),2) | AO48: ==ROUND(IFERROR(AM48/AN48,0),6) | AR48: Gesamteinnahmen in Periode | AS48: Durchschnittskurs: | AT48: ==ROUND(SUBTOTAL(109,$AT$43:$AT$47),2) | AU48: ==ROUND(SUBTOTAL(109,$AU$43:$AU$47),2) | AV48: ==ROUND(IFERROR(AT48/AU48,0),6) | AY48: Gesamteinnahmen in Periode | AZ48: Durchschnittskurs: | BA48: ==ROUND(SUBTOTAL(109,$BA$43:$BA$47),2) | BB48: ==ROUND(SUBTOTAL(109,$BB$43:$BB$47),2) | BC48: ==ROUND(IFERROR(BA48/BB48,0),6) | BF48: Gesamteinnahmen in Periode | BG48: Durchschnittskurs: | BH48: ==ROUND(SUBTOTAL(109,$BH$43:$BH$47),2) | BI48: ==ROUND(SUBTOTAL(109,$BI$43:$BI$47),2) | BJ48: ==ROUND(IFERROR(BH48/BI48,0),6) | BM48: Gesamteinnahmen in Periode | BN48: Durchschnittskurs: | BO48: ==ROUND(SUBTOTAL(109,$BO$43:$BO$47),2) | BP48: ==ROUND(SUBTOTAL(109,$BP$43:$BP$47),2) | BQ48: ==ROUND(IFERROR(BO48/BP48,0),6) | BT48: Gesamteinnahmen in Periode | BU48: Durchschnittskurs: | BV48: ==ROUND(SUBTOTAL(109,$BV$43:$BV$47),2) | BW48: ==ROUND(SUBTOTAL(109,$BW$43:$BW$47),2) | BX48: ==ROUND(IFERROR(BV48/BW48,0),6) | CA48: Gesamteinnahmen in Periode | CB48: Durchschnittskurs: | CC48: ==ROUND(SUBTOTAL(109,$CC$43:$CC$47),2) | CD48: ==ROUND(SUBTOTAL(109,$CD$43:$CD$47),2) | CE48: ==ROUND(IFERROR(CC48/CD48,0),6) | CH48: Gesamteinnahmen in Periode | CI48: Durchschnittskurs: | CJ48: ==ROUND(SUBTOTAL(109,$CJ$43:$CJ$47),2) | CK48: ==ROUND(SUBTOTAL(109,$CK$43:$CK$47),2) | CL48: ==ROUND(IFERROR(CJ48/CK48,0),6) | CO48: Gesamteinnahmen in Periode | CP48: Durchschnittskurs: | CQ48: ==ROUND(SUBTOTAL(109,$CQ$43:$CQ$47),2) | CR48: ==ROUND(SUBTOTAL(109,$CR$43:$CR$47),2) | CS48: ==ROUND(IFERROR(CQ48/CR48,0),6) | CV48: Gesamteinnahmen in Periode | CW48: Durchschnittskurs: | CX48: ==ROUND(SUBTOTAL(109,$CX$43:$CX$47),2) | CY48: ==ROUND(SUBTOTAL(109,$CY$43:$CY$47),2) | CZ48: ==ROUND(IFERROR(CX48/CY48,0),6) | DC48: Gesamteinnahmen in Periode | DD48: Durchschnittskurs: | DE48: ==ROUND(SUBTOTAL(109,$DE$43:$DE$47),2) | DF48: ==ROUND(SUBTOTAL(109,$DF$43:$DF$47),2) | DG48: ==ROUND(IFERROR(DE48/DF48,0),6) | DJ48: Gesamteinnahmen in Periode | DK48: Durchschnittskurs: | DL48: ==ROUND(SUBTOTAL(109,$DL$43:$DL$47),2) | DM48: ==ROUND(SUBTOTAL(109,$DM$43:$DM$47),2) | DN48: ==ROUND(IFERROR(DL48/DM48,0),6) | DQ48: Gesamteinnahmen in Periode | DR48: Durchschnittskurs: | DS48: ==ROUND(SUBTOTAL(109,$DS$43:$DS$47),2) | DT48: ==ROUND(SUBTOTAL(109,$DT$43:$DT$47),2) | DU48: ==ROUND(IFERROR(DS48/DT48,0),6)
B50: Einnahmen (Durchschnittskurs) | I50: Einnahmen (Durchschnittskurs) | P50: Einnahmen (Durchschnittskurs) | W50: Einnahmen (Durchschnittskurs) | AD50: Einnahmen (Durchschnittskurs) | AK50: Einnahmen (Durchschnittskurs) | AR50: Einnahmen (Durchschnittskurs) | AY50: Einnahmen (Durchschnittskurs) | BF50: Einnahmen (Durchschnittskurs) | BM50: Einnahmen (Durchschnittskurs) | BT50: Einnahmen (Durchschnittskurs) | CA50: Einnahmen (Durchschnittskurs) | CH50: Einnahmen (Durchschnittskurs) | CO50: Einnahmen (Durchschnittskurs) | CV50: Einnahmen (Durchschnittskurs) | DC50: Einnahmen (Durchschnittskurs) | DJ50: Einnahmen (Durchschnittskurs) | DQ50: Einnahmen (Durchschnittskurs)
B51: Typ | C51: Geber | D51: Einnahmen (LC) | E51: Einnahmen (EUR) | F51: Kurs | I51: Typ | J51: Geber | K51: Einnahmen (LC) | L51: Einnahmen (EUR) | M51: Kurs | P51: Typ | Q51: Geber | R51: Einnahmen (LC) | S51: Einnahmen (EUR) | T51: Kurs | W51: Typ | X51: Geber | Y51: Einnahmen (LC) | Z51: Einnahmen (EUR) | AA51: Kurs | AD51: Typ | AE51: Geber | AF51: Einnahmen (LC) | AG51: Einnahmen (EUR) | AH51: Kurs | AK51: Typ | AL51: Geber | AM51: Einnahmen (LC) | AN51: Einnahmen (EUR) | AO51: Kurs | AR51: Typ | AS51: Geber | AT51: Einnahmen (LC) | AU51: Einnahmen (EUR) | AV51: Kurs | AY51: Typ | AZ51: Geber | BA51: Einnahmen (LC) | BB51: Einnahmen (EUR) | BC51: Kurs | BF51: Typ | BG51: Geber | BH51: Einnahmen (LC) | BI51: Einnahmen (EUR) | BJ51: Kurs | BM51: Typ | BN51: Geber | BO51: Einnahmen (LC) | BP51: Einnahmen (EUR) | BQ51: Kurs | BT51: Typ | BU51: Geber | BV51: Einnahmen (LC) | BW51: Einnahmen (EUR) | BX51: Kurs | CA51: Typ | CB51: Geber | CC51: Einnahmen (LC) | CD51: Einnahmen (EUR) | CE51: Kurs | CH51: Typ | CI51: Geber | CJ51: Einnahmen (LC) | CK51: Einnahmen (EUR) | CL51: Kurs | CO51: Typ | CP51: Geber | CQ51: Einnahmen (LC) | CR51: Einnahmen (EUR) | CS51: Kurs | CV51: Typ | CW51: Geber | CX51: Einnahmen (LC) | CY51: Einnahmen (EUR) | CZ51: Kurs | DC51: Typ | DD51: Geber | DE51: Einnahmen (LC) | DF51: Einnahmen (EUR) | DG51: Kurs | DJ51: Typ | DK51: Geber | DL51: Einnahmen (LC) | DM51: Einnahmen (EUR) | DN51: Kurs | DQ51: Typ | DR51: Geber | DS51: Einnahmen (LC) | DT51: Einnahmen (EUR) | DU51: Kurs
B52: Eigenmittel | C52: Projektpartner | D52: 250000 | E52: ==IFERROR(ROUND(D52/$C$8,2),0) | F52: ==ROUND(IFERROR(D52/E52,0),6) | I52: Eigenmittel | J52: Projektpartner | K52: 200000 | L52: ==IFERROR(ROUND(K52/$J$8,2),0) | M52: ==ROUND(IFERROR(K52/L52,0),6) | P52: Eigenmittel | Q52: Projektpartner | S52: ==IFERROR(ROUND(R52/$Q$8,2),0) | T52: ==ROUND(IFERROR(R52/S52,0),6) | W52: Eigenmittel | X52: Projektpartner | Z52: ==IFERROR(ROUND(Y52/$X$8,2),0) | AA52: ==ROUND(IFERROR(Y52/Z52,0),6) | AD52: Eigenmittel | AE52: Projektpartner | AG52: ==IFERROR(ROUND(AF52/$AE$8,2),0) | AH52: ==ROUND(IFERROR(AF52/AG52,0),6) | AK52: Eigenmittel | AL52: Projektpartner | AN52: ==IFERROR(ROUND(AM52/$AL$8,2),0) | AO52: ==ROUND(IFERROR(AM52/AN52,0),6) | AR52: Eigenmittel | AS52: Projektpartner | AU52: ==IFERROR(ROUND(AT52/$AS$8,2),0) | AV52: ==ROUND(IFERROR(AT52/AU52,0),6) | AY52: Eigenmittel | AZ52: Projektpartner | BB52: ==IFERROR(ROUND(BA52/$AZ$8,2),0) | BC52: ==ROUND(IFERROR(BA52/BB52,0),6) | BF52: Eigenmittel | BG52: Projektpartner | BI52: ==IFERROR(ROUND(BH52/$BG$8,2),0) | BJ52: ==ROUND(IFERROR(BH52/BI52,0),6) | BM52: Eigenmittel | BN52: Projektpartner | BP52: ==IFERROR(ROUND(BO52/$BN$8,2),0) | BQ52: ==ROUND(IFERROR(BO52/BP52,0),6) | BT52: Eigenmittel | BU52: Projektpartner | BW52: ==IFERROR(ROUND(BV52/$BU$8,2),0) | BX52: ==ROUND(IFERROR(BV52/BW52,0),6) | CA52: Eigenmittel | CB52: Projektpartner | CD52: ==IFERROR(ROUND(CC52/$CB$8,2),0) | CE52: ==ROUND(IFERROR(CC52/CD52,0),6) | CH52: Eigenmittel | CI52: Projektpartner | CK52: ==IFERROR(ROUND(CJ52/$CI$8,2),0) | CL52: ==ROUND(IFERROR(CJ52/CK52,0),6) | CO52: Eigenmittel | CP52: Projektpartner | CR52: ==IFERROR(ROUND(CQ52/$CP$8,2),0) | CS52: ==ROUND(IFERROR(CQ52/CR52,0),6) | CV52: Eigenmittel | CW52: Projektpartner | CY52: ==IFERROR(ROUND(CX52/$CW$8,2),0) | CZ52: ==ROUND(IFERROR(CX52/CY52,0),6) | DC52: Eigenmittel | DD52: Projektpartner | DF52: ==IFERROR(ROUND(DE52/$DD$8,2),0) | DG52: ==ROUND(IFERROR(DE52/DF52,0),6) | DJ52: Eigenmittel | DK52: Projektpartner | DM52: ==IFERROR(ROUND(DL52/$DK$8,2),0) | DN52: ==ROUND(IFERROR(DL52/DM52,0),6) | DQ52: Eigenmittel | DR52: Projektpartner | DT52: ==IFERROR(ROUND(DS52/$DR$8,2),0) | DU52: ==ROUND(IFERROR(DS52/DT52,0),6)
B53: Drittmittel | D53: 125000 | E53: ==IFERROR(ROUND(D53/$C$8,2),0) | F53: ==ROUND(IFERROR(D53/E53,0),6) | I53: Drittmittel | K53: 100000 | L53: ==IFERROR(ROUND(K53/$J$8,2),0) | M53: ==ROUND(IFERROR(K53/L53,0),6) | P53: Drittmittel | S53: ==IFERROR(ROUND(R53/$Q$8,2),0) | T53: ==ROUND(IFERROR(R53/S53,0),6) | W53: Drittmittel | Z53: ==IFERROR(ROUND(Y53/$X$8,2),0) | AA53: ==ROUND(IFERROR(Y53/Z53,0),6) | AD53: Drittmittel | AG53: ==IFERROR(ROUND(AF53/$AE$8,2),0) | AH53: ==ROUND(IFERROR(AF53/AG53,0),6) | AK53: Drittmittel | AN53: ==IFERROR(ROUND(AM53/$AL$8,2),0) | AO53: ==ROUND(IFERROR(AM53/AN53,0),6) | AR53: Drittmittel | AU53: ==IFERROR(ROUND(AT53/$AS$8,2),0) | AV53: ==ROUND(IFERROR(AT53/AU53,0),6) | AY53: Drittmittel | BB53: ==IFERROR(ROUND(BA53/$AZ$8,2),0) | BC53: ==ROUND(IFERROR(BA53/BB53,0),6) | BF53: Drittmittel | BI53: ==IFERROR(ROUND(BH53/$BG$8,2),0) | BJ53: ==ROUND(IFERROR(BH53/BI53,0),6) | BM53: Drittmittel | BP53: ==IFERROR(ROUND(BO53/$BN$8,2),0) | BQ53: ==ROUND(IFERROR(BO53/BP53,0),6) | BT53: Drittmittel | BW53: ==IFERROR(ROUND(BV53/$BU$8,2),0) | BX53: ==ROUND(IFERROR(BV53/BW53,0),6) | CA53: Drittmittel | CD53: ==IFERROR(ROUND(CC53/$CB$8,2),0) | CE53: ==ROUND(IFERROR(CC53/CD53,0),6) | CH53: Drittmittel | CK53: ==IFERROR(ROUND(CJ53/$CI$8,2),0) | CL53: ==ROUND(IFERROR(CJ53/CK53,0),6) | CO53: Drittmittel | CR53: ==IFERROR(ROUND(CQ53/$CP$8,2),0) | CS53: ==ROUND(IFERROR(CQ53/CR53,0),6) | CV53: Drittmittel | CY53: ==IFERROR(ROUND(CX53/$CW$8,2),0) | CZ53: ==ROUND(IFERROR(CX53/CY53,0),6) | DC53: Drittmittel | DF53: ==IFERROR(ROUND(DE53/$DD$8,2),0) | DG53: ==ROUND(IFERROR(DE53/DF53,0),6) | DJ53: Drittmittel | DM53: ==IFERROR(ROUND(DL53/$DK$8,2),0) | DN53: ==ROUND(IFERROR(DL53/DM53,0),6) | DQ53: Drittmittel | DT53: ==IFERROR(ROUND(DS53/$DR$8,2),0) | DU53: ==ROUND(IFERROR(DS53/DT53,0),6)
B54: Zinsertraege | C54: Bank | E54: ==IFERROR(ROUND(D54/$C$8,2),0) | F54: ==ROUND(IFERROR(D54/E54,0),6) | I54: Zinsertraege | J54: Bank | L54: ==IFERROR(ROUND(K54/$J$8,2),0) | M54: ==ROUND(IFERROR(K54/L54,0),6) | P54: Zinsertraege | Q54: Bank | S54: ==IFERROR(ROUND(R54/$Q$8,2),0) | T54: ==ROUND(IFERROR(R54/S54,0),6) | W54: Zinsertraege | X54: Bank | Z54: ==IFERROR(ROUND(Y54/$X$8,2),0) | AA54: ==ROUND(IFERROR(Y54/Z54,0),6) | AD54: Zinsertraege | AE54: Bank | AG54: ==IFERROR(ROUND(AF54/$AE$8,2),0) | AH54: ==ROUND(IFERROR(AF54/AG54,0),6) | AK54: Zinsertraege | AL54: Bank | AN54: ==IFERROR(ROUND(AM54/$AL$8,2),0) | AO54: ==ROUND(IFERROR(AM54/AN54,0),6) | AR54: Zinsertraege | AS54: Bank | AU54: ==IFERROR(ROUND(AT54/$AS$8,2),0) | AV54: ==ROUND(IFERROR(AT54/AU54,0),6) | AY54: Zinsertraege | AZ54: Bank | BB54: ==IFERROR(ROUND(BA54/$AZ$8,2),0) | BC54: ==ROUND(IFERROR(BA54/BB54,0),6) | BF54: Zinsertraege | BG54: Bank | BI54: ==IFERROR(ROUND(BH54/$BG$8,2),0) | BJ54: ==ROUND(IFERROR(BH54/BI54,0),6) | BM54: Zinsertraege | BN54: Bank | BP54: ==IFERROR(ROUND(BO54/$BN$8,2),0) | BQ54: ==ROUND(IFERROR(BO54/BP54,0),6) | BT54: Zinsertraege | BU54: Bank | BW54: ==IFERROR(ROUND(BV54/$BU$8,2),0) | BX54: ==ROUND(IFERROR(BV54/BW54,0),6) | CA54: Zinsertraege | CB54: Bank | CD54: ==IFERROR(ROUND(CC54/$CB$8,2),0) | CE54: ==ROUND(IFERROR(CC54/CD54,0),6) | CH54: Zinsertraege | CI54: Bank | CK54: ==IFERROR(ROUND(CJ54/$CI$8,2),0) | CL54: ==ROUND(IFERROR(CJ54/CK54,0),6) | CO54: Zinsertraege | CP54: Bank | CR54: ==IFERROR(ROUND(CQ54/$CP$8,2),0) | CS54: ==ROUND(IFERROR(CQ54/CR54,0),6) | CV54: Zinsertraege | CW54: Bank | CY54: ==IFERROR(ROUND(CX54/$CW$8,2),0) | CZ54: ==ROUND(IFERROR(CX54/CY54,0),6) | DC54: Zinsertraege | DD54: Bank | DF54: ==IFERROR(ROUND(DE54/$DD$8,2),0) | DG54: ==ROUND(IFERROR(DE54/DF54,0),6) | DJ54: Zinsertraege | DK54: Bank | DM54: ==IFERROR(ROUND(DL54/$DK$8,2),0) | DN54: ==ROUND(IFERROR(DL54/DM54,0),6) | DQ54: Zinsertraege | DR54: Bank | DT54: ==IFERROR(ROUND(DS54/$DR$8,2),0) | DU54: ==ROUND(IFERROR(DS54/DT54,0),6)
E55: ==IFERROR(ROUND(D55/$C$8,2),0) | F55: ==ROUND(IFERROR(D55/E55,0),6) | L55: ==IFERROR(ROUND(K55/$J$8,2),0) | M55: ==ROUND(IFERROR(K55/L55,0),6) | S55: ==IFERROR(ROUND(R55/$Q$8,2),0) | T55: ==ROUND(IFERROR(R55/S55,0),6) | Z55: ==IFERROR(ROUND(Y55/$X$8,2),0) | AA55: ==ROUND(IFERROR(Y55/Z55,0),6) | AG55: ==IFERROR(ROUND(AF55/$AE$8,2),0) | AH55: ==ROUND(IFERROR(AF55/AG55,0),6) | AN55: ==IFERROR(ROUND(AM55/$AL$8,2),0) | AO55: ==ROUND(IFERROR(AM55/AN55,0),6) | AU55: ==IFERROR(ROUND(AT55/$AS$8,2),0) | AV55: ==ROUND(IFERROR(AT55/AU55,0),6) | BB55: ==IFERROR(ROUND(BA55/$AZ$8,2),0) | BC55: ==ROUND(IFERROR(BA55/BB55,0),6) | BI55: ==IFERROR(ROUND(BH55/$BG$8,2),0) | BJ55: ==ROUND(IFERROR(BH55/BI55,0),6) | BP55: ==IFERROR(ROUND(BO55/$BN$8,2),0) | BQ55: ==ROUND(IFERROR(BO55/BP55,0),6) | BW55: ==IFERROR(ROUND(BV55/$BU$8,2),0) | BX55: ==ROUND(IFERROR(BV55/BW55,0),6) | CD55: ==IFERROR(ROUND(CC55/$CB$8,2),0) | CE55: ==ROUND(IFERROR(CC55/CD55,0),6) | CK55: ==IFERROR(ROUND(CJ55/$CI$8,2),0) | CL55: ==ROUND(IFERROR(CJ55/CK55,0),6) | CR55: ==IFERROR(ROUND(CQ55/$CP$8,2),0) | CS55: ==ROUND(IFERROR(CQ55/CR55,0),6) | CY55: ==IFERROR(ROUND(CX55/$CW$8,2),0) | CZ55: ==ROUND(IFERROR(CX55/CY55,0),6) | DF55: ==IFERROR(ROUND(DE55/$DD$8,2),0) | DG55: ==ROUND(IFERROR(DE55/DF55,0),6) | DM55: ==IFERROR(ROUND(DL55/$DK$8,2),0) | DN55: ==ROUND(IFERROR(DL55/DM55,0),6) | DT55: ==IFERROR(ROUND(DS55/$DR$8,2),0) | DU55: ==ROUND(IFERROR(DS55/DT55,0),6)
E56: ==IFERROR(ROUND(D56/$C$8,2),0) | F56: ==ROUND(IFERROR(D56/E56,0),6) | L56: ==IFERROR(ROUND(K56/$J$8,2),0) | M56: ==ROUND(IFERROR(K56/L56,0),6) | S56: ==IFERROR(ROUND(R56/$Q$8,2),0) | T56: ==ROUND(IFERROR(R56/S56,0),6) | Z56: ==IFERROR(ROUND(Y56/$X$8,2),0) | AA56: ==ROUND(IFERROR(Y56/Z56,0),6) | AG56: ==IFERROR(ROUND(AF56/$AE$8,2),0) | AH56: ==ROUND(IFERROR(AF56/AG56,0),6) | AN56: ==IFERROR(ROUND(AM56/$AL$8,2),0) | AO56: ==ROUND(IFERROR(AM56/AN56,0),6) | AU56: ==IFERROR(ROUND(AT56/$AS$8,2),0) | AV56: ==ROUND(IFERROR(AT56/AU56,0),6) | BB56: ==IFERROR(ROUND(BA56/$AZ$8,2),0) | BC56: ==ROUND(IFERROR(BA56/BB56,0),6) | BI56: ==IFERROR(ROUND(BH56/$BG$8,2),0) | BJ56: ==ROUND(IFERROR(BH56/BI56,0),6) | BP56: ==IFERROR(ROUND(BO56/$BN$8,2),0) | BQ56: ==ROUND(IFERROR(BO56/BP56,0),6) | BW56: ==IFERROR(ROUND(BV56/$BU$8,2),0) | BX56: ==ROUND(IFERROR(BV56/BW56,0),6) | CD56: ==IFERROR(ROUND(CC56/$CB$8,2),0) | CE56: ==ROUND(IFERROR(CC56/CD56,0),6) | CK56: ==IFERROR(ROUND(CJ56/$CI$8,2),0) | CL56: ==ROUND(IFERROR(CJ56/CK56,0),6) | CR56: ==IFERROR(ROUND(CQ56/$CP$8,2),0) | CS56: ==ROUND(IFERROR(CQ56/CR56,0),6) | CY56: ==IFERROR(ROUND(CX56/$CW$8,2),0) | CZ56: ==ROUND(IFERROR(CX56/CY56,0),6) | DF56: ==IFERROR(ROUND(DE56/$DD$8,2),0) | DG56: ==ROUND(IFERROR(DE56/DF56,0),6) | DM56: ==IFERROR(ROUND(DL56/$DK$8,2),0) | DN56: ==ROUND(IFERROR(DL56/DM56,0),6) | DT56: ==IFERROR(ROUND(DS56/$DR$8,2),0) | DU56: ==ROUND(IFERROR(DS56/DT56,0),6)
E57: ==IFERROR(ROUND(D57/$C$8,2),0) | F57: ==ROUND(IFERROR(D57/E57,0),6) | L57: ==IFERROR(ROUND(K57/$J$8,2),0) | M57: ==ROUND(IFERROR(K57/L57,0),6) | S57: ==IFERROR(ROUND(R57/$Q$8,2),0) | T57: ==ROUND(IFERROR(R57/S57,0),6) | Z57: ==IFERROR(ROUND(Y57/$X$8,2),0) | AA57: ==ROUND(IFERROR(Y57/Z57,0),6) | AG57: ==IFERROR(ROUND(AF57/$AE$8,2),0) | AH57: ==ROUND(IFERROR(AF57/AG57,0),6) | AN57: ==IFERROR(ROUND(AM57/$AL$8,2),0) | AO57: ==ROUND(IFERROR(AM57/AN57,0),6) | AU57: ==IFERROR(ROUND(AT57/$AS$8,2),0) | AV57: ==ROUND(IFERROR(AT57/AU57,0),6) | BB57: ==IFERROR(ROUND(BA57/$AZ$8,2),0) | BC57: ==ROUND(IFERROR(BA57/BB57,0),6) | BI57: ==IFERROR(ROUND(BH57/$BG$8,2),0) | BJ57: ==ROUND(IFERROR(BH57/BI57,0),6) | BP57: ==IFERROR(ROUND(BO57/$BN$8,2),0) | BQ57: ==ROUND(IFERROR(BO57/BP57,0),6) | BW57: ==IFERROR(ROUND(BV57/$BU$8,2),0) | BX57: ==ROUND(IFERROR(BV57/BW57,0),6) | CD57: ==IFERROR(ROUND(CC57/$CB$8,2),0) | CE57: ==ROUND(IFERROR(CC57/CD57,0),6) | CK57: ==IFERROR(ROUND(CJ57/$CI$8,2),0) | CL57: ==ROUND(IFERROR(CJ57/CK57,0),6) | CR57: ==IFERROR(ROUND(CQ57/$CP$8,2),0) | CS57: ==ROUND(IFERROR(CQ57/CR57,0),6) | CY57: ==IFERROR(ROUND(CX57/$CW$8,2),0) | CZ57: ==ROUND(IFERROR(CX57/CY57,0),6) | DF57: ==IFERROR(ROUND(DE57/$DD$8,2),0) | DG57: ==ROUND(IFERROR(DE57/DF57,0),6) | DM57: ==IFERROR(ROUND(DL57/$DK$8,2),0) | DN57: ==ROUND(IFERROR(DL57/DM57,0),6) | DT57: ==IFERROR(ROUND(DS57/$DR$8,2),0) | DU57: ==ROUND(IFERROR(DS57/DT57,0),6)
B58: Gesamt (Durchschnittskurs) | C58: Durchschnittskurs: | D58: ==ROUND(SUBTOTAL(109,$D$52:$D$57),2) | E58: ==ROUND(SUBTOTAL(109,$E$52:$E$57),2) | F58: ==ROUND(IFERROR(D58/E58,0),6) | I58: Gesamt (Durchschnittskurs) | J58: Durchschnittskurs: | K58: ==ROUND(SUBTOTAL(109,$K$52:$K$57),2) | L58: ==ROUND(SUBTOTAL(109,$L$52:$L$57),2) | M58: ==ROUND(IFERROR(K58/L58,0),6) | P58: Gesamt (Durchschnittskurs) | Q58: Durchschnittskurs: | R58: ==ROUND(SUBTOTAL(109,$R$52:$R$57),2) | S58: ==ROUND(SUBTOTAL(109,$S$52:$S$57),2) | T58: ==ROUND(IFERROR(R58/S58,0),6) | W58: Gesamt (Durchschnittskurs) | X58: Durchschnittskurs: | Y58: ==ROUND(SUBTOTAL(109,$Y$52:$Y$57),2) | Z58: ==ROUND(SUBTOTAL(109,$Z$52:$Z$57),2) | AA58: ==ROUND(IFERROR(Y58/Z58,0),6) | AD58: Gesamt (Durchschnittskurs) | AE58: Durchschnittskurs: | AF58: ==ROUND(SUBTOTAL(109,$AF$52:$AF$57),2) | AG58: ==ROUND(SUBTOTAL(109,$AG$52:$AG$57),2) | AH58: ==ROUND(IFERROR(AF58/AG58,0),6) | AK58: Gesamt (Durchschnittskurs) | AL58: Durchschnittskurs: | AM58: ==ROUND(SUBTOTAL(109,$AM$52:$AM$57),2) | AN58: ==ROUND(SUBTOTAL(109,$AN$52:$AN$57),2) | AO58: ==ROUND(IFERROR(AM58/AN58,0),6) | AR58: Gesamt (Durchschnittskurs) | AS58: Durchschnittskurs: | AT58: ==ROUND(SUBTOTAL(109,$AT$52:$AT$57),2) | AU58: ==ROUND(SUBTOTAL(109,$AU$52:$AU$57),2) | AV58: ==ROUND(IFERROR(AT58/AU58,0),6) | AY58: Gesamt (Durchschnittskurs) | AZ58: Durchschnittskurs: | BA58: ==ROUND(SUBTOTAL(109,$BA$52:$BA$57),2) | BB58: ==ROUND(SUBTOTAL(109,$BB$52:$BB$57),2) | BC58: ==ROUND(IFERROR(BA58/BB58,0),6) | BF58: Gesamt (Durchschnittskurs) | BG58: Durchschnittskurs: | BH58: ==ROUND(SUBTOTAL(109,$BH$52:$BH$57),2) | BI58: ==ROUND(SUBTOTAL(109,$BI$52:$BI$57),2) | BJ58: ==ROUND(IFERROR(BH58/BI58,0),6) | BM58: Gesamt (Durchschnittskurs) | BN58: Durchschnittskurs: | BO58: ==ROUND(SUBTOTAL(109,$BO$52:$BO$57),2) | BP58: ==ROUND(SUBTOTAL(109,$BP$52:$BP$57),2) | BQ58: ==ROUND(IFERROR(BO58/BP58,0),6) | BT58: Gesamt (Durchschnittskurs) | BU58: Durchschnittskurs: | BV58: ==ROUND(SUBTOTAL(109,$BV$52:$BV$57),2) | BW58: ==ROUND(SUBTOTAL(109,$BW$52:$BW$57),2) | BX58: ==ROUND(IFERROR(BV58/BW58,0),6) | CA58: Gesamt (Durchschnittskurs) | CB58: Durchschnittskurs: | CC58: ==ROUND(SUBTOTAL(109,$CC$52:$CC$57),2) | CD58: ==ROUND(SUBTOTAL(109,$CD$52:$CD$57),2) | CE58: ==ROUND(IFERROR(CC58/CD58,0),6) | CH58: Gesamt (Durchschnittskurs) | CI58: Durchschnittskurs: | CJ58: ==ROUND(SUBTOTAL(109,$CJ$52:$CJ$57),2) | CK58: ==ROUND(SUBTOTAL(109,$CK$52:$CK$57),2) | CL58: ==ROUND(IFERROR(CJ58/CK58,0),6) | CO58: Gesamt (Durchschnittskurs) | CP58: Durchschnittskurs: | CQ58: ==ROUND(SUBTOTAL(109,$CQ$52:$CQ$57),2) | CR58: ==ROUND(SUBTOTAL(109,$CR$52:$CR$57),2) | CS58: ==ROUND(IFERROR(CQ58/CR58,0),6) | CV58: Gesamt (Durchschnittskurs) | CW58: Durchschnittskurs: | CX58: ==ROUND(SUBTOTAL(109,$CX$52:$CX$57),2) | CY58: ==ROUND(SUBTOTAL(109,$CY$52:$CY$57),2) | CZ58: ==ROUND(IFERROR(CX58/CY58,0),6) | DC58: Gesamt (Durchschnittskurs) | DD58: Durchschnittskurs: | DE58: ==ROUND(SUBTOTAL(109,$DE$52:$DE$57),2) | DF58: ==ROUND(SUBTOTAL(109,$DF$52:$DF$57),2) | DG58: ==ROUND(IFERROR(DE58/DF58,0),6) | DJ58: Gesamt (Durchschnittskurs) | DK58: Durchschnittskurs: | DL58: ==ROUND(SUBTOTAL(109,$DL$52:$DL$57),2) | DM58: ==ROUND(SUBTOTAL(109,$DM$52:$DM$57),2) | DN58: ==ROUND(IFERROR(DL58/DM58,0),6) | DQ58: Gesamt (Durchschnittskurs) | DR58: Durchschnittskurs: | DS58: ==ROUND(SUBTOTAL(109,$DS$52:$DS$57),2) | DT58: ==ROUND(SUBTOTAL(109,$DT$52:$DT$57),2) | DU58: ==ROUND(IFERROR(DS58/DT58,0),6)

Sheet IV. MA
E3: ➤ | I3: ➤ | M3: ➤ | Q3: ➤ | U3: ➤ | Y3: ➤ | AC3: ➤ | AG3: ➤ | AK3: ➤ | AO3: ➤ | AS3: ➤ | AW3: ➤ | BA3: ➤ | BE3: ➤ | BI3: ➤ | BM3: ➤ | BQ3: ➤
B4: Periode: | C4: Periode 1 | F4: Periode: | G4: Periode 2 | J4: Periode: | K4: Periode 3 | N4: Periode: | O4: Periode 4 | R4: Periode: | S4: Periode 5 | V4: Periode: | W4: Periode 6 | Z4: Periode: | AA4: Periode 7 | AD4: Periode: | AE4: Periode 8 | AH4: Periode: | AI4: Periode 9 | AL4: Periode: | AM4: Periode 10 | AP4: Periode: | AQ4: Periode 11 | AT4: Periode: | AU4: Periode 12 | AX4: Periode: | AY4: Periode 13 | BB4: Periode: | BC4: Periode 14 | BF4: Periode: | BG4: Periode 15 | BJ4: Periode: | BK4: Periode 16 | BN4: Periode: | BO4: Periode 17 | BR4: Periode: | BS4: Periode 18
B5: Von: | C5: 45658 | F5: Von: | G5: 45839 | J5: Von: | N5: Von: | R5: Von: | V5: Von: | Z5: Von: | AD5: Von: | AH5: Von: | AL5: Von: | AP5: Von: | AT5: Von: | AX5: Von: | BB5: Von: | BF5: Von: | BJ5: Von: | BN5: Von: | BR5: Von:
B6: Bis: | C6: 45838 | F6: Bis: | G6: 46022 | J6: Bis: | N6: Bis: | R6: Bis: | V6: Bis: | Z6: Bis: | AD6: Bis: | AH6: Bis: | AL6: Bis: | AP6: Bis: | AT6: Bis: | AX6: Bis: | BB6: Bis: | BF6: Bis: | BJ6: Bis: | BN6: Bis: | BR6: Bis:
B7: Zeitraum: | C7: ==IF(OR(C5="",C6=""),"",DATEDIF(C5,C6,"m")+1) | F7: Zeitraum: | G7: ==IF(OR(G5="",G6=""),"",DATEDIF(G5,G6,"m")+1) | J7: Zeitraum: | K7: ==IF(OR(K5="",K6=""),"",DATEDIF(K5,K6,"m")+1) | N7: Zeitraum: | O7: ==IF(OR(O5="",O6=""),"",DATEDIF(O5,O6,"m")+1) | R7: Zeitraum: | S7: ==IF(OR(S5="",S6=""),"",DATEDIF(S5,S6,"m")+1) | V7: Zeitraum: | W7: ==IF(OR(W5="",W6=""),"",DATEDIF(W5,W6,"m")+1) | Z7: Zeitraum: | AA7: ==IF(OR(AA5="",AA6=""),"",DATEDIF(AA5,AA6,"m")+1) | AD7: Zeitraum: | AE7: ==IF(OR(AE5="",AE6=""),"",DATEDIF(AE5,AE6,"m")+1) | AH7: Zeitraum: | AI7: ==IF(OR(AI5="",AI6=""),"",DATEDIF(AI5,AI6,"m")+1) | AL7: Zeitraum: | AM7: ==IF(OR(AM5="",AM6=""),"",DATEDIF(AM5,AM6,"m")+1) | AP7: Zeitraum: | AQ7: ==IF(OR(AQ5="",AQ6=""),"",DATEDIF(AQ5,AQ6,"m")+1) | AT7: Zeitraum: | AU7: ==IF(OR(AU5="",AU6=""),"",DATEDIF(AU5,AU6,"m")+1) | AX7: Zeitraum: | AY7: ==IF(OR(AY5="",AY6=""),"",DATEDIF(AY5,AY6,"m")+1) | BB7: Zeitraum: | BC7: ==IF(OR(BC5="",BC6=""),"",DATEDIF(BC5,BC6,"m")+1) | BF7: Zeitraum: | BG7: ==IF(OR(BG5="",BG6=""),"",DATEDIF(BG5,BG6,"m")+1) | BJ7: Zeitraum: | BK7: ==IF(OR(BK5="",BK6=""),"",DATEDIF(BK5,BK6,"m")+1) | BN7: Zeitraum: | BO7: ==IF(OR(BO5="",BO6=""),"",DATEDIF(BO5,BO6,"m")+1) | BR7: Zeitraum: | BS7: ==IF(OR(BS5="",BS6=""),"",DATEDIF(BS5,BS6,"m")+1)
B8: OANDA-Kurs: | C8: 125 | F8: OANDA-Kurs: | G8: 125 | J8: OANDA-Kurs: | N8: OANDA-Kurs: | R8: OANDA-Kurs: | V8: OANDA-Kurs: | Z8: OANDA-Kurs: | AD8: OANDA-Kurs: | AH8: OANDA-Kurs: | AL8: OANDA-Kurs: | AP8: OANDA-Kurs: | AT8: OANDA-Kurs: | AX8: OANDA-Kurs: | BB8: OANDA-Kurs: | BF8: OANDA-Kurs: | BJ8: OANDA-Kurs: | BN8: OANDA-Kurs: | BR8: OANDA-Kurs:
B9: Kostenkategorie | C9: Angefordert (LC) | D9: Angefordert (EUR) | F9: Kostenkategorie | G9: Angefordert (LC) | H9: Angefordert (EUR) | J9: Kostenkategorie | K9: Angefordert (LC) | L9: Angefordert (EUR) | N9: Kostenkategorie | O9: Angefordert (LC) | P9: Angefordert (EUR) | R9: Kostenkategorie | S9: Angefordert (LC) | T9: Angefordert (EUR) | V9: Kostenkategorie | W9: Angefordert (LC) | X9: Angefordert (EUR) | Z9: Kostenkategorie | AA9: Angefordert (LC) | AB9: Angefordert (EUR) | AD9: Kostenkategorie | AE9: Angefordert (LC) | AF9: Angefordert (EUR) | AH9: Kostenkategorie | AI9: Angefordert (LC) | AJ9: Angefordert (EUR) | AL9: Kostenkategorie | AM9: Angefordert (LC) | AN9: Angefordert (EUR) | AP9: Kostenkategorie | AQ9: Angefordert (LC) | AR9: Angefordert (EUR) | AT9: Kostenkategorie | AU9: Angefordert (LC) | AV9: Angefordert (EUR) | AX9: Kostenkategorie | AY9: Angefordert (LC) | AZ9: Angefordert (EUR) | BB9: Kostenkategorie | BC9: Angefordert (LC) | BD9: Angefordert (EUR) | BF9: Kostenkategorie | BG9: Angefordert (LC) | BH9: Angefordert (EUR) | BJ9: Kostenkategorie | BK9: Angefordert (LC) | BL9: Angefordert (EUR) | BN9: Kostenkategorie | BO9: Angefordert (LC) | BP9: Angefordert (EUR) | BR9: Kostenkategorie | BS9: Angefordert (LC) | BT9: Angefordert (EUR)
B10: Bauausgaben | C10: 700000 | D10: ==IFERROR(ROUND(C10/MA_Kurs_1,2),0) | F10: Bauausgaben | G10: 400000 | H10: ==IFERROR(ROUND(G10/MA_Kurs_2,2),0) | J10: Bauausgaben | L10: ==IFERROR(ROUND(K10/MA_Kurs_3,2),0) | N10: Bauausgaben | P10: ==IFERROR(ROUND(O10/MA_Kurs_4,2),0) | R10: Bauausgaben | T10: ==IFERROR(ROUND(S10/MA_Kurs_5,2),0) | V10: Bauausgaben | X10: ==IFERROR(ROUND(W10/MA_Kurs_6,2),0) | Z10: Bauausgaben | AB10: ==IFERROR(ROUND(AA10/MA_Kurs_7,2),0) | AD10: Bauausgaben | AF10: ==IFERROR(ROUND(AE10/MA_Kurs_8,2),0) | AH10: Bauausgaben | AJ10: ==IFERROR(ROUND(AI10/MA_Kurs_9,2),0) | AL10: Bauausgaben | AN10: ==IFERROR(ROUND(AM10/MA_Kurs_10,2),0) | AP10: Bauausgaben | AR10: ==IFERROR(ROUND(AQ10/MA_Kurs_11,2),0) | AT10: Bauausgaben | AV10: ==IFERROR(ROUND(AU10/MA_Kurs_12,2),0) | AX10: Bauausgaben | AZ10: ==IFERROR(ROUND(AY10/MA_Kurs_13,2),0) | BB10: Bauausgaben | BD10: ==IFERROR(ROUND(BC10/MA_Kurs_14,2),0) | BF10: Bauausgaben | BH10: ==IFERROR(ROUND(BG10/MA_Kurs_15,2),0) | BJ10: Bauausgaben | BL10: ==IFERROR(ROUND(BK10/MA_Kurs_16,2),0) | BN10: Bauausgaben | BP10: ==IFERROR(ROUND(BO10/MA_Kurs_17,2),0) | BR10: Bauausgaben | BT10: ==IFERROR(ROUND(BS10/MA_Kurs_18,2),0)
B11: Investitionen | C11: 300000 | D11: ==IFERROR(ROUND(C11/MA_Kurs_1,2),0) | F11: Investitionen | H11: ==IFERROR(ROUND(G11/MA_Kurs_2,2),0) | J11: Investitionen | L11: ==IFERROR(ROUND(K11/MA_Kurs_3,2),0) | N11: Investitionen | P11: ==IFERROR(ROUND(O11/MA_Kurs_4,2),0) | R11: Investitionen | T11: ==IFERROR(ROUND(S11/MA_Kurs_5,2),0) | V11: Investitionen | X11: ==IFERROR(ROUND(W11/MA_Kurs_6,2),0) | Z11: Investitionen | AB11: ==IFERROR(ROUND(AA11/MA_Kurs_7,2),0) | AD11: Investitionen | AF11: ==IFERROR(ROUND(AE11/MA_Kurs_8,2),0) | AH11: Investitionen | AJ11: ==IFERROR(ROUND(AI11/MA_Kurs_9,2),0) | AL11: Investitionen | AN11: ==IFERROR(ROUND(AM11/MA_Kurs_10,2),0) | AP11: Investitionen | AR11: ==IFERROR(ROUND(AQ11/MA_Kurs_11,2),0) | AT11: Investitionen | AV11: ==IFERROR(ROUND(AU11/MA_Kurs_12,2),0) | AX11: Investitionen | AZ11: ==IFERROR(ROUND(AY11/MA_Kurs_13,2),0) | BB11: Investitionen | BD11: ==IFERROR(ROUND(BC11/MA_Kurs_14,2),0) | BF11: Investitionen | BH11: ==IFERROR(ROUND(BG11/MA_Kurs_15,2),0) | BJ11: Investitionen | BL11: ==IFERROR(ROUND(BK11/MA_Kurs_16,2),0) | BN11: Investitionen | BP11: ==IFERROR(ROUND(BO11/MA_Kurs_17,2),0) | BR11: Investitionen | BT11: ==IFERROR(ROUND(BS11/MA_Kurs_18,2),0)
B12: Personalkosten | C12: 350000 | D12: ==IFERROR(ROUND(C12/MA_Kurs_1,2),0) | F12: Personalkosten | G12: 350000 | H12: ==IFERROR(ROUND(G12/MA_Kurs_2,2),0) | J12: Personalkosten | L12: ==IFERROR(ROUND(K12/MA_Kurs_3,2),0) | N12: Personalkosten | P12: ==IFERROR(ROUND(O12/MA_Kurs_4,2),0) | R12: Personalkosten | T12: ==IFERROR(ROUND(S12/MA_Kurs_5,2),0) | V12: Personalkosten | X12: ==IFERROR(ROUND(W12/MA_Kurs_6,2),0) | Z12: Personalkosten | AB12: ==IFERROR(ROUND(AA12/MA_Kurs_7,2),0) | AD12: Personalkosten | AF12: ==IFERROR(ROUND(AE12/MA_Kurs_8,2),0) | AH12: Personalkosten | AJ12: ==IFERROR(ROUND(AI12/MA_Kurs_9,2),0) | AL12: Personalkosten | AN12: ==IFERROR(ROUND(AM12/MA_Kurs_10,2),0) | AP12: Personalkosten | AR12: ==IFERROR(ROUND(AQ12/MA_Kurs_11,2),0) | AT12: Personalkosten | AV12: ==IFERROR(ROUND(AU12/MA_Kurs_12,2),0) | AX12: Personalkosten | AZ12: ==IFERROR(ROUND(AY12/MA_Kurs_13,2),0) | BB12: Personalkosten | BD12: ==IFERROR(ROUND(BC12/MA_Kurs_14,2),0) | BF12: Personalkosten | BH12: ==IFERROR(ROUND(BG12/MA_Kurs_15,2),0) | BJ12: Personalkosten | BL12: ==IFERROR(ROUND(BK12/MA_Kurs_16,2),0) | BN12: Personalkosten | BP12: ==IFERROR(ROUND(BO12/MA_Kurs_17,2),0) | BR12: Personalkosten | BT12: ==IFERROR(ROUND(BS12/MA_Kurs_18,2),0)
B13: Projektaktivitaeten | C13: 130000 | D13: ==IFERROR(ROUND(C13/MA_Kurs_1,2),0) | F13: Projektaktivitaeten | G13: 100000 | H13: ==IFERROR(ROUND(G13/MA_Kurs_2,2),0) | J13: Projektaktivitaeten | L13: ==IFERROR(ROUND(K13/MA_Kurs_3,2),0) | N13: Projektaktivitaeten | P13: ==IFERROR(ROUND(O13/MA_Kurs_4,2),0) | R13: Projektaktivitaeten | T13: ==IFERROR(ROUND(S13/MA_Kurs_5,2),0) | V13: Projektaktivitaeten | X13: ==IFERROR(ROUND(W13/MA_Kurs_6,2),0) | Z13: Projektaktivitaeten | AB13: ==IFERROR(ROUND(AA13/MA_Kurs_7,2),0) | AD13: Projektaktivitaeten | AF13: ==IFERROR(ROUND(AE13/MA_Kurs_8,2),0) | AH13: Projektaktivitaeten | AJ13: ==IFERROR(ROUND(AI13/MA_Kurs_9,2),0) | AL13: Projektaktivitaeten | AN13: ==IFERROR(ROUND(AM13/MA_Kurs_10,2),0) | AP13: Projektaktivitaeten | AR13: ==IFERROR(ROUND(AQ13/MA_Kurs_11,2),0) | AT13: Projektaktivitaeten | AV13: ==IFERROR(ROUND(AU13/MA_Kurs_12,2),0) | AX13: Projektaktivitaeten | AZ13: ==IFERROR(ROUND(AY13/MA_Kurs_13,2),0) | BB13: Projektaktivitaeten | BD13: ==IFERROR(ROUND(BC13/MA_Kurs_14,2),0) | BF13: Projektaktivitaeten | BH13: ==IFERROR(ROUND(BG13/MA_Kurs_15,2),0) | BJ13: Projektaktivitaeten | BL13: ==IFERROR(ROUND(BK13/MA_Kurs_16,2),0) | BN13: Projektaktivitaeten | BP13: ==IFERROR(ROUND(BO13/MA_Kurs_17,2),0) | BR13: Projektaktivitaeten | BT13: ==IFERROR(ROUND(BS13/MA_Kurs_18,2),0)
B14: Projektverwaltung | C14: 80000 | D14: ==IFERROR(ROUND(C14/MA_Kurs_1,2),0) | F14: Projektverwaltung | G14: 70000 | H14: ==IFERROR(ROUND(G14/MA_Kurs_2,2),0) | J14: Projektverwaltung | L14: ==IFERROR(ROUND(K14/MA_Kurs_3,2),0) | N14: Projektverwaltung | P14: ==IFERROR(ROUND(O14/MA_Kurs_4,2),0) | R14: Projektverwaltung | T14: ==IFERROR(ROUND(S14/MA_Kurs_5,2),0) | V14: Projektverwaltung | X14: ==IFERROR(ROUND(W14/MA_Kurs_6,2),0) | Z14: Projektverwaltung | AB14: ==IFERROR(ROUND(AA14/MA_Kurs_7,2),0) | AD14: Projektverwaltung | AF14: ==IFERROR(ROUND(AE14/MA_Kurs_8,2),0) | AH14: Projektverwaltung | AJ14: ==IFERROR(ROUND(AI14/MA_Kurs_9,2),0) | AL14: Projektverwaltung | AN14: ==IFERROR(ROUND(AM14/MA_Kurs_10,2),0) | AP14: Projektverwaltung | AR14: ==IFERROR(ROUND(AQ14/MA_Kurs_11,2),0) | AT14: Projektverwaltung | AV14: ==IFERROR(ROUND(AU14/MA_Kurs_12,2),0) | AX14: Projektverwaltung | AZ14: ==IFERROR(ROUND(AY14/MA_Kurs_13,2),0) | BB14: Projektverwaltung | BD14: ==IFERROR(ROUND(BC14/MA_Kurs_14,2),0) | BF14: Projektverwaltung | BH14: ==IFERROR(ROUND(BG14/MA_Kurs_15,2),0) | BJ14: Projektverwaltung | BL14: ==IFERROR(ROUND(BK14/MA_Kurs_16,2),0) | BN14: Projektverwaltung | BP14: ==IFERROR(ROUND(BO14/MA_Kurs_17,2),0) | BR14: Projektverwaltung | BT14: ==IFERROR(ROUND(BS14/MA_Kurs_18,2),0)
B15: Evaluierung | D15: ==IFERROR(ROUND(C15/MA_Kurs_1,2),0) | F15: Evaluierung | H15: ==IFERROR(ROUND(G15/MA_Kurs_2,2),0) | J15: Evaluierung | L15: ==IFERROR(ROUND(K15/MA_Kurs_3,2),0) | N15: Evaluierung | P15: ==IFERROR(ROUND(O15/MA_Kurs_4,2),0) | R15: Evaluierung | T15: ==IFERROR(ROUND(S15/MA_Kurs_5,2),0) | V15: Evaluierung | X15: ==IFERROR(ROUND(W15/MA_Kurs_6,2),0) | Z15: Evaluierung | AB15: ==IFERROR(ROUND(AA15/MA_Kurs_7,2),0) | AD15: Evaluierung | AF15: ==IFERROR(ROUND(AE15/MA_Kurs_8,2),0) | AH15: Evaluierung | AJ15: ==IFERROR(ROUND(AI15/MA_Kurs_9,2),0) | AL15: Evaluierung | AN15: ==IFERROR(ROUND(AM15/MA_Kurs_10,2),0) | AP15: Evaluierung | AR15: ==IFERROR(ROUND(AQ15/MA_Kurs_11,2),0) | AT15: Evaluierung | AV15: ==IFERROR(ROUND(AU15/MA_Kurs_12,2),0) | AX15: Evaluierung | AZ15: ==IFERROR(ROUND(AY15/MA_Kurs_13,2),0) | BB15: Evaluierung | BD15: ==IFERROR(ROUND(BC15/MA_Kurs_14,2),0) | BF15: Evaluierung | BH15: ==IFERROR(ROUND(BG15/MA_Kurs_15,2),0) | BJ15: Evaluierung | BL15: ==IFERROR(ROUND(BK15/MA_Kurs_16,2),0) | BN15: Evaluierung | BP15: ==IFERROR(ROUND(BO15/MA_Kurs_17,2),0) | BR15: Evaluierung | BT15: ==IFERROR(ROUND(BS15/MA_Kurs_18,2),0)
B16: Audit | C16: 50000 | D16: ==IFERROR(ROUND(C16/MA_Kurs_1,2),0) | F16: Audit | G16: 30000 | H16: ==IFERROR(ROUND(G16/MA_Kurs_2,2),0) | J16: Audit | L16: ==IFERROR(ROUND(K16/MA_Kurs_3,2),0) | N16: Audit | P16: ==IFERROR(ROUND(O16/MA_Kurs_4,2),0) | R16: Audit | T16: ==IFERROR(ROUND(S16/MA_Kurs_5,2),0) | V16: Audit | X16: ==IFERROR(ROUND(W16/MA_Kurs_6,2),0) | Z16: Audit | AB16: ==IFERROR(ROUND(AA16/MA_Kurs_7,2),0) | AD16: Audit | AF16: ==IFERROR(ROUND(AE16/MA_Kurs_8,2),0) | AH16: Audit | AJ16: ==IFERROR(ROUND(AI16/MA_Kurs_9,2),0) | AL16: Audit | AN16: ==IFERROR(ROUND(AM16/MA_Kurs_10,2),0) | AP16: Audit | AR16: ==IFERROR(ROUND(AQ16/MA_Kurs_11,2),0) | AT16: Audit | AV16: ==IFERROR(ROUND(AU16/MA_Kurs_12,2),0) | AX16: Audit | AZ16: ==IFERROR(ROUND(AY16/MA_Kurs_13,2),0) | BB16: Audit | BD16: ==IFERROR(ROUND(BC16/MA_Kurs_14,2),0) | BF16: Audit | BH16: ==IFERROR(ROUND(BG16/MA_Kurs_15,2),0) | BJ16: Audit | BL16: ==IFERROR(ROUND(BK16/MA_Kurs_16,2),0) | BN16: Audit | BP16: ==IFERROR(ROUND(BO16/MA_Kurs_17,2),0) | BR16: Audit | BT16: ==IFERROR(ROUND(BS16/MA_Kurs_18,2),0)
B17: Reserve | D17: ==IFERROR(ROUND(C17/MA_Kurs_1,2),0) | F17: Reserve | H17: ==IFERROR(ROUND(G17/MA_Kurs_2,2),0) | J17: Reserve | L17: ==IFERROR(ROUND(K17/MA_Kurs_3,2),0) | N17: Reserve | P17: ==IFERROR(ROUND(O17/MA_Kurs_4,2),0) | R17: Reserve | T17: ==IFERROR(ROUND(S17/MA_Kurs_5,2),0) | V17: Reserve | X17: ==IFERROR(ROUND(W17/MA_Kurs_6,2),0) | Z17: Reserve | AB17: ==IFERROR(ROUND(AA17/MA_Kurs_7,2),0) | AD17: Reserve | AF17: ==IFERROR(ROUND(AE17/MA_Kurs_8,2),0) | AH17: Reserve | AJ17: ==IFERROR(ROUND(AI17/MA_Kurs_9,2),0) | AL17: Reserve | AN17: ==IFERROR(ROUND(AM17/MA_Kurs_10,2),0) | AP17: Reserve | AR17: ==IFERROR(ROUND(AQ17/MA_Kurs_11,2),0) | AT17: Reserve | AV17: ==IFERROR(ROUND(AU17/MA_Kurs_12,2),0) | AX17: Reserve | AZ17: ==IFERROR(ROUND(AY17/MA_Kurs_13,2),0) | BB17: Reserve | BD17: ==IFERROR(ROUND(BC17/MA_Kurs_14,2),0) | BF17: Reserve | BH17: ==IFERROR(ROUND(BG17/MA_Kurs_15,2),0) | BJ17: Reserve | BL17: ==IFERROR(ROUND(BK17/MA_Kurs_16,2),0) | BN17: Reserve | BP17: ==IFERROR(ROUND(BO17/MA_Kurs_17,2),0) | BR17: Reserve | BT17: ==IFERROR(ROUND(BS17/MA_Kurs_18,2),0)
B18: SUMME | C18: ==ROUND(SUBTOTAL(109,MA_1[Angefordert (LC)]),2) | D18: ==ROUND(SUBTOTAL(109,MA_1[Angefordert (EUR)]),2) | F18: SUMME | G18: ==ROUND(SUBTOTAL(109,MA_2[Angefordert (LC)]),2) | H18: ==ROUND(SUBTOTAL(109,MA_2[Angefordert (EUR)]),2) | J18: SUMME | K18: ==ROUND(SUBTOTAL(109,MA_3[Angefordert (LC)]),2) | L18: ==ROUND(SUBTOTAL(109,MA_3[Angefordert (EUR)]),2) | N18: SUMME | O18: ==ROUND(SUBTOTAL(109,MA_4[Angefordert (LC)]),2) | P18: ==ROUND(SUBTOTAL(109,MA_4[Angefordert (EUR)]),2) | R18: SUMME | S18: ==ROUND(SUBTOTAL(109,MA_5[Angefordert (LC)]),2) | T18: ==ROUND(SUBTOTAL(109,MA_5[Angefordert (EUR)]),2) | V18: SUMME | W18: ==ROUND(SUBTOTAL(109,MA_6[Angefordert (LC)]),2) | X18: ==ROUND(SUBTOTAL(109,MA_6[Angefordert (EUR)]),2) | Z18: SUMME | AA18: ==ROUND(SUBTOTAL(109,MA_7[Angefordert (LC)]),2) | AB18: ==ROUND(SUBTOTAL(109,MA_7[Angefordert (EUR)]),2) | AD18: SUMME | AE18: ==ROUND(SUBTOTAL(109,MA_8[Angefordert (LC)]),2) | AF18: ==ROUND(SUBTOTAL(109,MA_8[Angefordert (EUR)]),2) | AH18: SUMME | AI18: ==ROUND(SUBTOTAL(109,MA_9[Angefordert (LC)]),2) | AJ18: ==ROUND(SUBTOTAL(109,MA_9[Angefordert (EUR)]),2) | AL18: SUMME | AM18: ==ROUND(SUBTOTAL(109,MA_10[Angefordert (LC)]),2) | AN18: ==ROUND(SUBTOTAL(109,MA_10[Angefordert (EUR)]),2) | AP18: SUMME | AQ18: ==ROUND(SUBTOTAL(109,MA_11[Angefordert (LC)]),2) | AR18: ==ROUND(SUBTOTAL(109,MA_11[Angefordert (EUR)]),2) | AT18: SUMME | AU18: ==ROUND(SUBTOTAL(109,MA_12[Angefordert (LC)]),2) | AV18: ==ROUND(SUBTOTAL(109,MA_12[Angefordert (EUR)]),2) | AX18: SUMME | AY18: ==ROUND(SUBTOTAL(109,MA_13[Angefordert (LC)]),2) | AZ18: ==ROUND(SUBTOTAL(109,MA_13[Angefordert (EUR)]),2) | BB18: SUMME | BC18: ==ROUND(SUBTOTAL(109,MA_14[Angefordert (LC)]),2) | BD18: ==ROUND(SUBTOTAL(109,MA_14[Angefordert (EUR)]),2) | BF18: SUMME | BG18: ==ROUND(SUBTOTAL(109,MA_15[Angefordert (LC)]),2) | BH18: ==ROUND(SUBTOTAL(109,MA_15[Angefordert (EUR)]),2) | BJ18: SUMME | BK18: ==ROUND(SUBTOTAL(109,MA_16[Angefordert (LC)]),2) | BL18: ==ROUND(SUBTOTAL(109,MA_16[Angefordert (EUR)]),2) | BN18: SUMME | BO18: ==ROUND(SUBTOTAL(109,MA_17[Angefordert (LC)]),2) | BP18: ==ROUND(SUBTOTAL(109,MA_17[Angefordert (EUR)]),2) | BR18: SUMME | BS18: ==ROUND(SUBTOTAL(109,MA_18[Angefordert (LC)]),2) | BT18: ==ROUND(SUBTOTAL(109,MA_18[Angefordert (EUR)]),2)
B20: Gesamtbedarf an Mitteln: | C20: ==ROUND($C$18,2) | D20: ==ROUND($D$18,2) | F20: Gesamtbedarf an Mitteln: | G20: ==ROUND($G$18,2) | H20: ==ROUND($H$18,2) | J20: Gesamtbedarf an Mitteln: | K20: ==ROUND($K$18,2) | L20: ==ROUND($L$18,2) | N20: Gesamtbedarf an Mitteln: | O20: ==ROUND($O$18,2) | P20: ==ROUND($P$18,2) | R20: Gesamtbedarf an Mitteln: | S20: ==ROUND($S$18,2) | T20: ==ROUND($T$18,2) | V20: Gesamtbedarf an Mitteln: | W20: ==ROUND($W$18,2) | X20: ==ROUND($X$18,2) | Z20: Gesamtbedarf an Mitteln: | AA20: ==ROUND($AA$18,2) | AB20: ==ROUND($AB$18,2) | AD20: Gesamtbedarf an Mitteln: | AE20: ==ROUND($AE$18,2) | AF20: ==ROUND($AF$18,2) | AH20: Gesamtbedarf an Mitteln: | AI20: ==ROUND($AI$18,2) | AJ20: ==ROUND($AJ$18,2) | AL20: Gesamtbedarf an Mitteln: | AM20: ==ROUND($AM$18,2) | AN20: ==ROUND($AN$18,2) | AP20: Gesamtbedarf an Mitteln: | AQ20: ==ROUND($AQ$18,2) | AR20: ==ROUND($AR$18,2) | AT20: Gesamtbedarf an Mitteln: | AU20: ==ROUND($AU$18,2) | AV20: ==ROUND($AV$18,2) | AX20: Gesamtbedarf an Mitteln: | AY20: ==ROUND($AY$18,2) | AZ20: ==ROUND($AZ$18,2) | BB20: Gesamtbedarf an Mitteln: | BC20: ==ROUND($BC$18,2) | BD20: ==ROUND($BD$18,2) | BF20: Gesamtbedarf an Mitteln: | BG20: ==ROUND($BG$18,2) | BH20: ==ROUND($BH$18,2) | BJ20: Gesamtbedarf an Mitteln: | BK20: ==ROUND($BK$18,2) | BL20: ==ROUND($BL$18,2) | BN20: Gesamtbedarf an Mitteln: | BO20: ==ROUND($BO$18,2) | BP20: ==ROUND($BP$18,2) | BR20: Gesamtbedarf an Mitteln: | BS20: ==ROUND($BS$18,2) | BT20: ==ROUND($BT$18,2)
B21: abzueglich Eigenmittel: | C21: 250000 | D21: ==IFERROR(ROUND($C$21/$C$8,2),0) | F21: abzueglich Eigenmittel: | G21: 200000 | H21: ==IFERROR(ROUND($G$21/$G$8,2),0) | J21: abzueglich Eigenmittel: | L21: ==IFERROR(ROUND($K$21/$K$8,2),0) | N21: abzueglich Eigenmittel: | P21: ==IFERROR(ROUND($O$21/$O$8,2),0) | R21: abzueglich Eigenmittel: | T21: ==IFERROR(ROUND($S$21/$S$8,2),0) | V21: abzueglich Eigenmittel: | X21: ==IFERROR(ROUND($W$21/$W$8,2),0) | Z21: abzueglich Eigenmittel: | AB21: ==IFERROR(ROUND($AA$21/$AA$8,2),0) | AD21: abzueglich Eigenmittel: | AF21: ==IFERROR(ROUND($AE$21/$AE$8,2),0) | AH21: abzueglich Eigenmittel: | AJ21: ==IFERROR(ROUND($AI$21/$AI$8,2),0) | AL21: abzueglich Eigenmittel: | AN21: ==IFERROR(ROUND($AM$21/$AM$8,2),0) | AP21: abzueglich Eigenmittel: | AR21: ==IFERROR(ROUND($AQ$21/$AQ$8,2),0) | AT21: abzueglich Eigenmittel: | AV21: ==IFERROR(ROUND($AU$21/$AU$8,2),0) | AX21: abzueglich Eigenmittel: | AZ21: ==IFERROR(ROUND($AY$21/$AY$8,2),0) | BB21: abzueglich Eigenmittel: | BD21: ==IFERROR(ROUND($BC$21/$BC$8,2),0) | BF21: abzueglich Eigenmittel: | BH21: ==IFERROR(ROUND($BG$21/$BG$8,2),0) | BJ21: abzueglich Eigenmittel: | BL21: ==IFERROR(ROUND($BK$21/$BK$8,2),0) | BN21: abzueglich Eigenmittel: | BP21: ==IFERROR(ROUND($BO$21/$BO$8,2),0) | BR21: abzueglich Eigenmittel: | BT21: ==IFERROR(ROUND($BS$21/$BS$8,2),0)
B22: abzueglich Drittmittel: | C22: 125000 | D22: ==IFERROR(ROUND($C$22/$C$8,2),0) | F22: abzueglich Drittmittel: | G22: 100000 | H22: ==IFERROR(ROUND($G$22/$G$8,2),0) | J22: abzueglich Drittmittel: | L22: ==IFERROR(ROUND($K$22/$K$8,2),0) | N22: abzueglich Drittmittel: | P22: ==IFERROR(ROUND($O$22/$O$8,2),0) | R22: abzueglich Drittmittel: | T22: ==IFERROR(ROUND($S$22/$S$8,2),0) | V22: abzueglich Drittmittel: | X22: ==IFERROR(ROUND($W$22/$W$8,2),0) | Z22: abzueglich Drittmittel: | AB22: ==IFERROR(ROUND($AA$22/$AA$8,2),0) | AD22: abzueglich Drittmittel: | AF22: ==IFERROR(ROUND($AE$22/$AE$8,2),0) | AH22: abzueglich Drittmittel: | AJ22: ==IFERROR(ROUND($AI$22/$AI$8,2),0) | AL22: abzueglich Drittmittel: | AN22: ==IFERROR(ROUND($AM$22/$AM$8,2),0) | AP22: abzueglich Drittmittel: | AR22: ==IFERROR(ROUND($AQ$22/$AQ$8,2),0) | AT22: abzueglich Drittmittel: | AV22: ==IFERROR(ROUND($AU$22/$AU$8,2),0) | AX22: abzueglich Drittmittel: | AZ22: ==IFERROR(ROUND($AY$22/$AY$8,2),0) | BB22: abzueglich Drittmittel: | BD22: ==IFERROR(ROUND($BC$22/$BC$8,2),0) | BF22: abzueglich Drittmittel: | BH22: ==IFERROR(ROUND($BG$22/$BG$8,2),0) | BJ22: abzueglich Drittmittel: | BL22: ==IFERROR(ROUND($BK$22/$BK$8,2),0) | BN22: abzueglich Drittmittel: | BP22: ==IFERROR(ROUND($BO$22/$BO$8,2),0) | BR22: abzueglich Drittmittel: | BT22: ==IFERROR(ROUND($BS$22/$BS$8,2),0)
B23: abzueglich Saldo Vorprojekt: | C23: ==ROUND(IF(Saldovortrag_LW="",0,Saldovortrag_LW),2) | D23: ==IFERROR(ROUND($C$23/$C$8,2),0) | F23: abzueglich Saldo Vorperiode (FB): | G23: ==ROUND(IFERROR(FB_SaldoLC_1,0),2) | H23: ==IFERROR(ROUND($G$23/$G$8,2),0) | J23: abzueglich Saldo Vorperiode (FB): | K23: ==ROUND(IFERROR(FB_SaldoLC_2,0),2) | L23: ==IFERROR(ROUND($K$23/$K$8,2),0) | N23: abzueglich Saldo Vorperiode (FB): | O23: ==ROUND(IFERROR(FB_SaldoLC_3,0),2) | P23: ==IFERROR(ROUND($O$23/$O$8,2),0) | R23: abzueglich Saldo Vorperiode (FB): | S23: ==ROUND(IFERROR(FB_SaldoLC_4,0),2) | T23: ==IFERROR(ROUND($S$23/$S$8,2),0) | V23: abzueglich Saldo Vorperiode (FB): | W23: ==ROUND(IFERROR(FB_SaldoLC_5,0),2) | X23: ==IFERROR(ROUND($W$23/$W$8,2),0) | Z23: abzueglich Saldo Vorperiode (FB): | AA23: ==ROUND(IFERROR(FB_SaldoLC_6,0),2) | AB23: ==IFERROR(ROUND($AA$23/$AA$8,2),0) | AD23: abzueglich Saldo Vorperiode (FB): | AE23: ==ROUND(IFERROR(FB_SaldoLC_7,0),2) | AF23: ==IFERROR(ROUND($AE$23/$AE$8,2),0) | AH23: abzueglich Saldo Vorperiode (FB): | AI23: ==ROUND(IFERROR(FB_SaldoLC_8,0),2) | AJ23: ==IFERROR(ROUND($AI$23/$AI$8,2),0) | AL23: abzueglich Saldo Vorperiode (FB): | AM23: ==ROUND(IFERROR(FB_SaldoLC_9,0),2) | AN23: ==IFERROR(ROUND($AM$23/$AM$8,2),0) | AP23: abzueglich Saldo Vorperiode (FB): | AQ23: ==ROUND(IFERROR(FB_SaldoLC_10,0),2) | AR23: ==IFERROR(ROUND($AQ$23/$AQ$8,2),0) | AT23: abzueglich Saldo Vorperiode (FB): | AU23: ==ROUND(IFERROR(FB_SaldoLC_11,0),2) | AV23: ==IFERROR(ROUND($AU$23/$AU$8,2),0) | AX23: abzueglich Saldo Vorperiode (FB): | AY23: ==ROUND(IFERROR(FB_SaldoLC_12,0),2) | AZ23: ==IFERROR(ROUND($AY$23/$AY$8,2),0) | BB23: abzueglich Saldo Vorperiode (FB): | BC23: ==ROUND(IFERROR(FB_SaldoLC_13,0),2) | BD23: ==IFERROR(ROUND($BC$23/$BC$8,2),0) | BF23: abzueglich Saldo Vorperiode (FB): | BG23: ==ROUND(IFERROR(FB_SaldoLC_14,0),2) | BH23: ==IFERROR(ROUND($BG$23/$BG$8,2),0) | BJ23: abzueglich Saldo Vorperiode (FB): | BK23: ==ROUND(IFERROR(FB_SaldoLC_15,0),2) | BL23: ==IFERROR(ROUND($BK$23/$BK$8,2),0) | BN23: abzueglich Saldo Vorperiode (FB): | BO23: ==ROUND(IFERROR(FB_SaldoLC_16,0),2) | BP23: ==IFERROR(ROUND($BO$23/$BO$8,2),0) | BR23: abzueglich Saldo Vorperiode (FB): | BS23: ==ROUND(IFERROR(FB_SaldoLC_17,0),2) | BT23: ==IFERROR(ROUND($BS$23/$BS$8,2),0)
B25: KMW-Mittel Anforderung: | C25: ==IFERROR(ROUND($C$18-$C$21-$C$22-$C$23,2),0) | D25: ==IFERROR(ROUND($D$18-$D$21-$D$22-$D$23,2),0) | F25: KMW-Mittel Anforderung: | G25: ==IFERROR(ROUND($G$18-$G$21-$G$22-$G$23,2),0) | H25: ==IFERROR(ROUND($H$18-$H$21-$H$22-$H$23,2),0) | J25: KMW-Mittel Anforderung: | K25: ==IFERROR(ROUND($K$18-$K$21-$K$22-$K$23,2),0) | L25: ==IFERROR(ROUND($L$18-$L$21-$L$22-$L$23,2),0) | N25: KMW-Mittel Anforderung: | O25: ==IFERROR(ROUND($O$18-$O$21-$O$22-$O$23,2),0) | P25: ==IFERROR(ROUND($P$18-$P$21-$P$22-$P$23,2),0) | R25: KMW-Mittel Anforderung: | S25: ==IFERROR(ROUND($S$18-$S$21-$S$22-$S$23,2),0) | T25: ==IFERROR(ROUND($T$18-$T$21-$T$22-$T$23,2),0) | V25: KMW-Mittel Anforderung: | W25: ==IFERROR(ROUND($W$18-$W$21-$W$22-$W$23,2),0) | X25: ==IFERROR(ROUND($X$18-$X$21-$X$22-$X$23,2),0) | Z25: KMW-Mittel Anforderung: | AA25: ==IFERROR(ROUND($AA$18-$AA$21-$AA$22-$AA$23,2),0) | AB25: ==IFERROR(ROUND($AB$18-$AB$21-$AB$22-$AB$23,2),0) | AD25: KMW-Mittel Anforderung: | AE25: ==IFERROR(ROUND($AE$18-$AE$21-$AE$22-$AE$23,2),0) | AF25: ==IFERROR(ROUND($AF$18-$AF$21-$AF$22-$AF$23,2),0) | AH25: KMW-Mittel Anforderung: | AI25: ==IFERROR(ROUND($AI$18-$AI$21-$AI$22-$AI$23,2),0) | AJ25: ==IFERROR(ROUND($AJ$18-$AJ$21-$AJ$22-$AJ$23,2),0) | AL25: KMW-Mittel Anforderung: | AM25: ==IFERROR(ROUND($AM$18-$AM$21-$AM$22-$AM$23,2),0) | AN25: ==IFERROR(ROUND($AN$18-$AN$21-$AN$22-$AN$23,2),0) | AP25: KMW-Mittel Anforderung: | AQ25: ==IFERROR(ROUND($AQ$18-$AQ$21-$AQ$22-$AQ$23,2),0) | AR25: ==IFERROR(ROUND($AR$18-$AR$21-$AR$22-$AR$23,2),0) | AT25: KMW-Mittel Anforderung: | AU25: ==IFERROR(ROUND($AU$18-$AU$21-$AU$22-$AU$23,2),0) | AV25: ==IFERROR(ROUND($AV$18-$AV$21-$AV$22-$AV$23,2),0) | AX25: KMW-Mittel Anforderung: | AY25: ==IFERROR(ROUND($AY$18-$AY$21-$AY$22-$AY$23,2),0) | AZ25: ==IFERROR(ROUND($AZ$18-$AZ$21-$AZ$22-$AZ$23,2),0) | BB25: KMW-Mittel Anforderung: | BC25: ==IFERROR(ROUND($BC$18-$BC$21-$BC$22-$BC$23,2),0) | BD25: ==IFERROR(ROUND($BD$18-$BD$21-$BD$22-$BD$23,2),0) | BF25: KMW-Mittel Anforderung: | BG25: ==IFERROR(ROUND($BG$18-$BG$21-$BG$22-$BG$23,2),0) | BH25: ==IFERROR(ROUND($BH$18-$BH$21-$BH$22-$BH$23,2),0) | BJ25: KMW-Mittel Anforderung: | BK25: ==IFERROR(ROUND($BK$18-$BK$21-$BK$22-$BK$23,2),0) | BL25: ==IFERROR(ROUND($BL$18-$BL$21-$BL$22-$BL$23,2),0) | BN25: KMW-Mittel Anforderung: | BO25: ==IFERROR(ROUND($BO$18-$BO$21-$BO$22-$BO$23,2),0) | BP25: ==IFERROR(ROUND($BP$18-$BP$21-$BP$22-$BP$23,2),0) | BR25: KMW-Mittel Anforderung: | BS25: ==IFERROR(ROUND($BS$18-$BS$21-$BS$22-$BS$23,2),0) | BT25: ==IFERROR(ROUND($BT$18-$BT$21-$BT$22-$BT$23,2),0)

Sheet V. AUSWERTUNG
B2: V. AUSWERTUNG
B3: Automatische Prüfung von Mittelanforderung und Finanzberichten
B5: MITTELANFORDERUNGSPRÜFUNG | L5: ==IF(E11=0,"Aktuelle Mittelanforderung (keine gewählt)","Aktuelle Mittelanforderung – Periode "&E10&" (#"&E11&")") | AD5: ==IFERROR(SUMPRODUCT('Daten'!$BA$1:$BA$18,('Daten'!$BB$1:$BB$18=E10)*('Daten'!$BD$1:$BD$18=E11)),0)
B6: Basis: ausgewählte Mittelanforderung (Folgeperiode des Finanzberichts) | L6: Periode: | M6: ==IFERROR(CHOOSE($AD$5,'IV. MA'!$C$4,'IV. MA'!$G$4,'IV. MA'!$K$4,'IV. MA'!$O$4,'IV. MA'!$S$4,'IV. MA'!$W$4,'IV. MA'!$AA$4,'IV. MA'!$AE$4,'IV. MA'!$AI$4,'IV. MA'!$AM$4,'IV. MA'!$AQ$4,'IV. MA'!$AU$4,'IV. MA'!$AY$4,'IV. MA'!$BC$4,'IV. MA'!$BG$4,'IV. MA'!$BK$4,'IV. MA'!$BO$4,'IV. MA'!$BS$4),"")
L7: Von: | M7: ==IFERROR(CHOOSE($AD$5,'IV. MA'!$C$5,'IV. MA'!$G$5,'IV. MA'!$K$5,'IV. MA'!$O$5,'IV. MA'!$S$5,'IV. MA'!$W$5,'IV. MA'!$AA$5,'IV. MA'!$AE$5,'IV. MA'!$AI$5,'IV. MA'!$AM$5,'IV. MA'!$AQ$5,'IV. MA'!$AU$5,'IV. MA'!$AY$5,'IV. MA'!$BC$5,'IV. MA'!$BG$5,'IV. MA'!$BK$5,'IV. MA'!$BO$5,'IV. MA'!$BS$5),"")
C8: Mittelanforderung auswählen | L8: Bis: | M8: ==IFERROR(CHOOSE($AD$5,'IV. MA'!$C$6,'IV. MA'!$G$6,'IV. MA'!$K$6,'IV. MA'!$O$6,'IV. MA'!$S$6,'IV. MA'!$W$6,'IV. MA'!$AA$6,'IV. MA'!$AE$6,'IV. MA'!$AI$6,'IV. MA'!$AM$6,'IV. MA'!$AQ$6,'IV. MA'!$AU$6,'IV. MA'!$AY$6,'IV. MA'!$BC$6,'IV. MA'!$BG$6,'IV. MA'!$BK$6,'IV. MA'!$BO$6,'IV. MA'!$BS$6),"")
C9: Auswahl: | E9: Neuste MA | L9: Zeitraum: | M9: ==IFERROR(CHOOSE($AD$5,'IV. MA'!$C$7,'IV. MA'!$G$7,'IV. MA'!$K$7,'IV. MA'!$O$7,'IV. MA'!$S$7,'IV. MA'!$W$7,'IV. MA'!$AA$7,'IV. MA'!$AE$7,'IV. MA'!$AI$7,'IV. MA'!$AM$7,'IV. MA'!$AQ$7,'IV. MA'!$AU$7,'IV. MA'!$AY$7,'IV. MA'!$BC$7,'IV. MA'!$BG$7,'IV. MA'!$BK$7,'IV. MA'!$BO$7,'IV. MA'!$BS$7),"")
C10: Geprüfte Periode | E10: ==E82+1 -> 0 | L10: OANDA-Kurs: | M10: ==IFERROR(CHOOSE($AD$5,'IV. MA'!$C$8,'IV. MA'!$G$8,'IV. MA'!$K$8,'IV. MA'!$O$8,'IV. MA'!$S$8,'IV. MA'!$W$8,'IV. MA'!$AA$8,'IV. MA'!$AE$8,'IV. MA'!$AI$8,'IV. MA'!$AM$8,'IV. MA'!$AQ$8,'IV. MA'!$AU$8,'IV. MA'!$AY$8,'IV. MA'!$BC$8,'IV. MA'!$BG$8,'IV. MA'!$BK$8,'IV. MA'!$BO$8,'IV. MA'!$BS$8),"")
C11: Ausgewählte Anforderung (#) | E11: ==IF(E9="Neuste MA",IFERROR(SUMPRODUCT(MAX(('Daten'!$BB$1:$BB$18=E10)*('Daten'!$BC$1:$BC$18=1)*'Daten'!$BD$1:$BD$18)),0),IFERROR(VALUE(MID(E9,FIND("(#",E9)+2,FIND(")",E9)-FIND("(#",E9)-2)),0))
C12: Einbezogene Anforderungen | L12: Kostenkategorie | M12: Angefordert (LC) | N12: Angefordert (EUR)
C13: ==IF(1<=E11,"Periode "&E10&" (#1)","") | E13: ==IF(1<=E11,IFERROR(SUMIFS('Daten'!$BF$1:$BF$18,'Daten'!$BB$1:$BB$18,E10,'Daten'!$BD$1:$BD$18,1),0),"") | G13: ==IF(1<=E11,IFERROR(SUMIFS('Daten'!$BG$1:$BG$18,'Daten'!$BB$1:$BB$18,E10,'Daten'!$BD$1:$BD$18,1),0),"") | L13: Bauausgaben | M13: ==IFERROR(CHOOSE($AD$5,'IV. MA'!$C$10,'IV. MA'!$G$10,'IV. MA'!$K$10,'IV. MA'!$O$10,'IV. MA'!$S$10,'IV. MA'!$W$10,'IV. MA'!$AA$10,'IV. MA'!$AE$10,'IV. MA'!$AI$10,'IV. MA'!$AM$10,'IV. MA'!$AQ$10,'IV. MA'!$AU$10,'IV. MA'!$AY$10,'IV. MA'!$BC$10,'IV. MA'!$BG$10,'IV. MA'!$BK$10,'IV. MA'!$BO$10,'IV. MA'!$BS$10),"") | N13: ==IFERROR(CHOOSE($AD$5,'IV. MA'!$D$10,'IV. MA'!$H$10,'IV. MA'!$L$10,'IV. MA'!$P$10,'IV. MA'!$T$10,'IV. MA'!$X$10,'IV. MA'!$AB$10,'IV. MA'!$AF$10,'IV. MA'!$AJ$10,'IV. MA'!$AN$10,'IV. MA'!$AR$10,'IV. MA'!$AV$10,'IV. MA'!$AZ$10,'IV. MA'!$BD$10,'IV. MA'!$BH$10,'IV. MA'!$BL$10,'IV. MA'!$BP$10,'IV. MA'!$BT$10),"")
C14: ==IF(2<=E11,"Periode "&E10&" (#2)","") | E14: ==IF(2<=E11,IFERROR(SUMIFS('Daten'!$BF$1:$BF$18,'Daten'!$BB$1:$BB$18,E10,'Daten'!$BD$1:$BD$18,2),0),"") | G14: ==IF(2<=E11,IFERROR(SUMIFS('Daten'!$BG$1:$BG$18,'Daten'!$BB$1:$BB$18,E10,'Daten'!$BD$1:$BD$18,2),0),"") | L14: Investitionen | M14: ==IFERROR(CHOOSE($AD$5,'IV. MA'!$C$11,'IV. MA'!$G$11,'IV. MA'!$K$11,'IV. MA'!$O$11,'IV. MA'!$S$11,'IV. MA'!$W$11,'IV. MA'!$AA$11,'IV. MA'!$AE$11,'IV. MA'!$AI$11,'IV. MA'!$AM$11,'IV. MA'!$AQ$11,'IV. MA'!$AU$11,'IV. MA'!$AY$11,'IV. MA'!$BC$11,'IV. MA'!$BG$11,'IV. MA'!$BK$11,'IV. MA'!$BO$11,'IV. MA'!$BS$11),"") | N14: ==IFERROR(CHOOSE($AD$5,'IV. MA'!$D$11,'IV. MA'!$H$11,'IV. MA'!$L$11,'IV. MA'!$P$11,'IV. MA'!$T$11,'IV. MA'!$X$11,'IV. MA'!$AB$11,'IV. MA'!$AF$11,'IV. MA'!$AJ$11,'IV. MA'!$AN$11,'IV. MA'!$AR$11,'IV. MA'!$AV$11,'IV. MA'!$AZ$11,'IV. MA'!$BD$11,'IV. MA'!$BH$11,'IV. MA'!$BL$11,'IV. MA'!$BP$11,'IV. MA'!$BT$11),"")
C15: ==IF(3<=E11,"Periode "&E10&" (#3)","") | E15: ==IF(3<=E11,IFERROR(SUMIFS('Daten'!$BF$1:$BF$18,'Daten'!$BB$1:$BB$18,E10,'Daten'!$BD$1:$BD$18,3),0),"") | G15: ==IF(3<=E11,IFERROR(SUMIFS('Daten'!$BG$1:$BG$18,'Daten'!$BB$1:$BB$18,E10,'Daten'!$BD$1:$BD$18,3),0),"") | L15: Personalkosten | M15: ==IFERROR(CHOOSE($AD$5,'IV. MA'!$C$12,'IV. MA'!$G$12,'IV. MA'!$K$12,'IV. MA'!$O$12,'IV. MA'!$S$12,'IV. MA'!$W$12,'IV. MA'!$AA$12,'IV. MA'!$AE$12,'IV. MA'!$AI$12,'IV. MA'!$AM$12,'IV. MA'!$AQ$12,'IV. MA'!$AU$12,'IV. MA'!$AY$12,'IV. MA'!$BC$12,'IV. MA'!$BG$12,'IV. MA'!$BK$12,'IV. MA'!$BO$12,'IV. MA'!$BS$12),"") | N15: ==IFERROR(CHOOSE($AD$5,'IV. MA'!$D$12,'IV. MA'!$H$12,'IV. MA'!$L$12,'IV. MA'!$P$12,'IV. MA'!$T$12,'IV. MA'!$X$12,'IV. MA'!$AB$12,'IV. MA'!$AF$12,'IV. MA'!$AJ$12,'IV. MA'!$AN$12,'IV. MA'!$AR$12,'IV. MA'!$AV$12,'IV. MA'!$AZ$12,'IV. MA'!$BD$12,'IV. MA'!$BH$12,'IV. MA'!$BL$12,'IV. MA'!$BP$12,'IV. MA'!$BT$12),"")
C16: ==IF(4<=E11,"Periode "&E10&" (#4)","") | E16: ==IF(4<=E11,IFERROR(SUMIFS('Daten'!$BF$1:$BF$18,'Daten'!$BB$1:$BB$18,E10,'Daten'!$BD$1:$BD$18,4),0),"") | G16: ==IF(4<=E11,IFERROR(SUMIFS('Daten'!$BG$1:$BG$18,'Daten'!$BB$1:$BB$18,E10,'Daten'!$BD$1:$BD$18,4),0),"") | L16: Projektaktivitaeten | M16: ==IFERROR(CHOOSE($AD$5,'IV. MA'!$C$13,'IV. MA'!$G$13,'IV. MA'!$K$13,'IV. MA'!$O$13,'IV. MA'!$S$13,'IV. MA'!$W$13,'IV. MA'!$AA$13,'IV. MA'!$AE$13,'IV. MA'!$AI$13,'IV. MA'!$AM$13,'IV. MA'!$AQ$13,'IV. MA'!$AU$13,'IV. MA'!$AY$13,'IV. MA'!$BC$13,'IV. MA'!$BG$13,'IV. MA'!$BK$13,'IV. MA'!$BO$13,'IV. MA'!$BS$13),"") | N16: ==IFERROR(CHOOSE($AD$5,'IV. MA'!$D$13,'IV. MA'!$H$13,'IV. MA'!$L$13,'IV. MA'!$P$13,'IV. MA'!$T$13,'IV. MA'!$X$13,'IV. MA'!$AB$13,'IV. MA'!$AF$13,'IV. MA'!$AJ$13,'IV. MA'!$AN$13,'IV. MA'!$AR$13,'IV. MA'!$AV$13,'IV. MA'!$AZ$13,'IV. MA'!$BD$13,'IV. MA'!$BH$13,'IV. MA'!$BL$13,'IV. MA'!$BP$13,'IV. MA'!$BT$13),"")
C17: ==IF(5<=E11,"Periode "&E10&" (#5)","") | E17: ==IF(5<=E11,IFERROR(SUMIFS('Daten'!$BF$1:$BF$18,'Daten'!$BB$1:$BB$18,E10,'Daten'!$BD$1:$BD$18,5),0),"") | G17: ==IF(5<=E11,IFERROR(SUMIFS('Daten'!$BG$1:$BG$18,'Daten'!$BB$1:$BB$18,E10,'Daten'!$BD$1:$BD$18,5),0),"") | L17: Projektverwaltung | M17: ==IFERROR(CHOOSE($AD$5,'IV. MA'!$C$14,'IV. MA'!$G$14,'IV. MA'!$K$14,'IV. MA'!$O$14,'IV. MA'!$S$14,'IV. MA'!$W$14,'IV. MA'!$AA$14,'IV. MA'!$AE$14,'IV. MA'!$AI$14,'IV. MA'!$AM$14,'IV. MA'!$AQ$14,'IV. MA'!$AU$14,'IV. MA'!$AY$14,'IV. MA'!$BC$14,'IV. MA'!$BG$14,'IV. MA'!$BK$14,'IV. MA'!$BO$14,'IV. MA'!$BS$14),"") | N17: ==IFERROR(CHOOSE($AD$5,'IV. MA'!$D$14,'IV. MA'!$H$14,'IV. MA'!$L$14,'IV. MA'!$P$14,'IV. MA'!$T$14,'IV. MA'!$X$14,'IV. MA'!$AB$14,'IV. MA'!$AF$14,'IV. MA'!$AJ$14,'IV. MA'!$AN$14,'IV. MA'!$AR$14,'IV. MA'!$AV$14,'IV. MA'!$AZ$14,'IV. MA'!$BD$14,'IV. MA'!$BH$14,'IV. MA'!$BL$14,'IV. MA'!$BP$14,'IV. MA'!$BT$14),"")
C18: ==IF(6<=E11,"Periode "&E10&" (#6)","") | E18: ==IF(6<=E11,IFERROR(SUMIFS('Daten'!$BF$1:$BF$18,'Daten'!$BB$1:$BB$18,E10,'Daten'!$BD$1:$BD$18,6),0),"") | G18: ==IF(6<=E11,IFERROR(SUMIFS('Daten'!$BG$1:$BG$18,'Daten'!$BB$1:$BB$18,E10,'Daten'!$BD$1:$BD$18,6),0),"") | L18: Evaluierung | M18: ==IFERROR(CHOOSE($AD$5,'IV. MA'!$C$15,'IV. MA'!$G$15,'IV. MA'!$K$15,'IV. MA'!$O$15,'IV. MA'!$S$15,'IV. MA'!$W$15,'IV. MA'!$AA$15,'IV. MA'!$AE$15,'IV. MA'!$AI$15,'IV. MA'!$AM$15,'IV. MA'!$AQ$15,'IV. MA'!$AU$15,'IV. MA'!$AY$15,'IV. MA'!$BC$15,'IV. MA'!$BG$15,'IV. MA'!$BK$15,'IV. MA'!$BO$15,'IV. MA'!$BS$15),"") | N18: ==IFERROR(CHOOSE($AD$5,'IV. MA'!$D$15,'IV. MA'!$H$15,'IV. MA'!$L$15,'IV. MA'!$P$15,'IV. MA'!$T$15,'IV. MA'!$X$15,'IV. MA'!$AB$15,'IV. MA'!$AF$15,'IV. MA'!$AJ$15,'IV. MA'!$AN$15,'IV. MA'!$AR$15,'IV. MA'!$AV$15,'IV. MA'!$AZ$15,'IV. MA'!$BD$15,'IV. MA'!$BH$15,'IV. MA'!$BL$15,'IV. MA'!$BP$15,'IV. MA'!$BT$15),"")
L19: Audit | M19: ==IFERROR(CHOOSE($AD$5,'IV. MA'!$C$16,'IV. MA'!$G$16,'IV. MA'!$K$16,'IV. MA'!$O$16,'IV. MA'!$S$16,'IV. MA'!$W$16,'IV. MA'!$AA$16,'IV. MA'!$AE$16,'IV. MA'!$AI$16,'IV. MA'!$AM$16,'IV. MA'!$AQ$16,'IV. MA'!$AU$16,'IV. MA'!$AY$16,'IV. MA'!$BC$16,'IV. MA'!$BG$16,'IV. MA'!$BK$16,'IV. MA'!$BO$16,'IV. MA'!$BS$16),"") | N19: ==IFERROR(CHOOSE($AD$5,'IV. MA'!$D$16,'IV. MA'!$H$16,'IV. MA'!$L$16,'IV. MA'!$P$16,'IV. MA'!$T$16,'IV. MA'!$X$16,'IV. MA'!$AB$16,'IV. MA'!$AF$16,'IV. MA'!$AJ$16,'IV. MA'!$AN$16,'IV. MA'!$AR$16,'IV. MA'!$AV$16,'IV. MA'!$AZ$16,'IV. MA'!$BD$16,'IV. MA'!$BH$16,'IV. MA'!$BL$16,'IV. MA'!$BP$16,'IV. MA'!$BT$16),"")
B20: KMW-Mittelprüfung (Mittelanforderung) | L20: Reserve | M20: ==IFERROR(CHOOSE($AD$5,'IV. MA'!$C$17,'IV. MA'!$G$17,'IV. MA'!$K$17,'IV. MA'!$O$17,'IV. MA'!$S$17,'IV. MA'!$W$17,'IV. MA'!$AA$17,'IV. MA'!$AE$17,'IV. MA'!$AI$17,'IV. MA'!$AM$17,'IV. MA'!$AQ$17,'IV. MA'!$AU$17,'IV. MA'!$AY$17,'IV. MA'!$BC$17,'IV. MA'!$BG$17,'IV. MA'!$BK$17,'IV. MA'!$BO$17,'IV. MA'!$BS$17),"") | N20: ==IFERROR(CHOOSE($AD$5,'IV. MA'!$D$17,'IV. MA'!$H$17,'IV. MA'!$L$17,'IV. MA'!$P$17,'IV. MA'!$T$17,'IV. MA'!$X$17,'IV. MA'!$AB$17,'IV. MA'!$AF$17,'IV. MA'!$AJ$17,'IV. MA'!$AN$17,'IV. MA'!$AR$17,'IV. MA'!$AV$17,'IV. MA'!$AZ$17,'IV. MA'!$BD$17,'IV. MA'!$BH$17,'IV. MA'!$BL$17,'IV. MA'!$BP$17,'IV. MA'!$BT$17),"")
L21: SUMME | M21: ==IFERROR(CHOOSE($AD$5,'IV. MA'!$C$18,'IV. MA'!$G$18,'IV. MA'!$K$18,'IV. MA'!$O$18,'IV. MA'!$S$18,'IV. MA'!$W$18,'IV. MA'!$AA$18,'IV. MA'!$AE$18,'IV. MA'!$AI$18,'IV. MA'!$AM$18,'IV. MA'!$AQ$18,'IV. MA'!$AU$18,'IV. MA'!$AY$18,'IV. MA'!$BC$18,'IV. MA'!$BG$18,'IV. MA'!$BK$18,'IV. MA'!$BO$18,'IV. MA'!$BS$18),"") | N21: ==IFERROR(CHOOSE($AD$5,'IV. MA'!$D$18,'IV. MA'!$H$18,'IV. MA'!$L$18,'IV. MA'!$P$18,'IV. MA'!$T$18,'IV. MA'!$X$18,'IV. MA'!$AB$18,'IV. MA'!$AF$18,'IV. MA'!$AJ$18,'IV. MA'!$AN$18,'IV. MA'!$AR$18,'IV. MA'!$AV$18,'IV. MA'!$AZ$18,'IV. MA'!$BD$18,'IV. MA'!$BH$18,'IV. MA'!$BL$18,'IV. MA'!$BP$18,'IV. MA'!$BT$18),"")
B22: Bewilligte KMW-Mittel | D22: ==IFERROR(ROUND(KMW_Mittel_EUR,2),0) | F22: Abzugsoptionen KMW-Mittel
B23: Davon Reserve | D23: ==IFERROR(ROUND(Kosten_Reserve_EUR,2),0) | F23: Abzug | G23: Saldovortrag | I23: ==IFERROR(ROUND(Saldovortrag_EUR,2),0) | L23: Gesamtbedarf an Mitteln: | M23: ==IFERROR(CHOOSE($AD$5,'IV. MA'!$C$20,'IV. MA'!$G$20,'IV. MA'!$K$20,'IV. MA'!$O$20,'IV. MA'!$S$20,'IV. MA'!$W$20,'IV. MA'!$AA$20,'IV. MA'!$AE$20,'IV. MA'!$AI$20,'IV. MA'!$AM$20,'IV. MA'!$AQ$20,'IV. MA'!$AU$20,'IV. MA'!$AY$20,'IV. MA'!$BC$20,'IV. MA'!$BG$20,'IV. MA'!$BK$20,'IV. MA'!$BO$20,'IV. MA'!$BS$20),"") | N23: ==IFERROR(CHOOSE($AD$5,'IV. MA'!$D$20,'IV. MA'!$H$20,'IV. MA'!$L$20,'IV. MA'!$P$20,'IV. MA'!$T$20,'IV. MA'!$X$20,'IV. MA'!$AB$20,'IV. MA'!$AF$20,'IV. MA'!$AJ$20,'IV. MA'!$AN$20,'IV. MA'!$AR$20,'IV. MA'!$AV$20,'IV. MA'!$AZ$20,'IV. MA'!$BD$20,'IV. MA'!$BH$20,'IV. MA'!$BL$20,'IV. MA'!$BP$20,'IV. MA'!$BT$20),"")
B24: ==IF(Reserve_Freigabe="Ja","Operatives Budget (Reserve freigegeben)","Operatives Budget (abzgl. Reserve)") | D24: ==IF(Reserve_Freigabe="Ja",ROUND($D$22,2),ROUND($D$22-$D$23,2)) | F24: Abzug | G24: Mehreinnahmen | I24: ==I88 -> 0 | L24: abzüglich Eigenmittel: | M24: ==IFERROR(CHOOSE($AD$5,'IV. MA'!$C$21,'IV. MA'!$G$21,'IV. MA'!$K$21,'IV. MA'!$O$21,'IV. MA'!$S$21,'IV. MA'!$W$21,'IV. MA'!$AA$21,'IV. MA'!$AE$21,'IV. MA'!$AI$21,'IV. MA'!$AM$21,'IV. MA'!$AQ$21,'IV. MA'!$AU$21,'IV. MA'!$AY$21,'IV. MA'!$BC$21,'IV. MA'!$BG$21,'IV. MA'!$BK$21,'IV. MA'!$BO$21,'IV. MA'!$BS$21),"") | N24: ==IFERROR(CHOOSE($AD$5,'IV. MA'!$D$21,'IV. MA'!$H$21,'IV. MA'!$L$21,'IV. MA'!$P$21,'IV. MA'!$T$21,'IV. MA'!$X$21,'IV. MA'!$AB$21,'IV. MA'!$AF$21,'IV. MA'!$AJ$21,'IV. MA'!$AN$21,'IV. MA'!$AR$21,'IV. MA'!$AV$21,'IV. MA'!$AZ$21,'IV. MA'!$BD$21,'IV. MA'!$BH$21,'IV. MA'!$BL$21,'IV. MA'!$BP$21,'IV. MA'!$BT$21),"")
B25: Bereitgestellte KMW-Mittel | D25: ==IFERROR(ROUND(SUBTOTAL(109,TblKMWMittel[Betrag]),2),0) | F25: Abzug | G25: Prognostizierte Mehreinnahmen | I25: ==ROUND(MAX(0,MAX(0,(SUM($G$97:$G$100)-$G$99)+SUMIFS('Daten'!$BH$1:$BH$18,'Daten'!$BB$1:$BB$18,E10,'Daten'!$BD$1:$BD$18,"<="&E11,'Daten'!$BD$1:$BD$18,">=1")-(SUM($H$97:$H$100)-$H$99))-I88),2) -> 0 | L25: abzüglich Drittmittel: | M25: ==IFERROR(CHOOSE($AD$5,'IV. MA'!$C$22,'IV. MA'!$G$22,'IV. MA'!$K$22,'IV. MA'!$O$22,'IV. MA'!$S$22,'IV. MA'!$W$22,'IV. MA'!$AA$22,'IV. MA'!$AE$22,'IV. MA'!$AI$22,'IV. MA'!$AM$22,'IV. MA'!$AQ$22,'IV. MA'!$AU$22,'IV. MA'!$AY$22,'IV. MA'!$BC$22,'IV. MA'!$BG$22,'IV. MA'!$BK$22,'IV. MA'!$BO$22,'IV. MA'!$BS$22),"") | N25: ==IFERROR(CHOOSE($AD$5,'IV. MA'!$D$22,'IV. MA'!$H$22,'IV. MA'!$L$22,'IV. MA'!$P$22,'IV. MA'!$T$22,'IV. MA'!$X$22,'IV. MA'!$AB$22,'IV. MA'!$AF$22,'IV. MA'!$AJ$22,'IV. MA'!$AN$22,'IV. MA'!$AR$22,'IV. MA'!$AV$22,'IV. MA'!$AZ$22,'IV. MA'!$BD$22,'IV. MA'!$BH$22,'IV. MA'!$BL$22,'IV. MA'!$BP$22,'IV. MA'!$BT$22),"")
B26: Verfügbare KMW-Mittel | D26: ==ROUND($D$24-$D$25,2) | G26: Abzugsoptionen KMW insgesamt | I26: ==ROUND(IF($F$23="Abzug",MAX(0,$I$23),0)+IF($F$24="Abzug",MAX(0,$I$24),0)+IF($F$25="Abzug",MAX(0,$I$25),0),2) | L26: ==IFERROR(CHOOSE($AD$5,'IV. MA'!$B$23,'IV. MA'!$F$23,'IV. MA'!$J$23,'IV. MA'!$N$23,'IV. MA'!$R$23,'IV. MA'!$V$23,'IV. MA'!$Z$23,'IV. MA'!$AD$23,'IV. MA'!$AH$23,'IV. MA'!$AL$23,'IV. MA'!$AP$23,'IV. MA'!$AT$23,'IV. MA'!$AX$23,'IV. MA'!$BB$23,'IV. MA'!$BF$23,'IV. MA'!$BJ$23,'IV. MA'!$BN$23,'IV. MA'!$BR$23),"") | M26: ==IFERROR(CHOOSE($AD$5,'IV. MA'!$C$23,'IV. MA'!$G$23,'IV. MA'!$K$23,'IV. MA'!$O$23,'IV. MA'!$S$23,'IV. MA'!$W$23,'IV. MA'!$AA$23,'IV. MA'!$AE$23,'IV. MA'!$AI$23,'IV. MA'!$AM$23,'IV. MA'!$AQ$23,'IV. MA'!$AU$23,'IV. MA'!$AY$23,'IV. MA'!$BC$23,'IV. MA'!$BG$23,'IV. MA'!$BK$23,'IV. MA'!$BO$23,'IV. MA'!$BS$23),"") | N26: ==IFERROR(CHOOSE($AD$5,'IV. MA'!$D$23,'IV. MA'!$H$23,'IV. MA'!$L$23,'IV. MA'!$P$23,'IV. MA'!$T$23,'IV. MA'!$X$23,'IV. MA'!$AB$23,'IV. MA'!$AF$23,'IV. MA'!$AJ$23,'IV. MA'!$AN$23,'IV. MA'!$AR$23,'IV. MA'!$AV$23,'IV. MA'!$AZ$23,'IV. MA'!$BD$23,'IV. MA'!$BH$23,'IV. MA'!$BL$23,'IV. MA'!$BP$23,'IV. MA'!$BT$23),"")
G27: Verfügbare KMW-Mittel (bereinigt) | I27: ==ROUND($D$26-$I$26,2)
L28: KMW-Mittel Anforderung: | M28: ==IFERROR(CHOOSE($AD$5,'IV. MA'!$C$25,'IV. MA'!$G$25,'IV. MA'!$K$25,'IV. MA'!$O$25,'IV. MA'!$S$25,'IV. MA'!$W$25,'IV. MA'!$AA$25,'IV. MA'!$AE$25,'IV. MA'!$AI$25,'IV. MA'!$AM$25,'IV. MA'!$AQ$25,'IV. MA'!$AU$25,'IV. MA'!$AY$25,'IV. MA'!$BC$25,'IV. MA'!$BG$25,'IV. MA'!$BK$25,'IV. MA'!$BO$25,'IV. MA'!$BS$25),"") | N28: ==IFERROR(CHOOSE($AD$5,'IV. MA'!$D$25,'IV. MA'!$H$25,'IV. MA'!$L$25,'IV. MA'!$P$25,'IV. MA'!$T$25,'IV. MA'!$X$25,'IV. MA'!$AB$25,'IV. MA'!$AF$25,'IV. MA'!$AJ$25,'IV. MA'!$AN$25,'IV. MA'!$AR$25,'IV. MA'!$AV$25,'IV. MA'!$AZ$25,'IV. MA'!$BD$25,'IV. MA'!$BH$25,'IV. MA'!$BL$25,'IV. MA'!$BP$25,'IV. MA'!$BT$25),"")
B29: Abzüglich aktuelle Anforderung | D29: ==IFERROR(ROUND(SUMIFS('Daten'!$BV$1:$BV$198,'Daten'!$BT$1:$BT$198,"KMW-Mittel",'Daten'!$BR$1:$BR$198,E10,'Daten'!$BS$1:$BS$198,E11),2),0) | F29: Abzüglich aktuelle Anforderung | I29: ==IFERROR(ROUND(SUMIFS('Daten'!$BV$1:$BV$198,'Daten'!$BT$1:$BT$198,"KMW-Mittel",'Daten'!$BR$1:$BR$198,E10,'Daten'!$BS$1:$BS$198,E11),2),0)
B30: Verbleibende KMW-Mittel | D30: ==ROUND($D$26-MAX(0,$D$29),2) | F30: Verbleibende KMW-Mittel (bereinigt) | I30: ==ROUND($I$27-MAX(0,$I$29),2)
B32: Abzüglich manueller Betrag | F32: Abzüglich manueller Betrag
B33: Verbleibende KMW-Mittel | D33: ==ROUND($D$26-MAX(0,$D$29)-MAX(0,$D$32),2) | F33: Verbleibende KMW-Mittel (bereinigt) | I33: ==ROUND($I$27-MAX(0,$I$29)-MAX(0,$I$32),2)
B36: Monatslimit-Prüfung
D38: Lokalwährung | E38: Euro
B39: Geprüfte Periode (aus MA-Auswahl) | D39: ==E10
B40: Anforderungshöhe | D40: ==IFERROR(ROUND(SUMIFS('Daten'!$BF$1:$BF$18,'Daten'!$BB$1:$BB$18,E10,'Daten'!$BD$1:$BD$18,"<="&E11,'Daten'!$BD$1:$BD$18,">=1"),2),0) | E40: ==IFERROR(ROUND(SUMIFS('Daten'!$BG$1:$BG$18,'Daten'!$BB$1:$BB$18,E10,'Daten'!$BD$1:$BD$18,"<="&E11,'Daten'!$BD$1:$BD$18,">=1"),2),0)
B41: Jahr | D41: Jahr 1
B42: Jahresbudget | D42: ==IFERROR(ROUND(CHOOSE(MATCH($D$41,{"Jahr 1";"Jahr 2";"Jahr 3"},0),SUBTOTAL(109,TblBudgetAusgaben[Jahr 1]),SUBTOTAL(109,TblBudgetAusgaben[Jahr 2]),SUBTOTAL(109,TblBudgetAusgaben[Jahr 3])),2),0) | E42: ==IFERROR(ROUND($D$42/Budget_Kurs,2),0)
B43: Limit-Monate | D43: 8
B44: Bezugszeitraum (Monate) | D44: 12
B45: Anforderung deckt (Monate) | D45: 6
B46: 8-Monats-Limit | D46: ==IFERROR(ROUND($D$42*$D$43/$D$44,2),0) | E46: ==IFERROR(ROUND($E$42*$D$43/$D$44,2),0)
B47: Status | D47: ==IF($D$40<=$D$46,"OK","ÜBERSCHRITTEN") | E47: ==IF($E$40<=$E$46,"OK","ÜBERSCHRITTEN")
B48: Überschreitung | D48: ==ROUND(MAX(0,$D$40-$D$46),2) | E48: ==ROUND(MAX(0,$E$40-$E$46),2)
B49: Auslastung % | D49: ==IFERROR($D$40/$D$46,0) | E49: ==IFERROR($E$40/$E$46,0)
B51: Prognostizierte Finanzierungsanteile
B53: Kategorie | C53: Prognose (LC) | D53: Budget (LC) | E53: Differenz (LC) | F53: Abweichung (LC) | G53: Prognose (EUR) | H53: Budget (EUR) | I53: Differenz (EUR) | J53: Abweichung (EUR)
B54: Eigenmittel | C54: ==IFERROR(ROUND(SUMIFS('Daten'!$BU$1:$BU$198,'Daten'!$BT$1:$BT$198,"Eigenmittel",'Daten'!$BR$1:$BR$198,E10,'Daten'!$BS$1:$BS$198,"<="&E11,'Daten'!$BS$1:$BS$198,">=1"),2),0) | D54: ==IFERROR(ROUND(Eigenmittel_LW,2),0) | E54: ==ROUND(IFERROR($C$54-$D$54,0),2) | F54: ==ROUND(IFERROR(($C$54/$D$54)-1,0),4) | G54: ==IFERROR(ROUND(SUMIFS('Daten'!$BV$1:$BV$198,'Daten'!$BT$1:$BT$198,"Eigenmittel",'Daten'!$BR$1:$BR$198,E10,'Daten'!$BS$1:$BS$198,"<="&E11,'Daten'!$BS$1:$BS$198,">=1"),2),0) | H54: ==IFERROR(ROUND(Eigenmittel_EUR,2),0) | I54: ==ROUND(IFERROR($G$54-$H$54,0),2) | J54: ==ROUND(IFERROR(($G$54/$H$54)-1,0),4)
B55: Drittmittel | C55: ==IFERROR(ROUND(SUMIFS('Daten'!$BU$1:$BU$198,'Daten'!$BT$1:$BT$198,"Drittmittel",'Daten'!$BR$1:$BR$198,E10,'Daten'!$BS$1:$BS$198,"<="&E11,'Daten'!$BS$1:$BS$198,">=1"),2),0) | D55: ==IFERROR(ROUND(Drittmittel_LW,2),0) | E55: ==ROUND(IFERROR($C$55-$D$55,0),2) | F55: ==ROUND(IFERROR(($C$55/$D$55)-1,0),4) | G55: ==IFERROR(ROUND(SUMIFS('Daten'!$BV$1:$BV$198,'Daten'!$BT$1:$BT$198,"Drittmittel",'Daten'!$BR$1:$BR$198,E10,'Daten'!$BS$1:$BS$198,"<="&E11,'Daten'!$BS$1:$BS$198,">=1"),2),0) | H55: ==IFERROR(ROUND(Drittmittel_EUR,2),0) | I55: ==ROUND(IFERROR($G$55-$H$55,0),2) | J55: ==ROUND(IFERROR(($G$55/$H$55)-1,0),4)
B56: KMW-Mittel | C56: ==IFERROR(ROUND(SUMIFS('Daten'!$BU$1:$BU$198,'Daten'!$BT$1:$BT$198,"KMW-Mittel",'Daten'!$BR$1:$BR$198,E10,'Daten'!$BS$1:$BS$198,"<="&E11,'Daten'!$BS$1:$BS$198,">=1"),2),0) | D56: ==IFERROR(ROUND(KMW_Mittel_LW,2),0) | E56: ==ROUND(IFERROR($C$56-$D$56,0),2) | F56: ==ROUND(IFERROR(($C$56/$D$56)-1,0),4) | G56: ==IFERROR(ROUND(SUMIFS('Daten'!$BV$1:$BV$198,'Daten'!$BT$1:$BT$198,"KMW-Mittel",'Daten'!$BR$1:$BR$198,E10,'Daten'!$BS$1:$BS$198,"<="&E11,'Daten'!$BS$1:$BS$198,">=1"),2),0) | H56: ==IFERROR(ROUND(KMW_Mittel_EUR,2),0) | I56: ==ROUND(IFERROR($G$56-$H$56,0),2) | J56: ==ROUND(IFERROR(($G$56/$H$56)-1,0),4)
B57: Zinsertraege | C57: ==IFERROR(ROUND(SUMIFS('Daten'!$BU$1:$BU$198,'Daten'!$BT$1:$BT$198,"Zinsertraege",'Daten'!$BR$1:$BR$198,E10,'Daten'!$BS$1:$BS$198,"<="&E11,'Daten'!$BS$1:$BS$198,">=1"),2),0) | D57: ==IFERROR(ROUND(0,2),0) | E57: ==ROUND(IFERROR($C$57-$D$57,0),2) | F57: ==ROUND(IFERROR(($C$57/$D$57)-1,0),4) | G57: ==IFERROR(ROUND(SUMIFS('Daten'!$BV$1:$BV$198,'Daten'!$BT$1:$BT$198,"Zinsertraege",'Daten'!$BR$1:$BR$198,E10,'Daten'!$BS$1:$BS$198,"<="&E11,'Daten'!$BS$1:$BS$198,">=1"),2),0) | H57: ==IFERROR(ROUND(0,2),0) | I57: ==ROUND(IFERROR($G$57-$H$57,0),2) | J57: ==ROUND(IFERROR(($G$57/$H$57)-1,0),4)
B58: GESAMT | C58: ==ROUND(SUM($C$54:$C$57),2) | D58: ==ROUND(SUM($D$54:$D$57),2) | E58: ==ROUND(SUM($E$54:$E$57),2) | F58: ==ROUND(IFERROR(($C$58/$D$58)-1,0),4) | G58: ==ROUND(SUM($G$54:$G$57),2) | H58: ==ROUND(SUM($H$54:$H$57),2) | I58: ==ROUND(SUM($I$54:$I$57),2) | J58: ==ROUND(IFERROR(($G$58/$H$58)-1,0),4)
B60: Prognoseprüfung (Ausgaben)
B62: Kategorie | C62: Prognose (LC) | D62: Budget (LC) | E62: Differenz (LC) | F62: Abweichung (LC) | G62: Prognose (EUR) | H62: Budget (EUR) | I62: Differenz (EUR) | J62: Abweichung (EUR)
B63: Bauausgaben | C63: ==IFERROR(ROUND(SUMIFS('Daten'!$BU$1:$BU$198,'Daten'!$BT$1:$BT$198,"Bauausgaben",'Daten'!$BR$1:$BR$198,E10,'Daten'!$BS$1:$BS$198,"<="&E11,'Daten'!$BS$1:$BS$198,">=1"),2),0) | D63: ==IFERROR(ROUND(Kosten_Bauausgaben_LW,2),0) | E63: ==ROUND(IFERROR($C$63-$D$63,0),2) | F63: ==ROUND(IFERROR(($C$63/$D$63)-1,0),4) | G63: ==IFERROR(ROUND(SUMIFS('Daten'!$BV$1:$BV$198,'Daten'!$BT$1:$BT$198,"Bauausgaben",'Daten'!$BR$1:$BR$198,E10,'Daten'!$BS$1:$BS$198,"<="&E11,'Daten'!$BS$1:$BS$198,">=1"),2),0) | H63: ==IFERROR(ROUND(Kosten_Bauausgaben_EUR,2),0) | I63: ==ROUND(IFERROR($G$63-$H$63,0),2) | J63: ==ROUND(IFERROR(($G$63/$H$63)-1,0),4)
B64: Investitionen | C64: ==IFERROR(ROUND(SUMIFS('Daten'!$BU$1:$BU$198,'Daten'!$BT$1:$BT$198,"Investitionen",'Daten'!$BR$1:$BR$198,E10,'Daten'!$BS$1:$BS$198,"<="&E11,'Daten'!$BS$1:$BS$198,">=1"),2),0) | D64: ==IFERROR(ROUND(Kosten_Investitionen_LW,2),0) | E64: ==ROUND(IFERROR($C$64-$D$64,0),2) | F64: ==ROUND(IFERROR(($C$64/$D$64)-1,0),4) | G64: ==IFERROR(ROUND(SUMIFS('Daten'!$BV$1:$BV$198,'Daten'!$BT$1:$BT$198,"Investitionen",'Daten'!$BR$1:$BR$198,E10,'Daten'!$BS$1:$BS$198,"<="&E11,'Daten'!$BS$1:$BS$198,">=1"),2),0) | H64: ==IFERROR(ROUND(Kosten_Investitionen_EUR,2),0) | I64: ==ROUND(IFERROR($G$64-$H$64,0),2) | J64: ==ROUND(IFERROR(($G$64/$H$64)-1,0),4)
B65: Personalkosten | C65: ==IFERROR(ROUND(SUMIFS('Daten'!$BU$1:$BU$198,'Daten'!$BT$1:$BT$198,"Personalkosten",'Daten'!$BR$1:$BR$198,E10,'Daten'!$BS$1:$BS$198,"<="&E11,'Daten'!$BS$1:$BS$198,">=1"),2),0) | D65: ==IFERROR(ROUND(Kosten_Personalkosten_LW,2),0) | E65: ==ROUND(IFERROR($C$65-$D$65,0),2) | F65: ==ROUND(IFERROR(($C$65/$D$65)-1,0),4) | G65: ==IFERROR(ROUND(SUMIFS('Daten'!$BV$1:$BV$198,'Daten'!$BT$1:$BT$198,"Personalkosten",'Daten'!$BR$1:$BR$198,E10,'Daten'!$BS$1:$BS$198,"<="&E11,'Daten'!$BS$1:$BS$198,">=1"),2),0) | H65: ==IFERROR(ROUND(Kosten_Personalkosten_EUR,2),0) | I65: ==ROUND(IFERROR($G$65-$H$65,0),2) | J65: ==ROUND(IFERROR(($G$65/$H$65)-1,0),4)
B66: Projektaktivitaeten | C66: ==IFERROR(ROUND(SUMIFS('Daten'!$BU$1:$BU$198,'Daten'!$BT$1:$BT$198,"Projektaktivitaeten",'Daten'!$BR$1:$BR$198,E10,'Daten'!$BS$1:$BS$198,"<="&E11,'Daten'!$BS$1:$BS$198,">=1"),2),0) | D66: ==IFERROR(ROUND(Kosten_Projektaktivitaeten_LW,2),0) | E66: ==ROUND(IFERROR($C$66-$D$66,0),2) | F66: ==ROUND(IFERROR(($C$66/$D$66)-1,0),4) | G66: ==IFERROR(ROUND(SUMIFS('Daten'!$BV$1:$BV$198,'Daten'!$BT$1:$BT$198,"Projektaktivitaeten",'Daten'!$BR$1:$BR$198,E10,'Daten'!$BS$1:$BS$198,"<="&E11,'Daten'!$BS$1:$BS$198,">=1"),2),0) | H66: ==IFERROR(ROUND(Kosten_Projektaktivitaeten_EUR,2),0) | I66: ==ROUND(IFERROR($G$66-$H$66,0),2) | J66: ==ROUND(IFERROR(($G$66/$H$66)-1,0),4)
B67: Projektverwaltung | C67: ==IFERROR(ROUND(SUMIFS('Daten'!$BU$1:$BU$198,'Daten'!$BT$1:$BT$198,"Projektverwaltung",'Daten'!$BR$1:$BR$198,E10,'Daten'!$BS$1:$BS$198,"<="&E11,'Daten'!$BS$1:$BS$198,">=1"),2),0) | D67: ==IFERROR(ROUND(Kosten_Projektverwaltung_LW,2),0) | E67: ==ROUND(IFERROR($C$67-$D$67,0),2) | F67: ==ROUND(IFERROR(($C$67/$D$67)-1,0),4) | G67: ==IFERROR(ROUND(SUMIFS('Daten'!$BV$1:$BV$198,'Daten'!$BT$1:$BT$198,"Projektverwaltung",'Daten'!$BR$1:$BR$198,E10,'Daten'!$BS$1:$BS$198,"<="&E11,'Daten'!$BS$1:$BS$198,">=1"),2),0) | H67: ==IFERROR(ROUND(Kosten_Projektverwaltung_EUR,2),0) | I67: ==ROUND(IFERROR($G$67-$H$67,0),2) | J67: ==ROUND(IFERROR(($G$67/$H$67)-1,0),4)
B68: Evaluierung | C68: ==IFERROR(ROUND(SUMIFS('Daten'!$BU$1:$BU$198,'Daten'!$BT$1:$BT$198,"Evaluierung",'Daten'!$BR$1:$BR$198,E10,'Daten'!$BS$1:$BS$198,"<="&E11,'Daten'!$BS$1:$BS$198,">=1"),2),0) | D68: ==IFERROR(ROUND(Kosten_Evaluierung_LW,2),0) | E68: ==ROUND(IFERROR($C$68-$D$68,0),2) | F68: ==ROUND(IFERROR(($C$68/$D$68)-1,0),4) | G68: ==IFERROR(ROUND(SUMIFS('Daten'!$BV$1:$BV$198,'Daten'!$BT$1:$BT$198,"Evaluierung",'Daten'!$BR$1:$BR$198,E10,'Daten'!$BS$1:$BS$198,"<="&E11,'Daten'!$BS$1:$BS$198,">=1"),2),0) | H68: ==IFERROR(ROUND(Kosten_Evaluierung_EUR,2),0) | I68: ==ROUND(IFERROR($G$68-$H$68,0),2) | J68: ==ROUND(IFERROR(($G$68/$H$68)-1,0),4)
B69: Audit | C69: ==IFERROR(ROUND(SUMIFS('Daten'!$BU$1:$BU$198,'Daten'!$BT$1:$BT$198,"Audit",'Daten'!$BR$1:$BR$198,E10,'Daten'!$BS$1:$BS$198,"<="&E11,'Daten'!$BS$1:$BS$198,">=1"),2),0) | D69: ==IFERROR(ROUND(Kosten_Audit_LW,2),0) | E69: ==ROUND(IFERROR($C$69-$D$69,0),2) | F69: ==ROUND(IFERROR(($C$69/$D$69)-1,0),4) | G69: ==IFERROR(ROUND(SUMIFS('Daten'!$BV$1:$BV$198,'Daten'!$BT$1:$BT$198,"Audit",'Daten'!$BR$1:$BR$198,E10,'Daten'!$BS$1:$BS$198,"<="&E11,'Daten'!$BS$1:$BS$198,">=1"),2),0) | H69: ==IFERROR(ROUND(Kosten_Audit_EUR,2),0) | I69: ==ROUND(IFERROR($G$69-$H$69,0),2) | J69: ==ROUND(IFERROR(($G$69/$H$69)-1,0),4)
B70: Reserve | C70: ==IFERROR(ROUND(SUMIFS('Daten'!$BU$1:$BU$198,'Daten'!$BT$1:$BT$198,"Reserve",'Daten'!$BR$1:$BR$198,E10,'Daten'!$BS$1:$BS$198,"<="&E11,'Daten'!$BS$1:$BS$198,">=1"),2),0) | D70: ==IFERROR(ROUND(Kosten_Reserve_LW,2),0) | E70: ==ROUND(IFERROR($C$70-$D$70,0),2) | F70: ==ROUND(IFERROR(($C$70/$D$70)-1,0),4) | G70: ==IFERROR(ROUND(SUMIFS('Daten'!$BV$1:$BV$198,'Daten'!$BT$1:$BT$198,"Reserve",'Daten'!$BR$1:$BR$198,E10,'Daten'!$BS$1:$BS$198,"<="&E11,'Daten'!$BS$1:$BS$198,">=1"),2),0) | H70: ==IFERROR(ROUND(Kosten_Reserve_EUR,2),0) | I70: ==ROUND(IFERROR($G$70-$H$70,0),2) | J70: ==ROUND(IFERROR(($G$70/$H$70)-1,0),4)
B71: GESAMT | C71: ==ROUND(SUM($C$63:$C$70),2) | D71: ==ROUND(SUM($D$63:$D$70),2) | E71: ==ROUND(SUM($E$63:$E$70),2) | F71: ==ROUND(IFERROR(($C$71/$D$71)-1,0),4) | G71: ==ROUND(SUM($G$63:$G$70),2) | H71: ==ROUND(SUM($H$63:$H$70),2) | I71: ==ROUND(SUM($I$63:$I$70),2) | J71: ==ROUND(IFERROR(($G$71/$H$71)-1,0),4)
B77: FINANZBERICHTSPRÜFUNG | L77: ==IF(E82=0,"Aktueller Finanzbericht (keiner gewählt)","Aktueller Finanzbericht – Periode "&E82)
B78: Basis: ausgewählter Finanzbericht (kumulativ bis zur Periode) | L78: Periode: | M78: ==IFERROR(CHOOSE(E82,'III. Finanzberichte'!$C$4,'III. Finanzberichte'!$J$4,'III. Finanzberichte'!$Q$4,'III. Finanzberichte'!$X$4,'III. Finanzberichte'!$AE$4,'III. Finanzberichte'!$AL$4,'III. Finanzberichte'!$AS$4,'III. Finanzberichte'!$AZ$4,'III. Finanzberichte'!$BG$4,'III. Finanzberichte'!$BN$4,'III. Finanzberichte'!$BU$4,'III. Finanzberichte'!$CB$4,'III. Finanzberichte'!$CI$4,'III. Finanzberichte'!$CP$4,'III. Finanzberichte'!$CW$4,'III. Finanzberichte'!$DD$4,'III. Finanzberichte'!$DK$4,'III. Finanzberichte'!$DR$4),"")
L79: Von: | M79: ==IFERROR(CHOOSE(E82,'III. Finanzberichte'!$C$5,'III. Finanzberichte'!$J$5,'III. Finanzberichte'!$Q$5,'III. Finanzberichte'!$X$5,'III. Finanzberichte'!$AE$5,'III. Finanzberichte'!$AL$5,'III. Finanzberichte'!$AS$5,'III. Finanzberichte'!$AZ$5,'III. Finanzberichte'!$BG$5,'III. Finanzberichte'!$BN$5,'III. Finanzberichte'!$BU$5,'III. Finanzberichte'!$CB$5,'III. Finanzberichte'!$CI$5,'III. Finanzberichte'!$CP$5,'III. Finanzberichte'!$CW$5,'III. Finanzberichte'!$DD$5,'III. Finanzberichte'!$DK$5,'III. Finanzberichte'!$DR$5),"")
C80: Finanzbericht auswählen | L80: Bis: | M80: ==IFERROR(CHOOSE(E82,'III. Finanzberichte'!$C$6,'III. Finanzberichte'!$J$6,'III. Finanzberichte'!$Q$6,'III. Finanzberichte'!$X$6,'III. Finanzberichte'!$AE$6,'III. Finanzberichte'!$AL$6,'III. Finanzberichte'!$AS$6,'III. Finanzberichte'!$AZ$6,'III. Finanzberichte'!$BG$6,'III. Finanzberichte'!$BN$6,'III. Finanzberichte'!$BU$6,'III. Finanzberichte'!$CB$6,'III. Finanzberichte'!$CI$6,'III. Finanzberichte'!$CP$6,'III. Finanzberichte'!$CW$6,'III. Finanzberichte'!$DD$6,'III. Finanzberichte'!$DK$6,'III. Finanzberichte'!$DR$6),"")
C81: Auswahl: | E81: Neuester FB | L81: Zeitraum: | M81: ==IFERROR(CHOOSE(E82,'III. Finanzberichte'!$C$7,'III. Finanzberichte'!$J$7,'III. Finanzberichte'!$Q$7,'III. Finanzberichte'!$X$7,'III. Finanzberichte'!$AE$7,'III. Finanzberichte'!$AL$7,'III. Finanzberichte'!$AS$7,'III. Finanzberichte'!$AZ$7,'III. Finanzberichte'!$BG$7,'III. Finanzberichte'!$BN$7,'III. Finanzberichte'!$BU$7,'III. Finanzberichte'!$CB$7,'III. Finanzberichte'!$CI$7,'III. Finanzberichte'!$CP$7,'III. Finanzberichte'!$CW$7,'III. Finanzberichte'!$DD$7,'III. Finanzberichte'!$DK$7,'III. Finanzberichte'!$DR$7),"")
C82: Geprüfte Periode | E82: ==IF(E81="Neuester FB",IFERROR(SUMPRODUCT(MAX(('Daten'!$BK$1:$BK$18=1)*'Daten'!$BJ$1:$BJ$18)),0),IF(LEFT(E81,8)="Periode ",IFERROR(VALUE(TRIM(MID(E81,9,5))),0),0)) | L82: Durchschnittskurs: | M82: ==IFERROR(CHOOSE(E82,'III. Finanzberichte'!$C$8,'III. Finanzberichte'!$J$8,'III. Finanzberichte'!$Q$8,'III. Finanzberichte'!$X$8,'III. Finanzberichte'!$AE$8,'III. Finanzberichte'!$AL$8,'III. Finanzberichte'!$AS$8,'III. Finanzberichte'!$AZ$8,'III. Finanzberichte'!$BG$8,'III. Finanzberichte'!$BN$8,'III. Finanzberichte'!$BU$8,'III. Finanzberichte'!$CB$8,'III. Finanzberichte'!$CI$8,'III. Finanzberichte'!$CP$8,'III. Finanzberichte'!$CW$8,'III. Finanzberichte'!$DD$8,'III. Finanzberichte'!$DK$8,'III. Finanzberichte'!$DR$8),"")
B84: KMW-Mittelprüfung | L84: Einnahmen
L85: Typ / ID | M85: Einnahmen (LC) | N85: Einnahmen (EUR) | O85: Kum. Einnahmen (LC) | P85: Kum. Einnahmen (EUR)
B86: Bewilligte KMW-Mittel | D86: ==IFERROR(ROUND(KMW_Mittel_EUR,2),0) | F86: Abzugsoptionen KMW-Mittel | L86: ==IFERROR(CHOOSE(E82,'III. Finanzberichte'!$B$11,'III. Finanzberichte'!$I$11,'III. Finanzberichte'!$P$11,'III. Finanzberichte'!$W$11,'III. Finanzberichte'!$AD$11,'III. Finanzberichte'!$AK$11,'III. Finanzberichte'!$AR$11,'III. Finanzberichte'!$AY$11,'III. Finanzberichte'!$BF$11,'III. Finanzberichte'!$BM$11,'III. Finanzberichte'!$BT$11,'III. Finanzberichte'!$CA$11,'III. Finanzberichte'!$CH$11,'III. Finanzberichte'!$CO$11,'III. Finanzberichte'!$CV$11,'III. Finanzberichte'!$DC$11,'III. Finanzberichte'!$DJ$11,'III. Finanzberichte'!$DQ$11),"") | M86: ==IFERROR(CHOOSE(E82,'III. Finanzberichte'!$C$11,'III. Finanzberichte'!$J$11,'III. Finanzberichte'!$Q$11,'III. Finanzberichte'!$X$11,'III. Finanzberichte'!$AE$11,'III. Finanzberichte'!$AL$11,'III. Finanzberichte'!$AS$11,'III. Finanzberichte'!$AZ$11,'III. Finanzberichte'!$BG$11,'III. Finanzberichte'!$BN$11,'III. Finanzberichte'!$BU$11,'III. Finanzberichte'!$CB$11,'III. Finanzberichte'!$CI$11,'III. Finanzberichte'!$CP$11,'III. Finanzberichte'!$CW$11,'III. Finanzberichte'!$DD$11,'III. Finanzberichte'!$DK$11,'III. Finanzberichte'!$DR$11),"") | N86: ==IFERROR(CHOOSE(E82,'III. Finanzberichte'!$D$11,'III. Finanzberichte'!$K$11,'III. Finanzberichte'!$R$11,'III. Finanzberichte'!$Y$11,'III. Finanzberichte'!$AF$11,'III. Finanzberichte'!$AM$11,'III. Finanzberichte'!$AT$11,'III. Finanzberichte'!$BA$11,'III. Finanzberichte'!$BH$11,'III. Finanzberichte'!$BO$11,'III. Finanzberichte'!$BV$11,'III. Finanzberichte'!$CC$11,'III. Finanzberichte'!$CJ$11,'III. Finanzberichte'!$CQ$11,'III. Finanzberichte'!$CX$11,'III. Finanzberichte'!$DE$11,'III. Finanzberichte'!$DL$11,'III. Finanzberichte'!$DS$11),"") | O86: ==IFERROR(CHOOSE(E82,'III. Finanzberichte'!$E$11,'III. Finanzberichte'!$L$11,'III. Finanzberichte'!$S$11,'III. Finanzberichte'!$Z$11,'III. Finanzberichte'!$AG$11,'III. Finanzberichte'!$AN$11,'III. Finanzberichte'!$AU$11,'III. Finanzberichte'!$BB$11,'III. Finanzberichte'!$BI$11,'III. Finanzberichte'!$BP$11,'III. Finanzberichte'!$BW$11,'III. Finanzberichte'!$CD$11,'III. Finanzberichte'!$CK$11,'III. Finanzberichte'!$CR$11,'III. Finanzberichte'!$CY$11,'III. Finanzberichte'!$DF$11,'III. Finanzberichte'!$DM$11,'III. Finanzberichte'!$DT$11),"") | P86: ==IFERROR(CHOOSE(E82,'III. Finanzberichte'!$F$11,'III. Finanzberichte'!$M$11,'III. Finanzberichte'!$T$11,'III. Finanzberichte'!$AA$11,'III. Finanzberichte'!$AH$11,'III. Finanzberichte'!$AO$11,'III. Finanzberichte'!$AV$11,'III. Finanzberichte'!$BC$11,'III. Finanzberichte'!$BJ$11,'III. Finanzberichte'!$BQ$11,'III. Finanzberichte'!$BX$11,'III. Finanzberichte'!$CE$11,'III. Finanzberichte'!$CL$11,'III. Finanzberichte'!$CS$11,'III. Finanzberichte'!$CZ$11,'III. Finanzberichte'!$DG$11,'III. Finanzberichte'!$DN$11,'III. Finanzberichte'!$DU$11),"")
B87: Davon Reserve | D87: ==IFERROR(ROUND(Kosten_Reserve_EUR,2),0) | F87: Abzug | G87: Saldovortrag | I87: ==IFERROR(ROUND(Saldovortrag_EUR,2),0) | L87: Eigenmittel | M87: ==IFERROR(CHOOSE(E82,'III. Finanzberichte'!$C$12,'III. Finanzberichte'!$J$12,'III. Finanzberichte'!$Q$12,'III. Finanzberichte'!$X$12,'III. Finanzberichte'!$AE$12,'III. Finanzberichte'!$AL$12,'III. Finanzberichte'!$AS$12,'III. Finanzberichte'!$AZ$12,'III. Finanzberichte'!$BG$12,'III. Finanzberichte'!$BN$12,'III. Finanzberichte'!$BU$12,'III. Finanzberichte'!$CB$12,'III. Finanzberichte'!$CI$12,'III. Finanzberichte'!$CP$12,'III. Finanzberichte'!$CW$12,'III. Finanzberichte'!$DD$12,'III. Finanzberichte'!$DK$12,'III. Finanzberichte'!$DR$12),"") | N87: ==IFERROR(CHOOSE(E82,'III. Finanzberichte'!$D$12,'III. Finanzberichte'!$K$12,'III. Finanzberichte'!$R$12,'III. Finanzberichte'!$Y$12,'III. Finanzberichte'!$AF$12,'III. Finanzberichte'!$AM$12,'III. Finanzberichte'!$AT$12,'III. Finanzberichte'!$BA$12,'III. Finanzberichte'!$BH$12,'III. Finanzberichte'!$BO$12,'III. Finanzberichte'!$BV$12,'III. Finanzberichte'!$CC$12,'III. Finanzberichte'!$CJ$12,'III. Finanzberichte'!$CQ$12,'III. Finanzberichte'!$CX$12,'III. Finanzberichte'!$DE$12,'III. Finanzberichte'!$DL$12,'III. Finanzberichte'!$DS$12),"") | O87: ==IFERROR(CHOOSE(E82,'III. Finanzberichte'!$E$12,'III. Finanzberichte'!$L$12,'III. Finanzberichte'!$S$12,'III. Finanzberichte'!$Z$12,'III. Finanzberichte'!$AG$12,'III. Finanzberichte'!$AN$12,'III. Finanzberichte'!$AU$12,'III. Finanzberichte'!$BB$12,'III. Finanzberichte'!$BI$12,'III. Finanzberichte'!$BP$12,'III. Finanzberichte'!$BW$12,'III. Finanzberichte'!$CD$12,'III. Finanzberichte'!$CK$12,'III. Finanzberichte'!$CR$12,'III. Finanzberichte'!$CY$12,'III. Finanzberichte'!$DF$12,'III. Finanzberichte'!$DM$12,'III. Finanzberichte'!$DT$12),"") | P87: ==IFERROR(CHOOSE(E82,'III. Finanzberichte'!$F$12,'III. Finanzberichte'!$M$12,'III. Finanzberichte'!$T$12,'III. Finanzberichte'!$AA$12,'III. Finanzberichte'!$AH$12,'III. Finanzberichte'!$AO$12,'III. Finanzberichte'!$AV$12,'III. Finanzberichte'!$BC$12,'III. Finanzberichte'!$BJ$12,'III. Finanzberichte'!$BQ$12,'III. Finanzberichte'!$BX$12,'III. Finanzberichte'!$CE$12,'III. Finanzberichte'!$CL$12,'III. Finanzberichte'!$CS$12,'III. Finanzberichte'!$CZ$12,'III. Finanzberichte'!$DG$12,'III. Finanzberichte'!$DN$12,'III. Finanzberichte'!$DU$12),"")
B88: ==IF(Reserve_Freigabe="Ja","Operatives Budget (Reserve freigegeben)","Operatives Budget (abzgl. Reserve)") | D88: ==IF(Reserve_Freigabe="Ja",ROUND($D$86,2),ROUND($D$86-$D$87,2)) | F88: Abzug | G88: Mehreinnahmen | I88: ==IFERROR(ROUND(MAX(0,(SUM($G$97:$G$100)-$G$99)-(SUM($H$97:$H$100)-$H$99)),2),0) -> 0 | L88: Drittmittel | M88: ==IFERROR(CHOOSE(E82,'III. Finanzberichte'!$C$13,'III. Finanzberichte'!$J$13,'III. Finanzberichte'!$Q$13,'III. Finanzberichte'!$X$13,'III. Finanzberichte'!$AE$13,'III. Finanzberichte'!$AL$13,'III. Finanzberichte'!$AS$13,'III. Finanzberichte'!$AZ$13,'III. Finanzberichte'!$BG$13,'III. Finanzberichte'!$BN$13,'III. Finanzberichte'!$BU$13,'III. Finanzberichte'!$CB$13,'III. Finanzberichte'!$CI$13,'III. Finanzberichte'!$CP$13,'III. Finanzberichte'!$CW$13,'III. Finanzberichte'!$DD$13,'III. Finanzberichte'!$DK$13,'III. Finanzberichte'!$DR$13),"") | N88: ==IFERROR(CHOOSE(E82,'III. Finanzberichte'!$D$13,'III. Finanzberichte'!$K$13,'III. Finanzberichte'!$R$13,'III. Finanzberichte'!$Y$13,'III. Finanzberichte'!$AF$13,'III. Finanzberichte'!$AM$13,'III. Finanzberichte'!$AT$13,'III. Finanzberichte'!$BA$13,'III. Finanzberichte'!$BH$13,'III. Finanzberichte'!$BO$13,'III. Finanzberichte'!$BV$13,'III. Finanzberichte'!$CC$13,'III. Finanzberichte'!$CJ$13,'III. Finanzberichte'!$CQ$13,'III. Finanzberichte'!$CX$13,'III. Finanzberichte'!$DE$13,'III. Finanzberichte'!$DL$13,'III. Finanzberichte'!$DS$13),"") | O88: ==IFERROR(CHOOSE(E82,'III. Finanzberichte'!$E$13,'III. Finanzberichte'!$L$13,'III. Finanzberichte'!$S$13,'III. Finanzberichte'!$Z$13,'III. Finanzberichte'!$AG$13,'III. Finanzberichte'!$AN$13,'III. Finanzberichte'!$AU$13,'III. Finanzberichte'!$BB$13,'III. Finanzberichte'!$BI$13,'III. Finanzberichte'!$BP$13,'III. Finanzberichte'!$BW$13,'III. Finanzberichte'!$CD$13,'III. Finanzberichte'!$CK$13,'III. Finanzberichte'!$CR$13,'III. Finanzberichte'!$CY$13,'III. Finanzberichte'!$DF$13,'III. Finanzberichte'!$DM$13,'III. Finanzberichte'!$DT$13),"") | P88: ==IFERROR(CHOOSE(E82,'III. Finanzberichte'!$F$13,'III. Finanzberichte'!$M$13,'III. Finanzberichte'!$T$13,'III. Finanzberichte'!$AA$13,'III. Finanzberichte'!$AH$13,'III. Finanzberichte'!$AO$13,'III. Finanzberichte'!$AV$13,'III. Finanzberichte'!$BC$13,'III. Finanzberichte'!$BJ$13,'III. Finanzberichte'!$BQ$13,'III. Finanzberichte'!$BX$13,'III. Finanzberichte'!$CE$13,'III. Finanzberichte'!$CL$13,'III. Finanzberichte'!$CS$13,'III. Finanzberichte'!$CZ$13,'III. Finanzberichte'!$DG$13,'III. Finanzberichte'!$DN$13,'III. Finanzberichte'!$DU$13),"")
B89: Bereitgestellte KMW-Mittel | D89: ==IFERROR(ROUND(SUBTOTAL(109,TblKMWMittel[Betrag]),2),0) | G89: Abzugsoptionen KMW insgesamt | I89: ==ROUND(IF($F$87="Abzug",MAX(0,$I$87),0)+IF($F$88="Abzug",MAX(0,$I$88),0),2) | L89: KMW-Mittel | M89: ==IFERROR(CHOOSE(E82,'III. Finanzberichte'!$C$14,'III. Finanzberichte'!$J$14,'III. Finanzberichte'!$Q$14,'III. Finanzberichte'!$X$14,'III. Finanzberichte'!$AE$14,'III. Finanzberichte'!$AL$14,'III. Finanzberichte'!$AS$14,'III. Finanzberichte'!$AZ$14,'III. Finanzberichte'!$BG$14,'III. Finanzberichte'!$BN$14,'III. Finanzberichte'!$BU$14,'III. Finanzberichte'!$CB$14,'III. Finanzberichte'!$CI$14,'III. Finanzberichte'!$CP$14,'III. Finanzberichte'!$CW$14,'III. Finanzberichte'!$DD$14,'III. Finanzberichte'!$DK$14,'III. Finanzberichte'!$DR$14),"") | N89: ==IFERROR(CHOOSE(E82,'III. Finanzberichte'!$D$14,'III. Finanzberichte'!$K$14,'III. Finanzberichte'!$R$14,'III. Finanzberichte'!$Y$14,'III. Finanzberichte'!$AF$14,'III. Finanzberichte'!$AM$14,'III. Finanzberichte'!$AT$14,'III. Finanzberichte'!$BA$14,'III. Finanzberichte'!$BH$14,'III. Finanzberichte'!$BO$14,'III. Finanzberichte'!$BV$14,'III. Finanzberichte'!$CC$14,'III. Finanzberichte'!$CJ$14,'III. Finanzberichte'!$CQ$14,'III. Finanzberichte'!$CX$14,'III. Finanzberichte'!$DE$14,'III. Finanzberichte'!$DL$14,'III. Finanzberichte'!$DS$14),"") | O89: ==IFERROR(CHOOSE(E82,'III. Finanzberichte'!$E$14,'III. Finanzberichte'!$L$14,'III. Finanzberichte'!$S$14,'III. Finanzberichte'!$Z$14,'III. Finanzberichte'!$AG$14,'III. Finanzberichte'!$AN$14,'III. Finanzberichte'!$AU$14,'III. Finanzberichte'!$BB$14,'III. Finanzberichte'!$BI$14,'III. Finanzberichte'!$BP$14,'III. Finanzberichte'!$BW$14,'III. Finanzberichte'!$CD$14,'III. Finanzberichte'!$CK$14,'III. Finanzberichte'!$CR$14,'III. Finanzberichte'!$CY$14,'III. Finanzberichte'!$DF$14,'III. Finanzberichte'!$DM$14,'III. Finanzberichte'!$DT$14),"") | P89: ==IFERROR(CHOOSE(E82,'III. Finanzberichte'!$F$14,'III. Finanzberichte'!$M$14,'III. Finanzberichte'!$T$14,'III. Finanzberichte'!$AA$14,'III. Finanzberichte'!$AH$14,'III. Finanzberichte'!$AO$14,'III. Finanzberichte'!$AV$14,'III. Finanzberichte'!$BC$14,'III. Finanzberichte'!$BJ$14,'III. Finanzberichte'!$BQ$14,'III. Finanzberichte'!$BX$14,'III. Finanzberichte'!$CE$14,'III. Finanzberichte'!$CL$14,'III. Finanzberichte'!$CS$14,'III. Finanzberichte'!$CZ$14,'III. Finanzberichte'!$DG$14,'III. Finanzberichte'!$DN$14,'III. Finanzberichte'!$DU$14),"")
B90: Verfügbare KMW-Mittel | D90: ==ROUND($D$88-$D$89,2) | G90: Verfügbare KMW-Mittel (bereinigt) | I90: ==ROUND($D$90-$I$89,2) | L90: Zinsertraege | M90: ==IFERROR(CHOOSE(E82,'III. Finanzberichte'!$C$15,'III. Finanzberichte'!$J$15,'III. Finanzberichte'!$Q$15,'III. Finanzberichte'!$X$15,'III. Finanzberichte'!$AE$15,'III. Finanzberichte'!$AL$15,'III. Finanzberichte'!$AS$15,'III. Finanzberichte'!$AZ$15,'III. Finanzberichte'!$BG$15,'III. Finanzberichte'!$BN$15,'III. Finanzberichte'!$BU$15,'III. Finanzberichte'!$CB$15,'III. Finanzberichte'!$CI$15,'III. Finanzberichte'!$CP$15,'III. Finanzberichte'!$CW$15,'III. Finanzberichte'!$DD$15,'III. Finanzberichte'!$DK$15,'III. Finanzberichte'!$DR$15),"") | N90: ==IFERROR(CHOOSE(E82,'III. Finanzberichte'!$D$15,'III. Finanzberichte'!$K$15,'III. Finanzberichte'!$R$15,'III. Finanzberichte'!$Y$15,'III. Finanzberichte'!$AF$15,'III. Finanzberichte'!$AM$15,'III. Finanzberichte'!$AT$15,'III. Finanzberichte'!$BA$15,'III. Finanzberichte'!$BH$15,'III. Finanzberichte'!$BO$15,'III. Finanzberichte'!$BV$15,'III. Finanzberichte'!$CC$15,'III. Finanzberichte'!$CJ$15,'III. Finanzberichte'!$CQ$15,'III. Finanzberichte'!$CX$15,'III. Finanzberichte'!$DE$15,'III. Finanzberichte'!$DL$15,'III. Finanzberichte'!$DS$15),"") | O90: ==IFERROR(CHOOSE(E82,'III. Finanzberichte'!$E$15,'III. Finanzberichte'!$L$15,'III. Finanzberichte'!$S$15,'III. Finanzberichte'!$Z$15,'III. Finanzberichte'!$AG$15,'III. Finanzberichte'!$AN$15,'III. Finanzberichte'!$AU$15,'III. Finanzberichte'!$BB$15,'III. Finanzberichte'!$BI$15,'III. Finanzberichte'!$BP$15,'III. Finanzberichte'!$BW$15,'III. Finanzberichte'!$CD$15,'III. Finanzberichte'!$CK$15,'III. Finanzberichte'!$CR$15,'III. Finanzberichte'!$CY$15,'III. Finanzberichte'!$DF$15,'III. Finanzberichte'!$DM$15,'III. Finanzberichte'!$DT$15),"") | P90: ==IFERROR(CHOOSE(E82,'III. Finanzberichte'!$F$15,'III. Finanzberichte'!$M$15,'III. Finanzberichte'!$T$15,'III. Finanzberichte'!$AA$15,'III. Finanzberichte'!$AH$15,'III. Finanzberichte'!$AO$15,'III. Finanzberichte'!$AV$15,'III. Finanzberichte'!$BC$15,'III. Finanzberichte'!$BJ$15,'III. Finanzberichte'!$BQ$15,'III. Finanzberichte'!$BX$15,'III. Finanzberichte'!$CE$15,'III. Finanzberichte'!$CL$15,'III. Finanzberichte'!$CS$15,'III. Finanzberichte'!$CZ$15,'III. Finanzberichte'!$DG$15,'III. Finanzberichte'!$DN$15,'III. Finanzberichte'!$DU$15),"")
L91: Gesamteinnahmen | M91: ==IFERROR(CHOOSE(E82,'III. Finanzberichte'!$C$16,'III. Finanzberichte'!$J$16,'III. Finanzberichte'!$Q$16,'III. Finanzberichte'!$X$16,'III. Finanzberichte'!$AE$16,'III. Finanzberichte'!$AL$16,'III. Finanzberichte'!$AS$16,'III. Finanzberichte'!$AZ$16,'III. Finanzberichte'!$BG$16,'III. Finanzberichte'!$BN$16,'III. Finanzberichte'!$BU$16,'III. Finanzberichte'!$CB$16,'III. Finanzberichte'!$CI$16,'III. Finanzberichte'!$CP$16,'III. Finanzberichte'!$CW$16,'III. Finanzberichte'!$DD$16,'III. Finanzberichte'!$DK$16,'III. Finanzberichte'!$DR$16),"") | N91: ==IFERROR(CHOOSE(E82,'III. Finanzberichte'!$D$16,'III. Finanzberichte'!$K$16,'III. Finanzberichte'!$R$16,'III. Finanzberichte'!$Y$16,'III. Finanzberichte'!$AF$16,'III. Finanzberichte'!$AM$16,'III. Finanzberichte'!$AT$16,'III. Finanzberichte'!$BA$16,'III. Finanzberichte'!$BH$16,'III. Finanzberichte'!$BO$16,'III. Finanzberichte'!$BV$16,'III. Finanzberichte'!$CC$16,'III. Finanzberichte'!$CJ$16,'III. Finanzberichte'!$CQ$16,'III. Finanzberichte'!$CX$16,'III. Finanzberichte'!$DE$16,'III. Finanzberichte'!$DL$16,'III. Finanzberichte'!$DS$16),"") | O91: ==IFERROR(CHOOSE(E82,'III. Finanzberichte'!$E$16,'III. Finanzberichte'!$L$16,'III. Finanzberichte'!$S$16,'III. Finanzberichte'!$Z$16,'III. Finanzberichte'!$AG$16,'III. Finanzberichte'!$AN$16,'III. Finanzberichte'!$AU$16,'III. Finanzberichte'!$BB$16,'III. Finanzberichte'!$BI$16,'III. Finanzberichte'!$BP$16,'III. Finanzberichte'!$BW$16,'III. Finanzberichte'!$CD$16,'III. Finanzberichte'!$CK$16,'III. Finanzberichte'!$CR$16,'III. Finanzberichte'!$CY$16,'III. Finanzberichte'!$DF$16,'III. Finanzberichte'!$DM$16,'III. Finanzberichte'!$DT$16),"") | P91: ==IFERROR(CHOOSE(E82,'III. Finanzberichte'!$F$16,'III. Finanzberichte'!$M$16,'III. Finanzberichte'!$T$16,'III. Finanzberichte'!$AA$16,'III. Finanzberichte'!$AH$16,'III. Finanzberichte'!$AO$16,'III. Finanzberichte'!$AV$16,'III. Finanzberichte'!$BC$16,'III. Finanzberichte'!$BJ$16,'III. Finanzberichte'!$BQ$16,'III. Finanzberichte'!$BX$16,'III. Finanzberichte'!$CE$16,'III. Finanzberichte'!$CL$16,'III. Finanzberichte'!$CS$16,'III. Finanzberichte'!$CZ$16,'III. Finanzberichte'!$DG$16,'III. Finanzberichte'!$DN$16,'III. Finanzberichte'!$DU$16),"")
L92: Ausgaben
L93: ID | M93: Ausgaben (LC) | N93: Ausgaben (EUR) | O93: Kum. Ausgaben (LC) | P93: Kum. Ausgaben (EUR)
B94: Finanzierungsanteile | L94: ==IFERROR(CHOOSE(E82,'III. Finanzberichte'!$B$19,'III. Finanzberichte'!$I$19,'III. Finanzberichte'!$P$19,'III. Finanzberichte'!$W$19,'III. Finanzberichte'!$AD$19,'III. Finanzberichte'!$AK$19,'III. Finanzberichte'!$AR$19,'III. Finanzberichte'!$AY$19,'III. Finanzberichte'!$BF$19,'III. Finanzberichte'!$BM$19,'III. Finanzberichte'!$BT$19,'III. Finanzberichte'!$CA$19,'III. Finanzberichte'!$CH$19,'III. Finanzberichte'!$CO$19,'III. Finanzberichte'!$CV$19,'III. Finanzberichte'!$DC$19,'III. Finanzberichte'!$DJ$19,'III. Finanzberichte'!$DQ$19),"") | M94: ==IFERROR(CHOOSE(E82,'III. Finanzberichte'!$C$19,'III. Finanzberichte'!$J$19,'III. Finanzberichte'!$Q$19,'III. Finanzberichte'!$X$19,'III. Finanzberichte'!$AE$19,'III. Finanzberichte'!$AL$19,'III. Finanzberichte'!$AS$19,'III. Finanzberichte'!$AZ$19,'III. Finanzberichte'!$BG$19,'III. Finanzberichte'!$BN$19,'III. Finanzberichte'!$BU$19,'III. Finanzberichte'!$CB$19,'III. Finanzberichte'!$CI$19,'III. Finanzberichte'!$CP$19,'III. Finanzberichte'!$CW$19,'III. Finanzberichte'!$DD$19,'III. Finanzberichte'!$DK$19,'III. Finanzberichte'!$DR$19),"") | N94: ==IFERROR(CHOOSE(E82,'III. Finanzberichte'!$D$19,'III. Finanzberichte'!$K$19,'III. Finanzberichte'!$R$19,'III. Finanzberichte'!$Y$19,'III. Finanzberichte'!$AF$19,'III. Finanzberichte'!$AM$19,'III. Finanzberichte'!$AT$19,'III. Finanzberichte'!$BA$19,'III. Finanzberichte'!$BH$19,'III. Finanzberichte'!$BO$19,'III. Finanzberichte'!$BV$19,'III. Finanzberichte'!$CC$19,'III. Finanzberichte'!$CJ$19,'III. Finanzberichte'!$CQ$19,'III. Finanzberichte'!$CX$19,'III. Finanzberichte'!$DE$19,'III. Finanzberichte'!$DL$19,'III. Finanzberichte'!$DS$19),"") | O94: ==IFERROR(CHOOSE(E82,'III. Finanzberichte'!$E$19,'III. Finanzberichte'!$L$19,'III. Finanzberichte'!$S$19,'III. Finanzberichte'!$Z$19,'III. Finanzberichte'!$AG$19,'III. Finanzberichte'!$AN$19,'III. Finanzberichte'!$AU$19,'III. Finanzberichte'!$BB$19,'III. Finanzberichte'!$BI$19,'III. Finanzberichte'!$BP$19,'III. Finanzberichte'!$BW$19,'III. Finanzberichte'!$CD$19,'III. Finanzberichte'!$CK$19,'III. Finanzberichte'!$CR$19,'III. Finanzberichte'!$CY$19,'III. Finanzberichte'!$DF$19,'III. Finanzberichte'!$DM$19,'III. Finanzberichte'!$DT$19),"") | P94: ==IFERROR(CHOOSE(E82,'III. Finanzberichte'!$F$19,'III. Finanzberichte'!$M$19,'III. Finanzberichte'!$T$19,'III. Finanzberichte'!$AA$19,'III. Finanzberichte'!$AH$19,'III. Finanzberichte'!$AO$19,'III. Finanzberichte'!$AV$19,'III. Finanzberichte'!$BC$19,'III. Finanzberichte'!$BJ$19,'III. Finanzberichte'!$BQ$19,'III. Finanzberichte'!$BX$19,'III. Finanzberichte'!$CE$19,'III. Finanzberichte'!$CL$19,'III. Finanzberichte'!$CS$19,'III. Finanzberichte'!$CZ$19,'III. Finanzberichte'!$DG$19,'III. Finanzberichte'!$DN$19,'III. Finanzberichte'!$DU$19),"")
L95: ==IFERROR(CHOOSE(E82,'III. Finanzberichte'!$B$20,'III. Finanzberichte'!$I$20,'III. Finanzberichte'!$P$20,'III. Finanzberichte'!$W$20,'III. Finanzberichte'!$AD$20,'III. Finanzberichte'!$AK$20,'III. Finanzberichte'!$AR$20,'III. Finanzberichte'!$AY$20,'III. Finanzberichte'!$BF$20,'III. Finanzberichte'!$BM$20,'III. Finanzberichte'!$BT$20,'III. Finanzberichte'!$CA$20,'III. Finanzberichte'!$CH$20,'III. Finanzberichte'!$CO$20,'III. Finanzberichte'!$CV$20,'III. Finanzberichte'!$DC$20,'III. Finanzberichte'!$DJ$20,'III. Finanzberichte'!$DQ$20),"") | M95: ==IFERROR(CHOOSE(E82,'III. Finanzberichte'!$C$20,'III. Finanzberichte'!$J$20,'III. Finanzberichte'!$Q$20,'III. Finanzberichte'!$X$20,'III. Finanzberichte'!$AE$20,'III. Finanzberichte'!$AL$20,'III. Finanzberichte'!$AS$20,'III. Finanzberichte'!$AZ$20,'III. Finanzberichte'!$BG$20,'III. Finanzberichte'!$BN$20,'III. Finanzberichte'!$BU$20,'III. Finanzberichte'!$CB$20,'III. Finanzberichte'!$CI$20,'III. Finanzberichte'!$CP$20,'III. Finanzberichte'!$CW$20,'III. Finanzberichte'!$DD$20,'III. Finanzberichte'!$DK$20,'III. Finanzberichte'!$DR$20),"") | N95: ==IFERROR(CHOOSE(E82,'III. Finanzberichte'!$D$20,'III. Finanzberichte'!$K$20,'III. Finanzberichte'!$R$20,'III. Finanzberichte'!$Y$20,'III. Finanzberichte'!$AF$20,'III. Finanzberichte'!$AM$20,'III. Finanzberichte'!$AT$20,'III. Finanzberichte'!$BA$20,'III. Finanzberichte'!$BH$20,'III. Finanzberichte'!$BO$20,'III. Finanzberichte'!$BV$20,'III. Finanzberichte'!$CC$20,'III. Finanzberichte'!$CJ$20,'III. Finanzberichte'!$CQ$20,'III. Finanzberichte'!$CX$20,'III. Finanzberichte'!$DE$20,'III. Finanzberichte'!$DL$20,'III. Finanzberichte'!$DS$20),"") | O95: ==IFERROR(CHOOSE(E82,'III. Finanzberichte'!$E$20,'III. Finanzberichte'!$L$20,'III. Finanzberichte'!$S$20,'III. Finanzberichte'!$Z$20,'III. Finanzberichte'!$AG$20,'III. Finanzberichte'!$AN$20,'III. Finanzberichte'!$AU$20,'III. Finanzberichte'!$BB$20,'III. Finanzberichte'!$BI$20,'III. Finanzberichte'!$BP$20,'III. Finanzberichte'!$BW$20,'III. Finanzberichte'!$CD$20,'III. Finanzberichte'!$CK$20,'III. Finanzberichte'!$CR$20,'III. Finanzberichte'!$CY$20,'III. Finanzberichte'!$DF$20,'III. Finanzberichte'!$DM$20,'III. Finanzberichte'!$DT$20),"") | P95: ==IFERROR(CHOOSE(E82,'III. Finanzberichte'!$F$20,'III. Finanzberichte'!$M$20,'III. Finanzberichte'!$T$20,'III. Finanzberichte'!$AA$20,'III. Finanzberichte'!$AH$20,'III. Finanzberichte'!$AO$20,'III. Finanzberichte'!$AV$20,'III. Finanzberichte'!$BC$20,'III. Finanzberichte'!$BJ$20,'III. Finanzberichte'!$BQ$20,'III. Finanzberichte'!$BX$20,'III. Finanzberichte'!$CE$20,'III. Finanzberichte'!$CL$20,'III. Finanzberichte'!$CS$20,'III. Finanzberichte'!$CZ$20,'III. Finanzberichte'!$DG$20,'III. Finanzberichte'!$DN$20,'III. Finanzberichte'!$DU$20),"")
B96: Kategorie | C96: Kumulativ (LC) | D96: Budget (LC) | E96: Differenz (LC) | F96: Abweichung (LC) | G96: Kumulativ (EUR) | H96: Budget (EUR) | I96: Differenz (EUR) | J96: Abweichung (EUR) | L96: ==IFERROR(CHOOSE(E82,'III. Finanzberichte'!$B$21,'III. Finanzberichte'!$I$21,'III. Finanzberichte'!$P$21,'III. Finanzberichte'!$W$21,'III. Finanzberichte'!$AD$21,'III. Finanzberichte'!$AK$21,'III. Finanzberichte'!$AR$21,'III. Finanzberichte'!$AY$21,'III. Finanzberichte'!$BF$21,'III. Finanzberichte'!$BM$21,'III. Finanzberichte'!$BT$21,'III. Finanzberichte'!$CA$21,'III. Finanzberichte'!$CH$21,'III. Finanzberichte'!$CO$21,'III. Finanzberichte'!$CV$21,'III. Finanzberichte'!$DC$21,'III. Finanzberichte'!$DJ$21,'III. Finanzberichte'!$DQ$21),"") | M96: ==IFERROR(CHOOSE(E82,'III. Finanzberichte'!$C$21,'III. Finanzberichte'!$J$21,'III. Finanzberichte'!$Q$21,'III. Finanzberichte'!$X$21,'III. Finanzberichte'!$AE$21,'III. Finanzberichte'!$AL$21,'III. Finanzberichte'!$AS$21,'III. Finanzberichte'!$AZ$21,'III. Finanzberichte'!$BG$21,'III. Finanzberichte'!$BN$21,'III. Finanzberichte'!$BU$21,'III. Finanzberichte'!$CB$21,'III. Finanzberichte'!$CI$21,'III. Finanzberichte'!$CP$21,'III. Finanzberichte'!$CW$21,'III. Finanzberichte'!$DD$21,'III. Finanzberichte'!$DK$21,'III. Finanzberichte'!$DR$21),"") | N96: ==IFERROR(CHOOSE(E82,'III. Finanzberichte'!$D$21,'III. Finanzberichte'!$K$21,'III. Finanzberichte'!$R$21,'III. Finanzberichte'!$Y$21,'III. Finanzberichte'!$AF$21,'III. Finanzberichte'!$AM$21,'III. Finanzberichte'!$AT$21,'III. Finanzberichte'!$BA$21,'III. Finanzberichte'!$BH$21,'III. Finanzberichte'!$BO$21,'III. Finanzberichte'!$BV$21,'III. Finanzberichte'!$CC$21,'III. Finanzberichte'!$CJ$21,'III. Finanzberichte'!$CQ$21,'III. Finanzberichte'!$CX$21,'III. Finanzberichte'!$DE$21,'III. Finanzberichte'!$DL$21,'III. Finanzberichte'!$DS$21),"") | O96: ==IFERROR(CHOOSE(E82,'III. Finanzberichte'!$E$21,'III. Finanzberichte'!$L$21,'III. Finanzberichte'!$S$21,'III. Finanzberichte'!$Z$21,'III. Finanzberichte'!$AG$21,'III. Finanzberichte'!$AN$21,'III. Finanzberichte'!$AU$21,'III. Finanzberichte'!$BB$21,'III. Finanzberichte'!$BI$21,'III. Finanzberichte'!$BP$21,'III. Finanzberichte'!$BW$21,'III. Finanzberichte'!$CD$21,'III. Finanzberichte'!$CK$21,'III. Finanzberichte'!$CR$21,'III. Finanzberichte'!$CY$21,'III. Finanzberichte'!$DF$21,'III. Finanzberichte'!$DM$21,'III. Finanzberichte'!$DT$21),"") | P96: ==IFERROR(CHOOSE(E82,'III. Finanzberichte'!$F$21,'III. Finanzberichte'!$M$21,'III. Finanzberichte'!$T$21,'III. Finanzberichte'!$AA$21,'III. Finanzberichte'!$AH$21,'III. Finanzberichte'!$AO$21,'III. Finanzberichte'!$AV$21,'III. Finanzberichte'!$BC$21,'III. Finanzberichte'!$BJ$21,'III. Finanzberichte'!$BQ$21,'III. Finanzberichte'!$BX$21,'III. Finanzberichte'!$CE$21,'III. Finanzberichte'!$CL$21,'III. Finanzberichte'!$CS$21,'III. Finanzberichte'!$CZ$21,'III. Finanzberichte'!$DG$21,'III. Finanzberichte'!$DN$21,'III. Finanzberichte'!$DU$21),"")
B97: Eigenmittel | C97: ==IFERROR(ROUND(CHOOSE(E82,'III. Finanzberichte'!$E$12,'III. Finanzberichte'!$L$12,'III. Finanzberichte'!$S$12,'III. Finanzberichte'!$Z$12,'III. Finanzberichte'!$AG$12,'III. Finanzberichte'!$AN$12,'III. Finanzberichte'!$AU$12,'III. Finanzberichte'!$BB$12,'III. Finanzberichte'!$BI$12,'III. Finanzberichte'!$BP$12,'III. Finanzberichte'!$BW$12,'III. Finanzberichte'!$CD$12,'III. Finanzberichte'!$CK$12,'III. Finanzberichte'!$CR$12,'III. Finanzberichte'!$CY$12,'III. Finanzberichte'!$DF$12,'III. Finanzberichte'!$DM$12,'III. Finanzberichte'!$DT$12),2),0) | D97: ==IFERROR(ROUND(Eigenmittel_LW,2),0) | E97: ==ROUND(IFERROR($C$97-$D$97,0),2) | F97: ==ROUND(IFERROR(($C$97/$D$97)-1,0),4) | G97: ==IFERROR(ROUND(CHOOSE(E82,'III. Finanzberichte'!$F$12,'III. Finanzberichte'!$M$12,'III. Finanzberichte'!$T$12,'III. Finanzberichte'!$AA$12,'III. Finanzberichte'!$AH$12,'III. Finanzberichte'!$AO$12,'III. Finanzberichte'!$AV$12,'III. Finanzberichte'!$BC$12,'III. Finanzberichte'!$BJ$12,'III. Finanzberichte'!$BQ$12,'III. Finanzberichte'!$BX$12,'III. Finanzberichte'!$CE$12,'III. Finanzberichte'!$CL$12,'III. Finanzberichte'!$CS$12,'III. Finanzberichte'!$CZ$12,'III. Finanzberichte'!$DG$12,'III. Finanzberichte'!$DN$12,'III. Finanzberichte'!$DU$12),2),0) | H97: ==IFERROR(ROUND(Eigenmittel_EUR,2),0) | I97: ==ROUND(IFERROR($G$97-$H$97,0),2) | J97: ==ROUND(IFERROR(($G$97/$H$97)-1,0),4) | L97: ==IFERROR(CHOOSE(E82,'III. Finanzberichte'!$B$22,'III. Finanzberichte'!$I$22,'III. Finanzberichte'!$P$22,'III. Finanzberichte'!$W$22,'III. Finanzberichte'!$AD$22,'III. Finanzberichte'!$AK$22,'III. Finanzberichte'!$AR$22,'III. Finanzberichte'!$AY$22,'III. Finanzberichte'!$BF$22,'III. Finanzberichte'!$BM$22,'III. Finanzberichte'!$BT$22,'III. Finanzberichte'!$CA$22,'III. Finanzberichte'!$CH$22,'III. Finanzberichte'!$CO$22,'III. Finanzberichte'!$CV$22,'III. Finanzberichte'!$DC$22,'III. Finanzberichte'!$DJ$22,'III. Finanzberichte'!$DQ$22),"") | M97: ==IFERROR(CHOOSE(E82,'III. Finanzberichte'!$C$22,'III. Finanzberichte'!$J$22,'III. Finanzberichte'!$Q$22,'III. Finanzberichte'!$X$22,'III. Finanzberichte'!$AE$22,'III. Finanzberichte'!$AL$22,'III. Finanzberichte'!$AS$22,'III. Finanzberichte'!$AZ$22,'III. Finanzberichte'!$BG$22,'III. Finanzberichte'!$BN$22,'III. Finanzberichte'!$BU$22,'III. Finanzberichte'!$CB$22,'III. Finanzberichte'!$CI$22,'III. Finanzberichte'!$CP$22,'III. Finanzberichte'!$CW$22,'III. Finanzberichte'!$DD$22,'III. Finanzberichte'!$DK$22,'III. Finanzberichte'!$DR$22),"") | N97: ==IFERROR(CHOOSE(E82,'III. Finanzberichte'!$D$22,'III. Finanzberichte'!$K$22,'III. Finanzberichte'!$R$22,'III. Finanzberichte'!$Y$22,'III. Finanzberichte'!$AF$22,'III. Finanzberichte'!$AM$22,'III. Finanzberichte'!$AT$22,'III. Finanzberichte'!$BA$22,'III. Finanzberichte'!$BH$22,'III. Finanzberichte'!$BO$22,'III. Finanzberichte'!$BV$22,'III. Finanzberichte'!$CC$22,'III. Finanzberichte'!$CJ$22,'III. Finanzberichte'!$CQ$22,'III. Finanzberichte'!$CX$22,'III. Finanzberichte'!$DE$22,'III. Finanzberichte'!$DL$22,'III. Finanzberichte'!$DS$22),"") | O97: ==IFERROR(CHOOSE(E82,'III. Finanzberichte'!$E$22,'III. Finanzberichte'!$L$22,'III. Finanzberichte'!$S$22,'III. Finanzberichte'!$Z$22,'III. Finanzberichte'!$AG$22,'III. Finanzberichte'!$AN$22,'III. Finanzberichte'!$AU$22,'III. Finanzberichte'!$BB$22,'III. Finanzberichte'!$BI$22,'III. Finanzberichte'!$BP$22,'III. Finanzberichte'!$BW$22,'III. Finanzberichte'!$CD$22,'III. Finanzberichte'!$CK$22,'III. Finanzberichte'!$CR$22,'III. Finanzberichte'!$CY$22,'III. Finanzberichte'!$DF$22,'III. Finanzberichte'!$DM$22,'III. Finanzberichte'!$DT$22),"") | P97: ==IFERROR(CHOOSE(E82,'III. Finanzberichte'!$F$22,'III. Finanzberichte'!$M$22,'III. Finanzberichte'!$T$22,'III. Finanzberichte'!$AA$22,'III. Finanzberichte'!$AH$22,'III. Finanzberichte'!$AO$22,'III. Finanzberichte'!$AV$22,'III. Finanzberichte'!$BC$22,'III. Finanzberichte'!$BJ$22,'III. Finanzberichte'!$BQ$22,'III. Finanzberichte'!$BX$22,'III. Finanzberichte'!$CE$22,'III. Finanzberichte'!$CL$22,'III. Finanzberichte'!$CS$22,'III. Finanzberichte'!$CZ$22,'III. Finanzberichte'!$DG$22,'III. Finanzberichte'!$DN$22,'III. Finanzberichte'!$DU$22),"")
B98: Drittmittel | C98: ==IFERROR(ROUND(CHOOSE(E82,'III. Finanzberichte'!$E$13,'III. Finanzberichte'!$L$13,'III. Finanzberichte'!$S$13,'III. Finanzberichte'!$Z$13,'III. Finanzberichte'!$AG$13,'III. Finanzberichte'!$AN$13,'III. Finanzberichte'!$AU$13,'III. Finanzberichte'!$BB$13,'III. Finanzberichte'!$BI$13,'III. Finanzberichte'!$BP$13,'III. Finanzberichte'!$BW$13,'III. Finanzberichte'!$CD$13,'III. Finanzberichte'!$CK$13,'III. Finanzberichte'!$CR$13,'III. Finanzberichte'!$CY$13,'III. Finanzberichte'!$DF$13,'III. Finanzberichte'!$DM$13,'III. Finanzberichte'!$DT$13),2),0) | D98: ==IFERROR(ROUND(Drittmittel_LW,2),0) | E98: ==ROUND(IFERROR($C$98-$D$98,0),2) | F98: ==ROUND(IFERROR(($C$98/$D$98)-1,0),4) | G98: ==IFERROR(ROUND(CHOOSE(E82,'III. Finanzberichte'!$F$13,'III. Finanzberichte'!$M$13,'III. Finanzberichte'!$T$13,'III. Finanzberichte'!$AA$13,'III. Finanzberichte'!$AH$13,'III. Finanzberichte'!$AO$13,'III. Finanzberichte'!$AV$13,'III. Finanzberichte'!$BC$13,'III. Finanzberichte'!$BJ$13,'III. Finanzberichte'!$BQ$13,'III. Finanzberichte'!$BX$13,'III. Finanzberichte'!$CE$13,'III. Finanzberichte'!$CL$13,'III. Finanzberichte'!$CS$13,'III. Finanzberichte'!$CZ$13,'III. Finanzberichte'!$DG$13,'III. Finanzberichte'!$DN$13,'III. Finanzberichte'!$DU$13),2),0) | H98: ==IFERROR(ROUND(Drittmittel_EUR,2),0) | I98: ==ROUND(IFERROR($G$98-$H$98,0),2) | J98: ==ROUND(IFERROR(($G$98/$H$98)-1,0),4) | L98: ==IFERROR(CHOOSE(E82,'III. Finanzberichte'!$B$23,'III. Finanzberichte'!$I$23,'III. Finanzberichte'!$P$23,'III. Finanzberichte'!$W$23,'III. Finanzberichte'!$AD$23,'III. Finanzberichte'!$AK$23,'III. Finanzberichte'!$AR$23,'III. Finanzberichte'!$AY$23,'III. Finanzberichte'!$BF$23,'III. Finanzberichte'!$BM$23,'III. Finanzberichte'!$BT$23,'III. Finanzberichte'!$CA$23,'III. Finanzberichte'!$CH$23,'III. Finanzberichte'!$CO$23,'III. Finanzberichte'!$CV$23,'III. Finanzberichte'!$DC$23,'III. Finanzberichte'!$DJ$23,'III. Finanzberichte'!$DQ$23),"") | M98: ==IFERROR(CHOOSE(E82,'III. Finanzberichte'!$C$23,'III. Finanzberichte'!$J$23,'III. Finanzberichte'!$Q$23,'III. Finanzberichte'!$X$23,'III. Finanzberichte'!$AE$23,'III. Finanzberichte'!$AL$23,'III. Finanzberichte'!$AS$23,'III. Finanzberichte'!$AZ$23,'III. Finanzberichte'!$BG$23,'III. Finanzberichte'!$BN$23,'III. Finanzberichte'!$BU$23,'III. Finanzberichte'!$CB$23,'III. Finanzberichte'!$CI$23,'III. Finanzberichte'!$CP$23,'III. Finanzberichte'!$CW$23,'III. Finanzberichte'!$DD$23,'III. Finanzberichte'!$DK$23,'III. Finanzberichte'!$DR$23),"") | N98: ==IFERROR(CHOOSE(E82,'III. Finanzberichte'!$D$23,'III. Finanzberichte'!$K$23,'III. Finanzberichte'!$R$23,'III. Finanzberichte'!$Y$23,'III. Finanzberichte'!$AF$23,'III. Finanzberichte'!$AM$23,'III. Finanzberichte'!$AT$23,'III. Finanzberichte'!$BA$23,'III. Finanzberichte'!$BH$23,'III. Finanzberichte'!$BO$23,'III. Finanzberichte'!$BV$23,'III. Finanzberichte'!$CC$23,'III. Finanzberichte'!$CJ$23,'III. Finanzberichte'!$CQ$23,'III. Finanzberichte'!$CX$23,'III. Finanzberichte'!$DE$23,'III. Finanzberichte'!$DL$23,'III. Finanzberichte'!$DS$23),"") | O98: ==IFERROR(CHOOSE(E82,'III. Finanzberichte'!$E$23,'III. Finanzberichte'!$L$23,'III. Finanzberichte'!$S$23,'III. Finanzberichte'!$Z$23,'III. Finanzberichte'!$AG$23,'III. Finanzberichte'!$AN$23,'III. Finanzberichte'!$AU$23,'III. Finanzberichte'!$BB$23,'III. Finanzberichte'!$BI$23,'III. Finanzberichte'!$BP$23,'III. Finanzberichte'!$BW$23,'III. Finanzberichte'!$CD$23,'III. Finanzberichte'!$CK$23,'III. Finanzberichte'!$CR$23,'III. Finanzberichte'!$CY$23,'III. Finanzberichte'!$DF$23,'III. Finanzberichte'!$DM$23,'III. Finanzberichte'!$DT$23),"") | P98: ==IFERROR(CHOOSE(E82,'III. Finanzberichte'!$F$23,'III. Finanzberichte'!$M$23,'III. Finanzberichte'!$T$23,'III. Finanzberichte'!$AA$23,'III. Finanzberichte'!$AH$23,'III. Finanzberichte'!$AO$23,'III. Finanzberichte'!$AV$23,'III. Finanzberichte'!$BC$23,'III. Finanzberichte'!$BJ$23,'III. Finanzberichte'!$BQ$23,'III. Finanzberichte'!$BX$23,'III. Finanzberichte'!$CE$23,'III. Finanzberichte'!$CL$23,'III. Finanzberichte'!$CS$23,'III. Finanzberichte'!$CZ$23,'III. Finanzberichte'!$DG$23,'III. Finanzberichte'!$DN$23,'III. Finanzberichte'!$DU$23),"")
